Workbook

Sheet 00_Основания
A1: Тема | B1: Условие
A2: Статус | B2: M09/v001 • 15.09.2026. Дополнение ценами SVB и других морских магазинов. Это рабочая оценка компонентов, не полная стоимость установленного МО и не утверждённая УТВ.
A3: Количество | B3: 1 двигатель с 1 редуктором, 2 генератора, 2 основных инвертора, 6+2+1 АКБ сохранены. Ранее пустые количества отдельных компонентов заданы только в явно обозначенном предварительном сценарии.
A4: Исходные цены | B4: Новые источники датированы 15.09.2026; перенесённые цены M03 сохраняют прежнюю дату и ограничения. Ни одна карточка магазина не названа полученным персональным КП.
A5: НДС | B5: NET извлечён по налоговому отображению конкретной карточки. В основной смете к NET добавлены предварительные 23% по D030. SOURCE_GROSS не облагается повторно; его ставка неизвестна.
A6: GBP | B6: Новые цены GBP переведены по ЕЦБ 14.09.2026: 1 EUR = 0.85598 GBP. Старые цены M03 с прежним FX 10.09 сохранены и маркированы. Импорт UK/доставка/таможня требуют отдельной оценки.
A7: Совместимость | B7: 12V стартерные кандидаты — только ценовые аналоги; требование владельца 24 V не изменено. Полная схема пуска от любого АКБ не разработана. PTO/Yanmar, объём пожаротушения, диаметры и расходы не подтверждены ценой.
A8: Состав | B8: Дополнительные компоненты не объявлены полными системами. За составом остались отдельные неоценённые строки; готовые баки Gianneschi 20 L и клапан HT1013 внутри гидробака повторно не начислены.
A9: Опции | B9: Резервное водяное отопление остаётся опцией и показано отдельно от основного итога.
A10: A/B/C | B10: Сохранены альтернативы M03, без ранжирования качества по цене. Общие новые компоненты применены с одинаковыми количествами; общий ценовой аналог не выдаётся за три независимых предложения.
A11: Изменения | B11: Исходные M03/M07 и комплект 1.0 сохранены. Рост суммы включает раскрытие состава и предварительных количеств, а не только изменение рыночных цен.

Sheet 01_КАЦ
A1: Вариант | B1: Система | C1: Фиксированные количества | D1: Оценено NET EUR | E1: Плановый налог EUR | F1: Оценено с налогом EUR | G1: Строк без суммы | H1: Статус | I1: Полный требуемый состав | J1: Открытые входы
A2: PK01-A | B2: Ход яхты | C2: 1 двигатель; 1 редуктор предлагается | D2: =SUMIFS(02_Состав!I2:I139,02_Состав!A2:A139,A2,02_Состав!S2:S139,"ДА") -> 46624.02 | E2: =SUMIFS(02_Состав!L2:L139,02_Состав!A2:A139,A2,02_Состав!S2:S139,"ДА") -> 10723.52 | F2: =SUMIFS(02_Состав!N2:N139,02_Состав!A2:A139,A2,02_Состав!S2:S139,"ДА") -> 57347.54 | G2: 0 | H2: НЕПОЛНЫЙ ПАКЕТ | I2: Двигатель и согласованный редуктор, заводские опоры, управление и жгуты; муфта, упорный узел, вал, дейдвуд, подшипники, уплотнение и согласованный движитель; монтаж, центровка, настройка и собственные испытания | Включения двигателя раскрыть по позициям | Внешнее топливо, охлаждение, выхлоп и вентиляция — PK09; гидронасос и его силовой привод — PK12; механическая совместимость PTO — интерфейс PK01/PK12 | J2: 300 л.с. — исходный ориентир. Скорость, сопротивление, рабочий режим и PTO не рассчитаны. Измеренная компоновка, монтажные и сервисные зоны, полный состав поставки и интерфейсы ещё требуют подтверждения.
A3: PK01-B | B3: Ход яхты | C3: 1 двигатель; 1 редуктор предлагается | D3: =SUMIFS(02_Состав!I2:I139,02_Состав!A2:A139,A3,02_Состав!S2:S139,"ДА") -> 647.02 | E3: =SUMIFS(02_Состав!L2:L139,02_Состав!A2:A139,A3,02_Состав!S2:S139,"ДА") -> 148.81 | F3: =SUMIFS(02_Состав!N2:N139,02_Состав!A2:A139,A3,02_Состав!S2:S139,"ДА") -> 59637.83 | G3: 0 | H3: НЕПОЛНЫЙ ПАКЕТ | I3: Двигатель и согласованный редуктор, заводские опоры, управление и жгуты; муфта, упорный узел, вал, дейдвуд, подшипники, уплотнение и согласованный движитель; монтаж, центровка, настройка и собственные испытания | Включения двигателя раскрыть по позициям | Внешнее топливо, охлаждение, выхлоп и вентиляция — PK09; гидронасос и его силовой привод — PK12; механическая совместимость PTO — интерфейс PK01/PK12 | J3: 300 л.с. — исходный ориентир. Скорость, сопротивление, рабочий режим и PTO не рассчитаны. Измеренная компоновка, монтажные и сервисные зоны, полный состав поставки и интерфейсы ещё требуют подтверждения.
A4: PK01-C | B4: Ход яхты | C4: 1 двигатель; 1 редуктор предлагается | D4: =SUMIFS(02_Состав!I2:I139,02_Состав!A2:A139,A4,02_Состав!S2:S139,"ДА") -> 647.02 | E4: =SUMIFS(02_Состав!L2:L139,02_Состав!A2:A139,A4,02_Состав!S2:S139,"ДА") -> 148.81 | F4: =SUMIFS(02_Состав!N2:N139,02_Состав!A2:A139,A4,02_Состав!S2:S139,"ДА") -> 795.83 | G4: 1 | H4: НЕПОЛНЫЙ ПАКЕТ | I4: Двигатель и согласованный редуктор, заводские опоры, управление и жгуты; муфта, упорный узел, вал, дейдвуд, подшипники, уплотнение и согласованный движитель; монтаж, центровка, настройка и собственные испытания | Включения двигателя раскрыть по позициям | Внешнее топливо, охлаждение, выхлоп и вентиляция — PK09; гидронасос и его силовой привод — PK12; механическая совместимость PTO — интерфейс PK01/PK12 | J4: 300 л.с. — исходный ориентир. Скорость, сопротивление, рабочий режим и PTO не рассчитаны. Измеренная компоновка, монтажные и сервисные зоны, полный состав поставки и интерфейсы ещё требуют подтверждения.
A5: PK02-A | B5: Генерация | C5: 2 генератора | D5: =SUMIFS(02_Состав!I2:I139,02_Состав!A2:A139,A5,02_Состав!S2:S139,"ДА") -> 24893 | E5: =SUMIFS(02_Состав!L2:L139,02_Состав!A2:A139,A5,02_Состав!S2:S139,"ДА") -> 5725.39 | F5: =SUMIFS(02_Состав!N2:N139,02_Состав!A2:A139,A5,02_Состав!S2:S139,"ДА") -> 30618.39 | G5: 0 | H5: НЕПОЛНЫЙ ПАКЕТ | I5: Два генераторных агрегата с согласованными капсулами, опорами, собственным управлением и заводским оснащением; монтаж, местная настройка и испытания каждого | Внешние независимые топливные, водяные и выхлопные ветви — PK09; силовое переключение, распределение и кабели — PK03; пусковые АКБ и резервные связи — PK04 | Параллельную работу не считать включённой по умолчанию | J5: Около 11.5–12 кВА — исходный ориентир. Постоянные и пиковые нагрузки, режим отказа открыты. Измеренная компоновка, монтажные и сервисные зоны, полный состав поставки и интерфейсы ещё требуют подтверждения.
A6: PK02-B | B6: Генерация | C6: 2 генератора | D6: =SUMIFS(02_Состав!I2:I139,02_Состав!A2:A139,A6,02_Состав!S2:S139,"ДА") -> 34902.44 | E6: =SUMIFS(02_Состав!L2:L139,02_Состав!A2:A139,A6,02_Состав!S2:S139,"ДА") -> 8027.56 | F6: =SUMIFS(02_Состав!N2:N139,02_Состав!A2:A139,A6,02_Состав!S2:S139,"ДА") -> 42930 | G6: 0 | H6: НЕПОЛНЫЙ ПАКЕТ | I6: Два генераторных агрегата с согласованными капсулами, опорами, собственным управлением и заводским оснащением; монтаж, местная настройка и испытания каждого | Внешние независимые топливные, водяные и выхлопные ветви — PK09; силовое переключение, распределение и кабели — PK03; пусковые АКБ и резервные связи — PK04 | Параллельную работу не считать включённой по умолчанию | J6: Около 11.5–12 кВА — исходный ориентир. Постоянные и пиковые нагрузки, режим отказа открыты. Измеренная компоновка, монтажные и сервисные зоны, полный состав поставки и интерфейсы ещё требуют подтверждения.
A7: PK02-C | B7: Генерация | C7: 2 генератора | D7: =SUMIFS(02_Состав!I2:I139,02_Состав!A2:A139,A7,02_Состав!S2:S139,"ДА") -> 35858.24 | E7: =SUMIFS(02_Состав!L2:L139,02_Состав!A2:A139,A7,02_Состав!S2:S139,"ДА") -> 8247.4 | F7: =SUMIFS(02_Состав!N2:N139,02_Состав!A2:A139,A7,02_Состав!S2:S139,"ДА") -> 44105.64 | G7: 0 | H7: НЕПОЛНЫЙ ПАКЕТ | I7: Два генераторных агрегата с согласованными капсулами, опорами, собственным управлением и заводским оснащением; монтаж, местная настройка и испытания каждого | Внешние независимые топливные, водяные и выхлопные ветви — PK09; силовое переключение, распределение и кабели — PK03; пусковые АКБ и резервные связи — PK04 | Параллельную работу не считать включённой по умолчанию | J7: Около 11.5–12 кВА — исходный ориентир. Постоянные и пиковые нагрузки, режим отказа открыты. Измеренная компоновка, монтажные и сервисные зоны, полный состав поставки и интерфейсы ещё требуют подтверждения.
A8: PK03-A | B8: Электропитание | C8: 2 основных инвертора; 1 независимая функция питания насоса | D8: =SUMIFS(02_Состав!I2:I139,02_Состав!A2:A139,A8,02_Состав!S2:S139,"ДА") -> 2475.36 | E8: =SUMIFS(02_Состав!L2:L139,02_Состав!A2:A139,A8,02_Состав!S2:S139,"ДА") -> 569.33 | F8: =SUMIFS(02_Состав!N2:N139,02_Состав!A2:A139,A8,02_Состав!S2:S139,"ДА") -> 3319.19 | G8: 2 | H8: НЕПОЛНЫЙ ПАКЕТ | I8: Два основных инвертора/зарядных устройства, береговой ввод и развязка, AC/DC распределение, защиты и общесудовые питающие кабели до границ потребителей; контроль источников, заряд и отключение второстепенных нагрузок, критическое питание | ME-06: одна независимая функция питания AC водяной ветви при отказе гостиничного инвертора; отдельный третий инвертор не назначен | Монтаж, маркировка и электрические проверки | Пусковые силовые пути, изоляция АКБ и BMS — PK04 | J8: 3 кВА — поисковый класс, не утверждённая мощность. Баланс и береговой ввод открыты. Измеренная компоновка, монтажные и сервисные зоны, полный состав поставки и интерфейсы ещё требуют подтверждения.
A9: PK03-B | B9: Электропитание | C9: 2 основных инвертора; 1 независимая функция питания насоса | D9: =SUMIFS(02_Состав!I2:I139,02_Состав!A2:A139,A9,02_Состав!S2:S139,"ДА") -> 3248.47 | E9: =SUMIFS(02_Состав!L2:L139,02_Состав!A2:A139,A9,02_Состав!S2:S139,"ДА") -> 747.14 | F9: =SUMIFS(02_Состав!N2:N139,02_Состав!A2:A139,A9,02_Состав!S2:S139,"ДА") -> 4270.11 | G9: 2 | H9: НЕПОЛНЫЙ ПАКЕТ | I9: Два основных инвертора/зарядных устройства, береговой ввод и развязка, AC/DC распределение, защиты и общесудовые питающие кабели до границ потребителей; контроль источников, заряд и отключение второстепенных нагрузок, критическое питание | ME-06: одна независимая функция питания AC водяной ветви при отказе гостиничного инвертора; отдельный третий инвертор не назначен | Монтаж, маркировка и электрические проверки | Пусковые силовые пути, изоляция АКБ и BMS — PK04 | J9: 3 кВА — поисковый класс, не утверждённая мощность. Баланс и береговой ввод открыты. Измеренная компоновка, монтажные и сервисные зоны, полный состав поставки и интерфейсы ещё требуют подтверждения.
A10: PK03-C | B10: Электропитание | C10: 2 основных инвертора; 1 независимая функция питания насоса | D10: =SUMIFS(02_Состав!I2:I139,02_Состав!A2:A139,A10,02_Состав!S2:S139,"ДА") -> 4256.89 | E10: =SUMIFS(02_Состав!L2:L139,02_Состав!A2:A139,A10,02_Состав!S2:S139,"ДА") -> 979.08 | F10: =SUMIFS(02_Состав!N2:N139,02_Состав!A2:A139,A10,02_Состав!S2:S139,"ДА") -> 5510.47 | G10: 2 | H10: НЕПОЛНЫЙ ПАКЕТ | I10: Два основных инвертора/зарядных устройства, береговой ввод и развязка, AC/DC распределение, защиты и общесудовые питающие кабели до границ потребителей; контроль источников, заряд и отключение второстепенных нагрузок, критическое питание | ME-06: одна независимая функция питания AC водяной ветви при отказе гостиничного инвертора; отдельный третий инвертор не назначен | Монтаж, маркировка и электрические проверки | Пусковые силовые пути, изоляция АКБ и BMS — PK04 | J10: 3 кВА — поисковый класс, не утверждённая мощность. Баланс и береговой ввод открыты. Измеренная компоновка, монтажные и сервисные зоны, полный состав поставки и интерфейсы ещё требуют подтверждения.
A11: PK04-A | B11: АКБ и резервный пуск | C11: 6 сервисных + 2 генераторных + 1 главного двигателя | D11: =SUMIFS(02_Состав!I2:I139,02_Состав!A2:A139,A11,02_Состав!S2:S139,"ДА") -> 2215.16 | E11: =SUMIFS(02_Состав!L2:L139,02_Состав!A2:A139,A11,02_Состав!S2:S139,"ДА") -> 509.49 | F11: =SUMIFS(02_Состав!N2:N139,02_Состав!A2:A139,A11,02_Состав!S2:S139,"ДА") -> 2724.65 | G11: 0 | H11: НЕПОЛНЫЙ ПАКЕТ | I11: Девять физических АКБ по назначению; крепления и защитные объёмы, BMS по химии, батарейная и стартерная коммутация, силовые кабели до согласованных точек подключения PK03/стартеров, дистанционные контакторы, межблокировки и подтверждение состояния | Изоляция неисправной АКБ перед резервным пуском; местная блокировка обслуживания, питание управления и проверка всех разрешённых путей запуска | Зарядные устройства — PK03; независимость и настройки зарядки совместно PK03/PK04 | J11: Уточнение 115 ампер/А·ч и напряжения каждой АКБ ожидается. Пусковые токи, химия и допустимый разряд открыты. Измеренная компоновка, монтажные и сервисные зоны, полный состав поставки и интерфейсы ещё требуют подтверждения.
A12: PK04-B | B12: АКБ и резервный пуск | C12: 6 сервисных + 2 генераторных + 1 главного двигателя | D12: =SUMIFS(02_Состав!I2:I139,02_Состав!A2:A139,A12,02_Состав!S2:S139,"ДА") -> 2982.14 | E12: =SUMIFS(02_Состав!L2:L139,02_Состав!A2:A139,A12,02_Состав!S2:S139,"ДА") -> 685.9 | F12: =SUMIFS(02_Состав!N2:N139,02_Состав!A2:A139,A12,02_Состав!S2:S139,"ДА") -> 3668.04 | G12: 0 | H12: НЕПОЛНЫЙ ПАКЕТ | I12: Девять физических АКБ по назначению; крепления и защитные объёмы, BMS по химии, батарейная и стартерная коммутация, силовые кабели до согласованных точек подключения PK03/стартеров, дистанционные контакторы, межблокировки и подтверждение состояния | Изоляция неисправной АКБ перед резервным пуском; местная блокировка обслуживания, питание управления и проверка всех разрешённых путей запуска | Зарядные устройства — PK03; независимость и настройки зарядки совместно PK03/PK04 | J12: Уточнение 115 ампер/А·ч и напряжения каждой АКБ ожидается. Пусковые токи, химия и допустимый разряд открыты. Измеренная компоновка, монтажные и сервисные зоны, полный состав поставки и интерфейсы ещё требуют подтверждения.
A13: PK04-C | B13: АКБ и резервный пуск | C13: 6 сервисных + 2 генераторных + 1 главного двигателя | D13: =SUMIFS(02_Состав!I2:I139,02_Состав!A2:A139,A13,02_Состав!S2:S139,"ДА") -> 3009.86 | E13: =SUMIFS(02_Состав!L2:L139,02_Состав!A2:A139,A13,02_Состав!S2:S139,"ДА") -> 692.27 | F13: =SUMIFS(02_Состав!N2:N139,02_Состав!A2:A139,A13,02_Состав!S2:S139,"ДА") -> 3702.13 | G13: 0 | H13: НЕПОЛНЫЙ ПАКЕТ | I13: Девять физических АКБ по назначению; крепления и защитные объёмы, BMS по химии, батарейная и стартерная коммутация, силовые кабели до согласованных точек подключения PK03/стартеров, дистанционные контакторы, межблокировки и подтверждение состояния | Изоляция неисправной АКБ перед резервным пуском; местная блокировка обслуживания, питание управления и проверка всех разрешённых путей запуска | Зарядные устройства — PK03; независимость и настройки зарядки совместно PK03/PK04 | J13: Уточнение 115 ампер/А·ч и напряжения каждой АКБ ожидается. Пусковые токи, химия и допустимый разряд открыты. Измеренная компоновка, монтажные и сервисные зоны, полный состав поставки и интерфейсы ещё требуют подтверждения.
A14: PK05-A | B14: Пресная вода | C14: 1 установка 24 В + 1 установка AC | D14: =SUMIFS(02_Состав!I2:I139,02_Состав!A2:A139,A14,02_Состав!S2:S139,"ДА") -> 1535.62 | E14: =SUMIFS(02_Состав!L2:L139,02_Состав!A2:A139,A14,02_Состав!S2:S139,"ДА") -> 353.19 | F14: =SUMIFS(02_Состав!N2:N139,02_Состав!A2:A139,A14,02_Состав!S2:S139,"ДА") -> 1888.81 | G14: 1 | H14: НЕПОЛНЫЙ ПАКЕТ | I14: Одна установка 24 В и одна AC; независимые пути с выбором и изоляцией, гидроаккумуляторы, фильтры, обратные клапаны, коллекторы, магистрали до водоразбора и контроль давления | Общие узлы ME-17, включая термостатическое смешение и рециркуляцию ГВС при принятии, принадлежат PK05 | Подача на RO промывку и бойлер — интерфейсы PK06/PK07 | Комплектные фильтры RO — PK06; баки — PK11 | Опрессовка, промывка и проверка обоих режимов | J14: Рабочая точка и одновременность водоразбора открыты. 15 л/мин при 2 бар — только поисковый пример. Измеренная компоновка, монтажные и сервисные зоны, полный состав поставки и интерфейсы ещё требуют подтверждения.
A15: PK05-B | B15: Пресная вода | C15: 1 установка 24 В + 1 установка AC | D15: =SUMIFS(02_Состав!I2:I139,02_Состав!A2:A139,A15,02_Состав!S2:S139,"ДА") -> 2656.45 | E15: =SUMIFS(02_Состав!L2:L139,02_Состав!A2:A139,A15,02_Состав!S2:S139,"ДА") -> 610.99 | F15: =SUMIFS(02_Состав!N2:N139,02_Состав!A2:A139,A15,02_Состав!S2:S139,"ДА") -> 3267.44 | G15: 0 | H15: НЕПОЛНЫЙ ПАКЕТ | I15: Одна установка 24 В и одна AC; независимые пути с выбором и изоляцией, гидроаккумуляторы, фильтры, обратные клапаны, коллекторы, магистрали до водоразбора и контроль давления | Общие узлы ME-17, включая термостатическое смешение и рециркуляцию ГВС при принятии, принадлежат PK05 | Подача на RO промывку и бойлер — интерфейсы PK06/PK07 | Комплектные фильтры RO — PK06; баки — PK11 | Опрессовка, промывка и проверка обоих режимов | J15: Рабочая точка и одновременность водоразбора открыты. 15 л/мин при 2 бар — только поисковый пример. Измеренная компоновка, монтажные и сервисные зоны, полный состав поставки и интерфейсы ещё требуют подтверждения.
A16: PK05-C | B16: Пресная вода | C16: 1 установка 24 В + 1 установка AC | D16: =SUMIFS(02_Состав!I2:I139,02_Состав!A2:A139,A16,02_Состав!S2:S139,"ДА") -> 510.7 | E16: =SUMIFS(02_Состав!L2:L139,02_Состав!A2:A139,A16,02_Состав!S2:S139,"ДА") -> 117.46 | F16: =SUMIFS(02_Состав!N2:N139,02_Состав!A2:A139,A16,02_Состав!S2:S139,"ДА") -> 628.16 | G16: 2 | H16: НЕПОЛНЫЙ ПАКЕТ | I16: Одна установка 24 В и одна AC; независимые пути с выбором и изоляцией, гидроаккумуляторы, фильтры, обратные клапаны, коллекторы, магистрали до водоразбора и контроль давления | Общие узлы ME-17, включая термостатическое смешение и рециркуляцию ГВС при принятии, принадлежат PK05 | Подача на RO промывку и бойлер — интерфейсы PK06/PK07 | Комплектные фильтры RO — PK06; баки — PK11 | Опрессовка, промывка и проверка обоих режимов | J16: Рабочая точка и одновременность водоразбора открыты. 15 л/мин при 2 бар — только поисковый пример. Измеренная компоновка, монтажные и сервисные зоны, полный состав поставки и интерфейсы ещё требуют подтверждения.
A17: PK06-A | B17: Опреснение | C17: 1 опреснитель | D17: =SUMIFS(02_Состав!I2:I139,02_Состав!A2:A139,A17,02_Состав!S2:S139,"ДА") -> 6335.29 | E17: =SUMIFS(02_Состав!L2:L139,02_Состав!A2:A139,A17,02_Состав!S2:S139,"ДА") -> 1457.12 | F17: =SUMIFS(02_Состав!N2:N139,02_Состав!A2:A139,A17,02_Состав!S2:S139,"ДА") -> 7792.41 | G17: 0 | H17: НЕПОЛНЫЙ ПАКЕТ | I17: Один RO с подающим и высоким давлением по исполнению, мембранами, штатными фильтрами, контролем солёности и автоматическим отводом некондиционного продукта, промывкой и управлением | Внутренняя обвязка, крепления, монтаж и наладка; трассы забортной подачи и концентрата этой установки принадлежат PK06, не PK09 | Подача пресной воды на промывку — PK05; приёмный танк — PK11 | Проверить качество, производительность и все автоматические режимы | J17: Температура, солёность и окончательная комплектация открыты. Измеренная компоновка, монтажные и сервисные зоны, полный состав поставки и интерфейсы ещё требуют подтверждения.
A18: PK06-B | B18: Опреснение | C18: 1 опреснитель | D18: =SUMIFS(02_Состав!I2:I139,02_Состав!A2:A139,A18,02_Состав!S2:S139,"ДА") -> 10683.5 | E18: =SUMIFS(02_Состав!L2:L139,02_Состав!A2:A139,A18,02_Состав!S2:S139,"ДА") -> 2457.21 | F18: =SUMIFS(02_Состав!N2:N139,02_Состав!A2:A139,A18,02_Состав!S2:S139,"ДА") -> 13140.71 | G18: 0 | H18: НЕПОЛНЫЙ ПАКЕТ | I18: Один RO с подающим и высоким давлением по исполнению, мембранами, штатными фильтрами, контролем солёности и автоматическим отводом некондиционного продукта, промывкой и управлением | Внутренняя обвязка, крепления, монтаж и наладка; трассы забортной подачи и концентрата этой установки принадлежат PK06, не PK09 | Подача пресной воды на промывку — PK05; приёмный танк — PK11 | Проверить качество, производительность и все автоматические режимы | J18: Температура, солёность и окончательная комплектация открыты. Измеренная компоновка, монтажные и сервисные зоны, полный состав поставки и интерфейсы ещё требуют подтверждения.
A19: PK06-C | B19: Опреснение | C19: 1 опреснитель | D19: =SUMIFS(02_Состав!I2:I139,02_Состав!A2:A139,A19,02_Состав!S2:S139,"ДА") -> 0 | E19: =SUMIFS(02_Состав!L2:L139,02_Состав!A2:A139,A19,02_Состав!S2:S139,"ДА") -> 0 | F19: =SUMIFS(02_Состав!N2:N139,02_Состав!A2:A139,A19,02_Состав!S2:S139,"ДА") -> 0 | G19: 1 | H19: НЕПОЛНЫЙ ПАКЕТ | I19: Один RO с подающим и высоким давлением по исполнению, мембранами, штатными фильтрами, контролем солёности и автоматическим отводом некондиционного продукта, промывкой и управлением | Внутренняя обвязка, крепления, монтаж и наладка; трассы забортной подачи и концентрата этой установки принадлежат PK06, не PK09 | Подача пресной воды на промывку — PK05; приёмный танк — PK11 | Проверить качество, производительность и все автоматические режимы | J19: Температура, солёность и окончательная комплектация открыты. Измеренная компоновка, монтажные и сервисные зоны, полный состав поставки и интерфейсы ещё требуют подтверждения.
A20: PK07-A | B20: Горячая вода | C20: Количество бойлеров не принято | D20: =SUMIFS(02_Состав!I2:I139,02_Состав!A2:A139,A20,02_Состав!S2:S139,"ДА") -> 614.17 | E20: =SUMIFS(02_Состав!L2:L139,02_Состав!A2:A139,A20,02_Состав!S2:S139,"ДА") -> 141.26 | F20: =SUMIFS(02_Состав!N2:N139,02_Состав!A2:A139,A20,02_Состав!S2:S139,"ДА") -> 755.43 | G20: 0 | H20: НЕПОЛНЫЙ ПАКЕТ | I20: Бойлеры с электрическим и двигательным нагревом, штатной защитной арматурой, изоляцией, креплениями и сливом; теплоноситель от согласованного присоединения двигателя до бойлера и обратно | Монтаж, проверка нагрева и восстановления запаса | Число и объём не назначены | Термостатическое смешение и общая рециркуляция — PK05, не повторная покупка PK07; питание — PK03 | J20: 40 л / 1200 Вт — рыночный пример, не заданная потребность. Измеренная компоновка, монтажные и сервисные зоны, полный состав поставки и интерфейсы ещё требуют подтверждения.
A21: PK07-B | B21: Горячая вода | C21: Количество бойлеров не принято | D21: =SUMIFS(02_Состав!I2:I139,02_Состав!A2:A139,A21,02_Состав!S2:S139,"ДА") -> 690.83 | E21: =SUMIFS(02_Состав!L2:L139,02_Состав!A2:A139,A21,02_Состав!S2:S139,"ДА") -> 158.89 | F21: =SUMIFS(02_Состав!N2:N139,02_Состав!A2:A139,A21,02_Состав!S2:S139,"ДА") -> 849.72 | G21: 0 | H21: НЕПОЛНЫЙ ПАКЕТ | I21: Бойлеры с электрическим и двигательным нагревом, штатной защитной арматурой, изоляцией, креплениями и сливом; теплоноситель от согласованного присоединения двигателя до бойлера и обратно | Монтаж, проверка нагрева и восстановления запаса | Число и объём не назначены | Термостатическое смешение и общая рециркуляция — PK05, не повторная покупка PK07; питание — PK03 | J21: 40 л / 1200 Вт — рыночный пример, не заданная потребность. Измеренная компоновка, монтажные и сервисные зоны, полный состав поставки и интерфейсы ещё требуют подтверждения.
A22: PK07-C | B22: Горячая вода | C22: Количество бойлеров не принято | D22: =SUMIFS(02_Состав!I2:I139,02_Состав!A2:A139,A22,02_Состав!S2:S139,"ДА") -> 757.5 | E22: =SUMIFS(02_Состав!L2:L139,02_Состав!A2:A139,A22,02_Состав!S2:S139,"ДА") -> 174.23 | F22: =SUMIFS(02_Состав!N2:N139,02_Состав!A2:A139,A22,02_Состав!S2:S139,"ДА") -> 931.73 | G22: 0 | H22: НЕПОЛНЫЙ ПАКЕТ | I22: Бойлеры с электрическим и двигательным нагревом, штатной защитной арматурой, изоляцией, креплениями и сливом; теплоноситель от согласованного присоединения двигателя до бойлера и обратно | Монтаж, проверка нагрева и восстановления запаса | Число и объём не назначены | Термостатическое смешение и общая рециркуляция — PK05, не повторная покупка PK07; питание — PK03 | J22: 40 л / 1200 Вт — рыночный пример, не заданная потребность. Измеренная компоновка, монтажные и сервисные зоны, полный состав поставки и интерфейсы ещё требуют подтверждения.
A23: PK08-A | B23: Климат | C23: 2 чиллера; дополнительное отопление — опция | D23: =SUMIFS(02_Состав!I2:I139,02_Состав!A2:A139,A23,02_Состав!S2:S139,"ДА") -> 8568.5 | E23: =SUMIFS(02_Состав!L2:L139,02_Состав!A2:A139,A23,02_Состав!S2:S139,"ДА") -> 1970.76 | F23: =SUMIFS(02_Состав!N2:N139,02_Состав!A2:A139,A23,02_Состав!S2:S139,"ДА") -> 10539.26 | G23: 0 | H23: НЕПОЛНЫЙ ПАКЕТ | I23: Два независимо изолируемых чиллерных модуля; шкафы и панели управления, согласованные фанкойлы по помещениям, гидравлические контуры холода и забортного охлаждения, насосы, фильтры, расширение, клапаны, трубная изоляция, воздухораспределение и дренаж конденсата; монтаж, балансировка и наладка | Все собственные HVAC водяные ветви — PK08, не PK09 | Дополнительное отопление ME-26 — отдельная опция с контуром и управлением, без автоматического назначения котла | Фанкойлы — явное расширение до результата, их количество открыто | J23: 16 000 BTU/h на модуль — пример рынка. Тепловой расчёт и уровень сервиса при отказе открыты. Измеренная компоновка, монтажные и сервисные зоны, полный состав поставки и интерфейсы ещё требуют подтверждения.
A24: PK08-B | B24: Климат | C24: 2 чиллера; дополнительное отопление — опция | D24: =SUMIFS(02_Состав!I2:I139,02_Состав!A2:A139,A24,02_Состав!S2:S139,"ДА") -> 9637.1 | E24: =SUMIFS(02_Состав!L2:L139,02_Состав!A2:A139,A24,02_Состав!S2:S139,"ДА") -> 2216.54 | F24: =SUMIFS(02_Состав!N2:N139,02_Состав!A2:A139,A24,02_Состав!S2:S139,"ДА") -> 11853.64 | G24: 0 | H24: НЕПОЛНЫЙ ПАКЕТ | I24: Два независимо изолируемых чиллерных модуля; шкафы и панели управления, согласованные фанкойлы по помещениям, гидравлические контуры холода и забортного охлаждения, насосы, фильтры, расширение, клапаны, трубная изоляция, воздухораспределение и дренаж конденсата; монтаж, балансировка и наладка | Все собственные HVAC водяные ветви — PK08, не PK09 | Дополнительное отопление ME-26 — отдельная опция с контуром и управлением, без автоматического назначения котла | Фанкойлы — явное расширение до результата, их количество открыто | J24: 16 000 BTU/h на модуль — пример рынка. Тепловой расчёт и уровень сервиса при отказе открыты. Измеренная компоновка, монтажные и сервисные зоны, полный состав поставки и интерфейсы ещё требуют подтверждения.
A25: PK08-C | B25: Климат | C25: 2 чиллера; дополнительное отопление — опция | D25: =SUMIFS(02_Состав!I2:I139,02_Состав!A2:A139,A25,02_Состав!S2:S139,"ДА") -> 1326.5 | E25: =SUMIFS(02_Состав!L2:L139,02_Состав!A2:A139,A25,02_Состав!S2:S139,"ДА") -> 305.1 | F25: =SUMIFS(02_Состав!N2:N139,02_Состав!A2:A139,A25,02_Состав!S2:S139,"ДА") -> 1631.6 | G25: 1 | H25: НЕПОЛНЫЙ ПАКЕТ | I25: Два независимо изолируемых чиллерных модуля; шкафы и панели управления, согласованные фанкойлы по помещениям, гидравлические контуры холода и забортного охлаждения, насосы, фильтры, расширение, клапаны, трубная изоляция, воздухораспределение и дренаж конденсата; монтаж, балансировка и наладка | Все собственные HVAC водяные ветви — PK08, не PK09 | Дополнительное отопление ME-26 — отдельная опция с контуром и управлением, без автоматического назначения котла | Фанкойлы — явное расширение до результата, их количество открыто | J25: 16 000 BTU/h на модуль — пример рынка. Тепловой расчёт и уровень сервиса при отказе открыты. Измеренная компоновка, монтажные и сервисные зоны, полный состав поставки и интерфейсы ещё требуют подтверждения.
A26: PK09-A | B26: Обеспечение МО | C26: Число элементов определяется выбранными системами | D26: =SUMIFS(02_Состав!I2:I139,02_Состав!A2:A139,A26,02_Состав!S2:S139,"ДА") -> 3691.47 | E26: =SUMIFS(02_Состав!L2:L139,02_Состав!A2:A139,A26,02_Состав!S2:S139,"ДА") -> 849.04 | F26: =SUMIFS(02_Состав!N2:N139,02_Состав!A2:A139,A26,02_Состав!S2:S139,"ДА") -> 4540.51 | G26: 1 | H26: НЕПОЛНЫЙ ПАКЕТ | I26: Общие и раздельные внешние топливные ветви двигателя/генераторов: фильтрация, подача, обратки, арматура и сервис; их забортное охлаждение, антисифонные меры, выхлоп и выходы; приток и вытяжка МО с каналами, заслонками и остановом по пожару | Маслосмена, поддоны, местные сервисные узлы и освещение с интерфейсом PK03 | Монтаж, изоляция, маркировка и испытания | Топливные танки и уровнемеры — PK11; заводские внутренние элементы агрегатов — PK01/PK02; отдельные RO/HVAC/гидравлические охладители и ветви — PK06/PK08/PK12 | J26: Диаметры, тепловыделение, напор, длины и комплектность открыты. Измеренная компоновка, монтажные и сервисные зоны, полный состав поставки и интерфейсы ещё требуют подтверждения.
A27: PK09-B | B27: Обеспечение МО | C27: Число элементов определяется выбранными системами | D27: =SUMIFS(02_Состав!I2:I139,02_Состав!A2:A139,A27,02_Состав!S2:S139,"ДА") -> 3855.93 | E27: =SUMIFS(02_Состав!L2:L139,02_Состав!A2:A139,A27,02_Состав!S2:S139,"ДА") -> 886.87 | F27: =SUMIFS(02_Состав!N2:N139,02_Состав!A2:A139,A27,02_Состав!S2:S139,"ДА") -> 4742.8 | G27: 0 | H27: НЕПОЛНЫЙ ПАКЕТ | I27: Общие и раздельные внешние топливные ветви двигателя/генераторов: фильтрация, подача, обратки, арматура и сервис; их забортное охлаждение, антисифонные меры, выхлоп и выходы; приток и вытяжка МО с каналами, заслонками и остановом по пожару | Маслосмена, поддоны, местные сервисные узлы и освещение с интерфейсом PK03 | Монтаж, изоляция, маркировка и испытания | Топливные танки и уровнемеры — PK11; заводские внутренние элементы агрегатов — PK01/PK02; отдельные RO/HVAC/гидравлические охладители и ветви — PK06/PK08/PK12 | J27: Диаметры, тепловыделение, напор, длины и комплектность открыты. Измеренная компоновка, монтажные и сервисные зоны, полный состав поставки и интерфейсы ещё требуют подтверждения.
A28: PK09-C | B28: Обеспечение МО | C28: Число элементов определяется выбранными системами | D28: =SUMIFS(02_Состав!I2:I139,02_Состав!A2:A139,A28,02_Состав!S2:S139,"ДА") -> 3855.93 | E28: =SUMIFS(02_Состав!L2:L139,02_Состав!A2:A139,A28,02_Состав!S2:S139,"ДА") -> 886.87 | F28: =SUMIFS(02_Состав!N2:N139,02_Состав!A2:A139,A28,02_Состав!S2:S139,"ДА") -> 4742.8 | G28: 0 | H28: НЕПОЛНЫЙ ПАКЕТ | I28: Общие и раздельные внешние топливные ветви двигателя/генераторов: фильтрация, подача, обратки, арматура и сервис; их забортное охлаждение, антисифонные меры, выхлоп и выходы; приток и вытяжка МО с каналами, заслонками и остановом по пожару | Маслосмена, поддоны, местные сервисные узлы и освещение с интерфейсом PK03 | Монтаж, изоляция, маркировка и испытания | Топливные танки и уровнемеры — PK11; заводские внутренние элементы агрегатов — PK01/PK02; отдельные RO/HVAC/гидравлические охладители и ветви — PK06/PK08/PK12 | J28: Диаметры, тепловыделение, напор, длины и комплектность открыты. Измеренная компоновка, монтажные и сервисные зоны, полный состав поставки и интерфейсы ещё требуют подтверждения.
A29: PK10-A | B29: Аварийные системы | C29: Число компонентов определяется расчётом | D29: =SUMIFS(02_Состав!I2:I139,02_Состав!A2:A139,A29,02_Состав!S2:S139,"ДА") -> 700.63 | E29: =SUMIFS(02_Состав!L2:L139,02_Состав!A2:A139,A29,02_Состав!S2:S139,"ДА") -> 161.15 | F29: =SUMIFS(02_Состав!N2:N139,02_Состав!A2:A139,A29,02_Состав!S2:S139,"ДА") -> 5699.28 | G29: 0 | H29: НЕПОЛНЫЙ ПАКЕТ | I29: Зональное и аварийное осушение с насосами, ручными средствами, трубами, арматурой, датчиками и независимой тревогой; пожарное обнаружение, стационарное тушение, ручной пуск и контроль готовности | Матрица остановов двигателя/генераторов и вентиляции, собственные исполнительные приводы пожарной отсечки топлива — PK10, корпуса топливной арматуры — PK09 | Монтаж и проверка сценариев, без необоснованного расходования заряда | Числа, защищаемый объём и тип агента открыты | J29: Отсеки, защищаемый объём и аварийные режимы открыты. Измеренная компоновка, монтажные и сервисные зоны, полный состав поставки и интерфейсы ещё требуют подтверждения.
A30: PK10-B | B30: Аварийные системы | C30: Число компонентов определяется расчётом | D30: =SUMIFS(02_Состав!I2:I139,02_Состав!A2:A139,A30,02_Состав!S2:S139,"ДА") -> 700.63 | E30: =SUMIFS(02_Состав!L2:L139,02_Состав!A2:A139,A30,02_Состав!S2:S139,"ДА") -> 161.15 | F30: =SUMIFS(02_Состав!N2:N139,02_Состав!A2:A139,A30,02_Состав!S2:S139,"ДА") -> 5699.28 | G30: 0 | H30: НЕПОЛНЫЙ ПАКЕТ | I30: Зональное и аварийное осушение с насосами, ручными средствами, трубами, арматурой, датчиками и независимой тревогой; пожарное обнаружение, стационарное тушение, ручной пуск и контроль готовности | Матрица остановов двигателя/генераторов и вентиляции, собственные исполнительные приводы пожарной отсечки топлива — PK10, корпуса топливной арматуры — PK09 | Монтаж и проверка сценариев, без необоснованного расходования заряда | Числа, защищаемый объём и тип агента открыты | J30: Отсеки, защищаемый объём и аварийные режимы открыты. Измеренная компоновка, монтажные и сервисные зоны, полный состав поставки и интерфейсы ещё требуют подтверждения.
A31: PK10-C | B31: Аварийные системы | C31: Число компонентов определяется расчётом | D31: =SUMIFS(02_Состав!I2:I139,02_Состав!A2:A139,A31,02_Состав!S2:S139,"ДА") -> 700.63 | E31: =SUMIFS(02_Состав!L2:L139,02_Состав!A2:A139,A31,02_Состав!S2:S139,"ДА") -> 161.15 | F31: =SUMIFS(02_Состав!N2:N139,02_Состав!A2:A139,A31,02_Состав!S2:S139,"ДА") -> 5699.28 | G31: 0 | H31: НЕПОЛНЫЙ ПАКЕТ | I31: Зональное и аварийное осушение с насосами, ручными средствами, трубами, арматурой, датчиками и независимой тревогой; пожарное обнаружение, стационарное тушение, ручной пуск и контроль готовности | Матрица остановов двигателя/генераторов и вентиляции, собственные исполнительные приводы пожарной отсечки топлива — PK10, корпуса топливной арматуры — PK09 | Монтаж и проверка сценариев, без необоснованного расходования заряда | Числа, защищаемый объём и тип агента открыты | J31: Отсеки, защищаемый объём и аварийные режимы открыты. Измеренная компоновка, монтажные и сервисные зоны, полный состав поставки и интерфейсы ещё требуют подтверждения.
A32: PK11-A | B32: Танки и стоки | C32: Количество и объёмы открыты | D32: =SUMIFS(02_Состав!I2:I139,02_Состав!A2:A139,A32,02_Состав!S2:S139,"ДА") -> 568.94 | E32: =SUMIFS(02_Состав!L2:L139,02_Состав!A2:A139,A32,02_Состав!S2:S139,"ДА") -> 130.86 | F32: =SUMIFS(02_Состав!N2:N139,02_Состав!A2:A139,A32,02_Состав!S2:S139,"ДА") -> 699.8 | G32: 0 | H32: НЕПОЛНЫЙ ПАКЕТ | I32: Полезные запасы и стоки: реестр фактических танков, встроенные либо съёмные ёмкости, люки, вентиляция, залив/слив, уровнемеры и управление; санитарная техническая подача, изоляция источников смыва, насосы стоков, откачка и контроль доступа к сбросу | Изготовление встроенного танка и его испытание раскрыть отдельно от испытания всей системы | В рамках учёта M03 — PK11, с интерфейсом корпусному W10.90, без двойной цены | Санприборы, не входящие в перечень МО, — внешний пакет W50.58 | Трубопроводы от танковых сервисных границ — PK05/PK09 по назначению | J32: Конструкция встроенных танков, уровни и маршруты доступа открыты. Измеренная компоновка, монтажные и сервисные зоны, полный состав поставки и интерфейсы ещё требуют подтверждения.
A33: PK11-B | B33: Танки и стоки | C33: Количество и объёмы открыты | D33: =SUMIFS(02_Состав!I2:I139,02_Состав!A2:A139,A33,02_Состав!S2:S139,"ДА") -> 1148.49 | E33: =SUMIFS(02_Состав!L2:L139,02_Состав!A2:A139,A33,02_Состав!S2:S139,"ДА") -> 264.15 | F33: =SUMIFS(02_Состав!N2:N139,02_Состав!A2:A139,A33,02_Состав!S2:S139,"ДА") -> 1412.64 | G33: 0 | H33: НЕПОЛНЫЙ ПАКЕТ | I33: Полезные запасы и стоки: реестр фактических танков, встроенные либо съёмные ёмкости, люки, вентиляция, залив/слив, уровнемеры и управление; санитарная техническая подача, изоляция источников смыва, насосы стоков, откачка и контроль доступа к сбросу | Изготовление встроенного танка и его испытание раскрыть отдельно от испытания всей системы | В рамках учёта M03 — PK11, с интерфейсом корпусному W10.90, без двойной цены | Санприборы, не входящие в перечень МО, — внешний пакет W50.58 | Трубопроводы от танковых сервисных границ — PK05/PK09 по назначению | J33: Конструкция встроенных танков, уровни и маршруты доступа открыты. Измеренная компоновка, монтажные и сервисные зоны, полный состав поставки и интерфейсы ещё требуют подтверждения.
A34: PK11-C | B34: Танки и стоки | C34: Количество и объёмы открыты | D34: =SUMIFS(02_Состав!I2:I139,02_Состав!A2:A139,A34,02_Состав!S2:S139,"ДА") -> 1148.49 | E34: =SUMIFS(02_Состав!L2:L139,02_Состав!A2:A139,A34,02_Состав!S2:S139,"ДА") -> 264.15 | F34: =SUMIFS(02_Состав!N2:N139,02_Состав!A2:A139,A34,02_Состав!S2:S139,"ДА") -> 1412.64 | G34: 0 | H34: НЕПОЛНЫЙ ПАКЕТ | I34: Полезные запасы и стоки: реестр фактических танков, встроенные либо съёмные ёмкости, люки, вентиляция, залив/слив, уровнемеры и управление; санитарная техническая подача, изоляция источников смыва, насосы стоков, откачка и контроль доступа к сбросу | Изготовление встроенного танка и его испытание раскрыть отдельно от испытания всей системы | В рамках учёта M03 — PK11, с интерфейсом корпусному W10.90, без двойной цены | Санприборы, не входящие в перечень МО, — внешний пакет W50.58 | Трубопроводы от танковых сервисных границ — PK05/PK09 по назначению | J34: Конструкция встроенных танков, уровни и маршруты доступа открыты. Измеренная компоновка, монтажные и сервисные зоны, полный состав поставки и интерфейсы ещё требуют подтверждения.
A35: PK12-A | B35: Гидравлика | C35: Гидропривод обязателен; число потребителей не принято | D35: =SUMIFS(02_Состав!I2:I139,02_Состав!A2:A139,A35,02_Состав!S2:S139,"ДА") -> 7432.51 | E35: =SUMIFS(02_Состав!L2:L139,02_Состав!A2:A139,A35,02_Состав!S2:S139,"ДА") -> 1709.47 | F35: =SUMIFS(02_Состав!N2:N139,02_Состав!A2:A139,A35,02_Состав!S2:S139,"ДА") -> 9141.98 | G35: 3 | H35: НЕПОЛНЫЙ ПАКЕТ | I35: Полная гидросистема до нужных функций всех подруливающих и всех лебёдок: насосы и выбранный привод, PTO/адаптация либо электрический или отдельный привод, бак, фильтры, охлаждение, распределители, регулирование и защита давления, трассы, местные клапаны, управление и исполнительные гидромоторы/механизмы | Выдать ведомость всех внешних потребителей и включений их пакетов: одинаковый предмет не суммировать дважды | Монтаж, промывка, чистота масла, наладка приоритетов и испытания режимов, в том числе согласованного режима без главного дизеля | Рулевое не включать в общий контур автоматически | J35: Тяга, момент, скорость, одновременность и источники мощности открыты. Измеренная компоновка, монтажные и сервисные зоны, полный состав поставки и интерфейсы ещё требуют подтверждения.
A36: PK12-B | B36: Гидравлика | C36: Гидропривод обязателен; число потребителей не принято | D36: =SUMIFS(02_Состав!I2:I139,02_Состав!A2:A139,A36,02_Состав!S2:S139,"ДА") -> 7432.51 | E36: =SUMIFS(02_Состав!L2:L139,02_Состав!A2:A139,A36,02_Состав!S2:S139,"ДА") -> 1709.47 | F36: =SUMIFS(02_Состав!N2:N139,02_Состав!A2:A139,A36,02_Состав!S2:S139,"ДА") -> 9141.98 | G36: 3 | H36: НЕПОЛНЫЙ ПАКЕТ | I36: Полная гидросистема до нужных функций всех подруливающих и всех лебёдок: насосы и выбранный привод, PTO/адаптация либо электрический или отдельный привод, бак, фильтры, охлаждение, распределители, регулирование и защита давления, трассы, местные клапаны, управление и исполнительные гидромоторы/механизмы | Выдать ведомость всех внешних потребителей и включений их пакетов: одинаковый предмет не суммировать дважды | Монтаж, промывка, чистота масла, наладка приоритетов и испытания режимов, в том числе согласованного режима без главного дизеля | Рулевое не включать в общий контур автоматически | J36: Тяга, момент, скорость, одновременность и источники мощности открыты. Измеренная компоновка, монтажные и сервисные зоны, полный состав поставки и интерфейсы ещё требуют подтверждения.
A37: PK12-C | B37: Гидравлика | C37: Гидропривод обязателен; число потребителей не принято | D37: =SUMIFS(02_Состав!I2:I139,02_Состав!A2:A139,A37,02_Состав!S2:S139,"ДА") -> 7432.51 | E37: =SUMIFS(02_Состав!L2:L139,02_Состав!A2:A139,A37,02_Состав!S2:S139,"ДА") -> 1709.47 | F37: =SUMIFS(02_Состав!N2:N139,02_Состав!A2:A139,A37,02_Состав!S2:S139,"ДА") -> 9141.98 | G37: 3 | H37: НЕПОЛНЫЙ ПАКЕТ | I37: Полная гидросистема до нужных функций всех подруливающих и всех лебёдок: насосы и выбранный привод, PTO/адаптация либо электрический или отдельный привод, бак, фильтры, охлаждение, распределители, регулирование и защита давления, трассы, местные клапаны, управление и исполнительные гидромоторы/механизмы | Выдать ведомость всех внешних потребителей и включений их пакетов: одинаковый предмет не суммировать дважды | Монтаж, промывка, чистота масла, наладка приоритетов и испытания режимов, в том числе согласованного режима без главного дизеля | Рулевое не включать в общий контур автоматически | J37: Тяга, момент, скорость, одновременность и источники мощности открыты. Измеренная компоновка, монтажные и сервисные зоны, полный состав поставки и интерфейсы ещё требуют подтверждения.
A38: Итого A | B38: Частичная компонентная оценка, не полная стоимость установки | D38: =SUMIF(A2:A37,"*-A",D2:D37) -> 105654.67 | E38: =SUMIF(A2:A37,"*-A",E2:E37) -> 24300.58 | F38: =SUMIF(A2:A37,"*-A",F2:F37) -> 135067.25
A39: Итого B | B39: Частичная компонентная оценка, не полная стоимость установки | D39: =SUMIF(A2:A37,"*-B",D2:D37) -> 78585.51 | E39: =SUMIF(A2:A37,"*-B",E2:E37) -> 18074.68 | F39: =SUMIF(A2:A37,"*-B",F2:F37) -> 160614.19
A40: Итого C | B40: Частичная компонентная оценка, не полная стоимость установки | D40: =SUMIF(A2:A37,"*-C",D2:D37) -> 59504.27 | E40: =SUMIF(A2:A37,"*-C",E2:E37) -> 13685.99 | F40: =SUMIF(A2:A37,"*-C",F2:F37) -> 78302.26

Sheet 02_Состав
A1: Вариант | B1: ID | C1: ME | D1: Исполнение | E1: Кол-во | F1: Ед. | G1: Источник | H1: NET EUR/ед. | I1: NET EUR | J1: Налог | K1: План % | L1: НДС EUR | M1: Исх.gross/ед. | N1: С налогом EUR | O1: Основание количества | P1: Открытый состав / совместимость | Q1: Дата | R1: URL | S1: В основном итоге
A2: PK01-A | B2: PK01-A-L01 | C2: ME-01|ME-02|ME-03 | D2: Volvo Penta D4-300 I + HS85A | E2: 1 | F2: package | G2: PROP-E02 | H2: 45977 | I2: =IF(AND(ISNUMBER(E2),ISNUMBER(H2)),ROUND(E2*H2,2),"") -> 45977 | J2: PL23_ESTIMATE | K2: 23 | L2: =IF(AND(J2="PL23_ESTIMATE",ISNUMBER(I2)),ROUND(I2*K2/100,2),"") -> 10574.71 | N2: =IF(J2="SOURCE_GROSS",IF(AND(ISNUMBER(E2),ISNUMBER(M2)),ROUND(E2*M2,2),""),IF(ISNUMBER(I2),ROUND(I2+L2,2),"")) -> 56551.71 | O2: Количество исходной M03; основные агрегаты без изменения | P2: 300 metric hp crank / 289 prop shaft; 3500rpm R5; 24V option price open; ratio2.500. L=433+801 W=441+407 H=274+520 from drawing; excludes projecting lifting eye/service space; not installation GA; ME-03 partial only factory mounts where included: shaft/coupling/thrust unit quantities and price OPEN | 300 metric hp crank / 289 prop shaft; 3500rpm R5; 24V option price open; ratio2.500. L=433+801 W=441+407 H=274+520 from drawing; excludes projecting lifting eye/service space; not installation GA; ME-03 partial only factory mounts where included: shaft/coupling/thrust unit quantities and price OPEN | Исключено: Исходные ограничения M03 сохранены | HISTORICAL_NET_REFERENCE|RFQ_REQUIRED|DUTY_OPEN | Q2: 2026-09-11 | R2: https://www.dbmoteurs.fr/sites/default/files/Volvo-Penta-tarifs-prix-achat-moteurs-2023-DB-Moteurs-motorisation-marine-bateau-plaisance.pdf | S2: ДА
A3: PK01-B | B3: PK01-B-L01 | C3: ME-01|ME-02 | D3: Yanmar 8LV320E-KMH50A + VC20 | E3: 1 | F3: package | G3: YAN-E01 | I3: =IF(AND(ISNUMBER(E3),ISNUMBER(H3)),ROUND(E3*H3,2),"") | J3: SOURCE_GROSS | L3: =IF(AND(J3="PL23_ESTIMATE",ISNUMBER(I3)),ROUND(I3*K3/100,2),"") | M3: 58842 | N3: =IF(J3="SOURCE_GROSS",IF(AND(ISNUMBER(E3),ISNUMBER(M3)),ROUND(E3*M3,2),""),IF(ISNUMBER(I3),ROUND(I3+L3,2),"")) -> 58842 | O3: Количество исходной M03; основные агрегаты без изменения | P3: 320 mhp / 235 kW at 3800 rpm; 1 engine + 1 KMH50A + VC20; manufacturer 2021 package dry mass 435+52 kg and envelope with gear/elbow; standard 12V starter; front belt PTO optional capacity unverified; dealer includes mounts/panel/wiring/fluids; installed propulsion scope incomplete | 320 mhp / 235 kW at 3800 rpm; 1 engine + 1 KMH50A + VC20; manufacturer 2021 package dry mass 435+52 kg and envelope with gear/elbow; standard 12V starter; front belt PTO optional capacity unverified; dealer includes mounts/panel/wiring/fluids; installed propulsion scope incomplete | Исключено: Исходные ограничения M03 сохранены | CONDITIONAL_DUTY_PTO_START_VOLTAGE; NET_RFQ_REQUIRED | Q3: 2026-09-11 | R3: https://www.abma-sneek.nl/yanmar/engines-gears-drives/powerboat-engines?prod_id=650436 | S3: ДА
A4: PK01-C | B4: PK01-C-L01 | C4: ME-01|ME-02|ME-03 | D4: FPT Industrial C90 410 rating D 300hp + gearbox RFQ | E4: 1 | F4: package | G4: PROP-E04 | I4: =IF(AND(ISNUMBER(E4),ISNUMBER(H4)),ROUND(E4*H4,2),"") | J4: PL23_ESTIMATE | K4: 23 | L4: =IF(AND(J4="PL23_ESTIMATE",ISNUMBER(I4)),ROUND(I4*K4/100,2),"") | N4: =IF(J4="SOURCE_GROSS",IF(AND(ISNUMBER(E4),ISNUMBER(M4)),ROUND(E4*M4,2),""),IF(ISNUMBER(I4),ROUND(I4+L4,2),"")) | O4: Количество исходной M03; основные агрегаты без изменения | P4: Official2026 220kW300hp@2000rpm ratingD heavy duty; gearbox unselected/unpriced; shown dimensions length to flywheel and mass ENGINE ONLY; not complete package envelope;24V option RFQ; ME-03 partial only factory mounts where included: shaft/coupling/thrust unit quantities and price OPEN | Official2026 220kW300hp@2000rpm ratingD heavy duty; gearbox unselected/unpriced; shown dimensions length to flywheel and mass ENGINE ONLY; not complete package envelope;24V option RFQ; ME-03 partial only factory mounts where included: shaft/coupling/thrust unit quantities and price OPEN | Исключено: Исходные ограничения M03 сохранены | RFQ_REQUIRED|INCOMPLETE_PACKAGE|DUTY_COMPARISON_OPEN | Q4: 2026-09-11 | R4: https://www.etruck.fi/shop-1 | S4: ДА
A5: PK02-A | B5: PK02-A-L01 | C5: ME-04|ME-19 | D5: Volpi Tecno Energia Paguro12000V AP12023050M0 | E5: 2 | F5: package | G5: PROP-G03 | H5: 12446.5 | I5: =IF(AND(ISNUMBER(E5),ISNUMBER(H5)),ROUND(E5*H5,2),"") -> 24893 | J5: PL23_ESTIMATE | K5: 23 | L5: =IF(AND(J5="PL23_ESTIMATE",ISNUMBER(I5)),ROUND(I5*K5/100,2),"") -> 5725.39 | N5: =IF(J5="SOURCE_GROSS",IF(AND(ISNUMBER(E5),ISNUMBER(M5)),ROUND(E5*M5,2),""),IF(ISNUMBER(I5),ROUND(I5+L5,2),"")) -> 30618.39 | O5: Количество исходной M03; основные агрегаты без изменения | P5: 12kVA10kW continuous50Hz230V;12V starter;mass165capsule+15control electronics. Official dimensions capsule only; separate electronics footprint RFQ. Dealer/allpa dimensions/mass differ; exact SKU installationdrawing required. Published net directly not Polish VAT assumption; ME-19 partial factory cooling only: external seawater/exhaust runs and installation OPEN | 12kVA10kW continuous50Hz230V;12V starter;mass165capsule+15control electronics. Official dimensions capsule only; separate electronics footprint RFQ. Dealer/allpa dimensions/mass differ; exact SKU installationdrawing required. Published net directly not Polish VAT assumption; ME-19 partial factory cooling only: external seawater/exhaust runs and installation OPEN | Исключено: Исходные ограничения M03 сохранены | CONDITIONAL_START_VOLTAGE|AC_COMPATIBILITY_OPEN|REVISION_OPEN | Q5: 2026-09-11 | R5: https://www.manelservice.com/it/gruppi-elettrogeni-marini/3925-vte-paguro-12000-v-ap12023050m0.html | S5: ДА
A6: PK02-B | B6: PK02-B-L01 | C6: ME-04|ME-19 | D6: Fischer Panda 12000x-230V PMS NautiRadar0028284 | E6: 2 | F6: package | G6: PAN-G02 | H6: 17451.22 | I6: =IF(AND(ISNUMBER(E6),ISNUMBER(H6)),ROUND(E6*H6,2),"") -> 34902.44 | J6: PL23_ESTIMATE | K6: 23 | L6: =IF(AND(J6="PL23_ESTIMATE",ISNUMBER(I6)),ROUND(I6*K6/100,2),"") -> 8027.56 | N6: =IF(J6="SOURCE_GROSS",IF(AND(ISNUMBER(E6),ISNUMBER(M6)),ROUND(E6*M6,2),""),IF(ISNUMBER(I6),ROUND(I6+L6,2),"")) -> 42930 | O6: Количество исходной M03; основные агрегаты без изменения | P6: 50Hz230V not yet accepted as220V target;2generators retained;standard datasheet12Vstarter, priced24V SKU unconfirmed. 10.2kW/12kVA NOMINAL at20C;2026catalogue treats0.85 kVA factor as short inductive starting only;hot continuous useful output OPEN. Capsule dimensions exclude fittings and service space;ME19 partial factory cooling only. SellerSKU0028284 vsOEMsheet0024660:exact revision must be tied to offer. EU seller does not yet prove EU dispatch/free-circulation/Poland delivery. | 50Hz230V not yet accepted as220V target;2generators retained;standard datasheet12Vstarter, priced24V SKU unconfirmed. 10.2kW/12kVA NOMINAL at20C;2026catalogue treats0.85 kVA factor as short inductive starting only;hot continuous useful output OPEN. Capsule dimensions exclude fittings and service space;ME19 partial factory cooling only. SellerSKU0028284 vsOEMsheet0024660:exact revision must be tied to offer. EU seller does not yet prove EU dispatch/free-circulation/Poland delivery. | Исключено: Исходные ограничения M03 сохранены | MARKET_REFERENCE|START24V_OPEN|HOT_OUTPUT_OPEN|SKU_REVISION_OPEN | Q6: 2026-09-11 | R6: https://www.nautiradar.pt/en/products/fischer-panda/panda-12000x-230v-pms-12kva-fixed-engine-speed-marine-generator | S6: ДА
A7: PK02-C | B7: PK02-C-L01 | C7: ME-04|ME-19 | D7: Kohler / Rehlko 12EFKOZD | E7: 2 | F7: package | G7: PROP-G02 | H7: 17929.12 | I7: =IF(AND(ISNUMBER(E7),ISNUMBER(H7)),ROUND(E7*H7,2),"") -> 35858.24 | J7: PL23_ESTIMATE | K7: 23 | L7: =IF(AND(J7="PL23_ESTIMATE",ISNUMBER(I7)),ROUND(I7*K7/100,2),"") -> 8247.4 | N7: =IF(J7="SOURCE_GROSS",IF(AND(ISNUMBER(E7),ISNUMBER(M7)),ROUND(E7*M7,2),""),IF(ISNUMBER(I7),ROUND(I7+L7,2),"")) -> 44105.64 | O7: Количество исходной M03; основные агрегаты без изменения | P7: Singlephase115/230V50Hz:12kW12kVA continuous140C rise;11/11continuous115C;10.5/10.5prime. Official12or24V; JPC exactstarter/shield revision RFQ. Official shield mass385dry398wet; dealer406kg conflict. No borrowing US24V price scope; ME-19 partial factory cooling only: external seawater/exhaust runs and installation OPEN | Singlephase115/230V50Hz:12kW12kVA continuous140C rise;11/11continuous115C;10.5/10.5prime. Official12or24V; JPC exactstarter/shield revision RFQ. Official shield mass385dry398wet; dealer406kg conflict. No borrowing US24V price scope; ME-19 partial factory cooling only: external seawater/exhaust runs and installation OPEN | Исключено: Исходные ограничения M03 сохранены | CONDITIONAL_CONFIGURATION|AC_COMPATIBILITY_OPEN|RATING_OPEN|UK_REFERENCE | Q7: 2026-09-11 | R7: https://www.jpcdirect.com/product/kohler-12-kilowatt-generator/ | S7: ДА
A8: PK03-A | B8: PK03-A-L01 | C8: ME-05 | D8: Victron MultiPlus-II 24/3000/70-32 PMP242305010 | E8: 2 | F8: pcs | G8: EL-INV-A | H8: 739.45 | I8: =IF(AND(ISNUMBER(E8),ISNUMBER(H8)),ROUND(E8*H8,2),"") -> 1478.9 | J8: PL23_ESTIMATE | K8: 23 | L8: =IF(AND(J8="PL23_ESTIMATE",ISNUMBER(I8)),ROUND(I8*K8/100,2),"") -> 340.15 | N8: =IF(J8="SOURCE_GROSS",IF(AND(ISNUMBER(E8),ISNUMBER(M8)),ROUND(E8*M8,2),""),IF(ISNUMBER(I8),ROUND(I8+L8,2),"")) -> 1819.05 | O8: Количество исходной M03; основные агрегаты без изменения | P8: 24 V input; factory 230 V. 3000 VA not 3000 W: 2400 W at25C/2200 W at40C; charger70 A. 2 devices architecture target, capacity unapproved. | 24 V input; factory 230 V. 3000 VA not 3000 W: 2400 W at25C/2200 W at40C; charger70 A. 2 devices architecture target, capacity unapproved. | Исключено: Исходные ограничения M03 сохранены | CONDITIONAL_3KVA_REFERENCE | Q8: 2026-09-11 | R8: https://www.svb.de/de/victron-wechselrichter-ladegeraet-multiplus-ii-24-v-3000-va-70-a.html | S8: ДА
A9: PK03-A | B9: PK03-A-L02 | C9: ME-09 | D9: Victron 3600 ITR040362042 | E9: 1 | F9: pcs | G9: EL-ISO-A | H9: 436.93 | I9: =IF(AND(ISNUMBER(E9),ISNUMBER(H9)),ROUND(E9*H9,2),"") -> 436.93 | J9: PL23_ESTIMATE | K9: 23 | L9: =IF(AND(J9="PL23_ESTIMATE",ISNUMBER(I9)),ROUND(I9*K9/100,2),"") -> 100.49 | N9: =IF(J9="SOURCE_GROSS",IF(AND(ISNUMBER(E9),ISNUMBER(M9)),ROUND(E9*M9,2),""),IF(ISNUMBER(I9),ROUND(I9+L9,2),"")) -> 537.42 | O9: ПРЕДВАРИТЕЛЬНЫЙ СЦЕНАРИЙ M09: один береговой ввод, один разделительный трансформатор; не утверждённое количество закупки. | P9: 3.6 class; quantity and shore capacity unknown. Dimensions/mass from opened dealer data pending native drawing confirmation; no substitute of32A at115V for32A at230V. | 3.6 class; quantity and shore capacity unknown. Dimensions/mass from opened dealer data pending native drawing confirmation; no substitute of32A at115V for32A at230V. | Исключено: Исходные ограничения M03 сохранены | CONDITIONAL_UNIT_BENCHMARK_DIMENSIONS_DEALER | Q9: 2026-09-11 | R9: https://www.svb24.com/en/p/victron-isolation-transformer-3600-w-115-230-v.html | S9: ДА
A10: PK03-B | B10: PK03-B-L01 | C10: ME-05 | D10: Victron MultiPlus-II GX 24/3000/70-32 PMP242306000 | E10: 2 | F10: pcs | G10: EL-INV-B | H10: 840.29 | I10: =IF(AND(ISNUMBER(E10),ISNUMBER(H10)),ROUND(E10*H10,2),"") -> 1680.58 | J10: PL23_ESTIMATE | K10: 23 | L10: =IF(AND(J10="PL23_ESTIMATE",ISNUMBER(I10)),ROUND(I10*K10/100,2),"") -> 386.53 | N10: =IF(J10="SOURCE_GROSS",IF(AND(ISNUMBER(E10),ISNUMBER(M10)),ROUND(E10*M10,2),""),IF(ISNUMBER(I10),ROUND(I10+L10,2),"")) -> 2067.11 | O10: Количество исходной M03; основные агрегаты без изменения | P10: 24 V; factory230 V;2400 W at25C/2200 W at40C;70 A. GX monitoring differs; two GX units not required by yacht specification. Current manual geometry differs from catalogue: confirm revision. | 24 V; factory230 V;2400 W at25C/2200 W at40C;70 A. GX monitoring differs; two GX units not required by yacht specification. Current manual geometry differs from catalogue: confirm revision. | Исключено: Исходные ограничения M03 сохранены | CONDITIONAL_3KVA_REFERENCE | Q10: 2026-09-11 | R10: https://www.svb.de/de/victron-wechselrichter-ladegeraet-multiplus-ii-gx-24-v-3000-va-70-a.html | S10: ДА
A11: PK03-B | B11: PK03-B-L02 | C11: ME-09 | D11: Mastervolt Mass GI3.5 88000355 | E11: 1 | F11: pcs | G11: EL-ISO-B | H11: 1008.36 | I11: =IF(AND(ISNUMBER(E11),ISNUMBER(H11)),ROUND(E11*H11,2),"") -> 1008.36 | J11: PL23_ESTIMATE | K11: 23 | L11: =IF(AND(J11="PL23_ESTIMATE",ISNUMBER(I11)),ROUND(I11*K11/100,2),"") -> 231.92 | N11: =IF(J11="SOURCE_GROSS",IF(AND(ISNUMBER(E11),ISNUMBER(M11)),ROUND(E11*M11,2),""),IF(ISNUMBER(I11),ROUND(I11+L11,2),"")) -> 1240.28 | O11: ПРЕДВАРИТЕЛЬНЫЙ СЦЕНАРИЙ M09: один береговой ввод, один разделительный трансформатор; не утверждённое количество закупки. | P11: 3500 VA at230 V;16 A;HF technology;source IP23 supersedes dealer IP21. Not complete shore protection. | 3500 VA at230 V;16 A;HF technology;source IP23 supersedes dealer IP21. Not complete shore protection. | Исключено: Исходные ограничения M03 сохранены | CONDITIONAL_UNIT_BENCHMARK | Q11: 2026-09-11 | R11: https://www.svb24.com/en/mastervolt-mass-gi-3-5-isolation-transformer-16-a-3-5-kw.html | S11: ДА
A12: PK03-C | B12: PK03-C-L01 | C12: ME-05 | D12: Mastervolt CombiMaster 24/3000-60 230V 35023000 | E12: 2 | F12: pcs | G12: EL-INV-C | H12: 1344.5 | I12: =IF(AND(ISNUMBER(E12),ISNUMBER(H12)),ROUND(E12*H12,2),"") -> 2689 | J12: PL23_ESTIMATE | K12: 23 | L12: =IF(AND(J12="PL23_ESTIMATE",ISNUMBER(I12)),ROUND(I12*K12/100,2),"") -> 618.47 | N12: =IF(J12="SOURCE_GROSS",IF(AND(ISNUMBER(E12),ISNUMBER(M12)),ROUND(E12*M12,2),""),IF(ISNUMBER(I12),ROUND(I12+L12,2),"")) -> 3307.47 | O12: Количество исходной M03; основные агрегаты без изменения | P12: 24 V; factory230 V;3000 VA/2600 W at40C;60 A charger;25 A transfer versus32 A Victron. Parallel operation not qualified. | 24 V; factory230 V;3000 VA/2600 W at40C;60 A charger;25 A transfer versus32 A Victron. Parallel operation not qualified. | Исключено: Исходные ограничения M03 сохранены | CONDITIONAL_3KVA_NOT_EQUAL_W | Q12: 2026-09-11 | R12: https://www.svb.de/de/mastervolt-wechselrichter-ladegeraet-combimaster-24-v-3000-va-60-a.html?question_sort=oldest | S12: ДА
A13: PK03-C | B13: PK03-C-L02 | C13: ME-09 | D13: Mastervolt Mass GI3.5 88000355 | E13: 1 | F13: pcs | G13: EL-ISO-B | H13: 1008.36 | I13: =IF(AND(ISNUMBER(E13),ISNUMBER(H13)),ROUND(E13*H13,2),"") -> 1008.36 | J13: PL23_ESTIMATE | K13: 23 | L13: =IF(AND(J13="PL23_ESTIMATE",ISNUMBER(I13)),ROUND(I13*K13/100,2),"") -> 231.92 | N13: =IF(J13="SOURCE_GROSS",IF(AND(ISNUMBER(E13),ISNUMBER(M13)),ROUND(E13*M13,2),""),IF(ISNUMBER(I13),ROUND(I13+L13,2),"")) -> 1240.28 | O13: ПРЕДВАРИТЕЛЬНЫЙ СЦЕНАРИЙ M09: один береговой ввод, один разделительный трансформатор; не утверждённое количество закупки. | P13: 3500 VA at230 V;16 A;HF technology;source IP23 supersedes dealer IP21. Not complete shore protection. | 3500 VA at230 V;16 A;HF technology;source IP23 supersedes dealer IP21. Not complete shore protection. | Исключено: Исходные ограничения M03 сохранены | CONDITIONAL_UNIT_BENCHMARK | Q13: 2026-09-11 | R13: https://www.svb24.com/en/mastervolt-mass-gi-3-5-isolation-transformer-16-a-3-5-kw.html | S13: ДА
A14: PK04-A | B14: PK04-A-L01 | C14: ME-08 | D14: Exide ER550 12V115Ah | E14: 6 | F14: pcs | G14: EL-BAT-A | H14: 140.24 | I14: =IF(AND(ISNUMBER(E14),ISNUMBER(H14)),ROUND(E14*H14,2),"") -> 841.44 | J14: PL23_ESTIMATE | K14: 23 | L14: =IF(AND(J14="PL23_ESTIMATE",ISNUMBER(I14)),ROUND(I14*K14/100,2),"") -> 193.53 | N14: =IF(J14="SOURCE_GROSS",IF(AND(ISNUMBER(E14),ISNUMBER(M14)),ROUND(E14*M14,2),""),IF(ISNUMBER(I14),ROUND(I14+L14,2),"")) -> 1034.97 | O14: Количество исходной M03; основные агрегаты без изменения | P14: Flooded. Owner only said115 amperes; Ah and unit voltage unconfirmed. 6 physical units; no bank wiring/capacity inferred. Deposit extra. Dealer350mm/29kg differs from brochure. | Flooded. Owner only said115 amperes; Ah and unit voltage unconfirmed. 6 physical units; no bank wiring/capacity inferred. Deposit extra. Dealer350mm/29kg differs from brochure. | Исключено: Исходные ограничения M03 сохранены | CONDITIONAL_115AH12V_NOT_OWNER_APPROVED | Q14: 2026-09-11 | R14: https://online-batterien.de/a/exide-er550-dual-versorgungsbatterie-starterbatterie-12v-115ah-550wh/400440 | S14: ДА
A15: PK04-A | B15: PK04-A-L02 | C15: ME-07 | D15: Vetus SMF 125 Ah 12 V, стартерный кандидат | E15: 1 | F15: pcs | G15: EL-02 | H15: 193.24 | I15: =IF(AND(ISNUMBER(E15),ISNUMBER(H15)),ROUND(E15*H15,2),"") -> 193.24 | J15: PL23_ESTIMATE | K15: 23 | L15: =IF(AND(J15="PL23_ESTIMATE",ISNUMBER(I15)),ROUND(I15*K15/100,2),"") -> 44.45 | N15: =IF(J15="SOURCE_GROSS",IF(AND(ISNUMBER(E15),ISNUMBER(M15)),ROUND(E15*M15,2),""),IF(ISNUMBER(I15),ROUND(I15+L15,2),"")) -> 237.69 | O15: Количество исходной M03; основные агрегаты без изменения | P15: Подстановка M09 вместо EL-OPEN-MAIN. Прежнее описание относится к старому SKU и сохранено в M03. | Одна физическая стартерная батарея. | Исключено: Крепление, кабели, зарядка, доставка перевозчиком. | Только условный 12 V кандидат. OEM двигателя должен подтвердить напряжение/CCA; не образует принятую 24 V схему. Паспорт VESMF125: 950 A EN. | Q15: 2026-09-15 | R15: https://www.svb24.com/en/vetus-boat-battery-60-ah-to-230-ah.html | S15: ДА
A16: PK04-A | B16: PK04-A-L03 | C16: ME-27 | D16: Vetus SMF 70 Ah 12 V, генераторный кандидат | E16: 2 | F16: pcs | G16: EL-03 | H16: 111.34 | I16: =IF(AND(ISNUMBER(E16),ISNUMBER(H16)),ROUND(E16*H16,2),"") -> 222.68 | J16: PL23_ESTIMATE | K16: 23 | L16: =IF(AND(J16="PL23_ESTIMATE",ISNUMBER(I16)),ROUND(I16*K16/100,2),"") -> 51.22 | N16: =IF(J16="SOURCE_GROSS",IF(AND(ISNUMBER(E16),ISNUMBER(M16)),ROUND(E16*M16,2),""),IF(ISNUMBER(I16),ROUND(I16+L16,2),"")) -> 273.9 | O16: Количество исходной M03; основные агрегаты без изменения | P16: Подстановка M09 вместо EL-OPEN-GEN. Прежнее описание относится к старому SKU и сохранено в M03. | Две физические батареи, цена за одну. | Исключено: Крепления, кабели, зарядка, доставка. | Условные 12 V / 640 A EN; соответствие двум выбранным генераторам открыто. Не добавлять сверх 6+2+1. | Q16: 2026-09-15 | R16: https://www.svb24.com/en/vetus-boat-battery-60-ah-to-230-ah.html | S16: ДА
... A26: PK05-A | B26: PK05-A-L01 | C26: ME-11 | D26: CEM OSC-16.062.24 / OEM identity reconcile | E26: 1 | F26: шт | G26: WC-DC-01 | H26: 1024.92 | I26: =IF(AND(ISNUMBER(E26),ISNUMBER(H26)),ROUND(E26*H26,2),"") -> 1024.92 | J26: PL23_ESTIMATE | K26: 23 | L26: =IF(AND(J26="PL23_ESTIMATE",ISNUMBER(I26)),ROUND(I26*K26/100,2),"") -> 235.73 | N26: =IF(J26="SOURCE_GROSS",IF(AND(ISNUMBER(E26),ISNUMBER(M26)),ROUND(E26*M26,2),""),IF(ISNUMBER(I26),ROUND(I26+L26,2),"")) -> 1260.65 | O26: Количество исходной M03; основные агрегаты без изменения | P26: 24V20L accumulator; dealer50L/min max; source model mapping not proven. Common proposed test15L/min at2bar NOT verified. Do not add included tank again. | 24V20L accumulator; dealer50L/min max; source model mapping not proven. Common proposed test15L/min at2bar NOT verified. Do not add included tank again. | Исключено: Исходные ограничения M03 сохранены | WORKING_POINT_AND_OEM_ID_OPEN | Q26: 2026-09-11 | R26: https://www.comptoirnautique.com/groupe-d-eau-a-pressostat/53022-cem-elettromeccanica-autoclave-cem-vase-expansion-inox-20l-24v-50-l-min.html | S26: ДА
A27: PK05-A | B27: PK05-A-L02 | C27: ME-12 | D27: CEM J-INOX/20X 230M | E27: 1 | F27: шт | G27: WC-AC-01 | I27: =IF(AND(ISNUMBER(E27),ISNUMBER(H27)),ROUND(E27*H27,2),"") | J27: PL23_ESTIMATE | K27: 23 | L27: =IF(AND(J27="PL23_ESTIMATE",ISNUMBER(I27)),ROUND(I27*K27/100,2),"") | N27: =IF(J27="SOURCE_GROSS",IF(AND(ISNUMBER(E27),ISNUMBER(M27)),ROUND(E27*M27,2),""),IF(ISNUMBER(I27),ROUND(I27+L27,2),"")) | O27: Количество исходной M03; основные агрегаты без изменения | P27: Official230V singlephase variant exists. Proposedcommon15L/min at2bar not accepted from maxflow.20L stainless tank included. No price borrowed from24V sibling. | Official230V singlephase variant exists. Proposedcommon15L/min at2bar not accepted from maxflow.20L stainless tank included. No price borrowed from24V sibling. | Исключено: Исходные ограничения M03 сохранены | RFQ_REQUIRED;220V_COMPATIBILITY_OPEN;WORKING_POINT_OPEN | Q27: 2026-09-11 | R27: https://cempumps.com/wp-content/uploads/2024/10/Autoclavi_20L-20X.pdf | S27: ДА
A28: PK05-B | B28: PK05-B-L01 | C28: ME-11 | D28: Gianneschi EcoInox1 GE011 24V20L | E28: 1 | F28: шт | G28: WC-DC-02 | H28: 1093.25 | I28: =IF(AND(ISNUMBER(E28),ISNUMBER(H28)),ROUND(E28*H28,2),"") -> 1093.25 | J28: PL23_ESTIMATE | K28: 23 | L28: =IF(AND(J28="PL23_ESTIMATE",ISNUMBER(I28)),ROUND(I28*K28/100,2),"") -> 251.45 | N28: =IF(J28="SOURCE_GROSS",IF(AND(ISNUMBER(E28),ISNUMBER(M28)),ROUND(E28*M28,2),""),IF(ISNUMBER(I28),ROUND(I28+L28,2),"")) -> 1344.7 | O28: Количество исходной M03; основные агрегаты без изменения | P28: 45L/min max; common proposed15L/min at2bar needs curve. Includes20L tank/gauge/pressure switch; current OEM revision confirmation. | 45L/min max; common proposed15L/min at2bar needs curve. Includes20L tank/gauge/pressure switch; current OEM revision confirmation. | Исключено: Исходные ограничения M03 сохранены | WORKING_POINT_OPEN | Q28: 2026-09-11 | R28: https://www.comptoirnautique.com/groupe-d-eau-hydrophore/22947-gianneschi-groupe-d-eau-ecoinox-1-avec-reservoir-20l-24v-45lmin-7024.html | S28: ДА
A29: PK05-B | B29: PK05-B-L02 | C29: ME-12 | D29: Gianneschi EcoInox2 GE017 230V20L | E29: 1 | F29: шт | G29: WC-AC-02 | H29: 1052.5 | I29: =IF(AND(ISNUMBER(E29),ISNUMBER(H29)),ROUND(E29*H29,2),"") -> 1052.5 | J29: PL23_ESTIMATE | K29: 23 | L29: =IF(AND(J29="PL23_ESTIMATE",ISNUMBER(I29)),ROUND(I29*K29/100,2),"") -> 242.08 | N29: =IF(J29="SOURCE_GROSS",IF(AND(ISNUMBER(E29),ISNUMBER(M29)),ROUND(E29*M29,2),""),IF(ISNUMBER(I29),ROUND(I29+L29,2),"")) -> 1294.58 | O29: Количество исходной M03; основные агрегаты без изменения | P29: Open page1052.50HT supersedes search992.50. Dealer max55L/min conflicts Kent45: curves required.0.45kW/20L; common15L/min at2bar not verified. | Open page1052.50HT supersedes search992.50. Dealer max55L/min conflicts Kent45: curves required.0.45kW/20L; common15L/min at2bar not verified. | Исключено: Исходные ограничения M03 сохранены | 220V_COMPATIBILITY_OPEN;WORKING_POINT_OPEN | Q29: 2026-09-11 | R29: https://www.tyboat.com/achat/P-57388-gianneschi-groupe-d-eau-ecoinox2-3-5-bars-0-45-kw-55-litres-minute-reservoir-20-litres-230-volts.html | S29: ДА
A30: PK05-C | B30: PK05-C-L01 | C30: ME-11 | D30: ENAG GH24-0.37-24L-OT RB18-ED | E30: 1 | F30: шт | G30: WC-DC-03 | I30: =IF(AND(ISNUMBER(E30),ISNUMBER(H30)),ROUND(E30*H30,2),"") | J30: PL23_ESTIMATE | K30: 23 | L30: =IF(AND(J30="PL23_ESTIMATE",ISNUMBER(I30)),ROUND(I30*K30/100,2),"") | N30: =IF(J30="SOURCE_GROSS",IF(AND(ISNUMBER(E30),ISNUMBER(M30)),ROUND(E30*M30,2),""),IF(ISNUMBER(I30),ROUND(I30+L30,2),"")) | O30: Количество исходной M03; основные агрегаты без изменения | P30: Official24V/0.37kW; 1m3/h at30m published point; pressure switch1.5/2.5bar.24L tank differs20L competitors: standardise accumulator scope before comparison. Dimensions drawing orientation not mapped into LWH. | Official24V/0.37kW; 1m3/h at30m published point; pressure switch1.5/2.5bar.24L tank differs20L competitors: standardise accumulator scope before comparison. Dimensions drawing orientation not mapped into LWH. | Исключено: Исходные ограничения M03 сохранены | RFQ_REQUIRED;WORKING_POINT_OPEN | Q30: 2026-09-11 | R30: https://www.enag.fr/english/wp-content/uploads/sites/5/2022/11/FC-GH-EN-C.pdf | S30: ДА
A31: PK05-C | B31: PK05-C-L02 | C31: ME-12 | D31: ENAG GH230mono-0.37-24L-JET M-ED | E31: 1 | F31: шт | G31: WC-AC-03 | I31: =IF(AND(ISNUMBER(E31),ISNUMBER(H31)),ROUND(E31*H31,2),"") | J31: PL23_ESTIMATE | K31: 23 | L31: =IF(AND(J31="PL23_ESTIMATE",ISNUMBER(I31)),ROUND(I31*K31/100,2),"") | N31: =IF(J31="SOURCE_GROSS",IF(AND(ISNUMBER(E31),ISNUMBER(M31)),ROUND(E31*M31,2),""),IF(ISNUMBER(I31),ROUND(I31+L31,2),"")) | O31: Количество исходной M03; основные агрегаты без изменения | P31: Explicit230V singlephase; official1m3/h at40m, pressure switch1.5/2.5bar.24L accumulator vs20L needs standardisation; no equivalence claim. | Explicit230V singlephase; official1m3/h at40m, pressure switch1.5/2.5bar.24L accumulator vs20L needs standardisation; no equivalence claim. | Исключено: Исходные ограничения M03 сохранены | RFQ_REQUIRED;220V_COMPATIBILITY_OPEN;WORKING_POINT_OPEN | Q31: 2026-09-11 | R31: https://www.enag.fr/english/wp-content/uploads/sites/5/2022/11/FC-GH-EN-C.pdf | S31: ДА
A32: PK06-A | B32: PK06-A-L01 | C32: ME-13 | D32: Aquatec AC150 230V single phase | E32: 1 | F32: шт | G32: WC-RO-01 | H32: 6335.29 | I32: =IF(AND(ISNUMBER(E32),ISNUMBER(H32)),ROUND(E32*H32,2),"") -> 6335.29 | J32: PL23_ESTIMATE | K32: 23 | L32: =IF(AND(J32="PL23_ESTIMATE",ISNUMBER(I32)),ROUND(I32*K32/100,2),"") -> 1457.12 | N32: =IF(J32="SOURCE_GROSS",IF(AND(ISNUMBER(E32),ISNUMBER(M32)),ROUND(E32*M32,2),""),IF(ISNUMBER(I32),ROUND(I32+L32,2),"")) -> 7792.41 | O32: Количество исходной M03; основные агрегаты без изменения | P32: 150 L/h nominal ±10% at25C/35000ppm; modular conventional HP pump; base price only: automatic flush/salinity/reject parity must be itemised; generator minimum4kW manufacturer target, not electrical demand or selection | 150 L/h nominal ±10% at25C/35000ppm; modular conventional HP pump; base price only: automatic flush/salinity/reject parity must be itemised; generator minimum4kW manufacturer target, not electrical demand or selection | Исключено: Исходные ограничения M03 сохранены | FUNCTION_PARITY_OPEN;220V_COMPATIBILITY_OPEN | Q32: 2026-09-11 | R32: https://www.aquatec-watermaker.de/wassermacher-produkt-ac150-ac240.html | S32: ДА
A33: PK06-B | B33: PK06-B-L01 | C33: ME-13 | D33: Schenker ZEN150 24V/230V Touch plus salinity/reject | E33: 1 | F33: шт | G33: WC-RO-02 | H33: 10683.5 | I33: =IF(AND(ISNUMBER(E33),ISNUMBER(H33)),ROUND(E33*H33,2),"") -> 10683.5 | J33: PL23_ESTIMATE | K33: 23 | L33: =IF(AND(J33="PL23_ESTIMATE",ISNUMBER(I33)),ROUND(I33*K33/100,2),"") -> 2457.21 | N33: =IF(J33="SOURCE_GROSS",IF(AND(ISNUMBER(E33),ISNUMBER(M33)),ROUND(E33*M33,2),""),IF(ISNUMBER(I33),ROUND(I33+L33,2),"")) -> 13140.71 | O33: Количество исходной M03; основные агрегаты без изменения | P33: Observed FROM base price; net is FROM benchmark only, NOT complete Touch/salinity/reject price. Nominal150L/h. Manufacturer230V±15% includes220V. Basic has no salinity; Touch optional; 24V variant permitted. Modular unit dimensions not total installed envelope. | Observed FROM base price; net is FROM benchmark only, NOT complete Touch/salinity/reject price. Nominal150L/h. Manufacturer230V±15% includes220V. Basic has no salinity; Touch optional; 24V variant permitted. Modular unit dimensions not total installed envelope. | Исключено: Исходные ограничения M03 сохранены | FROM_PRICE_NOT_CONFIGURED;RFQ_REQUIRED | Q33: 2026-09-11 | R33: https://mar-nautic.com/schenker-watermaker-zen-150 | S33: ДА
A34: PK06-C | B34: PK06-C-L01 | C34: ME-13 | D34: Osmosea NEW12 150C 24V | E34: 1 | F34: шт | G34: WC-RO-03 | I34: =IF(AND(ISNUMBER(E34),ISNUMBER(H34)),ROUND(E34*H34,2),"") | J34: PL23_ESTIMATE | K34: 23 | L34: =IF(AND(J34="PL23_ESTIMATE",ISNUMBER(I34)),ROUND(I34*K34/100,2),"") | N34: =IF(J34="SOURCE_GROSS",IF(AND(ISNUMBER(E34),ISNUMBER(M34)),ROUND(E34*M34,2),""),IF(ISNUMBER(I34),ROUND(I34+L34,2),"")) | O34: Количество исходной M03; основные агрегаты без изменения | P34: Official150L/h/600W; flush/salinometer/unsafe-water discard included. Official63kg conflicts dealer65kg; dimensions dealer796x317x408 not official therefore blank. Dealer install/service kits included vs manufacturer optional: reconcile | Official150L/h/600W; flush/salinometer/unsafe-water discard included. Official63kg conflicts dealer65kg; dimensions dealer796x317x408 not official therefore blank. Dealer install/service kits included vs manufacturer optional: reconcile | Исключено: Исходные ограничения M03 сохранены | RFQ_REQUIRED;COMPACT_CANDIDATE | Q34: 2026-09-11 | R34: https://www.manelservice.com/en/marine-desalination-systems/17102-osmosea-new12-150c-nautical-watermaker-150-lth.html | S34: ДА
A35: PK07-A | B35: PK07-A-L01 | C35: ME-14 | D35: Quick B3 40L1200W FLB34012S000A00 | E35: 1 | F35: шт | G35: WC-HW-01 | H35: 614.17 | I35: =IF(AND(ISNUMBER(E35),ISNUMBER(H35)),ROUND(E35*H35,2),"") -> 614.17 | J35: PL23_ESTIMATE | K35: 23 | L35: =IF(AND(J35="PL23_ESTIMATE",ISNUMBER(I35)),ROUND(I35*K35/100,2),"") -> 141.26 | N35: =IF(J35="SOURCE_GROSS",IF(AND(ISNUMBER(E35),ISNUMBER(M35)),ROUND(E35*M35,2),""),IF(ISNUMBER(I35),ROUND(I35+L35,2),"")) -> 755.43 | O35: ПРЕДВАРИТЕЛЬНЫЙ СЦЕНАРИЙ M09: один бойлер; потребность ГВС не рассчитана; не утверждённое количество закупки. | P35: 40L1200W220V plus engine heat exchanger common illustrative class; not owner size. Supplier dimensions/mass in research only pending official drawing. Thermostatic mixing equalise separately. | 40L1200W220V plus engine heat exchanger common illustrative class; not owner size. Supplier dimensions/mass in research only pending official drawing. Thermostatic mixing equalise separately. | Исключено: Исходные ограничения M03 сохранены | UNIT_BENCHMARK_ONLY;QTY_OPEN | Q35: 2026-09-11 | R35: https://www.tyboat.com/achat/P-8889-quick-chauffe-eau-cylindrique-b3-40-litres-220-volts-1200-watts.html | S35: ДА
A36: PK07-B | B36: PK07-B-L01 | C36: ME-14 | D36: Quick BX40 1200W | E36: 1 | F36: шт | G36: M09-M-01 | H36: 690.83 | I36: =IF(AND(ISNUMBER(E36),ISNUMBER(H36)),ROUND(E36*H36,2),"") -> 690.83 | J36: PL23_ESTIMATE | K36: 23 | L36: =IF(AND(J36="PL23_ESTIMATE",ISNUMBER(I36)),ROUND(I36*K36/100,2),"") -> 158.89 | N36: =IF(J36="SOURCE_GROSS",IF(AND(ISNUMBER(E36),ISNUMBER(M36)),ROUND(E36*M36,2),""),IF(ISNUMBER(I36),ROUND(I36+L36,2),"")) -> 849.72 | O36: ПРЕДВАРИТЕЛЬНЫЙ СЦЕНАРИЙ M09: один бойлер; потребность ГВС не рассчитана; не утверждённое количество закупки. | P36: Подстановка M09 вместо WC-HW-02. Прежнее описание относится к старому SKU и сохранено в M03. | Бойлер40л,220V1200W, теплообменник, опоры | Исключено: Смесительный клапан, разводка, монтаж | Повтор цены M07, не дополнительный бойлер. Объём40л иллюстративный; потребление/доступ OPEN. | Q36: 2026-09-15 | R36: https://www.tyboat.com/achat/P-8880-quick-chauffe-eau-cylindrique-bx-40-litres-220-volts-1200-watts.html | S36: ДА
A37: PK07-C | B37: PK07-C-L01 | C37: ME-14 | D37: Quick BXS 40L1200W FLBXS4012S00A00 | E37: 1 | F37: шт | G37: WC-HW-03 | H37: 757.5 | I37: =IF(AND(ISNUMBER(E37),ISNUMBER(H37)),ROUND(E37*H37,2),"") -> 757.5 | J37: PL23_ESTIMATE | K37: 23 | L37: =IF(AND(J37="PL23_ESTIMATE",ISNUMBER(I37)),ROUND(I37*K37/100,2),"") -> 174.23 | N37: =IF(J37="SOURCE_GROSS",IF(AND(ISNUMBER(E37),ISNUMBER(M37)),ROUND(E37*M37,2),""),IF(ISNUMBER(I37),ROUND(I37+L37,2),"")) -> 931.73 | O37: ПРЕДВАРИТЕЛЬНЫЙ СЦЕНАРИЙ M09: один бойлер; потребность ГВС не рассчитана; не утверждённое количество закупки. | P37: 40L1200W220V plus engine heat exchanger common illustrative class; not owner size. Supplier dimensions/mass in research only pending official drawing. Thermostatic mixing equalise separately. | 40L1200W220V plus engine heat exchanger common illustrative class; not owner size. Supplier dimensions/mass in research only pending official drawing. Thermostatic mixing equalise separately. | Исключено: Исходные ограничения M03 сохранены | UNIT_BENCHMARK_ONLY;QTY_OPEN | Q37: 2026-09-11 | R37: https://www.tyboat.com/achat/P-18237-quick-chauffe-eau-cube-inox-bxs-40-litres-220-volts-1200-watts.html | S37: ДА
A38: PK08-A | B38: PK08-A-L01 | C38: ME-15 | D38: Thermowell UC16H | E38: 2 | F38: шт | G38: WC-CH-01 | H38: 3621 | I38: =IF(AND(ISNUMBER(E38),ISNUMBER(H38)),ROUND(E38*H38,2),"") -> 7242 | J38: PL23_ESTIMATE | K38: 23 | L38: =IF(AND(J38="PL23_ESTIMATE",ISNUMBER(I38)),ROUND(I38*K38/100,2),"") -> 1665.66 | N38: =IF(J38="SOURCE_GROSS",IF(AND(ISNUMBER(E38),ISNUMBER(M38)),ROUND(E38*M38,2),""),IF(ISNUMBER(I38),ROUND(I38+L38,2),"")) -> 8907.66 | O38: Количество исходной M03; основные агрегаты без изменения | P38: 16000BTU/h each; illustrative class NOT yacht heatload. Officialcatalog220/1/50; dealer230V. Dimensions exclude controlbox. OEM catalogue says box/display included BUT priced Esco SKU requires airhandler/controlpanel separately: inclusion CONFLICT, RFQ required; do not assume included display.1.5kWnominput at catalogue conditions; independent2module integration open. | 16000BTU/h each; illustrative class NOT yacht heatload. Officialcatalog220/1/50; dealer230V. Dimensions exclude controlbox. OEM catalogue says box/display included BUT priced Esco SKU requires airhandler/controlpanel separately: inclusion CONFLICT, RFQ required; do not assume included display.1.5kWnominput at catalogue conditions; independent2module integration open. | Исключено: Исходные ограничения M03 сохранены | REFERENCE_SIZE_ONLY;VOLTAGE_REVISION_CHECK;SUPPLY_SCOPE_CONFLICT_RFQ | Q38: 2026-09-11 | R38: https://www.esconet.fi/shop/uc16h-thermowell-uc16h-ilmastointilaite-chiller-230v-16000btu-27518 | S38: ДА
A39: PK08-A | B39: PK08-A-L02 | C39: ME-16 | D39: Frigomar NH150PS230V | E39: 2 | F39: шт | G39: M09-M-02 | H39: 663.25 | I39: =IF(AND(ISNUMBER(E39),ISNUMBER(H39)),ROUND(E39*H39,2),"") -> 1326.5 | J39: PL23_ESTIMATE | K39: 23 | L39: =IF(AND(J39="PL23_ESTIMATE",ISNUMBER(I39)),ROUND(I39*K39/100,2),"") -> 305.1 | N39: =IF(J39="SOURCE_GROSS",IF(AND(ISNUMBER(E39),ISNUMBER(M39)),ROUND(E39*M39,2),""),IF(ISNUMBER(I39),ROUND(I39+L39,2),"")) -> 1631.6 | O39: ПРЕДВАРИТЕЛЬНЫЙ СЦЕНАРИЙ M09: по одному насосу охлаждения на каждый из двух климатических модулей; гидравлический расчёт открыт; не утверждённое количество закупки. | P39: Подстановка M09 вместо WC-AUX-01. Прежнее описание относится к старому SKU и сохранено в M03. | Магнитный насос NH150PS230V50/60Hz | Исключено: Арматура, шланги, управление, монтаж | Повтор M07. Назначение на контур забортной/охлаждённой воды, требуемая рабочая точка и ACдопуск OPEN; не два контура одним насосом. | Q39: 2026-09-15 | R39: https://www.comptoirnautique.com/climatisation-bateau/91819-frigomar-pompes-a-entrainement-magnetique.html | S39: ДА
A40: PK08-B | B40: PK08-B-L01 | C40: ME-15 | D40: Climma CWS Aquacontrol161RC 230/1/50 | E40: 2 | F40: шт | G40: WC-CH-02 | H40: 4155.3 | I40: =IF(AND(ISNUMBER(E40),ISNUMBER(H40)),ROUND(E40*H40,2),"") -> 8310.6 | J40: PL23_ESTIMATE | K40: 23 | L40: =IF(AND(J40="PL23_ESTIMATE",ISNUMBER(I40)),ROUND(I40*K40/100,2),"") -> 1911.44 | N40: =IF(J40="SOURCE_GROSS",IF(AND(ISNUMBER(E40),ISNUMBER(M40)),ROUND(E40*M40,2),""),IF(ISNUMBER(I40),ROUND(I40+L40,2),"")) -> 10222.04 | O40: Количество исходной M03; основные агрегаты без изменения | P40: 16000BTU/h each; reversecycle. Price recovered live requests HTTP200 after web429; local source text retained. OEM dimensions require authenticated download; old dealerPDF not promoted. | 16000BTU/h each; reversecycle. Price recovered live requests HTTP200 after web429; local source text retained. OEM dimensions require authenticated download; old dealerPDF not promoted. | Исключено: Исходные ограничения M03 сохранены | REFERENCE_SIZE_ONLY;220V_COMPATIBILITY_OPEN | Q40: 2026-09-11 | R40: https://mdislandsupply.com/en/climma/879-cws-aquacontrol-161-rc-230150-climma.html | S40: ДА
A41: PK08-B | B41: PK08-B-L02 | C41: ME-16 | D41: Frigomar NH150PS230V | E41: 2 | F41: шт | G41: M09-M-02 | H41: 663.25 | I41: =IF(AND(ISNUMBER(E41),ISNUMBER(H41)),ROUND(E41*H41,2),"") -> 1326.5 | J41: PL23_ESTIMATE | K41: 23 | L41: =IF(AND(J41="PL23_ESTIMATE",ISNUMBER(I41)),ROUND(I41*K41/100,2),"") -> 305.1 | N41: =IF(J41="SOURCE_GROSS",IF(AND(ISNUMBER(E41),ISNUMBER(M41)),ROUND(E41*M41,2),""),IF(ISNUMBER(I41),ROUND(I41+L41,2),"")) -> 1631.6 | O41: ПРЕДВАРИТЕЛЬНЫЙ СЦЕНАРИЙ M09: по одному насосу охлаждения на каждый из двух климатических модулей; гидравлический расчёт открыт; не утверждённое количество закупки. | P41: Подстановка M09 вместо WC-AUX-01. Прежнее описание относится к старому SKU и сохранено в M03. | Магнитный насос NH150PS230V50/60Hz | Исключено: Арматура, шланги, управление, монтаж | Повтор M07. Назначение на контур забортной/охлаждённой воды, требуемая рабочая точка и ACдопуск OPEN; не два контура одним насосом. | Q41: 2026-09-15 | R41: https://www.comptoirnautique.com/climatisation-bateau/91819-frigomar-pompes-a-entrainement-magnetique.html | S41: ДА
A42: PK08-C | B42: PK08-C-L01 | C42: ME-15 | D42: Webasto BlueCool C16M | E42: 2 | F42: шт | G42: WC-CH-03 | I42: =IF(AND(ISNUMBER(E42),ISNUMBER(H42)),ROUND(E42*H42,2),"") | J42: PL23_ESTIMATE | K42: 23 | L42: =IF(AND(J42="PL23_ESTIMATE",ISNUMBER(I42)),ROUND(I42*K42/100,2),"") | N42: =IF(J42="SOURCE_GROSS",IF(AND(ISNUMBER(E42),ISNUMBER(M42)),ROUND(E42*M42,2),""),IF(ISNUMBER(I42),ROUND(I42+L42,2),"")) | O42: Количество исходной M03; основные агрегаты без изменения | P42: 16000BTU/h each; officialcurrentdimensions. Older F-suffix dealerweight differs: revision match required.3pricepaths found no verified EU net exactSKU; no US price conversion. | 16000BTU/h each; officialcurrentdimensions. Older F-suffix dealerweight differs: revision match required.3pricepaths found no verified EU net exactSKU; no US price conversion. | Исключено: Исходные ограничения M03 сохранены | RFQ_REQUIRED;REFERENCE_SIZE_ONLY;220V_COMPATIBILITY_OPEN | Q42: 2026-09-11 | R42: https://www.nauticsale.com/en/airconditioning/bluecool-chiller-systems/bluecool-c-series-chillers/ | S42: ДА
A43: PK08-C | B43: PK08-C-L02 | C43: ME-16 | D43: Frigomar NH150PS230V | E43: 2 | F43: шт | G43: M09-M-02 | H43: 663.25 | I43: =IF(AND(ISNUMBER(E43),ISNUMBER(H43)),ROUND(E43*H43,2),"") -> 1326.5 | J43: PL23_ESTIMATE | K43: 23 | L43: =IF(AND(J43="PL23_ESTIMATE",ISNUMBER(I43)),ROUND(I43*K43/100,2),"") -> 305.1 | N43: =IF(J43="SOURCE_GROSS",IF(AND(ISNUMBER(E43),ISNUMBER(M43)),ROUND(E43*M43,2),""),IF(ISNUMBER(I43),ROUND(I43+L43,2),"")) -> 1631.6 | O43: ПРЕДВАРИТЕЛЬНЫЙ СЦЕНАРИЙ M09: по одному насосу охлаждения на каждый из двух климатических модулей; гидравлический расчёт открыт; не утверждённое количество закупки. | P43: Подстановка M09 вместо WC-AUX-01. Прежнее описание относится к старому SKU и сохранено в M03. | Магнитный насос NH150PS230V50/60Hz | Исключено: Арматура, шланги, управление, монтаж | Повтор M07. Назначение на контур забортной/охлаждённой воды, требуемая рабочая точка и ACдопуск OPEN; не два контура одним насосом. | Q43: 2026-09-15 | R43: https://www.comptoirnautique.com/climatisation-bateau/91819-frigomar-pompes-a-entrainement-magnetique.html | S43: ДА
A44: PK09-A | B44: PK09-A-L01 | C44: ME-18 | D44: Racor дуплексный фильтр30мкм | E44: 1 | F44: шт | G44: M09-M-04 | H44: 1848.66 | I44: =IF(AND(ISNUMBER(E44),ISNUMBER(H44)),ROUND(E44*H44,2),"") -> 1848.66 | J44: PL23_ESTIMATE | K44: 23 | L44: =IF(AND(J44="PL23_ESTIMATE",ISNUMBER(I44)),ROUND(I44*K44/100,2),"") -> 425.19 | N44: =IF(J44="SOURCE_GROSS",IF(AND(ISNUMBER(E44),ISNUMBER(M44)),ROUND(E44*M44,2),""),IF(ISNUMBER(I44),ROUND(I44+L44,2),"")) -> 2273.85 | O44: ПРЕДВАРИТЕЛЬНЫЙ СЦЕНАРИЙ M09: одна внешняя фильтрующая ветвь главного двигателя; генерирующие ветви раскрыты отдельно; не утверждённое количество закупки. | P44: Подстановка M09 вместо A09. Прежнее описание относится к старому SKU и сохранено в M03. | Два корпуса,4ходовойклапан,кронштейн,30мкмэлементы | Исключено: Трубопроводы,фитинги,монтаж,первичнаяпрокачка | Повтор M07;2корпуса — один дуплексный узел. Расход одной активной ветви и OEMмикроны подтвердить;не умножать на3машиныавтоматически. | Q44: 2026-09-15 | R44: https://racorshop.de/product/racor-75500maxm30-turbine-filter-marine/ | S44: ДА
A45: PK09-A | B45: PK09-A-L02 | C45: ME-19 | D45: Vetus FTR330/32 | F45: шт | G45: A10 | H45: 95.06 | I45: =IF(AND(ISNUMBER(E45),ISNUMBER(H45)),ROUND(E45*H45,2),"") | J45: PL23_ESTIMATE | K45: 23 | L45: =IF(AND(J45="PL23_ESTIMATE",ISNUMBER(I45)),ROUND(I45*K45/100,2),"") | N45: =IF(J45="SOURCE_GROSS",IF(AND(ISNUMBER(E45),ISNUMBER(M45)),ROUND(E45*M45,2),""),IF(ISNUMBER(I45),ROUND(I45+L45,2),"")) | O45: Количество исходной M03; основные агрегаты без изменения | P45: Типоразмер32мм только ориентир; диаметр и положение относительно ватерлинии по выбранному агрегату. | Типоразмер32мм только ориентир; диаметр и положение относительно ватерлинии по выбранному агрегату. | Исключено: Исходные ограничения M03 сохранены | UNIT_BENCHMARK_TECH_OPEN | Q45: 2026-09-11 | R45: https://www.vetus-shop.com/vetus-raw-water-strainer-type-330-and21632mm-p-1026.html | S45: ДА
A46: PK09-A | B46: PK09-A-L03 | C46: ME-22 | D46: Ocean Technologies blower / 24 V / 1000 m³/h | E46: 2 | F46: шт | G46: AX04 | H46: 189.87 | I46: =IF(AND(ISNUMBER(E46),ISNUMBER(H46)),ROUND(E46*H46,2),"") -> 379.74 | J46: PL23_ESTIMATE | K46: 23 | L46: =IF(AND(J46="PL23_ESTIMATE",ISNUMBER(I46)),ROUND(I46*K46/100,2),"") -> 87.34 | N46: =IF(J46="SOURCE_GROSS",IF(AND(ISNUMBER(E46),ISNUMBER(M46)),ROUND(E46*M46,2),""),IF(ISNUMBER(I46),ROUND(I46+L46,2),"")) -> 467.08 | O46: ПРЕДВАРИТЕЛЬНЫЙ СЦЕНАРИЙ M09: один приточный и один вытяжной вентилятор; расход не суммировать как удвоенный расход МО; не утверждённое количество закупки. | P46: Подстановка M09 вместо A15. Прежнее описание относится к старому SKU и сохранено в M03. | Вентилятор 24 V. | Исключено: Воздуховоды, решётки, шумоглушение, противопожарное перекрытие и останов, питание, монтаж. | 24 V; 1000 м³/ч — каталожный расход, не подтверждённый расход сети. Нужен баланс воздуха двигателя и двух генераторов. | Q46: 2026-09-15 | R46: https://www.svb24.com/en/ocean-technologies-engine-compartment-blower-24-v-1000-m3-hour-150-mm-flex-mount.html | S46: ДА
A47: PK09-A | B47: PK09-A-L04 | C47: ME-23 | D47: Marco UP3 Oil Change Pump / 24 V | E47: 1 | F47: шт | G47: AX05 | H47: 168.03 | I47: =IF(AND(ISNUMBER(E47),ISNUMBER(H47)),ROUND(E47*H47,2),"") -> 168.03 | J47: PL23_ESTIMATE | K47: 23 | L47: =IF(AND(J47="PL23_ESTIMATE",ISNUMBER(I47)),ROUND(I47*K47/100,2),"") -> 38.65 | N47: =IF(J47="SOURCE_GROSS",IF(AND(ISNUMBER(E47),ISNUMBER(M47)),ROUND(E47*M47,2),""),IF(ISNUMBER(I47),ROUND(I47+L47,2),"")) -> 206.68 | O47: ПРЕДВАРИТЕЛЬНЫЙ СЦЕНАРИЙ M09: один компонент соответствующей функции; состав и производительность уточняются; не утверждённое количество закупки. | P47: Подстановка M09 вместо A16. Прежнее описание относится к старому SKU и сохранено в M03. | Насос и две трубки 6/8 мм длиной 80 см. | Исключено: Стационарный коллектор двигателя/двух генераторов/редуктора, запорная арматура, длинные шланги, ёмкость отработки, защиты, монтаж. | 24 V вариант: именно 168.03, не стартовая цена 12 V 166.34. Масло предварительно прогреть по карточке; вязкость и точки отбора уточнить. | Q47: 2026-09-15 | R47: https://www.svb24.com/en/marco-up3-electric-oil-change-pump.html | S47: ДА
A48: PK09-B | B48: PK09-B-L01 | C48: ME-18 | D48: Racor дуплексный фильтр30мкм | E48: 1 | F48: шт | G48: M09-M-04 | H48: 1848.66 | I48: =IF(AND(ISNUMBER(E48),ISNUMBER(H48)),ROUND(E48*H48,2),"") -> 1848.66 | J48: PL23_ESTIMATE | K48: 23 | L48: =IF(AND(J48="PL23_ESTIMATE",ISNUMBER(I48)),ROUND(I48*K48/100,2),"") -> 425.19 | N48: =IF(J48="SOURCE_GROSS",IF(AND(ISNUMBER(E48),ISNUMBER(M48)),ROUND(E48*M48,2),""),IF(ISNUMBER(I48),ROUND(I48+L48,2),"")) -> 2273.85 | O48: ПРЕДВАРИТЕЛЬНЫЙ СЦЕНАРИЙ M09: одна внешняя фильтрующая ветвь главного двигателя; генерирующие ветви раскрыты отдельно; не утверждённое количество закупки. | P48: Подстановка M09 вместо A09. Прежнее описание относится к старому SKU и сохранено в M03. | Два корпуса,4ходовойклапан,кронштейн,30мкмэлементы | Исключено: Трубопроводы,фитинги,монтаж,первичнаяпрокачка | Повтор M07;2корпуса — один дуплексный узел. Расход одной активной ветви и OEMмикроны подтвердить;не умножать на3машиныавтоматически. | Q48: 2026-09-15 | R48: https://racorshop.de/product/racor-75500maxm30-turbine-filter-marine/ | S48: ДА
A49: PK09-B | B49: PK09-B-L02 | C49: ME-19 | D49: Vetus330 heavy-duty32мм | E49: 1 | F49: шт | G49: M09-M-11 | H49: 164.46 | I49: =IF(AND(ISNUMBER(E49),ISNUMBER(H49)),ROUND(E49*H49,2),"") -> 164.46 | J49: PL23_ESTIMATE | K49: 23 | L49: =IF(AND(J49="PL23_ESTIMATE",ISNUMBER(I49)),ROUND(I49*K49/100,2),"") -> 37.83 | N49: =IF(J49="SOURCE_GROSS",IF(AND(ISNUMBER(E49),ISNUMBER(M49)),ROUND(E49*M49,2),""),IF(ISNUMBER(I49),ROUND(I49+L49,2),"")) -> 202.29 | O49: ПРЕДВАРИТЕЛЬНЫЙ СЦЕНАРИЙ M09: одна внешняя фильтрующая ветвь главного двигателя; генерирующие ветви раскрыты отдельно; не утверждённое количество закупки. | P49: Подстановка M09 вместо A11. Прежнее описание относится к старому SKU и сохранено в M03. | Фильтр забортной воды32мм, металлическаякрышка | Исключено: Кингстон,шланги,хомуты,монтаж | ПовторM07;не добавлять ккомплекту уже содержащему фильтр.Подобратьрасходиустановочныйуровень. | Q49: 2026-09-15 | R49: https://www.mediawinkel.eu/nl/heavy-duty-waterfilter-32-mm.html | S49: ДА
A50: PK09-B | B50: PK09-B-L03 | C50: ME-22 | D50: Ocean Technologies blower / 24 V / 1000 m³/h | E50: 2 | F50: шт | G50: AX04 | H50: 189.87 | I50: =IF(AND(ISNUMBER(E50),ISNUMBER(H50)),ROUND(E50*H50,2),"") -> 379.74 | J50: PL23_ESTIMATE | K50: 23 | L50: =IF(AND(J50="PL23_ESTIMATE",ISNUMBER(I50)),ROUND(I50*K50/100,2),"") -> 87.34 | N50: =IF(J50="SOURCE_GROSS",IF(AND(ISNUMBER(E50),ISNUMBER(M50)),ROUND(E50*M50,2),""),IF(ISNUMBER(I50),ROUND(I50+L50,2),"")) -> 467.08 | O50: ПРЕДВАРИТЕЛЬНЫЙ СЦЕНАРИЙ M09: один приточный и один вытяжной вентилятор; расход не суммировать как удвоенный расход МО; не утверждённое количество закупки. | P50: Подстановка M09 вместо A15. Прежнее описание относится к старому SKU и сохранено в M03. | Вентилятор 24 V. | Исключено: Воздуховоды, решётки, шумоглушение, противопожарное перекрытие и останов, питание, монтаж. | 24 V; 1000 м³/ч — каталожный расход, не подтверждённый расход сети. Нужен баланс воздуха двигателя и двух генераторов. | Q50: 2026-09-15 | R50: https://www.svb24.com/en/ocean-technologies-engine-compartment-blower-24-v-1000-m3-hour-150-mm-flex-mount.html | S50: ДА
A51: PK09-B | B51: PK09-B-L04 | C51: ME-23 | D51: Marco UP3 Oil Change Pump / 24 V | E51: 1 | F51: шт | G51: AX05 | H51: 168.03 | I51: =IF(AND(ISNUMBER(E51),ISNUMBER(H51)),ROUND(E51*H51,2),"") -> 168.03 | J51: PL23_ESTIMATE | K51: 23 | L51: =IF(AND(J51="PL23_ESTIMATE",ISNUMBER(I51)),ROUND(I51*K51/100,2),"") -> 38.65 | N51: =IF(J51="SOURCE_GROSS",IF(AND(ISNUMBER(E51),ISNUMBER(M51)),ROUND(E51*M51,2),""),IF(ISNUMBER(I51),ROUND(I51+L51,2),"")) -> 206.68 | O51: ПРЕДВАРИТЕЛЬНЫЙ СЦЕНАРИЙ M09: один компонент соответствующей функции; состав и производительность уточняются; не утверждённое количество закупки. | P51: Подстановка M09 вместо A16. Прежнее описание относится к старому SKU и сохранено в M03. | Насос и две трубки 6/8 мм длиной 80 см. | Исключено: Стационарный коллектор двигателя/двух генераторов/редуктора, запорная арматура, длинные шланги, ёмкость отработки, защиты, монтаж. | 24 V вариант: именно 168.03, не стартовая цена 12 V 166.34. Масло предварительно прогреть по карточке; вязкость и точки отбора уточнить. | Q51: 2026-09-15 | R51: https://www.svb24.com/en/marco-up3-electric-oil-change-pump.html | S51: ДА
A52: PK09-C | B52: PK09-C-L01 | C52: ME-18 | D52: Racor дуплексный фильтр30мкм | E52: 1 | F52: шт | G52: M09-M-04 | H52: 1848.66 | I52: =IF(AND(ISNUMBER(E52),ISNUMBER(H52)),ROUND(E52*H52,2),"") -> 1848.66 | J52: PL23_ESTIMATE | K52: 23 | L52: =IF(AND(J52="PL23_ESTIMATE",ISNUMBER(I52)),ROUND(I52*K52/100,2),"") -> 425.19 | N52: =IF(J52="SOURCE_GROSS",IF(AND(ISNUMBER(E52),ISNUMBER(M52)),ROUND(E52*M52,2),""),IF(ISNUMBER(I52),ROUND(I52+L52,2),"")) -> 2273.85 | O52: ПРЕДВАРИТЕЛЬНЫЙ СЦЕНАРИЙ M09: одна внешняя фильтрующая ветвь главного двигателя; генерирующие ветви раскрыты отдельно; не утверждённое количество закупки. | P52: Подстановка M09 вместо A09. Прежнее описание относится к старому SKU и сохранено в M03. | Два корпуса,4ходовойклапан,кронштейн,30мкмэлементы | Исключено: Трубопроводы,фитинги,монтаж,первичнаяпрокачка | Повтор M07;2корпуса — один дуплексный узел. Расход одной активной ветви и OEMмикроны подтвердить;не умножать на3машиныавтоматически. | Q52: 2026-09-15 | R52: https://racorshop.de/product/racor-75500maxm30-turbine-filter-marine/ | S52: ДА
A53: PK09-C | B53: PK09-C-L02 | C53: ME-19 | D53: Vetus330 heavy-duty32мм | E53: 1 | F53: шт | G53: M09-M-11 | H53: 164.46 | I53: =IF(AND(ISNUMBER(E53),ISNUMBER(H53)),ROUND(E53*H53,2),"") -> 164.46 | J53: PL23_ESTIMATE | K53: 23 | L53: =IF(AND(J53="PL23_ESTIMATE",ISNUMBER(I53)),ROUND(I53*K53/100,2),"") -> 37.83 | N53: =IF(J53="SOURCE_GROSS",IF(AND(ISNUMBER(E53),ISNUMBER(M53)),ROUND(E53*M53,2),""),IF(ISNUMBER(I53),ROUND(I53+L53,2),"")) -> 202.29 | O53: ПРЕДВАРИТЕЛЬНЫЙ СЦЕНАРИЙ M09: одна внешняя фильтрующая ветвь главного двигателя; генерирующие ветви раскрыты отдельно; не утверждённое количество закупки. | P53: Подстановка M09 вместо A11. Прежнее описание относится к старому SKU и сохранено в M03. | Фильтр забортной воды32мм, металлическаякрышка | Исключено: Кингстон,шланги,хомуты,монтаж | ПовторM07;не добавлять ккомплекту уже содержащему фильтр.Подобратьрасходиустановочныйуровень. | Q53: 2026-09-15 | R53: https://www.mediawinkel.eu/nl/heavy-duty-waterfilter-32-mm.html | S53: ДА
A54: PK09-C | B54: PK09-C-L03 | C54: ME-22 | D54: Ocean Technologies blower / 24 V / 1000 m³/h | E54: 2 | F54: шт | G54: AX04 | H54: 189.87 | I54: =IF(AND(ISNUMBER(E54),ISNUMBER(H54)),ROUND(E54*H54,2),"") -> 379.74 | J54: PL23_ESTIMATE | K54: 23 | L54: =IF(AND(J54="PL23_ESTIMATE",ISNUMBER(I54)),ROUND(I54*K54/100,2),"") -> 87.34 | N54: =IF(J54="SOURCE_GROSS",IF(AND(ISNUMBER(E54),ISNUMBER(M54)),ROUND(E54*M54,2),""),IF(ISNUMBER(I54),ROUND(I54+L54,2),"")) -> 467.08 | O54: ПРЕДВАРИТЕЛЬНЫЙ СЦЕНАРИЙ M09: один приточный и один вытяжной вентилятор; расход не суммировать как удвоенный расход МО; не утверждённое количество закупки. | P54: Подстановка M09 вместо A15. Прежнее описание относится к старому SKU и сохранено в M03. | Вентилятор 24 V. | Исключено: Воздуховоды, решётки, шумоглушение, противопожарное перекрытие и останов, питание, монтаж. | 24 V; 1000 м³/ч — каталожный расход, не подтверждённый расход сети. Нужен баланс воздуха двигателя и двух генераторов. | Q54: 2026-09-15 | R54: https://www.svb24.com/en/ocean-technologies-engine-compartment-blower-24-v-1000-m3-hour-150-mm-flex-mount.html | S54: ДА
A55: PK09-C | B55: PK09-C-L04 | C55: ME-23 | D55: Marco UP3 Oil Change Pump / 24 V | E55: 1 | F55: шт | G55: AX05 | H55: 168.03 | I55: =IF(AND(ISNUMBER(E55),ISNUMBER(H55)),ROUND(E55*H55,2),"") -> 168.03 | J55: PL23_ESTIMATE | K55: 23 | L55: =IF(AND(J55="PL23_ESTIMATE",ISNUMBER(I55)),ROUND(I55*K55/100,2),"") -> 38.65 | N55: =IF(J55="SOURCE_GROSS",IF(AND(ISNUMBER(E55),ISNUMBER(M55)),ROUND(E55*M55,2),""),IF(ISNUMBER(I55),ROUND(I55+L55,2),"")) -> 206.68 | O55: ПРЕДВАРИТЕЛЬНЫЙ СЦЕНАРИЙ M09: один компонент соответствующей функции; состав и производительность уточняются; не утверждённое количество закупки. | P55: Подстановка M09 вместо A16. Прежнее описание относится к старому SKU и сохранено в M03. | Насос и две трубки 6/8 мм длиной 80 см. | Исключено: Стационарный коллектор двигателя/двух генераторов/редуктора, запорная арматура, длинные шланги, ёмкость отработки, защиты, монтаж. | 24 V вариант: именно 168.03, не стартовая цена 12 V 166.34. Масло предварительно прогреть по карточке; вязкость и точки отбора уточнить. | Q55: 2026-09-15 | R55: https://www.svb24.com/en/marco-up3-electric-oil-change-pump.html | S55: ДА
A56: PK10-A | B56: PK10-A-L01 | C56: ME-20 | D56: Rule 2000 / 24 V | E56: 2 | F56: шт | G56: AX01 | H56: 153.36 | I56: =IF(AND(ISNUMBER(E56),ISNUMBER(H56)),ROUND(E56*H56,2),"") -> 306.72 | J56: PL23_ESTIMATE | K56: 23 | L56: =IF(AND(J56="PL23_ESTIMATE",ISNUMBER(I56)),ROUND(I56*K56/100,2),"") -> 70.55 | N56: =IF(J56="SOURCE_GROSS",IF(AND(ISNUMBER(E56),ISNUMBER(M56)),ROUND(E56*M56,2),""),IF(ISNUMBER(I56),ROUND(I56+L56,2),"")) -> 377.27 | O56: ПРЕДВАРИТЕЛЬНЫЙ СЦЕНАРИЙ M09: два местных поста осушения/сигнализации МО; не расчёт общей аварийной системы яхты; не утверждённое количество закупки. | P56: Подстановка M09 вместо A12. Прежнее описание относится к старому SKU и сохранено в M03. | Погружная осушительная помпа. | Исключено: Поплавок, независимая аварийная сигнализация, щит, проводка, шланги, арматура, монтаж. | 24 V; максимум 129 л/мин без подтверждения рабочего напора. Не доказана достаточность аварийного осушения VDS67. | Q56: 2026-09-15 | R56: https://www.svb24.com/en/rule-heavy-duty-bilge-pump-2000-24v.html | S56: ДА
A57: PK10-A | B57: PK10-A-L02 | C57: ME-20 | D57: Whale Gusher Urchin BP9005 | E57: 1 | F57: шт | G57: AX02 | H57: 89.87 | I57: =IF(AND(ISNUMBER(E57),ISNUMBER(H57)),ROUND(E57*H57,2),"") -> 89.87 | J57: PL23_ESTIMATE | K57: 23 | L57: =IF(AND(J57="PL23_ESTIMATE",ISNUMBER(I57)),ROUND(I57*K57/100,2),"") -> 20.67 | N57: =IF(J57="SOURCE_GROSS",IF(AND(ISNUMBER(E57),ISNUMBER(M57)),ROUND(E57*M57,2),""),IF(ISNUMBER(I57),ROUND(I57+L57,2),"")) -> 110.54 | O57: ПРЕДВАРИТЕЛЬНЫЙ СЦЕНАРИЙ M09: один компонент соответствующей функции; состав и производительность уточняются; не утверждённое количество закупки. | P57: Подстановка M09 вместо A13. Прежнее описание относится к старому SKU и сохранено в M03. | Ручная помпа указанного исполнения. | Исключено: Шланги, приёмники, арматура и монтаж. | Ручная. Компактный ценовой ориентир; не утверждена как главная аварийная помпа яхты 67 ft. | Q57: 2026-09-15 | R57: https://www.svb24.com/en/whale-gusher-urchin-manual-bilge-pump-type-bp-9005.html | S57: ДА
A58: PK10-A | B58: PK10-A-L03 | C58: ME-20 | D58: Johnson Bilge Alert / 24 V | E58: 2 | F58: шт | G58: AX08 | H58: 97.44 | I58: =IF(AND(ISNUMBER(E58),ISNUMBER(H58)),ROUND(E58*H58,2),"") -> 194.88 | J58: PL23_ESTIMATE | K58: 23 | L58: =IF(AND(J58="PL23_ESTIMATE",ISNUMBER(I58)),ROUND(I58*K58/100,2),"") -> 44.82 | N58: =IF(J58="SOURCE_GROSS",IF(AND(ISNUMBER(E58),ISNUMBER(M58)),ROUND(E58*M58,2),""),IF(ISNUMBER(I58),ROUND(I58+L58,2),"")) -> 239.7 | O58: ПРЕДВАРИТЕЛЬНЫЙ СЦЕНАРИЙ M09: два местных поста осушения/сигнализации МО; не расчёт общей аварийной системы яхты; не утверждённое количество закупки. | P58: Подстановка M09 вместо A14. Прежнее описание относится к старому SKU и сохранено в M03. | Датчик высокого уровня, звуковая/световая сигнализация и органы тестирования по карточке. | Исключено: Многозонная интеграция, независимое питание, проводка, помпы и монтаж. | 24 V вариант 97.44; 92.40 относится к 12 V. Сигнализацию не считать второй помпой или всей судовой автоматикой. | Q58: 2026-09-15 | R58: https://www.svb24.com/en/johnson-pump-bilge-alert-high-water-alarm-with-ultima-switch.html | S58: ДА
A59: PK10-A | B59: PK10-A-L04 | C59: ME-21 | D59: Fireboy MA / 26.8 kg / 31.1 m³ | E59: 1 | F59: шт | G59: AX14 | I59: =IF(AND(ISNUMBER(E59),ISNUMBER(H59)),ROUND(E59*H59,2),"") | J59: SOURCE_GROSS | L59: =IF(AND(J59="PL23_ESTIMATE",ISNUMBER(I59)),ROUND(I59*K59/100,2),"") | M59: 4251.1 | N59: =IF(J59="SOURCE_GROSS",IF(AND(ISNUMBER(E59),ISNUMBER(M59)),ROUND(E59*M59,2),""),IF(ISNUMBER(I59),ROUND(I59+L59,2),"")) -> 4251.1 | O59: ПРЕДВАРИТЕЛЬНЫЙ СЦЕНАРИЙ M09: один ценовой аналог баллона 31.1 м³; объём около 29.6 м³ G03 не доказывает достаточность заряда, нужна проверка проекта и изготовителя; не утверждённое количество закупки. | P59: Подстановка M09 вместо A20. Прежнее описание относится к старому SKU и сохранено в M03. | Баллон указанного исполнения; состав крепления и индикации подтвердить в КП. | Исключено: Трос ручного пуска, shutdown-контроллер, проводка, исполнительные клапаны/заслонки, монтаж и приёмка. | Исследовательский ориентир более крупного баллона: защищаемый объём по таблице 31.1 м³. G03 мокрая зона приблизительно 29.6 м³ не является утверждённым защищаемым объёмом. Подбор заряда и пригодность не подтверждены. Альтернатива AX10, не добавочный обязательный баллон. | Q59: 2026-09-15 | R59: https://www.nauticabasile.it/eng/osculati/fixed-fireboy-fire-extinguishers-with-clean-agent-and-manualautomatic-activation-46870/31.610.31/ | S59: ДА
A60: PK10-B | B60: PK10-B-L01 | C60: ME-20 | D60: Rule 2000 / 24 V | E60: 2 | F60: шт | G60: AX01 | H60: 153.36 | I60: =IF(AND(ISNUMBER(E60),ISNUMBER(H60)),ROUND(E60*H60,2),"") -> 306.72 | J60: PL23_ESTIMATE | K60: 23 | L60: =IF(AND(J60="PL23_ESTIMATE",ISNUMBER(I60)),ROUND(I60*K60/100,2),"") -> 70.55 | N60: =IF(J60="SOURCE_GROSS",IF(AND(ISNUMBER(E60),ISNUMBER(M60)),ROUND(E60*M60,2),""),IF(ISNUMBER(I60),ROUND(I60+L60,2),"")) -> 377.27 | O60: ПРЕДВАРИТЕЛЬНЫЙ СЦЕНАРИЙ M09: два местных поста осушения/сигнализации МО; не расчёт общей аварийной системы яхты; не утверждённое количество закупки. | P60: Подстановка M09 вместо A12. Прежнее описание относится к старому SKU и сохранено в M03. | Погружная осушительная помпа. | Исключено: Поплавок, независимая аварийная сигнализация, щит, проводка, шланги, арматура, монтаж. | 24 V; максимум 129 л/мин без подтверждения рабочего напора. Не доказана достаточность аварийного осушения VDS67. | Q60: 2026-09-15 | R60: https://www.svb24.com/en/rule-heavy-duty-bilge-pump-2000-24v.html | S60: ДА
A61: PK10-B | B61: PK10-B-L02 | C61: ME-20 | D61: Whale Gusher Urchin BP9005 | E61: 1 | F61: шт | G61: AX02 | H61: 89.87 | I61: =IF(AND(ISNUMBER(E61),ISNUMBER(H61)),ROUND(E61*H61,2),"") -> 89.87 | J61: PL23_ESTIMATE | K61: 23 | L61: =IF(AND(J61="PL23_ESTIMATE",ISNUMBER(I61)),ROUND(I61*K61/100,2),"") -> 20.67 | N61: =IF(J61="SOURCE_GROSS",IF(AND(ISNUMBER(E61),ISNUMBER(M61)),ROUND(E61*M61,2),""),IF(ISNUMBER(I61),ROUND(I61+L61,2),"")) -> 110.54 | O61: ПРЕДВАРИТЕЛЬНЫЙ СЦЕНАРИЙ M09: один компонент соответствующей функции; состав и производительность уточняются; не утверждённое количество закупки. | P61: Подстановка M09 вместо A13. Прежнее описание относится к старому SKU и сохранено в M03. | Ручная помпа указанного исполнения. | Исключено: Шланги, приёмники, арматура и монтаж. | Ручная. Компактный ценовой ориентир; не утверждена как главная аварийная помпа яхты 67 ft. | Q61: 2026-09-15 | R61: https://www.svb24.com/en/whale-gusher-urchin-manual-bilge-pump-type-bp-9005.html | S61: ДА
A62: PK10-B | B62: PK10-B-L03 | C62: ME-20 | D62: Johnson Bilge Alert / 24 V | E62: 2 | F62: шт | G62: AX08 | H62: 97.44 | I62: =IF(AND(ISNUMBER(E62),ISNUMBER(H62)),ROUND(E62*H62,2),"") -> 194.88 | J62: PL23_ESTIMATE | K62: 23 | L62: =IF(AND(J62="PL23_ESTIMATE",ISNUMBER(I62)),ROUND(I62*K62/100,2),"") -> 44.82 | N62: =IF(J62="SOURCE_GROSS",IF(AND(ISNUMBER(E62),ISNUMBER(M62)),ROUND(E62*M62,2),""),IF(ISNUMBER(I62),ROUND(I62+L62,2),"")) -> 239.7 | O62: ПРЕДВАРИТЕЛЬНЫЙ СЦЕНАРИЙ M09: два местных поста осушения/сигнализации МО; не расчёт общей аварийной системы яхты; не утверждённое количество закупки. | P62: Подстановка M09 вместо A14. Прежнее описание относится к старому SKU и сохранено в M03. | Датчик высокого уровня, звуковая/световая сигнализация и органы тестирования по карточке. | Исключено: Многозонная интеграция, независимое питание, проводка, помпы и монтаж. | 24 V вариант 97.44; 92.40 относится к 12 V. Сигнализацию не считать второй помпой или всей судовой автоматикой. | Q62: 2026-09-15 | R62: https://www.svb24.com/en/johnson-pump-bilge-alert-high-water-alarm-with-ultima-switch.html | S62: ДА
A63: PK10-B | B63: PK10-B-L04 | C63: ME-21 | D63: Fireboy MA / 26.8 kg / 31.1 m³ | E63: 1 | F63: шт | G63: AX14 | I63: =IF(AND(ISNUMBER(E63),ISNUMBER(H63)),ROUND(E63*H63,2),"") | J63: SOURCE_GROSS | L63: =IF(AND(J63="PL23_ESTIMATE",ISNUMBER(I63)),ROUND(I63*K63/100,2),"") | M63: 4251.1 | N63: =IF(J63="SOURCE_GROSS",IF(AND(ISNUMBER(E63),ISNUMBER(M63)),ROUND(E63*M63,2),""),IF(ISNUMBER(I63),ROUND(I63+L63,2),"")) -> 4251.1 | O63: ПРЕДВАРИТЕЛЬНЫЙ СЦЕНАРИЙ M09: один ценовой аналог баллона 31.1 м³; объём около 29.6 м³ G03 не доказывает достаточность заряда, нужна проверка проекта и изготовителя; не утверждённое количество закупки. | P63: Подстановка M09 вместо A20. Прежнее описание относится к старому SKU и сохранено в M03. | Баллон указанного исполнения; состав крепления и индикации подтвердить в КП. | Исключено: Трос ручного пуска, shutdown-контроллер, проводка, исполнительные клапаны/заслонки, монтаж и приёмка. | Исследовательский ориентир более крупного баллона: защищаемый объём по таблице 31.1 м³. G03 мокрая зона приблизительно 29.6 м³ не является утверждённым защищаемым объёмом. Подбор заряда и пригодность не подтверждены. Альтернатива AX10, не добавочный обязательный баллон. | Q63: 2026-09-15 | R63: https://www.nauticabasile.it/eng/osculati/fixed-fireboy-fire-extinguishers-with-clean-agent-and-manualautomatic-activation-46870/31.610.31/ | S63: ДА
A64: PK10-C | B64: PK10-C-L01 | C64: ME-20 | D64: Rule 2000 / 24 V | E64: 2 | F64: шт | G64: AX01 | H64: 153.36 | I64: =IF(AND(ISNUMBER(E64),ISNUMBER(H64)),ROUND(E64*H64,2),"") -> 306.72 | J64: PL23_ESTIMATE | K64: 23 | L64: =IF(AND(J64="PL23_ESTIMATE",ISNUMBER(I64)),ROUND(I64*K64/100,2),"") -> 70.55 | N64: =IF(J64="SOURCE_GROSS",IF(AND(ISNUMBER(E64),ISNUMBER(M64)),ROUND(E64*M64,2),""),IF(ISNUMBER(I64),ROUND(I64+L64,2),"")) -> 377.27 | O64: ПРЕДВАРИТЕЛЬНЫЙ СЦЕНАРИЙ M09: два местных поста осушения/сигнализации МО; не расчёт общей аварийной системы яхты; не утверждённое количество закупки. | P64: Подстановка M09 вместо A12. Прежнее описание относится к старому SKU и сохранено в M03. | Погружная осушительная помпа. | Исключено: Поплавок, независимая аварийная сигнализация, щит, проводка, шланги, арматура, монтаж. | 24 V; максимум 129 л/мин без подтверждения рабочего напора. Не доказана достаточность аварийного осушения VDS67. | Q64: 2026-09-15 | R64: https://www.svb24.com/en/rule-heavy-duty-bilge-pump-2000-24v.html | S64: ДА
A65: PK10-C | B65: PK10-C-L02 | C65: ME-20 | D65: Whale Gusher Urchin BP9005 | E65: 1 | F65: шт | G65: AX02 | H65: 89.87 | I65: =IF(AND(ISNUMBER(E65),ISNUMBER(H65)),ROUND(E65*H65,2),"") -> 89.87 | J65: PL23_ESTIMATE | K65: 23 | L65: =IF(AND(J65="PL23_ESTIMATE",ISNUMBER(I65)),ROUND(I65*K65/100,2),"") -> 20.67 | N65: =IF(J65="SOURCE_GROSS",IF(AND(ISNUMBER(E65),ISNUMBER(M65)),ROUND(E65*M65,2),""),IF(ISNUMBER(I65),ROUND(I65+L65,2),"")) -> 110.54 | O65: ПРЕДВАРИТЕЛЬНЫЙ СЦЕНАРИЙ M09: один компонент соответствующей функции; состав и производительность уточняются; не утверждённое количество закупки. | P65: Подстановка M09 вместо A13. Прежнее описание относится к старому SKU и сохранено в M03. | Ручная помпа указанного исполнения. | Исключено: Шланги, приёмники, арматура и монтаж. | Ручная. Компактный ценовой ориентир; не утверждена как главная аварийная помпа яхты 67 ft. | Q65: 2026-09-15 | R65: https://www.svb24.com/en/whale-gusher-urchin-manual-bilge-pump-type-bp-9005.html | S65: ДА
A66: PK10-C | B66: PK10-C-L03 | C66: ME-20 | D66: Johnson Bilge Alert / 24 V | E66: 2 | F66: шт | G66: AX08 | H66: 97.44 | I66: =IF(AND(ISNUMBER(E66),ISNUMBER(H66)),ROUND(E66*H66,2),"") -> 194.88 | J66: PL23_ESTIMATE | K66: 23 | L66: =IF(AND(J66="PL23_ESTIMATE",ISNUMBER(I66)),ROUND(I66*K66/100,2),"") -> 44.82 | N66: =IF(J66="SOURCE_GROSS",IF(AND(ISNUMBER(E66),ISNUMBER(M66)),ROUND(E66*M66,2),""),IF(ISNUMBER(I66),ROUND(I66+L66,2),"")) -> 239.7 | O66: ПРЕДВАРИТЕЛЬНЫЙ СЦЕНАРИЙ M09: два местных поста осушения/сигнализации МО; не расчёт общей аварийной системы яхты; не утверждённое количество закупки. | P66: Подстановка M09 вместо A14. Прежнее описание относится к старому SKU и сохранено в M03. | Датчик высокого уровня, звуковая/световая сигнализация и органы тестирования по карточке. | Исключено: Многозонная интеграция, независимое питание, проводка, помпы и монтаж. | 24 V вариант 97.44; 92.40 относится к 12 V. Сигнализацию не считать второй помпой или всей судовой автоматикой. | Q66: 2026-09-15 | R66: https://www.svb24.com/en/johnson-pump-bilge-alert-high-water-alarm-with-ultima-switch.html | S66: ДА
A67: PK10-C | B67: PK10-C-L04 | C67: ME-21 | D67: Fireboy MA / 26.8 kg / 31.1 m³ | E67: 1 | F67: шт | G67: AX14 | I67: =IF(AND(ISNUMBER(E67),ISNUMBER(H67)),ROUND(E67*H67,2),"") | J67: SOURCE_GROSS | L67: =IF(AND(J67="PL23_ESTIMATE",ISNUMBER(I67)),ROUND(I67*K67/100,2),"") | M67: 4251.1 | N67: =IF(J67="SOURCE_GROSS",IF(AND(ISNUMBER(E67),ISNUMBER(M67)),ROUND(E67*M67,2),""),IF(ISNUMBER(I67),ROUND(I67+L67,2),"")) -> 4251.1 | O67: ПРЕДВАРИТЕЛЬНЫЙ СЦЕНАРИЙ M09: один ценовой аналог баллона 31.1 м³; объём около 29.6 м³ G03 не доказывает достаточность заряда, нужна проверка проекта и изготовителя; не утверждённое количество закупки. | P67: Подстановка M09 вместо A20. Прежнее описание относится к старому SKU и сохранено в M03. | Баллон указанного исполнения; состав крепления и индикации подтвердить в КП. | Исключено: Трос ручного пуска, shutdown-контроллер, проводка, исполнительные клапаны/заслонки, монтаж и приёмка. | Исследовательский ориентир более крупного баллона: защищаемый объём по таблице 31.1 м³. G03 мокрая зона приблизительно 29.6 м³ не является утверждённым защищаемым объёмом. Подбор заряда и пригодность не подтверждены. Альтернатива AX10, не добавочный обязательный баллон. | Q67: 2026-09-15 | R67: https://www.nauticabasile.it/eng/osculati/fixed-fireboy-fire-extinguishers-with-clean-agent-and-manualautomatic-activation-46870/31.610.31/ | S67: ДА
A68: PK11-A | B68: PK11-A-L01 | C68: ME-24 | D68: Vetus SENSOR320 | E68: 5 | F68: шт | G68: A17 | H68: 71.78 | I68: =IF(AND(ISNUMBER(E68),ISNUMBER(H68)),ROUND(E68*H68,2),"") -> 358.9 | J68: PL23_ESTIMATE | K68: 23 | L68: =IF(AND(J68="PL23_ESTIMATE",ISNUMBER(I68)),ROUND(I68*K68/100,2),"") -> 82.55 | N68: =IF(J68="SOURCE_GROSS",IF(AND(ISNUMBER(E68),ISNUMBER(M68)),ROUND(E68*M68,2),""),IF(ISNUMBER(I68),ROUND(I68+L68,2),"")) -> 441.45 | O68: ПРЕДВАРИТЕЛЬНЫЙ СЦЕНАРИЙ M09: историческая spec-matrix: два топливных, два пресной воды, один сточный танк; наличие, глубины и пригодность датчиков ещё не проверены; не утверждённое количество закупки. | P68: Длина320мм исследовательская; не утверждена глубина/число танков. Цена связанного товара, отдельный индикатор не включён. | Длина320мм исследовательская; не утверждена глубина/число танков. Цена связанного товара, отдельный индикатор не включён. | Исключено: Исходные ограничения M03 сохранены | UNIT_BENCHMARK_TECH_OPEN | Q68: 2026-09-11 | R68: https://www.vetus-shop.com/vetus-fuel-tank-quickfit-diesel-40-litre-8mm-p-1786.html | S68: ДА
A69: PK11-A | B69: PK11-A-L02 | C69: ME-25 | D69: Jabsco Type 12GPM waste water pump / 24 V | E69: 1 | F69: шт | G69: AX06 | H69: 210.04 | I69: =IF(AND(ISNUMBER(E69),ISNUMBER(H69)),ROUND(E69*H69,2),"") -> 210.04 | J69: PL23_ESTIMATE | K69: 23 | L69: =IF(AND(J69="PL23_ESTIMATE",ISNUMBER(I69)),ROUND(I69*K69/100,2),"") -> 48.31 | N69: =IF(J69="SOURCE_GROSS",IF(AND(ISNUMBER(E69),ISNUMBER(M69)),ROUND(E69*M69,2),""),IF(ISNUMBER(I69),ROUND(I69+L69,2),"")) -> 258.35 | O69: ПРЕДВАРИТЕЛЬНЫЙ СЦЕНАРИЙ M09: один компонент соответствующей функции; состав и производительность уточняются; не утверждённое количество закупки. | P69: Подстановка M09 вместо A19. Прежнее описание относится к старому SKU и сохранено в M03. | Насос macerator. | Исключено: Санприборы, танки, трубопроводы, арматура, управление, монтаж. | 24 V. Проверить отсутствие повторного счёта насоса, включённого в сансистему; схема и допустимый сброс открыты. | Q69: 2026-09-15 | R69: https://www.svb24.com/en/jabsco-type-12gpm-waste-water-pump-24v.html | S69: ДА
A70: PK11-B | B70: PK11-B-L01 | C70: ME-24 | D70: Vetus SENSORA | E70: 5 | F70: шт | G70: A18 | H70: 187.69 | I70: =IF(AND(ISNUMBER(E70),ISNUMBER(H70)),ROUND(E70*H70,2),"") -> 938.45 | J70: PL23_ESTIMATE | K70: 23 | L70: =IF(AND(J70="PL23_ESTIMATE",ISNUMBER(I70)),ROUND(I70*K70/100,2),"") -> 215.84 | N70: =IF(J70="SOURCE_GROSS",IF(AND(ISNUMBER(E70),ISNUMBER(M70)),ROUND(E70*M70,2),""),IF(ISNUMBER(I70),ROUND(I70+L70,2),"")) -> 1154.29 | O70: ПРЕДВАРИТЕЛЬНЫЙ СЦЕНАРИЙ M09: историческая spec-matrix: два топливных, два пресной воды, один сточный танк; наличие, глубины и пригодность датчиков ещё не проверены; не утверждённое количество закупки. | P70: Ультразвуковой аналоговый датчик; работа в конкретном танке и интерфейс подлежат проверке. Не цена танка. | Ультразвуковой аналоговый датчик; работа в конкретном танке и интерфейс подлежат проверке. Не цена танка. | Исключено: Исходные ограничения M03 сохранены | UNIT_BENCHMARK_TECH_OPEN | Q70: 2026-09-11 | R70: https://www.vetus-shop.com/vetus-fuel-tank-quickfit-diesel-40-litre-8mm-p-1786.html | S70: ДА
A71: PK11-B | B71: PK11-B-L02 | C71: ME-25 | D71: Jabsco Type 12GPM waste water pump / 24 V | E71: 1 | F71: шт | G71: AX06 | H71: 210.04 | I71: =IF(AND(ISNUMBER(E71),ISNUMBER(H71)),ROUND(E71*H71,2),"") -> 210.04 | J71: PL23_ESTIMATE | K71: 23 | L71: =IF(AND(J71="PL23_ESTIMATE",ISNUMBER(I71)),ROUND(I71*K71/100,2),"") -> 48.31 | N71: =IF(J71="SOURCE_GROSS",IF(AND(ISNUMBER(E71),ISNUMBER(M71)),ROUND(E71*M71,2),""),IF(ISNUMBER(I71),ROUND(I71+L71,2),"")) -> 258.35 | O71: ПРЕДВАРИТЕЛЬНЫЙ СЦЕНАРИЙ M09: один компонент соответствующей функции; состав и производительность уточняются; не утверждённое количество закупки. | P71: Подстановка M09 вместо A19. Прежнее описание относится к старому SKU и сохранено в M03. | Насос macerator. | Исключено: Санприборы, танки, трубопроводы, арматура, управление, монтаж. | 24 V. Проверить отсутствие повторного счёта насоса, включённого в сансистему; схема и допустимый сброс открыты. | Q71: 2026-09-15 | R71: https://www.svb24.com/en/jabsco-type-12gpm-waste-water-pump-24v.html | S71: ДА
A72: PK11-C | B72: PK11-C-L01 | C72: ME-24 | D72: Vetus SENSORA | E72: 5 | F72: шт | G72: A18 | H72: 187.69 | I72: =IF(AND(ISNUMBER(E72),ISNUMBER(H72)),ROUND(E72*H72,2),"") -> 938.45 | J72: PL23_ESTIMATE | K72: 23 | L72: =IF(AND(J72="PL23_ESTIMATE",ISNUMBER(I72)),ROUND(I72*K72/100,2),"") -> 215.84 | N72: =IF(J72="SOURCE_GROSS",IF(AND(ISNUMBER(E72),ISNUMBER(M72)),ROUND(E72*M72,2),""),IF(ISNUMBER(I72),ROUND(I72+L72,2),"")) -> 1154.29 | O72: ПРЕДВАРИТЕЛЬНЫЙ СЦЕНАРИЙ M09: историческая spec-matrix: два топливных, два пресной воды, один сточный танк; наличие, глубины и пригодность датчиков ещё не проверены; не утверждённое количество закупки. | P72: Ультразвуковой аналоговый датчик; работа в конкретном танке и интерфейс подлежат проверке. Не цена танка. | Ультразвуковой аналоговый датчик; работа в конкретном танке и интерфейс подлежат проверке. Не цена танка. | Исключено: Исходные ограничения M03 сохранены | UNIT_BENCHMARK_TECH_OPEN | Q72: 2026-09-11 | R72: https://www.vetus-shop.com/vetus-fuel-tank-quickfit-diesel-40-litre-8mm-p-1786.html | S72: ДА
A73: PK11-C | B73: PK11-C-L02 | C73: ME-25 | D73: Jabsco Type 12GPM waste water pump / 24 V | E73: 1 | F73: шт | G73: AX06 | H73: 210.04 | I73: =IF(AND(ISNUMBER(E73),ISNUMBER(H73)),ROUND(E73*H73,2),"") -> 210.04 | J73: PL23_ESTIMATE | K73: 23 | L73: =IF(AND(J73="PL23_ESTIMATE",ISNUMBER(I73)),ROUND(I73*K73/100,2),"") -> 48.31 | N73: =IF(J73="SOURCE_GROSS",IF(AND(ISNUMBER(E73),ISNUMBER(M73)),ROUND(E73*M73,2),""),IF(ISNUMBER(I73),ROUND(I73+L73,2),"")) -> 258.35 | O73: ПРЕДВАРИТЕЛЬНЫЙ СЦЕНАРИЙ M09: один компонент соответствующей функции; состав и производительность уточняются; не утверждённое количество закупки. | P73: Подстановка M09 вместо A19. Прежнее описание относится к старому SKU и сохранено в M03. | Насос macerator. | Исключено: Санприборы, танки, трубопроводы, арматура, управление, монтаж. | 24 V. Проверить отсутствие повторного счёта насоса, включённого в сансистему; схема и допустимый сброс открыты. | Q73: 2026-09-15 | R73: https://www.svb24.com/en/jabsco-type-12gpm-waste-water-pump-24v.html | S73: ДА
A74: PK01-A | B74: M09-SHAFT-A | C74: ME-03 | D74: PSS уплотнениевала50мм | E74: 1 | F74: шт | G74: M09-M-17 | H74: 647.02 | I74: =IF(AND(ISNUMBER(E74),ISNUMBER(H74)),ROUND(E74*H74,2),"") -> 647.02 | J74: PL23_ESTIMATE | K74: 23 | L74: =IF(AND(J74="PL23_ESTIMATE",ISNUMBER(I74)),ROUND(I74*K74/100,2),"") -> 148.81 | N74: =IF(J74="SOURCE_GROSS",IF(AND(ISNUMBER(E74),ISNUMBER(M74)),ROUND(E74*M74,2),""),IF(ISNUMBER(I74),ROUND(I74+L74,2),"")) -> 795.83 | O74: ПРЕДВАРИТЕЛЬНЫЙ СЦЕНАРИЙ M09: одна валовая линия, 50 мм только ценовой типоразмер | P74: Уплотнение не включает вал, муфту, упорный узел, кронштейны и выверку. Диаметр и допустимый режим открыты. | УплотнениеPSSдлявала50мм,дейдвуд83–86мм | Исключено: Вал,дейдвуд,подача/вентиляцияводы,монтаж | Ценовойаналогдиаметра50мм,диаметрнеутверждён;геометриядейдвудаиусловияохлажденияOPEN.Одноуплотнениенаодинвалпредварительно. | Q74: 2026-09-15 | R74: https://www.svb24.com/en/pss-shaft-seal-for-50-mm-shaft.html | S74: ДА
A75: PK01-B | B75: M09-SHAFT-B | C75: ME-03 | D75: PSS уплотнениевала50мм | E75: 1 | F75: шт | G75: M09-M-17 | H75: 647.02 | I75: =IF(AND(ISNUMBER(E75),ISNUMBER(H75)),ROUND(E75*H75,2),"") -> 647.02 | J75: PL23_ESTIMATE | K75: 23 | L75: =IF(AND(J75="PL23_ESTIMATE",ISNUMBER(I75)),ROUND(I75*K75/100,2),"") -> 148.81 | N75: =IF(J75="SOURCE_GROSS",IF(AND(ISNUMBER(E75),ISNUMBER(M75)),ROUND(E75*M75,2),""),IF(ISNUMBER(I75),ROUND(I75+L75,2),"")) -> 795.83 | O75: ПРЕДВАРИТЕЛЬНЫЙ СЦЕНАРИЙ M09: одна валовая линия, 50 мм только ценовой типоразмер | P75: Уплотнение не включает вал, муфту, упорный узел, кронштейны и выверку. Диаметр и допустимый режим открыты. | УплотнениеPSSдлявала50мм,дейдвуд83–86мм | Исключено: Вал,дейдвуд,подача/вентиляцияводы,монтаж | Ценовойаналогдиаметра50мм,диаметрнеутверждён;геометриядейдвудаиусловияохлажденияOPEN.Одноуплотнениенаодинвалпредварительно. | Q75: 2026-09-15 | R75: https://www.svb24.com/en/pss-shaft-seal-for-50-mm-shaft.html | S75: ДА
A76: PK01-C | B76: M09-SHAFT-C | C76: ME-03 | D76: PSS уплотнениевала50мм | E76: 1 | F76: шт | G76: M09-M-17 | H76: 647.02 | I76: =IF(AND(ISNUMBER(E76),ISNUMBER(H76)),ROUND(E76*H76,2),"") -> 647.02 | J76: PL23_ESTIMATE | K76: 23 | L76: =IF(AND(J76="PL23_ESTIMATE",ISNUMBER(I76)),ROUND(I76*K76/100,2),"") -> 148.81 | N76: =IF(J76="SOURCE_GROSS",IF(AND(ISNUMBER(E76),ISNUMBER(M76)),ROUND(E76*M76,2),""),IF(ISNUMBER(I76),ROUND(I76+L76,2),"")) -> 795.83 | O76: ПРЕДВАРИТЕЛЬНЫЙ СЦЕНАРИЙ M09: одна валовая линия, 50 мм только ценовой типоразмер | P76: Уплотнение не включает вал, муфту, упорный узел, кронштейны и выверку. Диаметр и допустимый режим открыты. | УплотнениеPSSдлявала50мм,дейдвуд83–86мм | Исключено: Вал,дейдвуд,подача/вентиляцияводы,монтаж | Ценовойаналогдиаметра50мм,диаметрнеутверждён;геометриядейдвудаиусловияохлажденияOPEN.Одноуплотнениенаодинвалпредварительно. | Q76: 2026-09-15 | R76: https://www.svb24.com/en/pss-shaft-seal-for-50-mm-shaft.html | S76: ДА
A77: PK03-A | B77: M09-WATER-INV-A | C77: ME-06 | D77: Victron Phoenix 24/1200 VE.Direct Schuko | E77: 1 | F77: pcs | G77: EL-01 | I77: =IF(AND(ISNUMBER(E77),ISNUMBER(H77)),ROUND(E77*H77,2),"") | J77: SOURCE_GROSS | L77: =IF(AND(J77="PL23_ESTIMATE",ISNUMBER(I77)),ROUND(I77*K77/100,2),"") | M77: 274.5 | N77: =IF(J77="SOURCE_GROSS",IF(AND(ISNUMBER(E77),ISNUMBER(M77)),ROUND(E77*M77,2),""),IF(ISNUMBER(I77),ROUND(I77+L77,2),"")) -> 274.5 | O77: ПРЕДВАРИТЕЛЬНЫЙ СЦЕНАРИЙ M09: один независимый канал AC питания воды | P77: Пусковой ток насоса и независимость канала не проверены. Gross без выделения налога. Доставка продавца в Польшу не подтверждена. | Один инвертор 24 VDC / 230 VAC. | Исключено: Кабели, защита, переключение, монтаж; не включает насос. CGV: обычная доставка FR/BE; Польша по отдельному согласованию, расходы неизвестны. | Условный класс 1200 VA, пуск выбранного насоса не проверен. Отдельный канал не заменяет два основных инвертора. | Q77: 2026-09-15 | R77: https://www.mon-camping-car.com/convertisseur-24v-230v-phoenix-1200va-ve-direct-pur-sinus-victron.html | S77: ДА
A78: PK03-B | B78: M09-WATER-INV-B | C78: ME-06 | D78: Victron Phoenix 24/1200 VE.Direct Schuko | E78: 1 | F78: pcs | G78: EL-01 | I78: =IF(AND(ISNUMBER(E78),ISNUMBER(H78)),ROUND(E78*H78,2),"") | J78: SOURCE_GROSS | L78: =IF(AND(J78="PL23_ESTIMATE",ISNUMBER(I78)),ROUND(I78*K78/100,2),"") | M78: 274.5 | N78: =IF(J78="SOURCE_GROSS",IF(AND(ISNUMBER(E78),ISNUMBER(M78)),ROUND(E78*M78,2),""),IF(ISNUMBER(I78),ROUND(I78+L78,2),"")) -> 274.5 | O78: ПРЕДВАРИТЕЛЬНЫЙ СЦЕНАРИЙ M09: один независимый канал AC питания воды | P78: Пусковой ток насоса и независимость канала не проверены. Gross без выделения налога. Доставка продавца в Польшу не подтверждена. | Один инвертор 24 VDC / 230 VAC. | Исключено: Кабели, защита, переключение, монтаж; не включает насос. CGV: обычная доставка FR/BE; Польша по отдельному согласованию, расходы неизвестны. | Условный класс 1200 VA, пуск выбранного насоса не проверен. Отдельный канал не заменяет два основных инвертора. | Q78: 2026-09-15 | R78: https://www.mon-camping-car.com/convertisseur-24v-230v-phoenix-1200va-ve-direct-pur-sinus-victron.html | S78: ДА
A79: PK03-C | B79: M09-WATER-INV-C | C79: ME-06 | D79: Victron Phoenix 24/1200 VE.Direct Schuko | E79: 1 | F79: pcs | G79: EL-01 | I79: =IF(AND(ISNUMBER(E79),ISNUMBER(H79)),ROUND(E79*H79,2),"") | J79: SOURCE_GROSS | L79: =IF(AND(J79="PL23_ESTIMATE",ISNUMBER(I79)),ROUND(I79*K79/100,2),"") | M79: 274.5 | N79: =IF(J79="SOURCE_GROSS",IF(AND(ISNUMBER(E79),ISNUMBER(M79)),ROUND(E79*M79,2),""),IF(ISNUMBER(I79),ROUND(I79+L79,2),"")) -> 274.5 | O79: ПРЕДВАРИТЕЛЬНЫЙ СЦЕНАРИЙ M09: один независимый канал AC питания воды | P79: Пусковой ток насоса и независимость канала не проверены. Gross без выделения налога. Доставка продавца в Польшу не подтверждена. | Один инвертор 24 VDC / 230 VAC. | Исключено: Кабели, защита, переключение, монтаж; не включает насос. CGV: обычная доставка FR/BE; Польша по отдельному согласованию, расходы неизвестны. | Условный класс 1200 VA, пуск выбранного насоса не проверен. Отдельный канал не заменяет два основных инвертора. | Q79: 2026-09-15 | R79: https://www.mon-camping-car.com/convertisseur-24v-230v-phoenix-1200va-ve-direct-pur-sinus-victron.html | S79: ДА
A80: PK03-A | B80: M09-DC-PANEL-A | C80: ME-10 | D80: Philippi STV207 DC distribution panel | E80: 1 | F80: pcs | G80: EL-06 | H80: 214.24 | I80: =IF(AND(ISNUMBER(E80),ISNUMBER(H80)),ROUND(E80*H80,2),"") -> 214.24 | J80: PL23_ESTIMATE | K80: 23 | L80: =IF(AND(J80="PL23_ESTIMATE",ISNUMBER(I80)),ROUND(I80*K80/100,2),"") -> 49.28 | N80: =IF(J80="SOURCE_GROSS",IF(AND(ISNUMBER(E80),ISNUMBER(M80)),ROUND(E80*M80,2),""),IF(ISNUMBER(I80),ROUND(I80+L80,2),"")) -> 263.52 | O80: ПРЕДВАРИТЕЛЬНЫЙ СЦЕНАРИЙ M09: один образец распределительного DC щита | P80: Ценовая часть щита 24 V; число цепей и весь состав не определены. | 7 переключателей и тепловых автоматов, стандартно 10 A. | Исключено: Остальные цепи, силовые шины, кабели, общий шкаф и монтаж. | 12/24 V аппарат применим как кандидат для 24 V DC. Число цепей/номиналы по схеме; не весь DC щит яхты. | Q80: 2026-09-15 | R80: https://www.svb24.com/en/philippi-stv207-power-distribution-panel-configurable.html | S80: ДА
A81: PK03-B | B81: M09-DC-PANEL-B | C81: ME-10 | D81: Philippi STV207 DC distribution panel | E81: 1 | F81: pcs | G81: EL-06 | H81: 214.24 | I81: =IF(AND(ISNUMBER(E81),ISNUMBER(H81)),ROUND(E81*H81,2),"") -> 214.24 | J81: PL23_ESTIMATE | K81: 23 | L81: =IF(AND(J81="PL23_ESTIMATE",ISNUMBER(I81)),ROUND(I81*K81/100,2),"") -> 49.28 | N81: =IF(J81="SOURCE_GROSS",IF(AND(ISNUMBER(E81),ISNUMBER(M81)),ROUND(E81*M81,2),""),IF(ISNUMBER(I81),ROUND(I81+L81,2),"")) -> 263.52 | O81: ПРЕДВАРИТЕЛЬНЫЙ СЦЕНАРИЙ M09: один образец распределительного DC щита | P81: Ценовая часть щита 24 V; число цепей и весь состав не определены. | 7 переключателей и тепловых автоматов, стандартно 10 A. | Исключено: Остальные цепи, силовые шины, кабели, общий шкаф и монтаж. | 12/24 V аппарат применим как кандидат для 24 V DC. Число цепей/номиналы по схеме; не весь DC щит яхты. | Q81: 2026-09-15 | R81: https://www.svb24.com/en/philippi-stv207-power-distribution-panel-configurable.html | S81: ДА
A82: PK03-C | B82: M09-DC-PANEL-C | C82: ME-10 | D82: Philippi STV207 DC distribution panel | E82: 1 | F82: pcs | G82: EL-06 | H82: 214.24 | I82: =IF(AND(ISNUMBER(E82),ISNUMBER(H82)),ROUND(E82*H82,2),"") -> 214.24 | J82: PL23_ESTIMATE | K82: 23 | L82: =IF(AND(J82="PL23_ESTIMATE",ISNUMBER(I82)),ROUND(I82*K82/100,2),"") -> 49.28 | N82: =IF(J82="SOURCE_GROSS",IF(AND(ISNUMBER(E82),ISNUMBER(M82)),ROUND(E82*M82,2),""),IF(ISNUMBER(I82),ROUND(I82+L82,2),"")) -> 263.52 | O82: ПРЕДВАРИТЕЛЬНЫЙ СЦЕНАРИЙ M09: один образец распределительного DC щита | P82: Ценовая часть щита 24 V; число цепей и весь состав не определены. | 7 переключателей и тепловых автоматов, стандартно 10 A. | Исключено: Остальные цепи, силовые шины, кабели, общий шкаф и монтаж. | 12/24 V аппарат применим как кандидат для 24 V DC. Число цепей/номиналы по схеме; не весь DC щит яхты. | Q82: 2026-09-15 | R82: https://www.svb24.com/en/philippi-stv207-power-distribution-panel-configurable.html | S82: ДА
A83: PK03-A | B83: M09-AC-PANEL-A | C83: ME-10 | D83: Philippi LAE113 shore connection unit | E83: 1 | F83: pcs | G83: EL-07 | H83: 331.89 | I83: =IF(AND(ISNUMBER(E83),ISNUMBER(H83)),ROUND(E83*H83,2),"") -> 331.89 | J83: PL23_ESTIMATE | K83: 23 | L83: =IF(AND(J83="PL23_ESTIMATE",ISNUMBER(I83)),ROUND(I83*K83/100,2),"") -> 76.33 | N83: =IF(J83="SOURCE_GROSS",IF(AND(ISNUMBER(E83),ISNUMBER(M83)),ROUND(E83*M83,2),""),IF(ISNUMBER(I83),ROUND(I83+L83,2),"")) -> 408.22 | O83: ПРЕДВАРИТЕЛЬНЫЙ СЦЕНАРИЙ M09: один береговой AC ввод с защитой | P83: Не весь щит AC и не переключение двух генераторов/инверторов/берега. | Береговой блок 230 V: RCCB, главный выключатель, индикатор, розетка и две линии 10 A. | Исключено: Полное AC распределение, береговой ввод/шнур, переключение двух генераторов/инверторов. | Частичный AC блок, не законченный главный щит; не дублировать его встроенные автоматы отдельными строками. | Q83: 2026-09-15 | R83: https://www.svb24.com/en/philippi-lae-113-shore-connection-unit.html | S83: ДА
A84: PK03-B | B84: M09-AC-PANEL-B | C84: ME-10 | D84: Philippi LAE113 shore connection unit | E84: 1 | F84: pcs | G84: EL-07 | H84: 331.89 | I84: =IF(AND(ISNUMBER(E84),ISNUMBER(H84)),ROUND(E84*H84,2),"") -> 331.89 | J84: PL23_ESTIMATE | K84: 23 | L84: =IF(AND(J84="PL23_ESTIMATE",ISNUMBER(I84)),ROUND(I84*K84/100,2),"") -> 76.33 | N84: =IF(J84="SOURCE_GROSS",IF(AND(ISNUMBER(E84),ISNUMBER(M84)),ROUND(E84*M84,2),""),IF(ISNUMBER(I84),ROUND(I84+L84,2),"")) -> 408.22 | O84: ПРЕДВАРИТЕЛЬНЫЙ СЦЕНАРИЙ M09: один береговой AC ввод с защитой | P84: Не весь щит AC и не переключение двух генераторов/инверторов/берега. | Береговой блок 230 V: RCCB, главный выключатель, индикатор, розетка и две линии 10 A. | Исключено: Полное AC распределение, береговой ввод/шнур, переключение двух генераторов/инверторов. | Частичный AC блок, не законченный главный щит; не дублировать его встроенные автоматы отдельными строками. | Q84: 2026-09-15 | R84: https://www.svb24.com/en/philippi-lae-113-shore-connection-unit.html | S84: ДА
A85: PK03-C | B85: M09-AC-PANEL-C | C85: ME-10 | D85: Philippi LAE113 shore connection unit | E85: 1 | F85: pcs | G85: EL-07 | H85: 331.89 | I85: =IF(AND(ISNUMBER(E85),ISNUMBER(H85)),ROUND(E85*H85,2),"") -> 331.89 | J85: PL23_ESTIMATE | K85: 23 | L85: =IF(AND(J85="PL23_ESTIMATE",ISNUMBER(I85)),ROUND(I85*K85/100,2),"") -> 76.33 | N85: =IF(J85="SOURCE_GROSS",IF(AND(ISNUMBER(E85),ISNUMBER(M85)),ROUND(E85*M85,2),""),IF(ISNUMBER(I85),ROUND(I85+L85,2),"")) -> 408.22 | O85: ПРЕДВАРИТЕЛЬНЫЙ СЦЕНАРИЙ M09: один береговой AC ввод с защитой | P85: Не весь щит AC и не переключение двух генераторов/инверторов/берега. | Береговой блок 230 V: RCCB, главный выключатель, индикатор, розетка и две линии 10 A. | Исключено: Полное AC распределение, береговой ввод/шнур, переключение двух генераторов/инверторов. | Частичный AC блок, не законченный главный щит; не дублировать его встроенные автоматы отдельными строками. | Q85: 2026-09-15 | R85: https://www.svb24.com/en/philippi-lae-113-shore-connection-unit.html | S85: ДА
A86: PK03-A | B86: M09-SHORE-IN-A | C86: ME-09 | D86: CEE Shore Power Inlet 16 A 230 V male | E86: 1 | F86: pcs | G86: EL-11 | H86: 13.4 | I86: =IF(AND(ISNUMBER(E86),ISNUMBER(H86)),ROUND(E86*H86,2),"") -> 13.4 | J86: PL23_ESTIMATE | K86: 23 | L86: =IF(AND(J86="PL23_ESTIMATE",ISNUMBER(I86)),ROUND(I86*K86/100,2),"") -> 3.08 | N86: =IF(J86="SOURCE_GROSS",IF(AND(ISNUMBER(E86),ISNUMBER(M86)),ROUND(E86*M86,2),""),IF(ISNUMBER(I86),ROUND(I86+L86,2),"")) -> 16.48 | O86: ПРЕДВАРИТЕЛЬНЫЙ СЦЕНАРИЙ M09: один береговой разъём 16 A | P86: Ток и количество вводов уточняются; разъём не дублирует защитный блок. | Один береговой ввод, без кабеля и распределения. | Исключено: Кабели, держатель/сопряжённые детали, схема, монтаж и остальная система. | 16 A — условный ценовой класс; требуемая береговая мощность неизвестна. | Q86: 2026-09-15 | R86: https://www.svb24.com/en/cee-shore-power-inlet-16-a-230-v-male.html | S86: ДА
A87: PK03-B | B87: M09-SHORE-IN-B | C87: ME-09 | D87: CEE Shore Power Inlet 16 A 230 V male | E87: 1 | F87: pcs | G87: EL-11 | H87: 13.4 | I87: =IF(AND(ISNUMBER(E87),ISNUMBER(H87)),ROUND(E87*H87,2),"") -> 13.4 | J87: PL23_ESTIMATE | K87: 23 | L87: =IF(AND(J87="PL23_ESTIMATE",ISNUMBER(I87)),ROUND(I87*K87/100,2),"") -> 3.08 | N87: =IF(J87="SOURCE_GROSS",IF(AND(ISNUMBER(E87),ISNUMBER(M87)),ROUND(E87*M87,2),""),IF(ISNUMBER(I87),ROUND(I87+L87,2),"")) -> 16.48 | O87: ПРЕДВАРИТЕЛЬНЫЙ СЦЕНАРИЙ M09: один береговой разъём 16 A | P87: Ток и количество вводов уточняются; разъём не дублирует защитный блок. | Один береговой ввод, без кабеля и распределения. | Исключено: Кабели, держатель/сопряжённые детали, схема, монтаж и остальная система. | 16 A — условный ценовой класс; требуемая береговая мощность неизвестна. | Q87: 2026-09-15 | R87: https://www.svb24.com/en/cee-shore-power-inlet-16-a-230-v-male.html | S87: ДА
A88: PK03-C | B88: M09-SHORE-IN-C | C88: ME-09 | D88: CEE Shore Power Inlet 16 A 230 V male | E88: 1 | F88: pcs | G88: EL-11 | H88: 13.4 | I88: =IF(AND(ISNUMBER(E88),ISNUMBER(H88)),ROUND(E88*H88,2),"") -> 13.4 | J88: PL23_ESTIMATE | K88: 23 | L88: =IF(AND(J88="PL23_ESTIMATE",ISNUMBER(I88)),ROUND(I88*K88/100,2),"") -> 3.08 | N88: =IF(J88="SOURCE_GROSS",IF(AND(ISNUMBER(E88),ISNUMBER(M88)),ROUND(E88*M88,2),""),IF(ISNUMBER(I88),ROUND(I88+L88,2),"")) -> 16.48 | O88: ПРЕДВАРИТЕЛЬНЫЙ СЦЕНАРИЙ M09: один береговой разъём 16 A | P88: Ток и количество вводов уточняются; разъём не дублирует защитный блок. | Один береговой ввод, без кабеля и распределения. | Исключено: Кабели, держатель/сопряжённые детали, схема, монтаж и остальная система. | 16 A — условный ценовой класс; требуемая береговая мощность неизвестна. | Q88: 2026-09-15 | R88: https://www.svb24.com/en/cee-shore-power-inlet-16-a-230-v-male.html | S88: ДА
A89: PK03-A | B89: M09-FUSE-HOLDER-A | C89: ME-10 | D89: MEGA fuse holder in-line | F89: pcs | G89: EL-08 | H89: 10.04 | I89: =IF(AND(ISNUMBER(E89),ISNUMBER(H89)),ROUND(E89*H89,2),"") | J89: PL23_ESTIMATE | K89: 23 | L89: =IF(AND(J89="PL23_ESTIMATE",ISNUMBER(I89)),ROUND(I89*K89/100,2),"") | N89: =IF(J89="SOURCE_GROSS",IF(AND(ISNUMBER(E89),ISNUMBER(M89)),ROUND(E89*M89,2),""),IF(ISNUMBER(I89),ROUND(I89+L89,2),"")) | O89: ПРЕДВАРИТЕЛЬНЫЙ СЦЕНАРИЙ M09: количество определится схемой цепей | P89: Цена за один держатель, не вся силовая защита. | Один держатель MEGA. | Исключено: Предохранитель, наконечники, кабели, коробка, монтаж. | 24 V кандидат; сечение, отключающая способность и ток выбранного предохранителя открыты. | Q89: 2026-09-15 | R89: https://www.svb24.com/en/mega-fuse-holder-in-line.html | S89: ДА
A90: PK03-B | B90: M09-FUSE-HOLDER-B | C90: ME-10 | D90: MEGA fuse holder in-line | F90: pcs | G90: EL-08 | H90: 10.04 | I90: =IF(AND(ISNUMBER(E90),ISNUMBER(H90)),ROUND(E90*H90,2),"") | J90: PL23_ESTIMATE | K90: 23 | L90: =IF(AND(J90="PL23_ESTIMATE",ISNUMBER(I90)),ROUND(I90*K90/100,2),"") | N90: =IF(J90="SOURCE_GROSS",IF(AND(ISNUMBER(E90),ISNUMBER(M90)),ROUND(E90*M90,2),""),IF(ISNUMBER(I90),ROUND(I90+L90,2),"")) | O90: ПРЕДВАРИТЕЛЬНЫЙ СЦЕНАРИЙ M09: количество определится схемой цепей | P90: Цена за один держатель, не вся силовая защита. | Один держатель MEGA. | Исключено: Предохранитель, наконечники, кабели, коробка, монтаж. | 24 V кандидат; сечение, отключающая способность и ток выбранного предохранителя открыты. | Q90: 2026-09-15 | R90: https://www.svb24.com/en/mega-fuse-holder-in-line.html | S90: ДА
A91: PK03-C | B91: M09-FUSE-HOLDER-C | C91: ME-10 | D91: MEGA fuse holder in-line | F91: pcs | G91: EL-08 | H91: 10.04 | I91: =IF(AND(ISNUMBER(E91),ISNUMBER(H91)),ROUND(E91*H91,2),"") | J91: PL23_ESTIMATE | K91: 23 | L91: =IF(AND(J91="PL23_ESTIMATE",ISNUMBER(I91)),ROUND(I91*K91/100,2),"") | N91: =IF(J91="SOURCE_GROSS",IF(AND(ISNUMBER(E91),ISNUMBER(M91)),ROUND(E91*M91,2),""),IF(ISNUMBER(I91),ROUND(I91+L91,2),"")) | O91: ПРЕДВАРИТЕЛЬНЫЙ СЦЕНАРИЙ M09: количество определится схемой цепей | P91: Цена за один держатель, не вся силовая защита. | Один держатель MEGA. | Исключено: Предохранитель, наконечники, кабели, коробка, монтаж. | 24 V кандидат; сечение, отключающая способность и ток выбранного предохранителя открыты. | Q91: 2026-09-15 | R91: https://www.svb24.com/en/mega-fuse-holder-in-line.html | S91: ДА
A92: PK03-A | B92: M09-FUSE-PACK-A | C92: ME-10 | D92: MEGA fuse 60 A, pack of 5 | F92: pack_5 | G92: EL-12 | H92: 15.92 | I92: =IF(AND(ISNUMBER(E92),ISNUMBER(H92)),ROUND(E92*H92,2),"") | J92: PL23_ESTIMATE | K92: 23 | L92: =IF(AND(J92="PL23_ESTIMATE",ISNUMBER(I92)),ROUND(I92*K92/100,2),"") | N92: =IF(J92="SOURCE_GROSS",IF(AND(ISNUMBER(E92),ISNUMBER(M92)),ROUND(E92*M92,2),""),IF(ISNUMBER(I92),ROUND(I92+L92,2),"")) | O92: ПРЕДВАРИТЕЛЬНЫЙ СЦЕНАРИЙ M09: количество упаковок и номиналы открыты | P92: Цена за упаковку из 5 предохранителей 60 A; не считать упаковку одним предохранителем. | Упаковка из пяти предохранителей. | Исключено: Кабели, держатель/сопряжённые детали, схема, монтаж и остальная система. | 60 A — только ценовой ориентир, не назначение защиты пусковой/инверторной линии; требуется расчёт тока и отключающей способности. | Q92: 2026-09-15 | R92: https://www.svb24.com/en/mega-fuses-pack-of-5.html | S92: ДА
A93: PK03-B | B93: M09-FUSE-PACK-B | C93: ME-10 | D93: MEGA fuse 60 A, pack of 5 | F93: pack_5 | G93: EL-12 | H93: 15.92 | I93: =IF(AND(ISNUMBER(E93),ISNUMBER(H93)),ROUND(E93*H93,2),"") | J93: PL23_ESTIMATE | K93: 23 | L93: =IF(AND(J93="PL23_ESTIMATE",ISNUMBER(I93)),ROUND(I93*K93/100,2),"") | N93: =IF(J93="SOURCE_GROSS",IF(AND(ISNUMBER(E93),ISNUMBER(M93)),ROUND(E93*M93,2),""),IF(ISNUMBER(I93),ROUND(I93+L93,2),"")) | O93: ПРЕДВАРИТЕЛЬНЫЙ СЦЕНАРИЙ M09: количество упаковок и номиналы открыты | P93: Цена за упаковку из 5 предохранителей 60 A; не считать упаковку одним предохранителем. | Упаковка из пяти предохранителей. | Исключено: Кабели, держатель/сопряжённые детали, схема, монтаж и остальная система. | 60 A — только ценовой ориентир, не назначение защиты пусковой/инверторной линии; требуется расчёт тока и отключающей способности. | Q93: 2026-09-15 | R93: https://www.svb24.com/en/mega-fuses-pack-of-5.html | S93: ДА
A94: PK03-C | B94: M09-FUSE-PACK-C | C94: ME-10 | D94: MEGA fuse 60 A, pack of 5 | F94: pack_5 | G94: EL-12 | H94: 15.92 | I94: =IF(AND(ISNUMBER(E94),ISNUMBER(H94)),ROUND(E94*H94,2),"") | J94: PL23_ESTIMATE | K94: 23 | L94: =IF(AND(J94="PL23_ESTIMATE",ISNUMBER(I94)),ROUND(I94*K94/100,2),"") | N94: =IF(J94="SOURCE_GROSS",IF(AND(ISNUMBER(E94),ISNUMBER(M94)),ROUND(E94*M94,2),""),IF(ISNUMBER(I94),ROUND(I94+L94,2),"")) | O94: ПРЕДВАРИТЕЛЬНЫЙ СЦЕНАРИЙ M09: количество упаковок и номиналы открыты | P94: Цена за упаковку из 5 предохранителей 60 A; не считать упаковку одним предохранителем. | Упаковка из пяти предохранителей. | Исключено: Кабели, держатель/сопряжённые детали, схема, монтаж и остальная система. | 60 A — только ценовой ориентир, не назначение защиты пусковой/инверторной линии; требуется расчёт тока и отключающей способности. | Q94: 2026-09-15 | R94: https://www.svb24.com/en/mega-fuses-pack-of-5.html | S94: ДА
A95: PK05-A | B95: M09-MIX-A | C95: ME-17 | D95: Смесительный термоклапан | E95: 1 | F95: шт | G95: M09-M-06 | H95: 92.4 | I95: =IF(AND(ISNUMBER(E95),ISNUMBER(H95)),ROUND(E95*H95,2),"") -> 92.4 | J95: PL23_ESTIMATE | K95: 23 | L95: =IF(AND(J95="PL23_ESTIMATE",ISNUMBER(I95)),ROUND(I95*K95/100,2),"") -> 21.25 | N95: =IF(J95="SOURCE_GROSS",IF(AND(ISNUMBER(E95),ISNUMBER(M95)),ROUND(E95*M95,2),""),IF(ISNUMBER(I95),ROUND(I95+L95,2),"")) -> 113.65 | O95: ПРЕДВАРИТЕЛЬНЫЙ СЦЕНАРИЙ M09: один смесительный клапан ГВС | P95: Условный состав с Quick; исключить, если клапан уже входит в выбранный бойлер. | Клапан1/2дюйма дляQuickNAUTIC/B3 и ATI | Исключено: Принадлежности на фото не включены; фитинги и монтаж | Вариант кQuick; не добавлять кбойлеру с уже включённым смесителем. | Q95: 2026-09-15 | R95: https://www.svb24.com/en/p/thermostat-mixing-valve.html | S95: ДА
A96: PK05-B | B96: M09-MIX-B | C96: ME-17 | D96: Смесительный термоклапан | E96: 1 | F96: шт | G96: M09-M-06 | H96: 92.4 | I96: =IF(AND(ISNUMBER(E96),ISNUMBER(H96)),ROUND(E96*H96,2),"") -> 92.4 | J96: PL23_ESTIMATE | K96: 23 | L96: =IF(AND(J96="PL23_ESTIMATE",ISNUMBER(I96)),ROUND(I96*K96/100,2),"") -> 21.25 | N96: =IF(J96="SOURCE_GROSS",IF(AND(ISNUMBER(E96),ISNUMBER(M96)),ROUND(E96*M96,2),""),IF(ISNUMBER(I96),ROUND(I96+L96,2),"")) -> 113.65 | O96: ПРЕДВАРИТЕЛЬНЫЙ СЦЕНАРИЙ M09: один смесительный клапан ГВС | P96: Условный состав с Quick; исключить, если клапан уже входит в выбранный бойлер. | Клапан1/2дюйма дляQuickNAUTIC/B3 и ATI | Исключено: Принадлежности на фото не включены; фитинги и монтаж | Вариант кQuick; не добавлять кбойлеру с уже включённым смесителем. | Q96: 2026-09-15 | R96: https://www.svb24.com/en/p/thermostat-mixing-valve.html | S96: ДА
A97: PK05-C | B97: M09-MIX-C | C97: ME-17 | D97: Смесительный термоклапан | E97: 1 | F97: шт | G97: M09-M-06 | H97: 92.4 | I97: =IF(AND(ISNUMBER(E97),ISNUMBER(H97)),ROUND(E97*H97,2),"") -> 92.4 | J97: PL23_ESTIMATE | K97: 23 | L97: =IF(AND(J97="PL23_ESTIMATE",ISNUMBER(I97)),ROUND(I97*K97/100,2),"") -> 21.25 | N97: =IF(J97="SOURCE_GROSS",IF(AND(ISNUMBER(E97),ISNUMBER(M97)),ROUND(E97*M97,2),""),IF(ISNUMBER(I97),ROUND(I97+L97,2),"")) -> 113.65 | O97: ПРЕДВАРИТЕЛЬНЫЙ СЦЕНАРИЙ M09: один смесительный клапан ГВС | P97: Условный состав с Quick; исключить, если клапан уже входит в выбранный бойлер. | Клапан1/2дюйма дляQuickNAUTIC/B3 и ATI | Исключено: Принадлежности на фото не включены; фитинги и монтаж | Вариант кQuick; не добавлять кбойлеру с уже включённым смесителем. | Q97: 2026-09-15 | R97: https://www.svb24.com/en/p/thermostat-mixing-valve.html | S97: ДА
A98: PK05-A | B98: M09-WATER-FILTER-A | C98: ME-17 | D98: Угольный проточный фильтр | E98: 1 | F98: шт | G98: M09-M-08 | H98: 10.88 | I98: =IF(AND(ISNUMBER(E98),ISNUMBER(H98)),ROUND(E98*H98,2),"") -> 10.88 | J98: PL23_ESTIMATE | K98: 23 | L98: =IF(AND(J98="PL23_ESTIMATE",ISNUMBER(I98)),ROUND(I98*K98/100,2),"") -> 2.5 | N98: =IF(J98="SOURCE_GROSS",IF(AND(ISNUMBER(E98),ISNUMBER(M98)),ROUND(E98*M98,2),""),IF(ISNUMBER(I98),ROUND(I98+L98,2),"")) -> 13.38 | O98: ПРЕДВАРИТЕЛЬНЫЙ СЦЕНАРИЙ M09: один фильтр отдельной точки/заполнения; магистральная фильтрация OPEN | P98: До 200 л/ч (3.33 л/мин), не общий магистральный фильтр для рабочей точки 15 л/мин; полная фильтрация требует подбора. | Одноразовый угольный фильтр1/4дюйма,7000лпаспортныйресурс | Исключено: Штуцеры,дезинфекция,контролькачества,монтаж | 200л/чмаксимум,8бар;для точки/заполнениябака.Необещаетмикробиологическибезопаснуюводу;не универсальныйполносудовойфильтр. | Q98: 2026-09-15 | R98: https://www.svb24.com/product/510125?filter=4 | S98: ДА
A99: PK05-B | B99: M09-WATER-FILTER-B | C99: ME-17 | D99: Угольный проточный фильтр | E99: 1 | F99: шт | G99: M09-M-08 | H99: 10.88 | I99: =IF(AND(ISNUMBER(E99),ISNUMBER(H99)),ROUND(E99*H99,2),"") -> 10.88 | J99: PL23_ESTIMATE | K99: 23 | L99: =IF(AND(J99="PL23_ESTIMATE",ISNUMBER(I99)),ROUND(I99*K99/100,2),"") -> 2.5 | N99: =IF(J99="SOURCE_GROSS",IF(AND(ISNUMBER(E99),ISNUMBER(M99)),ROUND(E99*M99,2),""),IF(ISNUMBER(I99),ROUND(I99+L99,2),"")) -> 13.38 | O99: ПРЕДВАРИТЕЛЬНЫЙ СЦЕНАРИЙ M09: один фильтр отдельной точки/заполнения; магистральная фильтрация OPEN | P99: До 200 л/ч (3.33 л/мин), не общий магистральный фильтр для рабочей точки 15 л/мин; полная фильтрация требует подбора. | Одноразовый угольный фильтр1/4дюйма,7000лпаспортныйресурс | Исключено: Штуцеры,дезинфекция,контролькачества,монтаж | 200л/чмаксимум,8бар;для точки/заполнениябака.Необещаетмикробиологическибезопаснуюводу;не универсальныйполносудовойфильтр. | Q99: 2026-09-15 | R99: https://www.svb24.com/product/510125?filter=4 | S99: ДА
A100: PK05-C | B100: M09-WATER-FILTER-C | C100: ME-17 | D100: Угольный проточный фильтр | E100: 1 | F100: шт | G100: M09-M-08 | H100: 10.88 | I100: =IF(AND(ISNUMBER(E100),ISNUMBER(H100)),ROUND(E100*H100,2),"") -> 10.88 | J100: PL23_ESTIMATE | K100: 23 | L100: =IF(AND(J100="PL23_ESTIMATE",ISNUMBER(I100)),ROUND(I100*K100/100,2),"") -> 2.5 | N100: =IF(J100="SOURCE_GROSS",IF(AND(ISNUMBER(E100),ISNUMBER(M100)),ROUND(E100*M100,2),""),IF(ISNUMBER(I100),ROUND(I100+L100,2),"")) -> 13.38 | O100: ПРЕДВАРИТЕЛЬНЫЙ СЦЕНАРИЙ M09: один фильтр отдельной точки/заполнения; магистральная фильтрация OPEN | P100: До 200 л/ч (3.33 л/мин), не общий магистральный фильтр для рабочей точки 15 л/мин; полная фильтрация требует подбора. | Одноразовый угольный фильтр1/4дюйма,7000лпаспортныйресурс | Исключено: Штуцеры,дезинфекция,контролькачества,монтаж | 200л/чмаксимум,8бар;для точки/заполнениябака.Необещаетмикробиологическибезопаснуюводу;не универсальныйполносудовойфильтр. | Q100: 2026-09-15 | R100: https://www.svb24.com/product/510125?filter=4 | S100: ДА
A101: PK05-A | B101: M09-RECIRC-A | C101: ME-17 | D101: Jabsco Ecocirc горячая вода8–24V | E101: 1 | F101: шт | G101: M09-M-12 | H101: 407.42 | I101: =IF(AND(ISNUMBER(E101),ISNUMBER(H101)),ROUND(E101*H101,2),"") -> 407.42 | J101: PL23_ESTIMATE | K101: 23 | L101: =IF(AND(J101="PL23_ESTIMATE",ISNUMBER(I101)),ROUND(I101*K101/100,2),"") -> 93.71 | N101: =IF(J101="SOURCE_GROSS",IF(AND(ISNUMBER(E101),ISNUMBER(M101)),ROUND(E101*M101,2),""),IF(ISNUMBER(I101),ROUND(I101+L101,2),"")) -> 501.13 | O101: ПРЕДВАРИТЕЛЬНЫЙ СЦЕНАРИЙ M09: один насос рециркуляции ГВС | P101: Включён только насос; контур и управление отдельно. | Магнитныйнасос8–24V,штуцер3/4,до80C | Исключено: Клапаны,таймер/термоуправление,монтаж | ПредварительноциркуляцияГВС.21л/минпри0.1бар,несамовсасывающий; допускматериаловкпитьевойГВСподтвердить,не автоматическоезамещениеHVACнасоса. | Q101: 2026-09-15 | R101: https://flutech-marine.com/en/jabsco/jabsco-59530-0000b/ | S101: ДА
A102: PK05-B | B102: M09-RECIRC-B | C102: ME-17 | D102: Jabsco Ecocirc горячая вода8–24V | E102: 1 | F102: шт | G102: M09-M-12 | H102: 407.42 | I102: =IF(AND(ISNUMBER(E102),ISNUMBER(H102)),ROUND(E102*H102,2),"") -> 407.42 | J102: PL23_ESTIMATE | K102: 23 | L102: =IF(AND(J102="PL23_ESTIMATE",ISNUMBER(I102)),ROUND(I102*K102/100,2),"") -> 93.71 | N102: =IF(J102="SOURCE_GROSS",IF(AND(ISNUMBER(E102),ISNUMBER(M102)),ROUND(E102*M102,2),""),IF(ISNUMBER(I102),ROUND(I102+L102,2),"")) -> 501.13 | O102: ПРЕДВАРИТЕЛЬНЫЙ СЦЕНАРИЙ M09: один насос рециркуляции ГВС | P102: Включён только насос; контур и управление отдельно. | Магнитныйнасос8–24V,штуцер3/4,до80C | Исключено: Клапаны,таймер/термоуправление,монтаж | ПредварительноциркуляцияГВС.21л/минпри0.1бар,несамовсасывающий; допускматериаловкпитьевойГВСподтвердить,не автоматическоезамещениеHVACнасоса. | Q102: 2026-09-15 | R102: https://flutech-marine.com/en/jabsco/jabsco-59530-0000b/ | S102: ДА
A103: PK05-C | B103: M09-RECIRC-C | C103: ME-17 | D103: Jabsco Ecocirc горячая вода8–24V | E103: 1 | F103: шт | G103: M09-M-12 | H103: 407.42 | I103: =IF(AND(ISNUMBER(E103),ISNUMBER(H103)),ROUND(E103*H103,2),"") -> 407.42 | J103: PL23_ESTIMATE | K103: 23 | L103: =IF(AND(J103="PL23_ESTIMATE",ISNUMBER(I103)),ROUND(I103*K103/100,2),"") -> 93.71 | N103: =IF(J103="SOURCE_GROSS",IF(AND(ISNUMBER(E103),ISNUMBER(M103)),ROUND(E103*M103,2),""),IF(ISNUMBER(I103),ROUND(I103+L103,2),"")) -> 501.13 | O103: ПРЕДВАРИТЕЛЬНЫЙ СЦЕНАРИЙ M09: один насос рециркуляции ГВС | P103: Включён только насос; контур и управление отдельно. | Магнитныйнасос8–24V,штуцер3/4,до80C | Исключено: Клапаны,таймер/термоуправление,монтаж | ПредварительноциркуляцияГВС.21л/минпри0.1бар,несамовсасывающий; допускматериаловкпитьевойГВСподтвердить,не автоматическоезамещениеHVACнасоса. | Q103: 2026-09-15 | R103: https://flutech-marine.com/en/jabsco/jabsco-59530-0000b/ | S103: ДА
A104: PK09-A | B104: M09-GEN-FUEL-A | C104: ME-18 | D104: Racor одиночный морской фильтр10мкм | E104: 2 | F104: шт | G104: M09-M-10 | H104: 499.66 | I104: =IF(AND(ISNUMBER(E104),ISNUMBER(H104)),ROUND(E104*H104,2),"") -> 999.32 | J104: PL23_ESTIMATE | K104: 23 | L104: =IF(AND(J104="PL23_ESTIMATE",ISNUMBER(I104)),ROUND(I104*K104/100,2),"") -> 229.84 | N104: =IF(J104="SOURCE_GROSS",IF(AND(ISNUMBER(E104),ISNUMBER(M104)),ROUND(E104*M104,2),""),IF(ISNUMBER(I104),ROUND(I104+L104,2),"")) -> 1229.16 | O104: ПРЕДВАРИТЕЛЬНЫЙ СЦЕНАРИЙ M09: по одному внешнему одиночному фильтру на генератор | P104: Сверить заводскую комплектность, микроны и расход; не покупать повторно включённые OEM элементы. | Один морской фильтр-влагоотделитель | Исключено: Дуплексный переключающий узел,трубопроводы,монтаж | Альтернативаодиночнойветви;НЕ равнозначна75500пообслуживаниюбезостановки.Длягенераторарасход/микроны/qtyподобратьотдельно. | Q104: 2026-09-15 | R104: https://racorshop.de/product/racor-500mam10-turbine-filter-marine/ | S104: ДА
A105: PK09-B | B105: M09-GEN-FUEL-B | C105: ME-18 | D105: Racor одиночный морской фильтр10мкм | E105: 2 | F105: шт | G105: M09-M-10 | H105: 499.66 | I105: =IF(AND(ISNUMBER(E105),ISNUMBER(H105)),ROUND(E105*H105,2),"") -> 999.32 | J105: PL23_ESTIMATE | K105: 23 | L105: =IF(AND(J105="PL23_ESTIMATE",ISNUMBER(I105)),ROUND(I105*K105/100,2),"") -> 229.84 | N105: =IF(J105="SOURCE_GROSS",IF(AND(ISNUMBER(E105),ISNUMBER(M105)),ROUND(E105*M105,2),""),IF(ISNUMBER(I105),ROUND(I105+L105,2),"")) -> 1229.16 | O105: ПРЕДВАРИТЕЛЬНЫЙ СЦЕНАРИЙ M09: по одному внешнему одиночному фильтру на генератор | P105: Сверить заводскую комплектность, микроны и расход; не покупать повторно включённые OEM элементы. | Один морской фильтр-влагоотделитель | Исключено: Дуплексный переключающий узел,трубопроводы,монтаж | Альтернативаодиночнойветви;НЕ равнозначна75500пообслуживаниюбезостановки.Длягенераторарасход/микроны/qtyподобратьотдельно. | Q105: 2026-09-15 | R105: https://racorshop.de/product/racor-500mam10-turbine-filter-marine/ | S105: ДА
A106: PK09-C | B106: M09-GEN-FUEL-C | C106: ME-18 | D106: Racor одиночный морской фильтр10мкм | E106: 2 | F106: шт | G106: M09-M-10 | H106: 499.66 | I106: =IF(AND(ISNUMBER(E106),ISNUMBER(H106)),ROUND(E106*H106,2),"") -> 999.32 | J106: PL23_ESTIMATE | K106: 23 | L106: =IF(AND(J106="PL23_ESTIMATE",ISNUMBER(I106)),ROUND(I106*K106/100,2),"") -> 229.84 | N106: =IF(J106="SOURCE_GROSS",IF(AND(ISNUMBER(E106),ISNUMBER(M106)),ROUND(E106*M106,2),""),IF(ISNUMBER(I106),ROUND(I106+L106,2),"")) -> 1229.16 | O106: ПРЕДВАРИТЕЛЬНЫЙ СЦЕНАРИЙ M09: по одному внешнему одиночному фильтру на генератор | P106: Сверить заводскую комплектность, микроны и расход; не покупать повторно включённые OEM элементы. | Один морской фильтр-влагоотделитель | Исключено: Дуплексный переключающий узел,трубопроводы,монтаж | Альтернативаодиночнойветви;НЕ равнозначна75500пообслуживаниюбезостановки.Длягенераторарасход/микроны/qtyподобратьотдельно. | Q106: 2026-09-15 | R106: https://racorshop.de/product/racor-500mam10-turbine-filter-marine/ | S106: ДА
... A112: PK10-C | B112: M09-FLOAT-C | C112: ME-20 | D112: Rule-A-Matic Plus float switch | E112: 2 | F112: шт. | G112: AX07 | H112: 54.58 | I112: =IF(AND(ISNUMBER(E112),ISNUMBER(H112)),ROUND(E112*H112,2),"") -> 109.16 | J112: PL23_ESTIMATE | K112: 23 | L112: =IF(AND(J112="PL23_ESTIMATE",ISNUMBER(I112)),ROUND(I112*K112/100,2),"") -> 25.11 | N112: =IF(J112="SOURCE_GROSS",IF(AND(ISNUMBER(E112),ISNUMBER(M112)),ROUND(E112*M112,2),""),IF(ISNUMBER(I112),ROUND(I112+L112,2),"")) -> 134.27 | O112: ПРЕДВАРИТЕЛЬНЫЙ СЦЕНАРИЙ M09: по одному рабочему поплавку к двум помпам | P112: Отдельно от датчиков высокого уровня AX08. | Поплавковый выключатель с защитным кожухом. | Исключено: Помпа, независимый высокий уровень, щит, реле при необходимости, кабели и монтаж. | 24 V: коммутационный ток проверить по паспорту конкретной помпы; пусковой ток не равен рабочему. Не полная автоматика осушения. | Q112: 2026-09-15 | R112: https://www.svb24.com/en/rule-rule-a-matic-plus-automatic-float-switch.html | S112: ДА
A113: PK10-A | B113: M09-FIRE-STOP-A | C113: ME-21 | D113: Fireboy ESC shutdown / 8 circuits | E113: 1 | F113: шт. | G113: AX11 | I113: =IF(AND(ISNUMBER(E113),ISNUMBER(H113)),ROUND(E113*H113,2),"") | J113: SOURCE_GROSS | L113: =IF(AND(J113="PL23_ESTIMATE",ISNUMBER(I113)),ROUND(I113*K113/100,2),"") | M113: 586.4 | N113: =IF(J113="SOURCE_GROSS",IF(AND(ISNUMBER(E113),ISNUMBER(M113)),ROUND(E113*M113,2),""),IF(ISNUMBER(I113),ROUND(I113+L113,2),"")) -> 586.4 | O113: ПРЕДВАРИТЕЛЬНЫЙ СЦЕНАРИЙ M09: один блок аварийного останова на 8 цепей | P113: Подтвердить 24 V конкретного SKU; приводы, тросы и матрица останова не включены. Gross без выделения налога. | Контроллер аварийного останова, исполнение 8 цепей. | Исключено: Баллон, трос, силовые исполнительные устройства, проводка, монтаж и настройка. | 24 V совместимость точной ревизии подтвердить; число и ток цепей проектировать для двигателя, 2 генераторов, вентиляции, топлива. Не подменяет полный пожарный пакет. | Q113: 2026-09-15 | R113: https://www.nauticabasile.it/eng/osculati/fireboy-esc-series-automatic-engine-shutdown-systems-46872/?listRef=related | S113: ДА
A114: PK10-B | B114: M09-FIRE-STOP-B | C114: ME-21 | D114: Fireboy ESC shutdown / 8 circuits | E114: 1 | F114: шт. | G114: AX11 | I114: =IF(AND(ISNUMBER(E114),ISNUMBER(H114)),ROUND(E114*H114,2),"") | J114: SOURCE_GROSS | L114: =IF(AND(J114="PL23_ESTIMATE",ISNUMBER(I114)),ROUND(I114*K114/100,2),"") | M114: 586.4 | N114: =IF(J114="SOURCE_GROSS",IF(AND(ISNUMBER(E114),ISNUMBER(M114)),ROUND(E114*M114,2),""),IF(ISNUMBER(I114),ROUND(I114+L114,2),"")) -> 586.4 | O114: ПРЕДВАРИТЕЛЬНЫЙ СЦЕНАРИЙ M09: один блок аварийного останова на 8 цепей | P114: Подтвердить 24 V конкретного SKU; приводы, тросы и матрица останова не включены. Gross без выделения налога. | Контроллер аварийного останова, исполнение 8 цепей. | Исключено: Баллон, трос, силовые исполнительные устройства, проводка, монтаж и настройка. | 24 V совместимость точной ревизии подтвердить; число и ток цепей проектировать для двигателя, 2 генераторов, вентиляции, топлива. Не подменяет полный пожарный пакет. | Q114: 2026-09-15 | R114: https://www.nauticabasile.it/eng/osculati/fireboy-esc-series-automatic-engine-shutdown-systems-46872/?listRef=related | S114: ДА
...

Sheet 03_Все цены
A1: id | B1: me | C1: name | D1: sku | E1: seller | F1: url | G1: viewed_on | H1: currency | I1: source_price | J1: source_tax_basis | K1: source_tax_percent | L1: net_unit_eur | M1: unit | N1: scope_included | O1: scope_excluded | P1: compatibility | Q1: price_evidence | R1: revision | S1: fx_date | T1: fx_quote_per_eur
A2: PROP-E01 | B2: ME-01|ME-02|ME-03 | C2: Volvo Penta D4-300 I + HS68A | D2: D4-300 I + HS68A | E2: См. исходную карточку M03 | F2: https://www.dbmoteurs.fr/sites/default/files/Volvo-Penta-tarifs-prix-achat-moteurs-2023-DB-Moteurs-motorisation-marine-bateau-plaisance.pdf | G2: 2026-09-11 | H2: EUR | I2: 44716 | J2: explicit HT; historical March 2023 | L2: 44716.00 | M2: package | N2: 300 metric hp crank / 289 prop shaft at3500rpm; R5; 24V option official but quoted configuration unspecified; HS68A ratio selection open; dimensions for HS85A must not be substituted; ME-03 partial only factory mounts where included: shaft/coupling/thrust unit quantities and price OPEN | O2: Исходные ограничения M03 сохранены | P2: HISTORICAL_NET_REFERENCE|RFQ_REQUIRED|DUTY_OPEN | Q2: PUBLIC_PRICE_NOT_KP | R2: M03/v001; цена не перепроверялась в M09
A3: PROP-E02 | B3: ME-01|ME-02|ME-03 | C3: Volvo Penta D4-300 I + HS85A | D3: D4-300 I + HS85A | E3: См. исходную карточку M03 | F3: https://www.dbmoteurs.fr/sites/default/files/Volvo-Penta-tarifs-prix-achat-moteurs-2023-DB-Moteurs-motorisation-marine-bateau-plaisance.pdf | G3: 2026-09-11 | H3: EUR | I3: 45977 | J3: explicit HT; historical March 2023 | L3: 45977.00 | M3: package | N3: 300 metric hp crank / 289 prop shaft; 3500rpm R5; 24V option price open; ratio2.500. L=433+801 W=441+407 H=274+520 from drawing; excludes projecting lifting eye/service space; not installation GA; ME-03 partial only factory mounts where included: shaft/coupling/thrust unit quantities and price OPEN | O3: Исходные ограничения M03 сохранены | P3: HISTORICAL_NET_REFERENCE|RFQ_REQUIRED|DUTY_OPEN | Q3: PUBLIC_PRICE_NOT_KP | R3: M03/v001; цена не перепроверялась в M09
A4: PROP-E03 | B4: ME-01|ME-02|ME-03 | C4: Volvo Penta D6-300 I + HS85A | D4: D6-300 I + HS85A | E4: См. исходную карточку M03 | F4: https://www.dbmoteurs.fr/sites/default/files/Volvo-Penta-tarifs-prix-achat-moteurs-2023-DB-Moteurs-motorisation-marine-bateau-plaisance.pdf | G4: 2026-09-11 | H4: EUR | I4: 50146 | J4: explicit HT; historical March 2023 | L4: 50146.00 | M4: package | N4: 300 metric hp crank /289 prop shaft;3300rpm. 24V option price open; L=433+1037 W=441+407 H=274+520 drawing dimensions not installation/service envelope; lifting eye extends above dimension; ME-03 partial only factory mounts where included: shaft/coupling/thrust unit quantities and price OPEN | O4: Исходные ограничения M03 сохранены | P4: HISTORICAL_NET_REFERENCE|RFQ_REQUIRED|DUTY_OPEN | Q4: PUBLIC_PRICE_NOT_KP | R4: M03/v001; цена не перепроверялась в M09
A5: PROP-E04 | B5: ME-01|ME-02|ME-03 | C5: FPT Industrial C90 410 rating D 300hp + gearbox RFQ | D5: C90 410 rating D 300hp + gearbox RFQ | E5: См. исходную карточку M03 | F5: https://www.etruck.fi/shop-1 | G5: 2026-09-11 | H5: EUR | J5: RFQ_REQUIRED | M5: package | N5: Official2026 220kW300hp@2000rpm ratingD heavy duty; gearbox unselected/unpriced; shown dimensions length to flywheel and mass ENGINE ONLY; not complete package envelope;24V option RFQ; ME-03 partial only factory mounts where included: shaft/coupling/thrust unit quantities and price OPEN | O5: Исходные ограничения M03 сохранены | P5: RFQ_REQUIRED|INCOMPLETE_PACKAGE|DUTY_COMPARISON_OPEN | Q5: PUBLIC_PRICE_NOT_KP | R5: M03/v001; цена не перепроверялась в M09
A6: PROP-G01 | B6: ME-04|ME-19 | C6: Fischer Panda Panda12000x PMS | D6: Panda12000x PMS | E6: См. исходную карточку M03 | F6: https://www.jpcdirect.com/product/fischer-panda-12000x-generator/ | G6: 2026-09-11 | H6: GBP | I6: 16830 | J6: explicit inc vat/ex vat pair | K6: 20 | L6: 16324.27 | M6: package | N6: 12kVA10.2kW nominal; Manel continuous10.8kVA9.2kW;50Hz230V +/-3V;12V starter;capsule included spec; verify exactJPCSKU/manufacturer0024660 and installation accessories; UK import/logistics not included; ME-19 partial factory cooling only: external seawater/exhaust runs and installation OPEN; JPC revision conflict H565 / additional700x470x580 and192kg vs OEM705x450x590/195kg: exactSKU CAD RFQ; OEM values retained | O6: Исходные ограничения M03 сохранены | P6: CONDITIONAL_START_VOLTAGE|AC_COMPATIBILITY_OPEN|RATING_OPEN|UK_REFERENCE | Q6: PUBLIC_PRICE_NOT_KP | R6: M03/v001; цена не перепроверялась в M09 | S6: 2026-09-10 | T6: 0.85915
A7: PROP-G02 | B7: ME-04|ME-19 | C7: Kohler / Rehlko 12EFKOZD | D7: 12EFKOZD | E7: См. исходную карточку M03 | F7: https://www.jpcdirect.com/product/kohler-12-kilowatt-generator/ | G7: 2026-09-11 | H7: GBP | I7: 18484.56 | J7: explicit inc vat/ex vat pair | K7: 20 | L7: 17929.12 | M7: package | N7: Singlephase115/230V50Hz:12kW12kVA continuous140C rise;11/11continuous115C;10.5/10.5prime. Official12or24V; JPC exactstarter/shield revision RFQ. Official shield mass385dry398wet; dealer406kg conflict. No borrowing US24V price scope; ME-19 partial factory cooling only: external seawater/exhaust runs and installation OPEN | O7: Исходные ограничения M03 сохранены | P7: CONDITIONAL_CONFIGURATION|AC_COMPATIBILITY_OPEN|RATING_OPEN|UK_REFERENCE | Q7: PUBLIC_PRICE_NOT_KP | R7: M03/v001; цена не перепроверялась в M09 | S7: 2026-09-10 | T7: 0.85915
A8: PROP-G03 | B8: ME-04|ME-19 | C8: Volpi Tecno Energia Paguro12000V AP12023050M0 | D8: Paguro12000V AP12023050M0 | E8: См. исходную карточку M03 | F8: https://www.manelservice.com/it/gruppi-elettrogeni-marini/3925-vte-paguro-12000-v-ap12023050m0.html | G8: 2026-09-11 | H8: EUR | I8: 14935.8 | J8: direct page12446.50 +IVA; gross14935.80 labelled SK20% locale | K8: 20 | L8: 12446.50 | M8: package | N8: 12kVA10kW continuous50Hz230V;12V starter;mass165capsule+15control electronics. Official dimensions capsule only; separate electronics footprint RFQ. Dealer/allpa dimensions/mass differ; exact SKU installationdrawing required. Published net directly not Polish VAT assumption; ME-19 partial factory cooling only: external seawater/exhaust runs and installation OPEN | O8: Исходные ограничения M03 сохранены | P8: CONDITIONAL_START_VOLTAGE|AC_COMPATIBILITY_OPEN|REVISION_OPEN | Q8: PUBLIC_PRICE_NOT_KP | R8: M03/v001; цена не перепроверялась в M09
A9: PROP-G04 | B9: ME-04|ME-19 | C9: Kohler / Rehlko 12EFKOZD24-SS | D9: 12EFKOZD24-SS | E9: См. исходную карточку M03 | F9: https://mmarineonline.com/products/kohler-marine-diesel-generator-24v-12efkozd-ss-50hz-with-sound-shield | G9: 2026-09-11 | H9: USD | I9: 20165.6 | J9: not stated | M9: package | N9: Alternative offer for G02 not fourthgenerator;24V plus shield explicitlySKU; tax/import/Poland availability unknown; price originalUSD noFX; ME-19 partial factory cooling only: external seawater/exhaust runs and installation OPEN | O9: Исходные ограничения M03 сохранены | P9: NO_NET|US_REFERENCE_ONLY|AC_COMPATIBILITY_OPEN|RATING_OPEN | Q9: PUBLIC_PRICE_NOT_KP | R9: M03/v001; цена не перепроверялась в M09
A10: EL-INV-A | B10: ME-05 | C10: Victron MultiPlus-II 24/3000/70-32 PMP242305010 | D10: MultiPlus-II 24/3000/70-32 PMP242305010 | E10: См. исходную карточку M03 | F10: https://www.svb.de/de/victron-wechselrichter-ladegeraet-multiplus-ii-24-v-3000-va-70-a.html | G10: 2026-09-11 | H10: EUR | I10: 879.95 | J10: GROSS_RATE_CONFIRMED | K10: 19 | L10: 739.45 | M10: pcs | N10: 24 V input; factory 230 V. 3000 VA not 3000 W: 2400 W at25C/2200 W at40C; charger70 A. 2 devices architecture target, capacity unapproved. | O10: Исходные ограничения M03 сохранены | P10: CONDITIONAL_3KVA_REFERENCE | Q10: PUBLIC_PRICE_NOT_KP | R10: M03/v001; цена не перепроверялась в M09
A11: EL-INV-B | B11: ME-05 | C11: Victron MultiPlus-II GX 24/3000/70-32 PMP242306000 | D11: MultiPlus-II GX 24/3000/70-32 PMP242306000 | E11: См. исходную карточку M03 | F11: https://www.svb.de/de/victron-wechselrichter-ladegeraet-multiplus-ii-gx-24-v-3000-va-70-a.html | G11: 2026-09-11 | H11: EUR | I11: 999.95 | J11: GROSS_RATE_CONFIRMED | K11: 19 | L11: 840.29 | M11: pcs | N11: 24 V; factory230 V;2400 W at25C/2200 W at40C;70 A. GX monitoring differs; two GX units not required by yacht specification. Current manual geometry differs from catalogue: confirm revision. | O11: Исходные ограничения M03 сохранены | P11: CONDITIONAL_3KVA_REFERENCE | Q11: PUBLIC_PRICE_NOT_KP | R11: M03/v001; цена не перепроверялась в M09
A12: EL-INV-C | B12: ME-05 | C12: Mastervolt CombiMaster 24/3000-60 230V 35023000 | D12: CombiMaster 24/3000-60 230V 35023000 | E12: См. исходную карточку M03 | F12: https://www.svb.de/de/mastervolt-wechselrichter-ladegeraet-combimaster-24-v-3000-va-60-a.html?question_sort=oldest | G12: 2026-09-11 | H12: EUR | I12: 1599.96 | J12: GROSS_RATE_CONFIRMED | K12: 19 | L12: 1344.50 | M12: pcs | N12: 24 V; factory230 V;3000 VA/2600 W at40C;60 A charger;25 A transfer versus32 A Victron. Parallel operation not qualified. | O12: Исходные ограничения M03 сохранены | P12: CONDITIONAL_3KVA_NOT_EQUAL_W | Q12: PUBLIC_PRICE_NOT_KP | R12: M03/v001; цена не перепроверялась в M09
A13: EL-ISO-A | B13: ME-09 | C13: Victron 3600 ITR040362042 | D13: 3600 ITR040362042 | E13: См. исходную карточку M03 | F13: https://www.svb24.com/en/p/victron-isolation-transformer-3600-w-115-230-v.html | G13: 2026-09-11 | H13: EUR | I13: 436.93 | J13: NET_EXPLICIT | L13: 436.93 | M13: pcs | N13: 3.6 class; quantity and shore capacity unknown. Dimensions/mass from opened dealer data pending native drawing confirmation; no substitute of32A at115V for32A at230V. | O13: Исходные ограничения M03 сохранены | P13: CONDITIONAL_UNIT_BENCHMARK_DIMENSIONS_DEALER | Q13: PUBLIC_PRICE_NOT_KP | R13: M03/v001; цена не перепроверялась в M09
A14: EL-ISO-B | B14: ME-09 | C14: Mastervolt Mass GI3.5 88000355 | D14: Mass GI3.5 88000355 | E14: См. исходную карточку M03 | F14: https://www.svb24.com/en/mastervolt-mass-gi-3-5-isolation-transformer-16-a-3-5-kw.html | G14: 2026-09-11 | H14: EUR | I14: 1008.36 | J14: NET_EXPLICIT | L14: 1008.36 | M14: pcs | N14: 3500 VA at230 V;16 A;HF technology;source IP23 supersedes dealer IP21. Not complete shore protection. | O14: Исходные ограничения M03 сохранены | P14: CONDITIONAL_UNIT_BENCHMARK | Q14: PUBLIC_PRICE_NOT_KP | R14: M03/v001; цена не перепроверялась в M09
A15: EL-ISO-C | B15: ME-09 | C15: WhisperPower GI3600 60110102 | D15: GI3600 60110102 | E15: См. исходную карточку M03 | F15: https://www.hansenautic.de/36377/wp-gi-compact-galvanic-isolation-transformator-230v-16a-120v-32a/ | G15: 2026-09-11 | H15: EUR | I15: 1885.00 | J15: GROSS_RATE_UNCONFIRMED | M15: pcs | N15: 3.6 kVA;230/110 V;16/32 A. Open page confirms VAT included but not rate: NET deliberately blank. | O15: Исходные ограничения M03 сохранены | P15: CONDITIONAL_NET_PENDING_TAX | Q15: PUBLIC_PRICE_NOT_KP | R15: M03/v001; цена не перепроверялась в M09
A16: EL-BAT-A | B16: ME-08 | C16: Exide ER550 12V115Ah | D16: ER550 12V115Ah | E16: См. исходную карточку M03 | F16: https://online-batterien.de/a/exide-er550-dual-versorgungsbatterie-starterbatterie-12v-115ah-550wh/400440 | G16: 2026-09-11 | H16: EUR | I16: 166.89 | J16: GROSS_RATE_CONFIRMED | K16: 19 | L16: 140.24 | M16: pcs | N16: Flooded. Owner only said115 amperes; Ah and unit voltage unconfirmed. 6 physical units; no bank wiring/capacity inferred. Deposit extra. Dealer350mm/29kg differs from brochure. | O16: Исходные ограничения M03 сохранены | P16: CONDITIONAL_115AH12V_NOT_OWNER_APPROVED | Q16: PUBLIC_PRICE_NOT_KP | R16: M03/v001; цена не перепроверялась в M09
A17: EL-BAT-B | B17: ME-08 | C17: Aquamot ALS12115 12V115Ah | D17: ALS12115 12V115Ah | E17: См. исходную карточку M03 | F17: https://www.nothnagel-marine.de/product_info.php?info=p3857_aquamot---power-battery--dc-battery-als12115-12v-115ah-agm-deep-cycle-battery.html&language=en | G17: 2026-09-11 | H17: EUR | I17: 319.00 | J17: GROSS_RATE_CONFIRMED | K17: 19 | L17: 268.07 | M17: pcs | N17: AGM dealer description; legacy manufacturer sheet includes GEL construction wording, chemistry/revision confirmation needed. Body height214mm total220mm; dealer header6.4kg rejected in favour33.7kg technical sheet. | O17: Исходные ограничения M03 сохранены | P17: CONDITIONAL_115AH12V_NOT_OWNER_APPROVED | Q17: PUBLIC_PRICE_NOT_KP | R17: M03/v001; цена не перепроверялась в M09
A18: EL-BAT-C | B18: ME-08 | C18: Victron AGM Telecom115Ah M8 BAT412105164 | D18: AGM Telecom115Ah M8 BAT412105164 | E18: См. исходную карточку M03 | F18: https://ab-marineservice.com/product/12v-115ah-agm-telecom-batt-m8/ | G18: 2026-09-11 | H18: EUR | I18: 329.95 | J18: GROSS_RATE_CONFIRMED | K18: 21 | L18: 272.69 | M18: pcs | N18: 12 V AGM front terminal;6 units only if owner confirms115Ah12V. No12V housebus inferred. Open page21% supersedes search19%. | O18: Исходные ограничения M03 сохранены | P18: CONDITIONAL_115AH12V_NOT_OWNER_APPROVED | Q18: PUBLIC_PRICE_NOT_KP | R18: M03/v001; цена не перепроверялась в M09
A19: EL-DIST-A | B19: ME-10 | C19: Victron Lynx Distributor M8 LYN060102000 | D19: Lynx Distributor M8 LYN060102000 | E19: См. исходную карточку M03 | F19: https://www.dynastart.nl/lyn060102000-lynx-distributor-m8 | G19: 2026-09-11 | H19: EUR | I19: 182.75 | J19: NET_EXPLICIT | L19: 182.75 | M19: pcs | N19: Supports24 V;1000 A product rating not yacht demand; four fuse ways, fuses/monitor supply and full installation separate. Source axis hxlxw=290x170x80; check drawing for orientation. | O19: Исходные ограничения M03 сохранены | P19: CONDITIONAL_UNIT_BENCHMARK | Q19: PUBLIC_PRICE_NOT_KP | R19: M03/v001; цена не перепроверялась в M09
A20: EL-DIST-B | B20: ME-10 | C20: Philippi STV207 020002071 | D20: STV207 020002071 | E20: См. исходную карточку M03 | F20: https://www.svb24.com/en/philippi-stv207-power-distribution-panel-configurable.html | G20: 2026-09-11 | H20: EUR | I20: 214.24 | J20: NET_EXPLICIT | L20: 214.24 | M20: pcs | N20: 24 V compatible seven-circuit unit benchmark;10 A standard breakers not approved circuit ratings. DC accessory socket not permission for12V loads on24V. Mass not published. Not complete yacht switchboard. | O20: Исходные ограничения M03 сохранены | P20: CONDITIONAL_UNIT_BENCHMARK | Q20: PUBLIC_PRICE_NOT_KP | R20: M03/v001; цена не перепроверялась в M09
A21: EL-DIST-C | B21: ME-10 | C21: Philippi LAE113 010001130 | D21: LAE113 010001130 | E21: См. исходную карточку M03 | F21: https://www.svb24.com/en/philippi-lae-113-shore-connection-unit.html | G21: 2026-09-11 | H21: EUR | I21: 331.89 | J21: NET_EXPLICIT | L21: 331.89 | M21: pcs | N21: Factory230 V50Hz panel benchmark for220VAC target;16A/30mA RCBO and3two-pole10A circuits per official description. Not full multi-source AC switchboard; mass unknown. | O21: Исходные ограничения M03 сохранены | P21: CONDITIONAL_UNIT_BENCHMARK | Q21: PUBLIC_PRICE_NOT_KP | R21: M03/v001; цена не перепроверялась в M09
A22: EL-REM-A | B22: ME-28 | C22: Blue Sea ML-RBS7702 24V | D22: ML-RBS7702 24V | E22: См. исходную карточку M03 | F22: https://www.svb24.com/en/blue-sea-hd-remote-battery-switch-24v.html | G22: 2026-09-11 | H22: EUR | I22: 239.45 | J22: NET_EXPLICIT | L22: 239.45 | M22: pcs | N22: Manual override;24V coil;500A continuous product rating. Quantity, control failover, crank duty and24V live switching not qualified; dimensions drawing pending. | O22: Исходные ограничения M03 сохранены | P22: CONDITIONAL_UNIT_BENCHMARK | Q22: PUBLIC_PRICE_NOT_KP | R22: M03/v001; цена не перепроверялась в M09
A23: EL-REM-B | B23: ME-28 | C23: Blue Sea 7703 24V | D23: 7703 24V | E23: См. исходную карточку M03 | F23: https://www.svb24.com/en/blue-sea-universal-solenoid-switch-24-v.html | G23: 2026-09-11 | H23: EUR | I23: 226.85 | J23: NET_EXPLICIT | L23: 226.85 | M23: pcs | N23: Solenoid unit benchmark without manual override of7702; not automatic equivalent. Physical dimensions/mass unverified. No assertion reserve-start scheme works. | O23: Исходные ограничения M03 сохранены | P23: CONDITIONAL_UNIT_BENCHMARK | Q23: PUBLIC_PRICE_NOT_KP | R23: M03/v001; цена не перепроверялась в M09
A24: EL-OPEN-PUMP | B24: ME-06 | C24: UNSIZED | D24: UNSIZED | E24: См. исходную карточку M03 | G24: 2026-09-11 | J24: UNKNOWN | M24: function | N24: 1 independent function, not necessarily extra inverter. Select after pump running power/start waveform/duty; avoid double counting ME05. | O24: Исходные ограничения M03 сохранены | P24: OPEN_LOAD_AND_STARTUP | Q24: PUBLIC_PRICE_NOT_KP | R24: M03/v001; цена не перепроверялась в M09
A25: EL-OPEN-MAIN | B25: ME-07 | C25: UNSIZED | D25: UNSIZED | E25: См. исходную карточку M03 | G25: 2026-09-11 | J25: UNKNOWN | M25: pcs | N25: 1 physical owner battery, capacity/voltage/chemistry unknown. Not automatically ER550 or service115Ah. | O25: Исходные ограничения M03 сохранены | P25: OPEN_START_VOLTAGE_CCA | Q25: PUBLIC_PRICE_NOT_KP | R25: M03/v001; цена не перепроверялась в M09
A26: EL-OPEN-GEN | B26: ME-27 | C26: UNSIZED | D26: UNSIZED | E26: См. исходную карточку M03 | G26: 2026-09-11 | J26: UNKNOWN | M26: pcs | N26: 2 physical owner batteries for2generators; capacity/voltage/CCA unknown; keep9total with6service+1main. No fictitious unit price. | O26: Исходные ограничения M03 сохранены | P26: OPEN_START_VOLTAGE_CCA | Q26: PUBLIC_PRICE_NOT_KP | R26: M03/v001; цена не перепроверялась в M09
A27: WC-RO-01 | B27: ME-13 | C27: Aquatec AC150 230V single phase | D27: AC150 230V single phase | E27: См. исходную карточку M03 | F27: https://www.aquatec-watermaker.de/wassermacher-produkt-ac150-ac240.html | G27: 2026-09-11 | H27: EUR | I27: 7539 | J27: EXPLICIT_NET_AND_19_PERCENT_GROSS | K27: 19 | L27: 6335.29 | M27: шт | N27: 150 L/h nominal ±10% at25C/35000ppm; modular conventional HP pump; base price only: automatic flush/salinity/reject parity must be itemised; generator minimum4kW manufacturer target, not electrical demand or selection | O27: Исходные ограничения M03 сохранены | P27: FUNCTION_PARITY_OPEN;220V_COMPATIBILITY_OPEN | Q27: PUBLIC_PRICE_NOT_KP | R27: M03/v001; цена не перепроверялась в M09
A28: WC-RO-02 | B28: ME-13 | C28: Schenker ZEN150 24V/230V Touch plus salinity/reject | D28: ZEN150 24V/230V Touch plus salinity/reject | E28: См. исходную карточку M03 | F28: https://mar-nautic.com/schenker-watermaker-zen-150 | G28: 2026-09-11 | H28: EUR | I28: 12820.2 | J28: FROM_GROSS_EXPLICIT_20_PERCENT | K28: 20 | L28: 10683.50 | M28: шт | N28: Observed FROM base price; net is FROM benchmark only, NOT complete Touch/salinity/reject price. Nominal150L/h. Manufacturer230V±15% includes220V. Basic has no salinity; Touch optional; 24V variant permitted. Modular unit dimensions not total installed envelope. | O28: Исходные ограничения M03 сохранены | P28: FROM_PRICE_NOT_CONFIGURED;RFQ_REQUIRED | Q28: PUBLIC_PRICE_NOT_KP | R28: M03/v001; цена не перепроверялась в M09
A29: WC-RO-03 | B29: ME-13 | C29: Osmosea NEW12 150C 24V | D29: NEW12 150C 24V | E29: См. исходную карточку M03 | F29: https://www.manelservice.com/en/marine-desalination-systems/17102-osmosea-new12-150c-nautical-watermaker-150-lth.html | G29: 2026-09-11 | H29: EUR | M29: шт | N29: Official150L/h/600W; flush/salinometer/unsafe-water discard included. Official63kg conflicts dealer65kg; dimensions dealer796x317x408 not official therefore blank. Dealer install/service kits included vs manufacturer optional: reconcile | O29: Исходные ограничения M03 сохранены | P29: RFQ_REQUIRED;COMPACT_CANDIDATE | Q29: PUBLIC_PRICE_NOT_KP | R29: M03/v001; цена не перепроверялась в M09
A30: WC-DC-01 | B30: ME-11 | C30: CEM OSC-16.062.24 / OEM identity reconcile | D30: OSC-16.062.24 / OEM identity reconcile | E30: См. исходную карточку M03 | F30: https://www.comptoirnautique.com/groupe-d-eau-a-pressostat/53022-cem-elettromeccanica-autoclave-cem-vase-expansion-inox-20l-24v-50-l-min.html | G30: 2026-09-11 | H30: EUR | I30: 1229.9 | J30: EXPLICIT_HT | L30: 1024.92 | M30: шт | N30: 24V20L accumulator; dealer50L/min max; source model mapping not proven. Common proposed test15L/min at2bar NOT verified. Do not add included tank again. | O30: Исходные ограничения M03 сохранены | P30: WORKING_POINT_AND_OEM_ID_OPEN | Q30: PUBLIC_PRICE_NOT_KP | R30: M03/v001; цена не перепроверялась в M09
A31: WC-DC-02 | B31: ME-11 | C31: Gianneschi EcoInox1 GE011 24V20L | D31: EcoInox1 GE011 24V20L | E31: См. исходную карточку M03 | F31: https://www.comptoirnautique.com/groupe-d-eau-hydrophore/22947-gianneschi-groupe-d-eau-ecoinox-1-avec-reservoir-20l-24v-45lmin-7024.html | G31: 2026-09-11 | H31: EUR | I31: 1311.9 | J31: EXPLICIT_HT | L31: 1093.25 | M31: шт | N31: 45L/min max; common proposed15L/min at2bar needs curve. Includes20L tank/gauge/pressure switch; current OEM revision confirmation. | O31: Исходные ограничения M03 сохранены | P31: WORKING_POINT_OPEN | Q31: PUBLIC_PRICE_NOT_KP | R31: M03/v001; цена не перепроверялась в M09
A32: WC-DC-03 | B32: ME-11 | C32: ENAG GH24-0.37-24L-OT RB18-ED | D32: GH24-0.37-24L-OT RB18-ED | E32: См. исходную карточку M03 | F32: https://www.enag.fr/english/wp-content/uploads/sites/5/2022/11/FC-GH-EN-C.pdf | G32: 2026-09-11 | H32: EUR | M32: шт | N32: Official24V/0.37kW; 1m3/h at30m published point; pressure switch1.5/2.5bar.24L tank differs20L competitors: standardise accumulator scope before comparison. Dimensions drawing orientation not mapped into LWH. | O32: Исходные ограничения M03 сохранены | P32: RFQ_REQUIRED;WORKING_POINT_OPEN | Q32: PUBLIC_PRICE_NOT_KP | R32: M03/v001; цена не перепроверялась в M09
A33: WC-AC-01 | B33: ME-12 | C33: CEM J-INOX/20X 230M | D33: J-INOX/20X 230M | E33: См. исходную карточку M03 | F33: https://cempumps.com/wp-content/uploads/2024/10/Autoclavi_20L-20X.pdf | G33: 2026-09-11 | H33: EUR | M33: шт | N33: Official230V singlephase variant exists. Proposedcommon15L/min at2bar not accepted from maxflow.20L stainless tank included. No price borrowed from24V sibling. | O33: Исходные ограничения M03 сохранены | P33: RFQ_REQUIRED;220V_COMPATIBILITY_OPEN;WORKING_POINT_OPEN | Q33: PUBLIC_PRICE_NOT_KP | R33: M03/v001; цена не перепроверялась в M09
A34: WC-AC-02 | B34: ME-12 | C34: Gianneschi EcoInox2 GE017 230V20L | D34: EcoInox2 GE017 230V20L | E34: См. исходную карточку M03 | F34: https://www.tyboat.com/achat/P-57388-gianneschi-groupe-d-eau-ecoinox2-3-5-bars-0-45-kw-55-litres-minute-reservoir-20-litres-230-volts.html | G34: 2026-09-11 | H34: EUR | I34: 1263 | J34: EXPLICIT_HT | L34: 1052.50 | M34: шт | N34: Open page1052.50HT supersedes search992.50. Dealer max55L/min conflicts Kent45: curves required.0.45kW/20L; common15L/min at2bar not verified. | O34: Исходные ограничения M03 сохранены | P34: 220V_COMPATIBILITY_OPEN;WORKING_POINT_OPEN | Q34: PUBLIC_PRICE_NOT_KP | R34: M03/v001; цена не перепроверялась в M09
A35: WC-AC-03 | B35: ME-12 | C35: ENAG GH230mono-0.37-24L-JET M-ED | D35: GH230mono-0.37-24L-JET M-ED | E35: См. исходную карточку M03 | F35: https://www.enag.fr/english/wp-content/uploads/sites/5/2022/11/FC-GH-EN-C.pdf | G35: 2026-09-11 | H35: EUR | M35: шт | N35: Explicit230V singlephase; official1m3/h at40m, pressure switch1.5/2.5bar.24L accumulator vs20L needs standardisation; no equivalence claim. | O35: Исходные ограничения M03 сохранены | P35: RFQ_REQUIRED;220V_COMPATIBILITY_OPEN;WORKING_POINT_OPEN | Q35: PUBLIC_PRICE_NOT_KP | R35: M03/v001; цена не перепроверялась в M09
A36: WC-CH-01 | B36: ME-15 | C36: Thermowell UC16H | D36: UC16H | E36: См. исходную карточку M03 | F36: https://www.esconet.fi/shop/uc16h-thermowell-uc16h-ilmastointilaite-chiller-230v-16000btu-27518 | G36: 2026-09-11 | H36: EUR | I36: 4544.35 | J36: GROSS_EXPLICIT_ALV25.5 | K36: 25.5 | L36: 3621.00 | M36: шт | N36: 16000BTU/h each; illustrative class NOT yacht heatload. Officialcatalog220/1/50; dealer230V. Dimensions exclude controlbox. OEM catalogue says box/display included BUT priced Esco SKU requires airhandler/controlpanel separately: inclusion CONFLICT, RFQ required; do not assume included display.1.5kWnominput at catalogue conditions; independent2module integration open. | O36: Исходные ограничения M03 сохранены | P36: REFERENCE_SIZE_ONLY;VOLTAGE_REVISION_CHECK;SUPPLY_SCOPE_CONFLICT_RFQ | Q36: PUBLIC_PRICE_NOT_KP | R36: M03/v001; цена не перепроверялась в M09
A37: WC-CH-02 | B37: ME-15 | C37: Climma CWS Aquacontrol161RC 230/1/50 | D37: CWS Aquacontrol161RC 230/1/50 | E37: См. исходную карточку M03 | F37: https://mdislandsupply.com/en/climma/879-cws-aquacontrol-161-rc-230150-climma.html | G37: 2026-09-11 | H37: EUR | I37: 4155.3 | J37: EXPLICIT_TAX_EXCLUDED | L37: 4155.30 | M37: шт | N37: 16000BTU/h each; reversecycle. Price recovered live requests HTTP200 after web429; local source text retained. OEM dimensions require authenticated download; old dealerPDF not promoted. | O37: Исходные ограничения M03 сохранены | P37: REFERENCE_SIZE_ONLY;220V_COMPATIBILITY_OPEN | Q37: PUBLIC_PRICE_NOT_KP | R37: M03/v001; цена не перепроверялась в M09
A38: WC-CH-03 | B38: ME-15 | C38: Webasto BlueCool C16M | D38: BlueCool C16M | E38: См. исходную карточку M03 | F38: https://www.nauticsale.com/en/airconditioning/bluecool-chiller-systems/bluecool-c-series-chillers/ | G38: 2026-09-11 | H38: EUR | M38: шт | N38: 16000BTU/h each; officialcurrentdimensions. Older F-suffix dealerweight differs: revision match required.3pricepaths found no verified EU net exactSKU; no US price conversion. | O38: Исходные ограничения M03 сохранены | P38: RFQ_REQUIRED;REFERENCE_SIZE_ONLY;220V_COMPATIBILITY_OPEN | Q38: PUBLIC_PRICE_NOT_KP | R38: M03/v001; цена не перепроверялась в M09
A39: WC-HW-01 | B39: ME-14 | C39: Quick B3 40L1200W FLB34012S000A00 | D39: B3 40L1200W FLB34012S000A00 | E39: См. исходную карточку M03 | F39: https://www.tyboat.com/achat/P-8889-quick-chauffe-eau-cylindrique-b3-40-litres-220-volts-1200-watts.html | G39: 2026-09-11 | H39: EUR | I39: 737 | J39: EXPLICIT_HT | L39: 614.17 | M39: шт | N39: 40L1200W220V plus engine heat exchanger common illustrative class; not owner size. Supplier dimensions/mass in research only pending official drawing. Thermostatic mixing equalise separately. | O39: Исходные ограничения M03 сохранены | P39: UNIT_BENCHMARK_ONLY;QTY_OPEN | Q39: PUBLIC_PRICE_NOT_KP | R39: M03/v001; цена не перепроверялась в M09
A40: WC-HW-02 | B40: ME-14 | C40: Quick BX 40L1200W FLBX4012S000A00 | D40: BX 40L1200W FLBX4012S000A00 | E40: См. исходную карточку M03 | F40: https://www.tyboat.com/achat/P-8880-quick-chauffe-eau-cylindrique-bx-40-litres-220-volts-1200-watts.html | G40: 2026-09-11 | H40: EUR | I40: 829 | J40: EXPLICIT_HT | L40: 690.83 | M40: шт | N40: 40L1200W220V plus engine heat exchanger common illustrative class; not owner size. Supplier dimensions/mass in research only pending official drawing. Thermostatic mixing equalise separately. | O40: Исходные ограничения M03 сохранены | P40: UNIT_BENCHMARK_ONLY;QTY_OPEN | Q40: PUBLIC_PRICE_NOT_KP | R40: M03/v001; цена не перепроверялась в M09
A41: WC-HW-03 | B41: ME-14 | C41: Quick BXS 40L1200W FLBXS4012S00A00 | D41: BXS 40L1200W FLBXS4012S00A00 | E41: См. исходную карточку M03 | F41: https://www.tyboat.com/achat/P-18237-quick-chauffe-eau-cube-inox-bxs-40-litres-220-volts-1200-watts.html | G41: 2026-09-11 | H41: EUR | I41: 909 | J41: EXPLICIT_HT | L41: 757.50 | M41: шт | N41: 40L1200W220V plus engine heat exchanger common illustrative class; not owner size. Supplier dimensions/mass in research only pending official drawing. Thermostatic mixing equalise separately. | O41: Исходные ограничения M03 сохранены | P41: UNIT_BENCHMARK_ONLY;QTY_OPEN | Q41: PUBLIC_PRICE_NOT_KP | R41: M03/v001; цена не перепроверялась в M09
A42: WC-AUX-01 | B42: ME-16 | C42: Frigomar NH150PS SWM0150230 | D42: NH150PS SWM0150230 | E42: См. исходную карточку M03 | F42: https://www.comptoirnautique.com/climatisation-bateau/91819-frigomar-pompes-a-entrainement-magnetique.html | G42: 2026-09-11 | H42: EUR | I42: 795.9 | J42: EXPLICIT_HT | L42: 663.25 | M42: шт | N42: 230V50/60Hz magneticdrive; count and pump duty notfixed. No proof this model meets both seawater and chilledwater circuits; official detailed curve required. | O42: Исходные ограничения M03 сохранены | P42: UNIT_BENCHMARK_ONLY;CURVE_AND_220V_OPEN | Q42: PUBLIC_PRICE_NOT_KP | R42: M03/v001; цена не перепроверялась в M09
A43: WC-AUX-02 | B43: ME-17 | C43: Quick QB002 mixing kit | D43: QB002 mixing kit | E43: См. исходную карточку M03 | F43: https://www.kent-marine.com/fr/produit/35262/chauffe-eau-cylindrique-40l-220v-1200w.html | G43: 2026-09-11 | H43: EUR | I43: 140.4 | J43: EXPLICIT_HT | L43: 117.00 | M43: шт | N43: Observed linked accessory publicHT price; count unknown; confirm inclusion in selected calorifier supply. | O43: Исходные ограничения M03 сохранены | P43: PUBLIC_LIST_UNIT_BENCHMARK | Q43: PUBLIC_PRICE_NOT_KP | R43: M03/v001; цена не перепроверялась в M09
A44: WC-AUX-03 | B44: ME-17 | C44: Jabsco Pumpgard36400-0002 / substitution46400-0000 | D44: Pumpgard36400-0002 / substitution46400-0000 | E44: См. исходную карточку M03 | F44: https://www.marine-impact.com/groupe-d-eau/313-filtre-en-ligne-pumpgard-o13-mm-jabsco.html | G44: 2026-09-11 | H44: EUR | I44: 33.5 | J44: TAX_NOT_PROVEN | M44: шт | N44: Observedprice; no explicit taxbasis verified so net blank.13mm40mesh strainer not sanitary treatment and not dimensioned for proposedpressurestation. | O44: Исходные ограничения M03 сохранены | P44: UNIT_BENCHMARK_GROSS_UNKNOWN;NET_WITHHELD | Q44: PUBLIC_PRICE_NOT_KP | R44: M03/v001; цена не перепроверялась в M09
A45: A01 | B45: ME-29 | C45: Vetus HT1010 | D45: HT1010 | E45: См. исходную карточку M03 | F45: https://www.vetus-shop.com/aluminium-hydraulic-tank-70-incl-ht1013-p-2024.html | G45: 2026-09-11 | H45: GBP | I45: 2412.08 | J45: NET_EXPLICIT | L45: 2807.52 | M45: шт | N45: 70л; HT1013 включён. Цена бака с частью управления, не станции. 615×475×360мм у продавца — только голый бак без клапанов, не монтажный габарит. | O45: Исходные ограничения M03 сохранены | P45: PARTIAL_HYDRAULIC_NOT_COMPLETE | Q45: PUBLIC_PRICE_NOT_KP | R45: M03/v001; цена не перепроверялась в M09 | S45: 2026-09-10 | T45: 0.85915
A46: A02 | B46: ME-29 | C46: Vetus HT1016SD2 | D46: HT1016SD2 | E46: См. исходную карточку M03 | F46: https://www.vetus-shop.com/vetus-power-hydraulics-c-21_210.html | G46: 2026-09-11 | H46: GBP | I46: 2716.67 | J46: NET_EXPLICIT | L46: 3162.04 | M46: шт | N46: 45см³/оборот; ориентация/SAE/привод и требуемый расход не выбраны. Не три уровня насосов разного размера. | O46: Исходные ограничения M03 сохранены | P46: PARTIAL_HYDRAULIC_NOT_COMPLETE | Q46: PUBLIC_PRICE_NOT_KP | R46: M03/v001; цена не перепроверялась в M09 | S46: 2026-09-10 | T46: 0.85915
A47: A03 | B47: ME-29 | C47: Vetus HT301132 | D47: HT301132 | E47: См. исходную карточку M03 | F47: https://www.vetus-shop.com/aluminium-hydraulic-tank-70-incl-ht1013-p-2024.html | G47: 2026-09-11 | H47: GBP | I47: 517.50 | J47: NET_EXPLICIT | L47: 602.34 | M47: шт | N47: Шланг32мм; теплоотдача/забортный контур требуют проверки; не доказана необходимость именно этого размера. | O47: Исходные ограничения M03 сохранены | P47: PARTIAL_HYDRAULIC_NOT_COMPLETE | Q47: PUBLIC_PRICE_NOT_KP | R47: M03/v001; цена не перепроверялась в M09 | S47: 2026-09-10 | T47: 0.85915
A48: A04 | B48: ME-29 | C48: Vetus HT102312 | D48: HT102312 | E48: См. исходную карточку M03 | F48: https://www.vetus-shop.com/aluminium-hydraulic-tank-70-incl-ht1013-p-2024.html | G48: 2026-09-11 | H48: GBP | I48: 487.92 | J48: NET_EXPLICIT | L48: 567.91 | M48: шт | N48: Один тип клапана; не весь блок гидролебёдок, количество потребителей открыто. | O48: Исходные ограничения M03 сохранены | P48: PARTIAL_HYDRAULIC_NOT_COMPLETE | Q48: PUBLIC_PRICE_NOT_KP | R48: M03/v001; цена не перепроверялась в M09 | S48: 2026-09-10 | T48: 0.85915
A49: A05 | B49: ME-29 | C49: Vetus HT1011 | D49: HT1011 | E49: См. исходную карточку M03 | F49: https://www.vetus-shop.com/vetus-power-hydraulics-c-21_210.html | G49: 2026-09-11 | H49: GBP | I49: 715.83 | J49: NET_EXPLICIT | L49: 833.18 | M49: шт | N49: Одноступенчатый load sensing; пригодность к общей системе открыта. | O49: Исходные ограничения M03 сохранены | P49: PARTIAL_HYDRAULIC_NOT_COMPLETE | Q49: PUBLIC_PRICE_NOT_KP | R49: M03/v001; цена не перепроверялась в M09 | S49: 2026-09-10 | T49: 0.85915
A50: A06 | B50: ME-29 | C50: Vetus HT1013 | D50: HT1013 | E50: См. исходную карточку M03 | F50: https://www.vetus-shop.com/aluminium-hydraulic-tank-70-incl-ht1013-p-2024.html | G50: 2026-09-11 | H50: GBP | I50: 300.83 | J50: NET_EXPLICIT | L50: 350.15 | M50: шт | N50: Уже входит в HT1010; отдельная цена только для дополнительного потребителя, не прибавлять повторно. | O50: Исходные ограничения M03 сохранены | P50: INCLUDED_COMPONENT_DO_NOT_ADD | Q50: PUBLIC_PRICE_NOT_KP | R50: M03/v001; цена не перепроверялась в M09 | S50: 2026-09-10 | T50: 0.85915
A51: A07 | B51: ME-29 | C51: Sleipner Load-sensing system / bulkhead tank 40L | D51: Load-sensing system / bulkhead tank 40L | E51: См. исходную карточку M03 | G51: 2026-09-11 | H51: EUR | J51: RFQ_REQUIRED | M51: шт | N51: Справочный габарит настенного танк-модуля из каталога2020; с блоком одного подруливающего, без всей установки. Ещё100мм для замены фильтра. Нужны текущийCAD и расчёт всех потребителей. | O51: Исходные ограничения M03 сохранены | P51: RFQ_REQUIRED_TECH_OPEN | Q51: PUBLIC_PRICE_NOT_KP | R51: M03/v001; цена не перепроверялась в M09
A52: A08 | B52: ME-29 | C52: Harken Hydro 2 | D52: Hydro 2 | E52: См. исходную карточку M03 | G52: 2026-09-11 | H52: EUR | J52: RFQ_REQUIRED | M52: шт | N52: 30л,2мотора24V4kW; стандартная помпа15л/мин140бар. Не доказана пригодность для подруливающих; не назначать резервное питание от6АКБ дорасчёта тока. | O52: Исходные ограничения M03 сохранены | P52: RFQ_REQUIRED_THRUSTER_CAPABILITY_OPEN | Q52: PUBLIC_PRICE_NOT_KP | R52: M03/v001; цена не перепроверялась в M09
A53: A09 | B53: ME-18 | C53: Parker Racor 75500MAXM30 | D53: 75500MAXM30 | E53: См. исходную карточку M03 | F53: https://racorshop.de/product/racor-75500maxm30-turbine-filter-marine/ | G53: 2026-09-11 | H53: EUR | I53: 2199.90 | J53: GROSS_RATE_VERIFIED | K53: 19 | L53: 1848.66 | M53: шт | N53: Root open2612.00gross/19%=2194.96NET; повторное открытие независимым агентом2199.90gross/19%=1848.66NET. Принято последнее наблюдение, расхождение сохранено; подтвердить цену до сравнения. Дуплексный узел, микроны/расход одной ветви под двигатель. | O53: Исходные ограничения M03 сохранены | P53: PRICE_VARIATION_RECONFIRM_TECH_OPEN | Q53: PUBLIC_PRICE_NOT_KP | R53: M03/v001; цена не перепроверялась в M09
A54: A10 | B54: ME-19 | C54: Vetus FTR330/32 | D54: FTR330/32 | E54: См. исходную карточку M03 | F54: https://www.vetus-shop.com/vetus-raw-water-strainer-type-330-and21632mm-p-1026.html | G54: 2026-09-11 | H54: GBP | I54: 81.67 | J54: NET_EXPLICIT | L54: 95.06 | M54: шт | N54: Типоразмер32мм только ориентир; диаметр и положение относительно ватерлинии по выбранному агрегату. | O54: Исходные ограничения M03 сохранены | P54: UNIT_BENCHMARK_TECH_OPEN | Q54: PUBLIC_PRICE_NOT_KP | R54: M03/v001; цена не перепроверялась в M09 | S54: 2026-09-10 | T54: 0.85915
A55: A11 | B55: ME-19 | C55: Vetus FTR33032M | D55: FTR33032M | E55: См. исходную карточку M03 | F55: https://www.mediawinkel.eu/nl/heavy-duty-waterfilter-32-mm.html | G55: 2026-09-11 | H55: EUR | I55: 164.46 | J55: NET_EXPLICIT | L55: 164.46 | M55: шт | N55: NET явно exclusiefBTW; усиленная версия с металлической крышкой. Сравнение с FTR330/32 требует одинаковых давления/установочного положения. | O55: Исходные ограничения M03 сохранены | P55: UNIT_BENCHMARK_TECH_OPEN | Q55: PUBLIC_PRICE_NOT_KP | R55: M03/v001; цена не перепроверялась в M09
A56: A12 | B56: ME-20 | C56: Rule 2000 GPH / model12 /24V | D56: 2000 GPH / model12 /24V | E56: См. исходную карточку M03 | F56: https://www.mackengineering.co.uk/rule-2000-gph-bilge-pump-24v.html | G56: 2026-09-11 | H56: GBP | I56: 107.24 | J56: NET_EXPLICIT | L56: 124.82 | M56: шт | N56: Габариты из официальной таблицы, у дилера155×105 отличаются; сверить ревизию. Не вся система осушения; поплавок/сигнализация отдельно. | O56: Исходные ограничения M03 сохранены | P56: UNIT_BENCHMARK_TECH_OPEN | Q56: PUBLIC_PRICE_NOT_KP | R56: M03/v001; цена не перепроверялась в M09 | S56: 2026-09-10 | T56: 0.85915
A57: A13 | B57: ME-20 | C57: Whale Gusher Urchin BP9005 | D57: Gusher Urchin BP9005 | E57: См. исходную карточку M03 | F57: https://www.mackengineering.co.uk/bp9005-whale-gusher-urchin-hand-pump.html | G57: 2026-09-11 | H57: GBP | I57: 55.10 | J57: NET_EXPLICIT | L57: 64.13 | M57: шт | N57: Ориентир цены ручного насоса; не назначенный главный аварийный насос67ft, расход/напор/доступ проверить. | O57: Исходные ограничения M03 сохранены | P57: UNIT_BENCHMARK_TECH_OPEN | Q57: PUBLIC_PRICE_NOT_KP | R57: M03/v001; цена не перепроверялась в M09 | S57: 2026-09-10 | T57: 0.85915
A58: A14 | B58: ME-20 | C58: Rule 32ALA /24V | D58: 32ALA /24V | E58: См. исходную карточку M03 | F58: https://www.mackengineering.co.uk/rule-2000-gph-bilge-pump-24v.html | G58: 2026-09-11 | H58: GBP | I58: 73.19 | J58: NET_EXPLICIT | L58: 85.19 | M58: шт | N58: Цена связанного товара открытой карточки; состав сигнализации и число отсеков открыты. | O58: Исходные ограничения M03 сохранены | P58: UNIT_BENCHMARK_TECH_OPEN | Q58: PUBLIC_PRICE_NOT_KP | R58: M03/v001; цена не перепроверялась в M09 | S58: 2026-09-10 | T58: 0.85915
A59: A15 | B59: ME-22 | C59: Jabsco 35770-0094 /24V | D59: 35770-0094 /24V | E59: См. исходную карточку M03 | F59: https://www.mackengineering.co.uk/35770-0094-24v-flexmount-blower.html | G59: 2026-09-11 | H59: GBP | I59: 224.42 | J59: SEARCH_ONLY_NET_CLAIM | M59: шт | N59: Поиск224.42exVAT, открытиеchallenge. Раздел дилера предупреждаетhold EU compliance. NET поле пусто; не считать доступным. Официально7м³/мин свободныйрасход, требуемыйнапорнепроверен. | O59: Исходные ограничения M03 сохранены | P59: PRICE_NOT_ADMITTED_AVAILABILITY_HOLD | Q59: PUBLIC_PRICE_NOT_KP | R59: M03/v001; цена не перепроверялась в M09 | S59: 2026-09-10 | T59: 0.85915
A60: A16 | B60: ME-23 | C60: Marco UP3/OIL 16402013 /24V | D60: UP3/OIL 16402013 /24V | E60: См. исходную карточку M03 | F60: https://www.mackengineering.co.uk/marco-up3-oil-pump-24v.html | G60: 2026-09-11 | H60: GBP | I60: 162.00 | J60: NET_EXPLICIT | L60: 188.56 | M60: шт | N60: Только насос; коллектор3агрегатов,шланги,поддоны,свет и автоматика не включены. | O60: Исходные ограничения M03 сохранены | P60: UNIT_BENCHMARK_TECH_OPEN | Q60: PUBLIC_PRICE_NOT_KP | R60: M03/v001; цена не перепроверялась в M09 | S60: 2026-09-10 | T60: 0.85915
A61: A17 | B61: ME-24 | C61: Vetus SENSOR320 | D61: SENSOR320 | E61: См. исходную карточку M03 | F61: https://www.vetus-shop.com/vetus-fuel-tank-quickfit-diesel-40-litre-8mm-p-1786.html | G61: 2026-09-11 | H61: GBP | I61: 61.67 | J61: NET_EXPLICIT | L61: 71.78 | M61: шт | N61: Длина320мм исследовательская; не утверждена глубина/число танков. Цена связанного товара, отдельный индикатор не включён. | O61: Исходные ограничения M03 сохранены | P61: UNIT_BENCHMARK_TECH_OPEN | Q61: PUBLIC_PRICE_NOT_KP | R61: M03/v001; цена не перепроверялась в M09 | S61: 2026-09-10 | T61: 0.85915
A62: A18 | B62: ME-24 | C62: Vetus SENSORA | D62: SENSORA | E62: См. исходную карточку M03 | F62: https://www.vetus-shop.com/vetus-fuel-tank-quickfit-diesel-40-litre-8mm-p-1786.html | G62: 2026-09-11 | H62: GBP | I62: 161.25 | J62: NET_EXPLICIT | L62: 187.69 | M62: шт | N62: Ультразвуковой аналоговый датчик; работа в конкретном танке и интерфейс подлежат проверке. Не цена танка. | O62: Исходные ограничения M03 сохранены | P62: UNIT_BENCHMARK_TECH_OPEN | Q62: PUBLIC_PRICE_NOT_KP | R62: M03/v001; цена не перепроверялась в M09 | S62: 2026-09-10 | T62: 0.85915
A63: A19 | B63: ME-25 | C63: Jabsco 18590-2094 /24V | D63: 18590-2094 /24V | E63: См. исходную карточку M03 | F63: https://www.cactusnav.com/jabsco-macerator-pump-p-37922.html | G63: 2026-09-11 | H63: GBP | I63: 141.63 | J63: NET_EXPLICIT | L63: 164.85 | M63: шт | N63: 24V; только насос сточного танка. Пересечение с комплектом туалета проверять; число танков не назначено. | O63: Исходные ограничения M03 сохранены | P63: UNIT_BENCHMARK_TECH_OPEN | Q63: PUBLIC_PRICE_NOT_KP | R63: M03/v001; цена не перепроверялась в M09 | S63: 2026-09-10 | T63: 0.85915
A64: A20 | B64: ME-21 | C64: Fireboy MA series 31.620.55 | D64: MA series 31.620.55 | E64: См. исходную карточку M03 | F64: https://www.oltrevela.com/en/31-620-55-fireboy-ma-series-automatic-manual-fire-extinguisher-13-4-kg-for-engine-rooms-and-motor-compartments-up-to-51m-uscg-and-iso-rina-approved-fireboy-4 | G64: 2026-09-11 | H64: EUR | I64: 1950.00 | J64: SEARCH_ONLY_NET_CLAIM | M64: шт | N64: Поиск1950NET, открытиеошибка. Заголовок51м³, таблица15.6м³ противоречат; модель/заряд не выбраны. Нельзя уменьшать заряд ради габарита. Отключение двигателей/вентиляции и ручнойпуск по отдельномуBOM. | O64: Исходные ограничения M03 сохранены | P64: PRICE_NOT_ADMITTED_VOLUME_AND_VARIANT_OPEN | Q64: PUBLIC_PRICE_NOT_KP | R64: M03/v001; цена не перепроверялась в M09
A65: A21 | B65: ME-26 | C65: Webasto Thermo Pro90 Marine 24V /9029943C | D65: Thermo Pro90 Marine 24V /9029943C | E65: См. исходную карточку M03 | F65: https://www.standkachel.nu/webasto-air-and-water-heaters-and/webasto-waterkachels-thermotop-spheros-dbw-valeo/webasto-marine-waterheaters-for-thermo-pro-90-24-volt/webasto-thermo-chiller--pro-90-marine-24-volt- | G65: 2026-09-11 | H65: EUR | I65: 2007.16 | J65: NET_LABEL_CONFLICT | M65: шт | N65: Открытая карточка маркирует2007.16NET, показывает2161.71sale/2543.18list: арифметика налоговойпары неясна. Неиспользоватьвранжировании; отоплениеещёопция, нечиллеркондиционирования. | O65: Исходные ограничения M03 сохранены | P65: OPTIONAL_PRICE_NOT_ADMITTED_TAX_CONFLICT | Q65: PUBLIC_PRICE_NOT_KP | R65: M03/v001; цена не перепроверялась в M09
A66: A22 | B66: ME-26 | C66: Webasto Thermo Pro90 Marine 24V /4111185A | D66: Thermo Pro90 Marine 24V /4111185A | E66: См. исходную карточку M03 | F66: https://www.butlertechnik.com/item/Webasto/Thermo-Pro-90-24v-Marine-Kit-With-Switch-91kW-4111185A/5G7 | G66: 2026-09-11 | H66: GBP | I66: 1995.49 | J66: NET_EXPLICIT | L66: 2322.63 | M66: шт | N66: 9.1kW только исследовательский класс; монтажный комплект с выключателем, остальные контуры и теплоотдающие устройства не включены. Не выбранное отопление и не чиллер. | O66: Исходные ограничения M03 сохранены | P66: OPTIONAL_UNIT_BENCHMARK_TECH_OPEN | Q66: PUBLIC_PRICE_NOT_KP | R66: M03/v001; цена не перепроверялась в M09 | S66: 2026-09-10 | T66: 0.85915
A67: YAN-E01 | B67: ME-01|ME-02 | C67: Yanmar 8LV320E-KMH50A + VC20 | D67: 8LV320E-KMH50A + VC20 | E67: См. исходную карточку M03 | F67: https://www.abma-sneek.nl/yanmar/engines-gears-drives/powerboat-engines?prod_id=650436 | G67: 2026-09-11 | H67: EUR | I67: 58842 | J67: incl BTW; rate not stated | M67: package | N67: 320 mhp / 235 kW at 3800 rpm; 1 engine + 1 KMH50A + VC20; manufacturer 2021 package dry mass 435+52 kg and envelope with gear/elbow; standard 12V starter; front belt PTO optional capacity unverified; dealer includes mounts/panel/wiring/fluids; installed propulsion scope incomplete | O67: Исходные ограничения M03 сохранены | P67: CONDITIONAL_DUTY_PTO_START_VOLTAGE; NET_RFQ_REQUIRED | Q67: PUBLIC_PRICE_NOT_KP | R67: M03/v001; цена не перепроверялась в M09
A68: YAN-E02 | B68: ME-01 | C68: Yanmar 6LPAM-STP2 bobtail (dealer); 6LPA-STP2 manufacturer | D68: 6LPAM-STP2 bobtail (dealer); 6LPA-STP2 manufacturer | E68: См. исходную карточку M03 | F68: https://useddieselenginecenter.nl/yanmar-6lpam-stp2-6-lpam-stp-2-bobtail | G68: 2026-09-11 | H68: EUR | I68: 21675 | J68: excl BTW; NET explicitly listed | L68: 21675.00 | M68: engine | N68: New per dealer; 315 mhp / 232 kW at 3800 rpm at 25C fuel; 299 mhp / 220 kW at 40C per 2017 spec; priced engine only excluding gear/panel/harness; proposed 1 KMH50A RFQ; engine-only dry mass; package envelope 1220x666x739 drawing vs1190 length table conflict; package dry mass459 kg; 12V starter; RCD1 only evidenced | O68: Исходные ограничения M03 сохранены | P68: CONDITIONAL_EU_NEWBUILD_CERT_DUTY_PTO_START_VOLTAGE; GEARBOX_NOT_PRICED | Q68: PUBLIC_PRICE_NOT_KP | R68: M03/v001; цена не перепроверялась в M09
A69: YAN-E03 | B69: ME-01|ME-02 | C69: Yanmar 6LY2M-WDT + YX-50S (proposed) | D69: 6LY2M-WDT + YX-50S (proposed) | E69: См. исходную карточку M03 | G69: 2026-09-11 | H69: EUR | J69: RFQ_REQUIRED | M69: package | N69: Current official card330 mhp /243 kW at3200 rpm; 1 engine +1 proposedYX-50S; package dry mass535+108kg; envelope with gear/high-riser elbow; optional24V electrical system official but exact starter/configuration RFQ; IMO Tier2 shown not EU RCD approval; PTO capacity unverified | O69: Исходные ограничения M03 сохранены | P69: RFQ_REQUIRED; CONDITIONAL_EU_NEWBUILD_CERT_DUTY_PTO | Q69: PUBLIC_PRICE_NOT_KP | R69: M03/v001; цена не перепроверялась в M09
A70: PAN-G01 | B70: ME-04|ME-19 | C70: Fischer Panda 12000x PMS JPC FP12000X | D70: 12000x PMS JPC FP12000X | E70: См. исходную карточку M03 | F70: https://www.jpcdirect.com/product/fischer-panda-12000x-generator/ | G70: 2026-09-11 | H70: GBP | I70: 16830.00 | J70: EXPLICIT_GROSS_NET_PAIR | K70: 20 | L70: 16324.27 | M70: package | N70: 50Hz230V not yet accepted as220V target;2generators retained;standard datasheet12Vstarter, priced24V SKU unconfirmed. 10.2kW/12kVA NOMINAL at20C;2026catalogue treats0.85 kVA factor as short inductive starting only;hot continuous useful output OPEN. Capsule dimensions exclude fittings and service space;ME19 partial factory cooling only. JPC H565/192kg metadata conflicts withOEM. Fuel pump/looms/control panel/capsule advertised;exact control revision and install kit RFQ. | O70: Исходные ограничения M03 сохранены | P70: MARKET_REFERENCE|START24V_OPEN|HOT_OUTPUT_OPEN|UK_IMPORT_OPEN | Q70: PUBLIC_PRICE_NOT_KP | R70: M03/v001; цена не перепроверялась в M09 | S70: 2026-09-10 | T70: 0.85915
A71: PAN-G02 | B71: ME-04|ME-19 | C71: Fischer Panda 12000x-230V PMS NautiRadar0028284 | D71: 12000x-230V PMS NautiRadar0028284 | E71: См. исходную карточку M03 | F71: https://www.nautiradar.pt/en/products/fischer-panda/panda-12000x-230v-pms-12kva-fixed-engine-speed-marine-generator | G71: 2026-09-11 | H71: EUR | I71: 17451.22 | J71: NET_EXPLICIT | L71: 17451.22 | M71: package | N71: 50Hz230V not yet accepted as220V target;2generators retained;standard datasheet12Vstarter, priced24V SKU unconfirmed. 10.2kW/12kVA NOMINAL at20C;2026catalogue treats0.85 kVA factor as short inductive starting only;hot continuous useful output OPEN. Capsule dimensions exclude fittings and service space;ME19 partial factory cooling only. SellerSKU0028284 vsOEMsheet0024660:exact revision must be tied to offer. EU seller does not yet prove EU dispatch/free-circulation/Poland delivery. | O71: Исходные ограничения M03 сохранены | P71: MARKET_REFERENCE|START24V_OPEN|HOT_OUTPUT_OPEN|SKU_REVISION_OPEN | Q71: PUBLIC_PRICE_NOT_KP | R71: M03/v001; цена не перепроверялась в M09
A72: PAN-G03 | B72: ME-04|ME-19 | C72: Fischer Panda 15000i-230V PMS NautiRadar0000182 | D72: 15000i-230V PMS NautiRadar0000182 | E72: См. исходную карточку M03 | F72: https://www.nautiradar.pt/en/products/fischer-panda/panda-15000i-230v-pms-12kw-230v-variable-speed-marine-generator | G72: 2026-09-11 | H72: EUR | I72: 20128.46 | J72: NET_EXPLICIT | L72: 20128.46 | M72: package | N72: Alternative model for same required useful output;not15kW.50Hz230V nominal12kW/15kVA;PMGi230V manual longterm12kW does not guarantee whole-set output at hot ambient;OEM20C engine reference.160kg capsule+16kg external inverter;dimensions capsule only;dealer162+16kg discrepancy. Inverter model/cooling/inclusion and24V starter RFQ.2gens retained;no automatic parallel operation. | O72: Исходные ограничения M03 сохранены | P72: MARKET_REFERENCE|START24V_OPEN|HOT_OUTPUT_OPEN|INVERTER_SCOPE_OPEN | Q72: PUBLIC_PRICE_NOT_KP | R72: M03/v001; цена не перепроверялась в M09
A73: AX01 | B73: ME-20 | C73: Rule 2000 / 24 V | D73: SVB 47726; Rule 12 | E73: SVB, Германия | F73: https://www.svb24.com/en/rule-heavy-duty-bilge-pump-2000-24v.html | G73: 2026-09-15 | H73: EUR | I73: 153.36 | J73: excl | L73: 153.36 | M73: шт. | N73: Погружная осушительная помпа. | O73: Поплавок, независимая аварийная сигнализация, щит, проводка, шланги, арматура, монтаж. | P73: 24 V; максимум 129 л/мин без подтверждения рабочего напора. Не доказана достаточность аварийного осушения VDS67. | Q73: Открыта конкретная карточка 15.09.2026: цена EUR, Excl. VAT. Наличие и доставка перепроверяются при заказе. | R73: deliverables/M09/v001/01_support/auxiliary/offers.json
A74: AX02 | B74: ME-20 | C74: Whale Gusher Urchin BP9005 | D74: SVB; WHBP9005 | E74: SVB, Германия | F74: https://www.svb24.com/en/whale-gusher-urchin-manual-bilge-pump-type-bp-9005.html | G74: 2026-09-15 | H74: EUR | I74: 89.87 | J74: excl | L74: 89.87 | M74: шт. | N74: Ручная помпа указанного исполнения. | O74: Шланги, приёмники, арматура и монтаж. | P74: Ручная. Компактный ценовой ориентир; не утверждена как главная аварийная помпа яхты 67 ft. | Q74: Открыта конкретная карточка 15.09.2026: цена EUR, Excl. VAT. Наличие и доставка перепроверяются при заказе. | R74: deliverables/M09/v001/01_support/auxiliary/offers.json
A75: AX03 | B75: ME-20 | C75: Whale Gusher 30 / surface mounting | D75: WHBP3000 | E75: SVB, Германия | F75: https://www.svb24.com/en/whale-gusher-30-manual-bilge-pump-surface-mounting.html | G75: 2026-09-15 | H75: EUR | I75: 783.15 | J75: excl | L75: 783.15 | M75: шт. | N75: Ручная помпа для поверхностного монтажа. | O75: Шланги, приёмники, арматура, монтаж и проверка доступа к рукоятке. | P75: Альтернатива ручной функции с другим исполнением; равная производительность с BP9005 не заявлена. | Q75: Открыта конкретная карточка 15.09.2026: цена EUR, Excl. VAT. Наличие и доставка перепроверяются при заказе. | R75: deliverables/M09/v001/01_support/auxiliary/offers.json
A76: AX04 | B76: ME-22 | C76: Ocean Technologies blower / 24 V / 1000 m³/h | D76: SVB 29771; 5500102624 | E76: SVB, Германия | F76: https://www.svb24.com/en/ocean-technologies-engine-compartment-blower-24-v-1000-m3-hour-150-mm-flex-mount.html | G76: 2026-09-15 | H76: EUR | I76: 189.87 | J76: excl | L76: 189.87 | M76: шт. | N76: Вентилятор 24 V. | O76: Воздуховоды, решётки, шумоглушение, противопожарное перекрытие и останов, питание, монтаж. | P76: 24 V; 1000 м³/ч — каталожный расход, не подтверждённый расход сети. Нужен баланс воздуха двигателя и двух генераторов. | Q76: Открыта конкретная карточка 15.09.2026: цена EUR, Excl. VAT. Наличие и доставка перепроверяются при заказе. | R76: deliverables/M09/v001/01_support/auxiliary/offers.json
A77: AX05 | B77: ME-23 | C77: Marco UP3 Oil Change Pump / 24 V | D77: SVB 52173 | E77: SVB, Германия | F77: https://www.svb24.com/en/marco-up3-electric-oil-change-pump.html | G77: 2026-09-15 | H77: EUR | I77: 168.03 | J77: excl | L77: 168.03 | M77: шт. | N77: Насос и две трубки 6/8 мм длиной 80 см. | O77: Стационарный коллектор двигателя/двух генераторов/редуктора, запорная арматура, длинные шланги, ёмкость отработки, защиты, монтаж. | P77: 24 V вариант: именно 168.03, не стартовая цена 12 V 166.34. Масло предварительно прогреть по карточке; вязкость и точки отбора уточнить. | Q77: Открыта конкретная карточка 15.09.2026: цена EUR, Excl. VAT. Наличие и доставка перепроверяются при заказе. | R77: deliverables/M09/v001/01_support/auxiliary/offers.json
A78: AX06 | B78: ME-25 | C78: Jabsco Type 12GPM waste water pump / 24 V | D78: SVB 13636; 18590-2094 | E78: SVB, Германия | F78: https://www.svb24.com/en/jabsco-type-12gpm-waste-water-pump-24v.html | G78: 2026-09-15 | H78: EUR | I78: 210.04 | J78: excl | L78: 210.04 | M78: шт. | N78: Насос macerator. | O78: Санприборы, танки, трубопроводы, арматура, управление, монтаж. | P78: 24 V. Проверить отсутствие повторного счёта насоса, включённого в сансистему; схема и допустимый сброс открыты. | Q78: Открыта конкретная карточка 15.09.2026: цена EUR, Excl. VAT. Наличие и доставка перепроверяются при заказе. | R78: deliverables/M09/v001/01_support/auxiliary/offers.json
A79: AX07 | B79: ME-20 | C79: Rule-A-Matic Plus float switch | D79: SVB 35958; 40A | E79: SVB, Германия | F79: https://www.svb24.com/en/rule-rule-a-matic-plus-automatic-float-switch.html | G79: 2026-09-15 | H79: EUR | I79: 54.58 | J79: excl | L79: 54.58 | M79: шт. | N79: Поплавковый выключатель с защитным кожухом. | O79: Помпа, независимый высокий уровень, щит, реле при необходимости, кабели и монтаж. | P79: 24 V: коммутационный ток проверить по паспорту конкретной помпы; пусковой ток не равен рабочему. Не полная автоматика осушения. | Q79: Открытая карточка 15.09.2026: EUR, Excl. VAT; вариант определён по напряжению/исполнению. | R79: deliverables/M09/v001/01_support/auxiliary/offers.json
A80: AX08 | B80: ME-20 | C80: Johnson Bilge Alert / 24 V | D80: SVB 47778; 34-72303-002 | E80: SVB, Германия | F80: https://www.svb24.com/en/johnson-pump-bilge-alert-high-water-alarm-with-ultima-switch.html | G80: 2026-09-15 | H80: EUR | I80: 97.44 | J80: excl | L80: 97.44 | M80: шт. | N80: Датчик высокого уровня, звуковая/световая сигнализация и органы тестирования по карточке. | O80: Многозонная интеграция, независимое питание, проводка, помпы и монтаж. | P80: 24 V вариант 97.44; 92.40 относится к 12 V. Сигнализацию не считать второй помпой или всей судовой автоматикой. | Q80: Открытая карточка 15.09.2026: EUR, Excl. VAT; вариант определён по напряжению/исполнению. | R80: deliverables/M09/v001/01_support/auxiliary/offers.json
