Workbook

Sheet 00_Итог
A1: Пакет | B1: Система | C1: Известная NET EUR | D1: НДС выделен / расчёт EUR | E1: Оценено с НДС EUR | F1: Строк без суммы | G1: Статус | H1: Примечание
A2: PK01 | B2: Ход яхты | C2: =IF(COUNT(01_Смета!J2,01_Смета!J27)=0,"",SUM(01_Смета!J2,01_Смета!J27)) | D2: =IF(COUNT(01_Смета!M2,01_Смета!M27)=0,"",SUM(01_Смета!M2,01_Смета!M27)) | E2: =IF(COUNT(01_Смета!O2,01_Смета!O27)=0,"",SUM(01_Смета!O2,01_Смета!O27)) -> 58842 | F2: 1 | G2: НЕПОЛНЫЙ | H2: Цена оборудования и компонента не закрывает установочный пакет
A3: PK02 | B3: Генерация | C3: =IF(COUNT(01_Смета!J3)=0,"",SUM(01_Смета!J3)) -> 34902.44 | D3: =IF(COUNT(01_Смета!M3)=0,"",SUM(01_Смета!M3)) -> 8027.56 | E3: =IF(COUNT(01_Смета!O3)=0,"",SUM(01_Смета!O3)) -> 42930 | F3: 0 | G3: НЕПОЛНЫЙ | H3: Цена оборудования и компонента не закрывает установочный пакет
A4: PK03 | B4: Электропитание | C4: =IF(COUNT(01_Смета!J4,01_Смета!J5,01_Смета!J28,01_Смета!J29)=0,"",SUM(01_Смета!J4,01_Смета!J5,01_Смета!J28,01_Смета!J29)) -> 1680.58 | D4: =IF(COUNT(01_Смета!M4,01_Смета!M5,01_Смета!M28,01_Смета!M29)=0,"",SUM(01_Смета!M4,01_Смета!M5,01_Смета!M28,01_Смета!M29)) -> 386.53 | E4: =IF(COUNT(01_Смета!O4,01_Смета!O5,01_Смета!O28,01_Смета!O29)=0,"",SUM(01_Смета!O4,01_Смета!O5,01_Смета!O28,01_Смета!O29)) -> 2067.11 | F4: 3 | G4: НЕПОЛНЫЙ | H4: Цена оборудования и компонента не закрывает установочный пакет
A5: PK04 | B5: АКБ и резервный пуск | C5: =IF(COUNT(01_Смета!J6,01_Смета!J7,01_Смета!J8,01_Смета!J9)=0,"",SUM(01_Смета!J6,01_Смета!J7,01_Смета!J8,01_Смета!J9)) -> 1608.42 | D5: =IF(COUNT(01_Смета!M6,01_Смета!M7,01_Смета!M8,01_Смета!M9)=0,"",SUM(01_Смета!M6,01_Смета!M7,01_Смета!M8,01_Смета!M9)) -> 369.94 | E5: =IF(COUNT(01_Смета!O6,01_Смета!O7,01_Смета!O8,01_Смета!O9)=0,"",SUM(01_Смета!O6,01_Смета!O7,01_Смета!O8,01_Смета!O9)) -> 1978.36 | F5: 3 | G5: НЕПОЛНЫЙ | H5: Цена оборудования и компонента не закрывает установочный пакет
A6: PK05 | B6: Пресная вода | C6: =IF(COUNT(01_Смета!J10,01_Смета!J11,01_Смета!J30)=0,"",SUM(01_Смета!J10,01_Смета!J11,01_Смета!J30)) -> 2145.75 | D6: =IF(COUNT(01_Смета!M10,01_Смета!M11,01_Смета!M30)=0,"",SUM(01_Смета!M10,01_Смета!M11,01_Смета!M30)) -> 493.53 | E6: =IF(COUNT(01_Смета!O10,01_Смета!O11,01_Смета!O30)=0,"",SUM(01_Смета!O10,01_Смета!O11,01_Смета!O30)) -> 2639.28 | F6: 1 | G6: НЕПОЛНЫЙ | H6: Цена оборудования и компонента не закрывает установочный пакет
A7: PK06 | B7: Опреснение | C7: =IF(COUNT(01_Смета!J12)=0,"",SUM(01_Смета!J12)) -> 10683.5 | D7: =IF(COUNT(01_Смета!M12)=0,"",SUM(01_Смета!M12)) -> 2457.21 | E7: =IF(COUNT(01_Смета!O12)=0,"",SUM(01_Смета!O12)) -> 13140.71 | F7: 0 | G7: НЕПОЛНЫЙ | H7: Цена оборудования и компонента не закрывает установочный пакет
A8: PK07 | B8: Горячая вода | C8: =IF(COUNT(01_Смета!J13)=0,"",SUM(01_Смета!J13)) | D8: =IF(COUNT(01_Смета!M13)=0,"",SUM(01_Смета!M13)) | E8: =IF(COUNT(01_Смета!O13)=0,"",SUM(01_Смета!O13)) | F8: 1 | G8: НЕПОЛНЫЙ | H8: Цена оборудования и компонента не закрывает установочный пакет
A9: PK08 | B9: Климат | C9: =IF(COUNT(01_Смета!J14,01_Смета!J15,01_Смета!J31)=0,"",SUM(01_Смета!J14,01_Смета!J15,01_Смета!J31)) -> 8310.6 | D9: =IF(COUNT(01_Смета!M14,01_Смета!M15,01_Смета!M31)=0,"",SUM(01_Смета!M14,01_Смета!M15,01_Смета!M31)) -> 1911.44 | E9: =IF(COUNT(01_Смета!O14,01_Смета!O15,01_Смета!O31)=0,"",SUM(01_Смета!O14,01_Смета!O15,01_Смета!O31)) -> 10222.04 | F9: 2 | G9: НЕПОЛНЫЙ | H9: Цена оборудования и компонента не закрывает установочный пакет
A10: PK09 | B10: Обеспечение МО | C10: =IF(COUNT(01_Смета!J16,01_Смета!J17,01_Смета!J18,01_Смета!J19)=0,"",SUM(01_Смета!J16,01_Смета!J17,01_Смета!J18,01_Смета!J19)) | D10: =IF(COUNT(01_Смета!M16,01_Смета!M17,01_Смета!M18,01_Смета!M19)=0,"",SUM(01_Смета!M16,01_Смета!M17,01_Смета!M18,01_Смета!M19)) | E10: =IF(COUNT(01_Смета!O16,01_Смета!O17,01_Смета!O18,01_Смета!O19)=0,"",SUM(01_Смета!O16,01_Смета!O17,01_Смета!O18,01_Смета!O19)) | F10: 4 | G10: НЕПОЛНЫЙ | H10: Цена оборудования и компонента не закрывает установочный пакет
A11: PK10 | B11: Аварийные системы | C11: =IF(COUNT(01_Смета!J20,01_Смета!J21,01_Смета!J22,01_Смета!J23)=0,"",SUM(01_Смета!J20,01_Смета!J21,01_Смета!J22,01_Смета!J23)) | D11: =IF(COUNT(01_Смета!M20,01_Смета!M21,01_Смета!M22,01_Смета!M23)=0,"",SUM(01_Смета!M20,01_Смета!M21,01_Смета!M22,01_Смета!M23)) | E11: =IF(COUNT(01_Смета!O20,01_Смета!O21,01_Смета!O22,01_Смета!O23)=0,"",SUM(01_Смета!O20,01_Смета!O21,01_Смета!O22,01_Смета!O23)) | F11: 4 | G11: НЕПОЛНЫЙ | H11: Цена оборудования и компонента не закрывает установочный пакет
A12: PK11 | B12: Танки и стоки | C12: =IF(COUNT(01_Смета!J24,01_Смета!J25)=0,"",SUM(01_Смета!J24,01_Смета!J25)) | D12: =IF(COUNT(01_Смета!M24,01_Смета!M25)=0,"",SUM(01_Смета!M24,01_Смета!M25)) | E12: =IF(COUNT(01_Смета!O24,01_Смета!O25)=0,"",SUM(01_Смета!O24,01_Смета!O25)) | F12: 2 | G12: НЕПОЛНЫЙ | H12: Цена оборудования и компонента не закрывает установочный пакет
A13: PK12 | B13: Гидравлика | C13: =IF(COUNT(01_Смета!J26)=0,"",SUM(01_Смета!J26)) | D13: =IF(COUNT(01_Смета!M26)=0,"",SUM(01_Смета!M26)) | E13: =IF(COUNT(01_Смета!O26)=0,"",SUM(01_Смета!O26)) | F13: 1 | G13: НЕПОЛНЫЙ | H13: Цена оборудования и компонента не закрывает установочный пакет
A14: ADD | B14: Монтаж и внешние затраты | C14: =IF(COUNT(01_Смета!J32,01_Смета!J33,01_Смета!J34,01_Смета!J35,01_Смета!J36,01_Смета!J37,01_Смета!J38,01_Смета!J39)=0,"",SUM(01_Смета!J32,01_Смета!J33,01_Смета!J34,01_Смета!J35,01_Смета!J36,01_Смета!J37,01_Смета!J38,01_Смета!J39)) | D14: =IF(COUNT(01_Смета!M32,01_Смета!M33,01_Смета!M34,01_Смета!M35,01_Смета!M36,01_Смета!M37,01_Смета!M38,01_Смета!M39)=0,"",SUM(01_Смета!M32,01_Смета!M33,01_Смета!M34,01_Смета!M35,01_Смета!M36,01_Смета!M37,01_Смета!M38,01_Смета!M39)) | E14: =IF(COUNT(01_Смета!O32,01_Смета!O33,01_Смета!O34,01_Смета!O35,01_Смета!O36,01_Смета!O37,01_Смета!O38,01_Смета!O39)=0,"",SUM(01_Смета!O32,01_Смета!O33,01_Смета!O34,01_Смета!O35,01_Смета!O36,01_Смета!O37,01_Смета!O38,01_Смета!O39)) | F14: 8 | G14: НЕПОЛНЫЙ | H14: Цена оборудования и компонента не закрывает установочный пакет
B15: ОЦЕНЁННАЯ ЧАСТЬ — НЕ ПОЛНАЯ СТОИМОСТЬ | C15: =SUM(C2:C14) -> 59331.29 | D15: =SUM(D2:D14) -> 13646.21 | E15: =SUM(E2:E14) -> 131819.5 | F15: 30
B16: Статус | C16: M07/v001 — выпуск текущей рабочей сметы по имеющимся сведениям. Не утверждённая УТВ, не заказ, не полный бюджет установленного МО.
B17: НДС в строках | C17: По уточнению владельца23% включены предварительно для известныхNET; SOURCE_GROSS уже сналогом, без повторного начисления. Налоговый вычет не применён.
B18: Смешанный gross | C18: Yanmar58842EUR включает налог неизвестнойставки. Его NET/VATневыделены. Общая оценённаяgrossсумма не единая унифицированная польская налоговая база и не график платежей.
B19: Открытые затраты | C19: Нулевых цен для неизвестного нет. Пустые количества/стоимости требуютданных; полныйитог незадан. Монтаж/материалы/трассы/таможня/ПНР не закрыты.
B20: Варианты | C20: Рабочая ветвьB сохранена изM03: Yanmar/Panda. Это не выбор закупки и не средний ценовойранг. A/C показаны в отдельном сравнении; альтернативы не складываются.
B21: Размещение | C21: По поручению владельца дальнейшаякомпоновка по сечениям проекта отдельно; G03не блокирует фиксациюэтогосостояниясметы и не подтверждает fit.
B22: Предыдущие версии | C22: U01/M01–M06/G03/EXP003 сохранены; сметные числа не перенесены в утверждённыйбюджет.
B23: Резерв | C23: Процент риска, накладных и установкиневыдуман. Неоценённыеработы не компенсированы произвольнойнадбавкой.

Sheet 01_Смета
A1: Строка | B1: Пакет | C1: Группы M01 | D1: Вид затрат | E1: Количество | F1: Ед. | G1: Наименование / исполнение | H1: Источник ID | I1: Цена NET EUR/ед. | J1: Стоимость NET EUR | K1: Основание НДС | L1: НДС % предварит. | M1: Сумма НДС EUR | N1: Исходный gross EUR/ед. | O1: Стоимость с НДС EUR | P1: Комплектность | Q1: Статус цены | R1: Примечание / исключения | S1: Прямая ссылка | T1: Цена в источнике | U1: Валюта источника
A2: PK01-B-L01 | B2: PK01 | C2: ME-01|ME-02 | D2: Оборудование / компонент | E2: 1 | F2: package | G2: Yanmar 8LV320E-KMH50A + VC20 | H2: YAN-E01 | J2: =IF(AND(ISNUMBER(E2),ISNUMBER(I2)),ROUND(E2*I2,2),"") | K2: SOURCE_GROSS | M2: =IF(AND(K2="PL23_ESTIMATE",ISNUMBER(J2),ISNUMBER(L2)),ROUND(J2*L2/100,2),"") | N2: 58842 | O2: =IF(K2="SOURCE_GROSS",IF(AND(ISNUMBER(E2),ISNUMBER(N2)),ROUND(E2*N2,2),""),IF(AND(ISNUMBER(J2),ISNUMBER(M2)),ROUND(J2+M2,2),"")) -> 58842 | P2: OPEN | Q2: NO_VERIFIED_NET | R2: 320 mhp / 235 kW at 3800 rpm; 1 engine + 1 KMH50A + VC20; manufacturer 2021 package dry mass 435+52 kg and envelope with gear/elbow; standard 12V starter; front belt PTO optional capacity unverified; dealer includes mounts/panel/wiring/fluids; installed propulsion scope incomplete | Исходный gross включает налог неизвестной ставки; без повторного23%. NET и выделенныйVAT открыты. | S2: https://www.abma-sneek.nl/yanmar/engines-gears-drives/powerboat-engines?prod_id=650436 | T2: 58842 | U2: EUR
A3: PK02-B-L01 | B3: PK02 | C3: ME-04|ME-19 | D3: Оборудование / компонент | E3: 2 | F3: package | G3: Fischer Panda 12000x-230V PMS NautiRadar0028284 | H3: PAN-G02 | I3: 17451.22 | J3: =IF(AND(ISNUMBER(E3),ISNUMBER(I3)),ROUND(E3*I3,2),"") -> 34902.44 | K3: PL23_ESTIMATE | L3: 23 | M3: =IF(AND(K3="PL23_ESTIMATE",ISNUMBER(J3),ISNUMBER(L3)),ROUND(J3*L3/100,2),"") -> 8027.56 | O3: =IF(K3="SOURCE_GROSS",IF(AND(ISNUMBER(E3),ISNUMBER(N3)),ROUND(E3*N3,2),""),IF(AND(ISNUMBER(J3),ISNUMBER(M3)),ROUND(J3+M3,2),"")) -> 42930 | P3: OPEN | Q3: OBSERVED_NET_CONDITIONAL_SCOPE | R3: 50Hz230V not yet accepted as220V target;2generators retained;standard datasheet12Vstarter, priced24V SKU unconfirmed. 10.2kW/12kVA NOMINAL at20C;2026catalogue treats0.85 kVA factor as short inductive starting only;hot continuous useful output OPEN. Capsule dimensions exclude fittings and service space;ME19 partial factory cooling only. SellerSKU0028284 vsOEMsheet0024660:exact revision must be tied to offer. EU seller does not yet prove EU dispatch/free-circulation/Poland delivery. | НДС23% предварительно по поручению владельца; не установленный режим сделки. | S3: https://www.nautiradar.pt/en/products/fischer-panda/panda-12000x-230v-pms-12kva-fixed-engine-speed-marine-generator | T3: 17451.22 | U3: EUR
A4: PK03-B-L01 | B4: PK03 | C4: ME-05 | D4: Оборудование / компонент | E4: 2 | F4: pcs | G4: Victron MultiPlus-II GX 24/3000/70-32 PMP242306000 | H4: EL-INV-B | I4: 840.29 | J4: =IF(AND(ISNUMBER(E4),ISNUMBER(I4)),ROUND(E4*I4,2),"") -> 1680.58 | K4: PL23_ESTIMATE | L4: 23 | M4: =IF(AND(K4="PL23_ESTIMATE",ISNUMBER(J4),ISNUMBER(L4)),ROUND(J4*L4/100,2),"") -> 386.53 | O4: =IF(K4="SOURCE_GROSS",IF(AND(ISNUMBER(E4),ISNUMBER(N4)),ROUND(E4*N4,2),""),IF(AND(ISNUMBER(J4),ISNUMBER(M4)),ROUND(J4+M4,2),"")) -> 2067.11 | P4: OPEN | Q4: OBSERVED_NET_CONDITIONAL_SCOPE | R4: 24 V; factory230 V;2400 W at25C/2200 W at40C;70 A. GX monitoring differs; two GX units not required by yacht specification. Current manual geometry differs from catalogue: confirm revision. | НДС23% предварительно по поручению владельца; не установленный режим сделки. | S4: https://www.svb.de/de/victron-wechselrichter-ladegeraet-multiplus-ii-gx-24-v-3000-va-70-a.html | T4: 999.95 | U4: EUR
A5: PK03-B-L02 | B5: PK03 | C5: ME-09 | D5: Оборудование / компонент | F5: pcs | G5: Mastervolt Mass GI3.5 88000355 | H5: EL-ISO-B | I5: 1008.36 | J5: =IF(AND(ISNUMBER(E5),ISNUMBER(I5)),ROUND(E5*I5,2),"") | K5: PL23_ESTIMATE | L5: 23 | M5: =IF(AND(K5="PL23_ESTIMATE",ISNUMBER(J5),ISNUMBER(L5)),ROUND(J5*L5/100,2),"") | O5: =IF(K5="SOURCE_GROSS",IF(AND(ISNUMBER(E5),ISNUMBER(N5)),ROUND(E5*N5,2),""),IF(AND(ISNUMBER(J5),ISNUMBER(M5)),ROUND(J5+M5,2),"")) | P5: OPEN | Q5: OBSERVED_NET_CONDITIONAL_SCOPE | R5: 3500 VA at230 V;16 A;HF technology;source IP23 supersedes dealer IP21. Not complete shore protection. | НДС23% предварительно по поручению владельца; не установленный режим сделки. | S5: https://www.svb24.com/en/mastervolt-mass-gi-3-5-isolation-transformer-16-a-3-5-kw.html | T5: 1008.36 | U5: EUR
A6: PK04-B-L01 | B6: PK04 | C6: ME-08 | D6: Оборудование / компонент | E6: 6 | F6: pcs | G6: Aquamot ALS12115 12V115Ah | H6: EL-BAT-B | I6: 268.07 | J6: =IF(AND(ISNUMBER(E6),ISNUMBER(I6)),ROUND(E6*I6,2),"") -> 1608.42 | K6: PL23_ESTIMATE | L6: 23 | M6: =IF(AND(K6="PL23_ESTIMATE",ISNUMBER(J6),ISNUMBER(L6)),ROUND(J6*L6/100,2),"") -> 369.94 | O6: =IF(K6="SOURCE_GROSS",IF(AND(ISNUMBER(E6),ISNUMBER(N6)),ROUND(E6*N6,2),""),IF(AND(ISNUMBER(J6),ISNUMBER(M6)),ROUND(J6+M6,2),"")) -> 1978.36 | P6: OPEN | Q6: OBSERVED_NET_CONDITIONAL_SCOPE | R6: AGM dealer description; legacy manufacturer sheet includes GEL construction wording, chemistry/revision confirmation needed. Body height214mm total220mm; dealer header6.4kg rejected in favour33.7kg technical sheet. | НДС23% предварительно по поручению владельца; не установленный режим сделки. | S6: https://www.nothnagel-marine.de/product_info.php?info=p3857_aquamot---power-battery--dc-battery-als12115-12v-115ah-agm-deep-cycle-battery.html&language=en | T6: 319 | U6: EUR
A7: PK04-B-L02 | B7: PK04 | C7: ME-07 | D7: Оборудование / компонент | E7: 1 | F7: pcs | G7: Пусковая АКБ двигателя — тип уточняется | H7: EL-OPEN-MAIN | J7: =IF(AND(ISNUMBER(E7),ISNUMBER(I7)),ROUND(E7*I7,2),"") | K7: PL23_ESTIMATE | L7: 23 | M7: =IF(AND(K7="PL23_ESTIMATE",ISNUMBER(J7),ISNUMBER(L7)),ROUND(J7*L7/100,2),"") | O7: =IF(K7="SOURCE_GROSS",IF(AND(ISNUMBER(E7),ISNUMBER(N7)),ROUND(E7*N7,2),""),IF(AND(ISNUMBER(J7),ISNUMBER(M7)),ROUND(J7+M7,2),"")) | P7: OPEN | Q7: NO_VERIFIED_NET | R7: 1 physical owner battery, capacity/voltage/chemistry unknown. Not automatically ER550 or service115Ah. | НДС23% предварительно по поручению владельца; не установленный режим сделки.
A8: PK04-B-L03 | B8: PK04 | C8: ME-27 | D8: Оборудование / компонент | E8: 2 | F8: pcs | G8: Пусковые АКБ генераторов — тип уточняется | H8: EL-OPEN-GEN | J8: =IF(AND(ISNUMBER(E8),ISNUMBER(I8)),ROUND(E8*I8,2),"") | K8: PL23_ESTIMATE | L8: 23 | M8: =IF(AND(K8="PL23_ESTIMATE",ISNUMBER(J8),ISNUMBER(L8)),ROUND(J8*L8/100,2),"") | O8: =IF(K8="SOURCE_GROSS",IF(AND(ISNUMBER(E8),ISNUMBER(N8)),ROUND(E8*N8,2),""),IF(AND(ISNUMBER(J8),ISNUMBER(M8)),ROUND(J8+M8,2),"")) | P8: OPEN | Q8: NO_VERIFIED_NET | R8: 2 physical owner batteries for2generators; capacity/voltage/CCA unknown; keep9total with6service+1main. No fictitious unit price. | НДС23% предварительно по поручению владельца; не установленный режим сделки.
A9: PK04-B-L04 | B9: PK04 | C9: ME-28 | D9: Оборудование / компонент | F9: pcs | G9: Blue Sea ML-RBS7702 24V | H9: EL-REM-A | I9: 239.45 | J9: =IF(AND(ISNUMBER(E9),ISNUMBER(I9)),ROUND(E9*I9,2),"") | K9: PL23_ESTIMATE | L9: 23 | M9: =IF(AND(K9="PL23_ESTIMATE",ISNUMBER(J9),ISNUMBER(L9)),ROUND(J9*L9/100,2),"") | O9: =IF(K9="SOURCE_GROSS",IF(AND(ISNUMBER(E9),ISNUMBER(N9)),ROUND(E9*N9,2),""),IF(AND(ISNUMBER(J9),ISNUMBER(M9)),ROUND(J9+M9,2),"")) | P9: OPEN | Q9: OBSERVED_NET_CONDITIONAL_SCOPE | R9: Manual override;24V coil;500A continuous product rating. Quantity, control failover, crank duty and24V live switching not qualified; dimensions drawing pending. | НДС23% предварительно по поручению владельца; не установленный режим сделки. | S9: https://www.svb24.com/en/blue-sea-hd-remote-battery-switch-24v.html | T9: 239.45 | U9: EUR
A10: PK05-B-L01 | B10: PK05 | C10: ME-11 | D10: Оборудование / компонент | E10: 1 | F10: шт | G10: Gianneschi EcoInox1 GE011 24V20L | H10: WC-DC-02 | I10: 1093.25 | J10: =IF(AND(ISNUMBER(E10),ISNUMBER(I10)),ROUND(E10*I10,2),"") -> 1093.25 | K10: PL23_ESTIMATE | L10: 23 | M10: =IF(AND(K10="PL23_ESTIMATE",ISNUMBER(J10),ISNUMBER(L10)),ROUND(J10*L10/100,2),"") -> 251.45 | O10: =IF(K10="SOURCE_GROSS",IF(AND(ISNUMBER(E10),ISNUMBER(N10)),ROUND(E10*N10,2),""),IF(AND(ISNUMBER(J10),ISNUMBER(M10)),ROUND(J10+M10,2),"")) -> 1344.7 | P10: OPEN | Q10: OBSERVED_NET_CONDITIONAL_SCOPE | R10: 45L/min max; common proposed15L/min at2bar needs curve. Includes20L tank/gauge/pressure switch; current OEM revision confirmation. | НДС23% предварительно по поручению владельца; не установленный режим сделки. | S10: https://www.comptoirnautique.com/groupe-d-eau-hydrophore/22947-gianneschi-groupe-d-eau-ecoinox-1-avec-reservoir-20l-24v-45lmin-7024.html | T10: 1311.9 | U10: EUR
A11: PK05-B-L02 | B11: PK05 | C11: ME-12 | D11: Оборудование / компонент | E11: 1 | F11: шт | G11: Gianneschi EcoInox2 GE017 230V20L | H11: WC-AC-02 | I11: 1052.5 | J11: =IF(AND(ISNUMBER(E11),ISNUMBER(I11)),ROUND(E11*I11,2),"") -> 1052.5 | K11: PL23_ESTIMATE | L11: 23 | M11: =IF(AND(K11="PL23_ESTIMATE",ISNUMBER(J11),ISNUMBER(L11)),ROUND(J11*L11/100,2),"") -> 242.08 | O11: =IF(K11="SOURCE_GROSS",IF(AND(ISNUMBER(E11),ISNUMBER(N11)),ROUND(E11*N11,2),""),IF(AND(ISNUMBER(J11),ISNUMBER(M11)),ROUND(J11+M11,2),"")) -> 1294.58 | P11: OPEN | Q11: OBSERVED_NET_CONDITIONAL_SCOPE | R11: Open page1052.50HT supersedes search992.50. Dealer max55L/min conflicts Kent45: curves required.0.45kW/20L; common15L/min at2bar not verified. | НДС23% предварительно по поручению владельца; не установленный режим сделки. | S11: https://www.tyboat.com/achat/P-57388-gianneschi-groupe-d-eau-ecoinox2-3-5-bars-0-45-kw-55-litres-minute-reservoir-20-litres-230-volts.html | T11: 1263 | U11: EUR
A12: PK06-B-L01 | B12: PK06 | C12: ME-13 | D12: Оборудование / компонент | E12: 1 | F12: шт | G12: Schenker ZEN150 — базовая цена «от», полный состав открыт | H12: WC-RO-02 | I12: 10683.5 | J12: =IF(AND(ISNUMBER(E12),ISNUMBER(I12)),ROUND(E12*I12,2),"") -> 10683.5 | K12: PL23_ESTIMATE | L12: 23 | M12: =IF(AND(K12="PL23_ESTIMATE",ISNUMBER(J12),ISNUMBER(L12)),ROUND(J12*L12/100,2),"") -> 2457.21 | O12: =IF(K12="SOURCE_GROSS",IF(AND(ISNUMBER(E12),ISNUMBER(N12)),ROUND(E12*N12,2),""),IF(AND(ISNUMBER(J12),ISNUMBER(M12)),ROUND(J12+M12,2),"")) -> 13140.71 | P12: OPEN | Q12: FROM_INCOMPLETE_CONFIGURATION | R12: Observed FROM base price; net is FROM benchmark only, NOT complete Touch/salinity/reject price. Nominal150L/h. Manufacturer230V±15% includes220V. Basic has no salinity; Touch optional; 24V variant permitted. Modular unit dimensions not total installed envelope. | НДС23% предварительно по поручению владельца; не установленный режим сделки. | S12: https://mar-nautic.com/schenker-watermaker-zen-150 | T12: 12820.2 | U12: EUR
A13: PK07-B-L01 | B13: PK07 | C13: ME-14 | D13: Оборудование / компонент | F13: шт | G13: Quick BX 40L1200W FLBX4012S000A00 | H13: WC-HW-02 | I13: 690.83 | J13: =IF(AND(ISNUMBER(E13),ISNUMBER(I13)),ROUND(E13*I13,2),"") | K13: PL23_ESTIMATE | L13: 23 | M13: =IF(AND(K13="PL23_ESTIMATE",ISNUMBER(J13),ISNUMBER(L13)),ROUND(J13*L13/100,2),"") | O13: =IF(K13="SOURCE_GROSS",IF(AND(ISNUMBER(E13),ISNUMBER(N13)),ROUND(E13*N13,2),""),IF(AND(ISNUMBER(J13),ISNUMBER(M13)),ROUND(J13+M13,2),"")) | P13: OPEN | Q13: OBSERVED_NET_CONDITIONAL_SCOPE | R13: 40L1200W220V plus engine heat exchanger common illustrative class; not owner size. Supplier dimensions/mass in research only pending official drawing. Thermostatic mixing equalise separately. | НДС23% предварительно по поручению владельца; не установленный режим сделки. | S13: https://www.tyboat.com/achat/P-8880-quick-chauffe-eau-cylindrique-bx-40-litres-220-volts-1200-watts.html | T13: 829 | U13: EUR
A14: PK08-B-L01 | B14: PK08 | C14: ME-15 | D14: Оборудование / компонент | E14: 2 | F14: шт | G14: Climma CWS Aquacontrol161RC 230/1/50 | H14: WC-CH-02 | I14: 4155.3 | J14: =IF(AND(ISNUMBER(E14),ISNUMBER(I14)),ROUND(E14*I14,2),"") -> 8310.6 | K14: PL23_ESTIMATE | L14: 23 | M14: =IF(AND(K14="PL23_ESTIMATE",ISNUMBER(J14),ISNUMBER(L14)),ROUND(J14*L14/100,2),"") -> 1911.44 | O14: =IF(K14="SOURCE_GROSS",IF(AND(ISNUMBER(E14),ISNUMBER(N14)),ROUND(E14*N14,2),""),IF(AND(ISNUMBER(J14),ISNUMBER(M14)),ROUND(J14+M14,2),"")) -> 10222.04 | P14: OPEN | Q14: OBSERVED_NET_CONDITIONAL_SCOPE | R14: 16000BTU/h each; reversecycle. Price recovered live requests HTTP200 after web429; local source text retained. OEM dimensions require authenticated download; old dealerPDF not promoted. | НДС23% предварительно по поручению владельца; не установленный режим сделки. | S14: https://mdislandsupply.com/en/climma/879-cws-aquacontrol-161-rc-230150-climma.html | T14: 4155.3 | U14: EUR
A15: PK08-B-L02 | B15: PK08 | C15: ME-16 | D15: Оборудование / компонент | F15: шт | G15: Frigomar NH150PS SWM0150230 | H15: WC-AUX-01 | I15: 663.25 | J15: =IF(AND(ISNUMBER(E15),ISNUMBER(I15)),ROUND(E15*I15,2),"") | K15: PL23_ESTIMATE | L15: 23 | M15: =IF(AND(K15="PL23_ESTIMATE",ISNUMBER(J15),ISNUMBER(L15)),ROUND(J15*L15/100,2),"") | O15: =IF(K15="SOURCE_GROSS",IF(AND(ISNUMBER(E15),ISNUMBER(N15)),ROUND(E15*N15,2),""),IF(AND(ISNUMBER(J15),ISNUMBER(M15)),ROUND(J15+M15,2),"")) | P15: OPEN | Q15: OBSERVED_NET_CONDITIONAL_SCOPE | R15: 230V50/60Hz magneticdrive; count and pump duty notfixed. No proof this model meets both seawater and chilledwater circuits; official detailed curve required. | НДС23% предварительно по поручению владельца; не установленный режим сделки. | S15: https://www.comptoirnautique.com/climatisation-bateau/91819-frigomar-pompes-a-entrainement-magnetique.html | T15: 795.9 | U15: EUR
A16: PK09-B-L01 | B16: PK09 | C16: ME-18 | D16: Оборудование / компонент | F16: шт | G16: Parker Racor 75500MAXM30 | H16: A09 | I16: 1848.66 | J16: =IF(AND(ISNUMBER(E16),ISNUMBER(I16)),ROUND(E16*I16,2),"") | K16: PL23_ESTIMATE | L16: 23 | M16: =IF(AND(K16="PL23_ESTIMATE",ISNUMBER(J16),ISNUMBER(L16)),ROUND(J16*L16/100,2),"") | O16: =IF(K16="SOURCE_GROSS",IF(AND(ISNUMBER(E16),ISNUMBER(N16)),ROUND(E16*N16,2),""),IF(AND(ISNUMBER(J16),ISNUMBER(M16)),ROUND(J16+M16,2),"")) | P16: OPEN | Q16: VARIABLE_PRICE_RECONFIRM | R16: Root open2612.00gross/19%=2194.96NET; повторное открытие независимым агентом2199.90gross/19%=1848.66NET. Принято последнее наблюдение, расхождение сохранено; подтвердить цену до сравнения. Дуплексный узел, микроны/расход одной ветви под двигатель. | НДС23% предварительно по поручению владельца; не установленный режим сделки. | S16: https://racorshop.de/product/racor-75500maxm30-turbine-filter-marine/ | T16: 2199.9 | U16: EUR
A17: PK09-B-L02 | B17: PK09 | C17: ME-19 | D17: Оборудование / компонент | F17: шт | G17: Vetus FTR33032M | H17: A11 | I17: 164.46 | J17: =IF(AND(ISNUMBER(E17),ISNUMBER(I17)),ROUND(E17*I17,2),"") | K17: PL23_ESTIMATE | L17: 23 | M17: =IF(AND(K17="PL23_ESTIMATE",ISNUMBER(J17),ISNUMBER(L17)),ROUND(J17*L17/100,2),"") | O17: =IF(K17="SOURCE_GROSS",IF(AND(ISNUMBER(E17),ISNUMBER(N17)),ROUND(E17*N17,2),""),IF(AND(ISNUMBER(J17),ISNUMBER(M17)),ROUND(J17+M17,2),"")) | P17: OPEN | Q17: OBSERVED_NET_CONDITIONAL_SCOPE | R17: NET явно exclusiefBTW; усиленная версия с металлической крышкой. Сравнение с FTR330/32 требует одинаковых давления/установочного положения. | НДС23% предварительно по поручению владельца; не установленный режим сделки. | S17: https://www.mediawinkel.eu/nl/heavy-duty-waterfilter-32-mm.html | T17: 164.46 | U17: EUR
A18: PK09-B-L03 | B18: PK09 | C18: ME-22 | D18: Оборудование / компонент | F18: шт | G18: Jabsco 35770-0094 /24V | H18: A15 | J18: =IF(AND(ISNUMBER(E18),ISNUMBER(I18)),ROUND(E18*I18,2),"") | K18: PL23_ESTIMATE | L18: 23 | M18: =IF(AND(K18="PL23_ESTIMATE",ISNUMBER(J18),ISNUMBER(L18)),ROUND(J18*L18/100,2),"") | O18: =IF(K18="SOURCE_GROSS",IF(AND(ISNUMBER(E18),ISNUMBER(N18)),ROUND(E18*N18,2),""),IF(AND(ISNUMBER(J18),ISNUMBER(M18)),ROUND(J18+M18,2),"")) | P18: OPEN | Q18: NO_VERIFIED_NET | R18: Поиск224.42exVAT, открытиеchallenge. Раздел дилера предупреждаетhold EU compliance. NET поле пусто; не считать доступным. Официально7м³/мин свободныйрасход, требуемыйнапорнепроверен. | НДС23% предварительно по поручению владельца; не установленный режим сделки. | S18: https://www.mackengineering.co.uk/35770-0094-24v-flexmount-blower.html | T18: 224.42 | U18: GBP
A19: PK09-B-L04 | B19: PK09 | C19: ME-23 | D19: Оборудование / компонент | F19: шт | G19: Marco UP3/OIL 16402013 /24V | H19: A16 | I19: 188.56 | J19: =IF(AND(ISNUMBER(E19),ISNUMBER(I19)),ROUND(E19*I19,2),"") | K19: PL23_ESTIMATE | L19: 23 | M19: =IF(AND(K19="PL23_ESTIMATE",ISNUMBER(J19),ISNUMBER(L19)),ROUND(J19*L19/100,2),"") | O19: =IF(K19="SOURCE_GROSS",IF(AND(ISNUMBER(E19),ISNUMBER(N19)),ROUND(E19*N19,2),""),IF(AND(ISNUMBER(J19),ISNUMBER(M19)),ROUND(J19+M19,2),"")) | P19: OPEN | Q19: OBSERVED_NET_CONDITIONAL_SCOPE | R19: Только насос; коллектор3агрегатов,шланги,поддоны,свет и автоматика не включены. | НДС23% предварительно по поручению владельца; не установленный режим сделки. | S19: https://www.mackengineering.co.uk/marco-up3-oil-pump-24v.html | T19: 162 | U19: GBP
A20: PK10-B-L01 | B20: PK10 | C20: ME-20 | D20: Оборудование / компонент | F20: шт | G20: Rule 2000 GPH / model12 /24V | H20: A12 | I20: 124.82 | J20: =IF(AND(ISNUMBER(E20),ISNUMBER(I20)),ROUND(E20*I20,2),"") | K20: PL23_ESTIMATE | L20: 23 | M20: =IF(AND(K20="PL23_ESTIMATE",ISNUMBER(J20),ISNUMBER(L20)),ROUND(J20*L20/100,2),"") | O20: =IF(K20="SOURCE_GROSS",IF(AND(ISNUMBER(E20),ISNUMBER(N20)),ROUND(E20*N20,2),""),IF(AND(ISNUMBER(J20),ISNUMBER(M20)),ROUND(J20+M20,2),"")) | P20: OPEN | Q20: OBSERVED_NET_CONDITIONAL_SCOPE | R20: Габариты из официальной таблицы, у дилера155×105 отличаются; сверить ревизию. Не вся система осушения; поплавок/сигнализация отдельно. | НДС23% предварительно по поручению владельца; не установленный режим сделки. | S20: https://www.mackengineering.co.uk/rule-2000-gph-bilge-pump-24v.html | T20: 107.24 | U20: GBP
A21: PK10-B-L02 | B21: PK10 | C21: ME-20 | D21: Оборудование / компонент | F21: шт | G21: Whale Gusher Urchin BP9005 | H21: A13 | I21: 64.13 | J21: =IF(AND(ISNUMBER(E21),ISNUMBER(I21)),ROUND(E21*I21,2),"") | K21: PL23_ESTIMATE | L21: 23 | M21: =IF(AND(K21="PL23_ESTIMATE",ISNUMBER(J21),ISNUMBER(L21)),ROUND(J21*L21/100,2),"") | O21: =IF(K21="SOURCE_GROSS",IF(AND(ISNUMBER(E21),ISNUMBER(N21)),ROUND(E21*N21,2),""),IF(AND(ISNUMBER(J21),ISNUMBER(M21)),ROUND(J21+M21,2),"")) | P21: OPEN | Q21: OBSERVED_NET_CONDITIONAL_SCOPE | R21: Ориентир цены ручного насоса; не назначенный главный аварийный насос67ft, расход/напор/доступ проверить. | НДС23% предварительно по поручению владельца; не установленный режим сделки. | S21: https://www.mackengineering.co.uk/bp9005-whale-gusher-urchin-hand-pump.html | T21: 55.1 | U21: GBP
A22: PK10-B-L03 | B22: PK10 | C22: ME-20 | D22: Оборудование / компонент | F22: шт | G22: Rule 32ALA /24V | H22: A14 | I22: 85.19 | J22: =IF(AND(ISNUMBER(E22),ISNUMBER(I22)),ROUND(E22*I22,2),"") | K22: PL23_ESTIMATE | L22: 23 | M22: =IF(AND(K22="PL23_ESTIMATE",ISNUMBER(J22),ISNUMBER(L22)),ROUND(J22*L22/100,2),"") | O22: =IF(K22="SOURCE_GROSS",IF(AND(ISNUMBER(E22),ISNUMBER(N22)),ROUND(E22*N22,2),""),IF(AND(ISNUMBER(J22),ISNUMBER(M22)),ROUND(J22+M22,2),"")) | P22: OPEN | Q22: OBSERVED_NET_CONDITIONAL_SCOPE | R22: Цена связанного товара открытой карточки; состав сигнализации и число отсеков открыты. | НДС23% предварительно по поручению владельца; не установленный режим сделки. | S22: https://www.mackengineering.co.uk/rule-2000-gph-bilge-pump-24v.html | T22: 73.19 | U22: GBP
A23: PK10-B-L04 | B23: PK10 | C23: ME-21 | D23: Оборудование / компонент | F23: шт | G23: Fireboy MA series 31.620.55 | H23: A20 | J23: =IF(AND(ISNUMBER(E23),ISNUMBER(I23)),ROUND(E23*I23,2),"") | K23: PL23_ESTIMATE | L23: 23 | M23: =IF(AND(K23="PL23_ESTIMATE",ISNUMBER(J23),ISNUMBER(L23)),ROUND(J23*L23/100,2),"") | O23: =IF(K23="SOURCE_GROSS",IF(AND(ISNUMBER(E23),ISNUMBER(N23)),ROUND(E23*N23,2),""),IF(AND(ISNUMBER(J23),ISNUMBER(M23)),ROUND(J23+M23,2),"")) | P23: OPEN | Q23: NO_VERIFIED_NET | R23: Поиск1950NET, открытиеошибка. Заголовок51м³, таблица15.6м³ противоречат; модель/заряд не выбраны. Нельзя уменьшать заряд ради габарита. Отключение двигателей/вентиляции и ручнойпуск по отдельномуBOM. | НДС23% предварительно по поручению владельца; не установленный режим сделки. | S23: https://www.oltrevela.com/en/31-620-55-fireboy-ma-series-automatic-manual-fire-extinguisher-13-4-kg-for-engine-rooms-and-motor-compartments-up-to-51m-uscg-and-iso-rina-approved-fireboy-4 | T23: 1950 | U23: EUR
A24: PK11-B-L01 | B24: PK11 | C24: ME-24 | D24: Оборудование / компонент | F24: шт | G24: Vetus SENSORA | H24: A18 | I24: 187.69 | J24: =IF(AND(ISNUMBER(E24),ISNUMBER(I24)),ROUND(E24*I24,2),"") | K24: PL23_ESTIMATE | L24: 23 | M24: =IF(AND(K24="PL23_ESTIMATE",ISNUMBER(J24),ISNUMBER(L24)),ROUND(J24*L24/100,2),"") | O24: =IF(K24="SOURCE_GROSS",IF(AND(ISNUMBER(E24),ISNUMBER(N24)),ROUND(E24*N24,2),""),IF(AND(ISNUMBER(J24),ISNUMBER(M24)),ROUND(J24+M24,2),"")) | P24: OPEN | Q24: OBSERVED_NET_CONDITIONAL_SCOPE | R24: Ультразвуковой аналоговый датчик; работа в конкретном танке и интерфейс подлежат проверке. Не цена танка. | НДС23% предварительно по поручению владельца; не установленный режим сделки. | S24: https://www.vetus-shop.com/vetus-fuel-tank-quickfit-diesel-40-litre-8mm-p-1786.html | T24: 161.25 | U24: GBP
A25: PK11-B-L02 | B25: PK11 | C25: ME-25 | D25: Оборудование / компонент | F25: шт | G25: Jabsco 18590-2094 /24V | H25: A19 | I25: 164.85 | J25: =IF(AND(ISNUMBER(E25),ISNUMBER(I25)),ROUND(E25*I25,2),"") | K25: PL23_ESTIMATE | L25: 23 | M25: =IF(AND(K25="PL23_ESTIMATE",ISNUMBER(J25),ISNUMBER(L25)),ROUND(J25*L25/100,2),"") | O25: =IF(K25="SOURCE_GROSS",IF(AND(ISNUMBER(E25),ISNUMBER(N25)),ROUND(E25*N25,2),""),IF(AND(ISNUMBER(J25),ISNUMBER(M25)),ROUND(J25+M25,2),"")) | P25: OPEN | Q25: OBSERVED_NET_CONDITIONAL_SCOPE | R25: 24V; только насос сточного танка. Пересечение с комплектом туалета проверять; число танков не назначено. | НДС23% предварительно по поручению владельца; не установленный режим сделки. | S25: https://www.cactusnav.com/jabsco-macerator-pump-p-37922.html | T25: 141.63 | U25: GBP
A26: PK12-B-L01 | B26: PK12 | C26: ME-29 | D26: Оборудование / компонент | F26: шт | G26: Sleipner Load-sensing system / bulkhead tank 40L | H26: A07 | J26: =IF(AND(ISNUMBER(E26),ISNUMBER(I26)),ROUND(E26*I26,2),"") | K26: PL23_ESTIMATE | L26: 23 | M26: =IF(AND(K26="PL23_ESTIMATE",ISNUMBER(J26),ISNUMBER(L26)),ROUND(J26*L26/100,2),"") | O26: =IF(K26="SOURCE_GROSS",IF(AND(ISNUMBER(E26),ISNUMBER(N26)),ROUND(E26*N26,2),""),IF(AND(ISNUMBER(J26),ISNUMBER(M26)),ROUND(J26+M26,2),"")) | P26: OPEN | Q26: NO_VERIFIED_NET | R26: Справочный габарит настенного танк-модуля из каталога2020; с блоком одного подруливающего, без всей установки. Ещё100мм для замены фильтра. Нужны текущийCAD и расчёт всех потребителей. | НДС23% предварительно по поручению владельца; не установленный режим сделки. | U26: EUR
A27: OPEN-ME-03 | B27: PK01 | C27: ME-03 | D27: Неоценённая функция | G27: Муфта, опоры, упорный узел и элементы валопровода | H27: M01/ME-03 | J27: =IF(AND(ISNUMBER(E27),ISNUMBER(I27)),ROUND(E27*I27,2),"") | K27: PL23_ESTIMATE | L27: 23 | M27: =IF(AND(K27="PL23_ESTIMATE",ISNUMBER(J27),ISNUMBER(L27)),ROUND(J27*L27/100,2),"") | O27: =IF(K27="SOURCE_GROSS",IF(AND(ISNUMBER(E27),ISNUMBER(N27)),ROUND(E27*N27,2),""),IF(AND(ISNUMBER(J27),ISNUMBER(M27)),ROUND(J27+M27,2),"")) | P27: OPEN | Q27: NO_PRICE | R27: Функциональная линия одна; числа подшипников/опор/уплотнений и комплектность не установлены | Резервсостава,неповтор комплектных деталей; количествоаппаратов не назначено.
A28: OPEN-ME-06 | B28: PK03 | C28: ME-06 | D28: Неоценённая функция | E28: 1 | F28: канал | G28: Независимое инверторное питание AC насоса пресной воды | H28: M01/ME-06 | J28: =IF(AND(ISNUMBER(E28),ISNUMBER(I28)),ROUND(E28*I28,2),"") | K28: PL23_ESTIMATE | L28: 23 | M28: =IF(AND(K28="PL23_ESTIMATE",ISNUMBER(J28),ISNUMBER(L28)),ROUND(J28*L28/100,2),"") | O28: =IF(K28="SOURCE_GROSS",IF(AND(ISNUMBER(E28),ISNUMBER(N28)),ROUND(E28*N28,2),""),IF(AND(ISNUMBER(J28),ISNUMBER(M28)),ROUND(J28+M28,2),"")) | P28: OPEN | Q28: NO_PRICE | R28: РеестрO02 предлагает1 отдельный инвертор; brief допускает отдельное либо изолированное исполнение. Аппаратное исполнение выбрать одинаково для3вариантов | Резервсостава,неповтор комплектных деталей; количествоаппаратов не назначено.
A29: OPEN-ME-10 | B29: PK03 | C29: ME-10 | D29: Неоценённая функция | G29: Распределение AC/DC, переключение источников, зарядная и защитная автоматика | H29: M01/ME-10 | J29: =IF(AND(ISNUMBER(E29),ISNUMBER(I29)),ROUND(E29*I29,2),"") | K29: PL23_ESTIMATE | L29: 23 | M29: =IF(AND(K29="PL23_ESTIMATE",ISNUMBER(J29),ISNUMBER(L29)),ROUND(J29*L29/100,2),"") | O29: =IF(K29="SOURCE_GROSS",IF(AND(ISNUMBER(E29),ISNUMBER(N29)),ROUND(E29*N29,2),""),IF(AND(ISNUMBER(J29),ISNUMBER(M29)),ROUND(J29+M29,2),"")) | P29: OPEN | Q29: NO_PRICE | R29: Состав щитов/аппаратов/датчиков по однолинейной схеме; штатное включение в инверторы/генераторы не считать дважды | Резервсостава,неповтор комплектных деталей; количествоаппаратов не назначено.
A30: OPEN-ME-17 | B30: PK05 | C30: ME-17 | D30: Неоценённая функция | G30: Гидроаккумуляторы, коллекторы, фильтры, клапаны и рециркуляция ГВС | H30: M01/ME-17 | J30: =IF(AND(ISNUMBER(E30),ISNUMBER(I30)),ROUND(E30*I30,2),"") | K30: PL23_ESTIMATE | L30: 23 | M30: =IF(AND(K30="PL23_ESTIMATE",ISNUMBER(J30),ISNUMBER(L30)),ROUND(J30*L30/100,2),"") | O30: =IF(K30="SOURCE_GROSS",IF(AND(ISNUMBER(E30),ISNUMBER(N30)),ROUND(E30*N30,2),""),IF(AND(ISNUMBER(J30),ISNUMBER(M30)),ROUND(J30+M30,2),"")) | P30: OPEN | Q30: NO_PRICE | R30: Разделить комплектные и внешние детали; количество по P&ID, рециркуляция по необходимости | Резервсостава,неповтор комплектных деталей; количествоаппаратов не назначено.
A31: OPEN-ME-26 | B31: PK08 | C31: ME-26 | D31: Неоценённая функция | G31: Резервное водяное отопление | H31: M01/ME-26 | J31: =IF(AND(ISNUMBER(E31),ISNUMBER(I31)),ROUND(E31*I31,2),"") | K31: PL23_ESTIMATE | L31: 23 | M31: =IF(AND(K31="PL23_ESTIMATE",ISNUMBER(J31),ISNUMBER(L31)),ROUND(J31*L31/100,2),"") | O31: =IF(K31="SOURCE_GROSS",IF(AND(ISNUMBER(E31),ISNUMBER(N31)),ROUND(E31*N31,2),""),IF(AND(ISNUMBER(J31),ISNUMBER(M31)),ROUND(J31+M31,2),"")) | P31: CONDITIONAL | Q31: NO_PRICE | R31: Не обязательная покупка до решения; обратный цикл чиллеров и отдельное отопление не назначаются автоматически | Резервсостава,неповтор комплектных деталей; количествоаппаратов не назначено.
A32: GAP-01 | B32: ADD | D32: Работа / внешняя затрата | G32: Рабочее проектирование и интеграция МО | H32: M06/scope + office/cost-policy | J32: =IF(AND(ISNUMBER(E32),ISNUMBER(I32)),ROUND(E32*I32,2),"") | K32: PL23_ESTIMATE | L32: 23 | M32: =IF(AND(K32="PL23_ESTIMATE",ISNUMBER(J32),ISNUMBER(L32)),ROUND(J32*L32/100,2),"") | O32: =IF(K32="SOURCE_GROSS",IF(AND(ISNUMBER(E32),ISNUMBER(N32)),ROUND(E32*N32,2),""),IF(AND(ISNUMBER(J32),ISNUMBER(M32)),ROUND(J32+M32,2),"")) | P32: OPEN | Q32: NO_PRICE | R32: Чертежи фундаментов/трасс/систем; без общей архитектуры всей яхты
A33: GAP-02 | B33: ADD | D33: Работа / внешняя затрата | G33: Внешние трубопроводы, кабели и монтажные материалы | H33: M06/scope + office/cost-policy | J33: =IF(AND(ISNUMBER(E33),ISNUMBER(I33)),ROUND(E33*I33,2),"") | K33: PL23_ESTIMATE | L33: 23 | M33: =IF(AND(K33="PL23_ESTIMATE",ISNUMBER(J33),ISNUMBER(L33)),ROUND(J33*L33/100,2),"") | O33: =IF(K33="SOURCE_GROSS",IF(AND(ISNUMBER(E33),ISNUMBER(N33)),ROUND(E33*N33,2),""),IF(AND(ISNUMBER(J33),ISNUMBER(M33)),ROUND(J33+M33,2),"")) | P33: OPEN | Q33: NO_PRICE | R33: Только невключённые в поставку материалы: длины, диаметры, крепления и изоляция по проекту
A34: GAP-03 | B34: ADD | D34: Работа / внешняя затрата | G34: Изготовление фундаментов и локальных усилений | H34: M06/scope + office/cost-policy | J34: =IF(AND(ISNUMBER(E34),ISNUMBER(I34)),ROUND(E34*I34,2),"") | K34: PL23_ESTIMATE | L34: 23 | M34: =IF(AND(K34="PL23_ESTIMATE",ISNUMBER(J34),ISNUMBER(L34)),ROUND(J34*L34/100,2),"") | O34: =IF(K34="SOURCE_GROSS",IF(AND(ISNUMBER(E34),ISNUMBER(N34)),ROUND(E34*N34,2),""),IF(AND(ISNUMBER(J34),ISNUMBER(M34)),ROUND(J34+M34,2),"")) | P34: OPEN | Q34: NO_PRICE | R34: Внешние корпусные работы; не повтор заводских виброопор и корпусного бюджета
A35: GAP-04 | B35: ADD | D35: Работа / внешняя затрата | G35: Монтаж и центровка оборудования | H35: M06/scope + office/cost-policy | J35: =IF(AND(ISNUMBER(E35),ISNUMBER(I35)),ROUND(E35*I35,2),"") | K35: PL23_ESTIMATE | L35: 23 | M35: =IF(AND(K35="PL23_ESTIMATE",ISNUMBER(J35),ISNUMBER(L35)),ROUND(J35*L35/100,2),"") | O35: =IF(K35="SOURCE_GROSS",IF(AND(ISNUMBER(E35),ISNUMBER(N35)),ROUND(E35*N35,2),""),IF(AND(ISNUMBER(J35),ISNUMBER(M35)),ROUND(J35+M35,2),"")) | P35: OPEN | Q35: NO_PRICE | R35: Труд и оснастка; без уже включённого монтажа из будущих КП
A36: GAP-05 | B36: ADD | D36: Работа / внешняя затрата | G36: Настройка, пусконаладка и испытания МО | H36: M06/scope + office/cost-policy | J36: =IF(AND(ISNUMBER(E36),ISNUMBER(I36)),ROUND(E36*I36,2),"") | K36: PL23_ESTIMATE | L36: 23 | M36: =IF(AND(K36="PL23_ESTIMATE",ISNUMBER(J36),ISNUMBER(L36)),ROUND(J36*L36/100,2),"") | O36: =IF(K36="SOURCE_GROSS",IF(AND(ISNUMBER(E36),ISNUMBER(N36)),ROUND(E36*N36,2),""),IF(AND(ISNUMBER(J36),ISNUMBER(M36)),ROUND(J36+M36,2),"")) | P36: OPEN | Q36: NO_PRICE | R36: Системные/интеграционные испытания; не повтор заводских испытаний и общесудовой приёмки
A37: GAP-06 | B37: ADD | D37: Работа / внешняя затрата | G37: Доставка и страхование до верфи | H37: M06/scope + office/cost-policy | J37: =IF(AND(ISNUMBER(E37),ISNUMBER(I37)),ROUND(E37*I37,2),"") | K37: PL23_ESTIMATE | L37: 23 | M37: =IF(AND(K37="PL23_ESTIMATE",ISNUMBER(J37),ISNUMBER(L37)),ROUND(J37*L37/100,2),"") | O37: =IF(K37="SOURCE_GROSS",IF(AND(ISNUMBER(E37),ISNUMBER(N37)),ROUND(E37*N37,2),""),IF(AND(ISNUMBER(J37),ISNUMBER(M37)),ROUND(J37+M37,2),"")) | P37: OPEN | Q37: NO_PRICE | R37: Маршрут, местоотгрузки,масса/габариты; есливключеноКП — обоснованныйноль
A38: GAP-07 | B38: ADD | D38: Работа / внешняя затрата | G38: Пошлина и таможенное оформление | H38: M06/scope + office/cost-policy | J38: =IF(AND(ISNUMBER(E38),ISNUMBER(I38)),ROUND(E38*I38,2),"") | K38: TAX_REVIEW | M38: =IF(AND(K38="PL23_ESTIMATE",ISNUMBER(J38),ISNUMBER(L38)),ROUND(J38*L38/100,2),"") | O38: =IF(K38="SOURCE_GROSS",IF(AND(ISNUMBER(E38),ISNUMBER(N38)),ROUND(E38*N38,2),""),IF(AND(ISNUMBER(J38),ISNUMBER(M38)),ROUND(J38+M38,2),"")) | P38: OPEN | Q38: NO_PRICE | R38: Применимость по маршруту и происхождению; не автоматическое начисление; VATбаза уточняется
A39: GAP-08 | B39: ADD | D39: Работа / внешняя затрата | G39: Дополнительная установочная комплектность | H39: M06/scope + office/cost-policy | J39: =IF(AND(ISNUMBER(E39),ISNUMBER(I39)),ROUND(E39*I39,2),"") | K39: PL23_ESTIMATE | L39: 23 | M39: =IF(AND(K39="PL23_ESTIMATE",ISNUMBER(J39),ISNUMBER(L39)),ROUND(J39*L39/100,2),"") | O39: =IF(K39="SOURCE_GROSS",IF(AND(ISNUMBER(E39),ISNUMBER(N39)),ROUND(E39*N39,2),""),IF(AND(ISNUMBER(J39),ISNUMBER(M39)),ROUND(J39+M39,2),"")) | P39: OPEN | Q39: NO_PRICE | R39: Недостающие соединители,контроллеры,сервисные принадлежности послеM06; оплачиватьодинразпоBOM
G40: Известная оценённая часть, НЕ полный бюджет | J40: =SUM(J2:J39) -> 59331.29 | M40: =SUM(M2:M39) -> 13646.21 | O40: =SUM(O2:O39) -> 131819.5 | R40: NET и выделенныйVAT не включаютYanmarSOURCE_GROSS; суммаgrossсмешиваетPL23сценарий иценупродавцаснеизвестнойставкой. Остальныепустыезатраты сверхсуммы.

Sheet 02_Сравнение
A1: Пакет | B1: Система | C1: A известная NET | D1: A без оценки | E1: B известная NET | F1: B без оценки | G1: C известная NET | H1: C без оценки | I1: Условие
A2: PK01 | B2: Ход яхты | C2: 45977 | D2: 0 | F2: 1 | H2: 1 | I2: Только известная NETчасть; состав/налоги различны; неранжировать и нескладывать альтернативы
A3: PK02 | B3: Генерация | C3: 24893 | D3: 0 | E3: 34902.44 | F3: 0 | G3: 35858.24 | H3: 0 | I3: Только известная NETчасть; состав/налоги различны; неранжировать и нескладывать альтернативы
A4: PK03 | B4: Электропитание | C4: 1478.9 | D4: 1 | E4: 1680.58 | F4: 1 | G4: 2689 | H4: 1 | I4: Только известная NETчасть; состав/налоги различны; неранжировать и нескладывать альтернативы
A5: PK04 | B5: АКБ и резервный пуск | C5: 841.44 | D5: 3 | E5: 1608.42 | F5: 3 | G5: 1636.14 | H5: 3 | I5: Только известная NETчасть; состав/налоги различны; неранжировать и нескладывать альтернативы
A6: PK05 | B6: Пресная вода | C6: 1024.92 | D6: 1 | E6: 2145.75 | F6: 0 | H6: 2 | I6: Только известная NETчасть; состав/налоги различны; неранжировать и нескладывать альтернативы
A7: PK06 | B7: Опреснение | C7: 6335.29 | D7: 0 | E7: 10683.5 | F7: 0 | H7: 1 | I7: Только известная NETчасть; состав/налоги различны; неранжировать и нескладывать альтернативы
A8: PK07 | B8: Горячая вода | D8: 1 | F8: 1 | H8: 1 | I8: Только известная NETчасть; состав/налоги различны; неранжировать и нескладывать альтернативы
A9: PK08 | B9: Климат | C9: 7242 | D9: 1 | E9: 8310.6 | F9: 1 | H9: 2 | I9: Только известная NETчасть; состав/налоги различны; неранжировать и нескладывать альтернативы
A10: PK09 | B10: Обеспечение МО | D10: 4 | F10: 4 | H10: 4 | I10: Только известная NETчасть; состав/налоги различны; неранжировать и нескладывать альтернативы
A11: PK10 | B11: Аварийные системы | D11: 4 | F11: 4 | H11: 4 | I11: Только известная NETчасть; состав/налоги различны; неранжировать и нескладывать альтернативы
A12: PK11 | B12: Танки и стоки | D12: 2 | F12: 2 | H12: 2 | I12: Только известная NETчасть; состав/налоги различны; неранжировать и нескладывать альтернативы
A13: PK12 | B13: Гидравлика | D13: 5 | F13: 1 | H13: 1 | I13: Только известная NETчасть; состав/налоги различны; неранжировать и нескладывать альтернативы

Sheet 03_Источники
A1: candidate_id | B1: me_id | C1: category | D1: manufacturer | E1: model | F1: qty | G1: unit | H1: currency | I1: listed_price | J1: tax_basis | K1: tax_rate | L1: net_unit_price | M1: price_url | N1: spec_url | O1: length_mm | P1: width_mm | Q1: height_mm | R1: mass_kg | S1: technical_status | T1: scope_notes | U1: availability | V1: access_date | W1: price_class | X1: evidence_type | Y1: price_date | Z1: source_revision | AA1: eur_net_unit
A2: PROP-E01 | B2: ME-01|ME-02|ME-03 | C2: engine_gearbox | D2: Volvo Penta | E2: D4-300 I + HS68A | F2: 1 | G2: package | H2: EUR | I2: 44716 | J2: explicit HT; historical March 2023 | L2: 44716 | M2: https://www.dbmoteurs.fr/sites/default/files/Volvo-Penta-tarifs-prix-achat-moteurs-2023-DB-Moteurs-motorisation-marine-bateau-plaisance.pdf | N2: https://www.dbmoteurs.fr/sites/default/files/Moteur-Volvo-Penta-D4-270-300-320-fiche-commerciale-2021-47711815-en.pdf | R2: 580 | S2: HISTORICAL_NET_REFERENCE|RFQ_REQUIRED|DUTY_OPEN | T2: 300 metric hp crank / 289 prop shaft at3500rpm; R5; 24V option official but quoted configuration unspecified; HS68A ratio selection open; dimensions for HS85A must not be substituted; ME-03 partial only factory mounts where included: shaft/coupling/thrust unit quantities and price OPEN | U2: 2026 availability unknown | V2: 2026-09-11 | W2: HISTORICAL_NOT_CURRENT | X2: PUBLIC_PRICE_NOT_KP | Y2: 2023-03 | Z2: deliverables/M02/v001/01_support/all-candidates.csv | AA2: 44716
A3: PROP-E02 | B3: ME-01|ME-02|ME-03 | C3: engine_gearbox | D3: Volvo Penta | E3: D4-300 I + HS85A | F3: 1 | G3: package | H3: EUR | I3: 45977 | J3: explicit HT; historical March 2023 | L3: 45977 | M3: https://www.dbmoteurs.fr/sites/default/files/Volvo-Penta-tarifs-prix-achat-moteurs-2023-DB-Moteurs-motorisation-marine-bateau-plaisance.pdf | N3: https://www.dbmoteurs.fr/sites/default/files/Moteur-Volvo-Penta-D4-270-300-320-fiche-commerciale-2021-47711815-en.pdf | O3: 1234 | P3: 848 | Q3: 794 | R3: 605 | S3: HISTORICAL_NET_REFERENCE|RFQ_REQUIRED|DUTY_OPEN | T3: 300 metric hp crank / 289 prop shaft; 3500rpm R5; 24V option price open; ratio2.500. L=433+801 W=441+407 H=274+520 from drawing; excludes projecting lifting eye/service space; not installation GA; ME-03 partial only factory mounts where included: shaft/coupling/thrust unit quantities and price OPEN | U3: 2026 availability unknown | V3: 2026-09-11 | W3: HISTORICAL_NOT_CURRENT | X3: PUBLIC_PRICE_NOT_KP | Y3: 2023-03 | Z3: deliverables/M02/v001/01_support/all-candidates.csv | AA3: 45977
A4: PROP-E03 | B4: ME-01|ME-02|ME-03 | C4: engine_gearbox | D4: Volvo Penta | E4: D6-300 I + HS85A | F4: 1 | G4: package | H4: EUR | I4: 50146 | J4: explicit HT; historical March 2023 | L4: 50146 | M4: https://www.dbmoteurs.fr/sites/default/files/Volvo-Penta-tarifs-prix-achat-moteurs-2023-DB-Moteurs-motorisation-marine-bateau-plaisance.pdf | N4: https://www.dbmoteurs.fr/sites/default/files/Moteur-Volvo-Penta-D6-300-340-380-fiche-commerciale-brochure-2021-47711891-fr-dbmoteurs.pdf | O4: 1470 | P4: 848 | Q4: 794 | R4: 690 | S4: HISTORICAL_NET_REFERENCE|RFQ_REQUIRED|DUTY_OPEN | T4: 300 metric hp crank /289 prop shaft;3300rpm. 24V option price open; L=433+1037 W=441+407 H=274+520 drawing dimensions not installation/service envelope; lifting eye extends above dimension; ME-03 partial only factory mounts where included: shaft/coupling/thrust unit quantities and price OPEN | U4: 2026 availability unknown | V4: 2026-09-11 | W4: HISTORICAL_NOT_CURRENT | X4: PUBLIC_PRICE_NOT_KP | Y4: 2023-03 | Z4: deliverables/M02/v001/01_support/all-candidates.csv | AA4: 50146
A5: PROP-E04 | B5: ME-01|ME-02|ME-03 | C5: engine_gearbox | D5: FPT Industrial | E5: C90 410 rating D 300hp + gearbox RFQ | F5: 1 | G5: package | H5: EUR | J5: RFQ_REQUIRED | M5: https://www.etruck.fi/shop-1 | N5: https://www.fptindustrial.com/-/media/FPT/Brochures/Engines/MARINE/COMMERCIAL/Marine_Commercial_FR_2026.pdf?rev=-1 | O5: 1289 | P5: 861 | Q5: 973 | R5: 950 | S5: RFQ_REQUIRED|INCOMPLETE_PACKAGE|DUTY_COMPARISON_OPEN | T5: Official2026 220kW300hp@2000rpm ratingD heavy duty; gearbox unselected/unpriced; shown dimensions length to flywheel and mass ENGINE ONLY; not complete package envelope;24V option RFQ; ME-03 partial only factory mounts where included: shaft/coupling/thrust unit quantities and price OPEN | U5: No exact300hp package price found | V5: 2026-09-11 | W5: NO_VERIFIED_NET | X5: PUBLIC_PRICE_NOT_KP | Y5: UNKNOWN | Z5: deliverables/M02/v001/01_support/all-candidates.csv
A6: PROP-G01 | B6: ME-04|ME-19 | C6: generator | D6: Fischer Panda | E6: Panda12000x PMS | F6: 2 | G6: package | H6: GBP | I6: 16830 | J6: explicit inc vat/ex vat pair | K6: 20 | L6: 14025 | M6: https://www.jpcdirect.com/product/fischer-panda-12000x-generator/ | N6: https://www.onefischerpanda.com/marine/marine-generators/xseries-generators/panda-12000x-pms/ | O6: 705 | P6: 450 | Q6: 590 | R6: 195 | S6: CONDITIONAL_START_VOLTAGE|AC_COMPATIBILITY_OPEN|RATING_OPEN|UK_REFERENCE | T6: 12kVA10.2kW nominal; Manel continuous10.8kVA9.2kW;50Hz230V +/-3V;12V starter;capsule included spec; verify exactJPCSKU/manufacturer0024660 and installation accessories; UK import/logistics not included; ME-19 partial factory cooling only: external seawater/exhaust runs and installation OPEN; JPC revision conflict H565 / additional700x470x580 and192kg vs OEM705x450x590/195kg: exactSKU CAD RFQ; OEM values retained | U6: Available on back-order; qty2 and lead time RFQ | V6: 2026-09-11 | W6: OBSERVED_NET_CONDITIONAL_SCOPE | X6: PUBLIC_PRICE_NOT_KP | Y6: UNKNOWN | Z6: deliverables/M02/v001/01_support/all-candidates.csv | AA6: 16324.27
A7: PROP-G02 | B7: ME-04|ME-19 | C7: generator | D7: Kohler / Rehlko | E7: 12EFKOZD | F7: 2 | G7: package | H7: GBP | I7: 18484.56 | J7: explicit inc vat/ex vat pair | K7: 20 | L7: 15403.8 | M7: https://www.jpcdirect.com/product/kohler-12-kilowatt-generator/ | N7: https://techcomm.rehlko.com/techcomm/pdf/g2186.pdf | O7: 1064 | P7: 652.5 | Q7: 711 | R7: 385 | S7: CONDITIONAL_CONFIGURATION|AC_COMPATIBILITY_OPEN|RATING_OPEN|UK_REFERENCE | T7: Singlephase115/230V50Hz:12kW12kVA continuous140C rise;11/11continuous115C;10.5/10.5prime. Official12or24V; JPC exactstarter/shield revision RFQ. Official shield mass385dry398wet; dealer406kg conflict. No borrowing US24V price scope; ME-19 partial factory cooling only: external seawater/exhaust runs and installation OPEN | U7: Available on back-order | V7: 2026-09-11 | W7: OBSERVED_NET_CONDITIONAL_SCOPE | X7: PUBLIC_PRICE_NOT_KP | Y7: UNKNOWN | Z7: deliverables/M02/v001/01_support/all-candidates.csv | AA7: 17929.12
A8: PROP-G03 | B8: ME-04|ME-19 | C8: generator | D8: Volpi Tecno Energia | E8: Paguro12000V AP12023050M0 | F8: 2 | G8: package | H8: EUR | I8: 14935.8 | J8: direct page12446.50 +IVA; gross14935.80 labelled SK20% locale | K8: 20 | L8: 12446.5 | M8: https://www.manelservice.com/it/gruppi-elettrogeni-marini/3925-vte-paguro-12000-v-ap12023050m0.html | N8: https://www.volpitecno.com/portfolio/paguro-12000-v-10-kw-2000-%C3%B7-3000-g-1/ | O8: 770 | P8: 460 | Q8: 620 | R8: 180 | S8: CONDITIONAL_START_VOLTAGE|AC_COMPATIBILITY_OPEN|REVISION_OPEN | T8: 12kVA10kW continuous50Hz230V;12V starter;mass165capsule+15control electronics. Official dimensions capsule only; separate electronics footprint RFQ. Dealer/allpa dimensions/mass differ; exact SKU installationdrawing required. Published net directly not Polish VAT assumption; ME-19 partial factory cooling only: external seawater/exhaust runs and installation OPEN | U8: Manel Disponibile; qty2 and delivery date RFQ | V8: 2026-09-11 | W8: OBSERVED_NET_CONDITIONAL_SCOPE | X8: PUBLIC_PRICE_NOT_KP | Y8: UNKNOWN | Z8: deliverables/M02/v001/01_support/all-candidates.csv | AA8: 12446.5
A9: PROP-G04 | B9: ME-04|ME-19 | C9: generator | D9: Kohler / Rehlko | E9: 12EFKOZD24-SS | F9: 2 | G9: package | H9: USD | I9: 20165.6 | J9: not stated | M9: https://mmarineonline.com/products/kohler-marine-diesel-generator-24v-12efkozd-ss-50hz-with-sound-shield | N9: https://techcomm.rehlko.com/techcomm/pdf/g2186.pdf | O9: 1064 | P9: 652.5 | Q9: 711 | R9: 385 | S9: NO_NET|US_REFERENCE_ONLY|AC_COMPATIBILITY_OPEN|RATING_OPEN | T9: Alternative offer for G02 not fourthgenerator;24V plus shield explicitlySKU; tax/import/Poland availability unknown; price originalUSD noFX; ME-19 partial factory cooling only: external seawater/exhaust runs and installation OPEN | U9: Contradictory availability template; RFQ | V9: 2026-09-11 | W9: NO_VERIFIED_NET | X9: PUBLIC_PRICE_NOT_KP | Y9: UNKNOWN | Z9: deliverables/M02/v001/01_support/all-candidates.csv
A10: EL-INV-A | B10: ME-05 | C10: inverter_charger | D10: Victron | E10: MultiPlus-II 24/3000/70-32 PMP242305010 | F10: 2 | G10: pcs | H10: EUR | I10: 879.95 | J10: GROSS_RATE_CONFIRMED | K10: 19 | L10: 739.45 | M10: https://www.svb.de/de/victron-wechselrichter-ladegeraet-multiplus-ii-24-v-3000-va-70-a.html | N10: https://www.victronenergy.com/media/pg/MultiPlus-II_230V/en/technical-specifications-mp-ii-230v.html | O10: 141 | P10: 268 | Q10: 499 | R10: 19 | S10: CONDITIONAL_3KVA_REFERENCE | T10: 24 V input; factory 230 V. 3000 VA not 3000 W: 2400 W at25C/2200 W at40C; charger70 A. 2 devices architecture target, capacity unapproved. | U10: 1 listed in stock; second unconfirmed | V10: 2026-09-11 | W10: OBSERVED_NET_CONDITIONAL_SCOPE | X10: PUBLIC_PRICE_NOT_KP | Y10: UNKNOWN | Z10: deliverables/M02/v001/01_support/all-candidates.csv | AA10: 739.45
A11: EL-INV-B | B11: ME-05 | C11: inverter_charger | D11: Victron | E11: MultiPlus-II GX 24/3000/70-32 PMP242306000 | F11: 2 | G11: pcs | H11: EUR | I11: 999.95 | J11: GROSS_RATE_CONFIRMED | K11: 19 | L11: 840.29 | M11: https://www.svb.de/de/victron-wechselrichter-ladegeraet-multiplus-ii-gx-24-v-3000-va-70-a.html | N11: https://www.victronenergy.com/media/pg/MultiPlus-II_GX/en/technical-specifications-mp-ii-gx-230v.html | O11: 147 | P11: 275 | Q11: 506 | R11: 20 | S11: CONDITIONAL_3KVA_REFERENCE | T11: 24 V; factory230 V;2400 W at25C/2200 W at40C;70 A. GX monitoring differs; two GX units not required by yacht specification. Current manual geometry differs from catalogue: confirm revision. | U11: expected1-2weeks | V11: 2026-09-11 | W11: OBSERVED_NET_CONDITIONAL_SCOPE | X11: PUBLIC_PRICE_NOT_KP | Y11: UNKNOWN | Z11: deliverables/M02/v001/01_support/all-candidates.csv | AA11: 840.29
A12: EL-INV-C | B12: ME-05 | C12: inverter_charger | D12: Mastervolt | E12: CombiMaster 24/3000-60 230V 35023000 | F12: 2 | G12: pcs | H12: EUR | I12: 1599.96 | J12: GROSS_RATE_CONFIRMED | K12: 19 | L12: 1344.5 | M12: https://www.svb.de/de/mastervolt-wechselrichter-ladegeraet-combimaster-24-v-3000-va-60-a.html?question_sort=oldest | N12: https://www.mastervolt.com/products/combimaster/combimaster-24-3000-60-230-v/ | O12: 155 | P12: 284 | Q12: 448 | R12: 9.3 | S12: CONDITIONAL_3KVA_NOT_EQUAL_W | T12: 24 V; factory230 V;3000 VA/2600 W at40C;60 A charger;25 A transfer versus32 A Victron. Parallel operation not qualified. | U12: 1 listed in stock; second unconfirmed | V12: 2026-09-11 | W12: OBSERVED_NET_CONDITIONAL_SCOPE | X12: PUBLIC_PRICE_NOT_KP | Y12: UNKNOWN | Z12: deliverables/M02/v001/01_support/all-candidates.csv | AA12: 1344.5
A13: EL-ISO-A | B13: ME-09 | C13: isolation_transformer | D13: Victron | E13: 3600 ITR040362042 | G13: pcs | H13: EUR | I13: 436.93 | J13: NET_EXPLICIT | L13: 436.93 | M13: https://www.svb24.com/en/p/victron-isolation-transformer-3600-w-115-230-v.html | N13: https://www.victronenergy.com/upload/documents/Datasheet-Isolation-Transformers-EN.pdf | O13: 221 | P13: 258 | Q13: 362 | R13: 21.7 | S13: CONDITIONAL_UNIT_BENCHMARK_DIMENSIONS_DEALER | T13: 3.6 class; quantity and shore capacity unknown. Dimensions/mass from opened dealer data pending native drawing confirmation; no substitute of32A at115V for32A at230V. | U13: expected1-2weeks | V13: 2026-09-11 | W13: OBSERVED_NET_CONDITIONAL_SCOPE | X13: PUBLIC_PRICE_NOT_KP | Y13: UNKNOWN | Z13: deliverables/M02/v001/01_support/all-candidates.csv | AA13: 436.93
A14: EL-ISO-B | B14: ME-09 | C14: isolation_transformer | D14: Mastervolt | E14: Mass GI3.5 88000355 | G14: pcs | H14: EUR | I14: 1008.36 | J14: NET_EXPLICIT | L14: 1008.36 | M14: https://www.svb24.com/en/mastervolt-mass-gi-3-5-isolation-transformer-16-a-3-5-kw.html | N14: https://www.mastervolt.com/products/mass-gi/mass-gi-35-kva-16a-lightweight/ | O14: 144 | P14: 261 | Q14: 340 | R14: 6 | S14: CONDITIONAL_UNIT_BENCHMARK | T14: 3500 VA at230 V;16 A;HF technology;source IP23 supersedes dealer IP21. Not complete shore protection. | U14: 1 listed in stock | V14: 2026-09-11 | W14: OBSERVED_NET_CONDITIONAL_SCOPE | X14: PUBLIC_PRICE_NOT_KP | Y14: UNKNOWN | Z14: deliverables/M02/v001/01_support/all-candidates.csv | AA14: 1008.36
A15: EL-ISO-C | B15: ME-09 | C15: isolation_transformer | D15: WhisperPower | E15: GI3600 60110102 | G15: pcs | H15: EUR | I15: 1885 | J15: GROSS_RATE_UNCONFIRMED | M15: https://www.hansenautic.de/36377/wp-gi-compact-galvanic-isolation-transformator-230v-16a-120v-32a/ | N15: https://www.whisperpower.com/gi-3600-compact-galvanic-isolation-transformer | O15: 208 | P15: 290 | Q15: 380 | R15: 28.6 | S15: CONDITIONAL_NET_PENDING_TAX | T15: 3.6 kVA;230/110 V;16/32 A. Open page confirms VAT included but not rate: NET deliberately blank. | U15: availability on request | V15: 2026-09-11 | W15: NO_VERIFIED_NET | X15: PUBLIC_PRICE_NOT_KP | Y15: UNKNOWN | Z15: deliverables/M02/v001/01_support/all-candidates.csv
A16: EL-BAT-A | B16: ME-08 | C16: service_battery | D16: Exide | E16: ER550 12V115Ah | F16: 6 | G16: pcs | H16: EUR | I16: 166.89 | J16: GROSS_RATE_CONFIRMED | K16: 19 | L16: 140.24 | M16: https://online-batterien.de/a/exide-er550-dual-versorgungsbatterie-starterbatterie-12v-115ah-550wh/400440 | N16: https://www.exidegroup.com/en/document/ml-brochure-2022 | O16: 349 | P16: 175 | Q16: 235 | R16: 28 | S16: CONDITIONAL_115AH12V_NOT_OWNER_APPROVED | T16: Flooded. Owner only said115 amperes; Ah and unit voltage unconfirmed. 6 physical units; no bank wiring/capacity inferred. Deposit extra. Dealer350mm/29kg differs from brochure. | U16: not in stock | V16: 2026-09-11 | W16: OBSERVED_NET_CONDITIONAL_SCOPE | X16: PUBLIC_PRICE_NOT_KP | Y16: UNKNOWN | Z16: deliverables/M02/v001/01_support/all-candidates.csv | AA16: 140.24
A17: EL-BAT-B | B17: ME-08 | C17: service_battery | D17: Aquamot | E17: ALS12115 12V115Ah | F17: 6 | G17: pcs | H17: EUR | I17: 319 | J17: GROSS_RATE_CONFIRMED | K17: 19 | L17: 268.07 | M17: https://www.nothnagel-marine.de/product_info.php?info=p3857_aquamot---power-battery--dc-battery-als12115-12v-115ah-agm-deep-cycle-battery.html&language=en | N17: https://aquamot.at/wp-content/uploads/2018/02/Die-Batterie-Aquamot.pdf | O17: 331 | P17: 176 | Q17: 220 | R17: 33.7 | S17: CONDITIONAL_115AH12V_NOT_OWNER_APPROVED | T17: AGM dealer description; legacy manufacturer sheet includes GEL construction wording, chemistry/revision confirmation needed. Body height214mm total220mm; dealer header6.4kg rejected in favour33.7kg technical sheet. | U17: 3-7days; abroad may vary | V17: 2026-09-11 | W17: OBSERVED_NET_CONDITIONAL_SCOPE | X17: PUBLIC_PRICE_NOT_KP | Y17: UNKNOWN | Z17: deliverables/M02/v001/01_support/all-candidates.csv | AA17: 268.07
A18: EL-BAT-C | B18: ME-08 | C18: service_battery | D18: Victron | E18: AGM Telecom115Ah M8 BAT412105164 | F18: 6 | G18: pcs | H18: EUR | I18: 329.95 | J18: GROSS_RATE_CONFIRMED | K18: 21 | L18: 272.69 | M18: https://ab-marineservice.com/product/12v-115ah-agm-telecom-batt-m8/ | N18: https://www.victronenergy.com/upload/documents/Datasheet-Telecom-batteries-EN.pdf | O18: 395 | P18: 110 | Q18: 293 | R18: 35 | S18: CONDITIONAL_115AH12V_NOT_OWNER_APPROVED | T18: 12 V AGM front terminal;6 units only if owner confirms115Ah12V. No12V housebus inferred. Open page21% supersedes search19%. | U18: backorder3-5workingdays | V18: 2026-09-11 | W18: OBSERVED_NET_CONDITIONAL_SCOPE | X18: PUBLIC_PRICE_NOT_KP | Y18: UNKNOWN | Z18: deliverables/M02/v001/01_support/all-candidates.csv | AA18: 272.69
A19: EL-DIST-A | B19: ME-10 | C19: dc_distribution_module | D19: Victron | E19: Lynx Distributor M8 LYN060102000 | G19: pcs | H19: EUR | I19: 182.75 | J19: NET_EXPLICIT | L19: 182.75 | M19: https://www.dynastart.nl/lyn060102000-lynx-distributor-m8 | N19: https://www.victronenergy.com/media/pg/Lynx_Distributor/en/technical-specifications-lynx-distributor.html | O19: 170 | P19: 80 | Q19: 290 | R19: 2.2 | S19: CONDITIONAL_UNIT_BENCHMARK | T19: Supports24 V;1000 A product rating not yacht demand; four fuse ways, fuses/monitor supply and full installation separate. Source axis hxlxw=290x170x80; check drawing for orientation. | U19: in stock | V19: 2026-09-11 | W19: OBSERVED_NET_CONDITIONAL_SCOPE | X19: PUBLIC_PRICE_NOT_KP | Y19: UNKNOWN | Z19: deliverables/M02/v001/01_support/all-candidates.csv | AA19: 182.75
A20: EL-DIST-B | B20: ME-10 | C20: dc_distribution_panel | D20: Philippi | E20: STV207 020002071 | G20: pcs | H20: EUR | I20: 214.24 | J20: NET_EXPLICIT | L20: 214.24 | M20: https://www.svb24.com/en/philippi-stv207-power-distribution-panel-configurable.html | N20: https://www.philippi-online.de/en/collections/serie_200-marine/products/stv-207 | O20: 70 | P20: 105 | Q20: 210 | S20: CONDITIONAL_UNIT_BENCHMARK | T20: 24 V compatible seven-circuit unit benchmark;10 A standard breakers not approved circuit ratings. DC accessory socket not permission for12V loads on24V. Mass not published. Not complete yacht switchboard. | U20: 2 listed in stock | V20: 2026-09-11 | W20: OBSERVED_NET_CONDITIONAL_SCOPE | X20: PUBLIC_PRICE_NOT_KP | Y20: UNKNOWN | Z20: deliverables/M02/v001/01_support/all-candidates.csv | AA20: 214.24
A21: EL-DIST-C | B21: ME-10 | C21: ac_shore_distribution_panel | D21: Philippi | E21: LAE113 010001130 | G21: pcs | H21: EUR | I21: 331.89 | J21: NET_EXPLICIT | L21: 331.89 | M21: https://www.svb24.com/en/philippi-lae-113-shore-connection-unit.html | N21: https://www.philippi-online.de/en/products/lae-113 | O21: 100 | P21: 260 | Q21: 185 | S21: CONDITIONAL_UNIT_BENCHMARK | T21: Factory230 V50Hz panel benchmark for220VAC target;16A/30mA RCBO and3two-pole10A circuits per official description. Not full multi-source AC switchboard; mass unknown. | U21: 2 listed in stock | V21: 2026-09-11 | W21: OBSERVED_NET_CONDITIONAL_SCOPE | X21: PUBLIC_PRICE_NOT_KP | Y21: UNKNOWN | Z21: deliverables/M02/v001/01_support/all-candidates.csv | AA21: 331.89
A22: EL-REM-A | B22: ME-28 | C22: remote_battery_switch | D22: Blue Sea | E22: ML-RBS7702 24V | G22: pcs | H22: EUR | I22: 239.45 | J22: NET_EXPLICIT | L22: 239.45 | M22: https://www.svb24.com/en/blue-sea-hd-remote-battery-switch-24v.html | N22: https://www.bluesea.com/products/7702/ML-RBS_Remote_Battery_Switch_with_Manual_Control_-_24V_DC_500A | R22: 0.95 | S22: CONDITIONAL_UNIT_BENCHMARK | T22: Manual override;24V coil;500A continuous product rating. Quantity, control failover, crank duty and24V live switching not qualified; dimensions drawing pending. | U22: 9 listed in stock | V22: 2026-09-11 | W22: OBSERVED_NET_CONDITIONAL_SCOPE | X22: PUBLIC_PRICE_NOT_KP | Y22: UNKNOWN | Z22: deliverables/M02/v001/01_support/all-candidates.csv | AA22: 239.45
A23: EL-REM-B | B23: ME-28 | C23: remote_solenoid | D23: Blue Sea | E23: 7703 24V | G23: pcs | H23: EUR | I23: 226.85 | J23: NET_EXPLICIT | L23: 226.85 | M23: https://www.svb24.com/en/blue-sea-universal-solenoid-switch-24-v.html | N23: https://d2pyqm2yd3fw2i.cloudfront.net/files/resources/instructions/990180170-006.pdf | S23: CONDITIONAL_UNIT_BENCHMARK | T23: Solenoid unit benchmark without manual override of7702; not automatic equivalent. Physical dimensions/mass unverified. No assertion reserve-start scheme works. | U23: 2 listed in stock | V23: 2026-09-11 | W23: OBSERVED_NET_CONDITIONAL_SCOPE | X23: PUBLIC_PRICE_NOT_KP | Y23: UNKNOWN | Z23: deliverables/M02/v001/01_support/all-candidates.csv | AA23: 226.85
A24: EL-OPEN-PUMP | B24: ME-06 | C24: independent_ac_pump_channel | E24: UNSIZED | F24: 1 | G24: function | J24: UNKNOWN | S24: OPEN_LOAD_AND_STARTUP | T24: 1 independent function, not necessarily extra inverter. Select after pump running power/start waveform/duty; avoid double counting ME05. | U24: NOT_CONFIRMED | V24: 2026-09-11 | W24: NO_VERIFIED_NET | X24: PUBLIC_PRICE_NOT_KP | Y24: UNKNOWN | Z24: deliverables/M02/v001/01_support/all-candidates.csv
A25: EL-OPEN-MAIN | B25: ME-07 | C25: engine_start_battery | E25: UNSIZED | F25: 1 | G25: pcs | J25: UNKNOWN | S25: OPEN_START_VOLTAGE_CCA | T25: 1 physical owner battery, capacity/voltage/chemistry unknown. Not automatically ER550 or service115Ah. | U25: NOT_CONFIRMED | V25: 2026-09-11 | W25: NO_VERIFIED_NET | X25: PUBLIC_PRICE_NOT_KP | Y25: UNKNOWN | Z25: deliverables/M02/v001/01_support/all-candidates.csv
A26: EL-OPEN-GEN | B26: ME-27 | C26: generator_start_battery | E26: UNSIZED | F26: 2 | G26: pcs | J26: UNKNOWN | S26: OPEN_START_VOLTAGE_CCA | T26: 2 physical owner batteries for2generators; capacity/voltage/CCA unknown; keep9total with6service+1main. No fictitious unit price. | U26: NOT_CONFIRMED | V26: 2026-09-11 | W26: NO_VERIFIED_NET | X26: PUBLIC_PRICE_NOT_KP | Y26: UNKNOWN | Z26: deliverables/M02/v001/01_support/all-candidates.csv
A27: WC-RO-01 | B27: ME-13 | C27: RO150 | D27: Aquatec | E27: AC150 230V single phase | F27: 1 | G27: шт | H27: EUR | I27: 7539 | J27: EXPLICIT_NET_AND_19_PERCENT_GROSS | K27: 19 | L27: 6335.29 | M27: https://www.aquatec-watermaker.de/wassermacher-produkt-ac150-ac240.html | N27: https://www.aquatec-watermaker.de/wassermacher-produkt-ac150-ac240.html | S27: FUNCTION_PARITY_OPEN;220V_COMPATIBILITY_OPEN | T27: 150 L/h nominal ±10% at25C/35000ppm; modular conventional HP pump; base price only: automatic flush/salinity/reject parity must be itemised; generator minimum4kW manufacturer target, not electrical demand or selection | U27: NOT_CONFIRMED | V27: 2026-09-11 | W27: OBSERVED_NET_CONDITIONAL_SCOPE | X27: PUBLIC_PRICE_NOT_KP | Y27: UNKNOWN | Z27: deliverables/M02/v001/01_support/all-candidates.csv | AA27: 6335.29
A28: WC-RO-02 | B28: ME-13 | C28: RO150 | D28: Schenker | E28: ZEN150 24V/230V Touch plus salinity/reject | F28: 1 | G28: шт | H28: EUR | I28: 12820.2 | J28: FROM_GROSS_EXPLICIT_20_PERCENT | K28: 20 | L28: 10683.5 | M28: https://mar-nautic.com/schenker-watermaker-zen-150 | N28: https://schenkerwatermakers.com/wp-content/uploads/2025/03/ZEN150_datasheet_v4.pdf | S28: FROM_PRICE_NOT_CONFIGURED;RFQ_REQUIRED | T28: Observed FROM base price; net is FROM benchmark only, NOT complete Touch/salinity/reject price. Nominal150L/h. Manufacturer230V±15% includes220V. Basic has no salinity; Touch optional; 24V variant permitted. Modular unit dimensions not total installed envelope. | U28: Out of stock; order lead time on request | V28: 2026-09-11 | W28: FROM_INCOMPLETE_CONFIGURATION | X28: PUBLIC_PRICE_NOT_KP | Y28: UNKNOWN | Z28: deliverables/M02/v001/01_support/all-candidates.csv | AA28: 10683.5
A29: WC-RO-03 | B29: ME-13 | C29: RO150 | D29: Osmosea | E29: NEW12 150C 24V | F29: 1 | G29: шт | H29: EUR | M29: https://www.manelservice.com/en/marine-desalination-systems/17102-osmosea-new12-150c-nautical-watermaker-150-lth.html | N29: https://osmosea.it/en/new-12/ | R29: 63 | S29: RFQ_REQUIRED;COMPACT_CANDIDATE | T29: Official150L/h/600W; flush/salinometer/unsafe-water discard included. Official63kg conflicts dealer65kg; dimensions dealer796x317x408 not official therefore blank. Dealer install/service kits included vs manufacturer optional: reconcile | U29: NOT_CONFIRMED | V29: 2026-09-11 | W29: NO_VERIFIED_NET | X29: PUBLIC_PRICE_NOT_KP | Y29: UNKNOWN | Z29: deliverables/M02/v001/01_support/all-candidates.csv
A30: WC-DC-01 | B30: ME-11 | C30: FRESHWATER_24V | D30: CEM | E30: OSC-16.062.24 / OEM identity reconcile | F30: 1 | G30: шт | H30: EUR | I30: 1229.9 | J30: EXPLICIT_HT | L30: 1024.92 | M30: https://www.comptoirnautique.com/groupe-d-eau-a-pressostat/53022-cem-elettromeccanica-autoclave-cem-vase-expansion-inox-20l-24v-50-l-min.html | N30: https://cempumps.com/wp-content/uploads/2024/10/Autoclavi_20L-20X.pdf | S30: WORKING_POINT_AND_OEM_ID_OPEN | T30: 24V20L accumulator; dealer50L/min max; source model mapping not proven. Common proposed test15L/min at2bar NOT verified. Do not add included tank again. | U30: Preorder; replenishment23/09/2026 | V30: 2026-09-11 | W30: OBSERVED_NET_CONDITIONAL_SCOPE | X30: PUBLIC_PRICE_NOT_KP | Y30: UNKNOWN | Z30: deliverables/M02/v001/01_support/all-candidates.csv | AA30: 1024.92
A31: WC-DC-02 | B31: ME-11 | C31: FRESHWATER_24V | D31: Gianneschi | E31: EcoInox1 GE011 24V20L | F31: 1 | G31: шт | H31: EUR | I31: 1311.9 | J31: EXPLICIT_HT | L31: 1093.25 | M31: https://www.comptoirnautique.com/groupe-d-eau-hydrophore/22947-gianneschi-groupe-d-eau-ecoinox-1-avec-reservoir-20l-24v-45lmin-7024.html | N31: https://www.gianneschipumps.com/GIANNESCHI_Brochure-web.pdf | S31: WORKING_POINT_OPEN | T31: 45L/min max; common proposed15L/min at2bar needs curve. Includes20L tank/gauge/pressure switch; current OEM revision confirmation. | U31: In stock48/72h | V31: 2026-09-11 | W31: OBSERVED_NET_CONDITIONAL_SCOPE | X31: PUBLIC_PRICE_NOT_KP | Y31: UNKNOWN | Z31: deliverables/M02/v001/01_support/all-candidates.csv | AA31: 1093.25
A32: WC-DC-03 | B32: ME-11 | C32: FRESHWATER_24V | D32: ENAG | E32: GH24-0.37-24L-OT RB18-ED | F32: 1 | G32: шт | H32: EUR | M32: https://www.enag.fr/english/wp-content/uploads/sites/5/2022/11/FC-GH-EN-C.pdf | N32: https://www.enag.fr/english/wp-content/uploads/sites/5/2022/11/FC-GH-EN-C.pdf | R32: 29 | S32: RFQ_REQUIRED;WORKING_POINT_OPEN | T32: Official24V/0.37kW; 1m3/h at30m published point; pressure switch1.5/2.5bar.24L tank differs20L competitors: standardise accumulator scope before comparison. Dimensions drawing orientation not mapped into LWH. | U32: NOT_CONFIRMED | V32: 2026-09-11 | W32: NO_VERIFIED_NET | X32: PUBLIC_PRICE_NOT_KP | Y32: UNKNOWN | Z32: deliverables/M02/v001/01_support/all-candidates.csv
A33: WC-AC-01 | B33: ME-12 | C33: FRESHWATER_AC | D33: CEM | E33: J-INOX/20X 230M | F33: 1 | G33: шт | H33: EUR | M33: https://cempumps.com/wp-content/uploads/2024/10/Autoclavi_20L-20X.pdf | N33: https://cempumps.com/wp-content/uploads/2024/10/Autoclavi_20L-20X.pdf | S33: RFQ_REQUIRED;220V_COMPATIBILITY_OPEN;WORKING_POINT_OPEN | T33: Official230V singlephase variant exists. Proposedcommon15L/min at2bar not accepted from maxflow.20L stainless tank included. No price borrowed from24V sibling. | U33: NOT_CONFIRMED | V33: 2026-09-11 | W33: NO_VERIFIED_NET | X33: PUBLIC_PRICE_NOT_KP | Y33: UNKNOWN | Z33: deliverables/M02/v001/01_support/all-candidates.csv
A34: WC-AC-02 | B34: ME-12 | C34: FRESHWATER_AC | D34: Gianneschi | E34: EcoInox2 GE017 230V20L | F34: 1 | G34: шт | H34: EUR | I34: 1263 | J34: EXPLICIT_HT | L34: 1052.5 | M34: https://www.tyboat.com/achat/P-57388-gianneschi-groupe-d-eau-ecoinox2-3-5-bars-0-45-kw-55-litres-minute-reservoir-20-litres-230-volts.html | N34: https://www.gianneschipumps.com/GIANNESCHI_Brochure-web.pdf | S34: 220V_COMPATIBILITY_OPEN;WORKING_POINT_OPEN | T34: Open page1052.50HT supersedes search992.50. Dealer max55L/min conflicts Kent45: curves required.0.45kW/20L; common15L/min at2bar not verified. | U34: Stock1–6businessdays | V34: 2026-09-11 | W34: OBSERVED_NET_CONDITIONAL_SCOPE | X34: PUBLIC_PRICE_NOT_KP | Y34: UNKNOWN | Z34: deliverables/M02/v001/01_support/all-candidates.csv | AA34: 1052.5
A35: WC-AC-03 | B35: ME-12 | C35: FRESHWATER_AC | D35: ENAG | E35: GH230mono-0.37-24L-JET M-ED | F35: 1 | G35: шт | H35: EUR | M35: https://www.enag.fr/english/wp-content/uploads/sites/5/2022/11/FC-GH-EN-C.pdf | N35: https://www.enag.fr/english/wp-content/uploads/sites/5/2022/11/FC-GH-EN-C.pdf | R35: 18 | S35: RFQ_REQUIRED;220V_COMPATIBILITY_OPEN;WORKING_POINT_OPEN | T35: Explicit230V singlephase; official1m3/h at40m, pressure switch1.5/2.5bar.24L accumulator vs20L needs standardisation; no equivalence claim. | U35: NOT_CONFIRMED | V35: 2026-09-11 | W35: NO_VERIFIED_NET | X35: PUBLIC_PRICE_NOT_KP | Y35: UNKNOWN | Z35: deliverables/M02/v001/01_support/all-candidates.csv
A36: WC-CH-01 | B36: ME-15 | C36: CHILLER_REFERENCE_16000BTUH | D36: Thermowell | E36: UC16H | F36: 2 | G36: шт | H36: EUR | I36: 4544.35 | J36: GROSS_EXPLICIT_ALV25.5 | K36: 25.5 | L36: 3621 | M36: https://www.esconet.fi/shop/uc16h-thermowell-uc16h-ilmastointilaite-chiller-230v-16000btu-27518 | N36: https://www.thermowellmarine.com/wp-content/uploads/2023/04/THERMOWELL-2023_rev1_apr_web.pdf | O36: 350 | P36: 340 | Q36: 380 | R36: 38 | S36: REFERENCE_SIZE_ONLY;VOLTAGE_REVISION_CHECK;SUPPLY_SCOPE_CONFLICT_RFQ | T36: 16000BTU/h each; illustrative class NOT yacht heatload. Officialcatalog220/1/50; dealer230V. Dimensions exclude controlbox. OEM catalogue says box/display included BUT priced Esco SKU requires airhandler/controlpanel separately: inclusion CONFLICT, RFQ required; do not assume included display.1.5kWnominput at catalogue conditions; independent2module integration open. | U36: Esco stock0; supplier availability unknown | V36: 2026-09-11 | W36: OBSERVED_NET_CONDITIONAL_SCOPE | X36: PUBLIC_PRICE_NOT_KP | Y36: UNKNOWN | Z36: deliverables/M02/v001/01_support/all-candidates.csv | AA36: 3621
A37: WC-CH-02 | B37: ME-15 | C37: CHILLER_REFERENCE_16000BTUH | D37: Climma | E37: CWS Aquacontrol161RC 230/1/50 | F37: 2 | G37: шт | H37: EUR | I37: 4155.3 | J37: EXPLICIT_TAX_EXCLUDED | L37: 4155.3 | M37: https://mdislandsupply.com/en/climma/879-cws-aquacontrol-161-rc-230150-climma.html | N37: https://www.veco.net/en/prodotti/climma-cws-aquacontrol-chillers/ | S37: REFERENCE_SIZE_ONLY;220V_COMPATIBILITY_OPEN | T37: 16000BTU/h each; reversecycle. Price recovered live requests HTTP200 after web429; local source text retained. OEM dimensions require authenticated download; old dealerPDF not promoted. | U37: Last items;1–2businessdays claim | V37: 2026-09-11 | W37: OBSERVED_NET_CONDITIONAL_SCOPE | X37: PUBLIC_PRICE_NOT_KP | Y37: UNKNOWN | Z37: deliverables/M02/v001/01_support/all-candidates.csv | AA37: 4155.3
A38: WC-CH-03 | B38: ME-15 | C38: CHILLER_REFERENCE_16000BTUH | D38: Webasto | E38: BlueCool C16M | F38: 2 | G38: шт | H38: EUR | M38: https://www.nauticsale.com/en/airconditioning/bluecool-chiller-systems/bluecool-c-series-chillers/ | N38: https://www.webasto.com/en-us/cooling/marine-chiller-air-conditioning-units/bluecool-c-series.html | O38: 385 | P38: 290 | Q38: 350 | R38: 30 | S38: RFQ_REQUIRED;REFERENCE_SIZE_ONLY;220V_COMPATIBILITY_OPEN | T38: 16000BTU/h each; officialcurrentdimensions. Older F-suffix dealerweight differs: revision match required.3pricepaths found no verified EU net exactSKU; no US price conversion. | U38: NOT_CONFIRMED | V38: 2026-09-11 | W38: NO_VERIFIED_NET | X38: PUBLIC_PRICE_NOT_KP | Y38: UNKNOWN | Z38: deliverables/M02/v001/01_support/all-candidates.csv
A39: WC-HW-01 | B39: ME-14 | C39: BOILER_REFERENCE_40L | D39: Quick | E39: B3 40L1200W FLB34012S000A00 | G39: шт | H39: EUR | I39: 737 | J39: EXPLICIT_HT | L39: 614.17 | M39: https://www.tyboat.com/achat/P-8889-quick-chauffe-eau-cylindrique-b3-40-litres-220-volts-1200-watts.html | N39: https://www.quickitaly.com/it/prodotti/scalda-acqua/scalda-acqua/nautic-boiler-b3/ | S39: UNIT_BENCHMARK_ONLY;QTY_OPEN | T39: 40L1200W220V plus engine heat exchanger common illustrative class; not owner size. Supplier dimensions/mass in research only pending official drawing. Thermostatic mixing equalise separately. | U39: Stock1–6businessdays | V39: 2026-09-11 | W39: OBSERVED_NET_CONDITIONAL_SCOPE | X39: PUBLIC_PRICE_NOT_KP | Y39: UNKNOWN | Z39: deliverables/M02/v001/01_support/all-candidates.csv | AA39: 614.17
A40: WC-HW-02 | B40: ME-14 | C40: BOILER_REFERENCE_40L | D40: Quick | E40: BX 40L1200W FLBX4012S000A00 | G40: шт | H40: EUR | I40: 829 | J40: EXPLICIT_HT | L40: 690.83 | M40: https://www.tyboat.com/achat/P-8880-quick-chauffe-eau-cylindrique-bx-40-litres-220-volts-1200-watts.html | N40: https://www.quickitaly.com/it/prodotti/scalda-acqua/scalda-acqua/nautic-boiler-bx/ | S40: UNIT_BENCHMARK_ONLY;QTY_OPEN | T40: 40L1200W220V plus engine heat exchanger common illustrative class; not owner size. Supplier dimensions/mass in research only pending official drawing. Thermostatic mixing equalise separately. | U40: Stock1–6businessdays | V40: 2026-09-11 | W40: OBSERVED_NET_CONDITIONAL_SCOPE | X40: PUBLIC_PRICE_NOT_KP | Y40: UNKNOWN | Z40: deliverables/M02/v001/01_support/all-candidates.csv | AA40: 690.83
A41: WC-HW-03 | B41: ME-14 | C41: BOILER_REFERENCE_40L | D41: Quick | E41: BXS 40L1200W FLBXS4012S00A00 | G41: шт | H41: EUR | I41: 909 | J41: EXPLICIT_HT | L41: 757.5 | M41: https://www.tyboat.com/achat/P-18237-quick-chauffe-eau-cube-inox-bxs-40-litres-220-volts-1200-watts.html | N41: https://www.quickitaly.com/it/prodotti/scalda-acqua/scalda-acqua/nautic-boiler-bxs/ | S41: UNIT_BENCHMARK_ONLY;QTY_OPEN | T41: 40L1200W220V plus engine heat exchanger common illustrative class; not owner size. Supplier dimensions/mass in research only pending official drawing. Thermostatic mixing equalise separately. | U41: Stock1–6businessdays | V41: 2026-09-11 | W41: OBSERVED_NET_CONDITIONAL_SCOPE | X41: PUBLIC_PRICE_NOT_KP | Y41: UNKNOWN | Z41: deliverables/M02/v001/01_support/all-candidates.csv | AA41: 757.5
A42: WC-AUX-01 | B42: ME-16 | C42: HVAC_PUMP | D42: Frigomar | E42: NH150PS SWM0150230 | G42: шт | H42: EUR | I42: 795.9 | J42: EXPLICIT_HT | L42: 663.25 | M42: https://www.comptoirnautique.com/climatisation-bateau/91819-frigomar-pompes-a-entrainement-magnetique.html | N42: https://www.frigomar.com/en/product-line/ | S42: UNIT_BENCHMARK_ONLY;CURVE_AND_220V_OPEN | T42: 230V50/60Hz magneticdrive; count and pump duty notfixed. No proof this model meets both seawater and chilledwater circuits; official detailed curve required. | U42: Preorder; replenishment19/09/2026 | V42: 2026-09-11 | W42: OBSERVED_NET_CONDITIONAL_SCOPE | X42: PUBLIC_PRICE_NOT_KP | Y42: UNKNOWN | Z42: deliverables/M02/v001/01_support/all-candidates.csv | AA42: 663.25
A43: WC-AUX-02 | B43: ME-17 | C43: THERMOSTATIC_MIXING | D43: Quick | E43: QB002 mixing kit | G43: шт | H43: EUR | I43: 140.4 | J43: EXPLICIT_HT | L43: 117 | M43: https://www.kent-marine.com/fr/produit/35262/chauffe-eau-cylindrique-40l-220v-1200w.html | N43: https://www.quickitaly.com/it/prodotti/scalda-acqua/ | S43: PUBLIC_LIST_UNIT_BENCHMARK | T43: Observed linked accessory publicHT price; count unknown; confirm inclusion in selected calorifier supply. | U43: Not confirmed | V43: 2026-09-11 | W43: OBSERVED_NET_CONDITIONAL_SCOPE | X43: PUBLIC_PRICE_NOT_KP | Y43: UNKNOWN | Z43: deliverables/M02/v001/01_support/all-candidates.csv | AA43: 117
A44: WC-AUX-03 | B44: ME-17 | C44: FRESHWATER_FILTER | D44: Jabsco | E44: Pumpgard36400-0002 / substitution46400-0000 | G44: шт | H44: EUR | I44: 33.5 | J44: TAX_NOT_PROVEN | M44: https://www.marine-impact.com/groupe-d-eau/313-filtre-en-ligne-pumpgard-o13-mm-jabsco.html | N44: https://www.xylem.com/siteassets/brand/jabsco/resources/manual/36800-technical-data-sheet.pdf | S44: UNIT_BENCHMARK_GROSS_UNKNOWN;NET_WITHHELD | T44: Observedprice; no explicit taxbasis verified so net blank.13mm40mesh strainer not sanitary treatment and not dimensioned for proposedpressurestation. | U44: Web listing | V44: 2026-09-11 | W44: NO_VERIFIED_NET | X44: PUBLIC_PRICE_NOT_KP | Y44: UNKNOWN | Z44: deliverables/M02/v001/01_support/all-candidates.csv
A45: A01 | B45: ME-29 | C45: Бак гидравлики | D45: Vetus | E45: HT1010 | G45: шт | H45: GBP | I45: 2412.08 | J45: NET_EXPLICIT | L45: 2412.08 | M45: https://www.vetus-shop.com/aluminium-hydraulic-tank-70-incl-ht1013-p-2024.html | N45: https://webshop.vetus.com/nl/products/power-hydraulics/hydraulische-tanks | S45: PARTIAL_HYDRAULIC_NOT_COMPLETE | T45: 70л; HT1013 включён. Цена бака с частью управления, не станции. 615×475×360мм у продавца — только голый бак без клапанов, не монтажный габарит. | U45: Out of Stock | V45: 2026-09-11 | W45: OBSERVED_NET_CONDITIONAL_SCOPE | X45: PUBLIC_PRICE_NOT_KP | Y45: UNKNOWN | Z45: deliverables/M02/v001/01_support/all-candidates.csv | AA45: 2807.52
A46: A02 | B46: ME-29 | C46: Насос гидравлики | D46: Vetus | E46: HT1016SD2 | G46: шт | H46: GBP | I46: 2716.67 | J46: NET_EXPLICIT | L46: 2716.67 | M46: https://www.vetus-shop.com/vetus-power-hydraulics-c-21_210.html | S46: PARTIAL_HYDRAULIC_NOT_COMPLETE | T46: 45см³/оборот; ориентация/SAE/привод и требуемый расход не выбраны. Не три уровня насосов разного размера. | U46: Не подтверждено | V46: 2026-09-11 | W46: OBSERVED_NET_CONDITIONAL_SCOPE | X46: PUBLIC_PRICE_NOT_KP | Y46: UNKNOWN | Z46: deliverables/M02/v001/01_support/all-candidates.csv | AA46: 3162.04
A47: A03 | B47: ME-29 | C47: Охладитель масла | D47: Vetus | E47: HT301132 | G47: шт | H47: GBP | I47: 517.5 | J47: NET_EXPLICIT | L47: 517.5 | M47: https://www.vetus-shop.com/aluminium-hydraulic-tank-70-incl-ht1013-p-2024.html | S47: PARTIAL_HYDRAULIC_NOT_COMPLETE | T47: Шланг32мм; теплоотдача/забортный контур требуют проверки; не доказана необходимость именно этого размера. | U47: Не подтверждено | V47: 2026-09-11 | W47: OBSERVED_NET_CONDITIONAL_SCOPE | X47: PUBLIC_PRICE_NOT_KP | Y47: UNKNOWN | Z47: deliverables/M02/v001/01_support/all-candidates.csv | AA47: 602.34
A48: A04 | B48: ME-29 | C48: Клапан якорной лебёдки | D48: Vetus | E48: HT102312 | G48: шт | H48: GBP | I48: 487.92 | J48: NET_EXPLICIT | L48: 487.92 | M48: https://www.vetus-shop.com/aluminium-hydraulic-tank-70-incl-ht1013-p-2024.html | S48: PARTIAL_HYDRAULIC_NOT_COMPLETE | T48: Один тип клапана; не весь блок гидролебёдок, количество потребителей открыто. | U48: Не подтверждено | V48: 2026-09-11 | W48: OBSERVED_NET_CONDITIONAL_SCOPE | X48: PUBLIC_PRICE_NOT_KP | Y48: UNKNOWN | Z48: deliverables/M02/v001/01_support/all-candidates.csv | AA48: 567.91
A49: A05 | B49: ME-29 | C49: Управление нагрузкой | D49: Vetus | E49: HT1011 | G49: шт | H49: GBP | I49: 715.83 | J49: NET_EXPLICIT | L49: 715.83 | M49: https://www.vetus-shop.com/vetus-power-hydraulics-c-21_210.html | S49: PARTIAL_HYDRAULIC_NOT_COMPLETE | T49: Одноступенчатый load sensing; пригодность к общей системе открыта. | U49: Не подтверждено | V49: 2026-09-11 | W49: OBSERVED_NET_CONDITIONAL_SCOPE | X49: PUBLIC_PRICE_NOT_KP | Y49: UNKNOWN | Z49: deliverables/M02/v001/01_support/all-candidates.csv | AA49: 833.18
A50: A06 | B50: ME-29 | C50: Клапан подруливающего | D50: Vetus | E50: HT1013 | G50: шт | H50: GBP | I50: 300.83 | J50: NET_EXPLICIT | L50: 300.83 | M50: https://www.vetus-shop.com/aluminium-hydraulic-tank-70-incl-ht1013-p-2024.html | S50: INCLUDED_COMPONENT_DO_NOT_ADD | T50: Уже входит в HT1010; отдельная цена только для дополнительного потребителя, не прибавлять повторно. | U50: Не подтверждено | V50: 2026-09-11 | W50: OBSERVED_NET_CONDITIONAL_SCOPE | X50: PUBLIC_PRICE_NOT_KP | Y50: UNKNOWN | Z50: deliverables/M02/v001/01_support/all-candidates.csv | AA50: 350.15
A51: A07 | B51: ME-29 | C51: Общая гидросистема | D51: Sleipner | E51: Load-sensing system / bulkhead tank 40L | G51: шт | H51: EUR | J51: RFQ_REQUIRED | N51: https://info.sleipnergroup.com/hubfs/Side-Power_Hydraulic_AC_Thrusters_2020.pdf | O51: 870 | P51: 330 | Q51: 705 | R51: 55 | S51: RFQ_REQUIRED_TECH_OPEN | T51: Справочный габарит настенного танк-модуля из каталога2020; с блоком одного подруливающего, без всей установки. Ещё100мм для замены фильтра. Нужны текущийCAD и расчёт всех потребителей. | U51: Не подтверждено | V51: 2026-09-11 | W51: NO_VERIFIED_NET | X51: PUBLIC_PRICE_NOT_KP | Y51: UNKNOWN | Z51: deliverables/M02/v001/01_support/all-candidates.csv
A52: A08 | B52: ME-29 | C52: Палубная гидростанция | D52: Harken | E52: Hydro 2 | G52: шт | H52: EUR | J52: RFQ_REQUIRED | N52: https://gallery.harken.com/gallery/3d369089-1f35-489d-8b71-ab3020e962a1.pdf | O52: 491 | P52: 341 | Q52: 567.7 | R52: 63.5 | S52: RFQ_REQUIRED_THRUSTER_CAPABILITY_OPEN | T52: 30л,2мотора24V4kW; стандартная помпа15л/мин140бар. Не доказана пригодность для подруливающих; не назначать резервное питание от6АКБ дорасчёта тока. | U52: Не подтверждено | V52: 2026-09-11 | W52: NO_VERIFIED_NET | X52: PUBLIC_PRICE_NOT_KP | Y52: UNKNOWN | Z52: deliverables/M02/v001/01_support/all-candidates.csv
A53: A09 | B53: ME-18 | C53: Дуплексный топливный фильтр | D53: Parker Racor | E53: 75500MAXM30 | G53: шт | H53: EUR | I53: 2199.9 | J53: GROSS_RATE_VERIFIED | K53: 19 | L53: 1848.66 | M53: https://racorshop.de/product/racor-75500maxm30-turbine-filter-marine/ | N53: https://www.parker.com/content/dam/Parker-com/Literature/Racor-Europe/FDRB544UK_BRO_Distribution_Solution_Brochure-_Racor_Europe.pdf | S53: PRICE_VARIATION_RECONFIRM_TECH_OPEN | T53: Root open2612.00gross/19%=2194.96NET; повторное открытие независимым агентом2199.90gross/19%=1848.66NET. Принято последнее наблюдение, расхождение сохранено; подтвердить цену до сравнения. Дуплексный узел, микроны/расход одной ветви под двигатель. | U53: 1 in stock | V53: 2026-09-11 | W53: VARIABLE_PRICE_RECONFIRM | X53: PUBLIC_PRICE_NOT_KP | Y53: UNKNOWN | Z53: deliverables/M02/v001/01_support/all-candidates.csv | AA53: 1848.66
A54: A10 | B54: ME-19 | C54: Фильтр забортной воды | D54: Vetus | E54: FTR330/32 | G54: шт | H54: GBP | I54: 81.67 | J54: NET_EXPLICIT | L54: 81.67 | M54: https://www.vetus-shop.com/vetus-raw-water-strainer-type-330-and21632mm-p-1026.html | S54: UNIT_BENCHMARK_TECH_OPEN | T54: Типоразмер32мм только ориентир; диаметр и положение относительно ватерлинии по выбранному агрегату. | U54: 10+ in stock | V54: 2026-09-11 | W54: OBSERVED_NET_CONDITIONAL_SCOPE | X54: PUBLIC_PRICE_NOT_KP | Y54: UNKNOWN | Z54: deliverables/M02/v001/01_support/all-candidates.csv | AA54: 95.06
A55: A11 | B55: ME-19 | C55: Фильтр забортной воды | D55: Vetus | E55: FTR33032M | G55: шт | H55: EUR | I55: 164.46 | J55: NET_EXPLICIT | L55: 164.46 | M55: https://www.mediawinkel.eu/nl/heavy-duty-waterfilter-32-mm.html | S55: UNIT_BENCHMARK_TECH_OPEN | T55: NET явно exclusiefBTW; усиленная версия с металлической крышкой. Сравнение с FTR330/32 требует одинаковых давления/установочного положения. | U55: Не подтверждено | V55: 2026-09-11 | W55: OBSERVED_NET_CONDITIONAL_SCOPE | X55: PUBLIC_PRICE_NOT_KP | Y55: UNKNOWN | Z55: deliverables/M02/v001/01_support/all-candidates.csv | AA55: 164.46
A56: A12 | B56: ME-20 | C56: Электрический осушительный насос | D56: Rule | E56: 2000 GPH / model12 /24V | G56: шт | H56: GBP | I56: 107.24 | J56: NET_EXPLICIT | L56: 107.24 | M56: https://www.mackengineering.co.uk/rule-2000-gph-bilge-pump-24v.html | N56: https://www.xylem.com/siteassets/brand/rule/resources/technical-brochure/standard-bilge-pumps-model-number-table.pdf | O56: 108 | P56: 108 | Q56: 152 | S56: UNIT_BENCHMARK_TECH_OPEN | T56: Габариты из официальной таблицы, у дилера155×105 отличаются; сверить ревизию. Не вся система осушения; поплавок/сигнализация отдельно. | U56: Не подтверждено | V56: 2026-09-11 | W56: OBSERVED_NET_CONDITIONAL_SCOPE | X56: PUBLIC_PRICE_NOT_KP | Y56: UNKNOWN | Z56: deliverables/M02/v001/01_support/all-candidates.csv | AA56: 124.82
A57: A13 | B57: ME-20 | C57: Ручной осушительный насос | D57: Whale | E57: Gusher Urchin BP9005 | G57: шт | H57: GBP | I57: 55.1 | J57: NET_EXPLICIT | L57: 55.1 | M57: https://www.mackengineering.co.uk/bp9005-whale-gusher-urchin-hand-pump.html | S57: UNIT_BENCHMARK_TECH_OPEN | T57: Ориентир цены ручного насоса; не назначенный главный аварийный насос67ft, расход/напор/доступ проверить. | U57: Не подтверждено | V57: 2026-09-11 | W57: OBSERVED_NET_CONDITIONAL_SCOPE | X57: PUBLIC_PRICE_NOT_KP | Y57: UNKNOWN | Z57: deliverables/M02/v001/01_support/all-candidates.csv | AA57: 64.13
A58: A14 | B58: ME-20 | C58: Датчик/сигнализация высокой воды | D58: Rule | E58: 32ALA /24V | G58: шт | H58: GBP | I58: 73.19 | J58: NET_EXPLICIT | L58: 73.19 | M58: https://www.mackengineering.co.uk/rule-2000-gph-bilge-pump-24v.html | S58: UNIT_BENCHMARK_TECH_OPEN | T58: Цена связанного товара открытой карточки; состав сигнализации и число отсеков открыты. | U58: Не подтверждено | V58: 2026-09-11 | W58: OBSERVED_NET_CONDITIONAL_SCOPE | X58: PUBLIC_PRICE_NOT_KP | Y58: UNKNOWN | Z58: deliverables/M02/v001/01_support/all-candidates.csv | AA58: 85.19
A59: A15 | B59: ME-22 | C59: Вентиляция МО | D59: Jabsco | E59: 35770-0094 /24V | G59: шт | H59: GBP | I59: 224.42 | J59: SEARCH_ONLY_NET_CLAIM | M59: https://www.mackengineering.co.uk/35770-0094-24v-flexmount-blower.html | N59: https://www.xylem.com/siteassets/brand/jabsco/resources/manual/357x0-technical-data-sheet.pdf | R59: 3.18 | S59: PRICE_NOT_ADMITTED_AVAILABILITY_HOLD | T59: Поиск224.42exVAT, открытиеchallenge. Раздел дилера предупреждаетhold EU compliance. NET поле пусто; не считать доступным. Официально7м³/мин свободныйрасход, требуемыйнапорнепроверен. | U59: CHECK_AVAILABILITY / category EU hold | V59: 2026-09-11 | W59: NO_VERIFIED_NET | X59: PUBLIC_PRICE_NOT_KP | Y59: UNKNOWN | Z59: deliverables/M02/v001/01_support/all-candidates.csv
A60: A16 | B60: ME-23 | C60: Насос смены масла | D60: Marco | E60: UP3/OIL 16402013 /24V | G60: шт | H60: GBP | I60: 162 | J60: NET_EXPLICIT | L60: 162 | M60: https://www.mackengineering.co.uk/marco-up3-oil-pump-24v.html | N60: https://items.marco.it/en/md_productpdf/index/generate/product/253/store/2/ | S60: UNIT_BENCHMARK_TECH_OPEN | T60: Только насос; коллектор3агрегатов,шланги,поддоны,свет и автоматика не включены. | U60: Не подтверждено | V60: 2026-09-11 | W60: OBSERVED_NET_CONDITIONAL_SCOPE | X60: PUBLIC_PRICE_NOT_KP | Y60: UNKNOWN | Z60: deliverables/M02/v001/01_support/all-candidates.csv | AA60: 188.56
A61: A17 | B61: ME-24 | C61: Датчик уровня танка | D61: Vetus | E61: SENSOR320 | G61: шт | H61: GBP | I61: 61.67 | J61: NET_EXPLICIT | L61: 61.67 | M61: https://www.vetus-shop.com/vetus-fuel-tank-quickfit-diesel-40-litre-8mm-p-1786.html | S61: UNIT_BENCHMARK_TECH_OPEN | T61: Длина320мм исследовательская; не утверждена глубина/число танков. Цена связанного товара, отдельный индикатор не включён. | U61: Не подтверждено | V61: 2026-09-11 | W61: OBSERVED_NET_CONDITIONAL_SCOPE | X61: PUBLIC_PRICE_NOT_KP | Y61: UNKNOWN | Z61: deliverables/M02/v001/01_support/all-candidates.csv | AA61: 71.78
A62: A18 | B62: ME-24 | C62: Датчик уровня танка | D62: Vetus | E62: SENSORA | G62: шт | H62: GBP | I62: 161.25 | J62: NET_EXPLICIT | L62: 161.25 | M62: https://www.vetus-shop.com/vetus-fuel-tank-quickfit-diesel-40-litre-8mm-p-1786.html | S62: UNIT_BENCHMARK_TECH_OPEN | T62: Ультразвуковой аналоговый датчик; работа в конкретном танке и интерфейс подлежат проверке. Не цена танка. | U62: Не подтверждено | V62: 2026-09-11 | W62: OBSERVED_NET_CONDITIONAL_SCOPE | X62: PUBLIC_PRICE_NOT_KP | Y62: UNKNOWN | Z62: deliverables/M02/v001/01_support/all-candidates.csv | AA62: 187.69
A63: A19 | B63: ME-25 | C63: Откачка сточного танка | D63: Jabsco | E63: 18590-2094 /24V | G63: шт | H63: GBP | I63: 141.63 | J63: NET_EXPLICIT | L63: 141.63 | M63: https://www.cactusnav.com/jabsco-macerator-pump-p-37922.html | S63: UNIT_BENCHMARK_TECH_OPEN | T63: 24V; только насос сточного танка. Пересечение с комплектом туалета проверять; число танков не назначено. | U63: In Stock Plymouth | V63: 2026-09-11 | W63: OBSERVED_NET_CONDITIONAL_SCOPE | X63: PUBLIC_PRICE_NOT_KP | Y63: UNKNOWN | Z63: deliverables/M02/v001/01_support/all-candidates.csv | AA63: 164.85
A64: A20 | B64: ME-21 | C64: Стационарное пожаротушение | D64: Fireboy | E64: MA series 31.620.55 | G64: шт | H64: EUR | I64: 1950 | J64: SEARCH_ONLY_NET_CLAIM | M64: https://www.oltrevela.com/en/31-620-55-fireboy-ma-series-automatic-manual-fire-extinguisher-13-4-kg-for-engine-rooms-and-motor-compartments-up-to-51m-uscg-and-iso-rina-approved-fireboy-4 | N64: https://fireboy.com/ma2-fire-extinguisher/ | S64: PRICE_NOT_ADMITTED_VOLUME_AND_VARIANT_OPEN | T64: Поиск1950NET, открытиеошибка. Заголовок51м³, таблица15.6м³ противоречат; модель/заряд не выбраны. Нельзя уменьшать заряд ради габарита. Отключение двигателей/вентиляции и ручнойпуск по отдельномуBOM. | U64: Не подтверждено | V64: 2026-09-11 | W64: NO_VERIFIED_NET | X64: PUBLIC_PRICE_NOT_KP | Y64: UNKNOWN | Z64: deliverables/M02/v001/01_support/all-candidates.csv
A65: A21 | B65: ME-26 | C65: Дополнительное водяное отопление | D65: Webasto | E65: Thermo Pro90 Marine 24V /9029943C | G65: шт | H65: EUR | I65: 2007.16 | J65: NET_LABEL_CONFLICT | M65: https://www.standkachel.nu/webasto-air-and-water-heaters-and/webasto-waterkachels-thermotop-spheros-dbw-valeo/webasto-marine-waterheaters-for-thermo-pro-90-24-volt/webasto-thermo-chiller--pro-90-marine-24-volt- | S65: OPTIONAL_PRICE_NOT_ADMITTED_TAX_CONFLICT | T65: Открытая карточка маркирует2007.16NET, показывает2161.71sale/2543.18list: арифметика налоговойпары неясна. Неиспользоватьвранжировании; отоплениеещёопция, нечиллеркондиционирования. | U65: Не подтверждено | V65: 2026-09-11 | W65: NO_VERIFIED_NET | X65: PUBLIC_PRICE_NOT_KP | Y65: UNKNOWN | Z65: deliverables/M02/v001/01_support/all-candidates.csv
A66: A22 | B66: ME-26 | C66: Дополнительное водяное отопление | D66: Webasto | E66: Thermo Pro90 Marine 24V /4111185A | G66: шт | H66: GBP | I66: 1995.49 | J66: NET_EXPLICIT | L66: 1995.49 | M66: https://www.butlertechnik.com/item/Webasto/Thermo-Pro-90-24v-Marine-Kit-With-Switch-91kW-4111185A/5G7 | N66: https://www.butlertechnik.com/downloads/cms/7432/webasto-thermo-pro-90-marine-installation-manual.pdf | S66: OPTIONAL_UNIT_BENCHMARK_TECH_OPEN | T66: 9.1kW только исследовательский класс; монтажный комплект с выключателем, остальные контуры и теплоотдающие устройства не включены. Не выбранное отопление и не чиллер. | U66: Item out of stock | V66: 2026-09-11 | W66: OBSERVED_NET_CONDITIONAL_SCOPE | X66: PUBLIC_PRICE_NOT_KP | Y66: UNKNOWN | Z66: deliverables/M02/v001/01_support/all-candidates.csv | AA66: 2322.63
A67: YAN-E01 | B67: ME-01|ME-02 | C67: engine_gearbox | D67: Yanmar | E67: 8LV320E-KMH50A + VC20 | F67: 1 | G67: package | H67: EUR | I67: 58842 | J67: incl BTW; rate not stated | M67: https://www.abma-sneek.nl/yanmar/engines-gears-drives/powerboat-engines?prod_id=650436 | N67: https://www.yanmar.com/marine/product/engines/8lv320/ | O67: 1340 | P67: 880 | Q67: 766 | R67: 487 | S67: CONDITIONAL_DUTY_PTO_START_VOLTAGE; NET_RFQ_REQUIRED | T67: 320 mhp / 235 kW at 3800 rpm; 1 engine + 1 KMH50A + VC20; manufacturer 2021 package dry mass 435+52 kg and envelope with gear/elbow; standard 12V starter; front belt PTO optional capacity unverified; dealer includes mounts/panel/wiring/fluids; installed propulsion scope incomplete | U67: Dealer says in stock; exact stock and price validity RFQ | V67: 2026-09-11 | W67: NO_VERIFIED_NET | X67: PUBLIC_PRICE_NOT_KP | Y67: UNKNOWN | Z67: deliverables/M03/v001/01_support/yanmar/candidates.csv
A68: YAN-E02 | B68: ME-01 | C68: engine_bobtail | D68: Yanmar | E68: 6LPAM-STP2 bobtail (dealer); 6LPA-STP2 manufacturer | F68: 1 | G68: engine | H68: EUR | I68: 21675 | J68: excl BTW; NET explicitly listed | L68: 21675 | M68: https://useddieselenginecenter.nl/yanmar-6lpam-stp2-6-lpam-stp-2-bobtail | N68: https://www.yanmar.com/marine/product/engines/6lpa-stp2-6lpa-stc/ | R68: 408 | S68: CONDITIONAL_EU_NEWBUILD_CERT_DUTY_PTO_START_VOLTAGE; GEARBOX_NOT_PRICED | T68: New per dealer; 315 mhp / 232 kW at 3800 rpm at 25C fuel; 299 mhp / 220 kW at 40C per 2017 spec; priced engine only excluding gear/panel/harness; proposed 1 KMH50A RFQ; engine-only dry mass; package envelope 1220x666x739 drawing vs1190 length table conflict; package dry mass459 kg; 12V starter; RCD1 only evidenced | U68: Stock field0 conflicts with availability from stock; RFQ | V68: 2026-09-11 | W68: OBSERVED_NET_CONDITIONAL_SCOPE | X68: PUBLIC_PRICE_NOT_KP | Y68: UNKNOWN | Z68: deliverables/M03/v001/01_support/yanmar/candidates.csv | AA68: 21675
A69: YAN-E03 | B69: ME-01|ME-02 | C69: engine_gearbox | D69: Yanmar | E69: 6LY2M-WDT + YX-50S (proposed) | F69: 1 | G69: package | H69: EUR | J69: RFQ_REQUIRED | N69: https://www.yanmar.com/marine/product/engines/6ly2m-wdt/ | O69: 1412 | P69: 835 | Q69: 880 | R69: 643 | S69: RFQ_REQUIRED; CONDITIONAL_EU_NEWBUILD_CERT_DUTY_PTO | T69: Current official card330 mhp /243 kW at3200 rpm; 1 engine +1 proposedYX-50S; package dry mass535+108kg; envelope with gear/high-riser elbow; optional24V electrical system official but exact starter/configuration RFQ; IMO Tier2 shown not EU RCD approval; PTO capacity unverified | U69: Official current catalogue; European delivery and new-build certification RFQ | V69: 2026-09-11 | W69: NO_VERIFIED_NET | X69: PUBLIC_PRICE_NOT_KP | Y69: UNKNOWN | Z69: deliverables/M03/v001/01_support/yanmar/candidates.csv
A70: PAN-G01 | B70: ME-04|ME-19 | C70: generator | D70: Fischer Panda | E70: 12000x PMS JPC FP12000X | F70: 2 | G70: package | H70: GBP | I70: 16830 | J70: EXPLICIT_GROSS_NET_PAIR | K70: 20 | L70: 14025 | M70: https://www.jpcdirect.com/product/fischer-panda-12000x-generator/ | N70: https://www.onefischerpanda.com/fileadmin/content/product-information/marine-generators-compact-power/12000x/Panda_12000x_PMS_-_EN.pdf | O70: 705 | P70: 450 | Q70: 590 | R70: 195 | S70: MARKET_REFERENCE|START24V_OPEN|HOT_OUTPUT_OPEN|UK_IMPORT_OPEN | T70: 50Hz230V not yet accepted as220V target;2generators retained;standard datasheet12Vstarter, priced24V SKU unconfirmed. 10.2kW/12kVA NOMINAL at20C;2026catalogue treats0.85 kVA factor as short inductive starting only;hot continuous useful output OPEN. Capsule dimensions exclude fittings and service space;ME19 partial factory cooling only. JPC H565/192kg metadata conflicts withOEM. Fuel pump/looms/control panel/capsule advertised;exact control revision and install kit RFQ. | U70: Available on back-order;qty2/dateRFQ | V70: 2026-09-11 | W70: OBSERVED_NET_CONDITIONAL_SCOPE | X70: PUBLIC_PRICE_NOT_KP | Y70: UNKNOWN | Z70: deliverables/M03/v001/01_support/panda/candidates.csv | AA70: 16324.27
A71: PAN-G02 | B71: ME-04|ME-19 | C71: generator | D71: Fischer Panda | E71: 12000x-230V PMS NautiRadar0028284 | F71: 2 | G71: package | H71: EUR | I71: 17451.22 | J71: NET_EXPLICIT | L71: 17451.22 | M71: https://www.nautiradar.pt/en/products/fischer-panda/panda-12000x-230v-pms-12kva-fixed-engine-speed-marine-generator | N71: https://www.onefischerpanda.com/fileadmin/content/product-information/marine-generators-compact-power/12000x/Panda_12000x_PMS_-_EN.pdf | O71: 705 | P71: 450 | Q71: 590 | R71: 195 | S71: MARKET_REFERENCE|START24V_OPEN|HOT_OUTPUT_OPEN|SKU_REVISION_OPEN | T71: 50Hz230V not yet accepted as220V target;2generators retained;standard datasheet12Vstarter, priced24V SKU unconfirmed. 10.2kW/12kVA NOMINAL at20C;2026catalogue treats0.85 kVA factor as short inductive starting only;hot continuous useful output OPEN. Capsule dimensions exclude fittings and service space;ME19 partial factory cooling only. SellerSKU0028284 vsOEMsheet0024660:exact revision must be tied to offer. EU seller does not yet prove EU dispatch/free-circulation/Poland delivery. | U71: Stock and lead time not stated;qty2/dateRFQ | V71: 2026-09-11 | W71: OBSERVED_NET_CONDITIONAL_SCOPE | X71: PUBLIC_PRICE_NOT_KP | Y71: UNKNOWN | Z71: deliverables/M03/v001/01_support/panda/candidates.csv | AA71: 17451.22
A72: PAN-G03 | B72: ME-04|ME-19 | C72: generator | D72: Fischer Panda | E72: 15000i-230V PMS NautiRadar0000182 | F72: 2 | G72: package | H72: EUR | I72: 20128.46 | J72: NET_EXPLICIT | L72: 20128.46 | M72: https://www.nautiradar.pt/en/products/fischer-panda/panda-15000i-230v-pms-12kw-230v-variable-speed-marine-generator | N72: https://www.fischerpanda.co.uk/res/Fischer%20Panda%20Marine%20Generators%202026%20-%20FPUK | O72: 650 | P72: 465 | Q72: 589 | R72: 176 | S72: MARKET_REFERENCE|START24V_OPEN|HOT_OUTPUT_OPEN|INVERTER_SCOPE_OPEN | T72: Alternative model for same required useful output;not15kW.50Hz230V nominal12kW/15kVA;PMGi230V manual longterm12kW does not guarantee whole-set output at hot ambient;OEM20C engine reference.160kg capsule+16kg external inverter;dimensions capsule only;dealer162+16kg discrepancy. Inverter model/cooling/inclusion and24V starter RFQ.2gens retained;no automatic parallel operation. | U72: Stock and lead time not stated;qty2/dateRFQ | V72: 2026-09-11 | W72: OBSERVED_NET_CONDITIONAL_SCOPE | X72: PUBLIC_PRICE_NOT_KP | Y72: UNKNOWN | Z72: deliverables/M03/v001/01_support/panda/candidates.csv | AA72: 20128.46

Sheet 04_Подстановки_M05
A1: substitution_id | B1: target | C1: quantity_basis | D1: source_id | E1: seller | F1: model | G1: currency | H1: source_price | I1: source_tax_basis | J1: net_unit_source | K1: net_unit_eur | L1: gross_or_unknown_tax_price | M1: price_date | N1: access_date | O1: price_url | P1: substitution_note | Q1: status | R1: source_revision | S1: Включение в основную смету
A2: S01 | B2: ME-02 / missing gearbox for M03 YAN-E02 | C2: 1 candidate; inclusion/configuration conditional | D2: GA01 | E2: Palmer Power USA | F2: KMH50A-LP 2.13/2.43 for6LP-STP2 | G2: USD | H2: 4544.00 | I2: HTML valueAddedTaxIncluded=false; FAQ sales tax added in cart | J2: 4544.00 | K2: 3911.85 | M2: UNKNOWN; embedded priceValidUntil2020-03-25 conflicts with live offer | N2: 2026-09-11 | O2: https://palmerpower.com/yanmar-kmh50a-lp-kmh50a-lp-2-13-2-43-for-6lp-stp2/ | P2: Цена подставлена из Palmer Power USA, https://palmerpower.com/yanmar-kmh50a-lp-kmh50a-lp-2-13-2-43-for-6lp-stp2/; источник проверен 11.09.2026. Рабочий ориентир NET товара; priceValidUntil2020-03-25 конфликтует с живой карточкой. Состояние/доставка/ввоз/монтаж открыты. | Q2: LIVE_PRICE_VERIFIED; SOURCE_DATE_CONFLICT; NEW_CONDITION_OPEN; US_IMPORT_OPEN | R2: M05/gearbox-alternatives.csv | S2: НЕ ДОБАВЛЕНО: альтернативный6LPA; не повторять комплектный8LV
A3: S02 | B3: M04 GB03 / damper | C3: 1 candidate; inclusion/configuration conditional | D3: GB03 | E3: Dutch Engine Parts | F3: Yanmar119773-85520 damper HSW630 / Torflex1000 | G3: EUR | H3: 797.34 | I3: ex VAT directly stated | J3: 797.34 | K3: 797.34 | M3: UNKNOWN | N3: 2026-09-11 | O3: https://www.dutchengineparts.nl/damper-hsw630-119773-85520.html | P3: Цена подставлена из Dutch Engine Parts, https://www.dutchengineparts.nl/damper-hsw630-119773-85520.html; источник проверен 11.09.2026. Цена M04 сохранена: альтернатива IMC916.94NET выше на119.60EUR; добавить только при отсутствии в комплекте. | Q3: RETAIN_M04_VERIFIED_PRICE_WITH_OPEN_CONFIG | R3: deliverables/M04/v001/01_support/yanmar-addendum.csv | S3: НЕ ДОБАВЛЕНО: альтернативный6LPA; не повторять комплектный8LV
A4: S03 | B4: M04 A01 / one B panel | C4: 1 candidate; inclusion/configuration conditional | D4: A01 | E4: Dutch Engine Parts | F4: Yanmar 119773-91132 panel B | G4: EUR | H4: 1108.55 | I4: NET explicitly ex VAT | J4: 1108.55 | K4: 1108.55 | M4: UNKNOWN | N4: 2026-09-11 | O4: https://www.dutchengineparts.nl/panel-instrument-b-119773-91132.html | P4: Цена подставлена из Dutch Engine Parts, https://www.dutchengineparts.nl/panel-instrument-b-119773-91132.html; источник проверен 11.09.2026. Цена M04 сохранена: альтернативная Repuestos1408.42gross не имеет подтвержденного NET; одна панель. | Q4: RETAIN_M04_VERIFIED_PRICE_WITH_OPEN_CONFIG | R4: deliverables/M04/v001/01_support/yanmar-addendum.csv | S4: НЕ ДОБАВЛЕНО: альтернативный6LPA; не повторять комплектный8LV
A5: S04 | B5: M04 GB04 / gear oil cooler | C5: 1 candidate; inclusion/configuration conditional | D5: GB04 | E5: Dutch Engine Parts | F5: Yanmar177523-04820 oil cooler | G5: EUR | H5: 1636.17 | I5: ex VAT directly stated | J5: 1636.17 | K5: 1636.17 | M5: UNKNOWN | N5: 2026-09-11 | O5: https://www.dutchengineparts.nl/cooler-oil-177523-04820.html | P5: Цена подставлена из Dutch Engine Parts, https://www.dutchengineparts.nl/cooler-oil-177523-04820.html; источник проверен 11.09.2026. Цена M04 сохранена: Vmarine1521.64 из поиска прямо не проверена, не подставлена. | Q5: RETAIN_M04_VERIFIED_PRICE_WITH_OPEN_CONFIG | R5: deliverables/M04/v001/01_support/yanmar-addendum.csv | S5: НЕ ДОБАВЛЕНО: альтернативный6LPA; не повторять комплектный8LV
A6: S05 | B6: New 77760 harness price, not interchangeable with M04 A06 by default | C6: 1 candidate; inclusion/configuration conditional | D6: ALT-A02 | E6: YACHTNEEDS marketplace; fulfilling vendor unconfirmed | F6: Yanmar129574-77760 6m harness | G6: EUR | H6: 160.12 | I6: incl tax; shipping selector Denmark; rate not stated | L6: 160.12 | M6: UNKNOWN | N6: 2026-09-11 | O6: https://yachtneeds.com/yanmar-6m-wiring-harness-6-metres-129574-77760 | P6: Цена подставлена из YACHTNEEDS marketplace; fulfilling vendor unconfirmed, https://yachtneeds.com/yanmar-6m-wiring-harness-6-metres-129574-77760; источник проверен 11.09.2026. Товарная цена160.12gross при направлении Denmark; NET открыт и не суммируется. 77760 не заменяется ценой77720. | Q6: DIRECT_GROSS_CONFIRMED_NET_OPEN | R6: M05/ancillary-alternatives.csv | S6: НЕ ДОБАВЛЕНО: альтернативный6LPA; не повторять комплектный8LV

Sheet 05_Комплектность_M06
A1: item_id | B1: group | C1: item | D1: quantity | E1: unit | F1: quantity_basis | G1: branch_8lv | H1: branch_6lpa | I1: supply_boundary | J1: interfaces | K1: price_ref | L1: technical_source | M1: required_evidence | N1: closure_owner | O1: status | P1: acceptance | Q1: notes
A2: M01 | B2: PK01 | C2: Главный двигатель:8LV320 либо6LPA-STP2 | D2: 1 | E2: шт | F2: Одна силовая установка; две альтернативы не суммируются | G2: INCLUDED_DEALER_STATEMENT | H2: INCLUDED_DEALER_STATEMENT | I2: 8LV в пакете;6LPA bobtail | J2: Нагрузка/редуктор/пуск/фундаменты | K2: M03 YAN-E01 /YAN-E02 | L2: M03/yanmar/research.md; OEM8LV2021spec and2019manual; M04/gearbox.md; OEM6LPA2021spec and partsfig48 | M2: ТочныйSKU/серийная ревизия; допустимый длительный режим; документы применимостиЕС | N2: Поставщик двигателя + проектант | O2: OPEN | P2: Подтверждён требуемый полезный ходовой результат и допустимость поставки | Q2: 8LV320мhp не300continuous; оба исходно12V;6LPA RCD1 applicabilityOPEN
A3: M02 | B3: PK01 | C3: Редуктор KMH50A либо KMH50A-LP | D3: 1 | E3: шт | F3: Один из альтернативных редукторов | G3: INCLUDED_DEALER_STATEMENT | H3: SEPARATE | I3: 8LV вместе с двигателем;LP отдельное предложение | J3: Отношение/фланцы/направление вращения/управление | K3: M03 YAN-E01; M05 GA01/GA02/GA03 | L3: M04/gearbox.md; OEM6LPA2021spec and partsfig48 | M3: BOM исполнения; расчёт отношения и винта; состав охлаждения/управления | N3: Поставщик + проектант пропульсии | O3: OPEN | P3: Редуктор согласован с двигателем и винтом | Q3: LP ratio2.13 только кандидат; историческийGA03 не текущаяцена
A4: M03 | B4: PK01 | C4: Торсионный демпфер | D4: 1 | E4: шт | F4: Функционально1; отдельная закупка лишь если отсутствует в выбранном пакете | G4: OPEN | H4: OPEN | I4: Проверить включённость;119773-85520 только кандидат6LPA | J4: Маховик/входной вал/торсионные колебания | K4: M04 GB03 | L4: M04/gearbox.md; OEM6LPA2021spec and partsfig48 | M4: Совместимость/замена артикула; включённость; торсионное согласование | N4: Поставщик силового комплекта | O4: OPEN | P4: Один согласованный демпфер без двойного счёта | Q4: 85520 заменяет85500; не передний демпфер коленвала
A5: M04 | B5: PK01 | C5: Присоединительный корпус, фланцы, лапы и крепёж | E5: позиции BOM | F5: Количество после ведомости точного двигателя/редуктора | G5: OPEN | H5: OPEN | I5: Только стык двигателя с редуктором | J5: BorgWarner/SAE; болтовые соединения | L5: M04/gearbox.md; OEM6LPA2021spec and partsfig48 | M5: Монтажный чертёж и артикулы присоединения | N5: Поставщик комплекта | O5: OPEN | P5: Стык комплектен по монтажному BOM
A6: M05 | B6: PK01 | C6: Гребной вал | D6: 1 | E6: шт | F6: Предварительно одна валовая линия для одного двигателя; схема на согласовании | G6: SEPARATE | H6: SEPARATE | I6: Изготовление вала; без подшипников/уплотнения/винта | J6: Редуктор/дейдвуд/винт | L6: Проектная декомпозиция M06 | M6: Материал,диаметр,длина,конусы/шпонки,расчёт и чертёж | N6: Проектант пропульсии + изготовитель | O6: OPEN | P6: Вал соответствует утверждённой схеме | Q6: Число1 — рабочая схема, размерыOPEN
A7: M06 | B7: PK01 | C7: Выходная муфта валопровода | D7: 1 | E7: шт | F7: Один стык редуктора и вала по рабочей схеме | G7: OPEN | H7: OPEN | I7: Не входной демпферM03 | J7: Выходной фланец/осевая нагрузка/допуск несоосности | L7: Проектная декомпозиция M06 | M7: Чертёж фланца; допустимые нагрузки; включённость | N7: Проектант + поставщик | O7: OPEN | P7: Совместимый согласованный стык
A8: M07 | B8: PK01 | C8: Дейдвудное уплотнение | D8: 1 | E8: шт | F8: Один ввод вала по рабочей схеме | G8: SEPARATE | H8: SEPARATE | I8: Уплотнение и его локальные подключения | J8: Вал/корпус/охлаждение/аварийный доступ | L8: Проектная декомпозиция M06 | M8: Диаметр; режим смазки/водоснабжения; сервисный доступ | N8: Проектант + поставщик | O8: OPEN | P8: Герметичность и доступ по инструкции изделия
A9: M08 | B9: PK01 | C9: Дейдвуд, подшипники и наружные опоры | E9: позиции BOM | F9: Количество и состояние исходного корпуса после обследования | G9: OPEN | H9: OPEN | I9: Не закупать уже существующее без проверки | J9: Вал/корпус/гальваническая развязка | L9: Проектная декомпозиция M06 | M9: Обмеры исходного корпуса; схема опор; нагрузки | N9: Корпусный проектант + верфь | O9: OPEN | P9: Согласованы опоры и линия вала
A10: M09 | B10: PK01 | C10: Гребной винт | D10: 1 | E10: шт | F10: Один винт для рабочей одновальной схемы | G10: SEPARATE | H10: SEPARATE | I10: Тип/диаметр/шаг/лопасти не выбраны | J10: Вал/корпус/двигатель/редуктор | L10: Проектная декомпозиция M06 | M10: Расчёт хода и кавитации; зазоры; сопротивление под парусом | N10: Проектант пропульсии | O10: OPEN | P10: Достижение согласованных режимов без перегрузки двигателя
A11: M10 | B11: PK01 | C11: Отдельный упорный подшипник и гибкая передача | E11: условная позиция | F11: Только если выбрана схема с разгрузкой редуктора | G11: OPTIONAL | H11: OPTIONAL | I11: Не обязательное дополнение к любой муфте | J11: Осевая нагрузка/корпус/центровка | L11: Проектная декомпозиция M06 | M11: Решение по передаче упора и расчёт фундамента | N11: Проектант | O11: OPEN | P11: Схема утверждена или позиция исключена
A12: M11 | B12: PK01 | C12: Эластичные опоры двигателя/редуктора | E12: шт | F12: Тип/количество поBOM; не назначать4 без поставки | G12: INCLUDED_DEALER_STATEMENT | H12: OPEN | I12: Abma заявляет опоры8LV; bobtail6LPA проверить | J12: Масса/центр тяжести/фундаменты | K12: M03 YAN-E01 | L12: M03/yanmar/research.md; OEM8LV2021spec and2019manual; M04/gearbox.md; OEM6LPA2021spec and partsfig48 | M12: Артикулы/количество/допустимые нагрузки/регулировки | N12: Поставщик + верфь | O12: OPEN | P12: Опоры согласованы с нагрузкой и регулировкой
A13: M12 | B13: PK01 | C13: Фундаменты и усиления корпуса | E13: объёмы работ | F13: После обследования и расчёта | G13: SEPARATE | H13: SEPARATE | I13: Изменения алюминиевого корпуса под главный двигатель | J13: Опоры/упор/коррозия/обслуживание | L13: Проектная декомпозиция M06 | M13: Обмер,расчёт,чертежи,материалы/сварка | N13: Корпусный проектант + верфь | O13: OPEN | P13: Приняты геометрия и качество работ
A14: M13 | B14: PK09 | C14: Подача и возврат топлива главного двигателя | E14: позиции/м поBOM | F14: Трасса/арматура/длиныOPEN | G14: SEPARATE | H14: SEPARATE | I14: Внешний контур от границы танка до двигателя; безгенераторов | J14: Танк/насос/расход/обратное давление | L14: OEM manuals8LV/6LPA; M03research | M14: Схема; диаметры; материалы; запорная арматура; допустимые давления | N14: Системный проектант + верфь | O14: OPEN | P14: Герметичность и параметры подачи/возврата подтверждены
A15: M14 | B15: PK09 | C15: Предварительная фильтрация/водоотделение топлива | E15: шт | F15: Число фильтров и необходимость резервирования по схеме | G15: OPEN | H15: OPEN | I15: Не путать со штатным фильтром на двигателе | J15: Топливоподача/обслуживание/сигнализация | L15: OEM engine specs; M03research | M15: Штатная комплектность; требуемая тонкость/расход/перепад | N15: Поставщик + системный проектант | O15: OPEN | P15: Фильтрация соответствует инструкции двигателя
A16: M15 | B16: PK09 | C16: Интерфейс топливных танков | E16: позиции BOM | F16: Ёмкость/число танков здесь не назначаются | G16: OPEN | H16: OPEN | I16: Отбор/возврат/отсечка/очистка; сами танки отдельный корпусной/системный пакет | J16: Общие танки яхты и отдельные потребители | L16: Проектная декомпозиция M06 | M16: Согласованные штуцеры/уровни/режимы и границы пакетов | N16: Системный проектант | O16: OPEN | P16: Утверждены интерфейсы без дублирования танков
A17: M16 | B17: PK09 | C17: Забортное охлаждение главного двигателя | E17: позиции/м поBOM | F17: Число вводов и длины после схемы | G17: SEPARATE | H17: SEPARATE | I17: Ввод/кингстон/фильтр/шланги/антисифон по применимости; безгенераторов | J17: Корпус/насос/теплообменники/выхлоп | L17: OEM manuals8LV/6LPA | M17: Расход/сопротивление/уровни при крене; развязка металлов | N17: Системный проектант + верфь | O17: OPEN | P17: Согласован расход; исключено обратное затопление по проекту
A18: M17 | B18: PK01|PK09 | C18: Штатный замкнутый контур охлаждения двигателя | E18: позиции BOM | F18: Проверить все штатные и выносные элементы | G18: OPEN | H18: OPEN | I18: Встроенный насос/теплообменник и расширение; проверитьBOM двигателя | J18: Высоты/развоздушивание/жидкость | L18: OEM8LV2021 and6LPA2021spec | M18: BOM; выносной бак/линии если нужны; инструкция заполнения | N18: Поставщик | O18: OPEN | P18: Полный согласованный контур без вторичной покупки штатных узлов
A19: M18 | B19: PK01|PK09 | C19: Маслоохладитель редуктора с подключением | D19: 1 | E19: функциональный узел | F19: Один контур однойкоробки; состав деталейOPEN; закупка по включённости | G19: OPEN | H19: OPEN | I19: GB04 только теплообменник, не готовый узел | J19: Редуктор/водяной контур/кронштейны/масляные шланги | K19: M04 GB04 | L19: M04/gearbox.md; OEM6LPA2021spec and partsfig48 | M19: Серийныйвариант; полныйBOM; включённость в пакет | N19: Поставщик редуктора | O19: OPEN | P19: Проверены давление/температура и отсутствие течей
A20: M19 | B20: PK01|PK09 | C20: Смесительное выпускное колено | D20: 1 | E20: шт | F20: Один выпуск; тип L/high-riser после отметок | G20: OPEN | H20: OPEN | I20: Сверить комплектность выбранногоSKU; альтернативные колена не складывать | J20: Двигатель/забортнаявода/выхлоп | L20: OEM8LV2021 and6LPA2021spec | M20: Тип/материал/высоты/включённость | N20: Поставщик + системный проектант | O20: OPEN | P20: Колено соответствует монтажной схеме
A21: M20 | B21: PK09 | C21: Внешний выпуск главного двигателя | E21: позиции/м поBOM | F21: Трасса,водянойзамок/глушитель/петли/выпуск порасчёту | G21: SEPARATE | H21: SEPARATE | I21: От колена до выхода за борт; без выпусков генераторов | J21: Противодавление/затопление/шум/температура | L21: OEM manuals8LV/6LPA | M21: Чертёж/длины/сечения/расчёт противодавления и водяногообъёма | N21: Системный проектант + верфь | O21: OPEN | P21: Противодавление/защита от воды соответствуют OEM
A22: M21 | B22: PK09 | C22: Воздух двигателя и интерфейс вентиляции МО | E22: расчёт/позиции BOM | F22: Расходы/сечения/число вентиляторовOPEN | G22: OPEN | H22: OPEN | I22: Требования главного двигателя к общей вентиляции; общий пакетМО не дублируется | J22: Генераторы/теплоприток/входы/выходы/шум | L22: OEM manuals8LV/6LPA | M22: Теплобаланс/расход воздуха/потери и общий ответственный PK09 | N22: Системный проектант | O22: OPEN | P22: Общая система обеспечивает согласованную среду для двигателя
A23: M22 | B23: PK01|PK12 | C23: Механический PTO и присоединение гидронасоса | E23: условные позиции | F23: Не назначен; одно утверждённое решение после баланса | G23: OPTIONAL | H23: OPEN | I23: Только механическое присоединение; насос/гидросеть уэлектрогидроагента | J23: Обороты/момент/винт/крепление/сцепление | L23: OEM8LVspec optionalbeltPTO; M04notes | M23: Допустимый отбор пооборотам/режиму; одновременнаянагрузка | N23: Поставщик двигателя + гидропроектант | O23: OPEN | P23: Есть письменное согласование выбранного отбора | Q23: РеменныйPTO не подтверждает мощность всех гидропотребителей
A24: M23 | B24: PK10 | C24: Интерфейс пожарной защиты и аварийных отсечек | E24: позиции BOM | F24: Число устройств определяет общий проектМО | G24: OPEN | H24: OPEN | I24: Только требования этой установки; общий пожарный пакет отдельно | J24: Топливо/вентиляция/дистанционныйостанов/электрика | L24: Проектная декомпозиция M06 | M24: Согласованные интерфейсы остановки и защиты; требования применимости | N24: Системный проектант + поставщик | O24: OPEN | P24: Защита и остановка проверены совместно без дублей устройств
A25: M24 | B25: PK09 | C25: Заправочные жидкости, слив/замена масла и поддоны | E25: л/шт поBOM | F25: ОбъёмыOPEN; комплекта1 не назначено | G25: OPEN | H25: OPEN | I25: Abmaжидкости заявлены; внешний слив/поддоны не заявлены | J25: Двигатель/редуктор/сбор отходов/доступ | K25: M03 YAN-E01 | L25: M03/yanmar/research.md; OEM8LV2021spec and2019manual; M04/gearbox.md; OEM6LPA2021spec and partsfig48 | M25: Первые заправки/BOM; точкислива; объёмподдонов; процедурасервиса | N25: Поставщик + верфь | O25: OPEN | P25: Жидкости и безопасное обслуживание обеспечены без двойного счёта
A26: M25 | B26: PK01 | C26: Сервисные зоны и путь демонтажа | E26: чертежи/обмер | F26: Размеры и объёмыOPEN | G26: OPEN | H26: OPEN | I26: Монтажныйобъём главнойустановки, не наружныйгабарит | J26: Фильтры/ремни/колено/редуктор/люки/подъём | L26: M03yanmarresearch; OEM installationGA required | M26: GA сдоступами,масса/ЦТ,обмерМО и путьвыноса | N26: Компоновщик + поставщик + верфь | O26: OPEN | P26: Проверена доступность; помещаемость не выводится изэскиза | Q26: 8LV1340x880x766 толькосправочныйгабарит;6LPAконфликтстарыхразмеровOPEN
A27: M26 | B27: PK01 | C27: Монтаж и центровка силовой линии | E27: объёмы работ | F27: После чертежей; часы/операцииOPEN | G27: SEPARATE | H27: SEPARATE | I27: Установка,крепление,подключение,центровка; без изготовленияM12 | J27: Все механическиестыки/спускнаводу | L27: Проектная декомпозиция M06 | M27: Технология/допуски/проверка после спуска | N27: Верфь + сервис OEM | O27: OPEN | P27: Подписанный монтажный ицентровочный протокол
A28: M27 | B28: PK01 | C28: Первые пуски,швартовные иходовые проверки | E28: операции испытаний | F28: План и длительностьOPEN | G28: OPEN | H28: OPEN | I28: Испытания главнойустановки; общий судовойплан уroot | J28: Нагрузка/температуры/давления/вибрации/течи/останов | L28: OEM manuals8LV/6LPA; M03duty notes | M28: Согласованный план/критерии и гарантийный ввод | N28: Верфь + OEMсервис + проектант | O28: OPEN | P28: Закрыты критерии согласованного плана и замечания
A29: M28 | B29: PK01 | C29: Документация,обучение и стартовый ЗИП | E29: документы/позиции BOM | F29: Состав документов и расходниковOPEN | G29: OPEN | H29: OPEN | I29: Главнаяустановка; штатные поставки учитывать | J29: Гарантия/серийныеномера/регламент/применимостьЕС | L29: M03/M04/M05 evidence | M29: As-built/BOM/руководства/сертификаты/гарантия/переченьЗИП | N29: Поставщик + верфь | O29: OPEN | P29: Документы переданы; персонал ознакомлен; ЗИП согласован
A30: EH01 | B30: EXISTING_MAIN_COMPONENT_REFS | C30: Ссылка на ранее заданные аккумуляторы; не новая закупочная строка | E30: reference only | F30: Уже задано 6+2+1=9; quantity пусто для исключения повторного суммирования | G30: N_A | H30: N_A | I30: M01 ME-07:1 пусковая; ME-08:6 сервисных; ME-27:2 генераторных | J30: Батареи / двигатели / заряд / резервный пуск | K30: M01 ME-07|ME-08|ME-27 | L30: deliverables/M01/v001/01_support/owner-requirements.md D018 | M30: Паспорта: напряжение каждой АКБ, химия, Ah, CCA и стандарт CCA, BMS и допустимый пусковой ток | N30: Владелец исходных данных + электропроектировщик | O30: OPEN | P30: В ведомости остаётся 9 физических АКБ; заполнены паспортные характеристики всех 9 | Q30: 115 ампер не преобразовано в 115 Ah; ссылка не означает наличие купленных АКБ
A31: EH02 | B31: START | C31: Исполнение пуска 24 В для точного двигателя | E31: functional scope | F31: Количество аппаратов определяется согласованной схемой | G31: OPEN | H31: OPEN | I31: Поставщик двигателя: стартер, соленоид, реле, генератор, ECU/приборы/датчики по совместимой схеме | J31: 24 VDC / штатная электрика двигателя | K31: M03 YAN-E01|YAN-E02 | L31: https://www.yanmar.com/marine/wp-content/uploads/2020/03/DS_8LV320-350-370_A4_2021_1018_HR.pdf?download=1 | https://www.yanmar.com/marine/wp-content/uploads/2020/05/Yanmar-Datasheet_6LPA-STP2.pdf?download=1 | M31: Есть ли одобренное OEM исполнение 24 В? Дайте SKU, схему, ограничения и гарантийное подтверждение; при отсутствии прямо укажите | N31: Yanmar / поставщик двигателя | O31: OPEN | P31: Документирована реализуемая архитектура с требованием 24 В; изменения согласованы до закрытия | Q31: Паспорта показывают штатно 12 В; отсутствие найденной опции не доказательство невозможности. Ветка 12 В не принята
A32: EH03 | B32: START | C32: Матрица резервного пуска от каждого исправного донора | E32: functional scope | F32: Количество аппаратов определяется согласованной схемой | G32: OPEN | H32: OPEN | I32: Системное решение, не один контактор | J32: Каждая из 9 АКБ / пусковые цели / работоспособность основной нагрузки | K32: M01 ME-28 | L32: deliverables/M01/v001/01_support/owner-requirements.md D018 | M32: Для каждого донора: допустимая цель, напряжение, доступный ток/энергия, условия SOC/температуры, BMS, способ преобразования если нужен | N32: Электропроектировщик + OEM двигателей | O32: OPEN | P32: Каждый требуемый сценарий подтверждён расчётом и программой испытаний; ограничения явно приняты | Q32: Не обещать запуск от любой одиночной АКБ до проверки; не добавлять АКБ и не назначать последовательную схему
A33: EH04 | B33: START | C33: Дистанционное отсоединение отказавшей батареи и коммутация донора | E33: functional scope | F33: Количество аппаратов определяется согласованной схемой | G33: SEPARATE | H33: SEPARATE | I33: Контакторы/изоляторы/блокировки как один функциональный узел; число по схеме | J33: Отказ КЗ / разряд / BMS trip / залипание контакта | K33: M01 ME-28 | L33: deliverables/M01/v001/01_support/owner-requirements.md D018 | M33: Однолинейная схема и последовательность: обнаружение, изоляция повреждённой ветви, подтверждение положения, разрешение донора | N33: Электропроектировщик + сборщик щита | O33: OPEN | P33: Отказавшая АКБ не подключается обратно через резерв; исключено недопустимое соединение источников | Q33: Прямая короткая перемычка между неизвестными напряжениями не решение; предусмотреть местное аварийное действие
A34: EH05 | B34: START | C34: Питание и индикация дистанционного резервного управления | E34: functional scope | F34: Количество аппаратов определяется согласованной схемой | G34: SEPARATE | H34: SEPARATE | I34: Цепи управления/сигнализации, источник независим от отказавшей пусковой ветви | J34: Пост управления / контакторы / обратная связь | K34: M01 ME-28 | L34: deliverables/M01/v001/01_support/owner-requirements.md D018 | M34: Откуда питается управление при обесточенной пусковой АКБ? Схема, индикация реальных положений и ручное восстановление | N34: Электропроектировщик | O34: OPEN | P34: Дистанционный перевод доступен при заданном отказе; потеря питания не создаёт опасное соединение
A35: EH06 | B35: START | C35: Пусковые кабели, защита и отключающая способность | E35: functional scope | F35: Количество аппаратов определяется согласованной схемой | G35: SEPARATE | H35: SEPARATE | I35: Внешняя силовая проводка, наконечники, защита и прокладка | J35: Стартер / контакторы / батареи / общий возврат | K35: M01 ME-28 | L35: https://www.yanmar.com/marine/wp-content/uploads/2020/03/DS_8LV320-350-370_A4_2021_1018_HR.pdf?download=1 | https://www.yanmar.com/marine/wp-content/uploads/2020/05/Yanmar-Datasheet_6LPA-STP2.pdf?download=1 | M35: Длина трасс, ток пуска/КЗ, падение напряжения, длительность пуска, нагрев, DC ratings защиты/контактов; обоснование исключений защиты пусковой цепи | N35: Электропроектировщик + электромонтажник | O35: OPEN | P35: Расчёт и спецификация покрывают штатный и резервный пуск, ток КЗ и среду МО | Q35: Не назначать сечение или номинал по мощности стартера без пускового тока
A36: EH07 | B36: POWER | C36: Заряд и разделение источников | E36: functional scope | F36: Количество аппаратов определяется согласованной схемой | G36: OPEN | H36: OPEN | I36: Штатный генератор двигателя отделён от судового распределения и зарядных устройств | J36: Сервис / 2 генераторные / главная пусковая / инверторы-зарядники | K36: M01 ME-05|ME-10|ME-28; M03 YAN-E01|YAN-E02 | L36: deliverables/M01/v001/01_support/owner-requirements.md D018 | https://www.yanmar.com/marine/wp-content/uploads/2020/03/DS_8LV320-350-370_A4_2021_1018_HR.pdf?download=1 | https://www.yanmar.com/marine/wp-content/uploads/2020/05/Yanmar-Datasheet_6LPA-STP2.pdf?download=1 | M36: Матрица зарядных режимов химии/BMS, напряжения, токи, изоляция обратных токов, действия при отказе/размыкании нагрузки | N36: Электропроектировщик + OEM | O36: OPEN | P36: Ни одна АКБ не заряжается несовместимым режимом; резервная коммутация согласована с работающими зарядниками | Q36: Не добавлять отдельный преобразователь до выбора архитектуры; 12-вольтовый генератор не принят как судовая сеть
A37: EH08 | B37: POWER | C37: Распределение 24 VDC / 220 VAC и возврат токов | E37: functional scope | F37: Количество аппаратов определяется согласованной схемой | G37: SEPARATE | H37: SEPARATE | I37: Судовые щиты/кабели/защита; число шкафов пока не задано | J37: Берег / 2 генератора / инверторы / алюминиевый корпус | K37: M01 ME-04|ME-05|ME-09|ME-10 | L37: deliverables/M01/v001/01_support/owner-requirements.md D018 | M37: Однолинейная схема: напряжение/частота, переключение источников, защита утечки, PE/DC return, уравнивание потенциалов и коррозионная защита | N37: Электропроектировщик + верфь | O37: OPEN | P37: Подтверждены 24 В DC и 220 В AC для потребителей; исключены непредусмотренная параллель источников и токовый возврат через корпус | Q37: 50 Гц — прежняя проектная цель, не новое подтверждение владельца; 230 В паспортов согласовать с 220 В требованием
A38: EH09 | B38: CONTROL | C38: Приборная панель и моторный жгут | E38: functional scope | F38: Количество аппаратов определяется согласованной схемой | G38: INCLUDED_DEALER_STATEMENT | H38: SEPARATE | I38: 8LV заявлен VC20/панель/проводка; 6LPA выбрать одну B/C/D и верный жгут | J38: Двигатель / пост / сигнализация / напряжение | K38: M03 YAN-E01; M04 A01|A02|A03|A06 | L38: deliverables/M04/v001/01_support/ancillaries.md | M38: Упаковочная спецификация, SKU панели и моторного/удлинительного жгута, длины, разъёмы и рабочее напряжение | N38: Поставщик двигателя | O38: OPEN | P38: Состав подтверждён по точному серийному исполнению; встроенные датчики/детали панели не задвоены | Q38: Для STP2 77760 против старого 77720; длина 6 м условна
A39: EH10 | B39: CONTROL | C39: Газ/реверс, нейтраль и разрешение пуска | E39: functional scope | F39: Количество аппаратов определяется согласованной схемой | G39: OPEN | H39: SEPARATE | I39: 8LV проверить состав VC20; 6LPA механический пост, тросы, кронштейны и нейтральная блокировка | J39: Редуктор / двигатель / PTO / посты | K39: M04 A07; M03 YAN-E01 | L39: deliverables/M04/v001/00_yanmar-completeness.md | M39: Схема управления и комплектность каждого поста; нейтральный датчик, ход тросов/актуаторов, отказ питания | N39: Поставщик управления + верфь | O39: OPEN | P39: Пуск при включённой передаче заблокирован; команды PTO/газа/реверса согласованы | Q39: Панель приборов не заменяет управление движением; число постов открыто
A40: EH11 | B40: HYDRAULIC | C40: Профиль гидравлических потребителей | E40: functional scope | F40: Количество аппаратов определяется согласованной схемой | G40: SEPARATE | H40: SEPARATE | I40: Подруливающие устройства и все лебёдки; это обязательный тип привода | J40: Каждый потребитель / насосы / распределители | K40: M01 ME-29 | L40: deliverables/M01/v001/01_support/owner-requirements.md D018 | M40: По каждому потребителю: давление, расход, длительность, пусковой переход, направление; таблица одновременных режимов | N40: Гидропроектировщик + поставщики потребителей | O40: OPEN | P40: Все подрульки и лебёдки включены в нагрузочную матрицу; основные режимы согласованы | Q40: Не добавлять электрические приводы вместо обязательной гидравлики
A41: EH12 | B41: HYDRAULIC | C41: Допустимый PTO и сопряжение насоса | E41: functional scope | F41: Количество аппаратов определяется согласованной схемой | G41: OPTIONAL | H41: OPEN | I41: 8LV опциональный передний ременный PTO; 6LPA подтверждённого привода нет | J41: Коленвал / ремни или муфта / насос / редуктор | K41: M03 YAN-E01|YAN-E02 | L41: https://www.yanmar.com/marine/product/engines/8lv320/ | M41: Кривые допустимой мощности/момента PTO по оборотам, боковые нагрузки, комплект привода, передача и ограничения гарантий | N41: Yanmar + поставщик гидросистемы | O41: OPEN | P41: OEM подтвердил точный привод и насос во всём требуемом диапазоне | Q41: Гидравлическое включение KMH50A не является внешним гидравлическим PTO
A42: EH13 | B42: HYDRAULIC | C42: Основной насос и управление расходом | E42: functional scope | F42: Количество аппаратов определяется согласованной схемой | G42: SEPARATE | H42: SEPARATE | I42: Насосный функциональный пакет; число насосов и секций открыто | J42: PTO / электрический или иной согласованный источник / распределение | K42: M01 ME-29 | L42: deliverables/M01/v001/01_support/owner-requirements.md D018 | M42: Рабочие точки p-Q, КПД, обороты, управление расходом, разгрузка, допустимость сухого пуска и кавитационный запас | N42: Гидропроектировщик | O42: OPEN | P42: Потребители обеспечены в согласованных режимах без превышения PTO/привода | Q42: Оборудование не выбирать только по максимальному давлению
A43: EH14 | B43: HYDRAULIC | C43: Совместный баланс ходовой мощности и гидравлики | E43: functional scope | F43: Количество аппаратов определяется согласованной схемой | G43: OPEN | H43: OPEN | I43: Расчёт режимов всей силовой установки | J43: Двигатель / винт / насос / генерация электроэнергии | K43: M03 YAN-E01|YAN-E02 | L43: https://www.yanmar.com/marine/wp-content/uploads/2020/03/DS_8LV320-350-370_A4_2021_1018_HR.pdf?download=1 | https://www.yanmar.com/marine/wp-content/uploads/2020/05/Yanmar-Datasheet_6LPA-STP2.pdf?download=1 | M43: Баланс по оборотам и продолжительности: ход+подрульки+лебёдки; ограничения включения и минимальные обороты | N43: Судовой проектировщик + OEM + гидропроектировщик | O43: OPEN | P43: Нет превышения длительного рейтинга двигателя и привода; доступная тяга показана | Q43: Паспортная пиковая мощность двигателя не равна непрерывной мощности PTO
A44: EH15 | B44: HYDRAULIC | C44: Резерв работоспособности при отказе основного насоса/двигателя | E44: functional scope | F44: Количество аппаратов определяется согласованной схемой | G44: OPEN | H44: OPEN | I44: Функция резерва; отдельный второй насос не назначен | J44: Донор энергии / аварийные режимы / необходимые потребители | K44: M01 ME-29 | L44: deliverables/M01/v001/01_support/owner-requirements.md D018 | M44: Сценарии отказа и минимально необходимые операции; варианты независимого привода, переключение и энергобаланс | N44: Гидропроектировщик + судовой проектировщик | O44: OPEN | P44: Согласованы обеспечиваемые аварийные функции и испытание переключения | Q44: Резервный пуск двигателя и резерв гидравлики — разные задачи; насос пресной воды ME-06 сюда не относится
A45: EH16 | B45: HYDRAULIC | C45: Бак, фильтрация, охладитель и обвязка | E45: functional scope | F45: Количество аппаратов определяется согласованной схемой | G45: SEPARATE | H45: SEPARATE | I45: Полный вспомогательный гидропакет; объёмы и число аппаратов по расчёту | J45: Воздух/вода охлаждения / корпус / МО / гидроприводы | K45: M01 ME-29 | L45: deliverables/M01/v001/01_support/owner-requirements.md D018 | M45: Тепловой баланс, температура масла, резервуар/деаэрация, фильтрация, датчики загрязнения/уровня, трубопроводы и обслуживание | N45: Гидропроектировщик + верфь | O45: OPEN | P45: Температура и чистота масла обеспечены в худшем согласованном цикле; комплектность/доступ показаны | Q45: Охладитель масла редуктора M04 не подменяет охладитель внешней гидросистемы
A46: EH17 | B46: HYDRAULIC | C46: Защитные функции и условный аккумулятор давления | E46: functional scope | F46: Количество аппаратов определяется согласованной схемой | G46: OPEN | H46: OPEN | I46: Предохранение от превышения давления/неуправляемого движения; аккумулятор только если требуется расчётом | J46: Клапаны / удержание нагрузок / аварийный останов / сброс энергии | K46: M01 ME-29 | L46: deliverables/M01/v001/01_support/owner-requirements.md D018 | M46: Схема предохранительных/удерживающих клапанов, ручной сброс, аварийный останов; для аккумулятора обоснование, объём и изоляция | N46: Гидропроектировщик + поставщики лебёдок/подрулек | O46: OPEN | P46: Нагрузки безопасно удерживаются при потере давления; остаточная энергия контролируема | Q46: Аккумулятор давления не назначен обязательным и не является электрической АКБ
A47: EH18 | B47: VERIFICATION | C47: Совместные приёмочные испытания пуска и гидравлики | E47: functional scope | F47: Количество аппаратов определяется согласованной схемой | G47: OPEN | H47: OPEN | I47: Программа FAT/SAT и комплект исполнительных схем | J47: Электрика / двигатель / PTO / гидравлика / оператор | K47: M01 ME-28|ME-29 | L47: deliverables/M01/v001/01_support/owner-requirements.md D018 | M47: Протоколы штатного и резервного пуска, изоляции отказа, потери управления, совместной нагрузки и температурного цикла | N47: Верфь + системные поставщики + независимая приёмка | O47: OPEN | P47: Результаты сопоставлены с числовыми критериями утверждённого проекта; замечания закрыты | Q47: Это будущие критерии приёмки, не заявление уже выполненных испытаний
A48: G01 | B48: GENERATOR_INTERFACE | C48: Два дизель-генератора как интерфейс силовой установки | D48: 2 | E48: шт. | F48: M01:2 генератора; две модели рассматриваются альтернативно, не суммируются | G48: SEPARATE | H48: SEPARATE | I48: PK02: агрегаты/капсулы/заводская комплектация; внешние ветви G02, электрическая коммутация EH | J48: Нагрузки AC/заряд/пуск/тепло/гидравлический резерв | K48: M03 PAN-G02|PAN-G03; комплектность не закрыта | L48: deliverables/M03/v001/01_support/panda/candidates.csv | M48: Два точных SKU; полезная мощность при температуре МО;24Впуск; 220Всовместимость; BOM/GA | N48: Fischer Panda + электропроектировщик | O48: OPEN | P48: Два агрегата подтверждены по одному согласованному требованию к полезному выходу; выбранная модель/режим документированы | Q48: Не назначены параллель и номинальная сумма мощностей; генераторы не посчитаны повторно в главном двигателе
A49: G02 | B49: GENERATOR_INTERFACE | C49: Внешние топливные, забортные и выхлопные ветви двух генераторов | E49: по схеме | F49: Два обслуживаемых агрегата; количества клапанов/фильтров/проходов и длины пока неизвестны | G49: SEPARATE | H49: SEPARATE | I49: PK09: вне заводского пакета; главному двигателю соответствуют механические строки | J49: G01 / корпус / водолиния / крен / вентиляция / отсечки | K49: M03 PK09; поставку и монтаж закрыть отдельно | L49: deliverables/M03/v001/01_support/packages.csv | M49: Схема каждой ветви, OEMпределы, отказ/обратныйпереток/сифон, BOMтруб/арматуры; функции общей и индивидуальной отсечки | N49: Механик + OEM + верфь | O49: OPEN | P49: Отказ/ремонт одного генератора не лишает второй предусмотренной работоспособности; испытания каждой ветви | Q49: Общий топливный танк не объявлен независимостью систем; общие причины отказа анализируются; вентиляция общая учитывается единожды
A50: G03 | B50: GENERATOR_INTERFACE | C50: Крепление, монтаж и пусконаладка генераторов | E50: работы по двум агрегатам | F50: Нормочасы, крепёж, центровка/проверка вибрации и испытания по монтажному проекту | G50: SEPARATE | H50: SEPARATE | I50: PK02: собственный монтаж/локальные испытания; общие электросистемные испытания EH отдельно | J50: G01 / фундаменты / шум / изоляция / сервис / программа приёмки | K50: M03 PK02; цена работ OPEN | L50: deliverables/M03/v001/01_support/packages.csv | M50: Расчёт креплений, рабочая и сервисная масса, маршрут заноса/извлечения; протокол по одному и двум агрегатам | N50: Верфь + сервис Fischer Panda | O50: OPEN | P50: Оформлены крепления и доступ; подтверждена работа в согласованных режимах; гарантийный ввод | Q50: Заводские опоры не покупать второй раз при включении в G01

Sheet 06_Основания
A1: Тема | B1: Основание / предел
A2: Статус | B2: M07/v001 — выпуск текущей рабочей сметы по имеющимся сведениям. Не утверждённая УТВ, не заказ, не полный бюджет установленного МО.
A3: НДС в строках | B3: По уточнению владельца23% включены предварительно для известныхNET; SOURCE_GROSS уже сналогом, без повторного начисления. Налоговый вычет не применён.
A4: Смешанный gross | B4: Yanmar58842EUR включает налог неизвестнойставки. Его NET/VATневыделены. Общая оценённаяgrossсумма не единая унифицированная польская налоговая база и не график платежей.
A5: Открытые затраты | B5: Нулевых цен для неизвестного нет. Пустые количества/стоимости требуютданных; полныйитог незадан. Монтаж/материалы/трассы/таможня/ПНР не закрыты.
A6: Варианты | B6: Рабочая ветвьB сохранена изM03: Yanmar/Panda. Это не выбор закупки и не средний ценовойранг. A/C показаны в отдельном сравнении; альтернативы не складываются.
A7: Размещение | B7: По поручению владельца дальнейшаякомпоновка по сечениям проекта отдельно; G03не блокирует фиксациюэтогосостояниясметы и не подтверждает fit.
A8: Предыдущие версии | B8: U01/M01–M06/G03/EXP003 сохранены; сметные числа не перенесены в утверждённыйбюджет.
A9: Резерв | B9: Процент риска, накладных и установкиневыдуман. Неоценённыеработы не компенсированы произвольнойнадбавкой.
A10: Первичная ставкаPL | B10: https://www.podatki.gov.pl/podatki-firmowe/vat/stawki-i-limity
A11: Основание источников | B11: M03/v001 цены11.09.2026 и справочныйFX10.09.2026. M05подстановки отдельно. Новый поиск цен не выполнялся.
A12: Округление | B12: ИсходныйNET→EURценаединицы какM03; количество×цена округляетсяHALF_UP доцента, затемVATстроки доцента, итогсуммируетстроки.
... A14: Состав команды | B14: Propulsion:experiment_basis;охват:tools_freecad;сведение:root;независимыйвыпуск:experiment_model
