Workbook

Sheet 00_Старт
A1: Тема | B1: Правило
A2: Статус | B2: M03 / 11.09.2026 — рабочая КАЦ с открытыми исходными данными. 36 слотов A/B/C для 12 функциональных пакетов; это не 36 полученных КП и не три утверждённых комплекта яхты.
A3: Yanmar и Fischer Panda | B3: Yanmar добавлен отдельными новыми источниками. Fischer Panda сохранён, добавлены предложения/исполнения. Наличие марки не означает выбор или совместимость с сетью/пуском.
A4: Сравниваем результат | B4: Разные устройства и внутренний BOM допустимы при нужном результате. Основные заданные количества сохраняются. A/B/C — гипотезы исполнения, не ранг цены или качества.
A5: Порядок работы | B5: Согласовать результат и BOM → дополнить источники цен/КП → закрыть комплектность со ссылками → проверить технику/коммерческие условия → доставка и налоги → решение. Слоты PK09–PK11 пока используют общие ориентиры, не три независимые поставки.
A6: Листы | B6: 01: функциональное задание; 02: цены и прямые URL; 03: построчный состав вариантов; 04: полнота; 05: КАЦ; 06: налоговые операции; 07: открытые вопросы.
A7: Известная часть | B7: На листе 05 сумма известных товаров дана отдельно. Полный NET появится только после закрытия состава, цен, исключений источников и двух допусков. Пустая ячейка не означает ноль. Общего итога МО нет.
A8: Количество | B8: 1 двигатель; 2 генератора; 2 основных инвертора; 6+2+1 физических АКБ; 1 водяная установка каждого питания; 1 опреснитель; 2 чиллера. ME06 — 1 функция резерва, не обязательный третий инвертор. Количество бойлеров и обвязки открыто.
A9: Цена | B9: NET в исходной валюте → единичный EUR с округлением HALF_UP до цента → количество. GBP / 0.85915, ECB 10.09.2026. Курс для сравнения, не автоматический курс налоговой декларации.
A10: Доплаты | B10: В 05_КАЦ шесть полей доплат: доставка, страхование, пошлина, оформление, монтаж/ПНР и прочее. Ввести обоснованный ноль, если затрата отсутствует или уже включена. Не учитывать повторно включённую услугу.
A11: НДС | B11: Покупатель, VAT-UE и использование яхты ещё неизвестны. На 06_НДС нет ставки 23% по умолчанию и автоматического вычета. Операции разделять по счетам/таможенным документам; не применять одну ставку ко всему варианту без основания.
A12: НДС и деньги | B12: Невозмещаемый VAT входит в стоимость, вычет показывается отдельно. Денежный платёж и ожидаемый возврат вводятся отдельно: при WNT зачёт может быть без оплаты VAT. График финансирования ещё не рассчитан.
... A15: Сохранность | B15: Исходные U01/M01/M02 и чертежи сохранены. Полные сторонние PDF локально .local/M03, ссылки и SHA в сопровождении. Поставщикам ничего не отправлено.

Sheet 01_Пакеты
A1: Пакет | B1: Результат / система | C1: Группы M01 | D1: Требуемый выход | E1: Фиксированные количества | F1: Полная граница поставки | G1: Критерий приёмки | H1: Открытые параметры
A2: PK01 | B2: Ход яхты | C2: ME-01|ME-02|ME-03 | D2: Нужные скорость, тяга, длительная работа, манёвр и привод гидравлики | E2: 1 двигатель; 1 редуктор предлагается | F2: Двигатель и согласованный редуктор, заводские опоры, управление и жгуты; муфта, упорный узел, вал, дейдвуд, подшипники, уплотнение и согласованный движитель; монтаж, центровка, настройка и собственные испытания | Включения двигателя раскрыть по позициям | Внешнее топливо, охлаждение, выхлоп и вентиляция — PK09; гидронасос и его силовой привод — PK12; механическая совместимость PTO — интерфейс PK01/PK12 | G2: Расход на крейсерском ходу, установленная длина и масса, шум, обслуживание. Номинал 300 л.с. не доказывает одинаковый результат. Единый согласованный режим и протокол проверки результата для слотов A/B/C; собственные монтажные испытания пакета отдельно от общесудовой приёмки. | H2: 300 л.с. — исходный ориентир. Скорость, сопротивление, рабочий режим и PTO не рассчитаны. Измеренная компоновка, монтажные и сервисные зоны, полный состав поставки и интерфейсы ещё требуют подтверждения.
A3: PK02 | B3: Генерация | C3: ME-04 | D3: Питание нагрузок и заряд; согласованный уровень сервиса при отказе одного генератора | E3: 2 генератора | F3: Два генераторных агрегата с согласованными капсулами, опорами, собственным управлением и заводским оснащением; монтаж, местная настройка и испытания каждого | Внешние независимые топливные, водяные и выхлопные ветви — PK09; силовое переключение, распределение и кабели — PK03; пусковые АКБ и резервные связи — PK04 | Параллельную работу не считать включённой по умолчанию | G3: Полезные кВт в условиях МО, пуск нагрузок, шум на одинаковой нагрузке, расход топлива, доступ для сервиса. Единый согласованный режим и протокол проверки результата для слотов A/B/C; собственные монтажные испытания пакета отдельно от общесудовой приёмки. | H3: Около 11.5–12 кВА — исходный ориентир. Постоянные и пиковые нагрузки, режим отказа открыты. Измеренная компоновка, монтажные и сервисные зоны, полный состав поставки и интерфейсы ещё требуют подтверждения.
A4: PK03 | B4: Электропитание | C4: ME-05|ME-06|ME-09|ME-10 | D4: 24 В DC / 220 В AC; питание согласованных потребителей, переключение источников и сохранение воды при отказе общего инвертора | E4: 2 основных инвертора; 1 независимая функция питания насоса | F4: Два основных инвертора/зарядных устройства, береговой ввод и развязка, AC/DC распределение, защиты и общесудовые питающие кабели до границ потребителей; контроль источников, заряд и отключение второстепенных нагрузок, критическое питание | ME-06: одна независимая функция питания AC водяной ветви при отказе гостиничного инвертора; отдельный третий инвертор не назначен | Монтаж, маркировка и электрические проверки | Пусковые силовые пути, изоляция АКБ и BMS — PK04 | G4: Непрерывная мощность при температуре МО, пуск потребителей, время заряда, потери, масса, габариты и резерв. Единый согласованный режим и протокол проверки результата для слотов A/B/C; собственные монтажные испытания пакета отдельно от общесудовой приёмки. | H4: 3 кВА — поисковый класс, не утверждённая мощность. Баланс и береговой ввод открыты. Измеренная компоновка, монтажные и сервисные зоны, полный состав поставки и интерфейсы ещё требуют подтверждения.
A5: PK04 | B5: АКБ и резервный пуск | C5: ME-07|ME-08|ME-27|ME-28 | D5: Автономность сервисных нагрузок и запуск с поста управления при отказе пусковой АКБ | E5: 6 сервисных + 2 генераторных + 1 главного двигателя | F5: Девять физических АКБ по назначению; крепления и защитные объёмы, BMS по химии, батарейная и стартерная коммутация, силовые кабели до согласованных точек подключения PK03/стартеров, дистанционные контакторы, межблокировки и подтверждение состояния | Изоляция неисправной АКБ перед резервным пуском; местная блокировка обслуживания, питание управления и проверка всех разрешённых путей запуска | Зарядные устройства — PK03; независимость и настройки зарядки совместно PK03/PK04 | G5: Доступная энергия при принятом разряде, пусковая способность резервных источников, ресурс и обслуживание. Одинаковые А·ч не достаточны. Единый согласованный режим и протокол проверки результата для слотов A/B/C; собственные монтажные испытания пакета отдельно от общесудовой приёмки. | H5: Уточнение 115 ампер/А·ч и напряжения каждой АКБ ожидается. Пусковые токи, химия и допустимый разряд открыты. Измеренная компоновка, монтажные и сервисные зоны, полный состав поставки и интерфейсы ещё требуют подтверждения.
A6: PK05 | B6: Пресная вода | C6: ME-11|ME-12|ME-17 | D6: Нужные напор и расход при согласованном числе открытых точек; работа резервной ветви | E6: 1 установка 24 В + 1 установка AC | F6: Одна установка 24 В и одна AC; независимые пути с выбором и изоляцией, гидроаккумуляторы, фильтры, обратные клапаны, коллекторы, магистрали до водоразбора и контроль давления | Общие узлы ME-17, включая термостатическое смешение и рециркуляцию ГВС при принятии, принадлежат PK05 | Подача на RO промывку и бойлер — интерфейсы PK06/PK07 | Комплектные фильтры RO — PK06; баки — PK11 | Опрессовка, промывка и проверка обоих режимов | G6: Напор в точке потребления, пульсации, шум, циклы включения, ресурс. Максимальный расход без напора не считать рабочим. Единый согласованный режим и протокол проверки результата для слотов A/B/C; собственные монтажные испытания пакета отдельно от общесудовой приёмки. | H6: Рабочая точка и одновременность водоразбора открыты. 15 л/мин при 2 бар — только поисковый пример. Измеренная компоновка, монтажные и сервисные зоны, полный состав поставки и интерфейсы ещё требуют подтверждения.
A7: PK06 | B7: Опреснение | C7: ME-13 | D7: 150 л/ч воды нужного качества в заданных условиях; промывка и отвод некачественной воды | E7: 1 опреснитель | F7: Один RO с подающим и высоким давлением по исполнению, мембранами, штатными фильтрами, контролем солёности и автоматическим отводом некондиционного продукта, промывкой и управлением | Внутренняя обвязка, крепления, монтаж и наладка; трассы забортной подачи и концентрата этой установки принадлежат PK06, не PK09 | Подача пресной воды на промывку — PK05; приёмный танк — PK11 | Проверить качество, производительность и все автоматические режимы | G7: Энергия на литр, включённая автоматика, шум, размещение модулей, путь извлечения мембран и обслуживание. Единый согласованный режим и протокол проверки результата для слотов A/B/C; собственные монтажные испытания пакета отдельно от общесудовой приёмки. | H7: Температура, солёность и окончательная комплектация открыты. Измеренная компоновка, монтажные и сервисные зоны, полный состав поставки и интерфейсы ещё требуют подтверждения.
A8: PK07 | B8: Горячая вода | C8: ME-14 | D8: Нужный запас воды заданной температуры и восстановление после душей | E8: Количество бойлеров не принято | F8: Бойлеры с электрическим и двигательным нагревом, штатной защитной арматурой, изоляцией, креплениями и сливом; теплоноситель от согласованного присоединения двигателя до бойлера и обратно | Монтаж, проверка нагрева и восстановления запаса | Число и объём не назначены | Термостатическое смешение и общая рециркуляция — PK05, не повторная покупка PK07; питание — PK03 | G8: Полезный запас с подмешиванием, время нагрева, теплопотери, масса, форма и извлечение нагревателя. Единый согласованный режим и протокол проверки результата для слотов A/B/C; собственные монтажные испытания пакета отдельно от общесудовой приёмки. | H8: 40 л / 1200 Вт — рыночный пример, не заданная потребность. Измеренная компоновка, монтажные и сервисные зоны, полный состав поставки и интерфейсы ещё требуют подтверждения.
A9: PK08 | B9: Климат | C9: ME-15|ME-16|ME-26 | D9: Комфортные температура и влажность по помещениям; допустимые шум и режим при отказе одного модуля | E9: 2 чиллера; дополнительное отопление — опция | F9: Два независимо изолируемых чиллерных модуля; шкафы и панели управления, согласованные фанкойлы по помещениям, гидравлические контуры холода и забортного охлаждения, насосы, фильтры, расширение, клапаны, трубная изоляция, воздухораспределение и дренаж конденсата; монтаж, балансировка и наладка | Все собственные HVAC водяные ветви — PK08, не PK09 | Дополнительное отопление ME-26 — отдельная опция с контуром и управлением, без автоматического назначения котла | Фанкойлы — явное расширение до результата, их количество открыто | G9: Холодопроизводительность в одинаковых условиях, потребление, шум, насосы, управление, обвязка и сервисные зоны. Единый согласованный режим и протокол проверки результата для слотов A/B/C; собственные монтажные испытания пакета отдельно от общесудовой приёмки. | H9: 16 000 BTU/h на модуль — пример рынка. Тепловой расчёт и уровень сервиса при отказе открыты. Измеренная компоновка, монтажные и сервисные зоны, полный состав поставки и интерфейсы ещё требуют подтверждения.
A10: PK09 | B10: Обеспечение МО | C10: ME-18|ME-19|ME-22|ME-23 | D10: Надёжные подача топлива, выхлоп, охлаждение, вентиляция и обслуживание | E10: Число элементов определяется выбранными системами | F10: Общие и раздельные внешние топливные ветви двигателя/генераторов: фильтрация, подача, обратки, арматура и сервис; их забортное охлаждение, антисифонные меры, выхлоп и выходы; приток и вытяжка МО с каналами, заслонками и остановом по пожару | Маслосмена, поддоны, местные сервисные узлы и освещение с интерфейсом PK03 | Монтаж, изоляция, маркировка и испытания | Топливные танки и уровнемеры — PK11; заводские внутренние элементы агрегатов — PK01/PK02; отдельные RO/HVAC/гидравлические охладители и ветви — PK06/PK08/PK12 | G10: Полная установленная система с защитами. Компактность должна сохранять доступ и допустимую температуру. Единый согласованный режим и протокол проверки результата для слотов A/B/C; собственные монтажные испытания пакета отдельно от общесудовой приёмки. | H10: Диаметры, тепловыделение, напор, длины и комплектность открыты. Измеренная компоновка, монтажные и сервисные зоны, полный состав поставки и интерфейсы ещё требуют подтверждения.
A11: PK10 | B11: Аварийные системы | C11: ME-20|ME-21 | D11: Осушение расчётного поступления воды, обнаружение и тушение пожара | E11: Число компонентов определяется расчётом | F11: Зональное и аварийное осушение с насосами, ручными средствами, трубами, арматурой, датчиками и независимой тревогой; пожарное обнаружение, стационарное тушение, ручной пуск и контроль готовности | Матрица остановов двигателя/генераторов и вентиляции, собственные исполнительные приводы пожарной отсечки топлива — PK10, корпуса топливной арматуры — PK09 | Монтаж и проверка сценариев, без необоснованного расходования заряда | Числа, защищаемый объём и тип агента открыты | G11: Фактическая производительность, защищённость, доступ и независимость. Цена одного насоса/баллона не равна цене системы. Единый согласованный режим и протокол проверки результата для слотов A/B/C; собственные монтажные испытания пакета отдельно от общесудовой приёмки. | H11: Отсеки, защищаемый объём и аварийные режимы открыты. Измеренная компоновка, монтажные и сервисные зоны, полный состав поставки и интерфейсы ещё требуют подтверждения.
A12: PK11 | B12: Танки и стоки | C12: ME-24|ME-25 | D12: Требуемые запасы, управляемое хранение и откачка стоков | E12: Количество и объёмы открыты | F12: Полезные запасы и стоки: реестр фактических танков, встроенные либо съёмные ёмкости, люки, вентиляция, залив/слив, уровнемеры и управление; санитарная техническая подача, изоляция источников смыва, насосы стоков, откачка и контроль доступа к сбросу | Изготовление встроенного танка и его испытание раскрыть отдельно от испытания всей системы | В рамках учёта M03 — PK11, с интерфейсом корпусному W10.90, без двойной цены | Санприборы, не входящие в перечень МО, — внешний пакет W50.58 | Трубопроводы от танковых сервисных границ — PK05/PK09 по назначению | G12: Полезный объём, гигиена, обслуживание, герметичность и масса. Заводской бак не равен изготовлению встроенного танка. Единый согласованный режим и протокол проверки результата для слотов A/B/C; собственные монтажные испытания пакета отдельно от общесудовой приёмки. | H12: Конструкция встроенных танков, уровни и маршруты доступа открыты. Измеренная компоновка, монтажные и сервисные зоны, полный состав поставки и интерфейсы ещё требуют подтверждения.
A13: PK12 | B13: Гидравлика | C13: ME-29 | D13: Нужная тяга подруливающих и работа всех лебёдок, включая согласованные режимы при остановленном дизеле | E13: Гидропривод обязателен; число потребителей не принято | F13: Полная гидросистема до нужных функций всех подруливающих и всех лебёдок: насосы и выбранный привод, PTO/адаптация либо электрический или отдельный привод, бак, фильтры, охлаждение, распределители, регулирование и защита давления, трассы, местные клапаны, управление и исполнительные гидромоторы/механизмы | Выдать ведомость всех внешних потребителей и включений их пакетов: одинаковый предмет не суммировать дважды | Монтаж, промывка, чистота масла, наладка приоритетов и испытания режимов, в том числе согласованного режима без главного дизеля | Рулевое не включать в общий контур автоматически | G13: Полная стоимость до исполнительных функций, тепло, ток, шум, ресурс, PTO/резерв и объём сервисных зон. Единый согласованный режим и протокол проверки результата для слотов A/B/C; собственные монтажные испытания пакета отдельно от общесудовой приёмки. | H13: Тяга, момент, скорость, одновременность и источники мощности открыты. Измеренная компоновка, монтажные и сервисные зоны, полный состав поставки и интерфейсы ещё требуют подтверждения.

Sheet 02_Цены
A1: Источник_ID | B1: M01 | C1: Производитель | D1: Исполнение | E1: Кол-во ориентир | F1: Ед. | G1: Валюта | H1: Исходная цена | I1: Налоговая основа | J1: Ставка источника % | K1: NET / ед. валюта | L1: NET / ед. EUR | M1: Класс цены | N1: Тип доказательства | O1: Дата цены | P1: Дата просмотра | Q1: Прямая цена | R1: Спецификация | S1: Габарит изделия мм | T1: Масса кг | U1: Технический статус | V1: Включения и ограничения | W1: Наличие | X1: Происхождение записи
A2: PROP-E01 | B2: ME-01|ME-02|ME-03 | C2: Volvo Penta | D2: D4-300 I + HS68A | E2: 1 | F2: package | G2: EUR | H2: 44716 | I2: explicit HT; historical March 2023 | K2: 44716 | L2: =IF(AND(ISNUMBER(K2),K2>=0,G2="EUR"),ROUND(K2,2),IF(AND(ISNUMBER(K2),K2>=0,G2="GBP"),ROUND(ROUND(K2,2)/0.85915,2),"")) -> 44716 | M2: HISTORICAL_NOT_CURRENT | N2: PUBLIC_PRICE_NOT_KP | O2: 2023-03 | P2: 2026-09-11 | Q2: https://www.dbmoteurs.fr/sites/default/files/Volvo-Penta-tarifs-prix-achat-moteurs-2023-DB-Moteurs-motorisation-marine-bateau-plaisance.pdf | R2: https://www.dbmoteurs.fr/sites/default/files/Moteur-Volvo-Penta-D4-270-300-320-fiche-commerciale-2021-47711815-en.pdf | T2: 580 | U2: HISTORICAL_NET_REFERENCE|RFQ_REQUIRED|DUTY_OPEN | V2: 300 metric hp crank / 289 prop shaft at3500rpm; R5; 24V option official but quoted configuration unspecified; HS68A ratio selection open; dimensions for HS85A must not be substituted; ME-03 partial only factory mounts where included: shaft/coupling/thrust unit quantities and price OPEN | W2: 2026 availability unknown | X2: deliverables/M02/v001/01_support/all-candidates.csv
A3: PROP-E02 | B3: ME-01|ME-02|ME-03 | C3: Volvo Penta | D3: D4-300 I + HS85A | E3: 1 | F3: package | G3: EUR | H3: 45977 | I3: explicit HT; historical March 2023 | K3: 45977 | L3: =IF(AND(ISNUMBER(K3),K3>=0,G3="EUR"),ROUND(K3,2),IF(AND(ISNUMBER(K3),K3>=0,G3="GBP"),ROUND(ROUND(K3,2)/0.85915,2),"")) -> 45977 | M3: HISTORICAL_NOT_CURRENT | N3: PUBLIC_PRICE_NOT_KP | O3: 2023-03 | P3: 2026-09-11 | Q3: https://www.dbmoteurs.fr/sites/default/files/Volvo-Penta-tarifs-prix-achat-moteurs-2023-DB-Moteurs-motorisation-marine-bateau-plaisance.pdf | R3: https://www.dbmoteurs.fr/sites/default/files/Moteur-Volvo-Penta-D4-270-300-320-fiche-commerciale-2021-47711815-en.pdf | S3: 1234 × 848 × 794 | T3: 605 | U3: HISTORICAL_NET_REFERENCE|RFQ_REQUIRED|DUTY_OPEN | V3: 300 metric hp crank / 289 prop shaft; 3500rpm R5; 24V option price open; ratio2.500. L=433+801 W=441+407 H=274+520 from drawing; excludes projecting lifting eye/service space; not installation GA; ME-03 partial only factory mounts where included: shaft/coupling/thrust unit quantities and price OPEN | W3: 2026 availability unknown | X3: deliverables/M02/v001/01_support/all-candidates.csv
A4: PROP-E03 | B4: ME-01|ME-02|ME-03 | C4: Volvo Penta | D4: D6-300 I + HS85A | E4: 1 | F4: package | G4: EUR | H4: 50146 | I4: explicit HT; historical March 2023 | K4: 50146 | L4: =IF(AND(ISNUMBER(K4),K4>=0,G4="EUR"),ROUND(K4,2),IF(AND(ISNUMBER(K4),K4>=0,G4="GBP"),ROUND(ROUND(K4,2)/0.85915,2),"")) -> 50146 | M4: HISTORICAL_NOT_CURRENT | N4: PUBLIC_PRICE_NOT_KP | O4: 2023-03 | P4: 2026-09-11 | Q4: https://www.dbmoteurs.fr/sites/default/files/Volvo-Penta-tarifs-prix-achat-moteurs-2023-DB-Moteurs-motorisation-marine-bateau-plaisance.pdf | R4: https://www.dbmoteurs.fr/sites/default/files/Moteur-Volvo-Penta-D6-300-340-380-fiche-commerciale-brochure-2021-47711891-fr-dbmoteurs.pdf | S4: 1470 × 848 × 794 | T4: 690 | U4: HISTORICAL_NET_REFERENCE|RFQ_REQUIRED|DUTY_OPEN | V4: 300 metric hp crank /289 prop shaft;3300rpm. 24V option price open; L=433+1037 W=441+407 H=274+520 drawing dimensions not installation/service envelope; lifting eye extends above dimension; ME-03 partial only factory mounts where included: shaft/coupling/thrust unit quantities and price OPEN | W4: 2026 availability unknown | X4: deliverables/M02/v001/01_support/all-candidates.csv
A5: PROP-E04 | B5: ME-01|ME-02|ME-03 | C5: FPT Industrial | D5: C90 410 rating D 300hp + gearbox RFQ | E5: 1 | F5: package | G5: EUR | I5: RFQ_REQUIRED | L5: =IF(AND(ISNUMBER(K5),K5>=0,G5="EUR"),ROUND(K5,2),IF(AND(ISNUMBER(K5),K5>=0,G5="GBP"),ROUND(ROUND(K5,2)/0.85915,2),"")) | M5: NO_VERIFIED_NET | N5: PUBLIC_PRICE_NOT_KP | O5: UNKNOWN | P5: 2026-09-11 | Q5: https://www.etruck.fi/shop-1 | R5: https://www.fptindustrial.com/-/media/FPT/Brochures/Engines/MARINE/COMMERCIAL/Marine_Commercial_FR_2026.pdf?rev=-1 | S5: 1289 × 861 × 973 | T5: 950 | U5: RFQ_REQUIRED|INCOMPLETE_PACKAGE|DUTY_COMPARISON_OPEN | V5: Official2026 220kW300hp@2000rpm ratingD heavy duty; gearbox unselected/unpriced; shown dimensions length to flywheel and mass ENGINE ONLY; not complete package envelope;24V option RFQ; ME-03 partial only factory mounts where included: shaft/coupling/thrust unit quantities and price OPEN | W5: No exact300hp package price found | X5: deliverables/M02/v001/01_support/all-candidates.csv
A6: PROP-G01 | B6: ME-04|ME-19 | C6: Fischer Panda | D6: Panda12000x PMS | E6: 2 | F6: package | G6: GBP | H6: 16830 | I6: explicit inc vat/ex vat pair | J6: 20 | K6: 14025 | L6: =IF(AND(ISNUMBER(K6),K6>=0,G6="EUR"),ROUND(K6,2),IF(AND(ISNUMBER(K6),K6>=0,G6="GBP"),ROUND(ROUND(K6,2)/0.85915,2),"")) -> 16324.27 | M6: OBSERVED_NET_CONDITIONAL_SCOPE | N6: PUBLIC_PRICE_NOT_KP | O6: UNKNOWN | P6: 2026-09-11 | Q6: https://www.jpcdirect.com/product/fischer-panda-12000x-generator/ | R6: https://www.onefischerpanda.com/marine/marine-generators/xseries-generators/panda-12000x-pms/ | S6: 705 × 450 × 590 | T6: 195 | U6: CONDITIONAL_START_VOLTAGE|AC_COMPATIBILITY_OPEN|RATING_OPEN|UK_REFERENCE | V6: 12kVA10.2kW nominal; Manel continuous10.8kVA9.2kW;50Hz230V +/-3V;12V starter;capsule included spec; verify exactJPCSKU/manufacturer0024660 and installation accessories; UK import/logistics not included; ME-19 partial factory cooling only: external seawater/exhaust runs and installation OPEN; JPC revision conflict H565 / additional700x470x580 and192kg vs OEM705x450x590/195kg: exactSKU CAD RFQ; OEM values retained | W6: Available on back-order; qty2 and lead time RFQ | X6: deliverables/M02/v001/01_support/all-candidates.csv
A7: PROP-G02 | B7: ME-04|ME-19 | C7: Kohler / Rehlko | D7: 12EFKOZD | E7: 2 | F7: package | G7: GBP | H7: 18484.56 | I7: explicit inc vat/ex vat pair | J7: 20 | K7: 15403.8 | L7: =IF(AND(ISNUMBER(K7),K7>=0,G7="EUR"),ROUND(K7,2),IF(AND(ISNUMBER(K7),K7>=0,G7="GBP"),ROUND(ROUND(K7,2)/0.85915,2),"")) -> 17929.12 | M7: OBSERVED_NET_CONDITIONAL_SCOPE | N7: PUBLIC_PRICE_NOT_KP | O7: UNKNOWN | P7: 2026-09-11 | Q7: https://www.jpcdirect.com/product/kohler-12-kilowatt-generator/ | R7: https://techcomm.rehlko.com/techcomm/pdf/g2186.pdf | S7: 1064 × 652.5 × 711 | T7: 385 | U7: CONDITIONAL_CONFIGURATION|AC_COMPATIBILITY_OPEN|RATING_OPEN|UK_REFERENCE | V7: Singlephase115/230V50Hz:12kW12kVA continuous140C rise;11/11continuous115C;10.5/10.5prime. Official12or24V; JPC exactstarter/shield revision RFQ. Official shield mass385dry398wet; dealer406kg conflict. No borrowing US24V price scope; ME-19 partial factory cooling only: external seawater/exhaust runs and installation OPEN | W7: Available on back-order | X7: deliverables/M02/v001/01_support/all-candidates.csv
A8: PROP-G03 | B8: ME-04|ME-19 | C8: Volpi Tecno Energia | D8: Paguro12000V AP12023050M0 | E8: 2 | F8: package | G8: EUR | H8: 14935.8 | I8: direct page12446.50 +IVA; gross14935.80 labelled SK20% locale | J8: 20 | K8: 12446.5 | L8: =IF(AND(ISNUMBER(K8),K8>=0,G8="EUR"),ROUND(K8,2),IF(AND(ISNUMBER(K8),K8>=0,G8="GBP"),ROUND(ROUND(K8,2)/0.85915,2),"")) -> 12446.5 | M8: OBSERVED_NET_CONDITIONAL_SCOPE | N8: PUBLIC_PRICE_NOT_KP | O8: UNKNOWN | P8: 2026-09-11 | Q8: https://www.manelservice.com/it/gruppi-elettrogeni-marini/3925-vte-paguro-12000-v-ap12023050m0.html | R8: https://www.volpitecno.com/portfolio/paguro-12000-v-10-kw-2000-%C3%B7-3000-g-1/ | S8: 770 × 460 × 620 | T8: 180 | U8: CONDITIONAL_START_VOLTAGE|AC_COMPATIBILITY_OPEN|REVISION_OPEN | V8: 12kVA10kW continuous50Hz230V;12V starter;mass165capsule+15control electronics. Official dimensions capsule only; separate electronics footprint RFQ. Dealer/allpa dimensions/mass differ; exact SKU installationdrawing required. Published net directly not Polish VAT assumption; ME-19 partial factory cooling only: external seawater/exhaust runs and installation OPEN | W8: Manel Disponibile; qty2 and delivery date RFQ | X8: deliverables/M02/v001/01_support/all-candidates.csv
A9: PROP-G04 | B9: ME-04|ME-19 | C9: Kohler / Rehlko | D9: 12EFKOZD24-SS | E9: 2 | F9: package | G9: USD | H9: 20165.6 | I9: not stated | L9: =IF(AND(ISNUMBER(K9),K9>=0,G9="EUR"),ROUND(K9,2),IF(AND(ISNUMBER(K9),K9>=0,G9="GBP"),ROUND(ROUND(K9,2)/0.85915,2),"")) | M9: NO_VERIFIED_NET | N9: PUBLIC_PRICE_NOT_KP | O9: UNKNOWN | P9: 2026-09-11 | Q9: https://mmarineonline.com/products/kohler-marine-diesel-generator-24v-12efkozd-ss-50hz-with-sound-shield | R9: https://techcomm.rehlko.com/techcomm/pdf/g2186.pdf | S9: 1064 × 652.5 × 711 | T9: 385 | U9: NO_NET|US_REFERENCE_ONLY|AC_COMPATIBILITY_OPEN|RATING_OPEN | V9: Alternative offer for G02 not fourthgenerator;24V plus shield explicitlySKU; tax/import/Poland availability unknown; price originalUSD noFX; ME-19 partial factory cooling only: external seawater/exhaust runs and installation OPEN | W9: Contradictory availability template; RFQ | X9: deliverables/M02/v001/01_support/all-candidates.csv
A10: EL-INV-A | B10: ME-05 | C10: Victron | D10: MultiPlus-II 24/3000/70-32 PMP242305010 | E10: 2 | F10: pcs | G10: EUR | H10: 879.95 | I10: GROSS_RATE_CONFIRMED | J10: 19 | K10: 739.45 | L10: =IF(AND(ISNUMBER(K10),K10>=0,G10="EUR"),ROUND(K10,2),IF(AND(ISNUMBER(K10),K10>=0,G10="GBP"),ROUND(ROUND(K10,2)/0.85915,2),"")) -> 739.45 | M10: OBSERVED_NET_CONDITIONAL_SCOPE | N10: PUBLIC_PRICE_NOT_KP | O10: UNKNOWN | P10: 2026-09-11 | Q10: https://www.svb.de/de/victron-wechselrichter-ladegeraet-multiplus-ii-24-v-3000-va-70-a.html | R10: https://www.victronenergy.com/media/pg/MultiPlus-II_230V/en/technical-specifications-mp-ii-230v.html | S10: 141 × 268 × 499 | T10: 19 | U10: CONDITIONAL_3KVA_REFERENCE | V10: 24 V input; factory 230 V. 3000 VA not 3000 W: 2400 W at25C/2200 W at40C; charger70 A. 2 devices architecture target, capacity unapproved. | W10: 1 listed in stock; second unconfirmed | X10: deliverables/M02/v001/01_support/all-candidates.csv
A11: EL-INV-B | B11: ME-05 | C11: Victron | D11: MultiPlus-II GX 24/3000/70-32 PMP242306000 | E11: 2 | F11: pcs | G11: EUR | H11: 999.95 | I11: GROSS_RATE_CONFIRMED | J11: 19 | K11: 840.29 | L11: =IF(AND(ISNUMBER(K11),K11>=0,G11="EUR"),ROUND(K11,2),IF(AND(ISNUMBER(K11),K11>=0,G11="GBP"),ROUND(ROUND(K11,2)/0.85915,2),"")) -> 840.29 | M11: OBSERVED_NET_CONDITIONAL_SCOPE | N11: PUBLIC_PRICE_NOT_KP | O11: UNKNOWN | P11: 2026-09-11 | Q11: https://www.svb.de/de/victron-wechselrichter-ladegeraet-multiplus-ii-gx-24-v-3000-va-70-a.html | R11: https://www.victronenergy.com/media/pg/MultiPlus-II_GX/en/technical-specifications-mp-ii-gx-230v.html | S11: 147 × 275 × 506 | T11: 20 | U11: CONDITIONAL_3KVA_REFERENCE | V11: 24 V; factory230 V;2400 W at25C/2200 W at40C;70 A. GX monitoring differs; two GX units not required by yacht specification. Current manual geometry differs from catalogue: confirm revision. | W11: expected1-2weeks | X11: deliverables/M02/v001/01_support/all-candidates.csv
A12: EL-INV-C | B12: ME-05 | C12: Mastervolt | D12: CombiMaster 24/3000-60 230V 35023000 | E12: 2 | F12: pcs | G12: EUR | H12: 1599.96 | I12: GROSS_RATE_CONFIRMED | J12: 19 | K12: 1344.5 | L12: =IF(AND(ISNUMBER(K12),K12>=0,G12="EUR"),ROUND(K12,2),IF(AND(ISNUMBER(K12),K12>=0,G12="GBP"),ROUND(ROUND(K12,2)/0.85915,2),"")) -> 1344.5 | M12: OBSERVED_NET_CONDITIONAL_SCOPE | N12: PUBLIC_PRICE_NOT_KP | O12: UNKNOWN | P12: 2026-09-11 | Q12: https://www.svb.de/de/mastervolt-wechselrichter-ladegeraet-combimaster-24-v-3000-va-60-a.html?question_sort=oldest | R12: https://www.mastervolt.com/products/combimaster/combimaster-24-3000-60-230-v/ | S12: 155 × 284 × 448 | T12: 9.3 | U12: CONDITIONAL_3KVA_NOT_EQUAL_W | V12: 24 V; factory230 V;3000 VA/2600 W at40C;60 A charger;25 A transfer versus32 A Victron. Parallel operation not qualified. | W12: 1 listed in stock; second unconfirmed | X12: deliverables/M02/v001/01_support/all-candidates.csv
A13: EL-ISO-A | B13: ME-09 | C13: Victron | D13: 3600 ITR040362042 | F13: pcs | G13: EUR | H13: 436.93 | I13: NET_EXPLICIT | K13: 436.93 | L13: =IF(AND(ISNUMBER(K13),K13>=0,G13="EUR"),ROUND(K13,2),IF(AND(ISNUMBER(K13),K13>=0,G13="GBP"),ROUND(ROUND(K13,2)/0.85915,2),"")) -> 436.93 | M13: OBSERVED_NET_CONDITIONAL_SCOPE | N13: PUBLIC_PRICE_NOT_KP | O13: UNKNOWN | P13: 2026-09-11 | Q13: https://www.svb24.com/en/p/victron-isolation-transformer-3600-w-115-230-v.html | R13: https://www.victronenergy.com/upload/documents/Datasheet-Isolation-Transformers-EN.pdf | S13: 221 × 258 × 362 | T13: 21.7 | U13: CONDITIONAL_UNIT_BENCHMARK_DIMENSIONS_DEALER | V13: 3.6 class; quantity and shore capacity unknown. Dimensions/mass from opened dealer data pending native drawing confirmation; no substitute of32A at115V for32A at230V. | W13: expected1-2weeks | X13: deliverables/M02/v001/01_support/all-candidates.csv
A14: EL-ISO-B | B14: ME-09 | C14: Mastervolt | D14: Mass GI3.5 88000355 | F14: pcs | G14: EUR | H14: 1008.36 | I14: NET_EXPLICIT | K14: 1008.36 | L14: =IF(AND(ISNUMBER(K14),K14>=0,G14="EUR"),ROUND(K14,2),IF(AND(ISNUMBER(K14),K14>=0,G14="GBP"),ROUND(ROUND(K14,2)/0.85915,2),"")) -> 1008.36 | M14: OBSERVED_NET_CONDITIONAL_SCOPE | N14: PUBLIC_PRICE_NOT_KP | O14: UNKNOWN | P14: 2026-09-11 | Q14: https://www.svb24.com/en/mastervolt-mass-gi-3-5-isolation-transformer-16-a-3-5-kw.html | R14: https://www.mastervolt.com/products/mass-gi/mass-gi-35-kva-16a-lightweight/ | S14: 144 × 261 × 340 | T14: 6 | U14: CONDITIONAL_UNIT_BENCHMARK | V14: 3500 VA at230 V;16 A;HF technology;source IP23 supersedes dealer IP21. Not complete shore protection. | W14: 1 listed in stock | X14: deliverables/M02/v001/01_support/all-candidates.csv
A15: EL-ISO-C | B15: ME-09 | C15: WhisperPower | D15: GI3600 60110102 | F15: pcs | G15: EUR | H15: 1885 | I15: GROSS_RATE_UNCONFIRMED | L15: =IF(AND(ISNUMBER(K15),K15>=0,G15="EUR"),ROUND(K15,2),IF(AND(ISNUMBER(K15),K15>=0,G15="GBP"),ROUND(ROUND(K15,2)/0.85915,2),"")) | M15: NO_VERIFIED_NET | N15: PUBLIC_PRICE_NOT_KP | O15: UNKNOWN | P15: 2026-09-11 | Q15: https://www.hansenautic.de/36377/wp-gi-compact-galvanic-isolation-transformator-230v-16a-120v-32a/ | R15: https://www.whisperpower.com/gi-3600-compact-galvanic-isolation-transformer | S15: 208 × 290 × 380 | T15: 28.6 | U15: CONDITIONAL_NET_PENDING_TAX | V15: 3.6 kVA;230/110 V;16/32 A. Open page confirms VAT included but not rate: NET deliberately blank. | W15: availability on request | X15: deliverables/M02/v001/01_support/all-candidates.csv
A16: EL-BAT-A | B16: ME-08 | C16: Exide | D16: ER550 12V115Ah | E16: 6 | F16: pcs | G16: EUR | H16: 166.89 | I16: GROSS_RATE_CONFIRMED | J16: 19 | K16: 140.24 | L16: =IF(AND(ISNUMBER(K16),K16>=0,G16="EUR"),ROUND(K16,2),IF(AND(ISNUMBER(K16),K16>=0,G16="GBP"),ROUND(ROUND(K16,2)/0.85915,2),"")) -> 140.24 | M16: OBSERVED_NET_CONDITIONAL_SCOPE | N16: PUBLIC_PRICE_NOT_KP | O16: UNKNOWN | P16: 2026-09-11 | Q16: https://online-batterien.de/a/exide-er550-dual-versorgungsbatterie-starterbatterie-12v-115ah-550wh/400440 | R16: https://www.exidegroup.com/en/document/ml-brochure-2022 | S16: 349 × 175 × 235 | T16: 28 | U16: CONDITIONAL_115AH12V_NOT_OWNER_APPROVED | V16: Flooded. Owner only said115 amperes; Ah and unit voltage unconfirmed. 6 physical units; no bank wiring/capacity inferred. Deposit extra. Dealer350mm/29kg differs from brochure. | W16: not in stock | X16: deliverables/M02/v001/01_support/all-candidates.csv
A17: EL-BAT-B | B17: ME-08 | C17: Aquamot | D17: ALS12115 12V115Ah | E17: 6 | F17: pcs | G17: EUR | H17: 319 | I17: GROSS_RATE_CONFIRMED | J17: 19 | K17: 268.07 | L17: =IF(AND(ISNUMBER(K17),K17>=0,G17="EUR"),ROUND(K17,2),IF(AND(ISNUMBER(K17),K17>=0,G17="GBP"),ROUND(ROUND(K17,2)/0.85915,2),"")) -> 268.07 | M17: OBSERVED_NET_CONDITIONAL_SCOPE | N17: PUBLIC_PRICE_NOT_KP | O17: UNKNOWN | P17: 2026-09-11 | Q17: https://www.nothnagel-marine.de/product_info.php?info=p3857_aquamot---power-battery--dc-battery-als12115-12v-115ah-agm-deep-cycle-battery.html&language=en | R17: https://aquamot.at/wp-content/uploads/2018/02/Die-Batterie-Aquamot.pdf | S17: 331 × 176 × 220 | T17: 33.7 | U17: CONDITIONAL_115AH12V_NOT_OWNER_APPROVED | V17: AGM dealer description; legacy manufacturer sheet includes GEL construction wording, chemistry/revision confirmation needed. Body height214mm total220mm; dealer header6.4kg rejected in favour33.7kg technical sheet. | W17: 3-7days; abroad may vary | X17: deliverables/M02/v001/01_support/all-candidates.csv
A18: EL-BAT-C | B18: ME-08 | C18: Victron | D18: AGM Telecom115Ah M8 BAT412105164 | E18: 6 | F18: pcs | G18: EUR | H18: 329.95 | I18: GROSS_RATE_CONFIRMED | J18: 21 | K18: 272.69 | L18: =IF(AND(ISNUMBER(K18),K18>=0,G18="EUR"),ROUND(K18,2),IF(AND(ISNUMBER(K18),K18>=0,G18="GBP"),ROUND(ROUND(K18,2)/0.85915,2),"")) -> 272.69 | M18: OBSERVED_NET_CONDITIONAL_SCOPE | N18: PUBLIC_PRICE_NOT_KP | O18: UNKNOWN | P18: 2026-09-11 | Q18: https://ab-marineservice.com/product/12v-115ah-agm-telecom-batt-m8/ | R18: https://www.victronenergy.com/upload/documents/Datasheet-Telecom-batteries-EN.pdf | S18: 395 × 110 × 293 | T18: 35 | U18: CONDITIONAL_115AH12V_NOT_OWNER_APPROVED | V18: 12 V AGM front terminal;6 units only if owner confirms115Ah12V. No12V housebus inferred. Open page21% supersedes search19%. | W18: backorder3-5workingdays | X18: deliverables/M02/v001/01_support/all-candidates.csv
A19: EL-DIST-A | B19: ME-10 | C19: Victron | D19: Lynx Distributor M8 LYN060102000 | F19: pcs | G19: EUR | H19: 182.75 | I19: NET_EXPLICIT | K19: 182.75 | L19: =IF(AND(ISNUMBER(K19),K19>=0,G19="EUR"),ROUND(K19,2),IF(AND(ISNUMBER(K19),K19>=0,G19="GBP"),ROUND(ROUND(K19,2)/0.85915,2),"")) -> 182.75 | M19: OBSERVED_NET_CONDITIONAL_SCOPE | N19: PUBLIC_PRICE_NOT_KP | O19: UNKNOWN | P19: 2026-09-11 | Q19: https://www.dynastart.nl/lyn060102000-lynx-distributor-m8 | R19: https://www.victronenergy.com/media/pg/Lynx_Distributor/en/technical-specifications-lynx-distributor.html | S19: 170 × 80 × 290 | T19: 2.2 | U19: CONDITIONAL_UNIT_BENCHMARK | V19: Supports24 V;1000 A product rating not yacht demand; four fuse ways, fuses/monitor supply and full installation separate. Source axis hxlxw=290x170x80; check drawing for orientation. | W19: in stock | X19: deliverables/M02/v001/01_support/all-candidates.csv
A20: EL-DIST-B | B20: ME-10 | C20: Philippi | D20: STV207 020002071 | F20: pcs | G20: EUR | H20: 214.24 | I20: NET_EXPLICIT | K20: 214.24 | L20: =IF(AND(ISNUMBER(K20),K20>=0,G20="EUR"),ROUND(K20,2),IF(AND(ISNUMBER(K20),K20>=0,G20="GBP"),ROUND(ROUND(K20,2)/0.85915,2),"")) -> 214.24 | M20: OBSERVED_NET_CONDITIONAL_SCOPE | N20: PUBLIC_PRICE_NOT_KP | O20: UNKNOWN | P20: 2026-09-11 | Q20: https://www.svb24.com/en/philippi-stv207-power-distribution-panel-configurable.html | R20: https://www.philippi-online.de/en/collections/serie_200-marine/products/stv-207 | S20: 70 × 105 × 210 | U20: CONDITIONAL_UNIT_BENCHMARK | V20: 24 V compatible seven-circuit unit benchmark;10 A standard breakers not approved circuit ratings. DC accessory socket not permission for12V loads on24V. Mass not published. Not complete yacht switchboard. | W20: 2 listed in stock | X20: deliverables/M02/v001/01_support/all-candidates.csv
A21: EL-DIST-C | B21: ME-10 | C21: Philippi | D21: LAE113 010001130 | F21: pcs | G21: EUR | H21: 331.89 | I21: NET_EXPLICIT | K21: 331.89 | L21: =IF(AND(ISNUMBER(K21),K21>=0,G21="EUR"),ROUND(K21,2),IF(AND(ISNUMBER(K21),K21>=0,G21="GBP"),ROUND(ROUND(K21,2)/0.85915,2),"")) -> 331.89 | M21: OBSERVED_NET_CONDITIONAL_SCOPE | N21: PUBLIC_PRICE_NOT_KP | O21: UNKNOWN | P21: 2026-09-11 | Q21: https://www.svb24.com/en/philippi-lae-113-shore-connection-unit.html | R21: https://www.philippi-online.de/en/products/lae-113 | S21: 100 × 260 × 185 | U21: CONDITIONAL_UNIT_BENCHMARK | V21: Factory230 V50Hz panel benchmark for220VAC target;16A/30mA RCBO and3two-pole10A circuits per official description. Not full multi-source AC switchboard; mass unknown. | W21: 2 listed in stock | X21: deliverables/M02/v001/01_support/all-candidates.csv
A22: EL-REM-A | B22: ME-28 | C22: Blue Sea | D22: ML-RBS7702 24V | F22: pcs | G22: EUR | H22: 239.45 | I22: NET_EXPLICIT | K22: 239.45 | L22: =IF(AND(ISNUMBER(K22),K22>=0,G22="EUR"),ROUND(K22,2),IF(AND(ISNUMBER(K22),K22>=0,G22="GBP"),ROUND(ROUND(K22,2)/0.85915,2),"")) -> 239.45 | M22: OBSERVED_NET_CONDITIONAL_SCOPE | N22: PUBLIC_PRICE_NOT_KP | O22: UNKNOWN | P22: 2026-09-11 | Q22: https://www.svb24.com/en/blue-sea-hd-remote-battery-switch-24v.html | R22: https://www.bluesea.com/products/7702/ML-RBS_Remote_Battery_Switch_with_Manual_Control_-_24V_DC_500A | T22: 0.95 | U22: CONDITIONAL_UNIT_BENCHMARK | V22: Manual override;24V coil;500A continuous product rating. Quantity, control failover, crank duty and24V live switching not qualified; dimensions drawing pending. | W22: 9 listed in stock | X22: deliverables/M02/v001/01_support/all-candidates.csv
A23: EL-REM-B | B23: ME-28 | C23: Blue Sea | D23: 7703 24V | F23: pcs | G23: EUR | H23: 226.85 | I23: NET_EXPLICIT | K23: 226.85 | L23: =IF(AND(ISNUMBER(K23),K23>=0,G23="EUR"),ROUND(K23,2),IF(AND(ISNUMBER(K23),K23>=0,G23="GBP"),ROUND(ROUND(K23,2)/0.85915,2),"")) -> 226.85 | M23: OBSERVED_NET_CONDITIONAL_SCOPE | N23: PUBLIC_PRICE_NOT_KP | O23: UNKNOWN | P23: 2026-09-11 | Q23: https://www.svb24.com/en/blue-sea-universal-solenoid-switch-24-v.html | R23: https://d2pyqm2yd3fw2i.cloudfront.net/files/resources/instructions/990180170-006.pdf | U23: CONDITIONAL_UNIT_BENCHMARK | V23: Solenoid unit benchmark without manual override of7702; not automatic equivalent. Physical dimensions/mass unverified. No assertion reserve-start scheme works. | W23: 2 listed in stock | X23: deliverables/M02/v001/01_support/all-candidates.csv
A24: EL-OPEN-PUMP | B24: ME-06 | D24: UNSIZED | E24: 1 | F24: function | I24: UNKNOWN | L24: =IF(AND(ISNUMBER(K24),K24>=0,G24="EUR"),ROUND(K24,2),IF(AND(ISNUMBER(K24),K24>=0,G24="GBP"),ROUND(ROUND(K24,2)/0.85915,2),"")) | M24: NO_VERIFIED_NET | N24: PUBLIC_PRICE_NOT_KP | O24: UNKNOWN | P24: 2026-09-11 | U24: OPEN_LOAD_AND_STARTUP | V24: 1 independent function, not necessarily extra inverter. Select after pump running power/start waveform/duty; avoid double counting ME05. | W24: NOT_CONFIRMED | X24: deliverables/M02/v001/01_support/all-candidates.csv
A25: EL-OPEN-MAIN | B25: ME-07 | D25: UNSIZED | E25: 1 | F25: pcs | I25: UNKNOWN | L25: =IF(AND(ISNUMBER(K25),K25>=0,G25="EUR"),ROUND(K25,2),IF(AND(ISNUMBER(K25),K25>=0,G25="GBP"),ROUND(ROUND(K25,2)/0.85915,2),"")) | M25: NO_VERIFIED_NET | N25: PUBLIC_PRICE_NOT_KP | O25: UNKNOWN | P25: 2026-09-11 | U25: OPEN_START_VOLTAGE_CCA | V25: 1 physical owner battery, capacity/voltage/chemistry unknown. Not automatically ER550 or service115Ah. | W25: NOT_CONFIRMED | X25: deliverables/M02/v001/01_support/all-candidates.csv
A26: EL-OPEN-GEN | B26: ME-27 | D26: UNSIZED | E26: 2 | F26: pcs | I26: UNKNOWN | L26: =IF(AND(ISNUMBER(K26),K26>=0,G26="EUR"),ROUND(K26,2),IF(AND(ISNUMBER(K26),K26>=0,G26="GBP"),ROUND(ROUND(K26,2)/0.85915,2),"")) | M26: NO_VERIFIED_NET | N26: PUBLIC_PRICE_NOT_KP | O26: UNKNOWN | P26: 2026-09-11 | U26: OPEN_START_VOLTAGE_CCA | V26: 2 physical owner batteries for2generators; capacity/voltage/CCA unknown; keep9total with6service+1main. No fictitious unit price. | W26: NOT_CONFIRMED | X26: deliverables/M02/v001/01_support/all-candidates.csv
A27: WC-RO-01 | B27: ME-13 | C27: Aquatec | D27: AC150 230V single phase | E27: 1 | F27: шт | G27: EUR | H27: 7539 | I27: EXPLICIT_NET_AND_19_PERCENT_GROSS | J27: 19 | K27: 6335.29 | L27: =IF(AND(ISNUMBER(K27),K27>=0,G27="EUR"),ROUND(K27,2),IF(AND(ISNUMBER(K27),K27>=0,G27="GBP"),ROUND(ROUND(K27,2)/0.85915,2),"")) -> 6335.29 | M27: OBSERVED_NET_CONDITIONAL_SCOPE | N27: PUBLIC_PRICE_NOT_KP | O27: UNKNOWN | P27: 2026-09-11 | Q27: https://www.aquatec-watermaker.de/wassermacher-produkt-ac150-ac240.html | R27: https://www.aquatec-watermaker.de/wassermacher-produkt-ac150-ac240.html | U27: FUNCTION_PARITY_OPEN;220V_COMPATIBILITY_OPEN | V27: 150 L/h nominal ±10% at25C/35000ppm; modular conventional HP pump; base price only: automatic flush/salinity/reject parity must be itemised; generator minimum4kW manufacturer target, not electrical demand or selection | W27: NOT_CONFIRMED | X27: deliverables/M02/v001/01_support/all-candidates.csv
A28: WC-RO-02 | B28: ME-13 | C28: Schenker | D28: ZEN150 24V/230V Touch plus salinity/reject | E28: 1 | F28: шт | G28: EUR | H28: 12820.2 | I28: FROM_GROSS_EXPLICIT_20_PERCENT | J28: 20 | K28: 10683.5 | L28: =IF(AND(ISNUMBER(K28),K28>=0,G28="EUR"),ROUND(K28,2),IF(AND(ISNUMBER(K28),K28>=0,G28="GBP"),ROUND(ROUND(K28,2)/0.85915,2),"")) -> 10683.5 | M28: FROM_INCOMPLETE_CONFIGURATION | N28: PUBLIC_PRICE_NOT_KP | O28: UNKNOWN | P28: 2026-09-11 | Q28: https://mar-nautic.com/schenker-watermaker-zen-150 | R28: https://schenkerwatermakers.com/wp-content/uploads/2025/03/ZEN150_datasheet_v4.pdf | U28: FROM_PRICE_NOT_CONFIGURED;RFQ_REQUIRED | V28: Observed FROM base price; net is FROM benchmark only, NOT complete Touch/salinity/reject price. Nominal150L/h. Manufacturer230V±15% includes220V. Basic has no salinity; Touch optional; 24V variant permitted. Modular unit dimensions not total installed envelope. | W28: Out of stock; order lead time on request | X28: deliverables/M02/v001/01_support/all-candidates.csv
A29: WC-RO-03 | B29: ME-13 | C29: Osmosea | D29: NEW12 150C 24V | E29: 1 | F29: шт | G29: EUR | L29: =IF(AND(ISNUMBER(K29),K29>=0,G29="EUR"),ROUND(K29,2),IF(AND(ISNUMBER(K29),K29>=0,G29="GBP"),ROUND(ROUND(K29,2)/0.85915,2),"")) | M29: NO_VERIFIED_NET | N29: PUBLIC_PRICE_NOT_KP | O29: UNKNOWN | P29: 2026-09-11 | Q29: https://www.manelservice.com/en/marine-desalination-systems/17102-osmosea-new12-150c-nautical-watermaker-150-lth.html | R29: https://osmosea.it/en/new-12/ | T29: 63 | U29: RFQ_REQUIRED;COMPACT_CANDIDATE | V29: Official150L/h/600W; flush/salinometer/unsafe-water discard included. Official63kg conflicts dealer65kg; dimensions dealer796x317x408 not official therefore blank. Dealer install/service kits included vs manufacturer optional: reconcile | W29: NOT_CONFIRMED | X29: deliverables/M02/v001/01_support/all-candidates.csv
A30: WC-DC-01 | B30: ME-11 | C30: CEM | D30: OSC-16.062.24 / OEM identity reconcile | E30: 1 | F30: шт | G30: EUR | H30: 1229.9 | I30: EXPLICIT_HT | K30: 1024.92 | L30: =IF(AND(ISNUMBER(K30),K30>=0,G30="EUR"),ROUND(K30,2),IF(AND(ISNUMBER(K30),K30>=0,G30="GBP"),ROUND(ROUND(K30,2)/0.85915,2),"")) -> 1024.92 | M30: OBSERVED_NET_CONDITIONAL_SCOPE | N30: PUBLIC_PRICE_NOT_KP | O30: UNKNOWN | P30: 2026-09-11 | Q30: https://www.comptoirnautique.com/groupe-d-eau-a-pressostat/53022-cem-elettromeccanica-autoclave-cem-vase-expansion-inox-20l-24v-50-l-min.html | R30: https://cempumps.com/wp-content/uploads/2024/10/Autoclavi_20L-20X.pdf | U30: WORKING_POINT_AND_OEM_ID_OPEN | V30: 24V20L accumulator; dealer50L/min max; source model mapping not proven. Common proposed test15L/min at2bar NOT verified. Do not add included tank again. | W30: Preorder; replenishment23/09/2026 | X30: deliverables/M02/v001/01_support/all-candidates.csv
A31: WC-DC-02 | B31: ME-11 | C31: Gianneschi | D31: EcoInox1 GE011 24V20L | E31: 1 | F31: шт | G31: EUR | H31: 1311.9 | I31: EXPLICIT_HT | K31: 1093.25 | L31: =IF(AND(ISNUMBER(K31),K31>=0,G31="EUR"),ROUND(K31,2),IF(AND(ISNUMBER(K31),K31>=0,G31="GBP"),ROUND(ROUND(K31,2)/0.85915,2),"")) -> 1093.25 | M31: OBSERVED_NET_CONDITIONAL_SCOPE | N31: PUBLIC_PRICE_NOT_KP | O31: UNKNOWN | P31: 2026-09-11 | Q31: https://www.comptoirnautique.com/groupe-d-eau-hydrophore/22947-gianneschi-groupe-d-eau-ecoinox-1-avec-reservoir-20l-24v-45lmin-7024.html | R31: https://www.gianneschipumps.com/GIANNESCHI_Brochure-web.pdf | U31: WORKING_POINT_OPEN | V31: 45L/min max; common proposed15L/min at2bar needs curve. Includes20L tank/gauge/pressure switch; current OEM revision confirmation. | W31: In stock48/72h | X31: deliverables/M02/v001/01_support/all-candidates.csv
A32: WC-DC-03 | B32: ME-11 | C32: ENAG | D32: GH24-0.37-24L-OT RB18-ED | E32: 1 | F32: шт | G32: EUR | L32: =IF(AND(ISNUMBER(K32),K32>=0,G32="EUR"),ROUND(K32,2),IF(AND(ISNUMBER(K32),K32>=0,G32="GBP"),ROUND(ROUND(K32,2)/0.85915,2),"")) | M32: NO_VERIFIED_NET | N32: PUBLIC_PRICE_NOT_KP | O32: UNKNOWN | P32: 2026-09-11 | Q32: https://www.enag.fr/english/wp-content/uploads/sites/5/2022/11/FC-GH-EN-C.pdf | R32: https://www.enag.fr/english/wp-content/uploads/sites/5/2022/11/FC-GH-EN-C.pdf | T32: 29 | U32: RFQ_REQUIRED;WORKING_POINT_OPEN | V32: Official24V/0.37kW; 1m3/h at30m published point; pressure switch1.5/2.5bar.24L tank differs20L competitors: standardise accumulator scope before comparison. Dimensions drawing orientation not mapped into LWH. | W32: NOT_CONFIRMED | X32: deliverables/M02/v001/01_support/all-candidates.csv
A33: WC-AC-01 | B33: ME-12 | C33: CEM | D33: J-INOX/20X 230M | E33: 1 | F33: шт | G33: EUR | L33: =IF(AND(ISNUMBER(K33),K33>=0,G33="EUR"),ROUND(K33,2),IF(AND(ISNUMBER(K33),K33>=0,G33="GBP"),ROUND(ROUND(K33,2)/0.85915,2),"")) | M33: NO_VERIFIED_NET | N33: PUBLIC_PRICE_NOT_KP | O33: UNKNOWN | P33: 2026-09-11 | Q33: https://cempumps.com/wp-content/uploads/2024/10/Autoclavi_20L-20X.pdf | R33: https://cempumps.com/wp-content/uploads/2024/10/Autoclavi_20L-20X.pdf | U33: RFQ_REQUIRED;220V_COMPATIBILITY_OPEN;WORKING_POINT_OPEN | V33: Official230V singlephase variant exists. Proposedcommon15L/min at2bar not accepted from maxflow.20L stainless tank included. No price borrowed from24V sibling. | W33: NOT_CONFIRMED | X33: deliverables/M02/v001/01_support/all-candidates.csv
A34: WC-AC-02 | B34: ME-12 | C34: Gianneschi | D34: EcoInox2 GE017 230V20L | E34: 1 | F34: шт | G34: EUR | H34: 1263 | I34: EXPLICIT_HT | K34: 1052.5 | L34: =IF(AND(ISNUMBER(K34),K34>=0,G34="EUR"),ROUND(K34,2),IF(AND(ISNUMBER(K34),K34>=0,G34="GBP"),ROUND(ROUND(K34,2)/0.85915,2),"")) -> 1052.5 | M34: OBSERVED_NET_CONDITIONAL_SCOPE | N34: PUBLIC_PRICE_NOT_KP | O34: UNKNOWN | P34: 2026-09-11 | Q34: https://www.tyboat.com/achat/P-57388-gianneschi-groupe-d-eau-ecoinox2-3-5-bars-0-45-kw-55-litres-minute-reservoir-20-litres-230-volts.html | R34: https://www.gianneschipumps.com/GIANNESCHI_Brochure-web.pdf | U34: 220V_COMPATIBILITY_OPEN;WORKING_POINT_OPEN | V34: Open page1052.50HT supersedes search992.50. Dealer max55L/min conflicts Kent45: curves required.0.45kW/20L; common15L/min at2bar not verified. | W34: Stock1–6businessdays | X34: deliverables/M02/v001/01_support/all-candidates.csv
A35: WC-AC-03 | B35: ME-12 | C35: ENAG | D35: GH230mono-0.37-24L-JET M-ED | E35: 1 | F35: шт | G35: EUR | L35: =IF(AND(ISNUMBER(K35),K35>=0,G35="EUR"),ROUND(K35,2),IF(AND(ISNUMBER(K35),K35>=0,G35="GBP"),ROUND(ROUND(K35,2)/0.85915,2),"")) | M35: NO_VERIFIED_NET | N35: PUBLIC_PRICE_NOT_KP | O35: UNKNOWN | P35: 2026-09-11 | Q35: https://www.enag.fr/english/wp-content/uploads/sites/5/2022/11/FC-GH-EN-C.pdf | R35: https://www.enag.fr/english/wp-content/uploads/sites/5/2022/11/FC-GH-EN-C.pdf | T35: 18 | U35: RFQ_REQUIRED;220V_COMPATIBILITY_OPEN;WORKING_POINT_OPEN | V35: Explicit230V singlephase; official1m3/h at40m, pressure switch1.5/2.5bar.24L accumulator vs20L needs standardisation; no equivalence claim. | W35: NOT_CONFIRMED | X35: deliverables/M02/v001/01_support/all-candidates.csv
A36: WC-CH-01 | B36: ME-15 | C36: Thermowell | D36: UC16H | E36: 2 | F36: шт | G36: EUR | H36: 4544.35 | I36: GROSS_EXPLICIT_ALV25.5 | J36: 25.5 | K36: 3621 | L36: =IF(AND(ISNUMBER(K36),K36>=0,G36="EUR"),ROUND(K36,2),IF(AND(ISNUMBER(K36),K36>=0,G36="GBP"),ROUND(ROUND(K36,2)/0.85915,2),"")) -> 3621 | M36: OBSERVED_NET_CONDITIONAL_SCOPE | N36: PUBLIC_PRICE_NOT_KP | O36: UNKNOWN | P36: 2026-09-11 | Q36: https://www.esconet.fi/shop/uc16h-thermowell-uc16h-ilmastointilaite-chiller-230v-16000btu-27518 | R36: https://www.thermowellmarine.com/wp-content/uploads/2023/04/THERMOWELL-2023_rev1_apr_web.pdf | S36: 350 × 340 × 380 | T36: 38 | U36: REFERENCE_SIZE_ONLY;VOLTAGE_REVISION_CHECK;SUPPLY_SCOPE_CONFLICT_RFQ | V36: 16000BTU/h each; illustrative class NOT yacht heatload. Officialcatalog220/1/50; dealer230V. Dimensions exclude controlbox. OEM catalogue says box/display included BUT priced Esco SKU requires airhandler/controlpanel separately: inclusion CONFLICT, RFQ required; do not assume included display.1.5kWnominput at catalogue conditions; independent2module integration open. | W36: Esco stock0; supplier availability unknown | X36: deliverables/M02/v001/01_support/all-candidates.csv
A37: WC-CH-02 | B37: ME-15 | C37: Climma | D37: CWS Aquacontrol161RC 230/1/50 | E37: 2 | F37: шт | G37: EUR | H37: 4155.3 | I37: EXPLICIT_TAX_EXCLUDED | K37: 4155.3 | L37: =IF(AND(ISNUMBER(K37),K37>=0,G37="EUR"),ROUND(K37,2),IF(AND(ISNUMBER(K37),K37>=0,G37="GBP"),ROUND(ROUND(K37,2)/0.85915,2),"")) -> 4155.3 | M37: OBSERVED_NET_CONDITIONAL_SCOPE | N37: PUBLIC_PRICE_NOT_KP | O37: UNKNOWN | P37: 2026-09-11 | Q37: https://mdislandsupply.com/en/climma/879-cws-aquacontrol-161-rc-230150-climma.html | R37: https://www.veco.net/en/prodotti/climma-cws-aquacontrol-chillers/ | U37: REFERENCE_SIZE_ONLY;220V_COMPATIBILITY_OPEN | V37: 16000BTU/h each; reversecycle. Price recovered live requests HTTP200 after web429; local source text retained. OEM dimensions require authenticated download; old dealerPDF not promoted. | W37: Last items;1–2businessdays claim | X37: deliverables/M02/v001/01_support/all-candidates.csv
A38: WC-CH-03 | B38: ME-15 | C38: Webasto | D38: BlueCool C16M | E38: 2 | F38: шт | G38: EUR | L38: =IF(AND(ISNUMBER(K38),K38>=0,G38="EUR"),ROUND(K38,2),IF(AND(ISNUMBER(K38),K38>=0,G38="GBP"),ROUND(ROUND(K38,2)/0.85915,2),"")) | M38: NO_VERIFIED_NET | N38: PUBLIC_PRICE_NOT_KP | O38: UNKNOWN | P38: 2026-09-11 | Q38: https://www.nauticsale.com/en/airconditioning/bluecool-chiller-systems/bluecool-c-series-chillers/ | R38: https://www.webasto.com/en-us/cooling/marine-chiller-air-conditioning-units/bluecool-c-series.html | S38: 385 × 290 × 350 | T38: 30 | U38: RFQ_REQUIRED;REFERENCE_SIZE_ONLY;220V_COMPATIBILITY_OPEN | V38: 16000BTU/h each; officialcurrentdimensions. Older F-suffix dealerweight differs: revision match required.3pricepaths found no verified EU net exactSKU; no US price conversion. | W38: NOT_CONFIRMED | X38: deliverables/M02/v001/01_support/all-candidates.csv
A39: WC-HW-01 | B39: ME-14 | C39: Quick | D39: B3 40L1200W FLB34012S000A00 | F39: шт | G39: EUR | H39: 737 | I39: EXPLICIT_HT | K39: 614.17 | L39: =IF(AND(ISNUMBER(K39),K39>=0,G39="EUR"),ROUND(K39,2),IF(AND(ISNUMBER(K39),K39>=0,G39="GBP"),ROUND(ROUND(K39,2)/0.85915,2),"")) -> 614.17 | M39: OBSERVED_NET_CONDITIONAL_SCOPE | N39: PUBLIC_PRICE_NOT_KP | O39: UNKNOWN | P39: 2026-09-11 | Q39: https://www.tyboat.com/achat/P-8889-quick-chauffe-eau-cylindrique-b3-40-litres-220-volts-1200-watts.html | R39: https://www.quickitaly.com/it/prodotti/scalda-acqua/scalda-acqua/nautic-boiler-b3/ | U39: UNIT_BENCHMARK_ONLY;QTY_OPEN | V39: 40L1200W220V plus engine heat exchanger common illustrative class; not owner size. Supplier dimensions/mass in research only pending official drawing. Thermostatic mixing equalise separately. | W39: Stock1–6businessdays | X39: deliverables/M02/v001/01_support/all-candidates.csv
A40: WC-HW-02 | B40: ME-14 | C40: Quick | D40: BX 40L1200W FLBX4012S000A00 | F40: шт | G40: EUR | H40: 829 | I40: EXPLICIT_HT | K40: 690.83 | L40: =IF(AND(ISNUMBER(K40),K40>=0,G40="EUR"),ROUND(K40,2),IF(AND(ISNUMBER(K40),K40>=0,G40="GBP"),ROUND(ROUND(K40,2)/0.85915,2),"")) -> 690.83 | M40: OBSERVED_NET_CONDITIONAL_SCOPE | N40: PUBLIC_PRICE_NOT_KP | O40: UNKNOWN | P40: 2026-09-11 | Q40: https://www.tyboat.com/achat/P-8880-quick-chauffe-eau-cylindrique-bx-40-litres-220-volts-1200-watts.html | R40: https://www.quickitaly.com/it/prodotti/scalda-acqua/scalda-acqua/nautic-boiler-bx/ | U40: UNIT_BENCHMARK_ONLY;QTY_OPEN | V40: 40L1200W220V plus engine heat exchanger common illustrative class; not owner size. Supplier dimensions/mass in research only pending official drawing. Thermostatic mixing equalise separately. | W40: Stock1–6businessdays | X40: deliverables/M02/v001/01_support/all-candidates.csv
A41: WC-HW-03 | B41: ME-14 | C41: Quick | D41: BXS 40L1200W FLBXS4012S00A00 | F41: шт | G41: EUR | H41: 909 | I41: EXPLICIT_HT | K41: 757.5 | L41: =IF(AND(ISNUMBER(K41),K41>=0,G41="EUR"),ROUND(K41,2),IF(AND(ISNUMBER(K41),K41>=0,G41="GBP"),ROUND(ROUND(K41,2)/0.85915,2),"")) -> 757.5 | M41: OBSERVED_NET_CONDITIONAL_SCOPE | N41: PUBLIC_PRICE_NOT_KP | O41: UNKNOWN | P41: 2026-09-11 | Q41: https://www.tyboat.com/achat/P-18237-quick-chauffe-eau-cube-inox-bxs-40-litres-220-volts-1200-watts.html | R41: https://www.quickitaly.com/it/prodotti/scalda-acqua/scalda-acqua/nautic-boiler-bxs/ | U41: UNIT_BENCHMARK_ONLY;QTY_OPEN | V41: 40L1200W220V plus engine heat exchanger common illustrative class; not owner size. Supplier dimensions/mass in research only pending official drawing. Thermostatic mixing equalise separately. | W41: Stock1–6businessdays | X41: deliverables/M02/v001/01_support/all-candidates.csv
A42: WC-AUX-01 | B42: ME-16 | C42: Frigomar | D42: NH150PS SWM0150230 | F42: шт | G42: EUR | H42: 795.9 | I42: EXPLICIT_HT | K42: 663.25 | L42: =IF(AND(ISNUMBER(K42),K42>=0,G42="EUR"),ROUND(K42,2),IF(AND(ISNUMBER(K42),K42>=0,G42="GBP"),ROUND(ROUND(K42,2)/0.85915,2),"")) -> 663.25 | M42: OBSERVED_NET_CONDITIONAL_SCOPE | N42: PUBLIC_PRICE_NOT_KP | O42: UNKNOWN | P42: 2026-09-11 | Q42: https://www.comptoirnautique.com/climatisation-bateau/91819-frigomar-pompes-a-entrainement-magnetique.html | R42: https://www.frigomar.com/en/product-line/ | U42: UNIT_BENCHMARK_ONLY;CURVE_AND_220V_OPEN | V42: 230V50/60Hz magneticdrive; count and pump duty notfixed. No proof this model meets both seawater and chilledwater circuits; official detailed curve required. | W42: Preorder; replenishment19/09/2026 | X42: deliverables/M02/v001/01_support/all-candidates.csv
A43: WC-AUX-02 | B43: ME-17 | C43: Quick | D43: QB002 mixing kit | F43: шт | G43: EUR | H43: 140.4 | I43: EXPLICIT_HT | K43: 117 | L43: =IF(AND(ISNUMBER(K43),K43>=0,G43="EUR"),ROUND(K43,2),IF(AND(ISNUMBER(K43),K43>=0,G43="GBP"),ROUND(ROUND(K43,2)/0.85915,2),"")) -> 117 | M43: OBSERVED_NET_CONDITIONAL_SCOPE | N43: PUBLIC_PRICE_NOT_KP | O43: UNKNOWN | P43: 2026-09-11 | Q43: https://www.kent-marine.com/fr/produit/35262/chauffe-eau-cylindrique-40l-220v-1200w.html | R43: https://www.quickitaly.com/it/prodotti/scalda-acqua/ | U43: PUBLIC_LIST_UNIT_BENCHMARK | V43: Observed linked accessory publicHT price; count unknown; confirm inclusion in selected calorifier supply. | W43: Not confirmed | X43: deliverables/M02/v001/01_support/all-candidates.csv
A44: WC-AUX-03 | B44: ME-17 | C44: Jabsco | D44: Pumpgard36400-0002 / substitution46400-0000 | F44: шт | G44: EUR | H44: 33.5 | I44: TAX_NOT_PROVEN | L44: =IF(AND(ISNUMBER(K44),K44>=0,G44="EUR"),ROUND(K44,2),IF(AND(ISNUMBER(K44),K44>=0,G44="GBP"),ROUND(ROUND(K44,2)/0.85915,2),"")) | M44: NO_VERIFIED_NET | N44: PUBLIC_PRICE_NOT_KP | O44: UNKNOWN | P44: 2026-09-11 | Q44: https://www.marine-impact.com/groupe-d-eau/313-filtre-en-ligne-pumpgard-o13-mm-jabsco.html | R44: https://www.xylem.com/siteassets/brand/jabsco/resources/manual/36800-technical-data-sheet.pdf | U44: UNIT_BENCHMARK_GROSS_UNKNOWN;NET_WITHHELD | V44: Observedprice; no explicit taxbasis verified so net blank.13mm40mesh strainer not sanitary treatment and not dimensioned for proposedpressurestation. | W44: Web listing | X44: deliverables/M02/v001/01_support/all-candidates.csv
A45: A01 | B45: ME-29 | C45: Vetus | D45: HT1010 | F45: шт | G45: GBP | H45: 2412.08 | I45: NET_EXPLICIT | K45: 2412.08 | L45: =IF(AND(ISNUMBER(K45),K45>=0,G45="EUR"),ROUND(K45,2),IF(AND(ISNUMBER(K45),K45>=0,G45="GBP"),ROUND(ROUND(K45,2)/0.85915,2),"")) -> 2807.52 | M45: OBSERVED_NET_CONDITIONAL_SCOPE | N45: PUBLIC_PRICE_NOT_KP | O45: UNKNOWN | P45: 2026-09-11 | Q45: https://www.vetus-shop.com/aluminium-hydraulic-tank-70-incl-ht1013-p-2024.html | R45: https://webshop.vetus.com/nl/products/power-hydraulics/hydraulische-tanks | U45: PARTIAL_HYDRAULIC_NOT_COMPLETE | V45: 70л; HT1013 включён. Цена бака с частью управления, не станции. 615×475×360мм у продавца — только голый бак без клапанов, не монтажный габарит. | W45: Out of Stock | X45: deliverables/M02/v001/01_support/all-candidates.csv
A46: A02 | B46: ME-29 | C46: Vetus | D46: HT1016SD2 | F46: шт | G46: GBP | H46: 2716.67 | I46: NET_EXPLICIT | K46: 2716.67 | L46: =IF(AND(ISNUMBER(K46),K46>=0,G46="EUR"),ROUND(K46,2),IF(AND(ISNUMBER(K46),K46>=0,G46="GBP"),ROUND(ROUND(K46,2)/0.85915,2),"")) -> 3162.04 | M46: OBSERVED_NET_CONDITIONAL_SCOPE | N46: PUBLIC_PRICE_NOT_KP | O46: UNKNOWN | P46: 2026-09-11 | Q46: https://www.vetus-shop.com/vetus-power-hydraulics-c-21_210.html | U46: PARTIAL_HYDRAULIC_NOT_COMPLETE | V46: 45см³/оборот; ориентация/SAE/привод и требуемый расход не выбраны. Не три уровня насосов разного размера. | W46: Не подтверждено | X46: deliverables/M02/v001/01_support/all-candidates.csv
A47: A03 | B47: ME-29 | C47: Vetus | D47: HT301132 | F47: шт | G47: GBP | H47: 517.5 | I47: NET_EXPLICIT | K47: 517.5 | L47: =IF(AND(ISNUMBER(K47),K47>=0,G47="EUR"),ROUND(K47,2),IF(AND(ISNUMBER(K47),K47>=0,G47="GBP"),ROUND(ROUND(K47,2)/0.85915,2),"")) -> 602.34 | M47: OBSERVED_NET_CONDITIONAL_SCOPE | N47: PUBLIC_PRICE_NOT_KP | O47: UNKNOWN | P47: 2026-09-11 | Q47: https://www.vetus-shop.com/aluminium-hydraulic-tank-70-incl-ht1013-p-2024.html | U47: PARTIAL_HYDRAULIC_NOT_COMPLETE | V47: Шланг32мм; теплоотдача/забортный контур требуют проверки; не доказана необходимость именно этого размера. | W47: Не подтверждено | X47: deliverables/M02/v001/01_support/all-candidates.csv
A48: A04 | B48: ME-29 | C48: Vetus | D48: HT102312 | F48: шт | G48: GBP | H48: 487.92 | I48: NET_EXPLICIT | K48: 487.92 | L48: =IF(AND(ISNUMBER(K48),K48>=0,G48="EUR"),ROUND(K48,2),IF(AND(ISNUMBER(K48),K48>=0,G48="GBP"),ROUND(ROUND(K48,2)/0.85915,2),"")) -> 567.91 | M48: OBSERVED_NET_CONDITIONAL_SCOPE | N48: PUBLIC_PRICE_NOT_KP | O48: UNKNOWN | P48: 2026-09-11 | Q48: https://www.vetus-shop.com/aluminium-hydraulic-tank-70-incl-ht1013-p-2024.html | U48: PARTIAL_HYDRAULIC_NOT_COMPLETE | V48: Один тип клапана; не весь блок гидролебёдок, количество потребителей открыто. | W48: Не подтверждено | X48: deliverables/M02/v001/01_support/all-candidates.csv
A49: A05 | B49: ME-29 | C49: Vetus | D49: HT1011 | F49: шт | G49: GBP | H49: 715.83 | I49: NET_EXPLICIT | K49: 715.83 | L49: =IF(AND(ISNUMBER(K49),K49>=0,G49="EUR"),ROUND(K49,2),IF(AND(ISNUMBER(K49),K49>=0,G49="GBP"),ROUND(ROUND(K49,2)/0.85915,2),"")) -> 833.18 | M49: OBSERVED_NET_CONDITIONAL_SCOPE | N49: PUBLIC_PRICE_NOT_KP | O49: UNKNOWN | P49: 2026-09-11 | Q49: https://www.vetus-shop.com/vetus-power-hydraulics-c-21_210.html | U49: PARTIAL_HYDRAULIC_NOT_COMPLETE | V49: Одноступенчатый load sensing; пригодность к общей системе открыта. | W49: Не подтверждено | X49: deliverables/M02/v001/01_support/all-candidates.csv
A50: A06 | B50: ME-29 | C50: Vetus | D50: HT1013 | F50: шт | G50: GBP | H50: 300.83 | I50: NET_EXPLICIT | K50: 300.83 | L50: =IF(AND(ISNUMBER(K50),K50>=0,G50="EUR"),ROUND(K50,2),IF(AND(ISNUMBER(K50),K50>=0,G50="GBP"),ROUND(ROUND(K50,2)/0.85915,2),"")) -> 350.15 | M50: OBSERVED_NET_CONDITIONAL_SCOPE | N50: PUBLIC_PRICE_NOT_KP | O50: UNKNOWN | P50: 2026-09-11 | Q50: https://www.vetus-shop.com/aluminium-hydraulic-tank-70-incl-ht1013-p-2024.html | U50: INCLUDED_COMPONENT_DO_NOT_ADD | V50: Уже входит в HT1010; отдельная цена только для дополнительного потребителя, не прибавлять повторно. | W50: Не подтверждено | X50: deliverables/M02/v001/01_support/all-candidates.csv
A51: A07 | B51: ME-29 | C51: Sleipner | D51: Load-sensing system / bulkhead tank 40L | F51: шт | G51: EUR | I51: RFQ_REQUIRED | L51: =IF(AND(ISNUMBER(K51),K51>=0,G51="EUR"),ROUND(K51,2),IF(AND(ISNUMBER(K51),K51>=0,G51="GBP"),ROUND(ROUND(K51,2)/0.85915,2),"")) | M51: NO_VERIFIED_NET | N51: PUBLIC_PRICE_NOT_KP | O51: UNKNOWN | P51: 2026-09-11 | R51: https://info.sleipnergroup.com/hubfs/Side-Power_Hydraulic_AC_Thrusters_2020.pdf | S51: 870 × 330 × 705 | T51: 55 | U51: RFQ_REQUIRED_TECH_OPEN | V51: Справочный габарит настенного танк-модуля из каталога2020; с блоком одного подруливающего, без всей установки. Ещё100мм для замены фильтра. Нужны текущийCAD и расчёт всех потребителей. | W51: Не подтверждено | X51: deliverables/M02/v001/01_support/all-candidates.csv
A52: A08 | B52: ME-29 | C52: Harken | D52: Hydro 2 | F52: шт | G52: EUR | I52: RFQ_REQUIRED | L52: =IF(AND(ISNUMBER(K52),K52>=0,G52="EUR"),ROUND(K52,2),IF(AND(ISNUMBER(K52),K52>=0,G52="GBP"),ROUND(ROUND(K52,2)/0.85915,2),"")) | M52: NO_VERIFIED_NET | N52: PUBLIC_PRICE_NOT_KP | O52: UNKNOWN | P52: 2026-09-11 | R52: https://gallery.harken.com/gallery/3d369089-1f35-489d-8b71-ab3020e962a1.pdf | S52: 491 × 341 × 567.7 | T52: 63.5 | U52: RFQ_REQUIRED_THRUSTER_CAPABILITY_OPEN | V52: 30л,2мотора24V4kW; стандартная помпа15л/мин140бар. Не доказана пригодность для подруливающих; не назначать резервное питание от6АКБ дорасчёта тока. | W52: Не подтверждено | X52: deliverables/M02/v001/01_support/all-candidates.csv
A53: A09 | B53: ME-18 | C53: Parker Racor | D53: 75500MAXM30 | F53: шт | G53: EUR | H53: 2199.9 | I53: GROSS_RATE_VERIFIED | J53: 19 | K53: 1848.66 | L53: =IF(AND(ISNUMBER(K53),K53>=0,G53="EUR"),ROUND(K53,2),IF(AND(ISNUMBER(K53),K53>=0,G53="GBP"),ROUND(ROUND(K53,2)/0.85915,2),"")) -> 1848.66 | M53: VARIABLE_PRICE_RECONFIRM | N53: PUBLIC_PRICE_NOT_KP | O53: UNKNOWN | P53: 2026-09-11 | Q53: https://racorshop.de/product/racor-75500maxm30-turbine-filter-marine/ | R53: https://www.parker.com/content/dam/Parker-com/Literature/Racor-Europe/FDRB544UK_BRO_Distribution_Solution_Brochure-_Racor_Europe.pdf | U53: PRICE_VARIATION_RECONFIRM_TECH_OPEN | V53: Root open2612.00gross/19%=2194.96NET; повторное открытие независимым агентом2199.90gross/19%=1848.66NET. Принято последнее наблюдение, расхождение сохранено; подтвердить цену до сравнения. Дуплексный узел, микроны/расход одной ветви под двигатель. | W53: 1 in stock | X53: deliverables/M02/v001/01_support/all-candidates.csv
A54: A10 | B54: ME-19 | C54: Vetus | D54: FTR330/32 | F54: шт | G54: GBP | H54: 81.67 | I54: NET_EXPLICIT | K54: 81.67 | L54: =IF(AND(ISNUMBER(K54),K54>=0,G54="EUR"),ROUND(K54,2),IF(AND(ISNUMBER(K54),K54>=0,G54="GBP"),ROUND(ROUND(K54,2)/0.85915,2),"")) -> 95.06 | M54: OBSERVED_NET_CONDITIONAL_SCOPE | N54: PUBLIC_PRICE_NOT_KP | O54: UNKNOWN | P54: 2026-09-11 | Q54: https://www.vetus-shop.com/vetus-raw-water-strainer-type-330-and21632mm-p-1026.html | U54: UNIT_BENCHMARK_TECH_OPEN | V54: Типоразмер32мм только ориентир; диаметр и положение относительно ватерлинии по выбранному агрегату. | W54: 10+ in stock | X54: deliverables/M02/v001/01_support/all-candidates.csv
A55: A11 | B55: ME-19 | C55: Vetus | D55: FTR33032M | F55: шт | G55: EUR | H55: 164.46 | I55: NET_EXPLICIT | K55: 164.46 | L55: =IF(AND(ISNUMBER(K55),K55>=0,G55="EUR"),ROUND(K55,2),IF(AND(ISNUMBER(K55),K55>=0,G55="GBP"),ROUND(ROUND(K55,2)/0.85915,2),"")) -> 164.46 | M55: OBSERVED_NET_CONDITIONAL_SCOPE | N55: PUBLIC_PRICE_NOT_KP | O55: UNKNOWN | P55: 2026-09-11 | Q55: https://www.mediawinkel.eu/nl/heavy-duty-waterfilter-32-mm.html | U55: UNIT_BENCHMARK_TECH_OPEN | V55: NET явно exclusiefBTW; усиленная версия с металлической крышкой. Сравнение с FTR330/32 требует одинаковых давления/установочного положения. | W55: Не подтверждено | X55: deliverables/M02/v001/01_support/all-candidates.csv
A56: A12 | B56: ME-20 | C56: Rule | D56: 2000 GPH / model12 /24V | F56: шт | G56: GBP | H56: 107.24 | I56: NET_EXPLICIT | K56: 107.24 | L56: =IF(AND(ISNUMBER(K56),K56>=0,G56="EUR"),ROUND(K56,2),IF(AND(ISNUMBER(K56),K56>=0,G56="GBP"),ROUND(ROUND(K56,2)/0.85915,2),"")) -> 124.82 | M56: OBSERVED_NET_CONDITIONAL_SCOPE | N56: PUBLIC_PRICE_NOT_KP | O56: UNKNOWN | P56: 2026-09-11 | Q56: https://www.mackengineering.co.uk/rule-2000-gph-bilge-pump-24v.html | R56: https://www.xylem.com/siteassets/brand/rule/resources/technical-brochure/standard-bilge-pumps-model-number-table.pdf | S56: 108 × 108 × 152 | U56: UNIT_BENCHMARK_TECH_OPEN | V56: Габариты из официальной таблицы, у дилера155×105 отличаются; сверить ревизию. Не вся система осушения; поплавок/сигнализация отдельно. | W56: Не подтверждено | X56: deliverables/M02/v001/01_support/all-candidates.csv
A57: A13 | B57: ME-20 | C57: Whale | D57: Gusher Urchin BP9005 | F57: шт | G57: GBP | H57: 55.1 | I57: NET_EXPLICIT | K57: 55.1 | L57: =IF(AND(ISNUMBER(K57),K57>=0,G57="EUR"),ROUND(K57,2),IF(AND(ISNUMBER(K57),K57>=0,G57="GBP"),ROUND(ROUND(K57,2)/0.85915,2),"")) -> 64.13 | M57: OBSERVED_NET_CONDITIONAL_SCOPE | N57: PUBLIC_PRICE_NOT_KP | O57: UNKNOWN | P57: 2026-09-11 | Q57: https://www.mackengineering.co.uk/bp9005-whale-gusher-urchin-hand-pump.html | U57: UNIT_BENCHMARK_TECH_OPEN | V57: Ориентир цены ручного насоса; не назначенный главный аварийный насос67ft, расход/напор/доступ проверить. | W57: Не подтверждено | X57: deliverables/M02/v001/01_support/all-candidates.csv
A58: A14 | B58: ME-20 | C58: Rule | D58: 32ALA /24V | F58: шт | G58: GBP | H58: 73.19 | I58: NET_EXPLICIT | K58: 73.19 | L58: =IF(AND(ISNUMBER(K58),K58>=0,G58="EUR"),ROUND(K58,2),IF(AND(ISNUMBER(K58),K58>=0,G58="GBP"),ROUND(ROUND(K58,2)/0.85915,2),"")) -> 85.19 | M58: OBSERVED_NET_CONDITIONAL_SCOPE | N58: PUBLIC_PRICE_NOT_KP | O58: UNKNOWN | P58: 2026-09-11 | Q58: https://www.mackengineering.co.uk/rule-2000-gph-bilge-pump-24v.html | U58: UNIT_BENCHMARK_TECH_OPEN | V58: Цена связанного товара открытой карточки; состав сигнализации и число отсеков открыты. | W58: Не подтверждено | X58: deliverables/M02/v001/01_support/all-candidates.csv
A59: A15 | B59: ME-22 | C59: Jabsco | D59: 35770-0094 /24V | F59: шт | G59: GBP | H59: 224.42 | I59: SEARCH_ONLY_NET_CLAIM | L59: =IF(AND(ISNUMBER(K59),K59>=0,G59="EUR"),ROUND(K59,2),IF(AND(ISNUMBER(K59),K59>=0,G59="GBP"),ROUND(ROUND(K59,2)/0.85915,2),"")) | M59: NO_VERIFIED_NET | N59: PUBLIC_PRICE_NOT_KP | O59: UNKNOWN | P59: 2026-09-11 | Q59: https://www.mackengineering.co.uk/35770-0094-24v-flexmount-blower.html | R59: https://www.xylem.com/siteassets/brand/jabsco/resources/manual/357x0-technical-data-sheet.pdf | T59: 3.18 | U59: PRICE_NOT_ADMITTED_AVAILABILITY_HOLD | V59: Поиск224.42exVAT, открытиеchallenge. Раздел дилера предупреждаетhold EU compliance. NET поле пусто; не считать доступным. Официально7м³/мин свободныйрасход, требуемыйнапорнепроверен. | W59: CHECK_AVAILABILITY / category EU hold | X59: deliverables/M02/v001/01_support/all-candidates.csv
A60: A16 | B60: ME-23 | C60: Marco | D60: UP3/OIL 16402013 /24V | F60: шт | G60: GBP | H60: 162 | I60: NET_EXPLICIT | K60: 162 | L60: =IF(AND(ISNUMBER(K60),K60>=0,G60="EUR"),ROUND(K60,2),IF(AND(ISNUMBER(K60),K60>=0,G60="GBP"),ROUND(ROUND(K60,2)/0.85915,2),"")) -> 188.56 | M60: OBSERVED_NET_CONDITIONAL_SCOPE | N60: PUBLIC_PRICE_NOT_KP | O60: UNKNOWN | P60: 2026-09-11 | Q60: https://www.mackengineering.co.uk/marco-up3-oil-pump-24v.html | R60: https://items.marco.it/en/md_productpdf/index/generate/product/253/store/2/ | U60: UNIT_BENCHMARK_TECH_OPEN | V60: Только насос; коллектор3агрегатов,шланги,поддоны,свет и автоматика не включены. | W60: Не подтверждено | X60: deliverables/M02/v001/01_support/all-candidates.csv
A61: A17 | B61: ME-24 | C61: Vetus | D61: SENSOR320 | F61: шт | G61: GBP | H61: 61.67 | I61: NET_EXPLICIT | K61: 61.67 | L61: =IF(AND(ISNUMBER(K61),K61>=0,G61="EUR"),ROUND(K61,2),IF(AND(ISNUMBER(K61),K61>=0,G61="GBP"),ROUND(ROUND(K61,2)/0.85915,2),"")) -> 71.78 | M61: OBSERVED_NET_CONDITIONAL_SCOPE | N61: PUBLIC_PRICE_NOT_KP | O61: UNKNOWN | P61: 2026-09-11 | Q61: https://www.vetus-shop.com/vetus-fuel-tank-quickfit-diesel-40-litre-8mm-p-1786.html | U61: UNIT_BENCHMARK_TECH_OPEN | V61: Длина320мм исследовательская; не утверждена глубина/число танков. Цена связанного товара, отдельный индикатор не включён. | W61: Не подтверждено | X61: deliverables/M02/v001/01_support/all-candidates.csv
A62: A18 | B62: ME-24 | C62: Vetus | D62: SENSORA | F62: шт | G62: GBP | H62: 161.25 | I62: NET_EXPLICIT | K62: 161.25 | L62: =IF(AND(ISNUMBER(K62),K62>=0,G62="EUR"),ROUND(K62,2),IF(AND(ISNUMBER(K62),K62>=0,G62="GBP"),ROUND(ROUND(K62,2)/0.85915,2),"")) -> 187.69 | M62: OBSERVED_NET_CONDITIONAL_SCOPE | N62: PUBLIC_PRICE_NOT_KP | O62: UNKNOWN | P62: 2026-09-11 | Q62: https://www.vetus-shop.com/vetus-fuel-tank-quickfit-diesel-40-litre-8mm-p-1786.html | U62: UNIT_BENCHMARK_TECH_OPEN | V62: Ультразвуковой аналоговый датчик; работа в конкретном танке и интерфейс подлежат проверке. Не цена танка. | W62: Не подтверждено | X62: deliverables/M02/v001/01_support/all-candidates.csv
A63: A19 | B63: ME-25 | C63: Jabsco | D63: 18590-2094 /24V | F63: шт | G63: GBP | H63: 141.63 | I63: NET_EXPLICIT | K63: 141.63 | L63: =IF(AND(ISNUMBER(K63),K63>=0,G63="EUR"),ROUND(K63,2),IF(AND(ISNUMBER(K63),K63>=0,G63="GBP"),ROUND(ROUND(K63,2)/0.85915,2),"")) -> 164.85 | M63: OBSERVED_NET_CONDITIONAL_SCOPE | N63: PUBLIC_PRICE_NOT_KP | O63: UNKNOWN | P63: 2026-09-11 | Q63: https://www.cactusnav.com/jabsco-macerator-pump-p-37922.html | U63: UNIT_BENCHMARK_TECH_OPEN | V63: 24V; только насос сточного танка. Пересечение с комплектом туалета проверять; число танков не назначено. | W63: In Stock Plymouth | X63: deliverables/M02/v001/01_support/all-candidates.csv
A64: A20 | B64: ME-21 | C64: Fireboy | D64: MA series 31.620.55 | F64: шт | G64: EUR | H64: 1950 | I64: SEARCH_ONLY_NET_CLAIM | L64: =IF(AND(ISNUMBER(K64),K64>=0,G64="EUR"),ROUND(K64,2),IF(AND(ISNUMBER(K64),K64>=0,G64="GBP"),ROUND(ROUND(K64,2)/0.85915,2),"")) | M64: NO_VERIFIED_NET | N64: PUBLIC_PRICE_NOT_KP | O64: UNKNOWN | P64: 2026-09-11 | Q64: https://www.oltrevela.com/en/31-620-55-fireboy-ma-series-automatic-manual-fire-extinguisher-13-4-kg-for-engine-rooms-and-motor-compartments-up-to-51m-uscg-and-iso-rina-approved-fireboy-4 | R64: https://fireboy.com/ma2-fire-extinguisher/ | U64: PRICE_NOT_ADMITTED_VOLUME_AND_VARIANT_OPEN | V64: Поиск1950NET, открытиеошибка. Заголовок51м³, таблица15.6м³ противоречат; модель/заряд не выбраны. Нельзя уменьшать заряд ради габарита. Отключение двигателей/вентиляции и ручнойпуск по отдельномуBOM. | W64: Не подтверждено | X64: deliverables/M02/v001/01_support/all-candidates.csv
A65: A21 | B65: ME-26 | C65: Webasto | D65: Thermo Pro90 Marine 24V /9029943C | F65: шт | G65: EUR | H65: 2007.16 | I65: NET_LABEL_CONFLICT | L65: =IF(AND(ISNUMBER(K65),K65>=0,G65="EUR"),ROUND(K65,2),IF(AND(ISNUMBER(K65),K65>=0,G65="GBP"),ROUND(ROUND(K65,2)/0.85915,2),"")) | M65: NO_VERIFIED_NET | N65: PUBLIC_PRICE_NOT_KP | O65: UNKNOWN | P65: 2026-09-11 | Q65: https://www.standkachel.nu/webasto-air-and-water-heaters-and/webasto-waterkachels-thermotop-spheros-dbw-valeo/webasto-marine-waterheaters-for-thermo-pro-90-24-volt/webasto-thermo-chiller--pro-90-marine-24-volt- | U65: OPTIONAL_PRICE_NOT_ADMITTED_TAX_CONFLICT | V65: Открытая карточка маркирует2007.16NET, показывает2161.71sale/2543.18list: арифметика налоговойпары неясна. Неиспользоватьвранжировании; отоплениеещёопция, нечиллеркондиционирования. | W65: Не подтверждено | X65: deliverables/M02/v001/01_support/all-candidates.csv
A66: A22 | B66: ME-26 | C66: Webasto | D66: Thermo Pro90 Marine 24V /4111185A | F66: шт | G66: GBP | H66: 1995.49 | I66: NET_EXPLICIT | K66: 1995.49 | L66: =IF(AND(ISNUMBER(K66),K66>=0,G66="EUR"),ROUND(K66,2),IF(AND(ISNUMBER(K66),K66>=0,G66="GBP"),ROUND(ROUND(K66,2)/0.85915,2),"")) -> 2322.63 | M66: OBSERVED_NET_CONDITIONAL_SCOPE | N66: PUBLIC_PRICE_NOT_KP | O66: UNKNOWN | P66: 2026-09-11 | Q66: https://www.butlertechnik.com/item/Webasto/Thermo-Pro-90-24v-Marine-Kit-With-Switch-91kW-4111185A/5G7 | R66: https://www.butlertechnik.com/downloads/cms/7432/webasto-thermo-pro-90-marine-installation-manual.pdf | U66: OPTIONAL_UNIT_BENCHMARK_TECH_OPEN | V66: 9.1kW только исследовательский класс; монтажный комплект с выключателем, остальные контуры и теплоотдающие устройства не включены. Не выбранное отопление и не чиллер. | W66: Item out of stock | X66: deliverables/M02/v001/01_support/all-candidates.csv
A67: YAN-E01 | B67: ME-01|ME-02 | C67: Yanmar | D67: 8LV320E-KMH50A + VC20 | E67: 1 | F67: package | G67: EUR | H67: 58842 | I67: incl BTW; rate not stated | L67: =IF(AND(ISNUMBER(K67),K67>=0,G67="EUR"),ROUND(K67,2),IF(AND(ISNUMBER(K67),K67>=0,G67="GBP"),ROUND(ROUND(K67,2)/0.85915,2),"")) | M67: NO_VERIFIED_NET | N67: PUBLIC_PRICE_NOT_KP | O67: UNKNOWN | P67: 2026-09-11 | Q67: https://www.abma-sneek.nl/yanmar/engines-gears-drives/powerboat-engines?prod_id=650436 | R67: https://www.yanmar.com/marine/product/engines/8lv320/ | S67: 1340 × 880 × 766 | T67: 487 | U67: CONDITIONAL_DUTY_PTO_START_VOLTAGE; NET_RFQ_REQUIRED | V67: 320 mhp / 235 kW at 3800 rpm; 1 engine + 1 KMH50A + VC20; manufacturer 2021 package dry mass 435+52 kg and envelope with gear/elbow; standard 12V starter; front belt PTO optional capacity unverified; dealer includes mounts/panel/wiring/fluids; installed propulsion scope incomplete | W67: Dealer says in stock; exact stock and price validity RFQ | X67: deliverables/M03/v001/01_support/yanmar/candidates.csv
A68: YAN-E02 | B68: ME-01 | C68: Yanmar | D68: 6LPAM-STP2 bobtail (dealer); 6LPA-STP2 manufacturer | E68: 1 | F68: engine | G68: EUR | H68: 21675 | I68: excl BTW; NET explicitly listed | K68: 21675 | L68: =IF(AND(ISNUMBER(K68),K68>=0,G68="EUR"),ROUND(K68,2),IF(AND(ISNUMBER(K68),K68>=0,G68="GBP"),ROUND(ROUND(K68,2)/0.85915,2),"")) -> 21675 | M68: OBSERVED_NET_CONDITIONAL_SCOPE | N68: PUBLIC_PRICE_NOT_KP | O68: UNKNOWN | P68: 2026-09-11 | Q68: https://useddieselenginecenter.nl/yanmar-6lpam-stp2-6-lpam-stp-2-bobtail | R68: https://www.yanmar.com/marine/product/engines/6lpa-stp2-6lpa-stc/ | T68: 408 | U68: CONDITIONAL_EU_NEWBUILD_CERT_DUTY_PTO_START_VOLTAGE; GEARBOX_NOT_PRICED | V68: New per dealer; 315 mhp / 232 kW at 3800 rpm at 25C fuel; 299 mhp / 220 kW at 40C per 2017 spec; priced engine only excluding gear/panel/harness; proposed 1 KMH50A RFQ; engine-only dry mass; package envelope 1220x666x739 drawing vs1190 length table conflict; package dry mass459 kg; 12V starter; RCD1 only evidenced | W68: Stock field0 conflicts with availability from stock; RFQ | X68: deliverables/M03/v001/01_support/yanmar/candidates.csv
A69: YAN-E03 | B69: ME-01|ME-02 | C69: Yanmar | D69: 6LY2M-WDT + YX-50S (proposed) | E69: 1 | F69: package | G69: EUR | I69: RFQ_REQUIRED | L69: =IF(AND(ISNUMBER(K69),K69>=0,G69="EUR"),ROUND(K69,2),IF(AND(ISNUMBER(K69),K69>=0,G69="GBP"),ROUND(ROUND(K69,2)/0.85915,2),"")) | M69: NO_VERIFIED_NET | N69: PUBLIC_PRICE_NOT_KP | O69: UNKNOWN | P69: 2026-09-11 | R69: https://www.yanmar.com/marine/product/engines/6ly2m-wdt/ | S69: 1412 × 835 × 880 | T69: 643 | U69: RFQ_REQUIRED; CONDITIONAL_EU_NEWBUILD_CERT_DUTY_PTO | V69: Current official card330 mhp /243 kW at3200 rpm; 1 engine +1 proposedYX-50S; package dry mass535+108kg; envelope with gear/high-riser elbow; optional24V electrical system official but exact starter/configuration RFQ; IMO Tier2 shown not EU RCD approval; PTO capacity unverified | W69: Official current catalogue; European delivery and new-build certification RFQ | X69: deliverables/M03/v001/01_support/yanmar/candidates.csv
A70: PAN-G01 | B70: ME-04|ME-19 | C70: Fischer Panda | D70: 12000x PMS JPC FP12000X | E70: 2 | F70: package | G70: GBP | H70: 16830 | I70: EXPLICIT_GROSS_NET_PAIR | J70: 20 | K70: 14025 | L70: =IF(AND(ISNUMBER(K70),K70>=0,G70="EUR"),ROUND(K70,2),IF(AND(ISNUMBER(K70),K70>=0,G70="GBP"),ROUND(ROUND(K70,2)/0.85915,2),"")) -> 16324.27 | M70: OBSERVED_NET_CONDITIONAL_SCOPE | N70: PUBLIC_PRICE_NOT_KP | O70: UNKNOWN | P70: 2026-09-11 | Q70: https://www.jpcdirect.com/product/fischer-panda-12000x-generator/ | R70: https://www.onefischerpanda.com/fileadmin/content/product-information/marine-generators-compact-power/12000x/Panda_12000x_PMS_-_EN.pdf | S70: 705 × 450 × 590 | T70: 195 | U70: MARKET_REFERENCE|START24V_OPEN|HOT_OUTPUT_OPEN|UK_IMPORT_OPEN | V70: 50Hz230V not yet accepted as220V target;2generators retained;standard datasheet12Vstarter, priced24V SKU unconfirmed. 10.2kW/12kVA NOMINAL at20C;2026catalogue treats0.85 kVA factor as short inductive starting only;hot continuous useful output OPEN. Capsule dimensions exclude fittings and service space;ME19 partial factory cooling only. JPC H565/192kg metadata conflicts withOEM. Fuel pump/looms/control panel/capsule advertised;exact control revision and install kit RFQ. | W70: Available on back-order;qty2/dateRFQ | X70: deliverables/M03/v001/01_support/panda/candidates.csv
A71: PAN-G02 | B71: ME-04|ME-19 | C71: Fischer Panda | D71: 12000x-230V PMS NautiRadar0028284 | E71: 2 | F71: package | G71: EUR | H71: 17451.22 | I71: NET_EXPLICIT | K71: 17451.22 | L71: =IF(AND(ISNUMBER(K71),K71>=0,G71="EUR"),ROUND(K71,2),IF(AND(ISNUMBER(K71),K71>=0,G71="GBP"),ROUND(ROUND(K71,2)/0.85915,2),"")) -> 17451.22 | M71: OBSERVED_NET_CONDITIONAL_SCOPE | N71: PUBLIC_PRICE_NOT_KP | O71: UNKNOWN | P71: 2026-09-11 | Q71: https://www.nautiradar.pt/en/products/fischer-panda/panda-12000x-230v-pms-12kva-fixed-engine-speed-marine-generator | R71: https://www.onefischerpanda.com/fileadmin/content/product-information/marine-generators-compact-power/12000x/Panda_12000x_PMS_-_EN.pdf | S71: 705 × 450 × 590 | T71: 195 | U71: MARKET_REFERENCE|START24V_OPEN|HOT_OUTPUT_OPEN|SKU_REVISION_OPEN | V71: 50Hz230V not yet accepted as220V target;2generators retained;standard datasheet12Vstarter, priced24V SKU unconfirmed. 10.2kW/12kVA NOMINAL at20C;2026catalogue treats0.85 kVA factor as short inductive starting only;hot continuous useful output OPEN. Capsule dimensions exclude fittings and service space;ME19 partial factory cooling only. SellerSKU0028284 vsOEMsheet0024660:exact revision must be tied to offer. EU seller does not yet prove EU dispatch/free-circulation/Poland delivery. | W71: Stock and lead time not stated;qty2/dateRFQ | X71: deliverables/M03/v001/01_support/panda/candidates.csv
A72: PAN-G03 | B72: ME-04|ME-19 | C72: Fischer Panda | D72: 15000i-230V PMS NautiRadar0000182 | E72: 2 | F72: package | G72: EUR | H72: 20128.46 | I72: NET_EXPLICIT | K72: 20128.46 | L72: =IF(AND(ISNUMBER(K72),K72>=0,G72="EUR"),ROUND(K72,2),IF(AND(ISNUMBER(K72),K72>=0,G72="GBP"),ROUND(ROUND(K72,2)/0.85915,2),"")) -> 20128.46 | M72: OBSERVED_NET_CONDITIONAL_SCOPE | N72: PUBLIC_PRICE_NOT_KP | O72: UNKNOWN | P72: 2026-09-11 | Q72: https://www.nautiradar.pt/en/products/fischer-panda/panda-15000i-230v-pms-12kw-230v-variable-speed-marine-generator | R72: https://www.fischerpanda.co.uk/res/Fischer%20Panda%20Marine%20Generators%202026%20-%20FPUK | S72: 650 × 465 × 589 | T72: 176 | U72: MARKET_REFERENCE|START24V_OPEN|HOT_OUTPUT_OPEN|INVERTER_SCOPE_OPEN | V72: Alternative model for same required useful output;not15kW.50Hz230V nominal12kW/15kVA;PMGi230V manual longterm12kW does not guarantee whole-set output at hot ambient;OEM20C engine reference.160kg capsule+16kg external inverter;dimensions capsule only;dealer162+16kg discrepancy. Inverter model/cooling/inclusion and24V starter RFQ.2gens retained;no automatic parallel operation. | W72: Stock and lead time not stated;qty2/dateRFQ | X72: deliverables/M03/v001/01_support/panda/candidates.csv

Sheet 03_Состав
A1: Строка | B1: Вариант | C1: M01 / интерфейсы | D1: Источник_ID | E1: Количество | F1: Ед. | G1: Исполнение из источника | H1: NET / ед. EUR | I1: Известная NET строки | J1: Класс цены | K1: Допуск ценового основания | L1: Состав / недостающее
A2: PK01-A-L01 | B2: PK01-A | C2: ME-01|ME-02|ME-03 | D2: PROP-E02 | E2: 1 | F2: package | G2: =IFERROR(IF(INDEX(02_Цены!$D$2:$D$1000,MATCH(D2,02_Цены!$A$2:$A$1000,0))="","",INDEX(02_Цены!$D$2:$D$1000,MATCH(D2,02_Цены!$A$2:$A$1000,0))),"") -> D4-300 I + HS85A | H2: =IFERROR(IF(INDEX(02_Цены!$L$2:$L$1000,MATCH(D2,02_Цены!$A$2:$A$1000,0))="","",INDEX(02_Цены!$L$2:$L$1000,MATCH(D2,02_Цены!$A$2:$A$1000,0))),"") -> 45977 | I2: =IF(AND(ISNUMBER(E2),E2>=0,ISNUMBER(H2)),ROUND(E2*H2,2),"") -> 45977 | J2: =IFERROR(IF(INDEX(02_Цены!$M$2:$M$1000,MATCH(D2,02_Цены!$A$2:$A$1000,0))="","",INDEX(02_Цены!$M$2:$M$1000,MATCH(D2,02_Цены!$A$2:$A$1000,0))),"") -> HISTORICAL_NOT_CURRENT | K2: =IF(AND(ISNUMBER(I2),J2="OBSERVED_NET_CONDITIONAL_SCOPE",OR(IFERROR(IF(INDEX(02_Цены!$E$2:$E$1000,MATCH(D2,02_Цены!$A$2:$A$1000,0))="","",INDEX(02_Цены!$E$2:$E$1000,MATCH(D2,02_Цены!$A$2:$A$1000,0))),"")="",E2=IFERROR(IF(INDEX(02_Цены!$E$2:$E$1000,MATCH(D2,02_Цены!$A$2:$A$1000,0))="","",INDEX(02_Цены!$E$2:$E$1000,MATCH(D2,02_Цены!$A$2:$A$1000,0))),""))),"PRICE_OBSERVED","BLOCK") -> BLOCK | L2: 300 metric hp crank / 289 prop shaft; 3500rpm R5; 24V option price open; ratio2.500. L=433+801 W=441+407 H=274+520 from drawing; excludes projecting lifting eye/service space; not installation GA; ME-03 partial only factory mounts where included: shaft/coupling/thrust unit quantities and price OPEN
A3: PK01-B-L01 | B3: PK01-B | C3: ME-01|ME-02 | D3: YAN-E01 | E3: 1 | F3: package | G3: =IFERROR(IF(INDEX(02_Цены!$D$2:$D$1000,MATCH(D3,02_Цены!$A$2:$A$1000,0))="","",INDEX(02_Цены!$D$2:$D$1000,MATCH(D3,02_Цены!$A$2:$A$1000,0))),"") -> 8LV320E-KMH50A + VC20 | H3: =IFERROR(IF(INDEX(02_Цены!$L$2:$L$1000,MATCH(D3,02_Цены!$A$2:$A$1000,0))="","",INDEX(02_Цены!$L$2:$L$1000,MATCH(D3,02_Цены!$A$2:$A$1000,0))),"") | I3: =IF(AND(ISNUMBER(E3),E3>=0,ISNUMBER(H3)),ROUND(E3*H3,2),"") | J3: =IFERROR(IF(INDEX(02_Цены!$M$2:$M$1000,MATCH(D3,02_Цены!$A$2:$A$1000,0))="","",INDEX(02_Цены!$M$2:$M$1000,MATCH(D3,02_Цены!$A$2:$A$1000,0))),"") -> NO_VERIFIED_NET | K3: =IF(AND(ISNUMBER(I3),J3="OBSERVED_NET_CONDITIONAL_SCOPE",OR(IFERROR(IF(INDEX(02_Цены!$E$2:$E$1000,MATCH(D3,02_Цены!$A$2:$A$1000,0))="","",INDEX(02_Цены!$E$2:$E$1000,MATCH(D3,02_Цены!$A$2:$A$1000,0))),"")="",E3=IFERROR(IF(INDEX(02_Цены!$E$2:$E$1000,MATCH(D3,02_Цены!$A$2:$A$1000,0))="","",INDEX(02_Цены!$E$2:$E$1000,MATCH(D3,02_Цены!$A$2:$A$1000,0))),""))),"PRICE_OBSERVED","BLOCK") -> BLOCK | L3: 320 mhp / 235 kW at 3800 rpm; 1 engine + 1 KMH50A + VC20; manufacturer 2021 package dry mass 435+52 kg and envelope with gear/elbow; standard 12V starter; front belt PTO optional capacity unverified; dealer includes mounts/panel/wiring/fluids; installed propulsion scope incomplete
A4: PK01-C-L01 | B4: PK01-C | C4: ME-01|ME-02|ME-03 | D4: PROP-E04 | E4: 1 | F4: package | G4: =IFERROR(IF(INDEX(02_Цены!$D$2:$D$1000,MATCH(D4,02_Цены!$A$2:$A$1000,0))="","",INDEX(02_Цены!$D$2:$D$1000,MATCH(D4,02_Цены!$A$2:$A$1000,0))),"") -> C90 410 rating D 300hp + gearbox RFQ | H4: =IFERROR(IF(INDEX(02_Цены!$L$2:$L$1000,MATCH(D4,02_Цены!$A$2:$A$1000,0))="","",INDEX(02_Цены!$L$2:$L$1000,MATCH(D4,02_Цены!$A$2:$A$1000,0))),"") | I4: =IF(AND(ISNUMBER(E4),E4>=0,ISNUMBER(H4)),ROUND(E4*H4,2),"") | J4: =IFERROR(IF(INDEX(02_Цены!$M$2:$M$1000,MATCH(D4,02_Цены!$A$2:$A$1000,0))="","",INDEX(02_Цены!$M$2:$M$1000,MATCH(D4,02_Цены!$A$2:$A$1000,0))),"") -> NO_VERIFIED_NET | K4: =IF(AND(ISNUMBER(I4),J4="OBSERVED_NET_CONDITIONAL_SCOPE",OR(IFERROR(IF(INDEX(02_Цены!$E$2:$E$1000,MATCH(D4,02_Цены!$A$2:$A$1000,0))="","",INDEX(02_Цены!$E$2:$E$1000,MATCH(D4,02_Цены!$A$2:$A$1000,0))),"")="",E4=IFERROR(IF(INDEX(02_Цены!$E$2:$E$1000,MATCH(D4,02_Цены!$A$2:$A$1000,0))="","",INDEX(02_Цены!$E$2:$E$1000,MATCH(D4,02_Цены!$A$2:$A$1000,0))),""))),"PRICE_OBSERVED","BLOCK") -> BLOCK | L4: Official2026 220kW300hp@2000rpm ratingD heavy duty; gearbox unselected/unpriced; shown dimensions length to flywheel and mass ENGINE ONLY; not complete package envelope;24V option RFQ; ME-03 partial only factory mounts where included: shaft/coupling/thrust unit quantities and price OPEN
A5: PK02-A-L01 | B5: PK02-A | C5: ME-04|ME-19 | D5: PROP-G03 | E5: 2 | F5: package | G5: =IFERROR(IF(INDEX(02_Цены!$D$2:$D$1000,MATCH(D5,02_Цены!$A$2:$A$1000,0))="","",INDEX(02_Цены!$D$2:$D$1000,MATCH(D5,02_Цены!$A$2:$A$1000,0))),"") -> Paguro12000V AP12023050M0 | H5: =IFERROR(IF(INDEX(02_Цены!$L$2:$L$1000,MATCH(D5,02_Цены!$A$2:$A$1000,0))="","",INDEX(02_Цены!$L$2:$L$1000,MATCH(D5,02_Цены!$A$2:$A$1000,0))),"") -> 12446.5 | I5: =IF(AND(ISNUMBER(E5),E5>=0,ISNUMBER(H5)),ROUND(E5*H5,2),"") -> 24893 | J5: =IFERROR(IF(INDEX(02_Цены!$M$2:$M$1000,MATCH(D5,02_Цены!$A$2:$A$1000,0))="","",INDEX(02_Цены!$M$2:$M$1000,MATCH(D5,02_Цены!$A$2:$A$1000,0))),"") -> OBSERVED_NET_CONDITIONAL_SCOPE | K5: =IF(AND(ISNUMBER(I5),J5="OBSERVED_NET_CONDITIONAL_SCOPE",OR(IFERROR(IF(INDEX(02_Цены!$E$2:$E$1000,MATCH(D5,02_Цены!$A$2:$A$1000,0))="","",INDEX(02_Цены!$E$2:$E$1000,MATCH(D5,02_Цены!$A$2:$A$1000,0))),"")="",E5=IFERROR(IF(INDEX(02_Цены!$E$2:$E$1000,MATCH(D5,02_Цены!$A$2:$A$1000,0))="","",INDEX(02_Цены!$E$2:$E$1000,MATCH(D5,02_Цены!$A$2:$A$1000,0))),""))),"PRICE_OBSERVED","BLOCK") -> PRICE_OBSERVED | L5: 12kVA10kW continuous50Hz230V;12V starter;mass165capsule+15control electronics. Official dimensions capsule only; separate electronics footprint RFQ. Dealer/allpa dimensions/mass differ; exact SKU installationdrawing required. Published net directly not Polish VAT assumption; ME-19 partial factory cooling only: external seawater/exhaust runs and installation OPEN
A6: PK02-B-L01 | B6: PK02-B | C6: ME-04|ME-19 | D6: PAN-G02 | E6: 2 | F6: package | G6: =IFERROR(IF(INDEX(02_Цены!$D$2:$D$1000,MATCH(D6,02_Цены!$A$2:$A$1000,0))="","",INDEX(02_Цены!$D$2:$D$1000,MATCH(D6,02_Цены!$A$2:$A$1000,0))),"") -> 12000x-230V PMS NautiRadar0028284 | H6: =IFERROR(IF(INDEX(02_Цены!$L$2:$L$1000,MATCH(D6,02_Цены!$A$2:$A$1000,0))="","",INDEX(02_Цены!$L$2:$L$1000,MATCH(D6,02_Цены!$A$2:$A$1000,0))),"") -> 17451.22 | I6: =IF(AND(ISNUMBER(E6),E6>=0,ISNUMBER(H6)),ROUND(E6*H6,2),"") -> 34902.44 | J6: =IFERROR(IF(INDEX(02_Цены!$M$2:$M$1000,MATCH(D6,02_Цены!$A$2:$A$1000,0))="","",INDEX(02_Цены!$M$2:$M$1000,MATCH(D6,02_Цены!$A$2:$A$1000,0))),"") -> OBSERVED_NET_CONDITIONAL_SCOPE | K6: =IF(AND(ISNUMBER(I6),J6="OBSERVED_NET_CONDITIONAL_SCOPE",OR(IFERROR(IF(INDEX(02_Цены!$E$2:$E$1000,MATCH(D6,02_Цены!$A$2:$A$1000,0))="","",INDEX(02_Цены!$E$2:$E$1000,MATCH(D6,02_Цены!$A$2:$A$1000,0))),"")="",E6=IFERROR(IF(INDEX(02_Цены!$E$2:$E$1000,MATCH(D6,02_Цены!$A$2:$A$1000,0))="","",INDEX(02_Цены!$E$2:$E$1000,MATCH(D6,02_Цены!$A$2:$A$1000,0))),""))),"PRICE_OBSERVED","BLOCK") -> PRICE_OBSERVED | L6: 50Hz230V not yet accepted as220V target;2generators retained;standard datasheet12Vstarter, priced24V SKU unconfirmed. 10.2kW/12kVA NOMINAL at20C;2026catalogue treats0.85 kVA factor as short inductive starting only;hot continuous useful output OPEN. Capsule dimensions exclude fittings and service space;ME19 partial factory cooling only. SellerSKU0028284 vsOEMsheet0024660:exact revision must be tied to offer. EU seller does not yet prove EU dispatch/free-circulation/Poland delivery.
A7: PK02-C-L01 | B7: PK02-C | C7: ME-04|ME-19 | D7: PROP-G02 | E7: 2 | F7: package | G7: =IFERROR(IF(INDEX(02_Цены!$D$2:$D$1000,MATCH(D7,02_Цены!$A$2:$A$1000,0))="","",INDEX(02_Цены!$D$2:$D$1000,MATCH(D7,02_Цены!$A$2:$A$1000,0))),"") -> 12EFKOZD | H7: =IFERROR(IF(INDEX(02_Цены!$L$2:$L$1000,MATCH(D7,02_Цены!$A$2:$A$1000,0))="","",INDEX(02_Цены!$L$2:$L$1000,MATCH(D7,02_Цены!$A$2:$A$1000,0))),"") -> 17929.12 | I7: =IF(AND(ISNUMBER(E7),E7>=0,ISNUMBER(H7)),ROUND(E7*H7,2),"") -> 35858.24 | J7: =IFERROR(IF(INDEX(02_Цены!$M$2:$M$1000,MATCH(D7,02_Цены!$A$2:$A$1000,0))="","",INDEX(02_Цены!$M$2:$M$1000,MATCH(D7,02_Цены!$A$2:$A$1000,0))),"") -> OBSERVED_NET_CONDITIONAL_SCOPE | K7: =IF(AND(ISNUMBER(I7),J7="OBSERVED_NET_CONDITIONAL_SCOPE",OR(IFERROR(IF(INDEX(02_Цены!$E$2:$E$1000,MATCH(D7,02_Цены!$A$2:$A$1000,0))="","",INDEX(02_Цены!$E$2:$E$1000,MATCH(D7,02_Цены!$A$2:$A$1000,0))),"")="",E7=IFERROR(IF(INDEX(02_Цены!$E$2:$E$1000,MATCH(D7,02_Цены!$A$2:$A$1000,0))="","",INDEX(02_Цены!$E$2:$E$1000,MATCH(D7,02_Цены!$A$2:$A$1000,0))),""))),"PRICE_OBSERVED","BLOCK") -> PRICE_OBSERVED | L7: Singlephase115/230V50Hz:12kW12kVA continuous140C rise;11/11continuous115C;10.5/10.5prime. Official12or24V; JPC exactstarter/shield revision RFQ. Official shield mass385dry398wet; dealer406kg conflict. No borrowing US24V price scope; ME-19 partial factory cooling only: external seawater/exhaust runs and installation OPEN
A8: PK03-A-L01 | B8: PK03-A | C8: ME-05 | D8: EL-INV-A | E8: 2 | F8: pcs | G8: =IFERROR(IF(INDEX(02_Цены!$D$2:$D$1000,MATCH(D8,02_Цены!$A$2:$A$1000,0))="","",INDEX(02_Цены!$D$2:$D$1000,MATCH(D8,02_Цены!$A$2:$A$1000,0))),"") -> MultiPlus-II 24/3000/70-32 PMP242305010 | H8: =IFERROR(IF(INDEX(02_Цены!$L$2:$L$1000,MATCH(D8,02_Цены!$A$2:$A$1000,0))="","",INDEX(02_Цены!$L$2:$L$1000,MATCH(D8,02_Цены!$A$2:$A$1000,0))),"") -> 739.45 | I8: =IF(AND(ISNUMBER(E8),E8>=0,ISNUMBER(H8)),ROUND(E8*H8,2),"") -> 1478.9 | J8: =IFERROR(IF(INDEX(02_Цены!$M$2:$M$1000,MATCH(D8,02_Цены!$A$2:$A$1000,0))="","",INDEX(02_Цены!$M$2:$M$1000,MATCH(D8,02_Цены!$A$2:$A$1000,0))),"") -> OBSERVED_NET_CONDITIONAL_SCOPE | K8: =IF(AND(ISNUMBER(I8),J8="OBSERVED_NET_CONDITIONAL_SCOPE",OR(IFERROR(IF(INDEX(02_Цены!$E$2:$E$1000,MATCH(D8,02_Цены!$A$2:$A$1000,0))="","",INDEX(02_Цены!$E$2:$E$1000,MATCH(D8,02_Цены!$A$2:$A$1000,0))),"")="",E8=IFERROR(IF(INDEX(02_Цены!$E$2:$E$1000,MATCH(D8,02_Цены!$A$2:$A$1000,0))="","",INDEX(02_Цены!$E$2:$E$1000,MATCH(D8,02_Цены!$A$2:$A$1000,0))),""))),"PRICE_OBSERVED","BLOCK") -> PRICE_OBSERVED | L8: 24 V input; factory 230 V. 3000 VA not 3000 W: 2400 W at25C/2200 W at40C; charger70 A. 2 devices architecture target, capacity unapproved.
A9: PK03-A-L02 | B9: PK03-A | C9: ME-09 | D9: EL-ISO-A | F9: pcs | G9: =IFERROR(IF(INDEX(02_Цены!$D$2:$D$1000,MATCH(D9,02_Цены!$A$2:$A$1000,0))="","",INDEX(02_Цены!$D$2:$D$1000,MATCH(D9,02_Цены!$A$2:$A$1000,0))),"") -> 3600 ITR040362042 | H9: =IFERROR(IF(INDEX(02_Цены!$L$2:$L$1000,MATCH(D9,02_Цены!$A$2:$A$1000,0))="","",INDEX(02_Цены!$L$2:$L$1000,MATCH(D9,02_Цены!$A$2:$A$1000,0))),"") -> 436.93 | I9: =IF(AND(ISNUMBER(E9),E9>=0,ISNUMBER(H9)),ROUND(E9*H9,2),"") | J9: =IFERROR(IF(INDEX(02_Цены!$M$2:$M$1000,MATCH(D9,02_Цены!$A$2:$A$1000,0))="","",INDEX(02_Цены!$M$2:$M$1000,MATCH(D9,02_Цены!$A$2:$A$1000,0))),"") -> OBSERVED_NET_CONDITIONAL_SCOPE | K9: =IF(AND(ISNUMBER(I9),J9="OBSERVED_NET_CONDITIONAL_SCOPE",OR(IFERROR(IF(INDEX(02_Цены!$E$2:$E$1000,MATCH(D9,02_Цены!$A$2:$A$1000,0))="","",INDEX(02_Цены!$E$2:$E$1000,MATCH(D9,02_Цены!$A$2:$A$1000,0))),"")="",E9=IFERROR(IF(INDEX(02_Цены!$E$2:$E$1000,MATCH(D9,02_Цены!$A$2:$A$1000,0))="","",INDEX(02_Цены!$E$2:$E$1000,MATCH(D9,02_Цены!$A$2:$A$1000,0))),""))),"PRICE_OBSERVED","BLOCK") -> BLOCK | L9: 3.6 class; quantity and shore capacity unknown. Dimensions/mass from opened dealer data pending native drawing confirmation; no substitute of32A at115V for32A at230V.
A10: PK03-B-L01 | B10: PK03-B | C10: ME-05 | D10: EL-INV-B | E10: 2 | F10: pcs | G10: =IFERROR(IF(INDEX(02_Цены!$D$2:$D$1000,MATCH(D10,02_Цены!$A$2:$A$1000,0))="","",INDEX(02_Цены!$D$2:$D$1000,MATCH(D10,02_Цены!$A$2:$A$1000,0))),"") -> MultiPlus-II GX 24/3000/70-32 PMP242306000 | H10: =IFERROR(IF(INDEX(02_Цены!$L$2:$L$1000,MATCH(D10,02_Цены!$A$2:$A$1000,0))="","",INDEX(02_Цены!$L$2:$L$1000,MATCH(D10,02_Цены!$A$2:$A$1000,0))),"") -> 840.29 | I10: =IF(AND(ISNUMBER(E10),E10>=0,ISNUMBER(H10)),ROUND(E10*H10,2),"") -> 1680.58 | J10: =IFERROR(IF(INDEX(02_Цены!$M$2:$M$1000,MATCH(D10,02_Цены!$A$2:$A$1000,0))="","",INDEX(02_Цены!$M$2:$M$1000,MATCH(D10,02_Цены!$A$2:$A$1000,0))),"") -> OBSERVED_NET_CONDITIONAL_SCOPE | K10: =IF(AND(ISNUMBER(I10),J10="OBSERVED_NET_CONDITIONAL_SCOPE",OR(IFERROR(IF(INDEX(02_Цены!$E$2:$E$1000,MATCH(D10,02_Цены!$A$2:$A$1000,0))="","",INDEX(02_Цены!$E$2:$E$1000,MATCH(D10,02_Цены!$A$2:$A$1000,0))),"")="",E10=IFERROR(IF(INDEX(02_Цены!$E$2:$E$1000,MATCH(D10,02_Цены!$A$2:$A$1000,0))="","",INDEX(02_Цены!$E$2:$E$1000,MATCH(D10,02_Цены!$A$2:$A$1000,0))),""))),"PRICE_OBSERVED","BLOCK") -> PRICE_OBSERVED | L10: 24 V; factory230 V;2400 W at25C/2200 W at40C;70 A. GX monitoring differs; two GX units not required by yacht specification. Current manual geometry differs from catalogue: confirm revision.
A11: PK03-B-L02 | B11: PK03-B | C11: ME-09 | D11: EL-ISO-B | F11: pcs | G11: =IFERROR(IF(INDEX(02_Цены!$D$2:$D$1000,MATCH(D11,02_Цены!$A$2:$A$1000,0))="","",INDEX(02_Цены!$D$2:$D$1000,MATCH(D11,02_Цены!$A$2:$A$1000,0))),"") -> Mass GI3.5 88000355 | H11: =IFERROR(IF(INDEX(02_Цены!$L$2:$L$1000,MATCH(D11,02_Цены!$A$2:$A$1000,0))="","",INDEX(02_Цены!$L$2:$L$1000,MATCH(D11,02_Цены!$A$2:$A$1000,0))),"") -> 1008.36 | I11: =IF(AND(ISNUMBER(E11),E11>=0,ISNUMBER(H11)),ROUND(E11*H11,2),"") | J11: =IFERROR(IF(INDEX(02_Цены!$M$2:$M$1000,MATCH(D11,02_Цены!$A$2:$A$1000,0))="","",INDEX(02_Цены!$M$2:$M$1000,MATCH(D11,02_Цены!$A$2:$A$1000,0))),"") -> OBSERVED_NET_CONDITIONAL_SCOPE | K11: =IF(AND(ISNUMBER(I11),J11="OBSERVED_NET_CONDITIONAL_SCOPE",OR(IFERROR(IF(INDEX(02_Цены!$E$2:$E$1000,MATCH(D11,02_Цены!$A$2:$A$1000,0))="","",INDEX(02_Цены!$E$2:$E$1000,MATCH(D11,02_Цены!$A$2:$A$1000,0))),"")="",E11=IFERROR(IF(INDEX(02_Цены!$E$2:$E$1000,MATCH(D11,02_Цены!$A$2:$A$1000,0))="","",INDEX(02_Цены!$E$2:$E$1000,MATCH(D11,02_Цены!$A$2:$A$1000,0))),""))),"PRICE_OBSERVED","BLOCK") -> BLOCK | L11: 3500 VA at230 V;16 A;HF technology;source IP23 supersedes dealer IP21. Not complete shore protection.
A12: PK03-C-L01 | B12: PK03-C | C12: ME-05 | D12: EL-INV-C | E12: 2 | F12: pcs | G12: =IFERROR(IF(INDEX(02_Цены!$D$2:$D$1000,MATCH(D12,02_Цены!$A$2:$A$1000,0))="","",INDEX(02_Цены!$D$2:$D$1000,MATCH(D12,02_Цены!$A$2:$A$1000,0))),"") -> CombiMaster 24/3000-60 230V 35023000 | H12: =IFERROR(IF(INDEX(02_Цены!$L$2:$L$1000,MATCH(D12,02_Цены!$A$2:$A$1000,0))="","",INDEX(02_Цены!$L$2:$L$1000,MATCH(D12,02_Цены!$A$2:$A$1000,0))),"") -> 1344.5 | I12: =IF(AND(ISNUMBER(E12),E12>=0,ISNUMBER(H12)),ROUND(E12*H12,2),"") -> 2689 | J12: =IFERROR(IF(INDEX(02_Цены!$M$2:$M$1000,MATCH(D12,02_Цены!$A$2:$A$1000,0))="","",INDEX(02_Цены!$M$2:$M$1000,MATCH(D12,02_Цены!$A$2:$A$1000,0))),"") -> OBSERVED_NET_CONDITIONAL_SCOPE | K12: =IF(AND(ISNUMBER(I12),J12="OBSERVED_NET_CONDITIONAL_SCOPE",OR(IFERROR(IF(INDEX(02_Цены!$E$2:$E$1000,MATCH(D12,02_Цены!$A$2:$A$1000,0))="","",INDEX(02_Цены!$E$2:$E$1000,MATCH(D12,02_Цены!$A$2:$A$1000,0))),"")="",E12=IFERROR(IF(INDEX(02_Цены!$E$2:$E$1000,MATCH(D12,02_Цены!$A$2:$A$1000,0))="","",INDEX(02_Цены!$E$2:$E$1000,MATCH(D12,02_Цены!$A$2:$A$1000,0))),""))),"PRICE_OBSERVED","BLOCK") -> PRICE_OBSERVED | L12: 24 V; factory230 V;3000 VA/2600 W at40C;60 A charger;25 A transfer versus32 A Victron. Parallel operation not qualified.
A13: PK03-C-L02 | B13: PK03-C | C13: ME-09 | D13: EL-ISO-B | F13: pcs | G13: =IFERROR(IF(INDEX(02_Цены!$D$2:$D$1000,MATCH(D13,02_Цены!$A$2:$A$1000,0))="","",INDEX(02_Цены!$D$2:$D$1000,MATCH(D13,02_Цены!$A$2:$A$1000,0))),"") -> Mass GI3.5 88000355 | H13: =IFERROR(IF(INDEX(02_Цены!$L$2:$L$1000,MATCH(D13,02_Цены!$A$2:$A$1000,0))="","",INDEX(02_Цены!$L$2:$L$1000,MATCH(D13,02_Цены!$A$2:$A$1000,0))),"") -> 1008.36 | I13: =IF(AND(ISNUMBER(E13),E13>=0,ISNUMBER(H13)),ROUND(E13*H13,2),"") | J13: =IFERROR(IF(INDEX(02_Цены!$M$2:$M$1000,MATCH(D13,02_Цены!$A$2:$A$1000,0))="","",INDEX(02_Цены!$M$2:$M$1000,MATCH(D13,02_Цены!$A$2:$A$1000,0))),"") -> OBSERVED_NET_CONDITIONAL_SCOPE | K13: =IF(AND(ISNUMBER(I13),J13="OBSERVED_NET_CONDITIONAL_SCOPE",OR(IFERROR(IF(INDEX(02_Цены!$E$2:$E$1000,MATCH(D13,02_Цены!$A$2:$A$1000,0))="","",INDEX(02_Цены!$E$2:$E$1000,MATCH(D13,02_Цены!$A$2:$A$1000,0))),"")="",E13=IFERROR(IF(INDEX(02_Цены!$E$2:$E$1000,MATCH(D13,02_Цены!$A$2:$A$1000,0))="","",INDEX(02_Цены!$E$2:$E$1000,MATCH(D13,02_Цены!$A$2:$A$1000,0))),""))),"PRICE_OBSERVED","BLOCK") -> BLOCK | L13: 3500 VA at230 V;16 A;HF technology;source IP23 supersedes dealer IP21. Not complete shore protection.
A14: PK04-A-L01 | B14: PK04-A | C14: ME-08 | D14: EL-BAT-A | E14: 6 | F14: pcs | G14: =IFERROR(IF(INDEX(02_Цены!$D$2:$D$1000,MATCH(D14,02_Цены!$A$2:$A$1000,0))="","",INDEX(02_Цены!$D$2:$D$1000,MATCH(D14,02_Цены!$A$2:$A$1000,0))),"") -> ER550 12V115Ah | H14: =IFERROR(IF(INDEX(02_Цены!$L$2:$L$1000,MATCH(D14,02_Цены!$A$2:$A$1000,0))="","",INDEX(02_Цены!$L$2:$L$1000,MATCH(D14,02_Цены!$A$2:$A$1000,0))),"") -> 140.24 | I14: =IF(AND(ISNUMBER(E14),E14>=0,ISNUMBER(H14)),ROUND(E14*H14,2),"") -> 841.44 | J14: =IFERROR(IF(INDEX(02_Цены!$M$2:$M$1000,MATCH(D14,02_Цены!$A$2:$A$1000,0))="","",INDEX(02_Цены!$M$2:$M$1000,MATCH(D14,02_Цены!$A$2:$A$1000,0))),"") -> OBSERVED_NET_CONDITIONAL_SCOPE | K14: =IF(AND(ISNUMBER(I14),J14="OBSERVED_NET_CONDITIONAL_SCOPE",OR(IFERROR(IF(INDEX(02_Цены!$E$2:$E$1000,MATCH(D14,02_Цены!$A$2:$A$1000,0))="","",INDEX(02_Цены!$E$2:$E$1000,MATCH(D14,02_Цены!$A$2:$A$1000,0))),"")="",E14=IFERROR(IF(INDEX(02_Цены!$E$2:$E$1000,MATCH(D14,02_Цены!$A$2:$A$1000,0))="","",INDEX(02_Цены!$E$2:$E$1000,MATCH(D14,02_Цены!$A$2:$A$1000,0))),""))),"PRICE_OBSERVED","BLOCK") -> PRICE_OBSERVED | L14: Flooded. Owner only said115 amperes; Ah and unit voltage unconfirmed. 6 physical units; no bank wiring/capacity inferred. Deposit extra. Dealer350mm/29kg differs from brochure.
A15: PK04-A-L02 | B15: PK04-A | C15: ME-07 | D15: EL-OPEN-MAIN | E15: 1 | F15: pcs | G15: =IFERROR(IF(INDEX(02_Цены!$D$2:$D$1000,MATCH(D15,02_Цены!$A$2:$A$1000,0))="","",INDEX(02_Цены!$D$2:$D$1000,MATCH(D15,02_Цены!$A$2:$A$1000,0))),"") -> UNSIZED | H15: =IFERROR(IF(INDEX(02_Цены!$L$2:$L$1000,MATCH(D15,02_Цены!$A$2:$A$1000,0))="","",INDEX(02_Цены!$L$2:$L$1000,MATCH(D15,02_Цены!$A$2:$A$1000,0))),"") | I15: =IF(AND(ISNUMBER(E15),E15>=0,ISNUMBER(H15)),ROUND(E15*H15,2),"") | J15: =IFERROR(IF(INDEX(02_Цены!$M$2:$M$1000,MATCH(D15,02_Цены!$A$2:$A$1000,0))="","",INDEX(02_Цены!$M$2:$M$1000,MATCH(D15,02_Цены!$A$2:$A$1000,0))),"") -> NO_VERIFIED_NET | K15: =IF(AND(ISNUMBER(I15),J15="OBSERVED_NET_CONDITIONAL_SCOPE",OR(IFERROR(IF(INDEX(02_Цены!$E$2:$E$1000,MATCH(D15,02_Цены!$A$2:$A$1000,0))="","",INDEX(02_Цены!$E$2:$E$1000,MATCH(D15,02_Цены!$A$2:$A$1000,0))),"")="",E15=IFERROR(IF(INDEX(02_Цены!$E$2:$E$1000,MATCH(D15,02_Цены!$A$2:$A$1000,0))="","",INDEX(02_Цены!$E$2:$E$1000,MATCH(D15,02_Цены!$A$2:$A$1000,0))),""))),"PRICE_OBSERVED","BLOCK") -> BLOCK | L15: 1 physical owner battery, capacity/voltage/chemistry unknown. Not automatically ER550 or service115Ah.
A16: PK04-A-L03 | B16: PK04-A | C16: ME-27 | D16: EL-OPEN-GEN | E16: 2 | F16: pcs | G16: =IFERROR(IF(INDEX(02_Цены!$D$2:$D$1000,MATCH(D16,02_Цены!$A$2:$A$1000,0))="","",INDEX(02_Цены!$D$2:$D$1000,MATCH(D16,02_Цены!$A$2:$A$1000,0))),"") -> UNSIZED | H16: =IFERROR(IF(INDEX(02_Цены!$L$2:$L$1000,MATCH(D16,02_Цены!$A$2:$A$1000,0))="","",INDEX(02_Цены!$L$2:$L$1000,MATCH(D16,02_Цены!$A$2:$A$1000,0))),"") | I16: =IF(AND(ISNUMBER(E16),E16>=0,ISNUMBER(H16)),ROUND(E16*H16,2),"") | J16: =IFERROR(IF(INDEX(02_Цены!$M$2:$M$1000,MATCH(D16,02_Цены!$A$2:$A$1000,0))="","",INDEX(02_Цены!$M$2:$M$1000,MATCH(D16,02_Цены!$A$2:$A$1000,0))),"") -> NO_VERIFIED_NET | K16: =IF(AND(ISNUMBER(I16),J16="OBSERVED_NET_CONDITIONAL_SCOPE",OR(IFERROR(IF(INDEX(02_Цены!$E$2:$E$1000,MATCH(D16,02_Цены!$A$2:$A$1000,0))="","",INDEX(02_Цены!$E$2:$E$1000,MATCH(D16,02_Цены!$A$2:$A$1000,0))),"")="",E16=IFERROR(IF(INDEX(02_Цены!$E$2:$E$1000,MATCH(D16,02_Цены!$A$2:$A$1000,0))="","",INDEX(02_Цены!$E$2:$E$1000,MATCH(D16,02_Цены!$A$2:$A$1000,0))),""))),"PRICE_OBSERVED","BLOCK") -> BLOCK | L16: 2 physical owner batteries for2generators; capacity/voltage/CCA unknown; keep9total with6service+1main. No fictitious unit price.
A17: PK04-A-L04 | B17: PK04-A | C17: ME-28 | D17: EL-REM-A | F17: pcs | G17: =IFERROR(IF(INDEX(02_Цены!$D$2:$D$1000,MATCH(D17,02_Цены!$A$2:$A$1000,0))="","",INDEX(02_Цены!$D$2:$D$1000,MATCH(D17,02_Цены!$A$2:$A$1000,0))),"") -> ML-RBS7702 24V | H17: =IFERROR(IF(INDEX(02_Цены!$L$2:$L$1000,MATCH(D17,02_Цены!$A$2:$A$1000,0))="","",INDEX(02_Цены!$L$2:$L$1000,MATCH(D17,02_Цены!$A$2:$A$1000,0))),"") -> 239.45 | I17: =IF(AND(ISNUMBER(E17),E17>=0,ISNUMBER(H17)),ROUND(E17*H17,2),"") | J17: =IFERROR(IF(INDEX(02_Цены!$M$2:$M$1000,MATCH(D17,02_Цены!$A$2:$A$1000,0))="","",INDEX(02_Цены!$M$2:$M$1000,MATCH(D17,02_Цены!$A$2:$A$1000,0))),"") -> OBSERVED_NET_CONDITIONAL_SCOPE | K17: =IF(AND(ISNUMBER(I17),J17="OBSERVED_NET_CONDITIONAL_SCOPE",OR(IFERROR(IF(INDEX(02_Цены!$E$2:$E$1000,MATCH(D17,02_Цены!$A$2:$A$1000,0))="","",INDEX(02_Цены!$E$2:$E$1000,MATCH(D17,02_Цены!$A$2:$A$1000,0))),"")="",E17=IFERROR(IF(INDEX(02_Цены!$E$2:$E$1000,MATCH(D17,02_Цены!$A$2:$A$1000,0))="","",INDEX(02_Цены!$E$2:$E$1000,MATCH(D17,02_Цены!$A$2:$A$1000,0))),""))),"PRICE_OBSERVED","BLOCK") -> BLOCK | L17: Manual override;24V coil;500A continuous product rating. Quantity, control failover, crank duty and24V live switching not qualified; dimensions drawing pending.
A18: PK04-B-L01 | B18: PK04-B | C18: ME-08 | D18: EL-BAT-B | E18: 6 | F18: pcs | G18: =IFERROR(IF(INDEX(02_Цены!$D$2:$D$1000,MATCH(D18,02_Цены!$A$2:$A$1000,0))="","",INDEX(02_Цены!$D$2:$D$1000,MATCH(D18,02_Цены!$A$2:$A$1000,0))),"") -> ALS12115 12V115Ah | H18: =IFERROR(IF(INDEX(02_Цены!$L$2:$L$1000,MATCH(D18,02_Цены!$A$2:$A$1000,0))="","",INDEX(02_Цены!$L$2:$L$1000,MATCH(D18,02_Цены!$A$2:$A$1000,0))),"") -> 268.07 | I18: =IF(AND(ISNUMBER(E18),E18>=0,ISNUMBER(H18)),ROUND(E18*H18,2),"") -> 1608.42 | J18: =IFERROR(IF(INDEX(02_Цены!$M$2:$M$1000,MATCH(D18,02_Цены!$A$2:$A$1000,0))="","",INDEX(02_Цены!$M$2:$M$1000,MATCH(D18,02_Цены!$A$2:$A$1000,0))),"") -> OBSERVED_NET_CONDITIONAL_SCOPE | K18: =IF(AND(ISNUMBER(I18),J18="OBSERVED_NET_CONDITIONAL_SCOPE",OR(IFERROR(IF(INDEX(02_Цены!$E$2:$E$1000,MATCH(D18,02_Цены!$A$2:$A$1000,0))="","",INDEX(02_Цены!$E$2:$E$1000,MATCH(D18,02_Цены!$A$2:$A$1000,0))),"")="",E18=IFERROR(IF(INDEX(02_Цены!$E$2:$E$1000,MATCH(D18,02_Цены!$A$2:$A$1000,0))="","",INDEX(02_Цены!$E$2:$E$1000,MATCH(D18,02_Цены!$A$2:$A$1000,0))),""))),"PRICE_OBSERVED","BLOCK") -> PRICE_OBSERVED | L18: AGM dealer description; legacy manufacturer sheet includes GEL construction wording, chemistry/revision confirmation needed. Body height214mm total220mm; dealer header6.4kg rejected in favour33.7kg technical sheet.
A19: PK04-B-L02 | B19: PK04-B | C19: ME-07 | D19: EL-OPEN-MAIN | E19: 1 | F19: pcs | G19: =IFERROR(IF(INDEX(02_Цены!$D$2:$D$1000,MATCH(D19,02_Цены!$A$2:$A$1000,0))="","",INDEX(02_Цены!$D$2:$D$1000,MATCH(D19,02_Цены!$A$2:$A$1000,0))),"") -> UNSIZED | H19: =IFERROR(IF(INDEX(02_Цены!$L$2:$L$1000,MATCH(D19,02_Цены!$A$2:$A$1000,0))="","",INDEX(02_Цены!$L$2:$L$1000,MATCH(D19,02_Цены!$A$2:$A$1000,0))),"") | I19: =IF(AND(ISNUMBER(E19),E19>=0,ISNUMBER(H19)),ROUND(E19*H19,2),"") | J19: =IFERROR(IF(INDEX(02_Цены!$M$2:$M$1000,MATCH(D19,02_Цены!$A$2:$A$1000,0))="","",INDEX(02_Цены!$M$2:$M$1000,MATCH(D19,02_Цены!$A$2:$A$1000,0))),"") -> NO_VERIFIED_NET | K19: =IF(AND(ISNUMBER(I19),J19="OBSERVED_NET_CONDITIONAL_SCOPE",OR(IFERROR(IF(INDEX(02_Цены!$E$2:$E$1000,MATCH(D19,02_Цены!$A$2:$A$1000,0))="","",INDEX(02_Цены!$E$2:$E$1000,MATCH(D19,02_Цены!$A$2:$A$1000,0))),"")="",E19=IFERROR(IF(INDEX(02_Цены!$E$2:$E$1000,MATCH(D19,02_Цены!$A$2:$A$1000,0))="","",INDEX(02_Цены!$E$2:$E$1000,MATCH(D19,02_Цены!$A$2:$A$1000,0))),""))),"PRICE_OBSERVED","BLOCK") -> BLOCK | L19: 1 physical owner battery, capacity/voltage/chemistry unknown. Not automatically ER550 or service115Ah.
A20: PK04-B-L03 | B20: PK04-B | C20: ME-27 | D20: EL-OPEN-GEN | E20: 2 | F20: pcs | G20: =IFERROR(IF(INDEX(02_Цены!$D$2:$D$1000,MATCH(D20,02_Цены!$A$2:$A$1000,0))="","",INDEX(02_Цены!$D$2:$D$1000,MATCH(D20,02_Цены!$A$2:$A$1000,0))),"") -> UNSIZED | H20: =IFERROR(IF(INDEX(02_Цены!$L$2:$L$1000,MATCH(D20,02_Цены!$A$2:$A$1000,0))="","",INDEX(02_Цены!$L$2:$L$1000,MATCH(D20,02_Цены!$A$2:$A$1000,0))),"") | I20: =IF(AND(ISNUMBER(E20),E20>=0,ISNUMBER(H20)),ROUND(E20*H20,2),"") | J20: =IFERROR(IF(INDEX(02_Цены!$M$2:$M$1000,MATCH(D20,02_Цены!$A$2:$A$1000,0))="","",INDEX(02_Цены!$M$2:$M$1000,MATCH(D20,02_Цены!$A$2:$A$1000,0))),"") -> NO_VERIFIED_NET | K20: =IF(AND(ISNUMBER(I20),J20="OBSERVED_NET_CONDITIONAL_SCOPE",OR(IFERROR(IF(INDEX(02_Цены!$E$2:$E$1000,MATCH(D20,02_Цены!$A$2:$A$1000,0))="","",INDEX(02_Цены!$E$2:$E$1000,MATCH(D20,02_Цены!$A$2:$A$1000,0))),"")="",E20=IFERROR(IF(INDEX(02_Цены!$E$2:$E$1000,MATCH(D20,02_Цены!$A$2:$A$1000,0))="","",INDEX(02_Цены!$E$2:$E$1000,MATCH(D20,02_Цены!$A$2:$A$1000,0))),""))),"PRICE_OBSERVED","BLOCK") -> BLOCK | L20: 2 physical owner batteries for2generators; capacity/voltage/CCA unknown; keep9total with6service+1main. No fictitious unit price.
A21: PK04-B-L04 | B21: PK04-B | C21: ME-28 | D21: EL-REM-A | F21: pcs | G21: =IFERROR(IF(INDEX(02_Цены!$D$2:$D$1000,MATCH(D21,02_Цены!$A$2:$A$1000,0))="","",INDEX(02_Цены!$D$2:$D$1000,MATCH(D21,02_Цены!$A$2:$A$1000,0))),"") -> ML-RBS7702 24V | H21: =IFERROR(IF(INDEX(02_Цены!$L$2:$L$1000,MATCH(D21,02_Цены!$A$2:$A$1000,0))="","",INDEX(02_Цены!$L$2:$L$1000,MATCH(D21,02_Цены!$A$2:$A$1000,0))),"") -> 239.45 | I21: =IF(AND(ISNUMBER(E21),E21>=0,ISNUMBER(H21)),ROUND(E21*H21,2),"") | J21: =IFERROR(IF(INDEX(02_Цены!$M$2:$M$1000,MATCH(D21,02_Цены!$A$2:$A$1000,0))="","",INDEX(02_Цены!$M$2:$M$1000,MATCH(D21,02_Цены!$A$2:$A$1000,0))),"") -> OBSERVED_NET_CONDITIONAL_SCOPE | K21: =IF(AND(ISNUMBER(I21),J21="OBSERVED_NET_CONDITIONAL_SCOPE",OR(IFERROR(IF(INDEX(02_Цены!$E$2:$E$1000,MATCH(D21,02_Цены!$A$2:$A$1000,0))="","",INDEX(02_Цены!$E$2:$E$1000,MATCH(D21,02_Цены!$A$2:$A$1000,0))),"")="",E21=IFERROR(IF(INDEX(02_Цены!$E$2:$E$1000,MATCH(D21,02_Цены!$A$2:$A$1000,0))="","",INDEX(02_Цены!$E$2:$E$1000,MATCH(D21,02_Цены!$A$2:$A$1000,0))),""))),"PRICE_OBSERVED","BLOCK") -> BLOCK | L21: Manual override;24V coil;500A continuous product rating. Quantity, control failover, crank duty and24V live switching not qualified; dimensions drawing pending.
A22: PK04-C-L01 | B22: PK04-C | C22: ME-08 | D22: EL-BAT-C | E22: 6 | F22: pcs | G22: =IFERROR(IF(INDEX(02_Цены!$D$2:$D$1000,MATCH(D22,02_Цены!$A$2:$A$1000,0))="","",INDEX(02_Цены!$D$2:$D$1000,MATCH(D22,02_Цены!$A$2:$A$1000,0))),"") -> AGM Telecom115Ah M8 BAT412105164 | H22: =IFERROR(IF(INDEX(02_Цены!$L$2:$L$1000,MATCH(D22,02_Цены!$A$2:$A$1000,0))="","",INDEX(02_Цены!$L$2:$L$1000,MATCH(D22,02_Цены!$A$2:$A$1000,0))),"") -> 272.69 | I22: =IF(AND(ISNUMBER(E22),E22>=0,ISNUMBER(H22)),ROUND(E22*H22,2),"") -> 1636.14 | J22: =IFERROR(IF(INDEX(02_Цены!$M$2:$M$1000,MATCH(D22,02_Цены!$A$2:$A$1000,0))="","",INDEX(02_Цены!$M$2:$M$1000,MATCH(D22,02_Цены!$A$2:$A$1000,0))),"") -> OBSERVED_NET_CONDITIONAL_SCOPE | K22: =IF(AND(ISNUMBER(I22),J22="OBSERVED_NET_CONDITIONAL_SCOPE",OR(IFERROR(IF(INDEX(02_Цены!$E$2:$E$1000,MATCH(D22,02_Цены!$A$2:$A$1000,0))="","",INDEX(02_Цены!$E$2:$E$1000,MATCH(D22,02_Цены!$A$2:$A$1000,0))),"")="",E22=IFERROR(IF(INDEX(02_Цены!$E$2:$E$1000,MATCH(D22,02_Цены!$A$2:$A$1000,0))="","",INDEX(02_Цены!$E$2:$E$1000,MATCH(D22,02_Цены!$A$2:$A$1000,0))),""))),"PRICE_OBSERVED","BLOCK") -> PRICE_OBSERVED | L22: 12 V AGM front terminal;6 units only if owner confirms115Ah12V. No12V housebus inferred. Open page21% supersedes search19%.
A23: PK04-C-L02 | B23: PK04-C | C23: ME-07 | D23: EL-OPEN-MAIN | E23: 1 | F23: pcs | G23: =IFERROR(IF(INDEX(02_Цены!$D$2:$D$1000,MATCH(D23,02_Цены!$A$2:$A$1000,0))="","",INDEX(02_Цены!$D$2:$D$1000,MATCH(D23,02_Цены!$A$2:$A$1000,0))),"") -> UNSIZED | H23: =IFERROR(IF(INDEX(02_Цены!$L$2:$L$1000,MATCH(D23,02_Цены!$A$2:$A$1000,0))="","",INDEX(02_Цены!$L$2:$L$1000,MATCH(D23,02_Цены!$A$2:$A$1000,0))),"") | I23: =IF(AND(ISNUMBER(E23),E23>=0,ISNUMBER(H23)),ROUND(E23*H23,2),"") | J23: =IFERROR(IF(INDEX(02_Цены!$M$2:$M$1000,MATCH(D23,02_Цены!$A$2:$A$1000,0))="","",INDEX(02_Цены!$M$2:$M$1000,MATCH(D23,02_Цены!$A$2:$A$1000,0))),"") -> NO_VERIFIED_NET | K23: =IF(AND(ISNUMBER(I23),J23="OBSERVED_NET_CONDITIONAL_SCOPE",OR(IFERROR(IF(INDEX(02_Цены!$E$2:$E$1000,MATCH(D23,02_Цены!$A$2:$A$1000,0))="","",INDEX(02_Цены!$E$2:$E$1000,MATCH(D23,02_Цены!$A$2:$A$1000,0))),"")="",E23=IFERROR(IF(INDEX(02_Цены!$E$2:$E$1000,MATCH(D23,02_Цены!$A$2:$A$1000,0))="","",INDEX(02_Цены!$E$2:$E$1000,MATCH(D23,02_Цены!$A$2:$A$1000,0))),""))),"PRICE_OBSERVED","BLOCK") -> BLOCK | L23: 1 physical owner battery, capacity/voltage/chemistry unknown. Not automatically ER550 or service115Ah.
A24: PK04-C-L03 | B24: PK04-C | C24: ME-27 | D24: EL-OPEN-GEN | E24: 2 | F24: pcs | G24: =IFERROR(IF(INDEX(02_Цены!$D$2:$D$1000,MATCH(D24,02_Цены!$A$2:$A$1000,0))="","",INDEX(02_Цены!$D$2:$D$1000,MATCH(D24,02_Цены!$A$2:$A$1000,0))),"") -> UNSIZED | H24: =IFERROR(IF(INDEX(02_Цены!$L$2:$L$1000,MATCH(D24,02_Цены!$A$2:$A$1000,0))="","",INDEX(02_Цены!$L$2:$L$1000,MATCH(D24,02_Цены!$A$2:$A$1000,0))),"") | I24: =IF(AND(ISNUMBER(E24),E24>=0,ISNUMBER(H24)),ROUND(E24*H24,2),"") | J24: =IFERROR(IF(INDEX(02_Цены!$M$2:$M$1000,MATCH(D24,02_Цены!$A$2:$A$1000,0))="","",INDEX(02_Цены!$M$2:$M$1000,MATCH(D24,02_Цены!$A$2:$A$1000,0))),"") -> NO_VERIFIED_NET | K24: =IF(AND(ISNUMBER(I24),J24="OBSERVED_NET_CONDITIONAL_SCOPE",OR(IFERROR(IF(INDEX(02_Цены!$E$2:$E$1000,MATCH(D24,02_Цены!$A$2:$A$1000,0))="","",INDEX(02_Цены!$E$2:$E$1000,MATCH(D24,02_Цены!$A$2:$A$1000,0))),"")="",E24=IFERROR(IF(INDEX(02_Цены!$E$2:$E$1000,MATCH(D24,02_Цены!$A$2:$A$1000,0))="","",INDEX(02_Цены!$E$2:$E$1000,MATCH(D24,02_Цены!$A$2:$A$1000,0))),""))),"PRICE_OBSERVED","BLOCK") -> BLOCK | L24: 2 physical owner batteries for2generators; capacity/voltage/CCA unknown; keep9total with6service+1main. No fictitious unit price.
A25: PK04-C-L04 | B25: PK04-C | C25: ME-28 | D25: EL-REM-A | F25: pcs | G25: =IFERROR(IF(INDEX(02_Цены!$D$2:$D$1000,MATCH(D25,02_Цены!$A$2:$A$1000,0))="","",INDEX(02_Цены!$D$2:$D$1000,MATCH(D25,02_Цены!$A$2:$A$1000,0))),"") -> ML-RBS7702 24V | H25: =IFERROR(IF(INDEX(02_Цены!$L$2:$L$1000,MATCH(D25,02_Цены!$A$2:$A$1000,0))="","",INDEX(02_Цены!$L$2:$L$1000,MATCH(D25,02_Цены!$A$2:$A$1000,0))),"") -> 239.45 | I25: =IF(AND(ISNUMBER(E25),E25>=0,ISNUMBER(H25)),ROUND(E25*H25,2),"") | J25: =IFERROR(IF(INDEX(02_Цены!$M$2:$M$1000,MATCH(D25,02_Цены!$A$2:$A$1000,0))="","",INDEX(02_Цены!$M$2:$M$1000,MATCH(D25,02_Цены!$A$2:$A$1000,0))),"") -> OBSERVED_NET_CONDITIONAL_SCOPE | K25: =IF(AND(ISNUMBER(I25),J25="OBSERVED_NET_CONDITIONAL_SCOPE",OR(IFERROR(IF(INDEX(02_Цены!$E$2:$E$1000,MATCH(D25,02_Цены!$A$2:$A$1000,0))="","",INDEX(02_Цены!$E$2:$E$1000,MATCH(D25,02_Цены!$A$2:$A$1000,0))),"")="",E25=IFERROR(IF(INDEX(02_Цены!$E$2:$E$1000,MATCH(D25,02_Цены!$A$2:$A$1000,0))="","",INDEX(02_Цены!$E$2:$E$1000,MATCH(D25,02_Цены!$A$2:$A$1000,0))),""))),"PRICE_OBSERVED","BLOCK") -> BLOCK | L25: Manual override;24V coil;500A continuous product rating. Quantity, control failover, crank duty and24V live switching not qualified; dimensions drawing pending.
A26: PK05-A-L01 | B26: PK05-A | C26: ME-11 | D26: WC-DC-01 | E26: 1 | F26: шт | G26: =IFERROR(IF(INDEX(02_Цены!$D$2:$D$1000,MATCH(D26,02_Цены!$A$2:$A$1000,0))="","",INDEX(02_Цены!$D$2:$D$1000,MATCH(D26,02_Цены!$A$2:$A$1000,0))),"") -> OSC-16.062.24 / OEM identity reconcile | H26: =IFERROR(IF(INDEX(02_Цены!$L$2:$L$1000,MATCH(D26,02_Цены!$A$2:$A$1000,0))="","",INDEX(02_Цены!$L$2:$L$1000,MATCH(D26,02_Цены!$A$2:$A$1000,0))),"") -> 1024.92 | I26: =IF(AND(ISNUMBER(E26),E26>=0,ISNUMBER(H26)),ROUND(E26*H26,2),"") -> 1024.92 | J26: =IFERROR(IF(INDEX(02_Цены!$M$2:$M$1000,MATCH(D26,02_Цены!$A$2:$A$1000,0))="","",INDEX(02_Цены!$M$2:$M$1000,MATCH(D26,02_Цены!$A$2:$A$1000,0))),"") -> OBSERVED_NET_CONDITIONAL_SCOPE | K26: =IF(AND(ISNUMBER(I26),J26="OBSERVED_NET_CONDITIONAL_SCOPE",OR(IFERROR(IF(INDEX(02_Цены!$E$2:$E$1000,MATCH(D26,02_Цены!$A$2:$A$1000,0))="","",INDEX(02_Цены!$E$2:$E$1000,MATCH(D26,02_Цены!$A$2:$A$1000,0))),"")="",E26=IFERROR(IF(INDEX(02_Цены!$E$2:$E$1000,MATCH(D26,02_Цены!$A$2:$A$1000,0))="","",INDEX(02_Цены!$E$2:$E$1000,MATCH(D26,02_Цены!$A$2:$A$1000,0))),""))),"PRICE_OBSERVED","BLOCK") -> PRICE_OBSERVED | L26: 24V20L accumulator; dealer50L/min max; source model mapping not proven. Common proposed test15L/min at2bar NOT verified. Do not add included tank again.
A27: PK05-A-L02 | B27: PK05-A | C27: ME-12 | D27: WC-AC-01 | E27: 1 | F27: шт | G27: =IFERROR(IF(INDEX(02_Цены!$D$2:$D$1000,MATCH(D27,02_Цены!$A$2:$A$1000,0))="","",INDEX(02_Цены!$D$2:$D$1000,MATCH(D27,02_Цены!$A$2:$A$1000,0))),"") -> J-INOX/20X 230M | H27: =IFERROR(IF(INDEX(02_Цены!$L$2:$L$1000,MATCH(D27,02_Цены!$A$2:$A$1000,0))="","",INDEX(02_Цены!$L$2:$L$1000,MATCH(D27,02_Цены!$A$2:$A$1000,0))),"") | I27: =IF(AND(ISNUMBER(E27),E27>=0,ISNUMBER(H27)),ROUND(E27*H27,2),"") | J27: =IFERROR(IF(INDEX(02_Цены!$M$2:$M$1000,MATCH(D27,02_Цены!$A$2:$A$1000,0))="","",INDEX(02_Цены!$M$2:$M$1000,MATCH(D27,02_Цены!$A$2:$A$1000,0))),"") -> NO_VERIFIED_NET | K27: =IF(AND(ISNUMBER(I27),J27="OBSERVED_NET_CONDITIONAL_SCOPE",OR(IFERROR(IF(INDEX(02_Цены!$E$2:$E$1000,MATCH(D27,02_Цены!$A$2:$A$1000,0))="","",INDEX(02_Цены!$E$2:$E$1000,MATCH(D27,02_Цены!$A$2:$A$1000,0))),"")="",E27=IFERROR(IF(INDEX(02_Цены!$E$2:$E$1000,MATCH(D27,02_Цены!$A$2:$A$1000,0))="","",INDEX(02_Цены!$E$2:$E$1000,MATCH(D27,02_Цены!$A$2:$A$1000,0))),""))),"PRICE_OBSERVED","BLOCK") -> BLOCK | L27: Official230V singlephase variant exists. Proposedcommon15L/min at2bar not accepted from maxflow.20L stainless tank included. No price borrowed from24V sibling.
A28: PK05-B-L01 | B28: PK05-B | C28: ME-11 | D28: WC-DC-02 | E28: 1 | F28: шт | G28: =IFERROR(IF(INDEX(02_Цены!$D$2:$D$1000,MATCH(D28,02_Цены!$A$2:$A$1000,0))="","",INDEX(02_Цены!$D$2:$D$1000,MATCH(D28,02_Цены!$A$2:$A$1000,0))),"") -> EcoInox1 GE011 24V20L | H28: =IFERROR(IF(INDEX(02_Цены!$L$2:$L$1000,MATCH(D28,02_Цены!$A$2:$A$1000,0))="","",INDEX(02_Цены!$L$2:$L$1000,MATCH(D28,02_Цены!$A$2:$A$1000,0))),"") -> 1093.25 | I28: =IF(AND(ISNUMBER(E28),E28>=0,ISNUMBER(H28)),ROUND(E28*H28,2),"") -> 1093.25 | J28: =IFERROR(IF(INDEX(02_Цены!$M$2:$M$1000,MATCH(D28,02_Цены!$A$2:$A$1000,0))="","",INDEX(02_Цены!$M$2:$M$1000,MATCH(D28,02_Цены!$A$2:$A$1000,0))),"") -> OBSERVED_NET_CONDITIONAL_SCOPE | K28: =IF(AND(ISNUMBER(I28),J28="OBSERVED_NET_CONDITIONAL_SCOPE",OR(IFERROR(IF(INDEX(02_Цены!$E$2:$E$1000,MATCH(D28,02_Цены!$A$2:$A$1000,0))="","",INDEX(02_Цены!$E$2:$E$1000,MATCH(D28,02_Цены!$A$2:$A$1000,0))),"")="",E28=IFERROR(IF(INDEX(02_Цены!$E$2:$E$1000,MATCH(D28,02_Цены!$A$2:$A$1000,0))="","",INDEX(02_Цены!$E$2:$E$1000,MATCH(D28,02_Цены!$A$2:$A$1000,0))),""))),"PRICE_OBSERVED","BLOCK") -> PRICE_OBSERVED | L28: 45L/min max; common proposed15L/min at2bar needs curve. Includes20L tank/gauge/pressure switch; current OEM revision confirmation.
A29: PK05-B-L02 | B29: PK05-B | C29: ME-12 | D29: WC-AC-02 | E29: 1 | F29: шт | G29: =IFERROR(IF(INDEX(02_Цены!$D$2:$D$1000,MATCH(D29,02_Цены!$A$2:$A$1000,0))="","",INDEX(02_Цены!$D$2:$D$1000,MATCH(D29,02_Цены!$A$2:$A$1000,0))),"") -> EcoInox2 GE017 230V20L | H29: =IFERROR(IF(INDEX(02_Цены!$L$2:$L$1000,MATCH(D29,02_Цены!$A$2:$A$1000,0))="","",INDEX(02_Цены!$L$2:$L$1000,MATCH(D29,02_Цены!$A$2:$A$1000,0))),"") -> 1052.5 | I29: =IF(AND(ISNUMBER(E29),E29>=0,ISNUMBER(H29)),ROUND(E29*H29,2),"") -> 1052.5 | J29: =IFERROR(IF(INDEX(02_Цены!$M$2:$M$1000,MATCH(D29,02_Цены!$A$2:$A$1000,0))="","",INDEX(02_Цены!$M$2:$M$1000,MATCH(D29,02_Цены!$A$2:$A$1000,0))),"") -> OBSERVED_NET_CONDITIONAL_SCOPE | K29: =IF(AND(ISNUMBER(I29),J29="OBSERVED_NET_CONDITIONAL_SCOPE",OR(IFERROR(IF(INDEX(02_Цены!$E$2:$E$1000,MATCH(D29,02_Цены!$A$2:$A$1000,0))="","",INDEX(02_Цены!$E$2:$E$1000,MATCH(D29,02_Цены!$A$2:$A$1000,0))),"")="",E29=IFERROR(IF(INDEX(02_Цены!$E$2:$E$1000,MATCH(D29,02_Цены!$A$2:$A$1000,0))="","",INDEX(02_Цены!$E$2:$E$1000,MATCH(D29,02_Цены!$A$2:$A$1000,0))),""))),"PRICE_OBSERVED","BLOCK") -> PRICE_OBSERVED | L29: Open page1052.50HT supersedes search992.50. Dealer max55L/min conflicts Kent45: curves required.0.45kW/20L; common15L/min at2bar not verified.
A30: PK05-C-L01 | B30: PK05-C | C30: ME-11 | D30: WC-DC-03 | E30: 1 | F30: шт | G30: =IFERROR(IF(INDEX(02_Цены!$D$2:$D$1000,MATCH(D30,02_Цены!$A$2:$A$1000,0))="","",INDEX(02_Цены!$D$2:$D$1000,MATCH(D30,02_Цены!$A$2:$A$1000,0))),"") -> GH24-0.37-24L-OT RB18-ED | H30: =IFERROR(IF(INDEX(02_Цены!$L$2:$L$1000,MATCH(D30,02_Цены!$A$2:$A$1000,0))="","",INDEX(02_Цены!$L$2:$L$1000,MATCH(D30,02_Цены!$A$2:$A$1000,0))),"") | I30: =IF(AND(ISNUMBER(E30),E30>=0,ISNUMBER(H30)),ROUND(E30*H30,2),"") | J30: =IFERROR(IF(INDEX(02_Цены!$M$2:$M$1000,MATCH(D30,02_Цены!$A$2:$A$1000,0))="","",INDEX(02_Цены!$M$2:$M$1000,MATCH(D30,02_Цены!$A$2:$A$1000,0))),"") -> NO_VERIFIED_NET | K30: =IF(AND(ISNUMBER(I30),J30="OBSERVED_NET_CONDITIONAL_SCOPE",OR(IFERROR(IF(INDEX(02_Цены!$E$2:$E$1000,MATCH(D30,02_Цены!$A$2:$A$1000,0))="","",INDEX(02_Цены!$E$2:$E$1000,MATCH(D30,02_Цены!$A$2:$A$1000,0))),"")="",E30=IFERROR(IF(INDEX(02_Цены!$E$2:$E$1000,MATCH(D30,02_Цены!$A$2:$A$1000,0))="","",INDEX(02_Цены!$E$2:$E$1000,MATCH(D30,02_Цены!$A$2:$A$1000,0))),""))),"PRICE_OBSERVED","BLOCK") -> BLOCK | L30: Official24V/0.37kW; 1m3/h at30m published point; pressure switch1.5/2.5bar.24L tank differs20L competitors: standardise accumulator scope before comparison. Dimensions drawing orientation not mapped into LWH.
A31: PK05-C-L02 | B31: PK05-C | C31: ME-12 | D31: WC-AC-03 | E31: 1 | F31: шт | G31: =IFERROR(IF(INDEX(02_Цены!$D$2:$D$1000,MATCH(D31,02_Цены!$A$2:$A$1000,0))="","",INDEX(02_Цены!$D$2:$D$1000,MATCH(D31,02_Цены!$A$2:$A$1000,0))),"") -> GH230mono-0.37-24L-JET M-ED | H31: =IFERROR(IF(INDEX(02_Цены!$L$2:$L$1000,MATCH(D31,02_Цены!$A$2:$A$1000,0))="","",INDEX(02_Цены!$L$2:$L$1000,MATCH(D31,02_Цены!$A$2:$A$1000,0))),"") | I31: =IF(AND(ISNUMBER(E31),E31>=0,ISNUMBER(H31)),ROUND(E31*H31,2),"") | J31: =IFERROR(IF(INDEX(02_Цены!$M$2:$M$1000,MATCH(D31,02_Цены!$A$2:$A$1000,0))="","",INDEX(02_Цены!$M$2:$M$1000,MATCH(D31,02_Цены!$A$2:$A$1000,0))),"") -> NO_VERIFIED_NET | K31: =IF(AND(ISNUMBER(I31),J31="OBSERVED_NET_CONDITIONAL_SCOPE",OR(IFERROR(IF(INDEX(02_Цены!$E$2:$E$1000,MATCH(D31,02_Цены!$A$2:$A$1000,0))="","",INDEX(02_Цены!$E$2:$E$1000,MATCH(D31,02_Цены!$A$2:$A$1000,0))),"")="",E31=IFERROR(IF(INDEX(02_Цены!$E$2:$E$1000,MATCH(D31,02_Цены!$A$2:$A$1000,0))="","",INDEX(02_Цены!$E$2:$E$1000,MATCH(D31,02_Цены!$A$2:$A$1000,0))),""))),"PRICE_OBSERVED","BLOCK") -> BLOCK | L31: Explicit230V singlephase; official1m3/h at40m, pressure switch1.5/2.5bar.24L accumulator vs20L needs standardisation; no equivalence claim.
A32: PK06-A-L01 | B32: PK06-A | C32: ME-13 | D32: WC-RO-01 | E32: 1 | F32: шт | G32: =IFERROR(IF(INDEX(02_Цены!$D$2:$D$1000,MATCH(D32,02_Цены!$A$2:$A$1000,0))="","",INDEX(02_Цены!$D$2:$D$1000,MATCH(D32,02_Цены!$A$2:$A$1000,0))),"") -> AC150 230V single phase | H32: =IFERROR(IF(INDEX(02_Цены!$L$2:$L$1000,MATCH(D32,02_Цены!$A$2:$A$1000,0))="","",INDEX(02_Цены!$L$2:$L$1000,MATCH(D32,02_Цены!$A$2:$A$1000,0))),"") -> 6335.29 | I32: =IF(AND(ISNUMBER(E32),E32>=0,ISNUMBER(H32)),ROUND(E32*H32,2),"") -> 6335.29 | J32: =IFERROR(IF(INDEX(02_Цены!$M$2:$M$1000,MATCH(D32,02_Цены!$A$2:$A$1000,0))="","",INDEX(02_Цены!$M$2:$M$1000,MATCH(D32,02_Цены!$A$2:$A$1000,0))),"") -> OBSERVED_NET_CONDITIONAL_SCOPE | K32: =IF(AND(ISNUMBER(I32),J32="OBSERVED_NET_CONDITIONAL_SCOPE",OR(IFERROR(IF(INDEX(02_Цены!$E$2:$E$1000,MATCH(D32,02_Цены!$A$2:$A$1000,0))="","",INDEX(02_Цены!$E$2:$E$1000,MATCH(D32,02_Цены!$A$2:$A$1000,0))),"")="",E32=IFERROR(IF(INDEX(02_Цены!$E$2:$E$1000,MATCH(D32,02_Цены!$A$2:$A$1000,0))="","",INDEX(02_Цены!$E$2:$E$1000,MATCH(D32,02_Цены!$A$2:$A$1000,0))),""))),"PRICE_OBSERVED","BLOCK") -> PRICE_OBSERVED | L32: 150 L/h nominal ±10% at25C/35000ppm; modular conventional HP pump; base price only: automatic flush/salinity/reject parity must be itemised; generator minimum4kW manufacturer target, not electrical demand or selection
A33: PK06-B-L01 | B33: PK06-B | C33: ME-13 | D33: WC-RO-02 | E33: 1 | F33: шт | G33: =IFERROR(IF(INDEX(02_Цены!$D$2:$D$1000,MATCH(D33,02_Цены!$A$2:$A$1000,0))="","",INDEX(02_Цены!$D$2:$D$1000,MATCH(D33,02_Цены!$A$2:$A$1000,0))),"") -> ZEN150 24V/230V Touch plus salinity/reject | H33: =IFERROR(IF(INDEX(02_Цены!$L$2:$L$1000,MATCH(D33,02_Цены!$A$2:$A$1000,0))="","",INDEX(02_Цены!$L$2:$L$1000,MATCH(D33,02_Цены!$A$2:$A$1000,0))),"") -> 10683.5 | I33: =IF(AND(ISNUMBER(E33),E33>=0,ISNUMBER(H33)),ROUND(E33*H33,2),"") -> 10683.5 | J33: =IFERROR(IF(INDEX(02_Цены!$M$2:$M$1000,MATCH(D33,02_Цены!$A$2:$A$1000,0))="","",INDEX(02_Цены!$M$2:$M$1000,MATCH(D33,02_Цены!$A$2:$A$1000,0))),"") -> FROM_INCOMPLETE_CONFIGURATION | K33: =IF(AND(ISNUMBER(I33),J33="OBSERVED_NET_CONDITIONAL_SCOPE",OR(IFERROR(IF(INDEX(02_Цены!$E$2:$E$1000,MATCH(D33,02_Цены!$A$2:$A$1000,0))="","",INDEX(02_Цены!$E$2:$E$1000,MATCH(D33,02_Цены!$A$2:$A$1000,0))),"")="",E33=IFERROR(IF(INDEX(02_Цены!$E$2:$E$1000,MATCH(D33,02_Цены!$A$2:$A$1000,0))="","",INDEX(02_Цены!$E$2:$E$1000,MATCH(D33,02_Цены!$A$2:$A$1000,0))),""))),"PRICE_OBSERVED","BLOCK") -> BLOCK | L33: Observed FROM base price; net is FROM benchmark only, NOT complete Touch/salinity/reject price. Nominal150L/h. Manufacturer230V±15% includes220V. Basic has no salinity; Touch optional; 24V variant permitted. Modular unit dimensions not total installed envelope.
A34: PK06-C-L01 | B34: PK06-C | C34: ME-13 | D34: WC-RO-03 | E34: 1 | F34: шт | G34: =IFERROR(IF(INDEX(02_Цены!$D$2:$D$1000,MATCH(D34,02_Цены!$A$2:$A$1000,0))="","",INDEX(02_Цены!$D$2:$D$1000,MATCH(D34,02_Цены!$A$2:$A$1000,0))),"") -> NEW12 150C 24V | H34: =IFERROR(IF(INDEX(02_Цены!$L$2:$L$1000,MATCH(D34,02_Цены!$A$2:$A$1000,0))="","",INDEX(02_Цены!$L$2:$L$1000,MATCH(D34,02_Цены!$A$2:$A$1000,0))),"") | I34: =IF(AND(ISNUMBER(E34),E34>=0,ISNUMBER(H34)),ROUND(E34*H34,2),"") | J34: =IFERROR(IF(INDEX(02_Цены!$M$2:$M$1000,MATCH(D34,02_Цены!$A$2:$A$1000,0))="","",INDEX(02_Цены!$M$2:$M$1000,MATCH(D34,02_Цены!$A$2:$A$1000,0))),"") -> NO_VERIFIED_NET | K34: =IF(AND(ISNUMBER(I34),J34="OBSERVED_NET_CONDITIONAL_SCOPE",OR(IFERROR(IF(INDEX(02_Цены!$E$2:$E$1000,MATCH(D34,02_Цены!$A$2:$A$1000,0))="","",INDEX(02_Цены!$E$2:$E$1000,MATCH(D34,02_Цены!$A$2:$A$1000,0))),"")="",E34=IFERROR(IF(INDEX(02_Цены!$E$2:$E$1000,MATCH(D34,02_Цены!$A$2:$A$1000,0))="","",INDEX(02_Цены!$E$2:$E$1000,MATCH(D34,02_Цены!$A$2:$A$1000,0))),""))),"PRICE_OBSERVED","BLOCK") -> BLOCK | L34: Official150L/h/600W; flush/salinometer/unsafe-water discard included. Official63kg conflicts dealer65kg; dimensions dealer796x317x408 not official therefore blank. Dealer install/service kits included vs manufacturer optional: reconcile
A35: PK07-A-L01 | B35: PK07-A | C35: ME-14 | D35: WC-HW-01 | F35: шт | G35: =IFERROR(IF(INDEX(02_Цены!$D$2:$D$1000,MATCH(D35,02_Цены!$A$2:$A$1000,0))="","",INDEX(02_Цены!$D$2:$D$1000,MATCH(D35,02_Цены!$A$2:$A$1000,0))),"") -> B3 40L1200W FLB34012S000A00 | H35: =IFERROR(IF(INDEX(02_Цены!$L$2:$L$1000,MATCH(D35,02_Цены!$A$2:$A$1000,0))="","",INDEX(02_Цены!$L$2:$L$1000,MATCH(D35,02_Цены!$A$2:$A$1000,0))),"") -> 614.17 | I35: =IF(AND(ISNUMBER(E35),E35>=0,ISNUMBER(H35)),ROUND(E35*H35,2),"") | J35: =IFERROR(IF(INDEX(02_Цены!$M$2:$M$1000,MATCH(D35,02_Цены!$A$2:$A$1000,0))="","",INDEX(02_Цены!$M$2:$M$1000,MATCH(D35,02_Цены!$A$2:$A$1000,0))),"") -> OBSERVED_NET_CONDITIONAL_SCOPE | K35: =IF(AND(ISNUMBER(I35),J35="OBSERVED_NET_CONDITIONAL_SCOPE",OR(IFERROR(IF(INDEX(02_Цены!$E$2:$E$1000,MATCH(D35,02_Цены!$A$2:$A$1000,0))="","",INDEX(02_Цены!$E$2:$E$1000,MATCH(D35,02_Цены!$A$2:$A$1000,0))),"")="",E35=IFERROR(IF(INDEX(02_Цены!$E$2:$E$1000,MATCH(D35,02_Цены!$A$2:$A$1000,0))="","",INDEX(02_Цены!$E$2:$E$1000,MATCH(D35,02_Цены!$A$2:$A$1000,0))),""))),"PRICE_OBSERVED","BLOCK") -> BLOCK | L35: 40L1200W220V plus engine heat exchanger common illustrative class; not owner size. Supplier dimensions/mass in research only pending official drawing. Thermostatic mixing equalise separately.
A36: PK07-B-L01 | B36: PK07-B | C36: ME-14 | D36: WC-HW-02 | F36: шт | G36: =IFERROR(IF(INDEX(02_Цены!$D$2:$D$1000,MATCH(D36,02_Цены!$A$2:$A$1000,0))="","",INDEX(02_Цены!$D$2:$D$1000,MATCH(D36,02_Цены!$A$2:$A$1000,0))),"") -> BX 40L1200W FLBX4012S000A00 | H36: =IFERROR(IF(INDEX(02_Цены!$L$2:$L$1000,MATCH(D36,02_Цены!$A$2:$A$1000,0))="","",INDEX(02_Цены!$L$2:$L$1000,MATCH(D36,02_Цены!$A$2:$A$1000,0))),"") -> 690.83 | I36: =IF(AND(ISNUMBER(E36),E36>=0,ISNUMBER(H36)),ROUND(E36*H36,2),"") | J36: =IFERROR(IF(INDEX(02_Цены!$M$2:$M$1000,MATCH(D36,02_Цены!$A$2:$A$1000,0))="","",INDEX(02_Цены!$M$2:$M$1000,MATCH(D36,02_Цены!$A$2:$A$1000,0))),"") -> OBSERVED_NET_CONDITIONAL_SCOPE | K36: =IF(AND(ISNUMBER(I36),J36="OBSERVED_NET_CONDITIONAL_SCOPE",OR(IFERROR(IF(INDEX(02_Цены!$E$2:$E$1000,MATCH(D36,02_Цены!$A$2:$A$1000,0))="","",INDEX(02_Цены!$E$2:$E$1000,MATCH(D36,02_Цены!$A$2:$A$1000,0))),"")="",E36=IFERROR(IF(INDEX(02_Цены!$E$2:$E$1000,MATCH(D36,02_Цены!$A$2:$A$1000,0))="","",INDEX(02_Цены!$E$2:$E$1000,MATCH(D36,02_Цены!$A$2:$A$1000,0))),""))),"PRICE_OBSERVED","BLOCK") -> BLOCK | L36: 40L1200W220V plus engine heat exchanger common illustrative class; not owner size. Supplier dimensions/mass in research only pending official drawing. Thermostatic mixing equalise separately.
A37: PK07-C-L01 | B37: PK07-C | C37: ME-14 | D37: WC-HW-03 | F37: шт | G37: =IFERROR(IF(INDEX(02_Цены!$D$2:$D$1000,MATCH(D37,02_Цены!$A$2:$A$1000,0))="","",INDEX(02_Цены!$D$2:$D$1000,MATCH(D37,02_Цены!$A$2:$A$1000,0))),"") -> BXS 40L1200W FLBXS4012S00A00 | H37: =IFERROR(IF(INDEX(02_Цены!$L$2:$L$1000,MATCH(D37,02_Цены!$A$2:$A$1000,0))="","",INDEX(02_Цены!$L$2:$L$1000,MATCH(D37,02_Цены!$A$2:$A$1000,0))),"") -> 757.5 | I37: =IF(AND(ISNUMBER(E37),E37>=0,ISNUMBER(H37)),ROUND(E37*H37,2),"") | J37: =IFERROR(IF(INDEX(02_Цены!$M$2:$M$1000,MATCH(D37,02_Цены!$A$2:$A$1000,0))="","",INDEX(02_Цены!$M$2:$M$1000,MATCH(D37,02_Цены!$A$2:$A$1000,0))),"") -> OBSERVED_NET_CONDITIONAL_SCOPE | K37: =IF(AND(ISNUMBER(I37),J37="OBSERVED_NET_CONDITIONAL_SCOPE",OR(IFERROR(IF(INDEX(02_Цены!$E$2:$E$1000,MATCH(D37,02_Цены!$A$2:$A$1000,0))="","",INDEX(02_Цены!$E$2:$E$1000,MATCH(D37,02_Цены!$A$2:$A$1000,0))),"")="",E37=IFERROR(IF(INDEX(02_Цены!$E$2:$E$1000,MATCH(D37,02_Цены!$A$2:$A$1000,0))="","",INDEX(02_Цены!$E$2:$E$1000,MATCH(D37,02_Цены!$A$2:$A$1000,0))),""))),"PRICE_OBSERVED","BLOCK") -> BLOCK | L37: 40L1200W220V plus engine heat exchanger common illustrative class; not owner size. Supplier dimensions/mass in research only pending official drawing. Thermostatic mixing equalise separately.
A38: PK08-A-L01 | B38: PK08-A | C38: ME-15 | D38: WC-CH-01 | E38: 2 | F38: шт | G38: =IFERROR(IF(INDEX(02_Цены!$D$2:$D$1000,MATCH(D38,02_Цены!$A$2:$A$1000,0))="","",INDEX(02_Цены!$D$2:$D$1000,MATCH(D38,02_Цены!$A$2:$A$1000,0))),"") -> UC16H | H38: =IFERROR(IF(INDEX(02_Цены!$L$2:$L$1000,MATCH(D38,02_Цены!$A$2:$A$1000,0))="","",INDEX(02_Цены!$L$2:$L$1000,MATCH(D38,02_Цены!$A$2:$A$1000,0))),"") -> 3621 | I38: =IF(AND(ISNUMBER(E38),E38>=0,ISNUMBER(H38)),ROUND(E38*H38,2),"") -> 7242 | J38: =IFERROR(IF(INDEX(02_Цены!$M$2:$M$1000,MATCH(D38,02_Цены!$A$2:$A$1000,0))="","",INDEX(02_Цены!$M$2:$M$1000,MATCH(D38,02_Цены!$A$2:$A$1000,0))),"") -> OBSERVED_NET_CONDITIONAL_SCOPE | K38: =IF(AND(ISNUMBER(I38),J38="OBSERVED_NET_CONDITIONAL_SCOPE",OR(IFERROR(IF(INDEX(02_Цены!$E$2:$E$1000,MATCH(D38,02_Цены!$A$2:$A$1000,0))="","",INDEX(02_Цены!$E$2:$E$1000,MATCH(D38,02_Цены!$A$2:$A$1000,0))),"")="",E38=IFERROR(IF(INDEX(02_Цены!$E$2:$E$1000,MATCH(D38,02_Цены!$A$2:$A$1000,0))="","",INDEX(02_Цены!$E$2:$E$1000,MATCH(D38,02_Цены!$A$2:$A$1000,0))),""))),"PRICE_OBSERVED","BLOCK") -> PRICE_OBSERVED | L38: 16000BTU/h each; illustrative class NOT yacht heatload. Officialcatalog220/1/50; dealer230V. Dimensions exclude controlbox. OEM catalogue says box/display included BUT priced Esco SKU requires airhandler/controlpanel separately: inclusion CONFLICT, RFQ required; do not assume included display.1.5kWnominput at catalogue conditions; independent2module integration open.
A39: PK08-A-L02 | B39: PK08-A | C39: ME-16 | D39: WC-AUX-01 | F39: шт | G39: =IFERROR(IF(INDEX(02_Цены!$D$2:$D$1000,MATCH(D39,02_Цены!$A$2:$A$1000,0))="","",INDEX(02_Цены!$D$2:$D$1000,MATCH(D39,02_Цены!$A$2:$A$1000,0))),"") -> NH150PS SWM0150230 | H39: =IFERROR(IF(INDEX(02_Цены!$L$2:$L$1000,MATCH(D39,02_Цены!$A$2:$A$1000,0))="","",INDEX(02_Цены!$L$2:$L$1000,MATCH(D39,02_Цены!$A$2:$A$1000,0))),"") -> 663.25 | I39: =IF(AND(ISNUMBER(E39),E39>=0,ISNUMBER(H39)),ROUND(E39*H39,2),"") | J39: =IFERROR(IF(INDEX(02_Цены!$M$2:$M$1000,MATCH(D39,02_Цены!$A$2:$A$1000,0))="","",INDEX(02_Цены!$M$2:$M$1000,MATCH(D39,02_Цены!$A$2:$A$1000,0))),"") -> OBSERVED_NET_CONDITIONAL_SCOPE | K39: =IF(AND(ISNUMBER(I39),J39="OBSERVED_NET_CONDITIONAL_SCOPE",OR(IFERROR(IF(INDEX(02_Цены!$E$2:$E$1000,MATCH(D39,02_Цены!$A$2:$A$1000,0))="","",INDEX(02_Цены!$E$2:$E$1000,MATCH(D39,02_Цены!$A$2:$A$1000,0))),"")="",E39=IFERROR(IF(INDEX(02_Цены!$E$2:$E$1000,MATCH(D39,02_Цены!$A$2:$A$1000,0))="","",INDEX(02_Цены!$E$2:$E$1000,MATCH(D39,02_Цены!$A$2:$A$1000,0))),""))),"PRICE_OBSERVED","BLOCK") -> BLOCK | L39: 230V50/60Hz magneticdrive; count and pump duty notfixed. No proof this model meets both seawater and chilledwater circuits; official detailed curve required.
A40: PK08-B-L01 | B40: PK08-B | C40: ME-15 | D40: WC-CH-02 | E40: 2 | F40: шт | G40: =IFERROR(IF(INDEX(02_Цены!$D$2:$D$1000,MATCH(D40,02_Цены!$A$2:$A$1000,0))="","",INDEX(02_Цены!$D$2:$D$1000,MATCH(D40,02_Цены!$A$2:$A$1000,0))),"") -> CWS Aquacontrol161RC 230/1/50 | H40: =IFERROR(IF(INDEX(02_Цены!$L$2:$L$1000,MATCH(D40,02_Цены!$A$2:$A$1000,0))="","",INDEX(02_Цены!$L$2:$L$1000,MATCH(D40,02_Цены!$A$2:$A$1000,0))),"") -> 4155.3 | I40: =IF(AND(ISNUMBER(E40),E40>=0,ISNUMBER(H40)),ROUND(E40*H40,2),"") -> 8310.6 | J40: =IFERROR(IF(INDEX(02_Цены!$M$2:$M$1000,MATCH(D40,02_Цены!$A$2:$A$1000,0))="","",INDEX(02_Цены!$M$2:$M$1000,MATCH(D40,02_Цены!$A$2:$A$1000,0))),"") -> OBSERVED_NET_CONDITIONAL_SCOPE | K40: =IF(AND(ISNUMBER(I40),J40="OBSERVED_NET_CONDITIONAL_SCOPE",OR(IFERROR(IF(INDEX(02_Цены!$E$2:$E$1000,MATCH(D40,02_Цены!$A$2:$A$1000,0))="","",INDEX(02_Цены!$E$2:$E$1000,MATCH(D40,02_Цены!$A$2:$A$1000,0))),"")="",E40=IFERROR(IF(INDEX(02_Цены!$E$2:$E$1000,MATCH(D40,02_Цены!$A$2:$A$1000,0))="","",INDEX(02_Цены!$E$2:$E$1000,MATCH(D40,02_Цены!$A$2:$A$1000,0))),""))),"PRICE_OBSERVED","BLOCK") -> PRICE_OBSERVED | L40: 16000BTU/h each; reversecycle. Price recovered live requests HTTP200 after web429; local source text retained. OEM dimensions require authenticated download; old dealerPDF not promoted.
A41: PK08-B-L02 | B41: PK08-B | C41: ME-16 | D41: WC-AUX-01 | F41: шт | G41: =IFERROR(IF(INDEX(02_Цены!$D$2:$D$1000,MATCH(D41,02_Цены!$A$2:$A$1000,0))="","",INDEX(02_Цены!$D$2:$D$1000,MATCH(D41,02_Цены!$A$2:$A$1000,0))),"") -> NH150PS SWM0150230 | H41: =IFERROR(IF(INDEX(02_Цены!$L$2:$L$1000,MATCH(D41,02_Цены!$A$2:$A$1000,0))="","",INDEX(02_Цены!$L$2:$L$1000,MATCH(D41,02_Цены!$A$2:$A$1000,0))),"") -> 663.25 | I41: =IF(AND(ISNUMBER(E41),E41>=0,ISNUMBER(H41)),ROUND(E41*H41,2),"") | J41: =IFERROR(IF(INDEX(02_Цены!$M$2:$M$1000,MATCH(D41,02_Цены!$A$2:$A$1000,0))="","",INDEX(02_Цены!$M$2:$M$1000,MATCH(D41,02_Цены!$A$2:$A$1000,0))),"") -> OBSERVED_NET_CONDITIONAL_SCOPE | K41: =IF(AND(ISNUMBER(I41),J41="OBSERVED_NET_CONDITIONAL_SCOPE",OR(IFERROR(IF(INDEX(02_Цены!$E$2:$E$1000,MATCH(D41,02_Цены!$A$2:$A$1000,0))="","",INDEX(02_Цены!$E$2:$E$1000,MATCH(D41,02_Цены!$A$2:$A$1000,0))),"")="",E41=IFERROR(IF(INDEX(02_Цены!$E$2:$E$1000,MATCH(D41,02_Цены!$A$2:$A$1000,0))="","",INDEX(02_Цены!$E$2:$E$1000,MATCH(D41,02_Цены!$A$2:$A$1000,0))),""))),"PRICE_OBSERVED","BLOCK") -> BLOCK | L41: 230V50/60Hz magneticdrive; count and pump duty notfixed. No proof this model meets both seawater and chilledwater circuits; official detailed curve required.
A42: PK08-C-L01 | B42: PK08-C | C42: ME-15 | D42: WC-CH-03 | E42: 2 | F42: шт | G42: =IFERROR(IF(INDEX(02_Цены!$D$2:$D$1000,MATCH(D42,02_Цены!$A$2:$A$1000,0))="","",INDEX(02_Цены!$D$2:$D$1000,MATCH(D42,02_Цены!$A$2:$A$1000,0))),"") -> BlueCool C16M | H42: =IFERROR(IF(INDEX(02_Цены!$L$2:$L$1000,MATCH(D42,02_Цены!$A$2:$A$1000,0))="","",INDEX(02_Цены!$L$2:$L$1000,MATCH(D42,02_Цены!$A$2:$A$1000,0))),"") | I42: =IF(AND(ISNUMBER(E42),E42>=0,ISNUMBER(H42)),ROUND(E42*H42,2),"") | J42: =IFERROR(IF(INDEX(02_Цены!$M$2:$M$1000,MATCH(D42,02_Цены!$A$2:$A$1000,0))="","",INDEX(02_Цены!$M$2:$M$1000,MATCH(D42,02_Цены!$A$2:$A$1000,0))),"") -> NO_VERIFIED_NET | K42: =IF(AND(ISNUMBER(I42),J42="OBSERVED_NET_CONDITIONAL_SCOPE",OR(IFERROR(IF(INDEX(02_Цены!$E$2:$E$1000,MATCH(D42,02_Цены!$A$2:$A$1000,0))="","",INDEX(02_Цены!$E$2:$E$1000,MATCH(D42,02_Цены!$A$2:$A$1000,0))),"")="",E42=IFERROR(IF(INDEX(02_Цены!$E$2:$E$1000,MATCH(D42,02_Цены!$A$2:$A$1000,0))="","",INDEX(02_Цены!$E$2:$E$1000,MATCH(D42,02_Цены!$A$2:$A$1000,0))),""))),"PRICE_OBSERVED","BLOCK") -> BLOCK | L42: 16000BTU/h each; officialcurrentdimensions. Older F-suffix dealerweight differs: revision match required.3pricepaths found no verified EU net exactSKU; no US price conversion.
A43: PK08-C-L02 | B43: PK08-C | C43: ME-16 | D43: WC-AUX-01 | F43: шт | G43: =IFERROR(IF(INDEX(02_Цены!$D$2:$D$1000,MATCH(D43,02_Цены!$A$2:$A$1000,0))="","",INDEX(02_Цены!$D$2:$D$1000,MATCH(D43,02_Цены!$A$2:$A$1000,0))),"") -> NH150PS SWM0150230 | H43: =IFERROR(IF(INDEX(02_Цены!$L$2:$L$1000,MATCH(D43,02_Цены!$A$2:$A$1000,0))="","",INDEX(02_Цены!$L$2:$L$1000,MATCH(D43,02_Цены!$A$2:$A$1000,0))),"") -> 663.25 | I43: =IF(AND(ISNUMBER(E43),E43>=0,ISNUMBER(H43)),ROUND(E43*H43,2),"") | J43: =IFERROR(IF(INDEX(02_Цены!$M$2:$M$1000,MATCH(D43,02_Цены!$A$2:$A$1000,0))="","",INDEX(02_Цены!$M$2:$M$1000,MATCH(D43,02_Цены!$A$2:$A$1000,0))),"") -> OBSERVED_NET_CONDITIONAL_SCOPE | K43: =IF(AND(ISNUMBER(I43),J43="OBSERVED_NET_CONDITIONAL_SCOPE",OR(IFERROR(IF(INDEX(02_Цены!$E$2:$E$1000,MATCH(D43,02_Цены!$A$2:$A$1000,0))="","",INDEX(02_Цены!$E$2:$E$1000,MATCH(D43,02_Цены!$A$2:$A$1000,0))),"")="",E43=IFERROR(IF(INDEX(02_Цены!$E$2:$E$1000,MATCH(D43,02_Цены!$A$2:$A$1000,0))="","",INDEX(02_Цены!$E$2:$E$1000,MATCH(D43,02_Цены!$A$2:$A$1000,0))),""))),"PRICE_OBSERVED","BLOCK") -> BLOCK | L43: 230V50/60Hz magneticdrive; count and pump duty notfixed. No proof this model meets both seawater and chilledwater circuits; official detailed curve required.
A44: PK09-A-L01 | B44: PK09-A | C44: ME-18 | D44: A09 | F44: шт | G44: =IFERROR(IF(INDEX(02_Цены!$D$2:$D$1000,MATCH(D44,02_Цены!$A$2:$A$1000,0))="","",INDEX(02_Цены!$D$2:$D$1000,MATCH(D44,02_Цены!$A$2:$A$1000,0))),"") -> 75500MAXM30 | H44: =IFERROR(IF(INDEX(02_Цены!$L$2:$L$1000,MATCH(D44,02_Цены!$A$2:$A$1000,0))="","",INDEX(02_Цены!$L$2:$L$1000,MATCH(D44,02_Цены!$A$2:$A$1000,0))),"") -> 1848.66 | I44: =IF(AND(ISNUMBER(E44),E44>=0,ISNUMBER(H44)),ROUND(E44*H44,2),"") | J44: =IFERROR(IF(INDEX(02_Цены!$M$2:$M$1000,MATCH(D44,02_Цены!$A$2:$A$1000,0))="","",INDEX(02_Цены!$M$2:$M$1000,MATCH(D44,02_Цены!$A$2:$A$1000,0))),"") -> VARIABLE_PRICE_RECONFIRM | K44: =IF(AND(ISNUMBER(I44),J44="OBSERVED_NET_CONDITIONAL_SCOPE",OR(IFERROR(IF(INDEX(02_Цены!$E$2:$E$1000,MATCH(D44,02_Цены!$A$2:$A$1000,0))="","",INDEX(02_Цены!$E$2:$E$1000,MATCH(D44,02_Цены!$A$2:$A$1000,0))),"")="",E44=IFERROR(IF(INDEX(02_Цены!$E$2:$E$1000,MATCH(D44,02_Цены!$A$2:$A$1000,0))="","",INDEX(02_Цены!$E$2:$E$1000,MATCH(D44,02_Цены!$A$2:$A$1000,0))),""))),"PRICE_OBSERVED","BLOCK") -> BLOCK | L44: Root open2612.00gross/19%=2194.96NET; повторное открытие независимым агентом2199.90gross/19%=1848.66NET. Принято последнее наблюдение, расхождение сохранено; подтвердить цену до сравнения. Дуплексный узел, микроны/расход одной ветви под двигатель.
A45: PK09-A-L02 | B45: PK09-A | C45: ME-19 | D45: A10 | F45: шт | G45: =IFERROR(IF(INDEX(02_Цены!$D$2:$D$1000,MATCH(D45,02_Цены!$A$2:$A$1000,0))="","",INDEX(02_Цены!$D$2:$D$1000,MATCH(D45,02_Цены!$A$2:$A$1000,0))),"") -> FTR330/32 | H45: =IFERROR(IF(INDEX(02_Цены!$L$2:$L$1000,MATCH(D45,02_Цены!$A$2:$A$1000,0))="","",INDEX(02_Цены!$L$2:$L$1000,MATCH(D45,02_Цены!$A$2:$A$1000,0))),"") -> 95.06 | I45: =IF(AND(ISNUMBER(E45),E45>=0,ISNUMBER(H45)),ROUND(E45*H45,2),"") | J45: =IFERROR(IF(INDEX(02_Цены!$M$2:$M$1000,MATCH(D45,02_Цены!$A$2:$A$1000,0))="","",INDEX(02_Цены!$M$2:$M$1000,MATCH(D45,02_Цены!$A$2:$A$1000,0))),"") -> OBSERVED_NET_CONDITIONAL_SCOPE | K45: =IF(AND(ISNUMBER(I45),J45="OBSERVED_NET_CONDITIONAL_SCOPE",OR(IFERROR(IF(INDEX(02_Цены!$E$2:$E$1000,MATCH(D45,02_Цены!$A$2:$A$1000,0))="","",INDEX(02_Цены!$E$2:$E$1000,MATCH(D45,02_Цены!$A$2:$A$1000,0))),"")="",E45=IFERROR(IF(INDEX(02_Цены!$E$2:$E$1000,MATCH(D45,02_Цены!$A$2:$A$1000,0))="","",INDEX(02_Цены!$E$2:$E$1000,MATCH(D45,02_Цены!$A$2:$A$1000,0))),""))),"PRICE_OBSERVED","BLOCK") -> BLOCK | L45: Типоразмер32мм только ориентир; диаметр и положение относительно ватерлинии по выбранному агрегату.
A46: PK09-A-L03 | B46: PK09-A | C46: ME-22 | D46: A15 | F46: шт | G46: =IFERROR(IF(INDEX(02_Цены!$D$2:$D$1000,MATCH(D46,02_Цены!$A$2:$A$1000,0))="","",INDEX(02_Цены!$D$2:$D$1000,MATCH(D46,02_Цены!$A$2:$A$1000,0))),"") -> 35770-0094 /24V | H46: =IFERROR(IF(INDEX(02_Цены!$L$2:$L$1000,MATCH(D46,02_Цены!$A$2:$A$1000,0))="","",INDEX(02_Цены!$L$2:$L$1000,MATCH(D46,02_Цены!$A$2:$A$1000,0))),"") | I46: =IF(AND(ISNUMBER(E46),E46>=0,ISNUMBER(H46)),ROUND(E46*H46,2),"") | J46: =IFERROR(IF(INDEX(02_Цены!$M$2:$M$1000,MATCH(D46,02_Цены!$A$2:$A$1000,0))="","",INDEX(02_Цены!$M$2:$M$1000,MATCH(D46,02_Цены!$A$2:$A$1000,0))),"") -> NO_VERIFIED_NET | K46: =IF(AND(ISNUMBER(I46),J46="OBSERVED_NET_CONDITIONAL_SCOPE",OR(IFERROR(IF(INDEX(02_Цены!$E$2:$E$1000,MATCH(D46,02_Цены!$A$2:$A$1000,0))="","",INDEX(02_Цены!$E$2:$E$1000,MATCH(D46,02_Цены!$A$2:$A$1000,0))),"")="",E46=IFERROR(IF(INDEX(02_Цены!$E$2:$E$1000,MATCH(D46,02_Цены!$A$2:$A$1000,0))="","",INDEX(02_Цены!$E$2:$E$1000,MATCH(D46,02_Цены!$A$2:$A$1000,0))),""))),"PRICE_OBSERVED","BLOCK") -> BLOCK | L46: Поиск224.42exVAT, открытиеchallenge. Раздел дилера предупреждаетhold EU compliance. NET поле пусто; не считать доступным. Официально7м³/мин свободныйрасход, требуемыйнапорнепроверен.
A47: PK09-A-L04 | B47: PK09-A | C47: ME-23 | D47: A16 | F47: шт | G47: =IFERROR(IF(INDEX(02_Цены!$D$2:$D$1000,MATCH(D47,02_Цены!$A$2:$A$1000,0))="","",INDEX(02_Цены!$D$2:$D$1000,MATCH(D47,02_Цены!$A$2:$A$1000,0))),"") -> UP3/OIL 16402013 /24V | H47: =IFERROR(IF(INDEX(02_Цены!$L$2:$L$1000,MATCH(D47,02_Цены!$A$2:$A$1000,0))="","",INDEX(02_Цены!$L$2:$L$1000,MATCH(D47,02_Цены!$A$2:$A$1000,0))),"") -> 188.56 | I47: =IF(AND(ISNUMBER(E47),E47>=0,ISNUMBER(H47)),ROUND(E47*H47,2),"") | J47: =IFERROR(IF(INDEX(02_Цены!$M$2:$M$1000,MATCH(D47,02_Цены!$A$2:$A$1000,0))="","",INDEX(02_Цены!$M$2:$M$1000,MATCH(D47,02_Цены!$A$2:$A$1000,0))),"") -> OBSERVED_NET_CONDITIONAL_SCOPE | K47: =IF(AND(ISNUMBER(I47),J47="OBSERVED_NET_CONDITIONAL_SCOPE",OR(IFERROR(IF(INDEX(02_Цены!$E$2:$E$1000,MATCH(D47,02_Цены!$A$2:$A$1000,0))="","",INDEX(02_Цены!$E$2:$E$1000,MATCH(D47,02_Цены!$A$2:$A$1000,0))),"")="",E47=IFERROR(IF(INDEX(02_Цены!$E$2:$E$1000,MATCH(D47,02_Цены!$A$2:$A$1000,0))="","",INDEX(02_Цены!$E$2:$E$1000,MATCH(D47,02_Цены!$A$2:$A$1000,0))),""))),"PRICE_OBSERVED","BLOCK") -> BLOCK | L47: Только насос; коллектор3агрегатов,шланги,поддоны,свет и автоматика не включены.
A48: PK09-B-L01 | B48: PK09-B | C48: ME-18 | D48: A09 | F48: шт | G48: =IFERROR(IF(INDEX(02_Цены!$D$2:$D$1000,MATCH(D48,02_Цены!$A$2:$A$1000,0))="","",INDEX(02_Цены!$D$2:$D$1000,MATCH(D48,02_Цены!$A$2:$A$1000,0))),"") -> 75500MAXM30 | H48: =IFERROR(IF(INDEX(02_Цены!$L$2:$L$1000,MATCH(D48,02_Цены!$A$2:$A$1000,0))="","",INDEX(02_Цены!$L$2:$L$1000,MATCH(D48,02_Цены!$A$2:$A$1000,0))),"") -> 1848.66 | I48: =IF(AND(ISNUMBER(E48),E48>=0,ISNUMBER(H48)),ROUND(E48*H48,2),"") | J48: =IFERROR(IF(INDEX(02_Цены!$M$2:$M$1000,MATCH(D48,02_Цены!$A$2:$A$1000,0))="","",INDEX(02_Цены!$M$2:$M$1000,MATCH(D48,02_Цены!$A$2:$A$1000,0))),"") -> VARIABLE_PRICE_RECONFIRM | K48: =IF(AND(ISNUMBER(I48),J48="OBSERVED_NET_CONDITIONAL_SCOPE",OR(IFERROR(IF(INDEX(02_Цены!$E$2:$E$1000,MATCH(D48,02_Цены!$A$2:$A$1000,0))="","",INDEX(02_Цены!$E$2:$E$1000,MATCH(D48,02_Цены!$A$2:$A$1000,0))),"")="",E48=IFERROR(IF(INDEX(02_Цены!$E$2:$E$1000,MATCH(D48,02_Цены!$A$2:$A$1000,0))="","",INDEX(02_Цены!$E$2:$E$1000,MATCH(D48,02_Цены!$A$2:$A$1000,0))),""))),"PRICE_OBSERVED","BLOCK") -> BLOCK | L48: Root open2612.00gross/19%=2194.96NET; повторное открытие независимым агентом2199.90gross/19%=1848.66NET. Принято последнее наблюдение, расхождение сохранено; подтвердить цену до сравнения. Дуплексный узел, микроны/расход одной ветви под двигатель.
A49: PK09-B-L02 | B49: PK09-B | C49: ME-19 | D49: A11 | F49: шт | G49: =IFERROR(IF(INDEX(02_Цены!$D$2:$D$1000,MATCH(D49,02_Цены!$A$2:$A$1000,0))="","",INDEX(02_Цены!$D$2:$D$1000,MATCH(D49,02_Цены!$A$2:$A$1000,0))),"") -> FTR33032M | H49: =IFERROR(IF(INDEX(02_Цены!$L$2:$L$1000,MATCH(D49,02_Цены!$A$2:$A$1000,0))="","",INDEX(02_Цены!$L$2:$L$1000,MATCH(D49,02_Цены!$A$2:$A$1000,0))),"") -> 164.46 | I49: =IF(AND(ISNUMBER(E49),E49>=0,ISNUMBER(H49)),ROUND(E49*H49,2),"") | J49: =IFERROR(IF(INDEX(02_Цены!$M$2:$M$1000,MATCH(D49,02_Цены!$A$2:$A$1000,0))="","",INDEX(02_Цены!$M$2:$M$1000,MATCH(D49,02_Цены!$A$2:$A$1000,0))),"") -> OBSERVED_NET_CONDITIONAL_SCOPE | K49: =IF(AND(ISNUMBER(I49),J49="OBSERVED_NET_CONDITIONAL_SCOPE",OR(IFERROR(IF(INDEX(02_Цены!$E$2:$E$1000,MATCH(D49,02_Цены!$A$2:$A$1000,0))="","",INDEX(02_Цены!$E$2:$E$1000,MATCH(D49,02_Цены!$A$2:$A$1000,0))),"")="",E49=IFERROR(IF(INDEX(02_Цены!$E$2:$E$1000,MATCH(D49,02_Цены!$A$2:$A$1000,0))="","",INDEX(02_Цены!$E$2:$E$1000,MATCH(D49,02_Цены!$A$2:$A$1000,0))),""))),"PRICE_OBSERVED","BLOCK") -> BLOCK | L49: NET явно exclusiefBTW; усиленная версия с металлической крышкой. Сравнение с FTR330/32 требует одинаковых давления/установочного положения.
A50: PK09-B-L03 | B50: PK09-B | C50: ME-22 | D50: A15 | F50: шт | G50: =IFERROR(IF(INDEX(02_Цены!$D$2:$D$1000,MATCH(D50,02_Цены!$A$2:$A$1000,0))="","",INDEX(02_Цены!$D$2:$D$1000,MATCH(D50,02_Цены!$A$2:$A$1000,0))),"") -> 35770-0094 /24V | H50: =IFERROR(IF(INDEX(02_Цены!$L$2:$L$1000,MATCH(D50,02_Цены!$A$2:$A$1000,0))="","",INDEX(02_Цены!$L$2:$L$1000,MATCH(D50,02_Цены!$A$2:$A$1000,0))),"") | I50: =IF(AND(ISNUMBER(E50),E50>=0,ISNUMBER(H50)),ROUND(E50*H50,2),"") | J50: =IFERROR(IF(INDEX(02_Цены!$M$2:$M$1000,MATCH(D50,02_Цены!$A$2:$A$1000,0))="","",INDEX(02_Цены!$M$2:$M$1000,MATCH(D50,02_Цены!$A$2:$A$1000,0))),"") -> NO_VERIFIED_NET | K50: =IF(AND(ISNUMBER(I50),J50="OBSERVED_NET_CONDITIONAL_SCOPE",OR(IFERROR(IF(INDEX(02_Цены!$E$2:$E$1000,MATCH(D50,02_Цены!$A$2:$A$1000,0))="","",INDEX(02_Цены!$E$2:$E$1000,MATCH(D50,02_Цены!$A$2:$A$1000,0))),"")="",E50=IFERROR(IF(INDEX(02_Цены!$E$2:$E$1000,MATCH(D50,02_Цены!$A$2:$A$1000,0))="","",INDEX(02_Цены!$E$2:$E$1000,MATCH(D50,02_Цены!$A$2:$A$1000,0))),""))),"PRICE_OBSERVED","BLOCK") -> BLOCK | L50: Поиск224.42exVAT, открытиеchallenge. Раздел дилера предупреждаетhold EU compliance. NET поле пусто; не считать доступным. Официально7м³/мин свободныйрасход, требуемыйнапорнепроверен.
A51: PK09-B-L04 | B51: PK09-B | C51: ME-23 | D51: A16 | F51: шт | G51: =IFERROR(IF(INDEX(02_Цены!$D$2:$D$1000,MATCH(D51,02_Цены!$A$2:$A$1000,0))="","",INDEX(02_Цены!$D$2:$D$1000,MATCH(D51,02_Цены!$A$2:$A$1000,0))),"") -> UP3/OIL 16402013 /24V | H51: =IFERROR(IF(INDEX(02_Цены!$L$2:$L$1000,MATCH(D51,02_Цены!$A$2:$A$1000,0))="","",INDEX(02_Цены!$L$2:$L$1000,MATCH(D51,02_Цены!$A$2:$A$1000,0))),"") -> 188.56 | I51: =IF(AND(ISNUMBER(E51),E51>=0,ISNUMBER(H51)),ROUND(E51*H51,2),"") | J51: =IFERROR(IF(INDEX(02_Цены!$M$2:$M$1000,MATCH(D51,02_Цены!$A$2:$A$1000,0))="","",INDEX(02_Цены!$M$2:$M$1000,MATCH(D51,02_Цены!$A$2:$A$1000,0))),"") -> OBSERVED_NET_CONDITIONAL_SCOPE | K51: =IF(AND(ISNUMBER(I51),J51="OBSERVED_NET_CONDITIONAL_SCOPE",OR(IFERROR(IF(INDEX(02_Цены!$E$2:$E$1000,MATCH(D51,02_Цены!$A$2:$A$1000,0))="","",INDEX(02_Цены!$E$2:$E$1000,MATCH(D51,02_Цены!$A$2:$A$1000,0))),"")="",E51=IFERROR(IF(INDEX(02_Цены!$E$2:$E$1000,MATCH(D51,02_Цены!$A$2:$A$1000,0))="","",INDEX(02_Цены!$E$2:$E$1000,MATCH(D51,02_Цены!$A$2:$A$1000,0))),""))),"PRICE_OBSERVED","BLOCK") -> BLOCK | L51: Только насос; коллектор3агрегатов,шланги,поддоны,свет и автоматика не включены.
A52: PK09-C-L01 | B52: PK09-C | C52: ME-18 | D52: A09 | F52: шт | G52: =IFERROR(IF(INDEX(02_Цены!$D$2:$D$1000,MATCH(D52,02_Цены!$A$2:$A$1000,0))="","",INDEX(02_Цены!$D$2:$D$1000,MATCH(D52,02_Цены!$A$2:$A$1000,0))),"") -> 75500MAXM30 | H52: =IFERROR(IF(INDEX(02_Цены!$L$2:$L$1000,MATCH(D52,02_Цены!$A$2:$A$1000,0))="","",INDEX(02_Цены!$L$2:$L$1000,MATCH(D52,02_Цены!$A$2:$A$1000,0))),"") -> 1848.66 | I52: =IF(AND(ISNUMBER(E52),E52>=0,ISNUMBER(H52)),ROUND(E52*H52,2),"") | J52: =IFERROR(IF(INDEX(02_Цены!$M$2:$M$1000,MATCH(D52,02_Цены!$A$2:$A$1000,0))="","",INDEX(02_Цены!$M$2:$M$1000,MATCH(D52,02_Цены!$A$2:$A$1000,0))),"") -> VARIABLE_PRICE_RECONFIRM | K52: =IF(AND(ISNUMBER(I52),J52="OBSERVED_NET_CONDITIONAL_SCOPE",OR(IFERROR(IF(INDEX(02_Цены!$E$2:$E$1000,MATCH(D52,02_Цены!$A$2:$A$1000,0))="","",INDEX(02_Цены!$E$2:$E$1000,MATCH(D52,02_Цены!$A$2:$A$1000,0))),"")="",E52=IFERROR(IF(INDEX(02_Цены!$E$2:$E$1000,MATCH(D52,02_Цены!$A$2:$A$1000,0))="","",INDEX(02_Цены!$E$2:$E$1000,MATCH(D52,02_Цены!$A$2:$A$1000,0))),""))),"PRICE_OBSERVED","BLOCK") -> BLOCK | L52: Root open2612.00gross/19%=2194.96NET; повторное открытие независимым агентом2199.90gross/19%=1848.66NET. Принято последнее наблюдение, расхождение сохранено; подтвердить цену до сравнения. Дуплексный узел, микроны/расход одной ветви под двигатель.
A53: PK09-C-L02 | B53: PK09-C | C53: ME-19 | D53: A11 | F53: шт | G53: =IFERROR(IF(INDEX(02_Цены!$D$2:$D$1000,MATCH(D53,02_Цены!$A$2:$A$1000,0))="","",INDEX(02_Цены!$D$2:$D$1000,MATCH(D53,02_Цены!$A$2:$A$1000,0))),"") -> FTR33032M | H53: =IFERROR(IF(INDEX(02_Цены!$L$2:$L$1000,MATCH(D53,02_Цены!$A$2:$A$1000,0))="","",INDEX(02_Цены!$L$2:$L$1000,MATCH(D53,02_Цены!$A$2:$A$1000,0))),"") -> 164.46 | I53: =IF(AND(ISNUMBER(E53),E53>=0,ISNUMBER(H53)),ROUND(E53*H53,2),"") | J53: =IFERROR(IF(INDEX(02_Цены!$M$2:$M$1000,MATCH(D53,02_Цены!$A$2:$A$1000,0))="","",INDEX(02_Цены!$M$2:$M$1000,MATCH(D53,02_Цены!$A$2:$A$1000,0))),"") -> OBSERVED_NET_CONDITIONAL_SCOPE | K53: =IF(AND(ISNUMBER(I53),J53="OBSERVED_NET_CONDITIONAL_SCOPE",OR(IFERROR(IF(INDEX(02_Цены!$E$2:$E$1000,MATCH(D53,02_Цены!$A$2:$A$1000,0))="","",INDEX(02_Цены!$E$2:$E$1000,MATCH(D53,02_Цены!$A$2:$A$1000,0))),"")="",E53=IFERROR(IF(INDEX(02_Цены!$E$2:$E$1000,MATCH(D53,02_Цены!$A$2:$A$1000,0))="","",INDEX(02_Цены!$E$2:$E$1000,MATCH(D53,02_Цены!$A$2:$A$1000,0))),""))),"PRICE_OBSERVED","BLOCK") -> BLOCK | L53: NET явно exclusiefBTW; усиленная версия с металлической крышкой. Сравнение с FTR330/32 требует одинаковых давления/установочного положения.
A54: PK09-C-L03 | B54: PK09-C | C54: ME-22 | D54: A15 | F54: шт | G54: =IFERROR(IF(INDEX(02_Цены!$D$2:$D$1000,MATCH(D54,02_Цены!$A$2:$A$1000,0))="","",INDEX(02_Цены!$D$2:$D$1000,MATCH(D54,02_Цены!$A$2:$A$1000,0))),"") -> 35770-0094 /24V | H54: =IFERROR(IF(INDEX(02_Цены!$L$2:$L$1000,MATCH(D54,02_Цены!$A$2:$A$1000,0))="","",INDEX(02_Цены!$L$2:$L$1000,MATCH(D54,02_Цены!$A$2:$A$1000,0))),"") | I54: =IF(AND(ISNUMBER(E54),E54>=0,ISNUMBER(H54)),ROUND(E54*H54,2),"") | J54: =IFERROR(IF(INDEX(02_Цены!$M$2:$M$1000,MATCH(D54,02_Цены!$A$2:$A$1000,0))="","",INDEX(02_Цены!$M$2:$M$1000,MATCH(D54,02_Цены!$A$2:$A$1000,0))),"") -> NO_VERIFIED_NET | K54: =IF(AND(ISNUMBER(I54),J54="OBSERVED_NET_CONDITIONAL_SCOPE",OR(IFERROR(IF(INDEX(02_Цены!$E$2:$E$1000,MATCH(D54,02_Цены!$A$2:$A$1000,0))="","",INDEX(02_Цены!$E$2:$E$1000,MATCH(D54,02_Цены!$A$2:$A$1000,0))),"")="",E54=IFERROR(IF(INDEX(02_Цены!$E$2:$E$1000,MATCH(D54,02_Цены!$A$2:$A$1000,0))="","",INDEX(02_Цены!$E$2:$E$1000,MATCH(D54,02_Цены!$A$2:$A$1000,0))),""))),"PRICE_OBSERVED","BLOCK") -> BLOCK | L54: Поиск224.42exVAT, открытиеchallenge. Раздел дилера предупреждаетhold EU compliance. NET поле пусто; не считать доступным. Официально7м³/мин свободныйрасход, требуемыйнапорнепроверен.
... A80: PK12-C-L01 | B80: PK12-C | C80: ME-29 | D80: A08 | F80: шт | G80: =IFERROR(IF(INDEX(02_Цены!$D$2:$D$1000,MATCH(D80,02_Цены!$A$2:$A$1000,0))="","",INDEX(02_Цены!$D$2:$D$1000,MATCH(D80,02_Цены!$A$2:$A$1000,0))),"") -> Hydro 2 | H80: =IFERROR(IF(INDEX(02_Цены!$L$2:$L$1000,MATCH(D80,02_Цены!$A$2:$A$1000,0))="","",INDEX(02_Цены!$L$2:$L$1000,MATCH(D80,02_Цены!$A$2:$A$1000,0))),"") | I80: =IF(AND(ISNUMBER(E80),E80>=0,ISNUMBER(H80)),ROUND(E80*H80,2),"") | J80: =IFERROR(IF(INDEX(02_Цены!$M$2:$M$1000,MATCH(D80,02_Цены!$A$2:$A$1000,0))="","",INDEX(02_Цены!$M$2:$M$1000,MATCH(D80,02_Цены!$A$2:$A$1000,0))),"") -> NO_VERIFIED_NET | K80: =IF(AND(ISNUMBER(I80),J80="OBSERVED_NET_CONDITIONAL_SCOPE",OR(IFERROR(IF(INDEX(02_Цены!$E$2:$E$1000,MATCH(D80,02_Цены!$A$2:$A$1000,0))="","",INDEX(02_Цены!$E$2:$E$1000,MATCH(D80,02_Цены!$A$2:$A$1000,0))),"")="",E80=IFERROR(IF(INDEX(02_Цены!$E$2:$E$1000,MATCH(D80,02_Цены!$A$2:$A$1000,0))="","",INDEX(02_Цены!$E$2:$E$1000,MATCH(D80,02_Цены!$A$2:$A$1000,0))),""))),"PRICE_OBSERVED","BLOCK") -> BLOCK | L80: 30л,2мотора24V4kW; стандартная помпа15л/мин140бар. Не доказана пригодность для подруливающих; не назначать резервное питание от6АКБ дорасчёта тока.

Sheet 04_Комплектность
A1: Проверка_ID | B1: Вариант | C1: Что должно быть закрыто | D1: Статус | E1: Документ / лист закрытия | F1: Ответственный | G1: Где учтена стоимость
A2: PK01-A-S01 | B2: PK01-A | C2: Двигатель и согласованный редуктор, заводские опоры, управление и жгуты; муфта, упорный узел, вал, дейдвуд, подшипники, уплотнение и согласованный движитель; монтаж, центровка, настройка и собственные испытания | D2: OPEN
A3: PK01-A-S02 | B3: PK01-A | C3: Включения двигателя раскрыть по позициям | D3: OPEN
A4: PK01-A-S03 | B4: PK01-A | C4: Внешнее топливо, охлаждение, выхлоп и вентиляция — PK09; гидронасос и его силовой привод — PK12; механическая совместимость PTO — интерфейс PK01/PK12 | D4: OPEN
A5: PK01-A-EXT | B5: PK01-A | C5: Подтвердить полный построчный BOM и границы: нет отсутствующих платных частей или внешних работ; у каждого включения/исключения есть место стоимости. Все монтажные доплаты учтены один раз. | D5: OPEN
A6: PK01-B-S01 | B6: PK01-B | C6: Двигатель и согласованный редуктор, заводские опоры, управление и жгуты; муфта, упорный узел, вал, дейдвуд, подшипники, уплотнение и согласованный движитель; монтаж, центровка, настройка и собственные испытания | D6: OPEN
A7: PK01-B-S02 | B7: PK01-B | C7: Включения двигателя раскрыть по позициям | D7: OPEN
A8: PK01-B-S03 | B8: PK01-B | C8: Внешнее топливо, охлаждение, выхлоп и вентиляция — PK09; гидронасос и его силовой привод — PK12; механическая совместимость PTO — интерфейс PK01/PK12 | D8: OPEN
A9: PK01-B-EXT | B9: PK01-B | C9: Подтвердить полный построчный BOM и границы: нет отсутствующих платных частей или внешних работ; у каждого включения/исключения есть место стоимости. Все монтажные доплаты учтены один раз. | D9: OPEN
A10: PK01-C-S01 | B10: PK01-C | C10: Двигатель и согласованный редуктор, заводские опоры, управление и жгуты; муфта, упорный узел, вал, дейдвуд, подшипники, уплотнение и согласованный движитель; монтаж, центровка, настройка и собственные испытания | D10: OPEN
A11: PK01-C-S02 | B11: PK01-C | C11: Включения двигателя раскрыть по позициям | D11: OPEN
A12: PK01-C-S03 | B12: PK01-C | C12: Внешнее топливо, охлаждение, выхлоп и вентиляция — PK09; гидронасос и его силовой привод — PK12; механическая совместимость PTO — интерфейс PK01/PK12 | D12: OPEN
A13: PK01-C-EXT | B13: PK01-C | C13: Подтвердить полный построчный BOM и границы: нет отсутствующих платных частей или внешних работ; у каждого включения/исключения есть место стоимости. Все монтажные доплаты учтены один раз. | D13: OPEN
... A178: PK12-C-EXT | B178: PK12-C | C178: Подтвердить полный построчный BOM и границы: нет отсутствующих платных частей или внешних работ; у каждого включения/исключения есть место стоимости. Все монтажные доплаты учтены один раз. | D178: OPEN

Sheet 05_КАЦ
A1: Вариант | B1: Пакет | C1: Начальная гипотеза исполнения | D1: Заданные количества | E1: Строк состава | F1: Строк с суммой | G1: Известная часть NET EUR | H1: Открыто по составу | I1: Недопущенных цен | J1: Технический допуск | K1: Коммерческий состав | L1: Полный NET состава EUR | M1: Доставка NET EUR | N1: Страхование NET EUR | O1: Пошлина EUR | P1: Оформление NET EUR | Q1: Монтаж / ПНР NET EUR | R1: Прочие NET EUR | S1: Полная стоимость NET EUR | T1: Невозмещаемый VAT EUR | U1: Стоимость проекта EUR | V1: Полнота налоговых документов | W1: Выбор владельца | X1: Что ещё требуется | Y1: Статус
A2: PK01-A | B2: PK01 | C2: D4-300 I + HS85A | D2: 1 двигатель; 1 редуктор предлагается | E2: =COUNTIF(03_Состав!$B$2:$B$80,A2) -> 1 | F2: =SUMPRODUCT((03_Состав!$B$2:$B$80=A2)*ISNUMBER(03_Состав!$I$2:$I$80)) -> 1 | G2: =IF(F2>0,ROUND(SUMIF(03_Состав!$B$2:$B$80,A2,03_Состав!$I$2:$I$80),2),"") -> 45977 | H2: =SUMPRODUCT((04_Комплектность!$B$2:$B$178=A2)*(((04_Комплектность!$D$2:$D$178<>"CLOSED")+(04_Комплектность!$E$2:$E$178="")+(04_Комплектность!$G$2:$G$178=""))>0)) -> 4 | I2: =COUNTIFS(03_Состав!$B$2:$B$80,A2,03_Состав!$K$2:$K$80,"BLOCK") -> 1 | J2: NOT_CHECKED | K2: PUBLIC_ONLY | L2: =IF(AND(E2>0,E2=F2,H2=0,I2=0,J2="PASS",K2="CONFIRMED_FULL"),G2,"") | S2: =IF(AND(ISNUMBER(L2),COUNT(M2:R2)=6),ROUND(SUM(L2:R2),2),"") | T2: =IF(AND(V2="CONFIRMED_ALL_DOCUMENTS",COUNTIF(06_НДС!$B$2:$B$1000,A2)>0,COUNTIFS(06_НДС!$B$2:$B$1000,A2,06_НДС!$S$2:$S$1000,"<>CALCULATED_WITH_INPUTS")=0),ROUND(SUMIF(06_НДС!$B$2:$B$1000,A2,06_НДС!$M$2:$M$1000),2),"") | U2: =IF(AND(ISNUMBER(S2),ISNUMBER(T2)),ROUND(S2+T2,2),"") | V2: OPEN | W2: NOT_SELECTED | X2: 300 л.с. — исходный ориентир. Скорость, сопротивление, рабочий режим и PTO не рассчитаны. Измеренная компоновка, монтажные и сервисные зоны, полный состав поставки и интерфейсы ещё требуют подтверждения. | Y2: =IF(ISNUMBER(U2),"CALCULATED_FOR_REVIEW","DRAFT_OPEN") -> DRAFT_OPEN
A3: PK01-B | B3: PK01 | C3: 8LV320E-KMH50A + VC20 | D3: 1 двигатель; 1 редуктор предлагается | E3: =COUNTIF(03_Состав!$B$2:$B$80,A3) -> 1 | F3: =SUMPRODUCT((03_Состав!$B$2:$B$80=A3)*ISNUMBER(03_Состав!$I$2:$I$80)) -> 0 | G3: =IF(F3>0,ROUND(SUMIF(03_Состав!$B$2:$B$80,A3,03_Состав!$I$2:$I$80),2),"") | H3: =SUMPRODUCT((04_Комплектность!$B$2:$B$178=A3)*(((04_Комплектность!$D$2:$D$178<>"CLOSED")+(04_Комплектность!$E$2:$E$178="")+(04_Комплектность!$G$2:$G$178=""))>0)) -> 4 | I3: =COUNTIFS(03_Состав!$B$2:$B$80,A3,03_Состав!$K$2:$K$80,"BLOCK") -> 1 | J3: NOT_CHECKED | K3: PUBLIC_ONLY | L3: =IF(AND(E3>0,E3=F3,H3=0,I3=0,J3="PASS",K3="CONFIRMED_FULL"),G3,"") | S3: =IF(AND(ISNUMBER(L3),COUNT(M3:R3)=6),ROUND(SUM(L3:R3),2),"") | T3: =IF(AND(V3="CONFIRMED_ALL_DOCUMENTS",COUNTIF(06_НДС!$B$2:$B$1000,A3)>0,COUNTIFS(06_НДС!$B$2:$B$1000,A3,06_НДС!$S$2:$S$1000,"<>CALCULATED_WITH_INPUTS")=0),ROUND(SUMIF(06_НДС!$B$2:$B$1000,A3,06_НДС!$M$2:$M$1000),2),"") | U3: =IF(AND(ISNUMBER(S3),ISNUMBER(T3)),ROUND(S3+T3,2),"") | V3: OPEN | W3: NOT_SELECTED | X3: 300 л.с. — исходный ориентир. Скорость, сопротивление, рабочий режим и PTO не рассчитаны. Измеренная компоновка, монтажные и сервисные зоны, полный состав поставки и интерфейсы ещё требуют подтверждения. | Y3: =IF(ISNUMBER(U3),"CALCULATED_FOR_REVIEW","DRAFT_OPEN") -> DRAFT_OPEN
A4: PK01-C | B4: PK01 | C4: C90 410 rating D 300hp + gearbox RFQ | D4: 1 двигатель; 1 редуктор предлагается | E4: =COUNTIF(03_Состав!$B$2:$B$80,A4) -> 1 | F4: =SUMPRODUCT((03_Состав!$B$2:$B$80=A4)*ISNUMBER(03_Состав!$I$2:$I$80)) -> 0 | G4: =IF(F4>0,ROUND(SUMIF(03_Состав!$B$2:$B$80,A4,03_Состав!$I$2:$I$80),2),"") | H4: =SUMPRODUCT((04_Комплектность!$B$2:$B$178=A4)*(((04_Комплектность!$D$2:$D$178<>"CLOSED")+(04_Комплектность!$E$2:$E$178="")+(04_Комплектность!$G$2:$G$178=""))>0)) -> 4 | I4: =COUNTIFS(03_Состав!$B$2:$B$80,A4,03_Состав!$K$2:$K$80,"BLOCK") -> 1 | J4: NOT_CHECKED | K4: PUBLIC_ONLY | L4: =IF(AND(E4>0,E4=F4,H4=0,I4=0,J4="PASS",K4="CONFIRMED_FULL"),G4,"") | S4: =IF(AND(ISNUMBER(L4),COUNT(M4:R4)=6),ROUND(SUM(L4:R4),2),"") | T4: =IF(AND(V4="CONFIRMED_ALL_DOCUMENTS",COUNTIF(06_НДС!$B$2:$B$1000,A4)>0,COUNTIFS(06_НДС!$B$2:$B$1000,A4,06_НДС!$S$2:$S$1000,"<>CALCULATED_WITH_INPUTS")=0),ROUND(SUMIF(06_НДС!$B$2:$B$1000,A4,06_НДС!$M$2:$M$1000),2),"") | U4: =IF(AND(ISNUMBER(S4),ISNUMBER(T4)),ROUND(S4+T4,2),"") | V4: OPEN | W4: NOT_SELECTED | X4: 300 л.с. — исходный ориентир. Скорость, сопротивление, рабочий режим и PTO не рассчитаны. Измеренная компоновка, монтажные и сервисные зоны, полный состав поставки и интерфейсы ещё требуют подтверждения. | Y4: =IF(ISNUMBER(U4),"CALCULATED_FOR_REVIEW","DRAFT_OPEN") -> DRAFT_OPEN
A5: PK02-A | B5: PK02 | C5: Paguro12000V AP12023050M0 | D5: 2 генератора | E5: =COUNTIF(03_Состав!$B$2:$B$80,A5) -> 1 | F5: =SUMPRODUCT((03_Состав!$B$2:$B$80=A5)*ISNUMBER(03_Состав!$I$2:$I$80)) -> 1 | G5: =IF(F5>0,ROUND(SUMIF(03_Состав!$B$2:$B$80,A5,03_Состав!$I$2:$I$80),2),"") -> 24893 | H5: =SUMPRODUCT((04_Комплектность!$B$2:$B$178=A5)*(((04_Комплектность!$D$2:$D$178<>"CLOSED")+(04_Комплектность!$E$2:$E$178="")+(04_Комплектность!$G$2:$G$178=""))>0)) -> 4 | I5: =COUNTIFS(03_Состав!$B$2:$B$80,A5,03_Состав!$K$2:$K$80,"BLOCK") -> 0 | J5: NOT_CHECKED | K5: PUBLIC_ONLY | L5: =IF(AND(E5>0,E5=F5,H5=0,I5=0,J5="PASS",K5="CONFIRMED_FULL"),G5,"") | S5: =IF(AND(ISNUMBER(L5),COUNT(M5:R5)=6),ROUND(SUM(L5:R5),2),"") | T5: =IF(AND(V5="CONFIRMED_ALL_DOCUMENTS",COUNTIF(06_НДС!$B$2:$B$1000,A5)>0,COUNTIFS(06_НДС!$B$2:$B$1000,A5,06_НДС!$S$2:$S$1000,"<>CALCULATED_WITH_INPUTS")=0),ROUND(SUMIF(06_НДС!$B$2:$B$1000,A5,06_НДС!$M$2:$M$1000),2),"") | U5: =IF(AND(ISNUMBER(S5),ISNUMBER(T5)),ROUND(S5+T5,2),"") | V5: OPEN | W5: NOT_SELECTED | X5: Около 11.5–12 кВА — исходный ориентир. Постоянные и пиковые нагрузки, режим отказа открыты. Измеренная компоновка, монтажные и сервисные зоны, полный состав поставки и интерфейсы ещё требуют подтверждения. | Y5: =IF(ISNUMBER(U5),"CALCULATED_FOR_REVIEW","DRAFT_OPEN") -> DRAFT_OPEN
A6: PK02-B | B6: PK02 | C6: 12000x-230V PMS NautiRadar0028284 | D6: 2 генератора | E6: =COUNTIF(03_Состав!$B$2:$B$80,A6) -> 1 | F6: =SUMPRODUCT((03_Состав!$B$2:$B$80=A6)*ISNUMBER(03_Состав!$I$2:$I$80)) -> 1 | G6: =IF(F6>0,ROUND(SUMIF(03_Состав!$B$2:$B$80,A6,03_Состав!$I$2:$I$80),2),"") -> 34902.44 | H6: =SUMPRODUCT((04_Комплектность!$B$2:$B$178=A6)*(((04_Комплектность!$D$2:$D$178<>"CLOSED")+(04_Комплектность!$E$2:$E$178="")+(04_Комплектность!$G$2:$G$178=""))>0)) -> 4 | I6: =COUNTIFS(03_Состав!$B$2:$B$80,A6,03_Состав!$K$2:$K$80,"BLOCK") -> 0 | J6: NOT_CHECKED | K6: PUBLIC_ONLY | L6: =IF(AND(E6>0,E6=F6,H6=0,I6=0,J6="PASS",K6="CONFIRMED_FULL"),G6,"") | S6: =IF(AND(ISNUMBER(L6),COUNT(M6:R6)=6),ROUND(SUM(L6:R6),2),"") | T6: =IF(AND(V6="CONFIRMED_ALL_DOCUMENTS",COUNTIF(06_НДС!$B$2:$B$1000,A6)>0,COUNTIFS(06_НДС!$B$2:$B$1000,A6,06_НДС!$S$2:$S$1000,"<>CALCULATED_WITH_INPUTS")=0),ROUND(SUMIF(06_НДС!$B$2:$B$1000,A6,06_НДС!$M$2:$M$1000),2),"") | U6: =IF(AND(ISNUMBER(S6),ISNUMBER(T6)),ROUND(S6+T6,2),"") | V6: OPEN | W6: NOT_SELECTED | X6: Около 11.5–12 кВА — исходный ориентир. Постоянные и пиковые нагрузки, режим отказа открыты. Измеренная компоновка, монтажные и сервисные зоны, полный состав поставки и интерфейсы ещё требуют подтверждения. | Y6: =IF(ISNUMBER(U6),"CALCULATED_FOR_REVIEW","DRAFT_OPEN") -> DRAFT_OPEN
A7: PK02-C | B7: PK02 | C7: 12EFKOZD | D7: 2 генератора | E7: =COUNTIF(03_Состав!$B$2:$B$80,A7) -> 1 | F7: =SUMPRODUCT((03_Состав!$B$2:$B$80=A7)*ISNUMBER(03_Состав!$I$2:$I$80)) -> 1 | G7: =IF(F7>0,ROUND(SUMIF(03_Состав!$B$2:$B$80,A7,03_Состав!$I$2:$I$80),2),"") -> 35858.24 | H7: =SUMPRODUCT((04_Комплектность!$B$2:$B$178=A7)*(((04_Комплектность!$D$2:$D$178<>"CLOSED")+(04_Комплектность!$E$2:$E$178="")+(04_Комплектность!$G$2:$G$178=""))>0)) -> 4 | I7: =COUNTIFS(03_Состав!$B$2:$B$80,A7,03_Состав!$K$2:$K$80,"BLOCK") -> 0 | J7: NOT_CHECKED | K7: PUBLIC_ONLY | L7: =IF(AND(E7>0,E7=F7,H7=0,I7=0,J7="PASS",K7="CONFIRMED_FULL"),G7,"") | S7: =IF(AND(ISNUMBER(L7),COUNT(M7:R7)=6),ROUND(SUM(L7:R7),2),"") | T7: =IF(AND(V7="CONFIRMED_ALL_DOCUMENTS",COUNTIF(06_НДС!$B$2:$B$1000,A7)>0,COUNTIFS(06_НДС!$B$2:$B$1000,A7,06_НДС!$S$2:$S$1000,"<>CALCULATED_WITH_INPUTS")=0),ROUND(SUMIF(06_НДС!$B$2:$B$1000,A7,06_НДС!$M$2:$M$1000),2),"") | U7: =IF(AND(ISNUMBER(S7),ISNUMBER(T7)),ROUND(S7+T7,2),"") | V7: OPEN | W7: NOT_SELECTED | X7: Около 11.5–12 кВА — исходный ориентир. Постоянные и пиковые нагрузки, режим отказа открыты. Измеренная компоновка, монтажные и сервисные зоны, полный состав поставки и интерфейсы ещё требуют подтверждения. | Y7: =IF(ISNUMBER(U7),"CALCULATED_FOR_REVIEW","DRAFT_OPEN") -> DRAFT_OPEN
A8: PK03-A | B8: PK03 | C8: MultiPlus-II 24/3000/70-32 PMP242305010 + 3600 ITR040362042 | D8: 2 основных инвертора; 1 независимая функция питания насоса | E8: =COUNTIF(03_Состав!$B$2:$B$80,A8) -> 2 | F8: =SUMPRODUCT((03_Состав!$B$2:$B$80=A8)*ISNUMBER(03_Состав!$I$2:$I$80)) -> 1 | G8: =IF(F8>0,ROUND(SUMIF(03_Состав!$B$2:$B$80,A8,03_Состав!$I$2:$I$80),2),"") -> 1478.9 | H8: =SUMPRODUCT((04_Комплектность!$B$2:$B$178=A8)*(((04_Комплектность!$D$2:$D$178<>"CLOSED")+(04_Комплектность!$E$2:$E$178="")+(04_Комплектность!$G$2:$G$178=""))>0)) -> 5 | I8: =COUNTIFS(03_Состав!$B$2:$B$80,A8,03_Состав!$K$2:$K$80,"BLOCK") -> 1 | J8: NOT_CHECKED | K8: PUBLIC_ONLY | L8: =IF(AND(E8>0,E8=F8,H8=0,I8=0,J8="PASS",K8="CONFIRMED_FULL"),G8,"") | S8: =IF(AND(ISNUMBER(L8),COUNT(M8:R8)=6),ROUND(SUM(L8:R8),2),"") | T8: =IF(AND(V8="CONFIRMED_ALL_DOCUMENTS",COUNTIF(06_НДС!$B$2:$B$1000,A8)>0,COUNTIFS(06_НДС!$B$2:$B$1000,A8,06_НДС!$S$2:$S$1000,"<>CALCULATED_WITH_INPUTS")=0),ROUND(SUMIF(06_НДС!$B$2:$B$1000,A8,06_НДС!$M$2:$M$1000),2),"") | U8: =IF(AND(ISNUMBER(S8),ISNUMBER(T8)),ROUND(S8+T8,2),"") | V8: OPEN | W8: NOT_SELECTED | X8: 3 кВА — поисковый класс, не утверждённая мощность. Баланс и береговой ввод открыты. Измеренная компоновка, монтажные и сервисные зоны, полный состав поставки и интерфейсы ещё требуют подтверждения. | Y8: =IF(ISNUMBER(U8),"CALCULATED_FOR_REVIEW","DRAFT_OPEN") -> DRAFT_OPEN
A9: PK03-B | B9: PK03 | C9: MultiPlus-II GX 24/3000/70-32 PMP242306000 + Mass GI3.5 88000355 | D9: 2 основных инвертора; 1 независимая функция питания насоса | E9: =COUNTIF(03_Состав!$B$2:$B$80,A9) -> 2 | F9: =SUMPRODUCT((03_Состав!$B$2:$B$80=A9)*ISNUMBER(03_Состав!$I$2:$I$80)) -> 1 | G9: =IF(F9>0,ROUND(SUMIF(03_Состав!$B$2:$B$80,A9,03_Состав!$I$2:$I$80),2),"") -> 1680.58 | H9: =SUMPRODUCT((04_Комплектность!$B$2:$B$178=A9)*(((04_Комплектность!$D$2:$D$178<>"CLOSED")+(04_Комплектность!$E$2:$E$178="")+(04_Комплектность!$G$2:$G$178=""))>0)) -> 5 | I9: =COUNTIFS(03_Состав!$B$2:$B$80,A9,03_Состав!$K$2:$K$80,"BLOCK") -> 1 | J9: NOT_CHECKED | K9: PUBLIC_ONLY | L9: =IF(AND(E9>0,E9=F9,H9=0,I9=0,J9="PASS",K9="CONFIRMED_FULL"),G9,"") | S9: =IF(AND(ISNUMBER(L9),COUNT(M9:R9)=6),ROUND(SUM(L9:R9),2),"") | T9: =IF(AND(V9="CONFIRMED_ALL_DOCUMENTS",COUNTIF(06_НДС!$B$2:$B$1000,A9)>0,COUNTIFS(06_НДС!$B$2:$B$1000,A9,06_НДС!$S$2:$S$1000,"<>CALCULATED_WITH_INPUTS")=0),ROUND(SUMIF(06_НДС!$B$2:$B$1000,A9,06_НДС!$M$2:$M$1000),2),"") | U9: =IF(AND(ISNUMBER(S9),ISNUMBER(T9)),ROUND(S9+T9,2),"") | V9: OPEN | W9: NOT_SELECTED | X9: 3 кВА — поисковый класс, не утверждённая мощность. Баланс и береговой ввод открыты. Измеренная компоновка, монтажные и сервисные зоны, полный состав поставки и интерфейсы ещё требуют подтверждения. | Y9: =IF(ISNUMBER(U9),"CALCULATED_FOR_REVIEW","DRAFT_OPEN") -> DRAFT_OPEN
A10: PK03-C | B10: PK03 | C10: CombiMaster 24/3000-60 230V 35023000 + Mass GI3.5 88000355 | D10: 2 основных инвертора; 1 независимая функция питания насоса | E10: =COUNTIF(03_Состав!$B$2:$B$80,A10) -> 2 | F10: =SUMPRODUCT((03_Состав!$B$2:$B$80=A10)*ISNUMBER(03_Состав!$I$2:$I$80)) -> 1 | G10: =IF(F10>0,ROUND(SUMIF(03_Состав!$B$2:$B$80,A10,03_Состав!$I$2:$I$80),2),"") -> 2689 | H10: =SUMPRODUCT((04_Комплектность!$B$2:$B$178=A10)*(((04_Комплектность!$D$2:$D$178<>"CLOSED")+(04_Комплектность!$E$2:$E$178="")+(04_Комплектность!$G$2:$G$178=""))>0)) -> 5 | I10: =COUNTIFS(03_Состав!$B$2:$B$80,A10,03_Состав!$K$2:$K$80,"BLOCK") -> 1 | J10: NOT_CHECKED | K10: PUBLIC_ONLY | L10: =IF(AND(E10>0,E10=F10,H10=0,I10=0,J10="PASS",K10="CONFIRMED_FULL"),G10,"") | S10: =IF(AND(ISNUMBER(L10),COUNT(M10:R10)=6),ROUND(SUM(L10:R10),2),"") | T10: =IF(AND(V10="CONFIRMED_ALL_DOCUMENTS",COUNTIF(06_НДС!$B$2:$B$1000,A10)>0,COUNTIFS(06_НДС!$B$2:$B$1000,A10,06_НДС!$S$2:$S$1000,"<>CALCULATED_WITH_INPUTS")=0),ROUND(SUMIF(06_НДС!$B$2:$B$1000,A10,06_НДС!$M$2:$M$1000),2),"") | U10: =IF(AND(ISNUMBER(S10),ISNUMBER(T10)),ROUND(S10+T10,2),"") | V10: OPEN | W10: NOT_SELECTED | X10: 3 кВА — поисковый класс, не утверждённая мощность. Баланс и береговой ввод открыты. Измеренная компоновка, монтажные и сервисные зоны, полный состав поставки и интерфейсы ещё требуют подтверждения. | Y10: =IF(ISNUMBER(U10),"CALCULATED_FOR_REVIEW","DRAFT_OPEN") -> DRAFT_OPEN
A11: PK04-A | B11: PK04 | C11: ER550 12V115Ah + UNSIZED + UNSIZED + ML-RBS7702 24V | D11: 6 сервисных + 2 генераторных + 1 главного двигателя | E11: =COUNTIF(03_Состав!$B$2:$B$80,A11) -> 4 | F11: =SUMPRODUCT((03_Состав!$B$2:$B$80=A11)*ISNUMBER(03_Состав!$I$2:$I$80)) -> 1 | G11: =IF(F11>0,ROUND(SUMIF(03_Состав!$B$2:$B$80,A11,03_Состав!$I$2:$I$80),2),"") -> 841.44 | H11: =SUMPRODUCT((04_Комплектность!$B$2:$B$178=A11)*(((04_Комплектность!$D$2:$D$178<>"CLOSED")+(04_Комплектность!$E$2:$E$178="")+(04_Комплектность!$G$2:$G$178=""))>0)) -> 4 | I11: =COUNTIFS(03_Состав!$B$2:$B$80,A11,03_Состав!$K$2:$K$80,"BLOCK") -> 3 | J11: NOT_CHECKED | K11: PUBLIC_ONLY | L11: =IF(AND(E11>0,E11=F11,H11=0,I11=0,J11="PASS",K11="CONFIRMED_FULL"),G11,"") | S11: =IF(AND(ISNUMBER(L11),COUNT(M11:R11)=6),ROUND(SUM(L11:R11),2),"") | T11: =IF(AND(V11="CONFIRMED_ALL_DOCUMENTS",COUNTIF(06_НДС!$B$2:$B$1000,A11)>0,COUNTIFS(06_НДС!$B$2:$B$1000,A11,06_НДС!$S$2:$S$1000,"<>CALCULATED_WITH_INPUTS")=0),ROUND(SUMIF(06_НДС!$B$2:$B$1000,A11,06_НДС!$M$2:$M$1000),2),"") | U11: =IF(AND(ISNUMBER(S11),ISNUMBER(T11)),ROUND(S11+T11,2),"") | V11: OPEN | W11: NOT_SELECTED | X11: Уточнение 115 ампер/А·ч и напряжения каждой АКБ ожидается. Пусковые токи, химия и допустимый разряд открыты. Измеренная компоновка, монтажные и сервисные зоны, полный состав поставки и интерфейсы ещё требуют подтверждения. | Y11: =IF(ISNUMBER(U11),"CALCULATED_FOR_REVIEW","DRAFT_OPEN") -> DRAFT_OPEN
A12: PK04-B | B12: PK04 | C12: ALS12115 12V115Ah + UNSIZED + UNSIZED + ML-RBS7702 24V | D12: 6 сервисных + 2 генераторных + 1 главного двигателя | E12: =COUNTIF(03_Состав!$B$2:$B$80,A12) -> 4 | F12: =SUMPRODUCT((03_Состав!$B$2:$B$80=A12)*ISNUMBER(03_Состав!$I$2:$I$80)) -> 1 | G12: =IF(F12>0,ROUND(SUMIF(03_Состав!$B$2:$B$80,A12,03_Состав!$I$2:$I$80),2),"") -> 1608.42 | H12: =SUMPRODUCT((04_Комплектность!$B$2:$B$178=A12)*(((04_Комплектность!$D$2:$D$178<>"CLOSED")+(04_Комплектность!$E$2:$E$178="")+(04_Комплектность!$G$2:$G$178=""))>0)) -> 4 | I12: =COUNTIFS(03_Состав!$B$2:$B$80,A12,03_Состав!$K$2:$K$80,"BLOCK") -> 3 | J12: NOT_CHECKED | K12: PUBLIC_ONLY | L12: =IF(AND(E12>0,E12=F12,H12=0,I12=0,J12="PASS",K12="CONFIRMED_FULL"),G12,"") | S12: =IF(AND(ISNUMBER(L12),COUNT(M12:R12)=6),ROUND(SUM(L12:R12),2),"") | T12: =IF(AND(V12="CONFIRMED_ALL_DOCUMENTS",COUNTIF(06_НДС!$B$2:$B$1000,A12)>0,COUNTIFS(06_НДС!$B$2:$B$1000,A12,06_НДС!$S$2:$S$1000,"<>CALCULATED_WITH_INPUTS")=0),ROUND(SUMIF(06_НДС!$B$2:$B$1000,A12,06_НДС!$M$2:$M$1000),2),"") | U12: =IF(AND(ISNUMBER(S12),ISNUMBER(T12)),ROUND(S12+T12,2),"") | V12: OPEN | W12: NOT_SELECTED | X12: Уточнение 115 ампер/А·ч и напряжения каждой АКБ ожидается. Пусковые токи, химия и допустимый разряд открыты. Измеренная компоновка, монтажные и сервисные зоны, полный состав поставки и интерфейсы ещё требуют подтверждения. | Y12: =IF(ISNUMBER(U12),"CALCULATED_FOR_REVIEW","DRAFT_OPEN") -> DRAFT_OPEN
A13: PK04-C | B13: PK04 | C13: AGM Telecom115Ah M8 BAT412105164 + UNSIZED + UNSIZED + ML-RBS7702 24V | D13: 6 сервисных + 2 генераторных + 1 главного двигателя | E13: =COUNTIF(03_Состав!$B$2:$B$80,A13) -> 4 | F13: =SUMPRODUCT((03_Состав!$B$2:$B$80=A13)*ISNUMBER(03_Состав!$I$2:$I$80)) -> 1 | G13: =IF(F13>0,ROUND(SUMIF(03_Состав!$B$2:$B$80,A13,03_Состав!$I$2:$I$80),2),"") -> 1636.14 | H13: =SUMPRODUCT((04_Комплектность!$B$2:$B$178=A13)*(((04_Комплектность!$D$2:$D$178<>"CLOSED")+(04_Комплектность!$E$2:$E$178="")+(04_Комплектность!$G$2:$G$178=""))>0)) -> 4 | I13: =COUNTIFS(03_Состав!$B$2:$B$80,A13,03_Состав!$K$2:$K$80,"BLOCK") -> 3 | J13: NOT_CHECKED | K13: PUBLIC_ONLY | L13: =IF(AND(E13>0,E13=F13,H13=0,I13=0,J13="PASS",K13="CONFIRMED_FULL"),G13,"") | S13: =IF(AND(ISNUMBER(L13),COUNT(M13:R13)=6),ROUND(SUM(L13:R13),2),"") | T13: =IF(AND(V13="CONFIRMED_ALL_DOCUMENTS",COUNTIF(06_НДС!$B$2:$B$1000,A13)>0,COUNTIFS(06_НДС!$B$2:$B$1000,A13,06_НДС!$S$2:$S$1000,"<>CALCULATED_WITH_INPUTS")=0),ROUND(SUMIF(06_НДС!$B$2:$B$1000,A13,06_НДС!$M$2:$M$1000),2),"") | U13: =IF(AND(ISNUMBER(S13),ISNUMBER(T13)),ROUND(S13+T13,2),"") | V13: OPEN | W13: NOT_SELECTED | X13: Уточнение 115 ампер/А·ч и напряжения каждой АКБ ожидается. Пусковые токи, химия и допустимый разряд открыты. Измеренная компоновка, монтажные и сервисные зоны, полный состав поставки и интерфейсы ещё требуют подтверждения. | Y13: =IF(ISNUMBER(U13),"CALCULATED_FOR_REVIEW","DRAFT_OPEN") -> DRAFT_OPEN
... A37: PK12-C | B37: PK12 | C37: Hydro 2 | D37: Гидропривод обязателен; число потребителей не принято | E37: =COUNTIF(03_Состав!$B$2:$B$80,A37) -> 1 | F37: =SUMPRODUCT((03_Состав!$B$2:$B$80=A37)*ISNUMBER(03_Состав!$I$2:$I$80)) -> 0 | G37: =IF(F37>0,ROUND(SUMIF(03_Состав!$B$2:$B$80,A37,03_Состав!$I$2:$I$80),2),"") | H37: =SUMPRODUCT((04_Комплектность!$B$2:$B$178=A37)*(((04_Комплектность!$D$2:$D$178<>"CLOSED")+(04_Комплектность!$E$2:$E$178="")+(04_Комплектность!$G$2:$G$178=""))>0)) -> 5 | I37: =COUNTIFS(03_Состав!$B$2:$B$80,A37,03_Состав!$K$2:$K$80,"BLOCK") -> 1 | J37: NOT_CHECKED | K37: PUBLIC_ONLY | L37: =IF(AND(E37>0,E37=F37,H37=0,I37=0,J37="PASS",K37="CONFIRMED_FULL"),G37,"") | S37: =IF(AND(ISNUMBER(L37),COUNT(M37:R37)=6),ROUND(SUM(L37:R37),2),"") | T37: =IF(AND(V37="CONFIRMED_ALL_DOCUMENTS",COUNTIF(06_НДС!$B$2:$B$1000,A37)>0,COUNTIFS(06_НДС!$B$2:$B$1000,A37,06_НДС!$S$2:$S$1000,"<>CALCULATED_WITH_INPUTS")=0),ROUND(SUMIF(06_НДС!$B$2:$B$1000,A37,06_НДС!$M$2:$M$1000),2),"") | U37: =IF(AND(ISNUMBER(S37),ISNUMBER(T37)),ROUND(S37+T37,2),"") | V37: OPEN | W37: NOT_SELECTED | X37: Тяга, момент, скорость, одновременность и источники мощности открыты. Измеренная компоновка, монтажные и сервисные зоны, полный состав поставки и интерфейсы ещё требуют подтверждения. | Y37: =IF(ISNUMBER(U37),"CALCULATED_FOR_REVIEW","DRAFT_OPEN") -> DRAFT_OPEN

Sheet 06_НДС
A1: Налоговая строка | B1: Вариант | C1: Счёт / операция / компоненты | D1: Покупатель / VAT статус | E1: Фактическая отправка | F1: Страна VAT / импортёр | G1: Режим | H1: Налоговая база EUR | I1: Ставка % | J1: Начисленный VAT EUR | K1: Подтверждённая доля вычета % | L1: VAT к вычету EUR | M1: Невозмещаемый VAT EUR | N1: VAT: денежный платёж EUR | O1: Ожидаемый денежный возврат EUR | P1: Дата оплаты | Q1: Дата возврата / зачёта | R1: Правовое и документальное основание | S1: Контроль расчёта
A2: TAX-PK01-A | B2: PK01-A | J2: =IF(AND(ISNUMBER(H2),H2>=0,ISNUMBER(I2),I2>=0,I2<=100),ROUND(H2*I2/100,2),"") | L2: =IF(AND(ISNUMBER(J2),ISNUMBER(K2),K2>=0,K2<=100),ROUND(J2*K2/100,2),"") | M2: =IF(AND(ISNUMBER(J2),ISNUMBER(L2)),ROUND(J2-L2,2),"") | S2: =IF(AND(C2<>"",D2<>"",E2<>"",F2<>"",G2<>"",R2<>"",ISNUMBER(M2)),"CALCULATED_WITH_INPUTS","OPEN") -> OPEN
A3: TAX-PK01-B | B3: PK01-B | J3: =IF(AND(ISNUMBER(H3),H3>=0,ISNUMBER(I3),I3>=0,I3<=100),ROUND(H3*I3/100,2),"") | L3: =IF(AND(ISNUMBER(J3),ISNUMBER(K3),K3>=0,K3<=100),ROUND(J3*K3/100,2),"") | M3: =IF(AND(ISNUMBER(J3),ISNUMBER(L3)),ROUND(J3-L3,2),"") | S3: =IF(AND(C3<>"",D3<>"",E3<>"",F3<>"",G3<>"",R3<>"",ISNUMBER(M3)),"CALCULATED_WITH_INPUTS","OPEN") -> OPEN
A4: TAX-PK01-C | B4: PK01-C | J4: =IF(AND(ISNUMBER(H4),H4>=0,ISNUMBER(I4),I4>=0,I4<=100),ROUND(H4*I4/100,2),"") | L4: =IF(AND(ISNUMBER(J4),ISNUMBER(K4),K4>=0,K4<=100),ROUND(J4*K4/100,2),"") | M4: =IF(AND(ISNUMBER(J4),ISNUMBER(L4)),ROUND(J4-L4,2),"") | S4: =IF(AND(C4<>"",D4<>"",E4<>"",F4<>"",G4<>"",R4<>"",ISNUMBER(M4)),"CALCULATED_WITH_INPUTS","OPEN") -> OPEN
A5: TAX-PK02-A | B5: PK02-A | J5: =IF(AND(ISNUMBER(H5),H5>=0,ISNUMBER(I5),I5>=0,I5<=100),ROUND(H5*I5/100,2),"") | L5: =IF(AND(ISNUMBER(J5),ISNUMBER(K5),K5>=0,K5<=100),ROUND(J5*K5/100,2),"") | M5: =IF(AND(ISNUMBER(J5),ISNUMBER(L5)),ROUND(J5-L5,2),"") | S5: =IF(AND(C5<>"",D5<>"",E5<>"",F5<>"",G5<>"",R5<>"",ISNUMBER(M5)),"CALCULATED_WITH_INPUTS","OPEN") -> OPEN
A6: TAX-PK02-B | B6: PK02-B | J6: =IF(AND(ISNUMBER(H6),H6>=0,ISNUMBER(I6),I6>=0,I6<=100),ROUND(H6*I6/100,2),"") | L6: =IF(AND(ISNUMBER(J6),ISNUMBER(K6),K6>=0,K6<=100),ROUND(J6*K6/100,2),"") | M6: =IF(AND(ISNUMBER(J6),ISNUMBER(L6)),ROUND(J6-L6,2),"") | S6: =IF(AND(C6<>"",D6<>"",E6<>"",F6<>"",G6<>"",R6<>"",ISNUMBER(M6)),"CALCULATED_WITH_INPUTS","OPEN") -> OPEN
A7: TAX-PK02-C | B7: PK02-C | J7: =IF(AND(ISNUMBER(H7),H7>=0,ISNUMBER(I7),I7>=0,I7<=100),ROUND(H7*I7/100,2),"") | L7: =IF(AND(ISNUMBER(J7),ISNUMBER(K7),K7>=0,K7<=100),ROUND(J7*K7/100,2),"") | M7: =IF(AND(ISNUMBER(J7),ISNUMBER(L7)),ROUND(J7-L7,2),"") | S7: =IF(AND(C7<>"",D7<>"",E7<>"",F7<>"",G7<>"",R7<>"",ISNUMBER(M7)),"CALCULATED_WITH_INPUTS","OPEN") -> OPEN
A8: TAX-PK03-A | B8: PK03-A | J8: =IF(AND(ISNUMBER(H8),H8>=0,ISNUMBER(I8),I8>=0,I8<=100),ROUND(H8*I8/100,2),"") | L8: =IF(AND(ISNUMBER(J8),ISNUMBER(K8),K8>=0,K8<=100),ROUND(J8*K8/100,2),"") | M8: =IF(AND(ISNUMBER(J8),ISNUMBER(L8)),ROUND(J8-L8,2),"") | S8: =IF(AND(C8<>"",D8<>"",E8<>"",F8<>"",G8<>"",R8<>"",ISNUMBER(M8)),"CALCULATED_WITH_INPUTS","OPEN") -> OPEN
A9: TAX-PK03-B | B9: PK03-B | J9: =IF(AND(ISNUMBER(H9),H9>=0,ISNUMBER(I9),I9>=0,I9<=100),ROUND(H9*I9/100,2),"") | L9: =IF(AND(ISNUMBER(J9),ISNUMBER(K9),K9>=0,K9<=100),ROUND(J9*K9/100,2),"") | M9: =IF(AND(ISNUMBER(J9),ISNUMBER(L9)),ROUND(J9-L9,2),"") | S9: =IF(AND(C9<>"",D9<>"",E9<>"",F9<>"",G9<>"",R9<>"",ISNUMBER(M9)),"CALCULATED_WITH_INPUTS","OPEN") -> OPEN
A10: TAX-PK03-C | B10: PK03-C | J10: =IF(AND(ISNUMBER(H10),H10>=0,ISNUMBER(I10),I10>=0,I10<=100),ROUND(H10*I10/100,2),"") | L10: =IF(AND(ISNUMBER(J10),ISNUMBER(K10),K10>=0,K10<=100),ROUND(J10*K10/100,2),"") | M10: =IF(AND(ISNUMBER(J10),ISNUMBER(L10)),ROUND(J10-L10,2),"") | S10: =IF(AND(C10<>"",D10<>"",E10<>"",F10<>"",G10<>"",R10<>"",ISNUMBER(M10)),"CALCULATED_WITH_INPUTS","OPEN") -> OPEN
A11: TAX-PK04-A | B11: PK04-A | J11: =IF(AND(ISNUMBER(H11),H11>=0,ISNUMBER(I11),I11>=0,I11<=100),ROUND(H11*I11/100,2),"") | L11: =IF(AND(ISNUMBER(J11),ISNUMBER(K11),K11>=0,K11<=100),ROUND(J11*K11/100,2),"") | M11: =IF(AND(ISNUMBER(J11),ISNUMBER(L11)),ROUND(J11-L11,2),"") | S11: =IF(AND(C11<>"",D11<>"",E11<>"",F11<>"",G11<>"",R11<>"",ISNUMBER(M11)),"CALCULATED_WITH_INPUTS","OPEN") -> OPEN
A12: TAX-PK04-B | B12: PK04-B | J12: =IF(AND(ISNUMBER(H12),H12>=0,ISNUMBER(I12),I12>=0,I12<=100),ROUND(H12*I12/100,2),"") | L12: =IF(AND(ISNUMBER(J12),ISNUMBER(K12),K12>=0,K12<=100),ROUND(J12*K12/100,2),"") | M12: =IF(AND(ISNUMBER(J12),ISNUMBER(L12)),ROUND(J12-L12,2),"") | S12: =IF(AND(C12<>"",D12<>"",E12<>"",F12<>"",G12<>"",R12<>"",ISNUMBER(M12)),"CALCULATED_WITH_INPUTS","OPEN") -> OPEN
A13: TAX-PK04-C | B13: PK04-C | J13: =IF(AND(ISNUMBER(H13),H13>=0,ISNUMBER(I13),I13>=0,I13<=100),ROUND(H13*I13/100,2),"") | L13: =IF(AND(ISNUMBER(J13),ISNUMBER(K13),K13>=0,K13<=100),ROUND(J13*K13/100,2),"") | M13: =IF(AND(ISNUMBER(J13),ISNUMBER(L13)),ROUND(J13-L13,2),"") | S13: =IF(AND(C13<>"",D13<>"",E13<>"",F13<>"",G13<>"",R13<>"",ISNUMBER(M13)),"CALCULATED_WITH_INPUTS","OPEN") -> OPEN
... A37: TAX-PK12-C | B37: PK12-C | J37: =IF(AND(ISNUMBER(H37),H37>=0,ISNUMBER(I37),I37>=0,I37<=100),ROUND(H37*I37/100,2),"") | L37: =IF(AND(ISNUMBER(J37),ISNUMBER(K37),K37>=0,K37<=100),ROUND(J37*K37/100,2),"") | M37: =IF(AND(ISNUMBER(J37),ISNUMBER(L37)),ROUND(J37-L37,2),"") | S37: =IF(AND(C37<>"",D37<>"",E37<>"",F37<>"",G37<>"",R37<>"",ISNUMBER(M37)),"CALCULATED_WITH_INPUTS","OPEN") -> OPEN

Sheet 07_Открытые вопросы
A1: Пакет | B1: Результат | C1: Требуется для допуска | D1: Первое действие
A2: PK01 | B2: Ход яхты | C2: 300 л.с. — исходный ориентир. Скорость, сопротивление, рабочий режим и PTO не рассчитаны. Измеренная компоновка, монтажные и сервисные зоны, полный состав поставки и интерфейсы ещё требуют подтверждения. | D2: Согласовать требуемый выход, проверить обслуживаемую компоновку и полный BOM; запросить недостающие основания.
A3: PK02 | B3: Генерация | C3: Около 11.5–12 кВА — исходный ориентир. Постоянные и пиковые нагрузки, режим отказа открыты. Измеренная компоновка, монтажные и сервисные зоны, полный состав поставки и интерфейсы ещё требуют подтверждения. | D3: Согласовать требуемый выход, проверить обслуживаемую компоновку и полный BOM; запросить недостающие основания.
A4: PK03 | B4: Электропитание | C4: 3 кВА — поисковый класс, не утверждённая мощность. Баланс и береговой ввод открыты. Измеренная компоновка, монтажные и сервисные зоны, полный состав поставки и интерфейсы ещё требуют подтверждения. | D4: Согласовать требуемый выход, проверить обслуживаемую компоновку и полный BOM; запросить недостающие основания.
A5: PK04 | B5: АКБ и резервный пуск | C5: Уточнение 115 ампер/А·ч и напряжения каждой АКБ ожидается. Пусковые токи, химия и допустимый разряд открыты. Измеренная компоновка, монтажные и сервисные зоны, полный состав поставки и интерфейсы ещё требуют подтверждения. | D5: Согласовать требуемый выход, проверить обслуживаемую компоновку и полный BOM; запросить недостающие основания.
A6: PK05 | B6: Пресная вода | C6: Рабочая точка и одновременность водоразбора открыты. 15 л/мин при 2 бар — только поисковый пример. Измеренная компоновка, монтажные и сервисные зоны, полный состав поставки и интерфейсы ещё требуют подтверждения. | D6: Согласовать требуемый выход, проверить обслуживаемую компоновку и полный BOM; запросить недостающие основания.
A7: PK06 | B7: Опреснение | C7: Температура, солёность и окончательная комплектация открыты. Измеренная компоновка, монтажные и сервисные зоны, полный состав поставки и интерфейсы ещё требуют подтверждения. | D7: Согласовать требуемый выход, проверить обслуживаемую компоновку и полный BOM; запросить недостающие основания.
A8: PK07 | B8: Горячая вода | C8: 40 л / 1200 Вт — рыночный пример, не заданная потребность. Измеренная компоновка, монтажные и сервисные зоны, полный состав поставки и интерфейсы ещё требуют подтверждения. | D8: Согласовать требуемый выход, проверить обслуживаемую компоновку и полный BOM; запросить недостающие основания.
A9: PK08 | B9: Климат | C9: 16 000 BTU/h на модуль — пример рынка. Тепловой расчёт и уровень сервиса при отказе открыты. Измеренная компоновка, монтажные и сервисные зоны, полный состав поставки и интерфейсы ещё требуют подтверждения. | D9: Согласовать требуемый выход, проверить обслуживаемую компоновку и полный BOM; запросить недостающие основания.
A10: PK09 | B10: Обеспечение МО | C10: Диаметры, тепловыделение, напор, длины и комплектность открыты. Измеренная компоновка, монтажные и сервисные зоны, полный состав поставки и интерфейсы ещё требуют подтверждения. | D10: Согласовать требуемый выход, проверить обслуживаемую компоновку и полный BOM; запросить недостающие основания.
A11: PK10 | B11: Аварийные системы | C11: Отсеки, защищаемый объём и аварийные режимы открыты. Измеренная компоновка, монтажные и сервисные зоны, полный состав поставки и интерфейсы ещё требуют подтверждения. | D11: Согласовать требуемый выход, проверить обслуживаемую компоновку и полный BOM; запросить недостающие основания.
A12: PK11 | B12: Танки и стоки | C12: Конструкция встроенных танков, уровни и маршруты доступа открыты. Измеренная компоновка, монтажные и сервисные зоны, полный состав поставки и интерфейсы ещё требуют подтверждения. | D12: Согласовать требуемый выход, проверить обслуживаемую компоновку и полный BOM; запросить недостающие основания.
A13: PK12 | B13: Гидравлика | C13: Тяга, момент, скорость, одновременность и источники мощности открыты. Измеренная компоновка, монтажные и сервисные зоны, полный состав поставки и интерфейсы ещё требуют подтверждения. | D13: Согласовать требуемый выход, проверить обслуживаемую компоновку и полный BOM; запросить недостающие основания.
