Workbook

Sheet 00_Старт
A1: VDS67 • Шаблон будущей УТВ
A2: Синие ячейки — ввод; серые — формулы. Пусто = нет данных. Код строки сохранять при сортировке.
A3: Раздел | B3: Порядок работы / правило
A4: Статус | B4: TEMPLATE / INCOMPLETE. УТВ возникает после отдельного решения владельца о базовом бюджете.
A5: 1. Основания | B5: Установить границу остатка достройки, валюту, налоговую основу, дату цен и ревизию проекта.
A6: 2. Состав | B6: WBS — системы яхты. Строки сметы разворачивать по ресурсам/работам; один пакет может содержать несколько строк.
A7: 3. Пакеты | B7: Сначала составить одинаковые задания RFQ с границами поставки, монтажа и испытаний.
A8: 4. КП | B8: Регистрировать документы и исходные строки без изменения оригиналов.
A9: 5. КАЦ | B9: Сначала техническая сопоставимость, затем единицы, валюта, налоги и исключённые работы. Автоматического выбора минимальной цены нет.
A10: 6. Смета | B10: Цена из выбранной КАЦ (KAC) или обоснованной оценки без КП (DIRECT). Количество и источник отдельно; выбор КАЦ единственный в группе.
A11: 7. Сводка | B11: Показывает только известную часть и незаполненные позиции. Пустые суммы не равны нулю. Полнота состава отдельно проверяется.
A12: Существующее | B12: Наличие, поставщик и граница затрат — разные поля. Имеющийся корпус не считать новой покупкой по умолчанию.
A13: Ноль | B13: Числовой 0 допустим с подтверждением; UNKNOWN и NOT_APPLICABLE не вводить в денежные клетки.
A14: Двойной счёт | B14: Включённые монтаж, доставка и испытания не добавлять повторно. Вести лист Стыки и ссылку на покрывающую строку.
... A20: Модель | B20: EXP-003 — принятая стартовая идея. Производственные объёмы, мощность оборудования и размеры из неё не утверждены.

Sheet 01_Основания
A1: Основания будущего бюджета
A2: Синие ячейки — ввод; серые — формулы. Пусто = нет данных. Код строки сохранять при сортировке.
A3: Поле | B3: Значение | C3: Источник / решение
A4: Проект | B4: VDS67 | C4: office/project.json
A5: Стройка | B5: Польша | C5: Решение владельца
A6: Статус | B6: TEMPLATE / INCOMPLETE | C6: Утверждение бюджета отсутствует
A7: Граница бюджета | B7: Остаток достройки; понесённое отдельно | C7: Уточнить перечень имущества и ранее оплаченного
A8: Базовая валюта
A9: Налоговая основа NET/GROSS
A10: Дата цен
A11: Ревизия проекта
A12: Владелец / заказчик
A13: Верфь / место передачи
A14: Налоговый режим / обоснование
A15: Курс: базовая валюта за1 валюты КП
A16: Решение об утверждении УТВ
A17: Дата утверждения
A18: Полнота состава проверена
A19: Правило округления | B19: Строка0.01; сумма округлённых строк | C19: Проверить договорные требования
A20: Версия шаблона | B20: U01/v001 | C20: Пустой инструмент; для заполнения копия
A21: Рабочая копия / ответственный
A22: Флаг / эксплуатация / применимость

Sheet 02_WBS
A1: Структура работ и систем яхты
A2: Синие ячейки — ввод; серые — формулы. Пусто = нет данных. Код строки сохранять при сортировке.
A3: WBS | B3: Родитель | C3: Раздел / пакет | D3: Входит | E3: Граница / исключено | F3: Нужные исходные данные | G3: Применимость | H3: Ответственный
A4: W00 | C4: Управление проектом | D4: Задание, бюджет, координация и документы | E4: См. дочерние пакеты | F4: Установить состав и ревизию | G4: REVIEW_REQUIRED
A5: W00.10 | B5: W00 | C5: Управление и координация проекта | D5: Планирование, ведение бюджета и документов, координация исполнителей | E5: Техническое проектирование W02; включённые накладные подрядчиков | F5: Организация проекта; состав услуг и договоры | G5: REVIEW_REQUIRED
A6: W01 | C6: Исходники и обследование | D6: Получение документов, обмер и состояние существующего | E6: См. дочерние пакеты | F6: Установить состав и ревизию | G6: REVIEW_REQUIRED
A7: W01.10 | B7: W01 | C7: Приёмка существующего корпуса и документов | D7: Реестр фактически имеющегося, ревизии, фотофиксация, права использования чертежей; отделение поставленного владельцем от недостающего | E7: Повторная покупка существующего корпуса; ремонт и достройка | F7: Передаточные документы; перечень имущества; происхождение и ревизии CAD | G7: REVIEW_REQUIRED
A8: W01.20 | B8: W01 | C8: Обмер, контроль состояния и дефектная ведомость | D8: Геометрия и толщины по программе обследования, доступные сварные соединения, коррозия, фактические переборки/фундаменты/танки | E8: Ремонт выявленного; производственный контроль новых швов | F8: Доступ к корпусу; программа обследования; квалификация исполнителей | G8: REVIEW_REQUIRED
A9: W02 | C9: Проектирование и применимость требований | D9: Расчётные задания, решения и необходимые согласования | E9: См. дочерние пакеты | F9: Установить состав и ревизию | G9: REVIEW_REQUIRED
A10: W02.10 | B10: W02 | C10: Базовая геометрия, компоновка и расчётная координация | D10: Сверка CAD и обмеров, общий вид/сечения, массы и центры, гидростатика/остойчивость, согласование геометрии всех дисциплин | E10: Серийное оборудование; повторное включение проектирования из пакетов поставщика | F10: Назначение и режим эксплуатации; обмер; выбранные варианты; применимые требования | G10: REVIEW_REQUIRED
A11: W02.20 | B11: W02 | C11: Проект конструкции и изменений | D11: Корпус, рубка, hardtop, мачтовая опора, кормовой гараж, фальшборт, проёмы/подкрепления; рабочие чертежи | E11: Материалы и изготовление W10; EXP-003 не рабочий проект | F11: Расчётные нагрузки; состояние корпуса; утверждённая конструктивная схема; ревизии | G11: REVIEW_REQUIRED
A12: W02.30 | B12: W02 | C12: Интерьерный проект и макеты помещаемости | D12: Раскладки помещений, чистые высоты, макеты критических проходов/мебели/мокрых зон, спецификации отделки | E12: Серийная мебель и её монтаж; повторение общей CAD координации | F12: Цель 3+1 каюты/санузлы; геометрия; сервисные габариты оборудования; образцы отделки | G12: REVIEW_REQUIRED
A13: W02.40 | B13: W02 | C13: Применимость требований и согласования | D13: Маршрут оценки соответствия, технический файл и необходимые внешние проверки по установленному флагу и эксплуатации | E13: Согласования не назначены автоматически; инженерная разработка в W02.10–30 | F13: Статус корпуса; флаг; режим эксплуатации; требования компетентных организаций | G13: REVIEW_REQUIRED
A14: W10 | C14: Корпус и конструкция | D14: Существующее, доработки и подтверждённые объёмы конструкции | E14: См. дочерние пакеты | F14: Установить состав и ревизию | G14: REVIEW_REQUIRED
A15: W10.10 | B15: W10 | C15: Ремонт и завершение исходного корпуса | D15: Только подтверждённые дефекты/недоделки: обшивка, набор, переборки, сварка, локальный производственный контроль | E15: Стоимость уже имеющегося корпуса; будущие изменения W10.20–40; покрытия W10.70–80 | F15: Дефектная ведомость; перечень выполненного; чертежи; программа контроля | G15: REVIEW_REQUIRED
A16: W10.20 | B16: W10 | C16: Новая рубка и hardtop | D16: Конструктивный металл, набор, опоры, крыша, переходы и сварка; геометрическая стартовая идея EXP-003 после переработки | E16: Остекление W20.10; интерьер W60; электрические/жидкостные сети; смета по массе визуальной сетки | F16: Рабочие чертежи; нагрузки мачты/гика; чистые высоты; ведомость металла | G16: REVIEW_REQUIRED
A17: W10.30 | B17: W10 | C17: Корма, гараж и встроенная дверь | D17: Изменение обшивки/набора, конструктивный объём гаража, силовая дверь/рама, переборки и корпусные усиления | E17: Тендер/балка W20.70–80; привод двери W20.80; отделка и системы | F17: Выбранный тендер; траектория; чертежи; нагрузки; водонепроницаемость; существующие отсеки | G17: REVIEW_REQUIRED
A18: W10.40 | B18: W10 | C18: Фальшборт, корпусные вырезы и проходы | D18: Добавка фальшборта, конструктивные кромки отверстий, приварные комингсы, встроенные подкрепления; корпусные шпигаты/штормовые портики и их конструктивное обрамление по проекту без назначения размеров | E18: Съёмные клюзы/утки/релинги W20; трубные системы палубного отвода и стоков W50; уже включённые в W10.20–30 отверстия; интегральные танки W10.90; аноды W10.85 | F18: Утверждённый периметр; узлы; водоотвод; координаты швартовного оборудования | G18: REVIEW_REQUIRED
A19: W10.50 | B19: W10 | C19: Корпусные фундаменты и встроенные опоры | D19: Приварные силовые основания двигателя/агрегатов/мачты/балки/оборудования, закладные и конструктивные проходки по единой ведомости | E19: Рамы в составе купленного агрегата; виброопоры и окончательная установка систем; уже включённые в другие W10 позиции | F19: Ведомость нагрузок и координат; граница заводского комплекта; интерфейсные листы | G19: REVIEW_REQUIRED
A20: W10.60 | B20: W10 | C20: Киль, балласт и корпусные элементы рулевого узла | D20: Проверка наличия, недостающая поставка/установка киля и балласта, корпусные опоры и трубы рулевого узла по проекту | E20: Рулевая машина/перья/подшипники если отнесены W30; не подтверждённые тип/масса балласта | F20: Исполнительные данные; выбранная конструкция; массы; комплектность; граница W30 | G20: REVIEW_REQUIRED
A21: W10.70 | B21: W10 | C21: Наружные покрытия корпуса и надстройки | D21: Подготовка алюминия, выравнивание по согласованным зонам, грунты/барьеры, наружный финиш, подводная система, локальная окраска после монтажа | E21: Палубный настил W20.30; заводское покрытие оборудования; двойной учёт ремонтной подкраски | F21: Карты площадей; требования к поверхности; выбранная совместимая система; климат нанесения | G21: REVIEW_REQUIRED
A22: W10.80 | B22: W10 | C22: Внутренние защитные покрытия | D22: Выбранные внутренние зоны корпуса, льяла и защищаемые металлические поверхности, подготовка и контроль нанесения | E22: Окраска мебельных деталей W60; заводское покрытие агрегатов; автоматически вся площадь алюминия | F22: Карта зон и доступа; спецификация покрытий; последовательность до изоляции | G22: REVIEW_REQUIRED
A23: W10.85 | B23: W10 | C23: Аноды и наружные элементы противокоррозионной защиты | D23: Аноды, их корпусные крепления и установка по проекту защиты алюминиевого корпуса | E23: Электрические защитные соединения и развязка W40.25; покрытия W10.70–80 | F23: Проект защиты; материалы смежных узлов; условия эксплуатации | G23: REVIEW_REQUIRED
A24: W10.90 | B24: W10 | C24: Интегральные сварные танки — условный пакет | D24: Изготовление встроенных танков, корпусные стенки/люки и испытание герметичности до подключения системы | E24: Покупные съёмные ёмкости и трубная обвязка W50; повторное начисление испытаний всей системы | F24: Решение о типе и материале танков; объёмы; чертежи; программа испытаний | G24: REVIEW_REQUIRED
A25: W20 | C25: Рангоут и палуба | D25: Пакеты систем Rig и Deck исходной базы | E25: См. дочерние пакеты | F25: Установить состав и ревизию | G25: REVIEW_REQUIRED
A26: W20.10 | B26: W20 | C26: Наружное остекление, люки и закрытия | D26: Изделия, рамки, стекло/прозрачные панели, уплотнение, крепёж, установка и локальный тест герметичности; наружные двери кроме силовой гаражной | E26: Приварные комингсы W10; шторы W60; силовая дверь гаража W10.30; непринятый материал тёмного стекла | F26: Ведомость проёмов; нагрузки; открывание/выходы; кривизна; оптические требования; монтажный узел | G26: REVIEW_REQUIRED
A27: W20.20 | B27: W20 | C27: Палубная металлическая арматура и швартовка | D27: Релинги/леера, поручни, утки, клюзы, трапы и съёмные детали: поставка, крепёж, установка | E27: Конструктивный фальшборт/подкрепления W10; якорная лебёдка W20.40; спасательные леера отдельно W70 если так назначено | F27: План палубы; нагрузки; электрическая изоляция соединений; чистые проходы | G27: REVIEW_REQUIRED
A28: W20.30 | B28: W20 | C28: Палубные настилы и наружная обивка | D28: Выбранный нескользящий настил или покрытие по раздельным зонам, наружные подушки/чехлы, посадочные поверхности | E28: Подготовка и окраска под настилом W10.70 если включена туда; интерьерная мягкая мебель W60 | F28: Карта зон; материал; масса; дренаж; уход; граница подготовки поверхности | G28: REVIEW_REQUIRED
A29: W20.40 | B29: W20 | C29: Якорное оборудование | D29: Якоря, цепь/канат, лебёдка, стопоры, ролики, направляющие: поставка и механический монтаж | E29: Корпус якорного колодца/подкрепления W10; питание W40; слив W50 | F29: Сценарий якорения; выбранные массы/цепь; падение цепи; места; граница электрического комплекта | G29: REVIEW_REQUIRED
A30: W20.50 | B30: W20 | C30: Рангоут и стоячий такелаж | D30: Мачта/гик, стоячий такелаж, оконцеватели и серийный степс, монтаж, настройка и собственные проверки | E30: Силовая опора корпуса W10.50; электрическая разводка мачты W40; общий спуск W90; паруса | F30: Парусный план; нагрузки; мачтовая схема; перечень включённого поставщиком; крановый план | G30: REVIEW_REQUIRED
A31: W20.55 | B31: W20 | C31: Бегучий такелаж и управление парусами | D31: Шкоты/фалы, блоки, погоны, каретки, лебёдки и закрутки: комплекты, монтаж, настройка | E31: Стоячий такелаж W20.50; центральная гидростанция/сеть W50 если назначена там; питание W40 | F31: Схема проводки; тип приводов; состав комплекта; рабочие зоны и усилия | G31: REVIEW_REQUIRED
A32: W20.60 | B32: W20 | C32: Паруса и их принадлежности | D32: Выбранный комплект парусов, чехлы/мешки, измерение под рангоут, доставка и примерка | E32: Неутверждённые площади как закупочные объёмы; бегучий такелаж; общесудовые ходовые испытания | F32: Окончательный парусный план; материал; комплектация; ветровые сценарии; согласование с рангоутом | G32: REVIEW_REQUIRED
A33: W20.70 | B33: W20 | C33: Тендер и его штатное оснащение | D33: Одна выбранная комплектация тендера, штатные принадлежности, передаточная проверка | E33: Гараж W10.30; балка/крепления W20.80; автоматический выбор Williams по названию типа | F33: Модель/масса в рабочем состоянии; габариты; способ хранения; комплектация и документы | G33: REVIEW_REQUIRED
A34: W20.80 | B34: W20 | C34: Подъём и размещение тендера, механизация гаража | D34: Кран-балка, тележка/стропы, ложемент, крепление в море, привод двери, локальная механика и собственные испытания | E34: Силовые корпусные основания/дверь W10; тендер W20.70; общая сеть гидравлики/питания вне локального комплекта | F34: Траектория и режимы; рабочая масса; опорные реакции; состав привода; аварийное закрытие; границы поставки | G34: REVIEW_REQUIRED
A35: W30 | C35: Движение и управление | D35: Propulsion, Steering и Thruster | E35: См. дочерние пакеты | F35: Установить состав и ревизию | G35: REVIEW_REQUIRED
A36: W30.10 | B36: W30 | C36: Главный двигатель и его установка | D36: Агрегат с редуктором по будущей комплектности; штатные приборы и локальные системы; монтаж, выверка и первичная проверка исполнителя. | E36: Изготовление корпусного фундамента W10; валопровод W30.20; общесудовое топливо W50.10; вентиляция W50.75; общие испытания W80. | F36: Утверждённая пропульсивная концепция, мощностной и весовой расчёт, габариты/сервисный доступ, перечень штатной поставки; модель не выбрана. | G36: REVIEW_REQUIRED
A37: W30.20 | B37: W30 | C37: Валопровод, движитель и внешние системы двигателя | D37: Муфты, упорный узел, вал, подшипники, уплотнения и винт по расчёту; внешние охлаждение и выхлоп от границы агрегата; защита от затопления, сервисные соединения. | E37: Редуктор, если включён в W30.10; изготовление корпуса/дейдвудных опор W10; общие забортные проходы W50.65; повторный учёт штатного охлаждения двигателя. | F37: Геометрия кормы, ось вала, расчёт нагрузок/вибрации, требования производителя к охлаждению/выхлопу, границы поставки. | G37: REVIEW_REQUIRED
A38: W30.30 | B38: W30 | C38: Рулевое устройство и аварийное управление | D38: Баллера/перо и подшипники по границе с конструкцией; механическое или гидравлическое управление, посты, аварийное управление; исполнительный привод автопилота и местные обходы. | E38: Киль/балласт W10.60; усиления корпуса W10; вычислитель/датчики автопилота W40.60; общая гидростанция W50.80. | F38: Обмер существующего рулевого, расчёт момента, выбор архитектуры, независимое аварийное управление, доступ и интерфейсы с автопилотом. | G38: REVIEW_REQUIRED
A39: W30.40 | B39: W30 | C39: Маневровые устройства — условный пакет | D39: Подруливающие или иные вспомогательные устройства, локальные исполнительные узлы и монтаж при принятии решения об установке. | E39: Туннели/вырезы/усиления W10; силовые батареи W40.40; внешние кабели W40.30; общая гидравлика W50.80. | F39: Решение о наличии, расчёт усилия/энергии, корпусная компоновка, шум и сервис; тип и количество не назначены. | G39: REVIEW_REQUIRED
A40: W40 | C40: Энергия, электрика и связь | D40: Electrical, Navigation и Networking | E40: См. дочерние пакеты | F40: Установить состав и ревизию | G40: REVIEW_REQUIRED
A41: W40.10 | B41: W40 | C41: Судовые источники электроэнергии | D41: Генераторные установки и штатные локальные системы, монтаж, внешние охлаждение/выхлоп генераторов от границ агрегатов; альтернативные источники только после выбора архитектуры. | E41: Корпусные фундаменты W10; общие топливные магистрали W50.10; AC распределение W40.20; повторные батареи/зарядные W40.40. | F41: Баланс нагрузок и резервирования, эксплуатационные режимы, состав штатной поставки, схема отвода тепла/газов и демонтажа. | G41: REVIEW_REQUIRED
A42: W40.20 | B42: W40 | C42: Сеть AC и береговое питание | D42: Береговой ввод, разделение/защита, переключение источников, щиты, селективность, кабельные линии до согласованных клемм потребителей, маркировка и локальные измерения. | E42: Генераторы W40.10; преобразователи/зарядные W40.40; внутренние заводские провода приборов; бытовые приборы W60.60. | F42: Однолинейная схема, напряжение/частота после утверждения, таблица нагрузок, требования марин, кабельные трассы, отключающая способность. | G42: REVIEW_REQUIRED
A43: W40.25 | B43: W40 | C43: Защитное соединение и электрическая защита алюминиевого корпуса | D43: Согласованная схема защитных проводников/уравнивания потенциалов, контроль утечек и гальванического взаимодействия, измерительные точки; молниезащита если предусмотрена проектом. | E43: Аноды и их механические крепления — W10.85; покрытия и иные корпусные работы — W10; береговой разделительный аппарат уже в W40.20. Проводники и электрическая защита остаются в W40.25; не считать корпус автоматически проводником тока. | F43: Электрическая концепция алюминиевого корпуса, сведения обо всех металлах/забортных соединениях, проект защиты и точки контроля. | G43: REVIEW_REQUIRED
A44: W40.30 | B44: W40 | C44: Сеть DC и критические потребители | D44: Главное и критическое DC распределение, коммутация, защиты, кабели и выводы к оборудованию, линии пуска по границе заводской поставки; местное аварийное управление. | E44: Батареи/зарядные/инверторы W40.40; заводские жгуты агрегатов; светильники W40.90; исполнительные насосы профильных пакетов. | F44: Однолинейная схема, токи/падение напряжения, режимы отказа, трассы, разделение стартовых и сервисных сетей. | G44: REVIEW_REQUIRED
A45: W40.40 | B45: W40 | C45: Батареи и преобразование энергии | D45: Стартовые/сервисные накопители по выбранной химии, BMS, инверторы/зарядные, DC преобразователи, UPS по согласованной границе; корпуса батарейных блоков и локальная защита. | E45: Основные питающие кабели W40.20/30; корпусные основания W10; общая вентиляция W50.75; не учитывать UPS отдельно повторно в навигации/сети. | F45: Суточный энергобаланс, резервирование, химия и ёмкость, размещение/вентиляция/тепло, аварийное отключение, комплектность. | G45: REVIEW_REQUIRED
A46: W40.50 | B46: W40 | C46: Автоматика, мониторинг и общесудовые тревоги | D46: Контроллеры, цифровая коммутация, интерфейсные модули, отображение уровней/энергии/машинных параметров, матрица тревог, локальное резервное управление, конфигурация и резервные копии. | E46: Первичные датчики в профильных системах, пожарные датчики W70.10; базовая сеть W40.80; штатные панели агрегатов; итоговые межсистемные испытания W80. | F46: Матрица сигналов/I-O, границы безопасности и удобства, независимость критических функций, протоколы, лицензии/подписки если потребуются. | G46: REVIEW_REQUIRED
A47: W40.60 | B47: W40 | C47: Навигация и навигационные сигналы | D47: Навигационные вычислители/дисплеи, компасы, датчики и антенны, радар/AIS по применимости, лог/эхолот/ветер, вычислитель автопилота; навигационные огни и звуковые сигналы. | E47: Механический привод автопилота W30.30; штатные двигательные панели W30.10; обычное освещение W40.90; инфраструктура сети W40.80; радио W40.70. | F47: Район плавания/назначение, компоновка постов, требования к независимости, сенсорный план, интерфейсы рулевого и места монтажа. | G47: REVIEW_REQUIRED
A48: W40.70 | B48: W40 | C48: Радиосвязь и внешние каналы данных | D48: Судовые радиостанции и средства доступа к ним, антенные тракты, спутниковый/сотовый канал по выбранной концепции, ввод и настройка разрешённых идентификаторов. | E48: Внутренняя сеть W40.80; AIS W40.60; аварийные автономные маяки/спасательное снабжение — отдельный пакет W70 после распределения ответственности. | F48: Флаг/район эксплуатации, лицензирование и радиоплан, выбранные каналы, антенные взаимные помехи, условия будущих подписок. | G48: REVIEW_REQUIRED
A49: W40.80 | B49: W40 | C49: Судовая сеть, AV и видеонаблюдение | D49: Кабельная информационная инфраструктура, коммутаторы/точки доступа, защищённые сегменты, AV стойка/усилители/экраны/акустика и камеры по согласованному интерьерному заданию; локальная работа без облака как проверяемая цель. | E49: Радиоканалы W40.70; навигационные приборы W40.60; деревянные ниши/панели/мебель W60; UPS W40.40; общий AC/DC кабель до шкафа. | F49: Топология, места установки и теплоотвод, AV требования, границы поставки дисплеев, резервирование, управление доступом/копиями конфигурации. | G49: REVIEW_REQUIRED
A50: W40.90 | B50: W40 | C50: Рабочее, бытовое и аварийное освещение | D50: Светильники, местные органы управления и специфические драйверы, подсветка обслуживания/эвакуации, световые сцены по согласованному проекту. | E50: Навигационные огни W40.60; главные линии питания W40.20/30; контроллеры общего цифрового переключения W40.50; декоративная мебель W60. | F50: Светотехнический план, нагрузки, зоны защиты от воды, автономность аварийного режима, схема управления. | G50: REVIEW_REQUIRED
A51: W50 | C51: Жидкостные системы и климат | D51: Fuel, Water, Waste, Watermaker, Hot water, HVAC и Bilge | E51: См. дочерние пакеты | F51: Установить состав и ревизию | G51: REVIEW_REQUIRED
A52: W50.10 | B52: W50 | C52: Топливная система | D52: Съёмные/покупные топливные ёмкости с установкой; функциональная комплектация интегральных цистерн, залив/вентиляция, арматура, магистрали и возврат, фильтрация/перекачка, отсечение и первичные датчики; сервисный танк только при обосновании; испытание полной топливной системы. | E52: Изготовление/ремонт интегральных сварных цистерн, сварные патрубки и отдельное испытание изготовленного танка — W10.90; заводские топливные узлы агрегатов W30.10/W40.10; пожарная логика W70.10. Не повторять отдельное испытание танка как проверку монтажа системы. | F52: Реестр существующих танков, материалы/состояние, топливо, автономность, схема потребителей и возвратов, комплектность датчиков. | G52: REVIEW_REQUIRED
A53: W50.20 | B53: W50 | C53: Пресная вода | D53: Съёмные/покупные ёмкости пресной воды с установкой; функциональное оснащение интегральных ёмкостей, наполнение/вентиляция, арматура, насосы и коллекторы, холодные магистрали, изоляция и фильтрация; резервные пути как проектная цель; испытание полной водопроводной системы. | E53: Интегральные сварные цистерны и отдельное испытание изготовленного танка — W10.90; опреснитель W50.30; горячая вода W50.40; санприборы, раковины, смесители и душевые приборы — W50.58; электрические преобразователи W40.40. | F53: Баланс потребления/автономности, гигиеническая схема, карта танков, разводка, давление, выбранная концепция резервирования. | G53: REVIEW_REQUIRED
A54: W50.30 | B54: W50 | C54: Опреснение — условный пакет | D54: Опреснительная установка, предочистка, промывка, контроль качества, отвод некондиционного продукта и рассола; подключение в согласованных точках. | E54: Общий забортный ввод W50.65; пресноводное распределение W50.20; питание W40; не назначать производительность по прежним примерам. | F54: Решение о наличии, водный/энергетический баланс, качество исходной воды, сервисный доступ, паспортная комплектность. | G54: REVIEW_REQUIRED
A55: W50.40 | B55: W50 | C55: Горячее водоснабжение | D55: Нагреватели/теплообменники по концепции, горячие линии, рециркуляция при обосновании, смесительная защита и изоляция. | E55: Отопление помещений W50.70; холодный водопровод W50.20; штатные внутренние узлы двигателя; AC/DC питание W40. | F55: Потребление, источники тепла, температурные режимы, трассы, безопасность и санитарные требования после выбора решения. | G55: REVIEW_REQUIRED
A56: W50.50 | B56: W50 | C56: Чёрные воды и санитарная водоподача | D56: Съёмные/покупные ёмкости чёрных вод с установкой; функциональное оснащение интегральных танков, приём/перекачка/хранение/вентиляция стоков, арматура, палубная откачка, разрешённые запираемые сбросы; магистрали и насосы смыва с защитой питьевой воды, первичные датчики; испытание полной системы. | E56: Изготовление интегральных сварных танков и отдельное испытание изготовленного танка — W10.90; унитазы и остальные санприборы — W50.58; серые воды W50.55; общая автоматика W40.50. | F56: Санитарная схема, количество пользователей после утверждения, район/режим эксплуатации, танки, схема исключения обратного загрязнения. | G56: REVIEW_REQUIRED
A57: W50.55 | B57: W50 | C57: Серые воды и конденсат | D57: Съёмные/покупные ёмкости и локальные сборники серых вод с установкой; функциональное оснащение интегральных ёмкостей, магистрали, арматура, сбор/перекачка душевых и бытовых стоков, запахозапирание и вентиляция, общий приём кондиционерного конденсата по интерфейсу; испытание полной системы. | E57: Интегральные сварные ёмкости и отдельное испытание изготовленного танка — W10.90; трюмное осушение W50.60; бытовые приборы W60.60; санприборы W50.58; индивидуальный конденсатоотвод W50.70; не дублировать общие линии чёрных вод. | F57: Согласованная политика сброса/накопления, компоновка приёмников, допустимые высоты/уклоны, характеристики бытовых приборов. | G57: REVIEW_REQUIRED
A58: W50.58 | B58: W50 | C58: Санитарные приборы и их установка | D58: Унитазы, раковины, смесители, душевые приборы и установочные комплекты; приёмка подключения по интерфейсу | E58: Магистрали и насосы W50.20/50; мебель и гидроизоляция помещений W60.50; бытовые приборы W60.60 | F58: План санитарных зон; спецификация приборов; граница комплектов | G58: REVIEW_REQUIRED
A59: W50.60 | B59: W50 | C59: Осушение трюмов и аварийное удаление воды | D59: Зональные насосы/датчики, ручной независимый путь, аварийная магистраль при обосновании, сигнализация на первичном уровне и доступ к очистке. | E59: Серые/чёрные воды W50.50/55; основная автоматика W40.50; силовые сети W40.30; корпусные отверстия W10. | F59: Карта отсеков и низких точек, водонепроницаемые границы, сценарии затопления, расчёт производительности, независимость питания. | G59: REVIEW_REQUIRED
A60: W50.65 | B60: W50 | C60: Забортная арматура, общие морские магистрали и палубный водоотвод | D60: Реестр и комплектование проходов: кингстоны/клапаны, фильтры, общие коллекторы, антисифонные устройства, доступ/маркировка и присоединения к системам. Отдельная гравитационная ветвь трубного палубного водоотвода: приёмные соединения, трубы/шланги, арматура по проекту, крепления и проверка свободного отвода; это отвод воды, не забортная подача. | E60: Вырезы, сварные патрубки и усиления W10; локальные линии от согласованной границы к двигателю/генератору/чиллеру в профильном пакете; повторный учёт каждого общего ввода. Корпусные шпигаты, штормовые портики и их конструктивное обрамление — W10.40; не дублировать их трубной ветвью. | F60: Единый реестр забортных отверстий и владельцев, материалы совместимые с алюминием, расчёт расхода/затопления, доступ и границы поставки. | G60: REVIEW_REQUIRED
A61: W50.70 | B61: W50 | C61: Климат, охлаждение и отопление | D61: Теплохолодильные агрегаты по теплотехническому расчёту, распределительные контуры, зональные блоки, местное управление, изоляция и конденсат до приёмной точки W50.55. | E61: Общая вентиляция W50.75; горячая питьевая вода W50.40; общие забортные вводы W50.65; электропитание W40; мебельные короба W60. | F61: Тепловой баланс после принятия остекления/изоляции, климатические режимы, резервирование, шум, доступ, тепловыделение оборудования. | G61: REVIEW_REQUIRED
A62: W50.75 | B62: W50 | C62: Вентиляция помещений и машинных пространств | D62: Воздухообмен жилых/технических зон и машинного отделения, каналы, вентиляторы, решётки/заслонки, защита от воды, связь с пожарным отключением. | E62: Вентиляторы внутри заводских приборов; фанкойлы W50.70; мебельные декоративные панели W60; корпусные отверстия/усиления W10; пожарная управляющая логика W70.10. | F62: Баланс воздуха/тепла, компоновка каналов, требования производителей агрегатов, шум, огнестойкие границы по применимости. | G62: REVIEW_REQUIRED
A63: W50.80 | B63: W50 | C63: Общая гидравлика — условный пакет | D63: Общий источник/бак/аккумуляторы и распределительные магистрали, охлаждение/фильтрация, управление и аварийная изоляция при принятой общей гидравлической архитектуре. | E63: Локальные исполнительные устройства рулевого W30.30, маневровых W30.40, палубы/такелажа W20; автономные комплектные станции, уже включённые в соответствующее оборудование. | F63: Решение об общей или раздельных системах, потребители/приоритеты, давление/расход, схема резервирования, комплектность каждого привода. | G63: REVIEW_REQUIRED
... A65: W50.90 | B65: W50 | C65: Интерфейсы бытовых приборов и санитарных устройств | D65: Только специфические переходники и подключения воды/слива/воздуха на согласованной границе с бытовыми приборами W60.60 и санприборами W50.58; проверка герметичности интерфейса. | E65: Поставка и установка бытовых приборов — W60.60; унитазы/раковины/смесители/душевые приборы — W50.58; общие подводящие сети W50.20/40/50/55/75; линии и защиты питания W40; заводские соединители в комплекте прибора. Интерфейсную работу распределять по владельцам без дополнительного двойного счёта. | F65: Ведомость выбранных приборов/санприборов, карты подключений, ответственность поставщиков, сервисный доступ; пакет может быть распределён по системам без самостоятельной стоимости. | G65: REVIEW_REQUIRED
A66: W60 | C66: Компоновка и интерьер | D66: Accommodation и Machinery; смежные границы уточняются | E66: См. дочерние пакеты | F66: Установить состав и ревизию | G66: REVIEW_REQUIRED
A67: W60.10 | B67: W60 | C67: Тепло-, акустическая изоляция и обработка конденсата | D67: Материалы, крепления, согласованные паро/влагозащитные слои, монтаж по картам зон корпуса и машинных помещений | E67: Изоляция труб/воздуховодов W50; заводские капсулы агрегатов; декоративные панели W60.20 | F67: Климатический/акустический расчёт; карта мостиков; доступ к сварке/контролю; требования пожарной безопасности | G67: REVIEW_REQUIRED
A68: W60.20 | B68: W60 | C68: Подконструкции, чистые полы, потолки и облицовки | D68: Ненесущий интерьерный каркас, съёмные панели, чистые настилы, потолки, сервисные люки и финиш | E68: Силовые переборки W10; изоляция W60.10; уже включённые мебельные поверхности W60.30 | F68: Уровни пола и низа бимсов; трассы; весовая ведомость; карта ревизионного доступа | G68: REVIEW_REQUIRED
A69: W60.30 | B69: W60 | C69: Встроенная мебель и каютные двери | D69: Мебель кают/салона/штурманской, кровати, шкафы, столы, двери, фурнитура, покрытия, установка | E69: Светильники/AV W40; HVAC W50; матрасы/шторы W60.40; наружные закрытия W20.10 | F69: Утверждённая планировка 3+1; эргономика; материал; ведомость мебели; сервисные зоны | G69: REVIEW_REQUIRED
A70: W60.40 | B70: W60 | C70: Мягкая отделка, матрасы и солнцезащита | D70: Внутренние матрасы/обивка, шторы/жалюзи и съёмный интерьерный текстиль | E70: Наружные подушки W20.30; стационарная мебель W60.30; личные вещи владельца | F70: Раскладка спальных мест; образцы; требования ухода и влагостойкости | G70: REVIEW_REQUIRED
A71: W60.50 | B71: W60 | C71: Мокрые зоны и интерьер камбуза | D71: Душевые поддоны/экраны, гидроизоляция интерьерных сопряжений, столешницы/шкафы камбуза, установка мебели | E71: Поставка и установка унитазов/раковин/моек/смесителей/душевой арматуры W50.58; трубопроводы W50; бытовые приборы W60.60; повторные шкафы W60.30 | F71: Четыре санузла как цель; реальные габариты; уклоны/отвод; границы оборудования и мебели | G71: REVIEW_REQUIRED
A72: W60.60 | B72: W60 | C72: Бытовые приборы и неморское оснащение помещений | D72: Выбранные холодильники/плита/духовка/стирка и прочие приборы: поставка и установка в мебель | E72: Питание W40; газ/вода/слив/вентиляция W50; интегральные холодильные установки при включении W50; мебель | F72: Перечень и единый владелец каждого прибора; мощности; габариты; гарантийный доступ | G72: REVIEW_REQUIRED
A73: W70 | C73: Безопасность | D73: Fire и Safety; требования ещё подлежат установлению | E73: См. дочерние пакеты | F73: Установить состав и ревизию | G73: REVIEW_REQUIRED
A74: W70.10 | B74: W70 | C74: Обнаружение пожара и причинно-следственная логика | D74: Пожарные/газовые датчики по анализу рисков, панели/первичные цепи, ручные органы, останов вентиляции/машин и отсечение топлива через согласованные интерфейсы. | E74: Общесудовое отображение W40.50; исполнительные топливные клапаны W50.10; вентиляционные заслонки W50.75; системы тушения W70.20. | F74: План пожарной безопасности, карта опасных зон, матрица причин/следствий, независимость питания, нормы по выбранной применимости. | G74: REVIEW_REQUIRED
A75: W70.20 | B75: W70 | C75: Пожаротушение и противопожарное снабжение | D75: Стационарное тушение машинных/технических зон по проекту; переносные средства и одеяла, доступ/маркировка, исполнительные линии и безопасная проверка цепей. | E75: Огнезащитные корпусные/интерьерные конструкции W10/W60; пожарное обнаружение W70.10; расходование огнетушащего вещества при испытании не предполагается автоматически. | F75: Объёмы защищаемых помещений, пожарная нагрузка, выбранный агент/безопасность людей, применимые правила и программа приёмки. | G75: REVIEW_REQUIRED
A76: W70.30 | B76: W70 | C76: Спасательное, аварийное и медицинское снабжение | D76: Плоты, жилеты/страховочные системы, средства поиска и подъёма человека за бортом, автономные аварийные маяки/сигнальные средства, аварийный комплект и медицинское снабжение по выбранной применимости; размещение, крепления, учёт сроков обслуживания и обучение по границе с W80. | E76: Стационарная радио-/навигационная инфраструктура W40.60/70; корпусные усиления/вырезы W10 и общие палубные конструкции W20; пожарное снабжение W70.20; стационарное осушение W50.60. Маяк учитывается единожды в этом пакете, радиоданные/регистрация согласуются с W40. | F76: Флаг, режим/район эксплуатации, утверждённое число людей, план эвакуации/MOB, места хранения и доступ, применимые требования, обслуживание/сроки годности; типы и количества не назначены. | G76: REVIEW_REQUIRED
A77: W80 | C77: Интеграция, испытания и передача | D77: Монтажные стыки и согласованный объём проверки/сдачи | E77: См. дочерние пакеты | F77: Установить состав и ревизию | G77: REVIEW_REQUIRED
A78: W80.10 | B78: W80 | C78: Межсистемная проверка и готовность к закрытию | D78: План общесудовой приёмки и испытаний: критерии от W02/изготовителей, ответственные и точки контроля; готовность до закрытия работ/пуска/спуска; общий контроль интерфейсов, проходов/эвакуации, доступа, массы и комплектации; координационные протоколы | E78: Повторный монтаж, FAT и локальные проверки, включённые в профильные пакеты; инженерное обоснование критериев и расчёты W02; дополнительное участие свидетелей только отдельным согласованным составом | F78: Планы инспекций; checklists; исполнительная модель; протоколы дисциплин | G78: REVIEW_REQUIRED
A79: W80.20 | B79: W80 | C79: Общесудовые швартовные и ходовые испытания | D79: Общесудовые швартовные, ходовые и парусные проверки; согласованные первые пуски/межсистемная настройка только вне включений поставщиков, совместные нагрузки, тревоги/блокировки и резервные пути; организация, экипаж/измерения по договорной границе | E79: FAT, локальный первый пуск/настройка и проверки уже включённые в оборудование/монтаж; повторная оплата подготовки рангоута W20; аренда подъёмных средств/стоянки W90 если уже там; штатный ЗИП и начальный запас W80.40 | F79: Критерии и программа приёмки; акты локальной готовности; место/период/загрузка; специалисты и свидетели; единственный владелец топлива/масел/воды и других испытательных расходников; основания повторных выходов | G79: REVIEW_REQUIRED
A80: W80.30 | B80: W80 | C80: Исполнительная документация и сдача | D80: Общесудовое комплектование исполнительных схем/руководств/сертификатов и версий конфигураций, связь требований с протоколами, обучение владельца, гарантийная информация, закрытие замечаний и сдача; сверка реестра ЗИП без его повторной покупки | E80: Повторная оплата документации уже включённой поставщиками; физический ЗИП/специнструменты W80.40; эксплуатационное обслуживание после сдачи; гарантийное исправление подрядчиком не новая платная работа автоматически | F80: Контрактный перечень; реестр поставщиков; языки; испытательные протоколы; ответственность за замечания | G80: REVIEW_REQUIRED
A81: W80.40 | B81: W80 | C81: Первичное снабжение, запасные части и инструменты | D81: Первичный комплект ЗИП, специальные инструменты, маркировка и согласованное снабжение при передаче | E81: Штатные комплекты уже включённые в поставку систем; последующие эксплуатационные закупки | F81: BOM выбранного оборудования; комплектность поставок; перечень сдачи | G81: REVIEW_REQUIRED
A82: W90 | C82: Логистика и условия производства | D82: Доставка, хранение, доступ и производственная площадка по применимости | E82: См. дочерние пакеты | F82: Установить состав и ревизию | G82: REVIEW_REQUIRED
A83: W90.10 | B83: W90 | C83: Перемещение, хранение, помещение и стапель | D83: Доставка корпуса/крупных элементов по согласованным маршрутам, хранение, аренда места, опоры/леса и инфраструктура | E83: Доставка поставщика уже включённая в КП; станочное время/оснастка включённые в изготовление; произвольная ставка накладных | F83: Верфь/маршрут; габариты/массы; календарный план; договорные включения | G83: REVIEW_REQUIRED
A84: W90.20 | B84: W90 | C84: Общие производственные услуги и временные средства | D84: Общее электроснабжение/вентиляция/уборка/удаление отходов/защита готового по договорной границе, временные средства и охрана если поручена | E84: Пакетные расходники и локальная защита в цене работ; двойные общецеховые начисления; всё страхование W90.50 | F84: Условия верфи; календарь; разделение прямых услуг и включённых накладных; перечень временных средств | G84: REVIEW_REQUIRED
A85: W90.30 | B85: W90 | C85: Общие подъёмные операции и спуск | D85: Подъём/перестановка/спуск корпуса, общие подъёмы и обеспечение установки мачты/крупных агрегатов по реестру операций | E85: Крановая услуга внутри цены монтажа поставщика; собственно монтаж рангоута/оборудования | F85: План подъёмов; включения подрядчиков; число операций; массы/центры; доступ к воде | G85: REVIEW_REQUIRED
A86: W90.40 | B86: W90 | C86: Общая логистика и внешние расходы | D86: Перевозка оборудования/материалов, общая доставка и оформление по применимости | E86: Доставка уже включённая в цены КП или распределённая по позициям; двойное начисление запрещено | F86: Место передачи; условия КП; состав грузов; схема распределения | G86: REVIEW_REQUIRED
A87: W90.50 | B87: W90 | C87: Страхование строительства и согласованные сборы | D87: Страхование рисков строительства/перевозки и проектные сборы по подтверждённым условиям | E87: Включённые страховки подрядчиков; эксплуатационные расходы после передачи | F87: Граница ответственности; договоры и основания сборов | G87: REVIEW_REQUIRED

Sheet 03_Пакеты
A1: Задания на запрос КП / RFQ
A2: Синие ячейки — ввод; серые — формулы. Пусто = нет данных. Код строки сохранять при сортировке.
A3: Пакет_ID | B3: WBS | C3: Название | D3: Ревизия ТЗ | E3: Описание и характеристики | F3: Количество | G3: Единица | H3: Поставка / состав | I3: Монтаж / изготовление | J3: Испытания / документы | K3: Исключено | L3: Место передачи | M3: Желаемый срок | N3: Гарантия / сервис | O3: Источник ТЗ | P3: Ответственный | Q3: Статус

Sheet 04_КП
A1: Реестр исходных коммерческих предложений
A2: Синие ячейки — ввод; серые — формулы. Пусто = нет данных. Код строки сохранять при сортировке.
A3: КП_ID | B3: Поставщик_ID / имя | C3: Документ № | D3: Дата цены | E3: Действует до | F3: Валюта КП | G3: Основа NET/GROSS/OTHER | H3: Налог / режим текстом | I3: Ставка по документу | J3: Условия оплаты | K3: Срок поставки | L3: Место / условия передачи | M3: Доставка включена? | N3: Монтаж включён? | O3: Гарантия / сервис | P3: Документ_ID | Q3: Путь к оригиналу | R3: Доступ | S3: Примечание | T3: Контроль
T4: =IF(A4="","",IF(AND(COUNTIF(A$4:A$203,A4)=1,F4<>"",G4<>"",D4<>"",P4<>"",COUNTIF(13_Источники!$A$4:$A$203,P4)=1,OR(G4="NET",G4="GROSS",AND(G4="OTHER",H4<>""))),"READY","INCOMPLETE / ID"))
T5: =IF(A5="","",IF(AND(COUNTIF(A$4:A$203,A5)=1,F5<>"",G5<>"",D5<>"",P5<>"",COUNTIF(13_Источники!$A$4:$A$203,P5)=1,OR(G5="NET",G5="GROSS",AND(G5="OTHER",H5<>""))),"READY","INCOMPLETE / ID"))
T6: =IF(A6="","",IF(AND(COUNTIF(A$4:A$203,A6)=1,F6<>"",G6<>"",D6<>"",P6<>"",COUNTIF(13_Источники!$A$4:$A$203,P6)=1,OR(G6="NET",G6="GROSS",AND(G6="OTHER",H6<>""))),"READY","INCOMPLETE / ID"))
T7: =IF(A7="","",IF(AND(COUNTIF(A$4:A$203,A7)=1,F7<>"",G7<>"",D7<>"",P7<>"",COUNTIF(13_Источники!$A$4:$A$203,P7)=1,OR(G7="NET",G7="GROSS",AND(G7="OTHER",H7<>""))),"READY","INCOMPLETE / ID"))
T8: =IF(A8="","",IF(AND(COUNTIF(A$4:A$203,A8)=1,F8<>"",G8<>"",D8<>"",P8<>"",COUNTIF(13_Источники!$A$4:$A$203,P8)=1,OR(G8="NET",G8="GROSS",AND(G8="OTHER",H8<>""))),"READY","INCOMPLETE / ID"))
T9: =IF(A9="","",IF(AND(COUNTIF(A$4:A$203,A9)=1,F9<>"",G9<>"",D9<>"",P9<>"",COUNTIF(13_Источники!$A$4:$A$203,P9)=1,OR(G9="NET",G9="GROSS",AND(G9="OTHER",H9<>""))),"READY","INCOMPLETE / ID"))
T10: =IF(A10="","",IF(AND(COUNTIF(A$4:A$203,A10)=1,F10<>"",G10<>"",D10<>"",P10<>"",COUNTIF(13_Источники!$A$4:$A$203,P10)=1,OR(G10="NET",G10="GROSS",AND(G10="OTHER",H10<>""))),"READY","INCOMPLETE / ID"))
T11: =IF(A11="","",IF(AND(COUNTIF(A$4:A$203,A11)=1,F11<>"",G11<>"",D11<>"",P11<>"",COUNTIF(13_Источники!$A$4:$A$203,P11)=1,OR(G11="NET",G11="GROSS",AND(G11="OTHER",H11<>""))),"READY","INCOMPLETE / ID"))
T12: =IF(A12="","",IF(AND(COUNTIF(A$4:A$203,A12)=1,F12<>"",G12<>"",D12<>"",P12<>"",COUNTIF(13_Источники!$A$4:$A$203,P12)=1,OR(G12="NET",G12="GROSS",AND(G12="OTHER",H12<>""))),"READY","INCOMPLETE / ID"))
T13: =IF(A13="","",IF(AND(COUNTIF(A$4:A$203,A13)=1,F13<>"",G13<>"",D13<>"",P13<>"",COUNTIF(13_Источники!$A$4:$A$203,P13)=1,OR(G13="NET",G13="GROSS",AND(G13="OTHER",H13<>""))),"READY","INCOMPLETE / ID"))
T14: =IF(A14="","",IF(AND(COUNTIF(A$4:A$203,A14)=1,F14<>"",G14<>"",D14<>"",P14<>"",COUNTIF(13_Источники!$A$4:$A$203,P14)=1,OR(G14="NET",G14="GROSS",AND(G14="OTHER",H14<>""))),"READY","INCOMPLETE / ID"))
T15: =IF(A15="","",IF(AND(COUNTIF(A$4:A$203,A15)=1,F15<>"",G15<>"",D15<>"",P15<>"",COUNTIF(13_Источники!$A$4:$A$203,P15)=1,OR(G15="NET",G15="GROSS",AND(G15="OTHER",H15<>""))),"READY","INCOMPLETE / ID"))
... T203: =IF(A203="","",IF(AND(COUNTIF(A$4:A$203,A203)=1,F203<>"",G203<>"",D203<>"",P203<>"",COUNTIF(13_Источники!$A$4:$A$203,P203)=1,OR(G203="NET",G203="GROSS",AND(G203="OTHER",H203<>""))),"READY","INCOMPLETE / ID"))

Sheet 05_Строки_КП
A1: Исходные строки КП — без нормализации
A2: Синие ячейки — ввод; серые — формулы. Пусто = нет данных. Код строки сохранять при сортировке.
A3: СтрокаКП_ID | B3: КП_ID | C3: Пакет_ID | D3: Позиция / лист | E3: Наименование / исполнение | F3: Количество в КП | G3: Единица КП | H3: Цена единицы в валюте КП | I3: Состояние цены | J3: Включено | K3: Исключено | L3: Валюта (из КП) | M3: Основа (из КП) | N3: Источник / locator | O3: Контроль
L4: =IF(B4="","",IFERROR(INDEX(04_КП!$F$4:$F$203,MATCH(B4,04_КП!$A$4:$A$203,0)),"")) | M4: =IF(B4="","",IFERROR(INDEX(04_КП!$G$4:$G$203,MATCH(B4,04_КП!$A$4:$A$203,0)),"")) | O4: =IF(A4="","",IF(AND(COUNTIF(A$4:A$203,A4)=1,COUNTIF(04_КП!$A$4:$A$203,B4)=1,IFERROR(INDEX(04_КП!$T$4:$T$203,MATCH(B4,04_КП!$A$4:$A$203,0)),"")="READY",COUNTIF(03_Пакеты!$A$4:$A$203,C4)=1,G4<>"",ISNUMBER(H4),H4>=0,OR(AND(H4>0,I4="KNOWN"),AND(H4=0,I4="ZERO_CONFIRMED")),N4<>""),"READY","INCOMPLETE / SOURCE"))
L5: =IF(B5="","",IFERROR(INDEX(04_КП!$F$4:$F$203,MATCH(B5,04_КП!$A$4:$A$203,0)),"")) | M5: =IF(B5="","",IFERROR(INDEX(04_КП!$G$4:$G$203,MATCH(B5,04_КП!$A$4:$A$203,0)),"")) | O5: =IF(A5="","",IF(AND(COUNTIF(A$4:A$203,A5)=1,COUNTIF(04_КП!$A$4:$A$203,B5)=1,IFERROR(INDEX(04_КП!$T$4:$T$203,MATCH(B5,04_КП!$A$4:$A$203,0)),"")="READY",COUNTIF(03_Пакеты!$A$4:$A$203,C5)=1,G5<>"",ISNUMBER(H5),H5>=0,OR(AND(H5>0,I5="KNOWN"),AND(H5=0,I5="ZERO_CONFIRMED")),N5<>""),"READY","INCOMPLETE / SOURCE"))
L6: =IF(B6="","",IFERROR(INDEX(04_КП!$F$4:$F$203,MATCH(B6,04_КП!$A$4:$A$203,0)),"")) | M6: =IF(B6="","",IFERROR(INDEX(04_КП!$G$4:$G$203,MATCH(B6,04_КП!$A$4:$A$203,0)),"")) | O6: =IF(A6="","",IF(AND(COUNTIF(A$4:A$203,A6)=1,COUNTIF(04_КП!$A$4:$A$203,B6)=1,IFERROR(INDEX(04_КП!$T$4:$T$203,MATCH(B6,04_КП!$A$4:$A$203,0)),"")="READY",COUNTIF(03_Пакеты!$A$4:$A$203,C6)=1,G6<>"",ISNUMBER(H6),H6>=0,OR(AND(H6>0,I6="KNOWN"),AND(H6=0,I6="ZERO_CONFIRMED")),N6<>""),"READY","INCOMPLETE / SOURCE"))
L7: =IF(B7="","",IFERROR(INDEX(04_КП!$F$4:$F$203,MATCH(B7,04_КП!$A$4:$A$203,0)),"")) | M7: =IF(B7="","",IFERROR(INDEX(04_КП!$G$4:$G$203,MATCH(B7,04_КП!$A$4:$A$203,0)),"")) | O7: =IF(A7="","",IF(AND(COUNTIF(A$4:A$203,A7)=1,COUNTIF(04_КП!$A$4:$A$203,B7)=1,IFERROR(INDEX(04_КП!$T$4:$T$203,MATCH(B7,04_КП!$A$4:$A$203,0)),"")="READY",COUNTIF(03_Пакеты!$A$4:$A$203,C7)=1,G7<>"",ISNUMBER(H7),H7>=0,OR(AND(H7>0,I7="KNOWN"),AND(H7=0,I7="ZERO_CONFIRMED")),N7<>""),"READY","INCOMPLETE / SOURCE"))
L8: =IF(B8="","",IFERROR(INDEX(04_КП!$F$4:$F$203,MATCH(B8,04_КП!$A$4:$A$203,0)),"")) | M8: =IF(B8="","",IFERROR(INDEX(04_КП!$G$4:$G$203,MATCH(B8,04_КП!$A$4:$A$203,0)),"")) | O8: =IF(A8="","",IF(AND(COUNTIF(A$4:A$203,A8)=1,COUNTIF(04_КП!$A$4:$A$203,B8)=1,IFERROR(INDEX(04_КП!$T$4:$T$203,MATCH(B8,04_КП!$A$4:$A$203,0)),"")="READY",COUNTIF(03_Пакеты!$A$4:$A$203,C8)=1,G8<>"",ISNUMBER(H8),H8>=0,OR(AND(H8>0,I8="KNOWN"),AND(H8=0,I8="ZERO_CONFIRMED")),N8<>""),"READY","INCOMPLETE / SOURCE"))
L9: =IF(B9="","",IFERROR(INDEX(04_КП!$F$4:$F$203,MATCH(B9,04_КП!$A$4:$A$203,0)),"")) | M9: =IF(B9="","",IFERROR(INDEX(04_КП!$G$4:$G$203,MATCH(B9,04_КП!$A$4:$A$203,0)),"")) | O9: =IF(A9="","",IF(AND(COUNTIF(A$4:A$203,A9)=1,COUNTIF(04_КП!$A$4:$A$203,B9)=1,IFERROR(INDEX(04_КП!$T$4:$T$203,MATCH(B9,04_КП!$A$4:$A$203,0)),"")="READY",COUNTIF(03_Пакеты!$A$4:$A$203,C9)=1,G9<>"",ISNUMBER(H9),H9>=0,OR(AND(H9>0,I9="KNOWN"),AND(H9=0,I9="ZERO_CONFIRMED")),N9<>""),"READY","INCOMPLETE / SOURCE"))
L10: =IF(B10="","",IFERROR(INDEX(04_КП!$F$4:$F$203,MATCH(B10,04_КП!$A$4:$A$203,0)),"")) | M10: =IF(B10="","",IFERROR(INDEX(04_КП!$G$4:$G$203,MATCH(B10,04_КП!$A$4:$A$203,0)),"")) | O10: =IF(A10="","",IF(AND(COUNTIF(A$4:A$203,A10)=1,COUNTIF(04_КП!$A$4:$A$203,B10)=1,IFERROR(INDEX(04_КП!$T$4:$T$203,MATCH(B10,04_КП!$A$4:$A$203,0)),"")="READY",COUNTIF(03_Пакеты!$A$4:$A$203,C10)=1,G10<>"",ISNUMBER(H10),H10>=0,OR(AND(H10>0,I10="KNOWN"),AND(H10=0,I10="ZERO_CONFIRMED")),N10<>""),"READY","INCOMPLETE / SOURCE"))
L11: =IF(B11="","",IFERROR(INDEX(04_КП!$F$4:$F$203,MATCH(B11,04_КП!$A$4:$A$203,0)),"")) | M11: =IF(B11="","",IFERROR(INDEX(04_КП!$G$4:$G$203,MATCH(B11,04_КП!$A$4:$A$203,0)),"")) | O11: =IF(A11="","",IF(AND(COUNTIF(A$4:A$203,A11)=1,COUNTIF(04_КП!$A$4:$A$203,B11)=1,IFERROR(INDEX(04_КП!$T$4:$T$203,MATCH(B11,04_КП!$A$4:$A$203,0)),"")="READY",COUNTIF(03_Пакеты!$A$4:$A$203,C11)=1,G11<>"",ISNUMBER(H11),H11>=0,OR(AND(H11>0,I11="KNOWN"),AND(H11=0,I11="ZERO_CONFIRMED")),N11<>""),"READY","INCOMPLETE / SOURCE"))
L12: =IF(B12="","",IFERROR(INDEX(04_КП!$F$4:$F$203,MATCH(B12,04_КП!$A$4:$A$203,0)),"")) | M12: =IF(B12="","",IFERROR(INDEX(04_КП!$G$4:$G$203,MATCH(B12,04_КП!$A$4:$A$203,0)),"")) | O12: =IF(A12="","",IF(AND(COUNTIF(A$4:A$203,A12)=1,COUNTIF(04_КП!$A$4:$A$203,B12)=1,IFERROR(INDEX(04_КП!$T$4:$T$203,MATCH(B12,04_КП!$A$4:$A$203,0)),"")="READY",COUNTIF(03_Пакеты!$A$4:$A$203,C12)=1,G12<>"",ISNUMBER(H12),H12>=0,OR(AND(H12>0,I12="KNOWN"),AND(H12=0,I12="ZERO_CONFIRMED")),N12<>""),"READY","INCOMPLETE / SOURCE"))
L13: =IF(B13="","",IFERROR(INDEX(04_КП!$F$4:$F$203,MATCH(B13,04_КП!$A$4:$A$203,0)),"")) | M13: =IF(B13="","",IFERROR(INDEX(04_КП!$G$4:$G$203,MATCH(B13,04_КП!$A$4:$A$203,0)),"")) | O13: =IF(A13="","",IF(AND(COUNTIF(A$4:A$203,A13)=1,COUNTIF(04_КП!$A$4:$A$203,B13)=1,IFERROR(INDEX(04_КП!$T$4:$T$203,MATCH(B13,04_КП!$A$4:$A$203,0)),"")="READY",COUNTIF(03_Пакеты!$A$4:$A$203,C13)=1,G13<>"",ISNUMBER(H13),H13>=0,OR(AND(H13>0,I13="KNOWN"),AND(H13=0,I13="ZERO_CONFIRMED")),N13<>""),"READY","INCOMPLETE / SOURCE"))
L14: =IF(B14="","",IFERROR(INDEX(04_КП!$F$4:$F$203,MATCH(B14,04_КП!$A$4:$A$203,0)),"")) | M14: =IF(B14="","",IFERROR(INDEX(04_КП!$G$4:$G$203,MATCH(B14,04_КП!$A$4:$A$203,0)),"")) | O14: =IF(A14="","",IF(AND(COUNTIF(A$4:A$203,A14)=1,COUNTIF(04_КП!$A$4:$A$203,B14)=1,IFERROR(INDEX(04_КП!$T$4:$T$203,MATCH(B14,04_КП!$A$4:$A$203,0)),"")="READY",COUNTIF(03_Пакеты!$A$4:$A$203,C14)=1,G14<>"",ISNUMBER(H14),H14>=0,OR(AND(H14>0,I14="KNOWN"),AND(H14=0,I14="ZERO_CONFIRMED")),N14<>""),"READY","INCOMPLETE / SOURCE"))
L15: =IF(B15="","",IFERROR(INDEX(04_КП!$F$4:$F$203,MATCH(B15,04_КП!$A$4:$A$203,0)),"")) | M15: =IF(B15="","",IFERROR(INDEX(04_КП!$G$4:$G$203,MATCH(B15,04_КП!$A$4:$A$203,0)),"")) | O15: =IF(A15="","",IF(AND(COUNTIF(A$4:A$203,A15)=1,COUNTIF(04_КП!$A$4:$A$203,B15)=1,IFERROR(INDEX(04_КП!$T$4:$T$203,MATCH(B15,04_КП!$A$4:$A$203,0)),"")="READY",COUNTIF(03_Пакеты!$A$4:$A$203,C15)=1,G15<>"",ISNUMBER(H15),H15>=0,OR(AND(H15>0,I15="KNOWN"),AND(H15=0,I15="ZERO_CONFIRMED")),N15<>""),"READY","INCOMPLETE / SOURCE"))
... L203: =IF(B203="","",IFERROR(INDEX(04_КП!$F$4:$F$203,MATCH(B203,04_КП!$A$4:$A$203,0)),"")) | M203: =IF(B203="","",IFERROR(INDEX(04_КП!$G$4:$G$203,MATCH(B203,04_КП!$A$4:$A$203,0)),"")) | O203: =IF(A203="","",IF(AND(COUNTIF(A$4:A$203,A203)=1,COUNTIF(04_КП!$A$4:$A$203,B203)=1,IFERROR(INDEX(04_КП!$T$4:$T$203,MATCH(B203,04_КП!$A$4:$A$203,0)),"")="READY",COUNTIF(03_Пакеты!$A$4:$A$203,C203)=1,G203<>"",ISNUMBER(H203),H203>=0,OR(AND(H203>0,I203="KNOWN"),AND(H203=0,I203="ZERO_CONFIRMED")),N203<>""),"READY","INCOMPLETE / SOURCE"))

Sheet 06_КАЦ
A1: Сопоставление вариантов в единой валюте и составе
A2: Синие ячейки — ввод; серые — формулы. Пусто = нет данных. Код строки сохранять при сортировке.
A3: Опция_ID | B3: Группа сравнения_ID | C3: СтрокаКП_ID | D3: Пакет_ID | E3: Техническая сопоставимость | F3: Единица бюджета | G3: Единиц КП на1 ед. бюджета | H3: FX: база за1 валюты КП | I3: Дата FX | J3: Документ FX_ID | K3: Налоговая корректировка / ед. базы | L3: Недостающие работы / ед. базы | M3: Доставка / ед. базы | N3: Иные корректировки / ед. базы | O3: Исходная цена (из строки КП) | P3: Валюта КП | Q3: Основа КП | R3: Сопоставимая цена / ед. базы | S3: Выбор | T3: Причина решения | U3: Метод всех корректировок / единиц | V3: Контроль | W3: Документ корректировок_ID
O4: =IF(C4="","",IF(IFERROR(INDEX(05_Строки_КП!$O$4:$O$203,MATCH(C4,05_Строки_КП!$A$4:$A$203,0)),"")="READY",IFERROR(INDEX(05_Строки_КП!$H$4:$H$203,MATCH(C4,05_Строки_КП!$A$4:$A$203,0)),""),"")) | P4: =IF(C4="","",IF(IFERROR(INDEX(05_Строки_КП!$O$4:$O$203,MATCH(C4,05_Строки_КП!$A$4:$A$203,0)),"")="READY",IFERROR(INDEX(05_Строки_КП!$L$4:$L$203,MATCH(C4,05_Строки_КП!$A$4:$A$203,0)),""),"")) | Q4: =IF(C4="","",IF(IFERROR(INDEX(05_Строки_КП!$O$4:$O$203,MATCH(C4,05_Строки_КП!$A$4:$A$203,0)),"")="READY",IFERROR(INDEX(05_Строки_КП!$M$4:$M$203,MATCH(C4,05_Строки_КП!$A$4:$A$203,0)),""),"")) | R4: =IF(OR(V4="SELECTED_READY",V4="COMPARABLE_READY"),O4*G4*H4+SUM(K4:N4),"") | V4: =IF(A4="","",IF(AND(COUNTIF(A$4:A$203,A4)=1,B4<>"",C4<>"",D4<>"",COUNTIF(05_Строки_КП!$A$4:$A$203,C4)=1,IFERROR(INDEX(05_Строки_КП!$C$4:$C$203,MATCH(C4,05_Строки_КП!$A$4:$A$203,0)),"")=D4,IFERROR(INDEX(05_Строки_КП!$O$4:$O$203,MATCH(C4,05_Строки_КП!$A$4:$A$203,0)),"")="READY",E4="COMPARABLE",F4<>"",COUNT(G4:H4)=2,G4>0,H4>0,I4<>"",J4<>"",COUNTIF(13_Источники!$A$4:$A$203,J4)=1,W4<>"",COUNTIF(13_Источники!$A$4:$A$203,W4)=1,COUNT(K4:N4)=4,ISNUMBER(O4),U4<>"",01_Основания!$B$8<>"",OR(01_Основания!$B$9="NET",01_Основания!$B$9="GROSS"),01_Основания!$B$10<>"",IF(AND(ISNUMBER(O4),ISNUMBER(G4),ISNUMBER(H4)),O4*G4*H4+SUM(K4:N4)>=0,FALSE())),IF(S4="SELECTED",IF(AND(COUNTIFS(B$4:B$203,B4,S$4:S$203,"SELECTED")=1,T4<>""),"SELECTED_READY","SELECTION_ERROR"),"COMPARABLE_READY"),"INCOMPLETE / NOT_COMPARABLE"))
O5: =IF(C5="","",IF(IFERROR(INDEX(05_Строки_КП!$O$4:$O$203,MATCH(C5,05_Строки_КП!$A$4:$A$203,0)),"")="READY",IFERROR(INDEX(05_Строки_КП!$H$4:$H$203,MATCH(C5,05_Строки_КП!$A$4:$A$203,0)),""),"")) | P5: =IF(C5="","",IF(IFERROR(INDEX(05_Строки_КП!$O$4:$O$203,MATCH(C5,05_Строки_КП!$A$4:$A$203,0)),"")="READY",IFERROR(INDEX(05_Строки_КП!$L$4:$L$203,MATCH(C5,05_Строки_КП!$A$4:$A$203,0)),""),"")) | Q5: =IF(C5="","",IF(IFERROR(INDEX(05_Строки_КП!$O$4:$O$203,MATCH(C5,05_Строки_КП!$A$4:$A$203,0)),"")="READY",IFERROR(INDEX(05_Строки_КП!$M$4:$M$203,MATCH(C5,05_Строки_КП!$A$4:$A$203,0)),""),"")) | R5: =IF(OR(V5="SELECTED_READY",V5="COMPARABLE_READY"),O5*G5*H5+SUM(K5:N5),"") | V5: =IF(A5="","",IF(AND(COUNTIF(A$4:A$203,A5)=1,B5<>"",C5<>"",D5<>"",COUNTIF(05_Строки_КП!$A$4:$A$203,C5)=1,IFERROR(INDEX(05_Строки_КП!$C$4:$C$203,MATCH(C5,05_Строки_КП!$A$4:$A$203,0)),"")=D5,IFERROR(INDEX(05_Строки_КП!$O$4:$O$203,MATCH(C5,05_Строки_КП!$A$4:$A$203,0)),"")="READY",E5="COMPARABLE",F5<>"",COUNT(G5:H5)=2,G5>0,H5>0,I5<>"",J5<>"",COUNTIF(13_Источники!$A$4:$A$203,J5)=1,W5<>"",COUNTIF(13_Источники!$A$4:$A$203,W5)=1,COUNT(K5:N5)=4,ISNUMBER(O5),U5<>"",01_Основания!$B$8<>"",OR(01_Основания!$B$9="NET",01_Основания!$B$9="GROSS"),01_Основания!$B$10<>"",IF(AND(ISNUMBER(O5),ISNUMBER(G5),ISNUMBER(H5)),O5*G5*H5+SUM(K5:N5)>=0,FALSE())),IF(S5="SELECTED",IF(AND(COUNTIFS(B$4:B$203,B5,S$4:S$203,"SELECTED")=1,T5<>""),"SELECTED_READY","SELECTION_ERROR"),"COMPARABLE_READY"),"INCOMPLETE / NOT_COMPARABLE"))
O6: =IF(C6="","",IF(IFERROR(INDEX(05_Строки_КП!$O$4:$O$203,MATCH(C6,05_Строки_КП!$A$4:$A$203,0)),"")="READY",IFERROR(INDEX(05_Строки_КП!$H$4:$H$203,MATCH(C6,05_Строки_КП!$A$4:$A$203,0)),""),"")) | P6: =IF(C6="","",IF(IFERROR(INDEX(05_Строки_КП!$O$4:$O$203,MATCH(C6,05_Строки_КП!$A$4:$A$203,0)),"")="READY",IFERROR(INDEX(05_Строки_КП!$L$4:$L$203,MATCH(C6,05_Строки_КП!$A$4:$A$203,0)),""),"")) | Q6: =IF(C6="","",IF(IFERROR(INDEX(05_Строки_КП!$O$4:$O$203,MATCH(C6,05_Строки_КП!$A$4:$A$203,0)),"")="READY",IFERROR(INDEX(05_Строки_КП!$M$4:$M$203,MATCH(C6,05_Строки_КП!$A$4:$A$203,0)),""),"")) | R6: =IF(OR(V6="SELECTED_READY",V6="COMPARABLE_READY"),O6*G6*H6+SUM(K6:N6),"") | V6: =IF(A6="","",IF(AND(COUNTIF(A$4:A$203,A6)=1,B6<>"",C6<>"",D6<>"",COUNTIF(05_Строки_КП!$A$4:$A$203,C6)=1,IFERROR(INDEX(05_Строки_КП!$C$4:$C$203,MATCH(C6,05_Строки_КП!$A$4:$A$203,0)),"")=D6,IFERROR(INDEX(05_Строки_КП!$O$4:$O$203,MATCH(C6,05_Строки_КП!$A$4:$A$203,0)),"")="READY",E6="COMPARABLE",F6<>"",COUNT(G6:H6)=2,G6>0,H6>0,I6<>"",J6<>"",COUNTIF(13_Источники!$A$4:$A$203,J6)=1,W6<>"",COUNTIF(13_Источники!$A$4:$A$203,W6)=1,COUNT(K6:N6)=4,ISNUMBER(O6),U6<>"",01_Основания!$B$8<>"",OR(01_Основания!$B$9="NET",01_Основания!$B$9="GROSS"),01_Основания!$B$10<>"",IF(AND(ISNUMBER(O6),ISNUMBER(G6),ISNUMBER(H6)),O6*G6*H6+SUM(K6:N6)>=0,FALSE())),IF(S6="SELECTED",IF(AND(COUNTIFS(B$4:B$203,B6,S$4:S$203,"SELECTED")=1,T6<>""),"SELECTED_READY","SELECTION_ERROR"),"COMPARABLE_READY"),"INCOMPLETE / NOT_COMPARABLE"))
O7: =IF(C7="","",IF(IFERROR(INDEX(05_Строки_КП!$O$4:$O$203,MATCH(C7,05_Строки_КП!$A$4:$A$203,0)),"")="READY",IFERROR(INDEX(05_Строки_КП!$H$4:$H$203,MATCH(C7,05_Строки_КП!$A$4:$A$203,0)),""),"")) | P7: =IF(C7="","",IF(IFERROR(INDEX(05_Строки_КП!$O$4:$O$203,MATCH(C7,05_Строки_КП!$A$4:$A$203,0)),"")="READY",IFERROR(INDEX(05_Строки_КП!$L$4:$L$203,MATCH(C7,05_Строки_КП!$A$4:$A$203,0)),""),"")) | Q7: =IF(C7="","",IF(IFERROR(INDEX(05_Строки_КП!$O$4:$O$203,MATCH(C7,05_Строки_КП!$A$4:$A$203,0)),"")="READY",IFERROR(INDEX(05_Строки_КП!$M$4:$M$203,MATCH(C7,05_Строки_КП!$A$4:$A$203,0)),""),"")) | R7: =IF(OR(V7="SELECTED_READY",V7="COMPARABLE_READY"),O7*G7*H7+SUM(K7:N7),"") | V7: =IF(A7="","",IF(AND(COUNTIF(A$4:A$203,A7)=1,B7<>"",C7<>"",D7<>"",COUNTIF(05_Строки_КП!$A$4:$A$203,C7)=1,IFERROR(INDEX(05_Строки_КП!$C$4:$C$203,MATCH(C7,05_Строки_КП!$A$4:$A$203,0)),"")=D7,IFERROR(INDEX(05_Строки_КП!$O$4:$O$203,MATCH(C7,05_Строки_КП!$A$4:$A$203,0)),"")="READY",E7="COMPARABLE",F7<>"",COUNT(G7:H7)=2,G7>0,H7>0,I7<>"",J7<>"",COUNTIF(13_Источники!$A$4:$A$203,J7)=1,W7<>"",COUNTIF(13_Источники!$A$4:$A$203,W7)=1,COUNT(K7:N7)=4,ISNUMBER(O7),U7<>"",01_Основания!$B$8<>"",OR(01_Основания!$B$9="NET",01_Основания!$B$9="GROSS"),01_Основания!$B$10<>"",IF(AND(ISNUMBER(O7),ISNUMBER(G7),ISNUMBER(H7)),O7*G7*H7+SUM(K7:N7)>=0,FALSE())),IF(S7="SELECTED",IF(AND(COUNTIFS(B$4:B$203,B7,S$4:S$203,"SELECTED")=1,T7<>""),"SELECTED_READY","SELECTION_ERROR"),"COMPARABLE_READY"),"INCOMPLETE / NOT_COMPARABLE"))
O8: =IF(C8="","",IF(IFERROR(INDEX(05_Строки_КП!$O$4:$O$203,MATCH(C8,05_Строки_КП!$A$4:$A$203,0)),"")="READY",IFERROR(INDEX(05_Строки_КП!$H$4:$H$203,MATCH(C8,05_Строки_КП!$A$4:$A$203,0)),""),"")) | P8: =IF(C8="","",IF(IFERROR(INDEX(05_Строки_КП!$O$4:$O$203,MATCH(C8,05_Строки_КП!$A$4:$A$203,0)),"")="READY",IFERROR(INDEX(05_Строки_КП!$L$4:$L$203,MATCH(C8,05_Строки_КП!$A$4:$A$203,0)),""),"")) | Q8: =IF(C8="","",IF(IFERROR(INDEX(05_Строки_КП!$O$4:$O$203,MATCH(C8,05_Строки_КП!$A$4:$A$203,0)),"")="READY",IFERROR(INDEX(05_Строки_КП!$M$4:$M$203,MATCH(C8,05_Строки_КП!$A$4:$A$203,0)),""),"")) | R8: =IF(OR(V8="SELECTED_READY",V8="COMPARABLE_READY"),O8*G8*H8+SUM(K8:N8),"") | V8: =IF(A8="","",IF(AND(COUNTIF(A$4:A$203,A8)=1,B8<>"",C8<>"",D8<>"",COUNTIF(05_Строки_КП!$A$4:$A$203,C8)=1,IFERROR(INDEX(05_Строки_КП!$C$4:$C$203,MATCH(C8,05_Строки_КП!$A$4:$A$203,0)),"")=D8,IFERROR(INDEX(05_Строки_КП!$O$4:$O$203,MATCH(C8,05_Строки_КП!$A$4:$A$203,0)),"")="READY",E8="COMPARABLE",F8<>"",COUNT(G8:H8)=2,G8>0,H8>0,I8<>"",J8<>"",COUNTIF(13_Источники!$A$4:$A$203,J8)=1,W8<>"",COUNTIF(13_Источники!$A$4:$A$203,W8)=1,COUNT(K8:N8)=4,ISNUMBER(O8),U8<>"",01_Основания!$B$8<>"",OR(01_Основания!$B$9="NET",01_Основания!$B$9="GROSS"),01_Основания!$B$10<>"",IF(AND(ISNUMBER(O8),ISNUMBER(G8),ISNUMBER(H8)),O8*G8*H8+SUM(K8:N8)>=0,FALSE())),IF(S8="SELECTED",IF(AND(COUNTIFS(B$4:B$203,B8,S$4:S$203,"SELECTED")=1,T8<>""),"SELECTED_READY","SELECTION_ERROR"),"COMPARABLE_READY"),"INCOMPLETE / NOT_COMPARABLE"))
O9: =IF(C9="","",IF(IFERROR(INDEX(05_Строки_КП!$O$4:$O$203,MATCH(C9,05_Строки_КП!$A$4:$A$203,0)),"")="READY",IFERROR(INDEX(05_Строки_КП!$H$4:$H$203,MATCH(C9,05_Строки_КП!$A$4:$A$203,0)),""),"")) | P9: =IF(C9="","",IF(IFERROR(INDEX(05_Строки_КП!$O$4:$O$203,MATCH(C9,05_Строки_КП!$A$4:$A$203,0)),"")="READY",IFERROR(INDEX(05_Строки_КП!$L$4:$L$203,MATCH(C9,05_Строки_КП!$A$4:$A$203,0)),""),"")) | Q9: =IF(C9="","",IF(IFERROR(INDEX(05_Строки_КП!$O$4:$O$203,MATCH(C9,05_Строки_КП!$A$4:$A$203,0)),"")="READY",IFERROR(INDEX(05_Строки_КП!$M$4:$M$203,MATCH(C9,05_Строки_КП!$A$4:$A$203,0)),""),"")) | R9: =IF(OR(V9="SELECTED_READY",V9="COMPARABLE_READY"),O9*G9*H9+SUM(K9:N9),"") | V9: =IF(A9="","",IF(AND(COUNTIF(A$4:A$203,A9)=1,B9<>"",C9<>"",D9<>"",COUNTIF(05_Строки_КП!$A$4:$A$203,C9)=1,IFERROR(INDEX(05_Строки_КП!$C$4:$C$203,MATCH(C9,05_Строки_КП!$A$4:$A$203,0)),"")=D9,IFERROR(INDEX(05_Строки_КП!$O$4:$O$203,MATCH(C9,05_Строки_КП!$A$4:$A$203,0)),"")="READY",E9="COMPARABLE",F9<>"",COUNT(G9:H9)=2,G9>0,H9>0,I9<>"",J9<>"",COUNTIF(13_Источники!$A$4:$A$203,J9)=1,W9<>"",COUNTIF(13_Источники!$A$4:$A$203,W9)=1,COUNT(K9:N9)=4,ISNUMBER(O9),U9<>"",01_Основания!$B$8<>"",OR(01_Основания!$B$9="NET",01_Основания!$B$9="GROSS"),01_Основания!$B$10<>"",IF(AND(ISNUMBER(O9),ISNUMBER(G9),ISNUMBER(H9)),O9*G9*H9+SUM(K9:N9)>=0,FALSE())),IF(S9="SELECTED",IF(AND(COUNTIFS(B$4:B$203,B9,S$4:S$203,"SELECTED")=1,T9<>""),"SELECTED_READY","SELECTION_ERROR"),"COMPARABLE_READY"),"INCOMPLETE / NOT_COMPARABLE"))
O10: =IF(C10="","",IF(IFERROR(INDEX(05_Строки_КП!$O$4:$O$203,MATCH(C10,05_Строки_КП!$A$4:$A$203,0)),"")="READY",IFERROR(INDEX(05_Строки_КП!$H$4:$H$203,MATCH(C10,05_Строки_КП!$A$4:$A$203,0)),""),"")) | P10: =IF(C10="","",IF(IFERROR(INDEX(05_Строки_КП!$O$4:$O$203,MATCH(C10,05_Строки_КП!$A$4:$A$203,0)),"")="READY",IFERROR(INDEX(05_Строки_КП!$L$4:$L$203,MATCH(C10,05_Строки_КП!$A$4:$A$203,0)),""),"")) | Q10: =IF(C10="","",IF(IFERROR(INDEX(05_Строки_КП!$O$4:$O$203,MATCH(C10,05_Строки_КП!$A$4:$A$203,0)),"")="READY",IFERROR(INDEX(05_Строки_КП!$M$4:$M$203,MATCH(C10,05_Строки_КП!$A$4:$A$203,0)),""),"")) | R10: =IF(OR(V10="SELECTED_READY",V10="COMPARABLE_READY"),O10*G10*H10+SUM(K10:N10),"") | V10: =IF(A10="","",IF(AND(COUNTIF(A$4:A$203,A10)=1,B10<>"",C10<>"",D10<>"",COUNTIF(05_Строки_КП!$A$4:$A$203,C10)=1,IFERROR(INDEX(05_Строки_КП!$C$4:$C$203,MATCH(C10,05_Строки_КП!$A$4:$A$203,0)),"")=D10,IFERROR(INDEX(05_Строки_КП!$O$4:$O$203,MATCH(C10,05_Строки_КП!$A$4:$A$203,0)),"")="READY",E10="COMPARABLE",F10<>"",COUNT(G10:H10)=2,G10>0,H10>0,I10<>"",J10<>"",COUNTIF(13_Источники!$A$4:$A$203,J10)=1,W10<>"",COUNTIF(13_Источники!$A$4:$A$203,W10)=1,COUNT(K10:N10)=4,ISNUMBER(O10),U10<>"",01_Основания!$B$8<>"",OR(01_Основания!$B$9="NET",01_Основания!$B$9="GROSS"),01_Основания!$B$10<>"",IF(AND(ISNUMBER(O10),ISNUMBER(G10),ISNUMBER(H10)),O10*G10*H10+SUM(K10:N10)>=0,FALSE())),IF(S10="SELECTED",IF(AND(COUNTIFS(B$4:B$203,B10,S$4:S$203,"SELECTED")=1,T10<>""),"SELECTED_READY","SELECTION_ERROR"),"COMPARABLE_READY"),"INCOMPLETE / NOT_COMPARABLE"))
O11: =IF(C11="","",IF(IFERROR(INDEX(05_Строки_КП!$O$4:$O$203,MATCH(C11,05_Строки_КП!$A$4:$A$203,0)),"")="READY",IFERROR(INDEX(05_Строки_КП!$H$4:$H$203,MATCH(C11,05_Строки_КП!$A$4:$A$203,0)),""),"")) | P11: =IF(C11="","",IF(IFERROR(INDEX(05_Строки_КП!$O$4:$O$203,MATCH(C11,05_Строки_КП!$A$4:$A$203,0)),"")="READY",IFERROR(INDEX(05_Строки_КП!$L$4:$L$203,MATCH(C11,05_Строки_КП!$A$4:$A$203,0)),""),"")) | Q11: =IF(C11="","",IF(IFERROR(INDEX(05_Строки_КП!$O$4:$O$203,MATCH(C11,05_Строки_КП!$A$4:$A$203,0)),"")="READY",IFERROR(INDEX(05_Строки_КП!$M$4:$M$203,MATCH(C11,05_Строки_КП!$A$4:$A$203,0)),""),"")) | R11: =IF(OR(V11="SELECTED_READY",V11="COMPARABLE_READY"),O11*G11*H11+SUM(K11:N11),"") | V11: =IF(A11="","",IF(AND(COUNTIF(A$4:A$203,A11)=1,B11<>"",C11<>"",D11<>"",COUNTIF(05_Строки_КП!$A$4:$A$203,C11)=1,IFERROR(INDEX(05_Строки_КП!$C$4:$C$203,MATCH(C11,05_Строки_КП!$A$4:$A$203,0)),"")=D11,IFERROR(INDEX(05_Строки_КП!$O$4:$O$203,MATCH(C11,05_Строки_КП!$A$4:$A$203,0)),"")="READY",E11="COMPARABLE",F11<>"",COUNT(G11:H11)=2,G11>0,H11>0,I11<>"",J11<>"",COUNTIF(13_Источники!$A$4:$A$203,J11)=1,W11<>"",COUNTIF(13_Источники!$A$4:$A$203,W11)=1,COUNT(K11:N11)=4,ISNUMBER(O11),U11<>"",01_Основания!$B$8<>"",OR(01_Основания!$B$9="NET",01_Основания!$B$9="GROSS"),01_Основания!$B$10<>"",IF(AND(ISNUMBER(O11),ISNUMBER(G11),ISNUMBER(H11)),O11*G11*H11+SUM(K11:N11)>=0,FALSE())),IF(S11="SELECTED",IF(AND(COUNTIFS(B$4:B$203,B11,S$4:S$203,"SELECTED")=1,T11<>""),"SELECTED_READY","SELECTION_ERROR"),"COMPARABLE_READY"),"INCOMPLETE / NOT_COMPARABLE"))
O12: =IF(C12="","",IF(IFERROR(INDEX(05_Строки_КП!$O$4:$O$203,MATCH(C12,05_Строки_КП!$A$4:$A$203,0)),"")="READY",IFERROR(INDEX(05_Строки_КП!$H$4:$H$203,MATCH(C12,05_Строки_КП!$A$4:$A$203,0)),""),"")) | P12: =IF(C12="","",IF(IFERROR(INDEX(05_Строки_КП!$O$4:$O$203,MATCH(C12,05_Строки_КП!$A$4:$A$203,0)),"")="READY",IFERROR(INDEX(05_Строки_КП!$L$4:$L$203,MATCH(C12,05_Строки_КП!$A$4:$A$203,0)),""),"")) | Q12: =IF(C12="","",IF(IFERROR(INDEX(05_Строки_КП!$O$4:$O$203,MATCH(C12,05_Строки_КП!$A$4:$A$203,0)),"")="READY",IFERROR(INDEX(05_Строки_КП!$M$4:$M$203,MATCH(C12,05_Строки_КП!$A$4:$A$203,0)),""),"")) | R12: =IF(OR(V12="SELECTED_READY",V12="COMPARABLE_READY"),O12*G12*H12+SUM(K12:N12),"") | V12: =IF(A12="","",IF(AND(COUNTIF(A$4:A$203,A12)=1,B12<>"",C12<>"",D12<>"",COUNTIF(05_Строки_КП!$A$4:$A$203,C12)=1,IFERROR(INDEX(05_Строки_КП!$C$4:$C$203,MATCH(C12,05_Строки_КП!$A$4:$A$203,0)),"")=D12,IFERROR(INDEX(05_Строки_КП!$O$4:$O$203,MATCH(C12,05_Строки_КП!$A$4:$A$203,0)),"")="READY",E12="COMPARABLE",F12<>"",COUNT(G12:H12)=2,G12>0,H12>0,I12<>"",J12<>"",COUNTIF(13_Источники!$A$4:$A$203,J12)=1,W12<>"",COUNTIF(13_Источники!$A$4:$A$203,W12)=1,COUNT(K12:N12)=4,ISNUMBER(O12),U12<>"",01_Основания!$B$8<>"",OR(01_Основания!$B$9="NET",01_Основания!$B$9="GROSS"),01_Основания!$B$10<>"",IF(AND(ISNUMBER(O12),ISNUMBER(G12),ISNUMBER(H12)),O12*G12*H12+SUM(K12:N12)>=0,FALSE())),IF(S12="SELECTED",IF(AND(COUNTIFS(B$4:B$203,B12,S$4:S$203,"SELECTED")=1,T12<>""),"SELECTED_READY","SELECTION_ERROR"),"COMPARABLE_READY"),"INCOMPLETE / NOT_COMPARABLE"))
O13: =IF(C13="","",IF(IFERROR(INDEX(05_Строки_КП!$O$4:$O$203,MATCH(C13,05_Строки_КП!$A$4:$A$203,0)),"")="READY",IFERROR(INDEX(05_Строки_КП!$H$4:$H$203,MATCH(C13,05_Строки_КП!$A$4:$A$203,0)),""),"")) | P13: =IF(C13="","",IF(IFERROR(INDEX(05_Строки_КП!$O$4:$O$203,MATCH(C13,05_Строки_КП!$A$4:$A$203,0)),"")="READY",IFERROR(INDEX(05_Строки_КП!$L$4:$L$203,MATCH(C13,05_Строки_КП!$A$4:$A$203,0)),""),"")) | Q13: =IF(C13="","",IF(IFERROR(INDEX(05_Строки_КП!$O$4:$O$203,MATCH(C13,05_Строки_КП!$A$4:$A$203,0)),"")="READY",IFERROR(INDEX(05_Строки_КП!$M$4:$M$203,MATCH(C13,05_Строки_КП!$A$4:$A$203,0)),""),"")) | R13: =IF(OR(V13="SELECTED_READY",V13="COMPARABLE_READY"),O13*G13*H13+SUM(K13:N13),"") | V13: =IF(A13="","",IF(AND(COUNTIF(A$4:A$203,A13)=1,B13<>"",C13<>"",D13<>"",COUNTIF(05_Строки_КП!$A$4:$A$203,C13)=1,IFERROR(INDEX(05_Строки_КП!$C$4:$C$203,MATCH(C13,05_Строки_КП!$A$4:$A$203,0)),"")=D13,IFERROR(INDEX(05_Строки_КП!$O$4:$O$203,MATCH(C13,05_Строки_КП!$A$4:$A$203,0)),"")="READY",E13="COMPARABLE",F13<>"",COUNT(G13:H13)=2,G13>0,H13>0,I13<>"",J13<>"",COUNTIF(13_Источники!$A$4:$A$203,J13)=1,W13<>"",COUNTIF(13_Источники!$A$4:$A$203,W13)=1,COUNT(K13:N13)=4,ISNUMBER(O13),U13<>"",01_Основания!$B$8<>"",OR(01_Основания!$B$9="NET",01_Основания!$B$9="GROSS"),01_Основания!$B$10<>"",IF(AND(ISNUMBER(O13),ISNUMBER(G13),ISNUMBER(H13)),O13*G13*H13+SUM(K13:N13)>=0,FALSE())),IF(S13="SELECTED",IF(AND(COUNTIFS(B$4:B$203,B13,S$4:S$203,"SELECTED")=1,T13<>""),"SELECTED_READY","SELECTION_ERROR"),"COMPARABLE_READY"),"INCOMPLETE / NOT_COMPARABLE"))
O14: =IF(C14="","",IF(IFERROR(INDEX(05_Строки_КП!$O$4:$O$203,MATCH(C14,05_Строки_КП!$A$4:$A$203,0)),"")="READY",IFERROR(INDEX(05_Строки_КП!$H$4:$H$203,MATCH(C14,05_Строки_КП!$A$4:$A$203,0)),""),"")) | P14: =IF(C14="","",IF(IFERROR(INDEX(05_Строки_КП!$O$4:$O$203,MATCH(C14,05_Строки_КП!$A$4:$A$203,0)),"")="READY",IFERROR(INDEX(05_Строки_КП!$L$4:$L$203,MATCH(C14,05_Строки_КП!$A$4:$A$203,0)),""),"")) | Q14: =IF(C14="","",IF(IFERROR(INDEX(05_Строки_КП!$O$4:$O$203,MATCH(C14,05_Строки_КП!$A$4:$A$203,0)),"")="READY",IFERROR(INDEX(05_Строки_КП!$M$4:$M$203,MATCH(C14,05_Строки_КП!$A$4:$A$203,0)),""),"")) | R14: =IF(OR(V14="SELECTED_READY",V14="COMPARABLE_READY"),O14*G14*H14+SUM(K14:N14),"") | V14: =IF(A14="","",IF(AND(COUNTIF(A$4:A$203,A14)=1,B14<>"",C14<>"",D14<>"",COUNTIF(05_Строки_КП!$A$4:$A$203,C14)=1,IFERROR(INDEX(05_Строки_КП!$C$4:$C$203,MATCH(C14,05_Строки_КП!$A$4:$A$203,0)),"")=D14,IFERROR(INDEX(05_Строки_КП!$O$4:$O$203,MATCH(C14,05_Строки_КП!$A$4:$A$203,0)),"")="READY",E14="COMPARABLE",F14<>"",COUNT(G14:H14)=2,G14>0,H14>0,I14<>"",J14<>"",COUNTIF(13_Источники!$A$4:$A$203,J14)=1,W14<>"",COUNTIF(13_Источники!$A$4:$A$203,W14)=1,COUNT(K14:N14)=4,ISNUMBER(O14),U14<>"",01_Основания!$B$8<>"",OR(01_Основания!$B$9="NET",01_Основания!$B$9="GROSS"),01_Основания!$B$10<>"",IF(AND(ISNUMBER(O14),ISNUMBER(G14),ISNUMBER(H14)),O14*G14*H14+SUM(K14:N14)>=0,FALSE())),IF(S14="SELECTED",IF(AND(COUNTIFS(B$4:B$203,B14,S$4:S$203,"SELECTED")=1,T14<>""),"SELECTED_READY","SELECTION_ERROR"),"COMPARABLE_READY"),"INCOMPLETE / NOT_COMPARABLE"))
O15: =IF(C15="","",IF(IFERROR(INDEX(05_Строки_КП!$O$4:$O$203,MATCH(C15,05_Строки_КП!$A$4:$A$203,0)),"")="READY",IFERROR(INDEX(05_Строки_КП!$H$4:$H$203,MATCH(C15,05_Строки_КП!$A$4:$A$203,0)),""),"")) | P15: =IF(C15="","",IF(IFERROR(INDEX(05_Строки_КП!$O$4:$O$203,MATCH(C15,05_Строки_КП!$A$4:$A$203,0)),"")="READY",IFERROR(INDEX(05_Строки_КП!$L$4:$L$203,MATCH(C15,05_Строки_КП!$A$4:$A$203,0)),""),"")) | Q15: =IF(C15="","",IF(IFERROR(INDEX(05_Строки_КП!$O$4:$O$203,MATCH(C15,05_Строки_КП!$A$4:$A$203,0)),"")="READY",IFERROR(INDEX(05_Строки_КП!$M$4:$M$203,MATCH(C15,05_Строки_КП!$A$4:$A$203,0)),""),"")) | R15: =IF(OR(V15="SELECTED_READY",V15="COMPARABLE_READY"),O15*G15*H15+SUM(K15:N15),"") | V15: =IF(A15="","",IF(AND(COUNTIF(A$4:A$203,A15)=1,B15<>"",C15<>"",D15<>"",COUNTIF(05_Строки_КП!$A$4:$A$203,C15)=1,IFERROR(INDEX(05_Строки_КП!$C$4:$C$203,MATCH(C15,05_Строки_КП!$A$4:$A$203,0)),"")=D15,IFERROR(INDEX(05_Строки_КП!$O$4:$O$203,MATCH(C15,05_Строки_КП!$A$4:$A$203,0)),"")="READY",E15="COMPARABLE",F15<>"",COUNT(G15:H15)=2,G15>0,H15>0,I15<>"",J15<>"",COUNTIF(13_Источники!$A$4:$A$203,J15)=1,W15<>"",COUNTIF(13_Источники!$A$4:$A$203,W15)=1,COUNT(K15:N15)=4,ISNUMBER(O15),U15<>"",01_Основания!$B$8<>"",OR(01_Основания!$B$9="NET",01_Основания!$B$9="GROSS"),01_Основания!$B$10<>"",IF(AND(ISNUMBER(O15),ISNUMBER(G15),ISNUMBER(H15)),O15*G15*H15+SUM(K15:N15)>=0,FALSE())),IF(S15="SELECTED",IF(AND(COUNTIFS(B$4:B$203,B15,S$4:S$203,"SELECTED")=1,T15<>""),"SELECTED_READY","SELECTION_ERROR"),"COMPARABLE_READY"),"INCOMPLETE / NOT_COMPARABLE"))
... O203: =IF(C203="","",IF(IFERROR(INDEX(05_Строки_КП!$O$4:$O$203,MATCH(C203,05_Строки_КП!$A$4:$A$203,0)),"")="READY",IFERROR(INDEX(05_Строки_КП!$H$4:$H$203,MATCH(C203,05_Строки_КП!$A$4:$A$203,0)),""),"")) | P203: =IF(C203="","",IF(IFERROR(INDEX(05_Строки_КП!$O$4:$O$203,MATCH(C203,05_Строки_КП!$A$4:$A$203,0)),"")="READY",IFERROR(INDEX(05_Строки_КП!$L$4:$L$203,MATCH(C203,05_Строки_КП!$A$4:$A$203,0)),""),"")) | Q203: =IF(C203="","",IF(IFERROR(INDEX(05_Строки_КП!$O$4:$O$203,MATCH(C203,05_Строки_КП!$A$4:$A$203,0)),"")="READY",IFERROR(INDEX(05_Строки_КП!$M$4:$M$203,MATCH(C203,05_Строки_КП!$A$4:$A$203,0)),""),"")) | R203: =IF(OR(V203="SELECTED_READY",V203="COMPARABLE_READY"),O203*G203*H203+SUM(K203:N203),"") | V203: =IF(A203="","",IF(AND(COUNTIF(A$4:A$203,A203)=1,B203<>"",C203<>"",D203<>"",COUNTIF(05_Строки_КП!$A$4:$A$203,C203)=1,IFERROR(INDEX(05_Строки_КП!$C$4:$C$203,MATCH(C203,05_Строки_КП!$A$4:$A$203,0)),"")=D203,IFERROR(INDEX(05_Строки_КП!$O$4:$O$203,MATCH(C203,05_Строки_КП!$A$4:$A$203,0)),"")="READY",E203="COMPARABLE",F203<>"",COUNT(G203:H203)=2,G203>0,H203>0,I203<>"",J203<>"",COUNTIF(13_Источники!$A$4:$A$203,J203)=1,W203<>"",COUNTIF(13_Источники!$A$4:$A$203,W203)=1,COUNT(K203:N203)=4,ISNUMBER(O203),U203<>"",01_Основания!$B$8<>"",OR(01_Основания!$B$9="NET",01_Основания!$B$9="GROSS"),01_Основания!$B$10<>"",IF(AND(ISNUMBER(O203),ISNUMBER(G203),ISNUMBER(H203)),O203*G203*H203+SUM(K203:N203)>=0,FALSE())),IF(S203="SELECTED",IF(AND(COUNTIFS(B$4:B$203,B203,S$4:S$203,"SELECTED")=1,T203<>""),"SELECTED_READY","SELECTION_ERROR"),"COMPARABLE_READY"),"INCOMPLETE / NOT_COMPARABLE"))

Sheet 07_Смета
A1: Рабочая смета — заготовка будущей УТВ
A2: Синие ячейки — ввод; серые — формулы. Пусто = нет данных. Код строки сохранять при сортировке.
A3: Строка_ID | B3: WBS | C3: Пакет_ID | D3: Наименование работы / ресурса | E3: Вид затрат | F3: Состояние объекта | G3: Кто поставляет | H3: Граница затрат | I3: Количество | J3: Единица | K3: Основание цены_ID | L3: Цена / ед. базовая | M3: Сумма базовая | N3: Контроль готовности | O3: Документ количества_ID | P3: Ревизия / лист | Q3: Состояние количества | R3: Состав / исключения | S3: Ответственный | T3: Решение / версия УТВ | U3: Примечание | V3: Тип основания цены
A4: EST-001 | B4: W00.10 | D4: Управление и координация проекта | L4: =IF(N4="READY",IF(V4="KAC",IFERROR(INDEX(06_КАЦ!$R$4:$R$203,MATCH(K4,06_КАЦ!$A$4:$A$203,0)),""),IFERROR(INDEX(06а_Оценки!$F$4:$F$203,MATCH(K4,06а_Оценки!$A$4:$A$203,0)),"")),"") | M4: =IF(N4="READY",ROUND(I4*L4,2),"") | N4: =IF(A4="","",IF(Q4="NOT_APPLICABLE",IF(AND(COUNTIF(A$4:A$203,A4)=1,H4="OUTSIDE",R4<>"",O4<>"",COUNTIF(13_Источники!$A$4:$A$203,O4)=1),"NOT_APPLICABLE","INCOMPLETE / EXCLUSION"),IF(AND(COUNTIF(A$4:A$203,A4)=1,COUNTIF(02_WBS!$A$4:$A$200,B4)=1,C4<>"",COUNTIF(03_Пакеты!$A$4:$A$203,C4)=1,IFERROR(INDEX(03_Пакеты!$B$4:$B$203,MATCH(C4,03_Пакеты!$A$4:$A$203,0)),"")=B4,E4<>"",F4<>"",F4<>"UNKNOWN",G4<>"",G4<>"UNKNOWN",OR(H4="REMAINING",H4="SUNK",H4="OUTSIDE"),ISNUMBER(I4),I4>=0,OR(AND(I4>0,Q4="KNOWN"),AND(I4=0,Q4="ZERO_CONFIRMED")),J4<>"",K4<>"",OR(AND(V4="KAC",COUNTIF(06_КАЦ!$A$4:$A$203,K4)=1,IFERROR(INDEX(06_КАЦ!$V$4:$V$203,MATCH(K4,06_КАЦ!$A$4:$A$203,0)),"")="SELECTED_READY",IFERROR(INDEX(06_КАЦ!$D$4:$D$203,MATCH(K4,06_КАЦ!$A$4:$A$203,0)),"")=C4,IFERROR(INDEX(06_КАЦ!$F$4:$F$203,MATCH(K4,06_КАЦ!$A$4:$A$203,0)),"")=J4),AND(V4="DIRECT",COUNTIF(06а_Оценки!$A$4:$A$203,K4)=1,IFERROR(INDEX(06а_Оценки!$N$4:$N$203,MATCH(K4,06а_Оценки!$A$4:$A$203,0)),"")="READY",IFERROR(INDEX(06а_Оценки!$B$4:$B$203,MATCH(K4,06а_Оценки!$A$4:$A$203,0)),"")=C4,IFERROR(INDEX(06а_Оценки!$E$4:$E$203,MATCH(K4,06а_Оценки!$A$4:$A$203,0)),"")=J4)),O4<>"",COUNTIF(13_Источники!$A$4:$A$203,O4)=1,P4<>"",R4<>""),"READY","INCOMPLETE / LINK"))) -> INCOMPLETE / LINK | Q4: UNKNOWN | R4: Техническое проектирование W02; включённые накладные подрядчиков
A5: EST-002 | B5: W01.10 | D5: Приёмка существующего корпуса и документов | L5: =IF(N5="READY",IF(V5="KAC",IFERROR(INDEX(06_КАЦ!$R$4:$R$203,MATCH(K5,06_КАЦ!$A$4:$A$203,0)),""),IFERROR(INDEX(06а_Оценки!$F$4:$F$203,MATCH(K5,06а_Оценки!$A$4:$A$203,0)),"")),"") | M5: =IF(N5="READY",ROUND(I5*L5,2),"") | N5: =IF(A5="","",IF(Q5="NOT_APPLICABLE",IF(AND(COUNTIF(A$4:A$203,A5)=1,H5="OUTSIDE",R5<>"",O5<>"",COUNTIF(13_Источники!$A$4:$A$203,O5)=1),"NOT_APPLICABLE","INCOMPLETE / EXCLUSION"),IF(AND(COUNTIF(A$4:A$203,A5)=1,COUNTIF(02_WBS!$A$4:$A$200,B5)=1,C5<>"",COUNTIF(03_Пакеты!$A$4:$A$203,C5)=1,IFERROR(INDEX(03_Пакеты!$B$4:$B$203,MATCH(C5,03_Пакеты!$A$4:$A$203,0)),"")=B5,E5<>"",F5<>"",F5<>"UNKNOWN",G5<>"",G5<>"UNKNOWN",OR(H5="REMAINING",H5="SUNK",H5="OUTSIDE"),ISNUMBER(I5),I5>=0,OR(AND(I5>0,Q5="KNOWN"),AND(I5=0,Q5="ZERO_CONFIRMED")),J5<>"",K5<>"",OR(AND(V5="KAC",COUNTIF(06_КАЦ!$A$4:$A$203,K5)=1,IFERROR(INDEX(06_КАЦ!$V$4:$V$203,MATCH(K5,06_КАЦ!$A$4:$A$203,0)),"")="SELECTED_READY",IFERROR(INDEX(06_КАЦ!$D$4:$D$203,MATCH(K5,06_КАЦ!$A$4:$A$203,0)),"")=C5,IFERROR(INDEX(06_КАЦ!$F$4:$F$203,MATCH(K5,06_КАЦ!$A$4:$A$203,0)),"")=J5),AND(V5="DIRECT",COUNTIF(06а_Оценки!$A$4:$A$203,K5)=1,IFERROR(INDEX(06а_Оценки!$N$4:$N$203,MATCH(K5,06а_Оценки!$A$4:$A$203,0)),"")="READY",IFERROR(INDEX(06а_Оценки!$B$4:$B$203,MATCH(K5,06а_Оценки!$A$4:$A$203,0)),"")=C5,IFERROR(INDEX(06а_Оценки!$E$4:$E$203,MATCH(K5,06а_Оценки!$A$4:$A$203,0)),"")=J5)),O5<>"",COUNTIF(13_Источники!$A$4:$A$203,O5)=1,P5<>"",R5<>""),"READY","INCOMPLETE / LINK"))) -> INCOMPLETE / LINK | Q5: UNKNOWN | R5: Повторная покупка существующего корпуса; ремонт и достройка
A6: EST-003 | B6: W01.20 | D6: Обмер, контроль состояния и дефектная ведомость | L6: =IF(N6="READY",IF(V6="KAC",IFERROR(INDEX(06_КАЦ!$R$4:$R$203,MATCH(K6,06_КАЦ!$A$4:$A$203,0)),""),IFERROR(INDEX(06а_Оценки!$F$4:$F$203,MATCH(K6,06а_Оценки!$A$4:$A$203,0)),"")),"") | M6: =IF(N6="READY",ROUND(I6*L6,2),"") | N6: =IF(A6="","",IF(Q6="NOT_APPLICABLE",IF(AND(COUNTIF(A$4:A$203,A6)=1,H6="OUTSIDE",R6<>"",O6<>"",COUNTIF(13_Источники!$A$4:$A$203,O6)=1),"NOT_APPLICABLE","INCOMPLETE / EXCLUSION"),IF(AND(COUNTIF(A$4:A$203,A6)=1,COUNTIF(02_WBS!$A$4:$A$200,B6)=1,C6<>"",COUNTIF(03_Пакеты!$A$4:$A$203,C6)=1,IFERROR(INDEX(03_Пакеты!$B$4:$B$203,MATCH(C6,03_Пакеты!$A$4:$A$203,0)),"")=B6,E6<>"",F6<>"",F6<>"UNKNOWN",G6<>"",G6<>"UNKNOWN",OR(H6="REMAINING",H6="SUNK",H6="OUTSIDE"),ISNUMBER(I6),I6>=0,OR(AND(I6>0,Q6="KNOWN"),AND(I6=0,Q6="ZERO_CONFIRMED")),J6<>"",K6<>"",OR(AND(V6="KAC",COUNTIF(06_КАЦ!$A$4:$A$203,K6)=1,IFERROR(INDEX(06_КАЦ!$V$4:$V$203,MATCH(K6,06_КАЦ!$A$4:$A$203,0)),"")="SELECTED_READY",IFERROR(INDEX(06_КАЦ!$D$4:$D$203,MATCH(K6,06_КАЦ!$A$4:$A$203,0)),"")=C6,IFERROR(INDEX(06_КАЦ!$F$4:$F$203,MATCH(K6,06_КАЦ!$A$4:$A$203,0)),"")=J6),AND(V6="DIRECT",COUNTIF(06а_Оценки!$A$4:$A$203,K6)=1,IFERROR(INDEX(06а_Оценки!$N$4:$N$203,MATCH(K6,06а_Оценки!$A$4:$A$203,0)),"")="READY",IFERROR(INDEX(06а_Оценки!$B$4:$B$203,MATCH(K6,06а_Оценки!$A$4:$A$203,0)),"")=C6,IFERROR(INDEX(06а_Оценки!$E$4:$E$203,MATCH(K6,06а_Оценки!$A$4:$A$203,0)),"")=J6)),O6<>"",COUNTIF(13_Источники!$A$4:$A$203,O6)=1,P6<>"",R6<>""),"READY","INCOMPLETE / LINK"))) -> INCOMPLETE / LINK | Q6: UNKNOWN | R6: Ремонт выявленного; производственный контроль новых швов
A7: EST-004 | B7: W02.10 | D7: Базовая геометрия, компоновка и расчётная координация | L7: =IF(N7="READY",IF(V7="KAC",IFERROR(INDEX(06_КАЦ!$R$4:$R$203,MATCH(K7,06_КАЦ!$A$4:$A$203,0)),""),IFERROR(INDEX(06а_Оценки!$F$4:$F$203,MATCH(K7,06а_Оценки!$A$4:$A$203,0)),"")),"") | M7: =IF(N7="READY",ROUND(I7*L7,2),"") | N7: =IF(A7="","",IF(Q7="NOT_APPLICABLE",IF(AND(COUNTIF(A$4:A$203,A7)=1,H7="OUTSIDE",R7<>"",O7<>"",COUNTIF(13_Источники!$A$4:$A$203,O7)=1),"NOT_APPLICABLE","INCOMPLETE / EXCLUSION"),IF(AND(COUNTIF(A$4:A$203,A7)=1,COUNTIF(02_WBS!$A$4:$A$200,B7)=1,C7<>"",COUNTIF(03_Пакеты!$A$4:$A$203,C7)=1,IFERROR(INDEX(03_Пакеты!$B$4:$B$203,MATCH(C7,03_Пакеты!$A$4:$A$203,0)),"")=B7,E7<>"",F7<>"",F7<>"UNKNOWN",G7<>"",G7<>"UNKNOWN",OR(H7="REMAINING",H7="SUNK",H7="OUTSIDE"),ISNUMBER(I7),I7>=0,OR(AND(I7>0,Q7="KNOWN"),AND(I7=0,Q7="ZERO_CONFIRMED")),J7<>"",K7<>"",OR(AND(V7="KAC",COUNTIF(06_КАЦ!$A$4:$A$203,K7)=1,IFERROR(INDEX(06_КАЦ!$V$4:$V$203,MATCH(K7,06_КАЦ!$A$4:$A$203,0)),"")="SELECTED_READY",IFERROR(INDEX(06_КАЦ!$D$4:$D$203,MATCH(K7,06_КАЦ!$A$4:$A$203,0)),"")=C7,IFERROR(INDEX(06_КАЦ!$F$4:$F$203,MATCH(K7,06_КАЦ!$A$4:$A$203,0)),"")=J7),AND(V7="DIRECT",COUNTIF(06а_Оценки!$A$4:$A$203,K7)=1,IFERROR(INDEX(06а_Оценки!$N$4:$N$203,MATCH(K7,06а_Оценки!$A$4:$A$203,0)),"")="READY",IFERROR(INDEX(06а_Оценки!$B$4:$B$203,MATCH(K7,06а_Оценки!$A$4:$A$203,0)),"")=C7,IFERROR(INDEX(06а_Оценки!$E$4:$E$203,MATCH(K7,06а_Оценки!$A$4:$A$203,0)),"")=J7)),O7<>"",COUNTIF(13_Источники!$A$4:$A$203,O7)=1,P7<>"",R7<>""),"READY","INCOMPLETE / LINK"))) -> INCOMPLETE / LINK | Q7: UNKNOWN | R7: Серийное оборудование; повторное включение проектирования из пакетов поставщика
A8: EST-005 | B8: W02.20 | D8: Проект конструкции и изменений | L8: =IF(N8="READY",IF(V8="KAC",IFERROR(INDEX(06_КАЦ!$R$4:$R$203,MATCH(K8,06_КАЦ!$A$4:$A$203,0)),""),IFERROR(INDEX(06а_Оценки!$F$4:$F$203,MATCH(K8,06а_Оценки!$A$4:$A$203,0)),"")),"") | M8: =IF(N8="READY",ROUND(I8*L8,2),"") | N8: =IF(A8="","",IF(Q8="NOT_APPLICABLE",IF(AND(COUNTIF(A$4:A$203,A8)=1,H8="OUTSIDE",R8<>"",O8<>"",COUNTIF(13_Источники!$A$4:$A$203,O8)=1),"NOT_APPLICABLE","INCOMPLETE / EXCLUSION"),IF(AND(COUNTIF(A$4:A$203,A8)=1,COUNTIF(02_WBS!$A$4:$A$200,B8)=1,C8<>"",COUNTIF(03_Пакеты!$A$4:$A$203,C8)=1,IFERROR(INDEX(03_Пакеты!$B$4:$B$203,MATCH(C8,03_Пакеты!$A$4:$A$203,0)),"")=B8,E8<>"",F8<>"",F8<>"UNKNOWN",G8<>"",G8<>"UNKNOWN",OR(H8="REMAINING",H8="SUNK",H8="OUTSIDE"),ISNUMBER(I8),I8>=0,OR(AND(I8>0,Q8="KNOWN"),AND(I8=0,Q8="ZERO_CONFIRMED")),J8<>"",K8<>"",OR(AND(V8="KAC",COUNTIF(06_КАЦ!$A$4:$A$203,K8)=1,IFERROR(INDEX(06_КАЦ!$V$4:$V$203,MATCH(K8,06_КАЦ!$A$4:$A$203,0)),"")="SELECTED_READY",IFERROR(INDEX(06_КАЦ!$D$4:$D$203,MATCH(K8,06_КАЦ!$A$4:$A$203,0)),"")=C8,IFERROR(INDEX(06_КАЦ!$F$4:$F$203,MATCH(K8,06_КАЦ!$A$4:$A$203,0)),"")=J8),AND(V8="DIRECT",COUNTIF(06а_Оценки!$A$4:$A$203,K8)=1,IFERROR(INDEX(06а_Оценки!$N$4:$N$203,MATCH(K8,06а_Оценки!$A$4:$A$203,0)),"")="READY",IFERROR(INDEX(06а_Оценки!$B$4:$B$203,MATCH(K8,06а_Оценки!$A$4:$A$203,0)),"")=C8,IFERROR(INDEX(06а_Оценки!$E$4:$E$203,MATCH(K8,06а_Оценки!$A$4:$A$203,0)),"")=J8)),O8<>"",COUNTIF(13_Источники!$A$4:$A$203,O8)=1,P8<>"",R8<>""),"READY","INCOMPLETE / LINK"))) -> INCOMPLETE / LINK | Q8: UNKNOWN | R8: Материалы и изготовление W10; EXP-003 не рабочий проект
A9: EST-006 | B9: W02.30 | D9: Интерьерный проект и макеты помещаемости | L9: =IF(N9="READY",IF(V9="KAC",IFERROR(INDEX(06_КАЦ!$R$4:$R$203,MATCH(K9,06_КАЦ!$A$4:$A$203,0)),""),IFERROR(INDEX(06а_Оценки!$F$4:$F$203,MATCH(K9,06а_Оценки!$A$4:$A$203,0)),"")),"") | M9: =IF(N9="READY",ROUND(I9*L9,2),"") | N9: =IF(A9="","",IF(Q9="NOT_APPLICABLE",IF(AND(COUNTIF(A$4:A$203,A9)=1,H9="OUTSIDE",R9<>"",O9<>"",COUNTIF(13_Источники!$A$4:$A$203,O9)=1),"NOT_APPLICABLE","INCOMPLETE / EXCLUSION"),IF(AND(COUNTIF(A$4:A$203,A9)=1,COUNTIF(02_WBS!$A$4:$A$200,B9)=1,C9<>"",COUNTIF(03_Пакеты!$A$4:$A$203,C9)=1,IFERROR(INDEX(03_Пакеты!$B$4:$B$203,MATCH(C9,03_Пакеты!$A$4:$A$203,0)),"")=B9,E9<>"",F9<>"",F9<>"UNKNOWN",G9<>"",G9<>"UNKNOWN",OR(H9="REMAINING",H9="SUNK",H9="OUTSIDE"),ISNUMBER(I9),I9>=0,OR(AND(I9>0,Q9="KNOWN"),AND(I9=0,Q9="ZERO_CONFIRMED")),J9<>"",K9<>"",OR(AND(V9="KAC",COUNTIF(06_КАЦ!$A$4:$A$203,K9)=1,IFERROR(INDEX(06_КАЦ!$V$4:$V$203,MATCH(K9,06_КАЦ!$A$4:$A$203,0)),"")="SELECTED_READY",IFERROR(INDEX(06_КАЦ!$D$4:$D$203,MATCH(K9,06_КАЦ!$A$4:$A$203,0)),"")=C9,IFERROR(INDEX(06_КАЦ!$F$4:$F$203,MATCH(K9,06_КАЦ!$A$4:$A$203,0)),"")=J9),AND(V9="DIRECT",COUNTIF(06а_Оценки!$A$4:$A$203,K9)=1,IFERROR(INDEX(06а_Оценки!$N$4:$N$203,MATCH(K9,06а_Оценки!$A$4:$A$203,0)),"")="READY",IFERROR(INDEX(06а_Оценки!$B$4:$B$203,MATCH(K9,06а_Оценки!$A$4:$A$203,0)),"")=C9,IFERROR(INDEX(06а_Оценки!$E$4:$E$203,MATCH(K9,06а_Оценки!$A$4:$A$203,0)),"")=J9)),O9<>"",COUNTIF(13_Источники!$A$4:$A$203,O9)=1,P9<>"",R9<>""),"READY","INCOMPLETE / LINK"))) -> INCOMPLETE / LINK | Q9: UNKNOWN | R9: Серийная мебель и её монтаж; повторение общей CAD координации
A10: EST-007 | B10: W02.40 | D10: Применимость требований и согласования | L10: =IF(N10="READY",IF(V10="KAC",IFERROR(INDEX(06_КАЦ!$R$4:$R$203,MATCH(K10,06_КАЦ!$A$4:$A$203,0)),""),IFERROR(INDEX(06а_Оценки!$F$4:$F$203,MATCH(K10,06а_Оценки!$A$4:$A$203,0)),"")),"") | M10: =IF(N10="READY",ROUND(I10*L10,2),"") | N10: =IF(A10="","",IF(Q10="NOT_APPLICABLE",IF(AND(COUNTIF(A$4:A$203,A10)=1,H10="OUTSIDE",R10<>"",O10<>"",COUNTIF(13_Источники!$A$4:$A$203,O10)=1),"NOT_APPLICABLE","INCOMPLETE / EXCLUSION"),IF(AND(COUNTIF(A$4:A$203,A10)=1,COUNTIF(02_WBS!$A$4:$A$200,B10)=1,C10<>"",COUNTIF(03_Пакеты!$A$4:$A$203,C10)=1,IFERROR(INDEX(03_Пакеты!$B$4:$B$203,MATCH(C10,03_Пакеты!$A$4:$A$203,0)),"")=B10,E10<>"",F10<>"",F10<>"UNKNOWN",G10<>"",G10<>"UNKNOWN",OR(H10="REMAINING",H10="SUNK",H10="OUTSIDE"),ISNUMBER(I10),I10>=0,OR(AND(I10>0,Q10="KNOWN"),AND(I10=0,Q10="ZERO_CONFIRMED")),J10<>"",K10<>"",OR(AND(V10="KAC",COUNTIF(06_КАЦ!$A$4:$A$203,K10)=1,IFERROR(INDEX(06_КАЦ!$V$4:$V$203,MATCH(K10,06_КАЦ!$A$4:$A$203,0)),"")="SELECTED_READY",IFERROR(INDEX(06_КАЦ!$D$4:$D$203,MATCH(K10,06_КАЦ!$A$4:$A$203,0)),"")=C10,IFERROR(INDEX(06_КАЦ!$F$4:$F$203,MATCH(K10,06_КАЦ!$A$4:$A$203,0)),"")=J10),AND(V10="DIRECT",COUNTIF(06а_Оценки!$A$4:$A$203,K10)=1,IFERROR(INDEX(06а_Оценки!$N$4:$N$203,MATCH(K10,06а_Оценки!$A$4:$A$203,0)),"")="READY",IFERROR(INDEX(06а_Оценки!$B$4:$B$203,MATCH(K10,06а_Оценки!$A$4:$A$203,0)),"")=C10,IFERROR(INDEX(06а_Оценки!$E$4:$E$203,MATCH(K10,06а_Оценки!$A$4:$A$203,0)),"")=J10)),O10<>"",COUNTIF(13_Источники!$A$4:$A$203,O10)=1,P10<>"",R10<>""),"READY","INCOMPLETE / LINK"))) -> INCOMPLETE / LINK | Q10: UNKNOWN | R10: Согласования не назначены автоматически; инженерная разработка в W02.10–30
A11: EST-008 | B11: W10.10 | D11: Ремонт и завершение исходного корпуса | L11: =IF(N11="READY",IF(V11="KAC",IFERROR(INDEX(06_КАЦ!$R$4:$R$203,MATCH(K11,06_КАЦ!$A$4:$A$203,0)),""),IFERROR(INDEX(06а_Оценки!$F$4:$F$203,MATCH(K11,06а_Оценки!$A$4:$A$203,0)),"")),"") | M11: =IF(N11="READY",ROUND(I11*L11,2),"") | N11: =IF(A11="","",IF(Q11="NOT_APPLICABLE",IF(AND(COUNTIF(A$4:A$203,A11)=1,H11="OUTSIDE",R11<>"",O11<>"",COUNTIF(13_Источники!$A$4:$A$203,O11)=1),"NOT_APPLICABLE","INCOMPLETE / EXCLUSION"),IF(AND(COUNTIF(A$4:A$203,A11)=1,COUNTIF(02_WBS!$A$4:$A$200,B11)=1,C11<>"",COUNTIF(03_Пакеты!$A$4:$A$203,C11)=1,IFERROR(INDEX(03_Пакеты!$B$4:$B$203,MATCH(C11,03_Пакеты!$A$4:$A$203,0)),"")=B11,E11<>"",F11<>"",F11<>"UNKNOWN",G11<>"",G11<>"UNKNOWN",OR(H11="REMAINING",H11="SUNK",H11="OUTSIDE"),ISNUMBER(I11),I11>=0,OR(AND(I11>0,Q11="KNOWN"),AND(I11=0,Q11="ZERO_CONFIRMED")),J11<>"",K11<>"",OR(AND(V11="KAC",COUNTIF(06_КАЦ!$A$4:$A$203,K11)=1,IFERROR(INDEX(06_КАЦ!$V$4:$V$203,MATCH(K11,06_КАЦ!$A$4:$A$203,0)),"")="SELECTED_READY",IFERROR(INDEX(06_КАЦ!$D$4:$D$203,MATCH(K11,06_КАЦ!$A$4:$A$203,0)),"")=C11,IFERROR(INDEX(06_КАЦ!$F$4:$F$203,MATCH(K11,06_КАЦ!$A$4:$A$203,0)),"")=J11),AND(V11="DIRECT",COUNTIF(06а_Оценки!$A$4:$A$203,K11)=1,IFERROR(INDEX(06а_Оценки!$N$4:$N$203,MATCH(K11,06а_Оценки!$A$4:$A$203,0)),"")="READY",IFERROR(INDEX(06а_Оценки!$B$4:$B$203,MATCH(K11,06а_Оценки!$A$4:$A$203,0)),"")=C11,IFERROR(INDEX(06а_Оценки!$E$4:$E$203,MATCH(K11,06а_Оценки!$A$4:$A$203,0)),"")=J11)),O11<>"",COUNTIF(13_Источники!$A$4:$A$203,O11)=1,P11<>"",R11<>""),"READY","INCOMPLETE / LINK"))) -> INCOMPLETE / LINK | Q11: UNKNOWN | R11: Стоимость уже имеющегося корпуса; будущие изменения W10.20–40; покрытия W10.70–80
A12: EST-009 | B12: W10.20 | D12: Новая рубка и hardtop | L12: =IF(N12="READY",IF(V12="KAC",IFERROR(INDEX(06_КАЦ!$R$4:$R$203,MATCH(K12,06_КАЦ!$A$4:$A$203,0)),""),IFERROR(INDEX(06а_Оценки!$F$4:$F$203,MATCH(K12,06а_Оценки!$A$4:$A$203,0)),"")),"") | M12: =IF(N12="READY",ROUND(I12*L12,2),"") | N12: =IF(A12="","",IF(Q12="NOT_APPLICABLE",IF(AND(COUNTIF(A$4:A$203,A12)=1,H12="OUTSIDE",R12<>"",O12<>"",COUNTIF(13_Источники!$A$4:$A$203,O12)=1),"NOT_APPLICABLE","INCOMPLETE / EXCLUSION"),IF(AND(COUNTIF(A$4:A$203,A12)=1,COUNTIF(02_WBS!$A$4:$A$200,B12)=1,C12<>"",COUNTIF(03_Пакеты!$A$4:$A$203,C12)=1,IFERROR(INDEX(03_Пакеты!$B$4:$B$203,MATCH(C12,03_Пакеты!$A$4:$A$203,0)),"")=B12,E12<>"",F12<>"",F12<>"UNKNOWN",G12<>"",G12<>"UNKNOWN",OR(H12="REMAINING",H12="SUNK",H12="OUTSIDE"),ISNUMBER(I12),I12>=0,OR(AND(I12>0,Q12="KNOWN"),AND(I12=0,Q12="ZERO_CONFIRMED")),J12<>"",K12<>"",OR(AND(V12="KAC",COUNTIF(06_КАЦ!$A$4:$A$203,K12)=1,IFERROR(INDEX(06_КАЦ!$V$4:$V$203,MATCH(K12,06_КАЦ!$A$4:$A$203,0)),"")="SELECTED_READY",IFERROR(INDEX(06_КАЦ!$D$4:$D$203,MATCH(K12,06_КАЦ!$A$4:$A$203,0)),"")=C12,IFERROR(INDEX(06_КАЦ!$F$4:$F$203,MATCH(K12,06_КАЦ!$A$4:$A$203,0)),"")=J12),AND(V12="DIRECT",COUNTIF(06а_Оценки!$A$4:$A$203,K12)=1,IFERROR(INDEX(06а_Оценки!$N$4:$N$203,MATCH(K12,06а_Оценки!$A$4:$A$203,0)),"")="READY",IFERROR(INDEX(06а_Оценки!$B$4:$B$203,MATCH(K12,06а_Оценки!$A$4:$A$203,0)),"")=C12,IFERROR(INDEX(06а_Оценки!$E$4:$E$203,MATCH(K12,06а_Оценки!$A$4:$A$203,0)),"")=J12)),O12<>"",COUNTIF(13_Источники!$A$4:$A$203,O12)=1,P12<>"",R12<>""),"READY","INCOMPLETE / LINK"))) -> INCOMPLETE / LINK | Q12: UNKNOWN | R12: Остекление W20.10; интерьер W60; электрические/жидкостные сети; смета по массе визуальной сетки
A13: EST-010 | B13: W10.30 | D13: Корма, гараж и встроенная дверь | L13: =IF(N13="READY",IF(V13="KAC",IFERROR(INDEX(06_КАЦ!$R$4:$R$203,MATCH(K13,06_КАЦ!$A$4:$A$203,0)),""),IFERROR(INDEX(06а_Оценки!$F$4:$F$203,MATCH(K13,06а_Оценки!$A$4:$A$203,0)),"")),"") | M13: =IF(N13="READY",ROUND(I13*L13,2),"") | N13: =IF(A13="","",IF(Q13="NOT_APPLICABLE",IF(AND(COUNTIF(A$4:A$203,A13)=1,H13="OUTSIDE",R13<>"",O13<>"",COUNTIF(13_Источники!$A$4:$A$203,O13)=1),"NOT_APPLICABLE","INCOMPLETE / EXCLUSION"),IF(AND(COUNTIF(A$4:A$203,A13)=1,COUNTIF(02_WBS!$A$4:$A$200,B13)=1,C13<>"",COUNTIF(03_Пакеты!$A$4:$A$203,C13)=1,IFERROR(INDEX(03_Пакеты!$B$4:$B$203,MATCH(C13,03_Пакеты!$A$4:$A$203,0)),"")=B13,E13<>"",F13<>"",F13<>"UNKNOWN",G13<>"",G13<>"UNKNOWN",OR(H13="REMAINING",H13="SUNK",H13="OUTSIDE"),ISNUMBER(I13),I13>=0,OR(AND(I13>0,Q13="KNOWN"),AND(I13=0,Q13="ZERO_CONFIRMED")),J13<>"",K13<>"",OR(AND(V13="KAC",COUNTIF(06_КАЦ!$A$4:$A$203,K13)=1,IFERROR(INDEX(06_КАЦ!$V$4:$V$203,MATCH(K13,06_КАЦ!$A$4:$A$203,0)),"")="SELECTED_READY",IFERROR(INDEX(06_КАЦ!$D$4:$D$203,MATCH(K13,06_КАЦ!$A$4:$A$203,0)),"")=C13,IFERROR(INDEX(06_КАЦ!$F$4:$F$203,MATCH(K13,06_КАЦ!$A$4:$A$203,0)),"")=J13),AND(V13="DIRECT",COUNTIF(06а_Оценки!$A$4:$A$203,K13)=1,IFERROR(INDEX(06а_Оценки!$N$4:$N$203,MATCH(K13,06а_Оценки!$A$4:$A$203,0)),"")="READY",IFERROR(INDEX(06а_Оценки!$B$4:$B$203,MATCH(K13,06а_Оценки!$A$4:$A$203,0)),"")=C13,IFERROR(INDEX(06а_Оценки!$E$4:$E$203,MATCH(K13,06а_Оценки!$A$4:$A$203,0)),"")=J13)),O13<>"",COUNTIF(13_Источники!$A$4:$A$203,O13)=1,P13<>"",R13<>""),"READY","INCOMPLETE / LINK"))) -> INCOMPLETE / LINK | Q13: UNKNOWN | R13: Тендер/балка W20.70–80; привод двери W20.80; отделка и системы
A14: EST-011 | B14: W10.40 | D14: Фальшборт, корпусные вырезы и проходы | L14: =IF(N14="READY",IF(V14="KAC",IFERROR(INDEX(06_КАЦ!$R$4:$R$203,MATCH(K14,06_КАЦ!$A$4:$A$203,0)),""),IFERROR(INDEX(06а_Оценки!$F$4:$F$203,MATCH(K14,06а_Оценки!$A$4:$A$203,0)),"")),"") | M14: =IF(N14="READY",ROUND(I14*L14,2),"") | N14: =IF(A14="","",IF(Q14="NOT_APPLICABLE",IF(AND(COUNTIF(A$4:A$203,A14)=1,H14="OUTSIDE",R14<>"",O14<>"",COUNTIF(13_Источники!$A$4:$A$203,O14)=1),"NOT_APPLICABLE","INCOMPLETE / EXCLUSION"),IF(AND(COUNTIF(A$4:A$203,A14)=1,COUNTIF(02_WBS!$A$4:$A$200,B14)=1,C14<>"",COUNTIF(03_Пакеты!$A$4:$A$203,C14)=1,IFERROR(INDEX(03_Пакеты!$B$4:$B$203,MATCH(C14,03_Пакеты!$A$4:$A$203,0)),"")=B14,E14<>"",F14<>"",F14<>"UNKNOWN",G14<>"",G14<>"UNKNOWN",OR(H14="REMAINING",H14="SUNK",H14="OUTSIDE"),ISNUMBER(I14),I14>=0,OR(AND(I14>0,Q14="KNOWN"),AND(I14=0,Q14="ZERO_CONFIRMED")),J14<>"",K14<>"",OR(AND(V14="KAC",COUNTIF(06_КАЦ!$A$4:$A$203,K14)=1,IFERROR(INDEX(06_КАЦ!$V$4:$V$203,MATCH(K14,06_КАЦ!$A$4:$A$203,0)),"")="SELECTED_READY",IFERROR(INDEX(06_КАЦ!$D$4:$D$203,MATCH(K14,06_КАЦ!$A$4:$A$203,0)),"")=C14,IFERROR(INDEX(06_КАЦ!$F$4:$F$203,MATCH(K14,06_КАЦ!$A$4:$A$203,0)),"")=J14),AND(V14="DIRECT",COUNTIF(06а_Оценки!$A$4:$A$203,K14)=1,IFERROR(INDEX(06а_Оценки!$N$4:$N$203,MATCH(K14,06а_Оценки!$A$4:$A$203,0)),"")="READY",IFERROR(INDEX(06а_Оценки!$B$4:$B$203,MATCH(K14,06а_Оценки!$A$4:$A$203,0)),"")=C14,IFERROR(INDEX(06а_Оценки!$E$4:$E$203,MATCH(K14,06а_Оценки!$A$4:$A$203,0)),"")=J14)),O14<>"",COUNTIF(13_Источники!$A$4:$A$203,O14)=1,P14<>"",R14<>""),"READY","INCOMPLETE / LINK"))) -> INCOMPLETE / LINK | Q14: UNKNOWN | R14: Съёмные клюзы/утки/релинги W20; трубные системы палубного отвода и стоков W50; уже включённые в W10.20–30 отверстия; интегральные танки W10.90; аноды W10.85
A15: EST-012 | B15: W10.50 | D15: Корпусные фундаменты и встроенные опоры | L15: =IF(N15="READY",IF(V15="KAC",IFERROR(INDEX(06_КАЦ!$R$4:$R$203,MATCH(K15,06_КАЦ!$A$4:$A$203,0)),""),IFERROR(INDEX(06а_Оценки!$F$4:$F$203,MATCH(K15,06а_Оценки!$A$4:$A$203,0)),"")),"") | M15: =IF(N15="READY",ROUND(I15*L15,2),"") | N15: =IF(A15="","",IF(Q15="NOT_APPLICABLE",IF(AND(COUNTIF(A$4:A$203,A15)=1,H15="OUTSIDE",R15<>"",O15<>"",COUNTIF(13_Источники!$A$4:$A$203,O15)=1),"NOT_APPLICABLE","INCOMPLETE / EXCLUSION"),IF(AND(COUNTIF(A$4:A$203,A15)=1,COUNTIF(02_WBS!$A$4:$A$200,B15)=1,C15<>"",COUNTIF(03_Пакеты!$A$4:$A$203,C15)=1,IFERROR(INDEX(03_Пакеты!$B$4:$B$203,MATCH(C15,03_Пакеты!$A$4:$A$203,0)),"")=B15,E15<>"",F15<>"",F15<>"UNKNOWN",G15<>"",G15<>"UNKNOWN",OR(H15="REMAINING",H15="SUNK",H15="OUTSIDE"),ISNUMBER(I15),I15>=0,OR(AND(I15>0,Q15="KNOWN"),AND(I15=0,Q15="ZERO_CONFIRMED")),J15<>"",K15<>"",OR(AND(V15="KAC",COUNTIF(06_КАЦ!$A$4:$A$203,K15)=1,IFERROR(INDEX(06_КАЦ!$V$4:$V$203,MATCH(K15,06_КАЦ!$A$4:$A$203,0)),"")="SELECTED_READY",IFERROR(INDEX(06_КАЦ!$D$4:$D$203,MATCH(K15,06_КАЦ!$A$4:$A$203,0)),"")=C15,IFERROR(INDEX(06_КАЦ!$F$4:$F$203,MATCH(K15,06_КАЦ!$A$4:$A$203,0)),"")=J15),AND(V15="DIRECT",COUNTIF(06а_Оценки!$A$4:$A$203,K15)=1,IFERROR(INDEX(06а_Оценки!$N$4:$N$203,MATCH(K15,06а_Оценки!$A$4:$A$203,0)),"")="READY",IFERROR(INDEX(06а_Оценки!$B$4:$B$203,MATCH(K15,06а_Оценки!$A$4:$A$203,0)),"")=C15,IFERROR(INDEX(06а_Оценки!$E$4:$E$203,MATCH(K15,06а_Оценки!$A$4:$A$203,0)),"")=J15)),O15<>"",COUNTIF(13_Источники!$A$4:$A$203,O15)=1,P15<>"",R15<>""),"READY","INCOMPLETE / LINK"))) -> INCOMPLETE / LINK | Q15: UNKNOWN | R15: Рамы в составе купленного агрегата; виброопоры и окончательная установка систем; уже включённые в другие W10 позиции
... A75: EST-072 | B75: W90.50 | D75: Страхование строительства и согласованные сборы | L75: =IF(N75="READY",IF(V75="KAC",IFERROR(INDEX(06_КАЦ!$R$4:$R$203,MATCH(K75,06_КАЦ!$A$4:$A$203,0)),""),IFERROR(INDEX(06а_Оценки!$F$4:$F$203,MATCH(K75,06а_Оценки!$A$4:$A$203,0)),"")),"") | M75: =IF(N75="READY",ROUND(I75*L75,2),"") | N75: =IF(A75="","",IF(Q75="NOT_APPLICABLE",IF(AND(COUNTIF(A$4:A$203,A75)=1,H75="OUTSIDE",R75<>"",O75<>"",COUNTIF(13_Источники!$A$4:$A$203,O75)=1),"NOT_APPLICABLE","INCOMPLETE / EXCLUSION"),IF(AND(COUNTIF(A$4:A$203,A75)=1,COUNTIF(02_WBS!$A$4:$A$200,B75)=1,C75<>"",COUNTIF(03_Пакеты!$A$4:$A$203,C75)=1,IFERROR(INDEX(03_Пакеты!$B$4:$B$203,MATCH(C75,03_Пакеты!$A$4:$A$203,0)),"")=B75,E75<>"",F75<>"",F75<>"UNKNOWN",G75<>"",G75<>"UNKNOWN",OR(H75="REMAINING",H75="SUNK",H75="OUTSIDE"),ISNUMBER(I75),I75>=0,OR(AND(I75>0,Q75="KNOWN"),AND(I75=0,Q75="ZERO_CONFIRMED")),J75<>"",K75<>"",OR(AND(V75="KAC",COUNTIF(06_КАЦ!$A$4:$A$203,K75)=1,IFERROR(INDEX(06_КАЦ!$V$4:$V$203,MATCH(K75,06_КАЦ!$A$4:$A$203,0)),"")="SELECTED_READY",IFERROR(INDEX(06_КАЦ!$D$4:$D$203,MATCH(K75,06_КАЦ!$A$4:$A$203,0)),"")=C75,IFERROR(INDEX(06_КАЦ!$F$4:$F$203,MATCH(K75,06_КАЦ!$A$4:$A$203,0)),"")=J75),AND(V75="DIRECT",COUNTIF(06а_Оценки!$A$4:$A$203,K75)=1,IFERROR(INDEX(06а_Оценки!$N$4:$N$203,MATCH(K75,06а_Оценки!$A$4:$A$203,0)),"")="READY",IFERROR(INDEX(06а_Оценки!$B$4:$B$203,MATCH(K75,06а_Оценки!$A$4:$A$203,0)),"")=C75,IFERROR(INDEX(06а_Оценки!$E$4:$E$203,MATCH(K75,06а_Оценки!$A$4:$A$203,0)),"")=J75)),O75<>"",COUNTIF(13_Источники!$A$4:$A$203,O75)=1,P75<>"",R75<>""),"READY","INCOMPLETE / LINK"))) -> INCOMPLETE / LINK | Q75: UNKNOWN | R75: Включённые страховки подрядчиков; эксплуатационные расходы после передачи
L76: =IF(N76="READY",IF(V76="KAC",IFERROR(INDEX(06_КАЦ!$R$4:$R$203,MATCH(K76,06_КАЦ!$A$4:$A$203,0)),""),IFERROR(INDEX(06а_Оценки!$F$4:$F$203,MATCH(K76,06а_Оценки!$A$4:$A$203,0)),"")),"") | M76: =IF(N76="READY",ROUND(I76*L76,2),"") | N76: =IF(A76="","",IF(Q76="NOT_APPLICABLE",IF(AND(COUNTIF(A$4:A$203,A76)=1,H76="OUTSIDE",R76<>"",O76<>"",COUNTIF(13_Источники!$A$4:$A$203,O76)=1),"NOT_APPLICABLE","INCOMPLETE / EXCLUSION"),IF(AND(COUNTIF(A$4:A$203,A76)=1,COUNTIF(02_WBS!$A$4:$A$200,B76)=1,C76<>"",COUNTIF(03_Пакеты!$A$4:$A$203,C76)=1,IFERROR(INDEX(03_Пакеты!$B$4:$B$203,MATCH(C76,03_Пакеты!$A$4:$A$203,0)),"")=B76,E76<>"",F76<>"",F76<>"UNKNOWN",G76<>"",G76<>"UNKNOWN",OR(H76="REMAINING",H76="SUNK",H76="OUTSIDE"),ISNUMBER(I76),I76>=0,OR(AND(I76>0,Q76="KNOWN"),AND(I76=0,Q76="ZERO_CONFIRMED")),J76<>"",K76<>"",OR(AND(V76="KAC",COUNTIF(06_КАЦ!$A$4:$A$203,K76)=1,IFERROR(INDEX(06_КАЦ!$V$4:$V$203,MATCH(K76,06_КАЦ!$A$4:$A$203,0)),"")="SELECTED_READY",IFERROR(INDEX(06_КАЦ!$D$4:$D$203,MATCH(K76,06_КАЦ!$A$4:$A$203,0)),"")=C76,IFERROR(INDEX(06_КАЦ!$F$4:$F$203,MATCH(K76,06_КАЦ!$A$4:$A$203,0)),"")=J76),AND(V76="DIRECT",COUNTIF(06а_Оценки!$A$4:$A$203,K76)=1,IFERROR(INDEX(06а_Оценки!$N$4:$N$203,MATCH(K76,06а_Оценки!$A$4:$A$203,0)),"")="READY",IFERROR(INDEX(06а_Оценки!$B$4:$B$203,MATCH(K76,06а_Оценки!$A$4:$A$203,0)),"")=C76,IFERROR(INDEX(06а_Оценки!$E$4:$E$203,MATCH(K76,06а_Оценки!$A$4:$A$203,0)),"")=J76)),O76<>"",COUNTIF(13_Источники!$A$4:$A$203,O76)=1,P76<>"",R76<>""),"READY","INCOMPLETE / LINK")))
L77: =IF(N77="READY",IF(V77="KAC",IFERROR(INDEX(06_КАЦ!$R$4:$R$203,MATCH(K77,06_КАЦ!$A$4:$A$203,0)),""),IFERROR(INDEX(06а_Оценки!$F$4:$F$203,MATCH(K77,06а_Оценки!$A$4:$A$203,0)),"")),"") | M77: =IF(N77="READY",ROUND(I77*L77,2),"") | N77: =IF(A77="","",IF(Q77="NOT_APPLICABLE",IF(AND(COUNTIF(A$4:A$203,A77)=1,H77="OUTSIDE",R77<>"",O77<>"",COUNTIF(13_Источники!$A$4:$A$203,O77)=1),"NOT_APPLICABLE","INCOMPLETE / EXCLUSION"),IF(AND(COUNTIF(A$4:A$203,A77)=1,COUNTIF(02_WBS!$A$4:$A$200,B77)=1,C77<>"",COUNTIF(03_Пакеты!$A$4:$A$203,C77)=1,IFERROR(INDEX(03_Пакеты!$B$4:$B$203,MATCH(C77,03_Пакеты!$A$4:$A$203,0)),"")=B77,E77<>"",F77<>"",F77<>"UNKNOWN",G77<>"",G77<>"UNKNOWN",OR(H77="REMAINING",H77="SUNK",H77="OUTSIDE"),ISNUMBER(I77),I77>=0,OR(AND(I77>0,Q77="KNOWN"),AND(I77=0,Q77="ZERO_CONFIRMED")),J77<>"",K77<>"",OR(AND(V77="KAC",COUNTIF(06_КАЦ!$A$4:$A$203,K77)=1,IFERROR(INDEX(06_КАЦ!$V$4:$V$203,MATCH(K77,06_КАЦ!$A$4:$A$203,0)),"")="SELECTED_READY",IFERROR(INDEX(06_КАЦ!$D$4:$D$203,MATCH(K77,06_КАЦ!$A$4:$A$203,0)),"")=C77,IFERROR(INDEX(06_КАЦ!$F$4:$F$203,MATCH(K77,06_КАЦ!$A$4:$A$203,0)),"")=J77),AND(V77="DIRECT",COUNTIF(06а_Оценки!$A$4:$A$203,K77)=1,IFERROR(INDEX(06а_Оценки!$N$4:$N$203,MATCH(K77,06а_Оценки!$A$4:$A$203,0)),"")="READY",IFERROR(INDEX(06а_Оценки!$B$4:$B$203,MATCH(K77,06а_Оценки!$A$4:$A$203,0)),"")=C77,IFERROR(INDEX(06а_Оценки!$E$4:$E$203,MATCH(K77,06а_Оценки!$A$4:$A$203,0)),"")=J77)),O77<>"",COUNTIF(13_Источники!$A$4:$A$203,O77)=1,P77<>"",R77<>""),"READY","INCOMPLETE / LINK")))
L78: =IF(N78="READY",IF(V78="KAC",IFERROR(INDEX(06_КАЦ!$R$4:$R$203,MATCH(K78,06_КАЦ!$A$4:$A$203,0)),""),IFERROR(INDEX(06а_Оценки!$F$4:$F$203,MATCH(K78,06а_Оценки!$A$4:$A$203,0)),"")),"") | M78: =IF(N78="READY",ROUND(I78*L78,2),"") | N78: =IF(A78="","",IF(Q78="NOT_APPLICABLE",IF(AND(COUNTIF(A$4:A$203,A78)=1,H78="OUTSIDE",R78<>"",O78<>"",COUNTIF(13_Источники!$A$4:$A$203,O78)=1),"NOT_APPLICABLE","INCOMPLETE / EXCLUSION"),IF(AND(COUNTIF(A$4:A$203,A78)=1,COUNTIF(02_WBS!$A$4:$A$200,B78)=1,C78<>"",COUNTIF(03_Пакеты!$A$4:$A$203,C78)=1,IFERROR(INDEX(03_Пакеты!$B$4:$B$203,MATCH(C78,03_Пакеты!$A$4:$A$203,0)),"")=B78,E78<>"",F78<>"",F78<>"UNKNOWN",G78<>"",G78<>"UNKNOWN",OR(H78="REMAINING",H78="SUNK",H78="OUTSIDE"),ISNUMBER(I78),I78>=0,OR(AND(I78>0,Q78="KNOWN"),AND(I78=0,Q78="ZERO_CONFIRMED")),J78<>"",K78<>"",OR(AND(V78="KAC",COUNTIF(06_КАЦ!$A$4:$A$203,K78)=1,IFERROR(INDEX(06_КАЦ!$V$4:$V$203,MATCH(K78,06_КАЦ!$A$4:$A$203,0)),"")="SELECTED_READY",IFERROR(INDEX(06_КАЦ!$D$4:$D$203,MATCH(K78,06_КАЦ!$A$4:$A$203,0)),"")=C78,IFERROR(INDEX(06_КАЦ!$F$4:$F$203,MATCH(K78,06_КАЦ!$A$4:$A$203,0)),"")=J78),AND(V78="DIRECT",COUNTIF(06а_Оценки!$A$4:$A$203,K78)=1,IFERROR(INDEX(06а_Оценки!$N$4:$N$203,MATCH(K78,06а_Оценки!$A$4:$A$203,0)),"")="READY",IFERROR(INDEX(06а_Оценки!$B$4:$B$203,MATCH(K78,06а_Оценки!$A$4:$A$203,0)),"")=C78,IFERROR(INDEX(06а_Оценки!$E$4:$E$203,MATCH(K78,06а_Оценки!$A$4:$A$203,0)),"")=J78)),O78<>"",COUNTIF(13_Источники!$A$4:$A$203,O78)=1,P78<>"",R78<>""),"READY","INCOMPLETE / LINK")))
L79: =IF(N79="READY",IF(V79="KAC",IFERROR(INDEX(06_КАЦ!$R$4:$R$203,MATCH(K79,06_КАЦ!$A$4:$A$203,0)),""),IFERROR(INDEX(06а_Оценки!$F$4:$F$203,MATCH(K79,06а_Оценки!$A$4:$A$203,0)),"")),"") | M79: =IF(N79="READY",ROUND(I79*L79,2),"") | N79: =IF(A79="","",IF(Q79="NOT_APPLICABLE",IF(AND(COUNTIF(A$4:A$203,A79)=1,H79="OUTSIDE",R79<>"",O79<>"",COUNTIF(13_Источники!$A$4:$A$203,O79)=1),"NOT_APPLICABLE","INCOMPLETE / EXCLUSION"),IF(AND(COUNTIF(A$4:A$203,A79)=1,COUNTIF(02_WBS!$A$4:$A$200,B79)=1,C79<>"",COUNTIF(03_Пакеты!$A$4:$A$203,C79)=1,IFERROR(INDEX(03_Пакеты!$B$4:$B$203,MATCH(C79,03_Пакеты!$A$4:$A$203,0)),"")=B79,E79<>"",F79<>"",F79<>"UNKNOWN",G79<>"",G79<>"UNKNOWN",OR(H79="REMAINING",H79="SUNK",H79="OUTSIDE"),ISNUMBER(I79),I79>=0,OR(AND(I79>0,Q79="KNOWN"),AND(I79=0,Q79="ZERO_CONFIRMED")),J79<>"",K79<>"",OR(AND(V79="KAC",COUNTIF(06_КАЦ!$A$4:$A$203,K79)=1,IFERROR(INDEX(06_КАЦ!$V$4:$V$203,MATCH(K79,06_КАЦ!$A$4:$A$203,0)),"")="SELECTED_READY",IFERROR(INDEX(06_КАЦ!$D$4:$D$203,MATCH(K79,06_КАЦ!$A$4:$A$203,0)),"")=C79,IFERROR(INDEX(06_КАЦ!$F$4:$F$203,MATCH(K79,06_КАЦ!$A$4:$A$203,0)),"")=J79),AND(V79="DIRECT",COUNTIF(06а_Оценки!$A$4:$A$203,K79)=1,IFERROR(INDEX(06а_Оценки!$N$4:$N$203,MATCH(K79,06а_Оценки!$A$4:$A$203,0)),"")="READY",IFERROR(INDEX(06а_Оценки!$B$4:$B$203,MATCH(K79,06а_Оценки!$A$4:$A$203,0)),"")=C79,IFERROR(INDEX(06а_Оценки!$E$4:$E$203,MATCH(K79,06а_Оценки!$A$4:$A$203,0)),"")=J79)),O79<>"",COUNTIF(13_Источники!$A$4:$A$203,O79)=1,P79<>"",R79<>""),"READY","INCOMPLETE / LINK")))
L80: =IF(N80="READY",IF(V80="KAC",IFERROR(INDEX(06_КАЦ!$R$4:$R$203,MATCH(K80,06_КАЦ!$A$4:$A$203,0)),""),IFERROR(INDEX(06а_Оценки!$F$4:$F$203,MATCH(K80,06а_Оценки!$A$4:$A$203,0)),"")),"") | M80: =IF(N80="READY",ROUND(I80*L80,2),"") | N80: =IF(A80="","",IF(Q80="NOT_APPLICABLE",IF(AND(COUNTIF(A$4:A$203,A80)=1,H80="OUTSIDE",R80<>"",O80<>"",COUNTIF(13_Источники!$A$4:$A$203,O80)=1),"NOT_APPLICABLE","INCOMPLETE / EXCLUSION"),IF(AND(COUNTIF(A$4:A$203,A80)=1,COUNTIF(02_WBS!$A$4:$A$200,B80)=1,C80<>"",COUNTIF(03_Пакеты!$A$4:$A$203,C80)=1,IFERROR(INDEX(03_Пакеты!$B$4:$B$203,MATCH(C80,03_Пакеты!$A$4:$A$203,0)),"")=B80,E80<>"",F80<>"",F80<>"UNKNOWN",G80<>"",G80<>"UNKNOWN",OR(H80="REMAINING",H80="SUNK",H80="OUTSIDE"),ISNUMBER(I80),I80>=0,OR(AND(I80>0,Q80="KNOWN"),AND(I80=0,Q80="ZERO_CONFIRMED")),J80<>"",K80<>"",OR(AND(V80="KAC",COUNTIF(06_КАЦ!$A$4:$A$203,K80)=1,IFERROR(INDEX(06_КАЦ!$V$4:$V$203,MATCH(K80,06_КАЦ!$A$4:$A$203,0)),"")="SELECTED_READY",IFERROR(INDEX(06_КАЦ!$D$4:$D$203,MATCH(K80,06_КАЦ!$A$4:$A$203,0)),"")=C80,IFERROR(INDEX(06_КАЦ!$F$4:$F$203,MATCH(K80,06_КАЦ!$A$4:$A$203,0)),"")=J80),AND(V80="DIRECT",COUNTIF(06а_Оценки!$A$4:$A$203,K80)=1,IFERROR(INDEX(06а_Оценки!$N$4:$N$203,MATCH(K80,06а_Оценки!$A$4:$A$203,0)),"")="READY",IFERROR(INDEX(06а_Оценки!$B$4:$B$203,MATCH(K80,06а_Оценки!$A$4:$A$203,0)),"")=C80,IFERROR(INDEX(06а_Оценки!$E$4:$E$203,MATCH(K80,06а_Оценки!$A$4:$A$203,0)),"")=J80)),O80<>"",COUNTIF(13_Источники!$A$4:$A$203,O80)=1,P80<>"",R80<>""),"READY","INCOMPLETE / LINK")))
L81: =IF(N81="READY",IF(V81="KAC",IFERROR(INDEX(06_КАЦ!$R$4:$R$203,MATCH(K81,06_КАЦ!$A$4:$A$203,0)),""),IFERROR(INDEX(06а_Оценки!$F$4:$F$203,MATCH(K81,06а_Оценки!$A$4:$A$203,0)),"")),"") | M81: =IF(N81="READY",ROUND(I81*L81,2),"") | N81: =IF(A81="","",IF(Q81="NOT_APPLICABLE",IF(AND(COUNTIF(A$4:A$203,A81)=1,H81="OUTSIDE",R81<>"",O81<>"",COUNTIF(13_Источники!$A$4:$A$203,O81)=1),"NOT_APPLICABLE","INCOMPLETE / EXCLUSION"),IF(AND(COUNTIF(A$4:A$203,A81)=1,COUNTIF(02_WBS!$A$4:$A$200,B81)=1,C81<>"",COUNTIF(03_Пакеты!$A$4:$A$203,C81)=1,IFERROR(INDEX(03_Пакеты!$B$4:$B$203,MATCH(C81,03_Пакеты!$A$4:$A$203,0)),"")=B81,E81<>"",F81<>"",F81<>"UNKNOWN",G81<>"",G81<>"UNKNOWN",OR(H81="REMAINING",H81="SUNK",H81="OUTSIDE"),ISNUMBER(I81),I81>=0,OR(AND(I81>0,Q81="KNOWN"),AND(I81=0,Q81="ZERO_CONFIRMED")),J81<>"",K81<>"",OR(AND(V81="KAC",COUNTIF(06_КАЦ!$A$4:$A$203,K81)=1,IFERROR(INDEX(06_КАЦ!$V$4:$V$203,MATCH(K81,06_КАЦ!$A$4:$A$203,0)),"")="SELECTED_READY",IFERROR(INDEX(06_КАЦ!$D$4:$D$203,MATCH(K81,06_КАЦ!$A$4:$A$203,0)),"")=C81,IFERROR(INDEX(06_КАЦ!$F$4:$F$203,MATCH(K81,06_КАЦ!$A$4:$A$203,0)),"")=J81),AND(V81="DIRECT",COUNTIF(06а_Оценки!$A$4:$A$203,K81)=1,IFERROR(INDEX(06а_Оценки!$N$4:$N$203,MATCH(K81,06а_Оценки!$A$4:$A$203,0)),"")="READY",IFERROR(INDEX(06а_Оценки!$B$4:$B$203,MATCH(K81,06а_Оценки!$A$4:$A$203,0)),"")=C81,IFERROR(INDEX(06а_Оценки!$E$4:$E$203,MATCH(K81,06а_Оценки!$A$4:$A$203,0)),"")=J81)),O81<>"",COUNTIF(13_Источники!$A$4:$A$203,O81)=1,P81<>"",R81<>""),"READY","INCOMPLETE / LINK")))
L82: =IF(N82="READY",IF(V82="KAC",IFERROR(INDEX(06_КАЦ!$R$4:$R$203,MATCH(K82,06_КАЦ!$A$4:$A$203,0)),""),IFERROR(INDEX(06а_Оценки!$F$4:$F$203,MATCH(K82,06а_Оценки!$A$4:$A$203,0)),"")),"") | M82: =IF(N82="READY",ROUND(I82*L82,2),"") | N82: =IF(A82="","",IF(Q82="NOT_APPLICABLE",IF(AND(COUNTIF(A$4:A$203,A82)=1,H82="OUTSIDE",R82<>"",O82<>"",COUNTIF(13_Источники!$A$4:$A$203,O82)=1),"NOT_APPLICABLE","INCOMPLETE / EXCLUSION"),IF(AND(COUNTIF(A$4:A$203,A82)=1,COUNTIF(02_WBS!$A$4:$A$200,B82)=1,C82<>"",COUNTIF(03_Пакеты!$A$4:$A$203,C82)=1,IFERROR(INDEX(03_Пакеты!$B$4:$B$203,MATCH(C82,03_Пакеты!$A$4:$A$203,0)),"")=B82,E82<>"",F82<>"",F82<>"UNKNOWN",G82<>"",G82<>"UNKNOWN",OR(H82="REMAINING",H82="SUNK",H82="OUTSIDE"),ISNUMBER(I82),I82>=0,OR(AND(I82>0,Q82="KNOWN"),AND(I82=0,Q82="ZERO_CONFIRMED")),J82<>"",K82<>"",OR(AND(V82="KAC",COUNTIF(06_КАЦ!$A$4:$A$203,K82)=1,IFERROR(INDEX(06_КАЦ!$V$4:$V$203,MATCH(K82,06_КАЦ!$A$4:$A$203,0)),"")="SELECTED_READY",IFERROR(INDEX(06_КАЦ!$D$4:$D$203,MATCH(K82,06_КАЦ!$A$4:$A$203,0)),"")=C82,IFERROR(INDEX(06_КАЦ!$F$4:$F$203,MATCH(K82,06_КАЦ!$A$4:$A$203,0)),"")=J82),AND(V82="DIRECT",COUNTIF(06а_Оценки!$A$4:$A$203,K82)=1,IFERROR(INDEX(06а_Оценки!$N$4:$N$203,MATCH(K82,06а_Оценки!$A$4:$A$203,0)),"")="READY",IFERROR(INDEX(06а_Оценки!$B$4:$B$203,MATCH(K82,06а_Оценки!$A$4:$A$203,0)),"")=C82,IFERROR(INDEX(06а_Оценки!$E$4:$E$203,MATCH(K82,06а_Оценки!$A$4:$A$203,0)),"")=J82)),O82<>"",COUNTIF(13_Источники!$A$4:$A$203,O82)=1,P82<>"",R82<>""),"READY","INCOMPLETE / LINK")))
L83: =IF(N83="READY",IF(V83="KAC",IFERROR(INDEX(06_КАЦ!$R$4:$R$203,MATCH(K83,06_КАЦ!$A$4:$A$203,0)),""),IFERROR(INDEX(06а_Оценки!$F$4:$F$203,MATCH(K83,06а_Оценки!$A$4:$A$203,0)),"")),"") | M83: =IF(N83="READY",ROUND(I83*L83,2),"") | N83: =IF(A83="","",IF(Q83="NOT_APPLICABLE",IF(AND(COUNTIF(A$4:A$203,A83)=1,H83="OUTSIDE",R83<>"",O83<>"",COUNTIF(13_Источники!$A$4:$A$203,O83)=1),"NOT_APPLICABLE","INCOMPLETE / EXCLUSION"),IF(AND(COUNTIF(A$4:A$203,A83)=1,COUNTIF(02_WBS!$A$4:$A$200,B83)=1,C83<>"",COUNTIF(03_Пакеты!$A$4:$A$203,C83)=1,IFERROR(INDEX(03_Пакеты!$B$4:$B$203,MATCH(C83,03_Пакеты!$A$4:$A$203,0)),"")=B83,E83<>"",F83<>"",F83<>"UNKNOWN",G83<>"",G83<>"UNKNOWN",OR(H83="REMAINING",H83="SUNK",H83="OUTSIDE"),ISNUMBER(I83),I83>=0,OR(AND(I83>0,Q83="KNOWN"),AND(I83=0,Q83="ZERO_CONFIRMED")),J83<>"",K83<>"",OR(AND(V83="KAC",COUNTIF(06_КАЦ!$A$4:$A$203,K83)=1,IFERROR(INDEX(06_КАЦ!$V$4:$V$203,MATCH(K83,06_КАЦ!$A$4:$A$203,0)),"")="SELECTED_READY",IFERROR(INDEX(06_КАЦ!$D$4:$D$203,MATCH(K83,06_КАЦ!$A$4:$A$203,0)),"")=C83,IFERROR(INDEX(06_КАЦ!$F$4:$F$203,MATCH(K83,06_КАЦ!$A$4:$A$203,0)),"")=J83),AND(V83="DIRECT",COUNTIF(06а_Оценки!$A$4:$A$203,K83)=1,IFERROR(INDEX(06а_Оценки!$N$4:$N$203,MATCH(K83,06а_Оценки!$A$4:$A$203,0)),"")="READY",IFERROR(INDEX(06а_Оценки!$B$4:$B$203,MATCH(K83,06а_Оценки!$A$4:$A$203,0)),"")=C83,IFERROR(INDEX(06а_Оценки!$E$4:$E$203,MATCH(K83,06а_Оценки!$A$4:$A$203,0)),"")=J83)),O83<>"",COUNTIF(13_Источники!$A$4:$A$203,O83)=1,P83<>"",R83<>""),"READY","INCOMPLETE / LINK")))
L84: =IF(N84="READY",IF(V84="KAC",IFERROR(INDEX(06_КАЦ!$R$4:$R$203,MATCH(K84,06_КАЦ!$A$4:$A$203,0)),""),IFERROR(INDEX(06а_Оценки!$F$4:$F$203,MATCH(K84,06а_Оценки!$A$4:$A$203,0)),"")),"") | M84: =IF(N84="READY",ROUND(I84*L84,2),"") | N84: =IF(A84="","",IF(Q84="NOT_APPLICABLE",IF(AND(COUNTIF(A$4:A$203,A84)=1,H84="OUTSIDE",R84<>"",O84<>"",COUNTIF(13_Источники!$A$4:$A$203,O84)=1),"NOT_APPLICABLE","INCOMPLETE / EXCLUSION"),IF(AND(COUNTIF(A$4:A$203,A84)=1,COUNTIF(02_WBS!$A$4:$A$200,B84)=1,C84<>"",COUNTIF(03_Пакеты!$A$4:$A$203,C84)=1,IFERROR(INDEX(03_Пакеты!$B$4:$B$203,MATCH(C84,03_Пакеты!$A$4:$A$203,0)),"")=B84,E84<>"",F84<>"",F84<>"UNKNOWN",G84<>"",G84<>"UNKNOWN",OR(H84="REMAINING",H84="SUNK",H84="OUTSIDE"),ISNUMBER(I84),I84>=0,OR(AND(I84>0,Q84="KNOWN"),AND(I84=0,Q84="ZERO_CONFIRMED")),J84<>"",K84<>"",OR(AND(V84="KAC",COUNTIF(06_КАЦ!$A$4:$A$203,K84)=1,IFERROR(INDEX(06_КАЦ!$V$4:$V$203,MATCH(K84,06_КАЦ!$A$4:$A$203,0)),"")="SELECTED_READY",IFERROR(INDEX(06_КАЦ!$D$4:$D$203,MATCH(K84,06_КАЦ!$A$4:$A$203,0)),"")=C84,IFERROR(INDEX(06_КАЦ!$F$4:$F$203,MATCH(K84,06_КАЦ!$A$4:$A$203,0)),"")=J84),AND(V84="DIRECT",COUNTIF(06а_Оценки!$A$4:$A$203,K84)=1,IFERROR(INDEX(06а_Оценки!$N$4:$N$203,MATCH(K84,06а_Оценки!$A$4:$A$203,0)),"")="READY",IFERROR(INDEX(06а_Оценки!$B$4:$B$203,MATCH(K84,06а_Оценки!$A$4:$A$203,0)),"")=C84,IFERROR(INDEX(06а_Оценки!$E$4:$E$203,MATCH(K84,06а_Оценки!$A$4:$A$203,0)),"")=J84)),O84<>"",COUNTIF(13_Источники!$A$4:$A$203,O84)=1,P84<>"",R84<>""),"READY","INCOMPLETE / LINK")))
L85: =IF(N85="READY",IF(V85="KAC",IFERROR(INDEX(06_КАЦ!$R$4:$R$203,MATCH(K85,06_КАЦ!$A$4:$A$203,0)),""),IFERROR(INDEX(06а_Оценки!$F$4:$F$203,MATCH(K85,06а_Оценки!$A$4:$A$203,0)),"")),"") | M85: =IF(N85="READY",ROUND(I85*L85,2),"") | N85: =IF(A85="","",IF(Q85="NOT_APPLICABLE",IF(AND(COUNTIF(A$4:A$203,A85)=1,H85="OUTSIDE",R85<>"",O85<>"",COUNTIF(13_Источники!$A$4:$A$203,O85)=1),"NOT_APPLICABLE","INCOMPLETE / EXCLUSION"),IF(AND(COUNTIF(A$4:A$203,A85)=1,COUNTIF(02_WBS!$A$4:$A$200,B85)=1,C85<>"",COUNTIF(03_Пакеты!$A$4:$A$203,C85)=1,IFERROR(INDEX(03_Пакеты!$B$4:$B$203,MATCH(C85,03_Пакеты!$A$4:$A$203,0)),"")=B85,E85<>"",F85<>"",F85<>"UNKNOWN",G85<>"",G85<>"UNKNOWN",OR(H85="REMAINING",H85="SUNK",H85="OUTSIDE"),ISNUMBER(I85),I85>=0,OR(AND(I85>0,Q85="KNOWN"),AND(I85=0,Q85="ZERO_CONFIRMED")),J85<>"",K85<>"",OR(AND(V85="KAC",COUNTIF(06_КАЦ!$A$4:$A$203,K85)=1,IFERROR(INDEX(06_КАЦ!$V$4:$V$203,MATCH(K85,06_КАЦ!$A$4:$A$203,0)),"")="SELECTED_READY",IFERROR(INDEX(06_КАЦ!$D$4:$D$203,MATCH(K85,06_КАЦ!$A$4:$A$203,0)),"")=C85,IFERROR(INDEX(06_КАЦ!$F$4:$F$203,MATCH(K85,06_КАЦ!$A$4:$A$203,0)),"")=J85),AND(V85="DIRECT",COUNTIF(06а_Оценки!$A$4:$A$203,K85)=1,IFERROR(INDEX(06а_Оценки!$N$4:$N$203,MATCH(K85,06а_Оценки!$A$4:$A$203,0)),"")="READY",IFERROR(INDEX(06а_Оценки!$B$4:$B$203,MATCH(K85,06а_Оценки!$A$4:$A$203,0)),"")=C85,IFERROR(INDEX(06а_Оценки!$E$4:$E$203,MATCH(K85,06а_Оценки!$A$4:$A$203,0)),"")=J85)),O85<>"",COUNTIF(13_Источники!$A$4:$A$203,O85)=1,P85<>"",R85<>""),"READY","INCOMPLETE / LINK")))
L86: =IF(N86="READY",IF(V86="KAC",IFERROR(INDEX(06_КАЦ!$R$4:$R$203,MATCH(K86,06_КАЦ!$A$4:$A$203,0)),""),IFERROR(INDEX(06а_Оценки!$F$4:$F$203,MATCH(K86,06а_Оценки!$A$4:$A$203,0)),"")),"") | M86: =IF(N86="READY",ROUND(I86*L86,2),"") | N86: =IF(A86="","",IF(Q86="NOT_APPLICABLE",IF(AND(COUNTIF(A$4:A$203,A86)=1,H86="OUTSIDE",R86<>"",O86<>"",COUNTIF(13_Источники!$A$4:$A$203,O86)=1),"NOT_APPLICABLE","INCOMPLETE / EXCLUSION"),IF(AND(COUNTIF(A$4:A$203,A86)=1,COUNTIF(02_WBS!$A$4:$A$200,B86)=1,C86<>"",COUNTIF(03_Пакеты!$A$4:$A$203,C86)=1,IFERROR(INDEX(03_Пакеты!$B$4:$B$203,MATCH(C86,03_Пакеты!$A$4:$A$203,0)),"")=B86,E86<>"",F86<>"",F86<>"UNKNOWN",G86<>"",G86<>"UNKNOWN",OR(H86="REMAINING",H86="SUNK",H86="OUTSIDE"),ISNUMBER(I86),I86>=0,OR(AND(I86>0,Q86="KNOWN"),AND(I86=0,Q86="ZERO_CONFIRMED")),J86<>"",K86<>"",OR(AND(V86="KAC",COUNTIF(06_КАЦ!$A$4:$A$203,K86)=1,IFERROR(INDEX(06_КАЦ!$V$4:$V$203,MATCH(K86,06_КАЦ!$A$4:$A$203,0)),"")="SELECTED_READY",IFERROR(INDEX(06_КАЦ!$D$4:$D$203,MATCH(K86,06_КАЦ!$A$4:$A$203,0)),"")=C86,IFERROR(INDEX(06_КАЦ!$F$4:$F$203,MATCH(K86,06_КАЦ!$A$4:$A$203,0)),"")=J86),AND(V86="DIRECT",COUNTIF(06а_Оценки!$A$4:$A$203,K86)=1,IFERROR(INDEX(06а_Оценки!$N$4:$N$203,MATCH(K86,06а_Оценки!$A$4:$A$203,0)),"")="READY",IFERROR(INDEX(06а_Оценки!$B$4:$B$203,MATCH(K86,06а_Оценки!$A$4:$A$203,0)),"")=C86,IFERROR(INDEX(06а_Оценки!$E$4:$E$203,MATCH(K86,06а_Оценки!$A$4:$A$203,0)),"")=J86)),O86<>"",COUNTIF(13_Источники!$A$4:$A$203,O86)=1,P86<>"",R86<>""),"READY","INCOMPLETE / LINK")))
L87: =IF(N87="READY",IF(V87="KAC",IFERROR(INDEX(06_КАЦ!$R$4:$R$203,MATCH(K87,06_КАЦ!$A$4:$A$203,0)),""),IFERROR(INDEX(06а_Оценки!$F$4:$F$203,MATCH(K87,06а_Оценки!$A$4:$A$203,0)),"")),"") | M87: =IF(N87="READY",ROUND(I87*L87,2),"") | N87: =IF(A87="","",IF(Q87="NOT_APPLICABLE",IF(AND(COUNTIF(A$4:A$203,A87)=1,H87="OUTSIDE",R87<>"",O87<>"",COUNTIF(13_Источники!$A$4:$A$203,O87)=1),"NOT_APPLICABLE","INCOMPLETE / EXCLUSION"),IF(AND(COUNTIF(A$4:A$203,A87)=1,COUNTIF(02_WBS!$A$4:$A$200,B87)=1,C87<>"",COUNTIF(03_Пакеты!$A$4:$A$203,C87)=1,IFERROR(INDEX(03_Пакеты!$B$4:$B$203,MATCH(C87,03_Пакеты!$A$4:$A$203,0)),"")=B87,E87<>"",F87<>"",F87<>"UNKNOWN",G87<>"",G87<>"UNKNOWN",OR(H87="REMAINING",H87="SUNK",H87="OUTSIDE"),ISNUMBER(I87),I87>=0,OR(AND(I87>0,Q87="KNOWN"),AND(I87=0,Q87="ZERO_CONFIRMED")),J87<>"",K87<>"",OR(AND(V87="KAC",COUNTIF(06_КАЦ!$A$4:$A$203,K87)=1,IFERROR(INDEX(06_КАЦ!$V$4:$V$203,MATCH(K87,06_КАЦ!$A$4:$A$203,0)),"")="SELECTED_READY",IFERROR(INDEX(06_КАЦ!$D$4:$D$203,MATCH(K87,06_КАЦ!$A$4:$A$203,0)),"")=C87,IFERROR(INDEX(06_КАЦ!$F$4:$F$203,MATCH(K87,06_КАЦ!$A$4:$A$203,0)),"")=J87),AND(V87="DIRECT",COUNTIF(06а_Оценки!$A$4:$A$203,K87)=1,IFERROR(INDEX(06а_Оценки!$N$4:$N$203,MATCH(K87,06а_Оценки!$A$4:$A$203,0)),"")="READY",IFERROR(INDEX(06а_Оценки!$B$4:$B$203,MATCH(K87,06а_Оценки!$A$4:$A$203,0)),"")=C87,IFERROR(INDEX(06а_Оценки!$E$4:$E$203,MATCH(K87,06а_Оценки!$A$4:$A$203,0)),"")=J87)),O87<>"",COUNTIF(13_Источники!$A$4:$A$203,O87)=1,P87<>"",R87<>""),"READY","INCOMPLETE / LINK")))
... L203: =IF(N203="READY",IF(V203="KAC",IFERROR(INDEX(06_КАЦ!$R$4:$R$203,MATCH(K203,06_КАЦ!$A$4:$A$203,0)),""),IFERROR(INDEX(06а_Оценки!$F$4:$F$203,MATCH(K203,06а_Оценки!$A$4:$A$203,0)),"")),"") | M203: =IF(N203="READY",ROUND(I203*L203,2),"") | N203: =IF(A203="","",IF(Q203="NOT_APPLICABLE",IF(AND(COUNTIF(A$4:A$203,A203)=1,H203="OUTSIDE",R203<>"",O203<>"",COUNTIF(13_Источники!$A$4:$A$203,O203)=1),"NOT_APPLICABLE","INCOMPLETE / EXCLUSION"),IF(AND(COUNTIF(A$4:A$203,A203)=1,COUNTIF(02_WBS!$A$4:$A$200,B203)=1,C203<>"",COUNTIF(03_Пакеты!$A$4:$A$203,C203)=1,IFERROR(INDEX(03_Пакеты!$B$4:$B$203,MATCH(C203,03_Пакеты!$A$4:$A$203,0)),"")=B203,E203<>"",F203<>"",F203<>"UNKNOWN",G203<>"",G203<>"UNKNOWN",OR(H203="REMAINING",H203="SUNK",H203="OUTSIDE"),ISNUMBER(I203),I203>=0,OR(AND(I203>0,Q203="KNOWN"),AND(I203=0,Q203="ZERO_CONFIRMED")),J203<>"",K203<>"",OR(AND(V203="KAC",COUNTIF(06_КАЦ!$A$4:$A$203,K203)=1,IFERROR(INDEX(06_КАЦ!$V$4:$V$203,MATCH(K203,06_КАЦ!$A$4:$A$203,0)),"")="SELECTED_READY",IFERROR(INDEX(06_КАЦ!$D$4:$D$203,MATCH(K203,06_КАЦ!$A$4:$A$203,0)),"")=C203,IFERROR(INDEX(06_КАЦ!$F$4:$F$203,MATCH(K203,06_КАЦ!$A$4:$A$203,0)),"")=J203),AND(V203="DIRECT",COUNTIF(06а_Оценки!$A$4:$A$203,K203)=1,IFERROR(INDEX(06а_Оценки!$N$4:$N$203,MATCH(K203,06а_Оценки!$A$4:$A$203,0)),"")="READY",IFERROR(INDEX(06а_Оценки!$B$4:$B$203,MATCH(K203,06а_Оценки!$A$4:$A$203,0)),"")=C203,IFERROR(INDEX(06а_Оценки!$E$4:$E$203,MATCH(K203,06а_Оценки!$A$4:$A$203,0)),"")=J203)),O203<>"",COUNTIF(13_Источники!$A$4:$A$203,O203)=1,P203<>"",R203<>""),"READY","INCOMPLETE / LINK")))

Sheet 06а_Оценки
A1: Обоснованные расценки без КП — отдельный источник
A2: Синие ячейки — ввод; серые — формулы. Пусто = нет данных. Код строки сохранять при сортировке.
A3: Оценка_ID | B3: Пакет_ID | C3: Тип основания | D3: Описание | E3: Единица | F3: Цена / ед. базовая | G3: Валюта базы | H3: Основа NET/GROSS | I3: Дата оценки | J3: Документ_ID | K3: Расчёт / метод / locator | L3: Статус цены | M3: Решение о применении | N3: Контроль
N4: =IF(A4="","",IF(AND(COUNTIF(A$4:A$203,A4)=1,B4<>"",COUNTIF(03_Пакеты!$A$4:$A$203,B4)=1,C4<>"",E4<>"",ISNUMBER(F4),F4>=0,G4<>"",G4=01_Основания!$B$8,H4<>"",H4=01_Основания!$B$9,I4<>"",J4<>"",COUNTIF(13_Источники!$A$4:$A$203,J4)=1,K4<>"",M4<>"",01_Основания!$B$10<>"",OR(AND(F4>0,L4="KNOWN"),AND(F4=0,L4="ZERO_CONFIRMED"))),"READY","INCOMPLETE / BASIS"))
N5: =IF(A5="","",IF(AND(COUNTIF(A$4:A$203,A5)=1,B5<>"",COUNTIF(03_Пакеты!$A$4:$A$203,B5)=1,C5<>"",E5<>"",ISNUMBER(F5),F5>=0,G5<>"",G5=01_Основания!$B$8,H5<>"",H5=01_Основания!$B$9,I5<>"",J5<>"",COUNTIF(13_Источники!$A$4:$A$203,J5)=1,K5<>"",M5<>"",01_Основания!$B$10<>"",OR(AND(F5>0,L5="KNOWN"),AND(F5=0,L5="ZERO_CONFIRMED"))),"READY","INCOMPLETE / BASIS"))
N6: =IF(A6="","",IF(AND(COUNTIF(A$4:A$203,A6)=1,B6<>"",COUNTIF(03_Пакеты!$A$4:$A$203,B6)=1,C6<>"",E6<>"",ISNUMBER(F6),F6>=0,G6<>"",G6=01_Основания!$B$8,H6<>"",H6=01_Основания!$B$9,I6<>"",J6<>"",COUNTIF(13_Источники!$A$4:$A$203,J6)=1,K6<>"",M6<>"",01_Основания!$B$10<>"",OR(AND(F6>0,L6="KNOWN"),AND(F6=0,L6="ZERO_CONFIRMED"))),"READY","INCOMPLETE / BASIS"))
N7: =IF(A7="","",IF(AND(COUNTIF(A$4:A$203,A7)=1,B7<>"",COUNTIF(03_Пакеты!$A$4:$A$203,B7)=1,C7<>"",E7<>"",ISNUMBER(F7),F7>=0,G7<>"",G7=01_Основания!$B$8,H7<>"",H7=01_Основания!$B$9,I7<>"",J7<>"",COUNTIF(13_Источники!$A$4:$A$203,J7)=1,K7<>"",M7<>"",01_Основания!$B$10<>"",OR(AND(F7>0,L7="KNOWN"),AND(F7=0,L7="ZERO_CONFIRMED"))),"READY","INCOMPLETE / BASIS"))
N8: =IF(A8="","",IF(AND(COUNTIF(A$4:A$203,A8)=1,B8<>"",COUNTIF(03_Пакеты!$A$4:$A$203,B8)=1,C8<>"",E8<>"",ISNUMBER(F8),F8>=0,G8<>"",G8=01_Основания!$B$8,H8<>"",H8=01_Основания!$B$9,I8<>"",J8<>"",COUNTIF(13_Источники!$A$4:$A$203,J8)=1,K8<>"",M8<>"",01_Основания!$B$10<>"",OR(AND(F8>0,L8="KNOWN"),AND(F8=0,L8="ZERO_CONFIRMED"))),"READY","INCOMPLETE / BASIS"))
N9: =IF(A9="","",IF(AND(COUNTIF(A$4:A$203,A9)=1,B9<>"",COUNTIF(03_Пакеты!$A$4:$A$203,B9)=1,C9<>"",E9<>"",ISNUMBER(F9),F9>=0,G9<>"",G9=01_Основания!$B$8,H9<>"",H9=01_Основания!$B$9,I9<>"",J9<>"",COUNTIF(13_Источники!$A$4:$A$203,J9)=1,K9<>"",M9<>"",01_Основания!$B$10<>"",OR(AND(F9>0,L9="KNOWN"),AND(F9=0,L9="ZERO_CONFIRMED"))),"READY","INCOMPLETE / BASIS"))
N10: =IF(A10="","",IF(AND(COUNTIF(A$4:A$203,A10)=1,B10<>"",COUNTIF(03_Пакеты!$A$4:$A$203,B10)=1,C10<>"",E10<>"",ISNUMBER(F10),F10>=0,G10<>"",G10=01_Основания!$B$8,H10<>"",H10=01_Основания!$B$9,I10<>"",J10<>"",COUNTIF(13_Источники!$A$4:$A$203,J10)=1,K10<>"",M10<>"",01_Основания!$B$10<>"",OR(AND(F10>0,L10="KNOWN"),AND(F10=0,L10="ZERO_CONFIRMED"))),"READY","INCOMPLETE / BASIS"))
N11: =IF(A11="","",IF(AND(COUNTIF(A$4:A$203,A11)=1,B11<>"",COUNTIF(03_Пакеты!$A$4:$A$203,B11)=1,C11<>"",E11<>"",ISNUMBER(F11),F11>=0,G11<>"",G11=01_Основания!$B$8,H11<>"",H11=01_Основания!$B$9,I11<>"",J11<>"",COUNTIF(13_Источники!$A$4:$A$203,J11)=1,K11<>"",M11<>"",01_Основания!$B$10<>"",OR(AND(F11>0,L11="KNOWN"),AND(F11=0,L11="ZERO_CONFIRMED"))),"READY","INCOMPLETE / BASIS"))
N12: =IF(A12="","",IF(AND(COUNTIF(A$4:A$203,A12)=1,B12<>"",COUNTIF(03_Пакеты!$A$4:$A$203,B12)=1,C12<>"",E12<>"",ISNUMBER(F12),F12>=0,G12<>"",G12=01_Основания!$B$8,H12<>"",H12=01_Основания!$B$9,I12<>"",J12<>"",COUNTIF(13_Источники!$A$4:$A$203,J12)=1,K12<>"",M12<>"",01_Основания!$B$10<>"",OR(AND(F12>0,L12="KNOWN"),AND(F12=0,L12="ZERO_CONFIRMED"))),"READY","INCOMPLETE / BASIS"))
N13: =IF(A13="","",IF(AND(COUNTIF(A$4:A$203,A13)=1,B13<>"",COUNTIF(03_Пакеты!$A$4:$A$203,B13)=1,C13<>"",E13<>"",ISNUMBER(F13),F13>=0,G13<>"",G13=01_Основания!$B$8,H13<>"",H13=01_Основания!$B$9,I13<>"",J13<>"",COUNTIF(13_Источники!$A$4:$A$203,J13)=1,K13<>"",M13<>"",01_Основания!$B$10<>"",OR(AND(F13>0,L13="KNOWN"),AND(F13=0,L13="ZERO_CONFIRMED"))),"READY","INCOMPLETE / BASIS"))
N14: =IF(A14="","",IF(AND(COUNTIF(A$4:A$203,A14)=1,B14<>"",COUNTIF(03_Пакеты!$A$4:$A$203,B14)=1,C14<>"",E14<>"",ISNUMBER(F14),F14>=0,G14<>"",G14=01_Основания!$B$8,H14<>"",H14=01_Основания!$B$9,I14<>"",J14<>"",COUNTIF(13_Источники!$A$4:$A$203,J14)=1,K14<>"",M14<>"",01_Основания!$B$10<>"",OR(AND(F14>0,L14="KNOWN"),AND(F14=0,L14="ZERO_CONFIRMED"))),"READY","INCOMPLETE / BASIS"))
N15: =IF(A15="","",IF(AND(COUNTIF(A$4:A$203,A15)=1,B15<>"",COUNTIF(03_Пакеты!$A$4:$A$203,B15)=1,C15<>"",E15<>"",ISNUMBER(F15),F15>=0,G15<>"",G15=01_Основания!$B$8,H15<>"",H15=01_Основания!$B$9,I15<>"",J15<>"",COUNTIF(13_Источники!$A$4:$A$203,J15)=1,K15<>"",M15<>"",01_Основания!$B$10<>"",OR(AND(F15>0,L15="KNOWN"),AND(F15=0,L15="ZERO_CONFIRMED"))),"READY","INCOMPLETE / BASIS"))
... N203: =IF(A203="","",IF(AND(COUNTIF(A$4:A$203,A203)=1,B203<>"",COUNTIF(03_Пакеты!$A$4:$A$203,B203)=1,C203<>"",E203<>"",ISNUMBER(F203),F203>=0,G203<>"",G203=01_Основания!$B$8,H203<>"",H203=01_Основания!$B$9,I203<>"",J203<>"",COUNTIF(13_Источники!$A$4:$A$203,J203)=1,K203<>"",M203<>"",01_Основания!$B$10<>"",OR(AND(F203>0,L203="KNOWN"),AND(F203=0,L203="ZERO_CONFIRMED"))),"READY","INCOMPLETE / BASIS"))

Sheet 08_Сводка
A1: Сводка известной части — не утверждённая цена яхты
A2: Синие ячейки — ввод; серые — формулы. Пусто = нет данных. Код строки сохранять при сортировке.
A3: WBS | B3: Раздел | C3: Позиций | D3: Готово к оценке | E3: Не закрыто | F3: Известный остаток достройки | G3: Известные понесённые | H3: Известное вне бюджета | I3: Статус
A4: W00 | B4: Управление проектом | C4: =COUNTIF(07_Смета!$B$4:$B$203,A4&"*") -> 1 | D4: =COUNTIFS(07_Смета!$B$4:$B$203,A4&"*",07_Смета!$N$4:$N$203,"READY") -> 0 | E4: =C4-D4-COUNTIFS(07_Смета!$B$4:$B$203,A4&"*",07_Смета!$N$4:$N$203,"NOT_APPLICABLE") -> 1 | F4: =IF(COUNTIFS(07_Смета!$B$4:$B$203,A4&"*",07_Смета!$N$4:$N$203,"READY",07_Смета!$H$4:$H$203,"REMAINING")=0,"",SUMIFS(07_Смета!$M$4:$M$203,07_Смета!$B$4:$B$203,A4&"*",07_Смета!$H$4:$H$203,"REMAINING")) | G4: =IF(COUNTIFS(07_Смета!$B$4:$B$203,A4&"*",07_Смета!$N$4:$N$203,"READY",07_Смета!$H$4:$H$203,"SUNK")=0,"",SUMIFS(07_Смета!$M$4:$M$203,07_Смета!$B$4:$B$203,A4&"*",07_Смета!$H$4:$H$203,"SUNK")) | H4: =IF(COUNTIFS(07_Смета!$B$4:$B$203,A4&"*",07_Смета!$N$4:$N$203,"READY",07_Смета!$H$4:$H$203,"OUTSIDE")=0,"",SUMIFS(07_Смета!$M$4:$M$203,07_Смета!$B$4:$B$203,A4&"*",07_Смета!$H$4:$H$203,"OUTSIDE")) | I4: =IF(C4=0,"SCOPE_NOT_DETAILED",IF(E4>0,"INCOMPLETE","INPUTS_COMPLETE_SCOPE_REVIEW")) -> INCOMPLETE
A5: W01 | B5: Исходники и обследование | C5: =COUNTIF(07_Смета!$B$4:$B$203,A5&"*") -> 2 | D5: =COUNTIFS(07_Смета!$B$4:$B$203,A5&"*",07_Смета!$N$4:$N$203,"READY") -> 0 | E5: =C5-D5-COUNTIFS(07_Смета!$B$4:$B$203,A5&"*",07_Смета!$N$4:$N$203,"NOT_APPLICABLE") -> 2 | F5: =IF(COUNTIFS(07_Смета!$B$4:$B$203,A5&"*",07_Смета!$N$4:$N$203,"READY",07_Смета!$H$4:$H$203,"REMAINING")=0,"",SUMIFS(07_Смета!$M$4:$M$203,07_Смета!$B$4:$B$203,A5&"*",07_Смета!$H$4:$H$203,"REMAINING")) | G5: =IF(COUNTIFS(07_Смета!$B$4:$B$203,A5&"*",07_Смета!$N$4:$N$203,"READY",07_Смета!$H$4:$H$203,"SUNK")=0,"",SUMIFS(07_Смета!$M$4:$M$203,07_Смета!$B$4:$B$203,A5&"*",07_Смета!$H$4:$H$203,"SUNK")) | H5: =IF(COUNTIFS(07_Смета!$B$4:$B$203,A5&"*",07_Смета!$N$4:$N$203,"READY",07_Смета!$H$4:$H$203,"OUTSIDE")=0,"",SUMIFS(07_Смета!$M$4:$M$203,07_Смета!$B$4:$B$203,A5&"*",07_Смета!$H$4:$H$203,"OUTSIDE")) | I5: =IF(C5=0,"SCOPE_NOT_DETAILED",IF(E5>0,"INCOMPLETE","INPUTS_COMPLETE_SCOPE_REVIEW")) -> INCOMPLETE
A6: W02 | B6: Проектирование и применимость требований | C6: =COUNTIF(07_Смета!$B$4:$B$203,A6&"*") -> 4 | D6: =COUNTIFS(07_Смета!$B$4:$B$203,A6&"*",07_Смета!$N$4:$N$203,"READY") -> 0 | E6: =C6-D6-COUNTIFS(07_Смета!$B$4:$B$203,A6&"*",07_Смета!$N$4:$N$203,"NOT_APPLICABLE") -> 4 | F6: =IF(COUNTIFS(07_Смета!$B$4:$B$203,A6&"*",07_Смета!$N$4:$N$203,"READY",07_Смета!$H$4:$H$203,"REMAINING")=0,"",SUMIFS(07_Смета!$M$4:$M$203,07_Смета!$B$4:$B$203,A6&"*",07_Смета!$H$4:$H$203,"REMAINING")) | G6: =IF(COUNTIFS(07_Смета!$B$4:$B$203,A6&"*",07_Смета!$N$4:$N$203,"READY",07_Смета!$H$4:$H$203,"SUNK")=0,"",SUMIFS(07_Смета!$M$4:$M$203,07_Смета!$B$4:$B$203,A6&"*",07_Смета!$H$4:$H$203,"SUNK")) | H6: =IF(COUNTIFS(07_Смета!$B$4:$B$203,A6&"*",07_Смета!$N$4:$N$203,"READY",07_Смета!$H$4:$H$203,"OUTSIDE")=0,"",SUMIFS(07_Смета!$M$4:$M$203,07_Смета!$B$4:$B$203,A6&"*",07_Смета!$H$4:$H$203,"OUTSIDE")) | I6: =IF(C6=0,"SCOPE_NOT_DETAILED",IF(E6>0,"INCOMPLETE","INPUTS_COMPLETE_SCOPE_REVIEW")) -> INCOMPLETE
A7: W10 | B7: Корпус и конструкция | C7: =COUNTIF(07_Смета!$B$4:$B$203,A7&"*") -> 10 | D7: =COUNTIFS(07_Смета!$B$4:$B$203,A7&"*",07_Смета!$N$4:$N$203,"READY") -> 0 | E7: =C7-D7-COUNTIFS(07_Смета!$B$4:$B$203,A7&"*",07_Смета!$N$4:$N$203,"NOT_APPLICABLE") -> 10 | F7: =IF(COUNTIFS(07_Смета!$B$4:$B$203,A7&"*",07_Смета!$N$4:$N$203,"READY",07_Смета!$H$4:$H$203,"REMAINING")=0,"",SUMIFS(07_Смета!$M$4:$M$203,07_Смета!$B$4:$B$203,A7&"*",07_Смета!$H$4:$H$203,"REMAINING")) | G7: =IF(COUNTIFS(07_Смета!$B$4:$B$203,A7&"*",07_Смета!$N$4:$N$203,"READY",07_Смета!$H$4:$H$203,"SUNK")=0,"",SUMIFS(07_Смета!$M$4:$M$203,07_Смета!$B$4:$B$203,A7&"*",07_Смета!$H$4:$H$203,"SUNK")) | H7: =IF(COUNTIFS(07_Смета!$B$4:$B$203,A7&"*",07_Смета!$N$4:$N$203,"READY",07_Смета!$H$4:$H$203,"OUTSIDE")=0,"",SUMIFS(07_Смета!$M$4:$M$203,07_Смета!$B$4:$B$203,A7&"*",07_Смета!$H$4:$H$203,"OUTSIDE")) | I7: =IF(C7=0,"SCOPE_NOT_DETAILED",IF(E7>0,"INCOMPLETE","INPUTS_COMPLETE_SCOPE_REVIEW")) -> INCOMPLETE
A8: W20 | B8: Рангоут и палуба | C8: =COUNTIF(07_Смета!$B$4:$B$203,A8&"*") -> 9 | D8: =COUNTIFS(07_Смета!$B$4:$B$203,A8&"*",07_Смета!$N$4:$N$203,"READY") -> 0 | E8: =C8-D8-COUNTIFS(07_Смета!$B$4:$B$203,A8&"*",07_Смета!$N$4:$N$203,"NOT_APPLICABLE") -> 9 | F8: =IF(COUNTIFS(07_Смета!$B$4:$B$203,A8&"*",07_Смета!$N$4:$N$203,"READY",07_Смета!$H$4:$H$203,"REMAINING")=0,"",SUMIFS(07_Смета!$M$4:$M$203,07_Смета!$B$4:$B$203,A8&"*",07_Смета!$H$4:$H$203,"REMAINING")) | G8: =IF(COUNTIFS(07_Смета!$B$4:$B$203,A8&"*",07_Смета!$N$4:$N$203,"READY",07_Смета!$H$4:$H$203,"SUNK")=0,"",SUMIFS(07_Смета!$M$4:$M$203,07_Смета!$B$4:$B$203,A8&"*",07_Смета!$H$4:$H$203,"SUNK")) | H8: =IF(COUNTIFS(07_Смета!$B$4:$B$203,A8&"*",07_Смета!$N$4:$N$203,"READY",07_Смета!$H$4:$H$203,"OUTSIDE")=0,"",SUMIFS(07_Смета!$M$4:$M$203,07_Смета!$B$4:$B$203,A8&"*",07_Смета!$H$4:$H$203,"OUTSIDE")) | I8: =IF(C8=0,"SCOPE_NOT_DETAILED",IF(E8>0,"INCOMPLETE","INPUTS_COMPLETE_SCOPE_REVIEW")) -> INCOMPLETE
A9: W30 | B9: Движение и управление | C9: =COUNTIF(07_Смета!$B$4:$B$203,A9&"*") -> 4 | D9: =COUNTIFS(07_Смета!$B$4:$B$203,A9&"*",07_Смета!$N$4:$N$203,"READY") -> 0 | E9: =C9-D9-COUNTIFS(07_Смета!$B$4:$B$203,A9&"*",07_Смета!$N$4:$N$203,"NOT_APPLICABLE") -> 4 | F9: =IF(COUNTIFS(07_Смета!$B$4:$B$203,A9&"*",07_Смета!$N$4:$N$203,"READY",07_Смета!$H$4:$H$203,"REMAINING")=0,"",SUMIFS(07_Смета!$M$4:$M$203,07_Смета!$B$4:$B$203,A9&"*",07_Смета!$H$4:$H$203,"REMAINING")) | G9: =IF(COUNTIFS(07_Смета!$B$4:$B$203,A9&"*",07_Смета!$N$4:$N$203,"READY",07_Смета!$H$4:$H$203,"SUNK")=0,"",SUMIFS(07_Смета!$M$4:$M$203,07_Смета!$B$4:$B$203,A9&"*",07_Смета!$H$4:$H$203,"SUNK")) | H9: =IF(COUNTIFS(07_Смета!$B$4:$B$203,A9&"*",07_Смета!$N$4:$N$203,"READY",07_Смета!$H$4:$H$203,"OUTSIDE")=0,"",SUMIFS(07_Смета!$M$4:$M$203,07_Смета!$B$4:$B$203,A9&"*",07_Смета!$H$4:$H$203,"OUTSIDE")) | I9: =IF(C9=0,"SCOPE_NOT_DETAILED",IF(E9>0,"INCOMPLETE","INPUTS_COMPLETE_SCOPE_REVIEW")) -> INCOMPLETE
A10: W40 | B10: Энергия, электрика и связь | C10: =COUNTIF(07_Смета!$B$4:$B$203,A10&"*") -> 10 | D10: =COUNTIFS(07_Смета!$B$4:$B$203,A10&"*",07_Смета!$N$4:$N$203,"READY") -> 0 | E10: =C10-D10-COUNTIFS(07_Смета!$B$4:$B$203,A10&"*",07_Смета!$N$4:$N$203,"NOT_APPLICABLE") -> 10 | F10: =IF(COUNTIFS(07_Смета!$B$4:$B$203,A10&"*",07_Смета!$N$4:$N$203,"READY",07_Смета!$H$4:$H$203,"REMAINING")=0,"",SUMIFS(07_Смета!$M$4:$M$203,07_Смета!$B$4:$B$203,A10&"*",07_Смета!$H$4:$H$203,"REMAINING")) | G10: =IF(COUNTIFS(07_Смета!$B$4:$B$203,A10&"*",07_Смета!$N$4:$N$203,"READY",07_Смета!$H$4:$H$203,"SUNK")=0,"",SUMIFS(07_Смета!$M$4:$M$203,07_Смета!$B$4:$B$203,A10&"*",07_Смета!$H$4:$H$203,"SUNK")) | H10: =IF(COUNTIFS(07_Смета!$B$4:$B$203,A10&"*",07_Смета!$N$4:$N$203,"READY",07_Смета!$H$4:$H$203,"OUTSIDE")=0,"",SUMIFS(07_Смета!$M$4:$M$203,07_Смета!$B$4:$B$203,A10&"*",07_Смета!$H$4:$H$203,"OUTSIDE")) | I10: =IF(C10=0,"SCOPE_NOT_DETAILED",IF(E10>0,"INCOMPLETE","INPUTS_COMPLETE_SCOPE_REVIEW")) -> INCOMPLETE
A11: W50 | B11: Жидкостные системы и климат | C11: =COUNTIF(07_Смета!$B$4:$B$203,A11&"*") -> 14 | D11: =COUNTIFS(07_Смета!$B$4:$B$203,A11&"*",07_Смета!$N$4:$N$203,"READY") -> 0 | E11: =C11-D11-COUNTIFS(07_Смета!$B$4:$B$203,A11&"*",07_Смета!$N$4:$N$203,"NOT_APPLICABLE") -> 14 | F11: =IF(COUNTIFS(07_Смета!$B$4:$B$203,A11&"*",07_Смета!$N$4:$N$203,"READY",07_Смета!$H$4:$H$203,"REMAINING")=0,"",SUMIFS(07_Смета!$M$4:$M$203,07_Смета!$B$4:$B$203,A11&"*",07_Смета!$H$4:$H$203,"REMAINING")) | G11: =IF(COUNTIFS(07_Смета!$B$4:$B$203,A11&"*",07_Смета!$N$4:$N$203,"READY",07_Смета!$H$4:$H$203,"SUNK")=0,"",SUMIFS(07_Смета!$M$4:$M$203,07_Смета!$B$4:$B$203,A11&"*",07_Смета!$H$4:$H$203,"SUNK")) | H11: =IF(COUNTIFS(07_Смета!$B$4:$B$203,A11&"*",07_Смета!$N$4:$N$203,"READY",07_Смета!$H$4:$H$203,"OUTSIDE")=0,"",SUMIFS(07_Смета!$M$4:$M$203,07_Смета!$B$4:$B$203,A11&"*",07_Смета!$H$4:$H$203,"OUTSIDE")) | I11: =IF(C11=0,"SCOPE_NOT_DETAILED",IF(E11>0,"INCOMPLETE","INPUTS_COMPLETE_SCOPE_REVIEW")) -> INCOMPLETE
A12: W60 | B12: Компоновка и интерьер | C12: =COUNTIF(07_Смета!$B$4:$B$203,A12&"*") -> 6 | D12: =COUNTIFS(07_Смета!$B$4:$B$203,A12&"*",07_Смета!$N$4:$N$203,"READY") -> 0 | E12: =C12-D12-COUNTIFS(07_Смета!$B$4:$B$203,A12&"*",07_Смета!$N$4:$N$203,"NOT_APPLICABLE") -> 6 | F12: =IF(COUNTIFS(07_Смета!$B$4:$B$203,A12&"*",07_Смета!$N$4:$N$203,"READY",07_Смета!$H$4:$H$203,"REMAINING")=0,"",SUMIFS(07_Смета!$M$4:$M$203,07_Смета!$B$4:$B$203,A12&"*",07_Смета!$H$4:$H$203,"REMAINING")) | G12: =IF(COUNTIFS(07_Смета!$B$4:$B$203,A12&"*",07_Смета!$N$4:$N$203,"READY",07_Смета!$H$4:$H$203,"SUNK")=0,"",SUMIFS(07_Смета!$M$4:$M$203,07_Смета!$B$4:$B$203,A12&"*",07_Смета!$H$4:$H$203,"SUNK")) | H12: =IF(COUNTIFS(07_Смета!$B$4:$B$203,A12&"*",07_Смета!$N$4:$N$203,"READY",07_Смета!$H$4:$H$203,"OUTSIDE")=0,"",SUMIFS(07_Смета!$M$4:$M$203,07_Смета!$B$4:$B$203,A12&"*",07_Смета!$H$4:$H$203,"OUTSIDE")) | I12: =IF(C12=0,"SCOPE_NOT_DETAILED",IF(E12>0,"INCOMPLETE","INPUTS_COMPLETE_SCOPE_REVIEW")) -> INCOMPLETE
A13: W70 | B13: Безопасность | C13: =COUNTIF(07_Смета!$B$4:$B$203,A13&"*") -> 3 | D13: =COUNTIFS(07_Смета!$B$4:$B$203,A13&"*",07_Смета!$N$4:$N$203,"READY") -> 0 | E13: =C13-D13-COUNTIFS(07_Смета!$B$4:$B$203,A13&"*",07_Смета!$N$4:$N$203,"NOT_APPLICABLE") -> 3 | F13: =IF(COUNTIFS(07_Смета!$B$4:$B$203,A13&"*",07_Смета!$N$4:$N$203,"READY",07_Смета!$H$4:$H$203,"REMAINING")=0,"",SUMIFS(07_Смета!$M$4:$M$203,07_Смета!$B$4:$B$203,A13&"*",07_Смета!$H$4:$H$203,"REMAINING")) | G13: =IF(COUNTIFS(07_Смета!$B$4:$B$203,A13&"*",07_Смета!$N$4:$N$203,"READY",07_Смета!$H$4:$H$203,"SUNK")=0,"",SUMIFS(07_Смета!$M$4:$M$203,07_Смета!$B$4:$B$203,A13&"*",07_Смета!$H$4:$H$203,"SUNK")) | H13: =IF(COUNTIFS(07_Смета!$B$4:$B$203,A13&"*",07_Смета!$N$4:$N$203,"READY",07_Смета!$H$4:$H$203,"OUTSIDE")=0,"",SUMIFS(07_Смета!$M$4:$M$203,07_Смета!$B$4:$B$203,A13&"*",07_Смета!$H$4:$H$203,"OUTSIDE")) | I13: =IF(C13=0,"SCOPE_NOT_DETAILED",IF(E13>0,"INCOMPLETE","INPUTS_COMPLETE_SCOPE_REVIEW")) -> INCOMPLETE
A14: W80 | B14: Интеграция, испытания и передача | C14: =COUNTIF(07_Смета!$B$4:$B$203,A14&"*") -> 4 | D14: =COUNTIFS(07_Смета!$B$4:$B$203,A14&"*",07_Смета!$N$4:$N$203,"READY") -> 0 | E14: =C14-D14-COUNTIFS(07_Смета!$B$4:$B$203,A14&"*",07_Смета!$N$4:$N$203,"NOT_APPLICABLE") -> 4 | F14: =IF(COUNTIFS(07_Смета!$B$4:$B$203,A14&"*",07_Смета!$N$4:$N$203,"READY",07_Смета!$H$4:$H$203,"REMAINING")=0,"",SUMIFS(07_Смета!$M$4:$M$203,07_Смета!$B$4:$B$203,A14&"*",07_Смета!$H$4:$H$203,"REMAINING")) | G14: =IF(COUNTIFS(07_Смета!$B$4:$B$203,A14&"*",07_Смета!$N$4:$N$203,"READY",07_Смета!$H$4:$H$203,"SUNK")=0,"",SUMIFS(07_Смета!$M$4:$M$203,07_Смета!$B$4:$B$203,A14&"*",07_Смета!$H$4:$H$203,"SUNK")) | H14: =IF(COUNTIFS(07_Смета!$B$4:$B$203,A14&"*",07_Смета!$N$4:$N$203,"READY",07_Смета!$H$4:$H$203,"OUTSIDE")=0,"",SUMIFS(07_Смета!$M$4:$M$203,07_Смета!$B$4:$B$203,A14&"*",07_Смета!$H$4:$H$203,"OUTSIDE")) | I14: =IF(C14=0,"SCOPE_NOT_DETAILED",IF(E14>0,"INCOMPLETE","INPUTS_COMPLETE_SCOPE_REVIEW")) -> INCOMPLETE
A15: W90 | B15: Логистика и условия производства | C15: =COUNTIF(07_Смета!$B$4:$B$203,A15&"*") -> 5 | D15: =COUNTIFS(07_Смета!$B$4:$B$203,A15&"*",07_Смета!$N$4:$N$203,"READY") -> 0 | E15: =C15-D15-COUNTIFS(07_Смета!$B$4:$B$203,A15&"*",07_Смета!$N$4:$N$203,"NOT_APPLICABLE") -> 5 | F15: =IF(COUNTIFS(07_Смета!$B$4:$B$203,A15&"*",07_Смета!$N$4:$N$203,"READY",07_Смета!$H$4:$H$203,"REMAINING")=0,"",SUMIFS(07_Смета!$M$4:$M$203,07_Смета!$B$4:$B$203,A15&"*",07_Смета!$H$4:$H$203,"REMAINING")) | G15: =IF(COUNTIFS(07_Смета!$B$4:$B$203,A15&"*",07_Смета!$N$4:$N$203,"READY",07_Смета!$H$4:$H$203,"SUNK")=0,"",SUMIFS(07_Смета!$M$4:$M$203,07_Смета!$B$4:$B$203,A15&"*",07_Смета!$H$4:$H$203,"SUNK")) | H15: =IF(COUNTIFS(07_Смета!$B$4:$B$203,A15&"*",07_Смета!$N$4:$N$203,"READY",07_Смета!$H$4:$H$203,"OUTSIDE")=0,"",SUMIFS(07_Смета!$M$4:$M$203,07_Смета!$B$4:$B$203,A15&"*",07_Смета!$H$4:$H$203,"OUTSIDE")) | I15: =IF(C15=0,"SCOPE_NOT_DETAILED",IF(E15>0,"INCOMPLETE","INPUTS_COMPLETE_SCOPE_REVIEW")) -> INCOMPLETE
A16: ИЗВЕСТНАЯ ЧАСТЬ | B16: Не полная стоимость яхты | C16: =SUM(C4:C15) -> 72 | D16: =SUM(D4:D15) -> 0 | E16: =SUM(E4:E15) -> 72 | F16: =IF(COUNT(F4:F15)=0,"",SUM(F4:F15)) | G16: =IF(COUNT(G4:G15)=0,"",SUM(G4:G15)) | H16: =IF(COUNT(H4:H15)=0,"",SUM(H4:H15)) | I16: ="НЕ УТВЕРЖДЕНО — проверить состав, источники и решение владельца" -> НЕ УТВЕРЖДЕНО — проверить состав, источники и решение владельца

Sheet 09_Риски
A1: Риски и обоснование резервов
A2: Синие ячейки — ввод; серые — формулы. Пусто = нет данных. Код строки сохранять при сортировке.
A3: Риск_ID | B3: WBS | C3: Описание | D3: Вероятность / основание | E3: Влияние / основание | F3: Мера снижения | G3: Резерв базовая валюта | H3: Метод / источник | I3: Решение | J3: Включён в Строка_ID | K3: Статус | L3: Ответственный

Sheet 10_Изменения
A1: Изменения после фиксации базового бюджета
A2: Синие ячейки — ввод; серые — формулы. Пусто = нет данных. Код строки сохранять при сортировке.
A3: Изменение_ID | B3: Дата | C3: Исходная версия УТВ | D3: Строка_ID | E3: Причина / решение | F3: Прежний состав | G3: Новый состав | H3: Старая сумма базы | I3: Новая сумма базы | J3: Дельта | K3: Влияние на срок | L3: Статус | M3: Утвердил / документ
J4: =IF(AND(A4<>"",COUNT(H4:I4)=2),ROUND(I4-H4,2),"")
J5: =IF(AND(A5<>"",COUNT(H5:I5)=2),ROUND(I5-H5,2),"")
J6: =IF(AND(A6<>"",COUNT(H6:I6)=2),ROUND(I6-H6,2),"")
J7: =IF(AND(A7<>"",COUNT(H7:I7)=2),ROUND(I7-H7,2),"")
J8: =IF(AND(A8<>"",COUNT(H8:I8)=2),ROUND(I8-H8,2),"")
J9: =IF(AND(A9<>"",COUNT(H9:I9)=2),ROUND(I9-H9,2),"")
J10: =IF(AND(A10<>"",COUNT(H10:I10)=2),ROUND(I10-H10,2),"")
J11: =IF(AND(A11<>"",COUNT(H11:I11)=2),ROUND(I11-H11,2),"")
J12: =IF(AND(A12<>"",COUNT(H12:I12)=2),ROUND(I12-H12,2),"")
J13: =IF(AND(A13<>"",COUNT(H13:I13)=2),ROUND(I13-H13,2),"")
J14: =IF(AND(A14<>"",COUNT(H14:I14)=2),ROUND(I14-H14,2),"")
J15: =IF(AND(A15<>"",COUNT(H15:I15)=2),ROUND(I15-H15,2),"")
... J203: =IF(AND(A203<>"",COUNT(H203:I203)=2),ROUND(I203-H203,2),"")

Sheet 11_Контроль
A1: После утверждения: факт, обязательства и прогноз
A2: Синие ячейки — ввод; серые — формулы. Пусто = нет данных. Код строки сохранять при сортировке.
A3: Период | B3: WBS | C3: Версия утверждённой УТВ | D3: Базовый бюджет | E3: Обязательства всего | F3: Факт стоимости | G3: Оплачено (справочно) | H3: Остаток обязательств | I3: Незаконтрактованный остаток | J3: Утверждённый неучтённый резерв | K3: Прогноз завершения | L3: Отклонение от базы | M3: Источник / решение | N3: Контроль
K4: =IF(N4="INPUTS_PRESENT_CHECK_OVERLAP",ROUND(F4+H4+I4+J4,2),"") | L4: =IF(ISNUMBER(K4),ROUND(K4-D4,2),"") | N4: =IF(A4="","",IF(AND(C4<>"",M4<>"",COUNT(D4:J4)=7,01_Основания!$B$16<>"",01_Основания!$B$8<>""),"INPUTS_PRESENT_CHECK_OVERLAP","INCOMPLETE"))
K5: =IF(N5="INPUTS_PRESENT_CHECK_OVERLAP",ROUND(F5+H5+I5+J5,2),"") | L5: =IF(ISNUMBER(K5),ROUND(K5-D5,2),"") | N5: =IF(A5="","",IF(AND(C5<>"",M5<>"",COUNT(D5:J5)=7,01_Основания!$B$16<>"",01_Основания!$B$8<>""),"INPUTS_PRESENT_CHECK_OVERLAP","INCOMPLETE"))
K6: =IF(N6="INPUTS_PRESENT_CHECK_OVERLAP",ROUND(F6+H6+I6+J6,2),"") | L6: =IF(ISNUMBER(K6),ROUND(K6-D6,2),"") | N6: =IF(A6="","",IF(AND(C6<>"",M6<>"",COUNT(D6:J6)=7,01_Основания!$B$16<>"",01_Основания!$B$8<>""),"INPUTS_PRESENT_CHECK_OVERLAP","INCOMPLETE"))
K7: =IF(N7="INPUTS_PRESENT_CHECK_OVERLAP",ROUND(F7+H7+I7+J7,2),"") | L7: =IF(ISNUMBER(K7),ROUND(K7-D7,2),"") | N7: =IF(A7="","",IF(AND(C7<>"",M7<>"",COUNT(D7:J7)=7,01_Основания!$B$16<>"",01_Основания!$B$8<>""),"INPUTS_PRESENT_CHECK_OVERLAP","INCOMPLETE"))
K8: =IF(N8="INPUTS_PRESENT_CHECK_OVERLAP",ROUND(F8+H8+I8+J8,2),"") | L8: =IF(ISNUMBER(K8),ROUND(K8-D8,2),"") | N8: =IF(A8="","",IF(AND(C8<>"",M8<>"",COUNT(D8:J8)=7,01_Основания!$B$16<>"",01_Основания!$B$8<>""),"INPUTS_PRESENT_CHECK_OVERLAP","INCOMPLETE"))
K9: =IF(N9="INPUTS_PRESENT_CHECK_OVERLAP",ROUND(F9+H9+I9+J9,2),"") | L9: =IF(ISNUMBER(K9),ROUND(K9-D9,2),"") | N9: =IF(A9="","",IF(AND(C9<>"",M9<>"",COUNT(D9:J9)=7,01_Основания!$B$16<>"",01_Основания!$B$8<>""),"INPUTS_PRESENT_CHECK_OVERLAP","INCOMPLETE"))
K10: =IF(N10="INPUTS_PRESENT_CHECK_OVERLAP",ROUND(F10+H10+I10+J10,2),"") | L10: =IF(ISNUMBER(K10),ROUND(K10-D10,2),"") | N10: =IF(A10="","",IF(AND(C10<>"",M10<>"",COUNT(D10:J10)=7,01_Основания!$B$16<>"",01_Основания!$B$8<>""),"INPUTS_PRESENT_CHECK_OVERLAP","INCOMPLETE"))
K11: =IF(N11="INPUTS_PRESENT_CHECK_OVERLAP",ROUND(F11+H11+I11+J11,2),"") | L11: =IF(ISNUMBER(K11),ROUND(K11-D11,2),"") | N11: =IF(A11="","",IF(AND(C11<>"",M11<>"",COUNT(D11:J11)=7,01_Основания!$B$16<>"",01_Основания!$B$8<>""),"INPUTS_PRESENT_CHECK_OVERLAP","INCOMPLETE"))
K12: =IF(N12="INPUTS_PRESENT_CHECK_OVERLAP",ROUND(F12+H12+I12+J12,2),"") | L12: =IF(ISNUMBER(K12),ROUND(K12-D12,2),"") | N12: =IF(A12="","",IF(AND(C12<>"",M12<>"",COUNT(D12:J12)=7,01_Основания!$B$16<>"",01_Основания!$B$8<>""),"INPUTS_PRESENT_CHECK_OVERLAP","INCOMPLETE"))
K13: =IF(N13="INPUTS_PRESENT_CHECK_OVERLAP",ROUND(F13+H13+I13+J13,2),"") | L13: =IF(ISNUMBER(K13),ROUND(K13-D13,2),"") | N13: =IF(A13="","",IF(AND(C13<>"",M13<>"",COUNT(D13:J13)=7,01_Основания!$B$16<>"",01_Основания!$B$8<>""),"INPUTS_PRESENT_CHECK_OVERLAP","INCOMPLETE"))
K14: =IF(N14="INPUTS_PRESENT_CHECK_OVERLAP",ROUND(F14+H14+I14+J14,2),"") | L14: =IF(ISNUMBER(K14),ROUND(K14-D14,2),"") | N14: =IF(A14="","",IF(AND(C14<>"",M14<>"",COUNT(D14:J14)=7,01_Основания!$B$16<>"",01_Основания!$B$8<>""),"INPUTS_PRESENT_CHECK_OVERLAP","INCOMPLETE"))
K15: =IF(N15="INPUTS_PRESENT_CHECK_OVERLAP",ROUND(F15+H15+I15+J15,2),"") | L15: =IF(ISNUMBER(K15),ROUND(K15-D15,2),"") | N15: =IF(A15="","",IF(AND(C15<>"",M15<>"",COUNT(D15:J15)=7,01_Основания!$B$16<>"",01_Основания!$B$8<>""),"INPUTS_PRESENT_CHECK_OVERLAP","INCOMPLETE"))
... K203: =IF(N203="INPUTS_PRESENT_CHECK_OVERLAP",ROUND(F203+H203+I203+J203,2),"") | L203: =IF(ISNUMBER(K203),ROUND(K203-D203,2),"") | N203: =IF(A203="","",IF(AND(C203<>"",M203<>"",COUNT(D203:J203)=7,01_Основания!$B$16<>"",01_Основания!$B$8<>""),"INPUTS_PRESENT_CHECK_OVERLAP","INCOMPLETE"))

Sheet 12_Стыки
A1: Включения и исключения — контроль двойного счёта
A2: Синие ячейки — ввод; серые — формулы. Пусто = нет данных. Код строки сохранять при сортировке.
A3: Стык_ID | B3: Пакет_ID | C3: Операция / компонент | D3: Статус включения | E3: Покрывающая Строка_ID | F3: Ответственный пакет_ID | G3: Основание / КП / ревизия | H3: Решение | I3: Статус

Sheet 13_Источники
A1: Документы и основания — реестр для заполнения
A2: Синие ячейки — ввод; серые — формулы. Пусто = нет данных. Код строки сохранять при сортировке.
A3: Документ_ID | B3: Тип | C3: Название | D3: Дата | E3: Ревизия | F3: Путь / ссылка | G3: SHA256 | H3: Доступ | I3: Статус | J3: Примечание
